Workbook

Sheet Read me
A1: Predictions for 2026-09-29
A3: Runners | B3: 364
A4: Races | B4: 38
A5: Meetings | B5: 5
A7: The model | B7: gated 10:53
A8: Features | B8: 993
A9: Trained through | B9: 2026-09-22
A10: Boosting rounds | B10: 12000
A11: Target | B11: logit_norm_prob
A12: Feature code hash | B12: f879b10c8369467a
A14: How to read it
A15: Predicted BSP | B15: The model's forecast of the Betfair Starting Price, from pre-race information only. The prices in each race make a book of exactly 100%.
A16: Win probability | B16: 1 / predicted BSP: the model's chance for the horse, normalised within the race.
A17: Model rank | B17: 1 = the model's shortest price in the race (highlighted green).
A18: Card odds (HRB) | B18: The odds printed on the horseracebase card when it was fetched: a bookmaker forecast, not the Betfair morning price the early-price rule was tested against.
A19: Card odds vs model | B19: Card odds / predicted BSP - 1. Positive: the card is longer than the model.
A21: The early-price rule
A22: Margin (log) | B22: 0.2
A23: Rule: back at Betfair ≥ | B23: Predicted BSP × e^margin: at 0.2, a Betfair price at least 1.22 times the model's (the model at least 22% shorter). The rule was fixed before it was first tested (reports/clv_betfair_2026q1.md): back at Betfair's morning volume-weighted price, where at least £100 has been matched in the morning, and close the position at BSP (lay at BSP to level the book). It is a trade on the price, not a bet held to the result. The margin (blue) is the one input: change it to see the prices at another threshold.
A25: Note | B25: The served model (the complete-careers pair gated with race_xent), re-run in full on horseracebase's card as it stood at 10:53 UTC (predict-now run 38): 364 runners in 38 races, every one priced, each race a book of 100%. All 11 of the day's non-runners are out (sheet Non-runners, each with its share of the book in the last run that priced it), and every price is compared with the 09:37 re-run. 11 non-runners since the prices were first made, in 9 races (sheet Non-runners). The prices here are without them, each race a book of 100%: a non-runner's share of the book goes to the rest of its race, whose prices shorten by about that share.

Sheet Top picks
A1: Time | B1: Course | C1: Race | D1: Runners | E1: Top pick | F1: Jockey | G1: Trainer | H1: Predicted BSP | I1: Win probability | J1: Second choice | K1: Second's BSP | L1: Second's probability | M1: Probability gap | N1: Card odds (HRB) | O1: Rule: back at Betfair ≥
A2: 1:55 | B2: Cork | C2: Irish Stallion Farms EBF Maiden | D2: 13 | E2: Bold Commander (IRE) | F2: Lordan, W M | G2: OBrien, A P | H2: 4.6201822 | I2: 0.21644168 | J2: Sonny Hayes (IRE) | K2: 5.1099387 | L2: 0.19569706 | M2: =IF(AND(ISNUMBER(I2),ISNUMBER(L2)),I2-L2,"") -> 0.020744618 | N2: 2.5 | O2: =IF(AND(ISNUMBER(H2),H2>0),H2*EXP('Read me'!$B$22),"") -> 5.6431032
A3: 2:02 | B3: Bath | C3: JDL Consultants Ltd Apprentice Handicap | D3: 11 | E3: Decalogue (USA) | F3: Paetel, Mason | G3: Osborne, J A | H3: 5.5561386 | I3: 0.17998111 | J3: Pangbourne | K3: 6.4064338 | L3: 0.15609308 | M3: =IF(AND(ISNUMBER(I3),ISNUMBER(L3)),I3-L3,"") -> 0.023888028 | N3: 4.5 | O3: =IF(AND(ISNUMBER(H3),H3>0),H3*EXP('Read me'!$B$22),"") -> 6.786283
A4: 2:08 | B4: Ayr | C4: Christmas Party Day Dancing At Ayr Racecourse Apprentice Handicap | D4: 8 | E4: Empirestateofmind (IRE) | F4: Callan, Jack | G4: Quinn, J J | H4: 3.2135037 | I4: 0.31118682 | J4: Motawaared | K4: 5.1649624 | L4: 0.19361225 | M4: =IF(AND(ISNUMBER(I4),ISNUMBER(L4)),I4-L4,"") -> 0.11757457 | N4: 2.75 | O4: =IF(AND(ISNUMBER(H4),H4>0),H4*EXP('Read me'!$B$22),"") -> 3.9249823
A5: 2:15 | B5: Sedgefield | C5: Happy 96th Birthday John Conditional Jockeys Handicap Hurdle | D5: 7 | E5: Spartan Times | F5: Scott, Luke | G5: Candlish, Jennie | H5: 3.3706659 | I5: 0.29667728 | J5: Jolie Coeur Allen (FR) | K5: 5.2106078 | L5: 0.19191619 | M5: =IF(AND(ISNUMBER(I5),ISNUMBER(L5)),I5-L5,"") -> 0.10476109 | N5: 2.875 | O5: =IF(AND(ISNUMBER(H5),H5>0),H5*EXP('Read me'!$B$22),"") -> 4.1169407
A6: 2:25 | B6: Cork | C6: Irish Stallion Farms EBF Nursery Handicap (Birdcatcher Series) | D6: 7 | E6: Pink Venom (IRE) | F6: Coen, Ben M | G6: Murtagh, J P | H6: 2.9968914 | I6: 0.33367909 | J6: Fine Line (IRE) | K6: 5.8739402 | L6: 0.17024348 | M6: =IF(AND(ISNUMBER(I6),ISNUMBER(L6)),I6-L6,"") -> 0.16343561 | N6: 2 | O6: =IF(AND(ISNUMBER(H6),H6>0),H6*EXP('Read me'!$B$22),"") -> 3.6604114
A7: 2:32 | B7: Bath | C7: MJ Church Handicap | D7: 13 | E7: Cosmo Brown (IRE) | F7: Edmunds, Lewis | G7: Muir, W R & Grassick, C | H7: 6.0547482 | I7: 0.16515963 | J7: Zarco | K7: 7.0423239 | L7: 0.14199858 | M7: =IF(AND(ISNUMBER(I7),ISNUMBER(L7)),I7-L7,"") -> 0.023161053 | N7: 6 | O7: =IF(AND(ISNUMBER(H7),H7>0),H7*EXP('Read me'!$B$22),"") -> 7.3952862
A8: 2:38 | B8: Ayr | C8: Weddings At Western House Hotel Maiden Stakes (GBB Race) | D8: 6 | E8: Melody Man | F8: Hart, Jason | G8: Quinn, J J | H8: 3.0885181 | I8: 0.32377987 | J8: What A Girl Wants (IRE) | K8: 3.9448211 | L8: 0.25349692 | M8: =IF(AND(ISNUMBER(I8),ISNUMBER(L8)),I8-L8,"") -> 0.070282951 | N8: 7 | O8: =IF(AND(ISNUMBER(H8),H8>0),H8*EXP('Read me'!$B$22),"") -> 3.7723246
A9: 2:45 | B9: Sedgefield | C9: Roxyfet Sports Lounge For Private Hire Juvenile Maiden Hurdle (GBB Race) | D9: 7 | E9: Steel Raven (IRE) | F9: Hughes, Brian | G9: Keatley, Adrian Paul | H9: 1.3730685 | I9: 0.72829576 | J9: Jerseygeordie | K9: 9.9272015 | L9: 0.10073332 | M9: =IF(AND(ISNUMBER(I9),ISNUMBER(L9)),I9-L9,"") -> 0.62756244 | N9: 1.6153846 | O9: =IF(AND(ISNUMBER(H9),H9>0),H9*EXP('Read me'!$B$22),"") -> 1.6770697
A10: 2:55 | B10: Cork | C10: Irish Stallion Farms EBF Fillies Handicap | D10: 9 | E10: By The Lake (IRE) | F10: Keane, C T | G10: McCormack, Derek | H10: 4.7378235 | I10: 0.21106738 | J10: Forza Magico | K10: 6.5293068 | L10: 0.15315562 | M10: =IF(AND(ISNUMBER(I10),ISNUMBER(L10)),I10-L10,"") -> 0.057911764 | N10: 7.5 | O10: =IF(AND(ISNUMBER(H10),H10>0),H10*EXP('Read me'!$B$22),"") -> 5.7867907
A11: 3:02 | B11: Bath | C11: AEL Solutions Handicap | D11: 12 | E11: Buckland Belle | F11: Marquand, Tom | G11: Sangster, Ollie | H11: 3.2266287 | I11: 0.309921 | J11: Rating (IRE) | K11: 6.9381041 | L11: 0.14413159 | M11: =IF(AND(ISNUMBER(I11),ISNUMBER(L11)),I11-L11,"") -> 0.16578941 | N11: 2.875 | O11: =IF(AND(ISNUMBER(H11),H11>0),H11*EXP('Read me'!$B$22),"") -> 3.9410132
A12: 3:08 | B12: Ayr | C12: Nairnss Oatcakes Handicap (GBBPlus Race) | D12: 9 | E12: Star Cast | F12: Dickson, Jake | G12: Tutty, Gemma | H12: 5.2588233 | I12: 0.19015661 | J12: Keep An Eye On It | K12: 5.3288144 | L12: 0.187659 | M12: =IF(AND(ISNUMBER(I12),ISNUMBER(L12)),I12-L12,"") -> 0.0024976039 | N12: 4 | O12: =IF(AND(ISNUMBER(H12),H12>0),H12*EXP('Read me'!$B$22),"") -> 6.4231413
A13: 3:15 | B13: Sedgefield | C13: Paxtons No1 CaseIH Dealer Handicap Chase (GBB Race) | D13: 4 | E13: Passengerontheship (IRE) | F13: England, Jonathan | G13: England, Sam | H13: 2.5505 | I13: 0.39207999 | J13: Thank You Blue | K13: 3.5014656 | L13: 0.2855947 | M13: =IF(AND(ISNUMBER(I13),ISNUMBER(L13)),I13-L13,"") -> 0.10648529 | N13: 2.5 | O13: =IF(AND(ISNUMBER(H13),H13>0),H13*EXP('Read me'!$B$22),"") -> 3.1151877
... A39: 8:30 | B39: Wolverhampton | C39: Sky Sports Racing Sky 415 Handicap (Div 2) | D39: 8 | E39: African Spirit (IRE) | F39: Loughnane, Billy | G39: Williams, Ian | H39: 2.6247749 | I39: 0.38098505 | J39: Dumfries | K39: 5.0308556 | L39: 0.19877335 | M39: =IF(AND(ISNUMBER(I39),ISNUMBER(L39)),I39-L39,"") -> 0.1822117 | N39: 3.5 | O39: =IF(AND(ISNUMBER(H39),H39>0),H39*EXP('Read me'!$B$22),"") -> 3.2059073

Sheet Non-runners
A1: Time | B1: Course | C1: Horse | D1: Its predicted BSP | E1: Share of the book | F1: Others' prices ×
A2: 3:02 | B2: Bath | C2: Mayberry Moon | D2: 45.456645 | E2: 0.021998984 | F2: =IF(ISNUMBER(E2),1-E2,"") -> 0.97800102
A3: 3:25 | B3: Cork | C3: Ukiyo (IRE) | D3: 16.090698 | E3: 0.062147708 | F3: =IF(ISNUMBER(E3),1-E3,"") -> 0.93785229
A4: 4:25 | B4: Cork | C4: Knightlight | D4: 102.98665 | E4: 0.0097099967 | F4: =IF(ISNUMBER(E4),1-E4,"") -> 0.99029
A5: 5:25 | B5: Cork | C5: Blue Orquidea (IRE) | D5: 84.053113 | E5: 0.011897239 | F5: =IF(ISNUMBER(E5),1-E5,"") -> 0.98810276
A6: 5:25 | B6: Cork | C6: Cause I Like You (IRE) | D6: 8.1881084 | E6: 0.12212833 | F6: =IF(ISNUMBER(E6),1-E6,"") -> 0.87787167
A7: 5:25 | B7: Cork | C7: Jazz Dreamers (IRE) | D7: 57.396099 | E7: 0.017422787 | F7: =IF(ISNUMBER(E7),1-E7,"") -> 0.98257721
A8: 5:30 | B8: Wolverhampton | C8: Arabian Summer (IRE) | D8: 4.2894501 | E8: 0.23313011 | F8: =IF(ISNUMBER(E8),1-E8,"") -> 0.76686989
A9: 6:00 | B9: Wolverhampton | C9: Venetian Romance (IRE) | D9: 348.91062 | E9: 0.0028660635 | F9: =IF(ISNUMBER(E9),1-E9,"") -> 0.99713394
A10: 7:00 | B10: Wolverhampton | C10: Cosmic Clarets (IRE) | D10: 12.451783 | E10: 0.080309786 | F10: =IF(ISNUMBER(E10),1-E10,"") -> 0.91969021
A11: 8:00 | B11: Wolverhampton | C11: Tortola (IRE) | D11: 9.8599752 | E11: 0.10142013 | F11: =IF(ISNUMBER(E11),1-E11,"") -> 0.89857987
A12: 8:30 | B12: Wolverhampton | C12: Book Of Life | D12: 4.3426933 | E12: 0.23027184 | F12: =IF(ISNUMBER(E12),1-E12,"") -> 0.76972816

Sheet gated 10.53 vs 09.37
A1: Time | B1: Course | C1: Race | D1: Runners (now) | E1: gated 10:53 top pick | F1: gated 10:53 BSP | G1: Its 09:37 BSP | H1: 09:37 top pick (runners still declared) | I1: 09:37 BSP | J1: Same pick? | K1: gated 10:53 vs 09:37 on the gated 10:53's pick
A2: 1:55 | B2: Cork | C2: Irish Stallion Farms EBF Maiden | D2: 13 | E2: Bold Commander (IRE) | F2: 4.6201822 | G2: 4.6201822 | H2: Bold Commander (IRE) | I2: 4.6201822 | J2: =IF(E2=H2,"yes","no") -> yes | K2: =IF(AND(ISNUMBER(F2),ISNUMBER(G2)),F2/G2-1,"") -> 0
A3: 2:02 | B3: Bath | C3: JDL Consultants Ltd Apprentice Handicap | D3: 11 | E3: Decalogue (USA) | F3: 5.5561386 | G3: 5.5561386 | H3: Decalogue (USA) | I3: 5.5561386 | J3: =IF(E3=H3,"yes","no") -> yes | K3: =IF(AND(ISNUMBER(F3),ISNUMBER(G3)),F3/G3-1,"") -> 0
A4: 2:08 | B4: Ayr | C4: Christmas Party Day Dancing At Ayr Racecourse Apprentice Handicap | D4: 8 | E4: Empirestateofmind (IRE) | F4: 3.2135037 | G4: 3.2135037 | H4: Empirestateofmind (IRE) | I4: 3.2135037 | J4: =IF(E4=H4,"yes","no") -> yes | K4: =IF(AND(ISNUMBER(F4),ISNUMBER(G4)),F4/G4-1,"") -> 0
A5: 2:15 | B5: Sedgefield | C5: Happy 96th Birthday John Conditional Jockeys Handicap Hurdle | D5: 7 | E5: Spartan Times | F5: 3.3706659 | G5: 3.3706659 | H5: Spartan Times | I5: 3.3706659 | J5: =IF(E5=H5,"yes","no") -> yes | K5: =IF(AND(ISNUMBER(F5),ISNUMBER(G5)),F5/G5-1,"") -> 0
A6: 2:25 | B6: Cork | C6: Irish Stallion Farms EBF Nursery Handicap (Birdcatcher Series) | D6: 7 | E6: Pink Venom (IRE) | F6: 2.9968914 | G6: 2.9977529 | H6: Pink Venom (IRE) | I6: 2.9977529 | J6: =IF(E6=H6,"yes","no") -> yes | K6: =IF(AND(ISNUMBER(F6),ISNUMBER(G6)),F6/G6-1,"") -> -0.00028736794
A7: 2:32 | B7: Bath | C7: MJ Church Handicap | D7: 13 | E7: Cosmo Brown (IRE) | F7: 6.0547482 | G7: 6.0547482 | H7: Cosmo Brown (IRE) | I7: 6.0547482 | J7: =IF(E7=H7,"yes","no") -> yes | K7: =IF(AND(ISNUMBER(F7),ISNUMBER(G7)),F7/G7-1,"") -> 0
A8: 2:38 | B8: Ayr | C8: Weddings At Western House Hotel Maiden Stakes (GBB Race) | D8: 6 | E8: Melody Man | F8: 3.0885181 | G8: 3.0885181 | H8: Melody Man | I8: 3.0885181 | J8: =IF(E8=H8,"yes","no") -> yes | K8: =IF(AND(ISNUMBER(F8),ISNUMBER(G8)),F8/G8-1,"") -> 0
A9: 2:45 | B9: Sedgefield | C9: Roxyfet Sports Lounge For Private Hire Juvenile Maiden Hurdle (GBB Race) | D9: 7 | E9: Steel Raven (IRE) | F9: 1.3730685 | G9: 1.3730685 | H9: Steel Raven (IRE) | I9: 1.3730685 | J9: =IF(E9=H9,"yes","no") -> yes | K9: =IF(AND(ISNUMBER(F9),ISNUMBER(G9)),F9/G9-1,"") -> 0
A10: 2:55 | B10: Cork | C10: Irish Stallion Farms EBF Fillies Handicap | D10: 9 | E10: By The Lake (IRE) | F10: 4.7378235 | G10: 4.7378235 | H10: By The Lake (IRE) | I10: 4.7378235 | J10: =IF(E10=H10,"yes","no") -> yes | K10: =IF(AND(ISNUMBER(F10),ISNUMBER(G10)),F10/G10-1,"") -> 0
A11: 3:02 | B11: Bath | C11: AEL Solutions Handicap | D11: 12 | E11: Buckland Belle | F11: 3.2266287 | G11: 3.2266287 | H11: Buckland Belle | I11: 3.2266287 | J11: =IF(E11=H11,"yes","no") -> yes | K11: =IF(AND(ISNUMBER(F11),ISNUMBER(G11)),F11/G11-1,"") -> 0
A12: 3:08 | B12: Ayr | C12: Nairnss Oatcakes Handicap (GBBPlus Race) | D12: 9 | E12: Star Cast | F12: 5.2588233 | G12: 5.2588233 | H12: Star Cast | I12: 5.2588233 | J12: =IF(E12=H12,"yes","no") -> yes | K12: =IF(AND(ISNUMBER(F12),ISNUMBER(G12)),F12/G12-1,"") -> 0
A13: 3:15 | B13: Sedgefield | C13: Paxtons No1 CaseIH Dealer Handicap Chase (GBB Race) | D13: 4 | E13: Passengerontheship (IRE) | F13: 2.5505 | G13: 2.5505 | H13: Passengerontheship (IRE) | I13: 2.5505 | J13: =IF(E13=H13,"yes","no") -> yes | K13: =IF(AND(ISNUMBER(F13),ISNUMBER(G13)),F13/G13-1,"") -> 0
... A39: 8:30 | B39: Wolverhampton | C39: Sky Sports Racing Sky 415 Handicap (Div 2) | D39: 8 | E39: African Spirit (IRE) | F39: 2.6247749 | G39: 3.3404251 | H39: African Spirit (IRE) | I39: 3.3404251 | J39: =IF(E39=H39,"yes","no") -> yes | K39: =IF(AND(ISNUMBER(F39),ISNUMBER(G39)),F39/G39-1,"") -> -0.21423926
A41: Races with the same top pick | E41: =COUNTIF(J2:J39,"yes")&" of "&COUNTA(J2:J39) -> 38 of 38

Sheet All runners
A1: Time | B1: Course | C1: Race | D1: Class | E1: Furlongs | F1: Going | G1: Runners | H1: Horse | I1: Jockey | J1: Trainer | K1: Draw | L1: OR | M1: Age | N1: Days since run | O1: Model rank | P1: Predicted BSP | Q1: Win probability | R1: Card odds (HRB) | S1: Card odds vs model | T1: Rule: back at Betfair ≥
A2: 1:55 | B2: Cork | C2: Irish Stallion Farms EBF Maiden | E2: 5 | F2: Yielding | G2: 13 | H2: Bold Commander (IRE) | I2: Lordan, W M | J2: OBrien, A P | K2: 4 | L2: 78 | M2: 2 | N2: 12 | O2: 1 | P2: 4.6201822 | Q2: 0.21644168 | R2: 2.5 | S2: =IF(AND(ISNUMBER(R2),R2>1,P2>0),R2/P2-1,"") -> -0.45889579 | T2: =IF(AND(ISNUMBER(P2),P2>0),P2*EXP('Read me'!$B$22),"") -> 5.6431032
A3: 1:55 | B3: Cork | C3: Irish Stallion Farms EBF Maiden | E3: 5 | F3: Yielding | G3: 13 | H3: Sonny Hayes (IRE) | I3: OConnor, Donagh | J3: Aguiar, Robson | K3: 7 | L3: 0 | M3: 2 | O3: 2 | P3: 5.1099387 | Q3: 0.19569706 | R3: 6 | S3: =IF(AND(ISNUMBER(R3),R3>1,P3>0),R3/P3-1,"") -> 0.17418239 | T3: =IF(AND(ISNUMBER(P3),P3>0),P3*EXP('Read me'!$B$22),"") -> 6.2412932
A4: 1:55 | B4: Cork | C4: Irish Stallion Farms EBF Maiden | E4: 5 | F4: Yielding | G4: 13 | H4: El Domino | I4: Slattery, A J | J4: Slattery, Andrew | K4: 9 | L4: 75 | M4: 2 | N4: 20 | O4: 3 | P4: 6.8919554 | Q4: 0.1450967 | R4: 5.5 | S4: =IF(AND(ISNUMBER(R4),R4>1,P4>0),R4/P4-1,"") -> -0.20196814 | T4: =IF(AND(ISNUMBER(P4),P4>0),P4*EXP('Read me'!$B$22),"") -> 8.4178533
A5: 1:55 | B5: Cork | C5: Irish Stallion Farms EBF Maiden | E5: 5 | F5: Yielding | G5: 13 | H5: Alfresco (IRE) | I5: Ryan, Gavin | J5: Obrien, Donnacha | K5: 5 | L5: 0 | M5: 2 | N5: 12 | O5: 4 | P5: 8.3317733 | Q5: 0.12002247 | R5: 7 | S5: =IF(AND(ISNUMBER(R5),R5>1,P5>0),R5/P5-1,"") -> -0.15984272 | T5: =IF(AND(ISNUMBER(P5),P5>0),P5*EXP('Read me'!$B$22),"") -> 10.176451
A6: 1:55 | B6: Cork | C6: Irish Stallion Farms EBF Maiden | E6: 5 | F6: Yielding | G6: 13 | H6: Anthony Of Lisbon | I6: Frain, Freya | J6: OBrien, A P | K6: 12 | L6: 0 | M6: 2 | N6: 109 | O6: 5 | P6: 9.9724355 | Q6: 0.10027641 | R6: 7 | S6: =IF(AND(ISNUMBER(R6),R6>1,P6>0),R6/P6-1,"") -> -0.29806515 | T6: =IF(AND(ISNUMBER(P6),P6>0),P6*EXP('Read me'!$B$22),"") -> 12.18036
A7: 1:55 | B7: Cork | C7: Irish Stallion Farms EBF Maiden | E7: 5 | F7: Yielding | G7: 13 | H7: Sapphire Sun (IRE) | J7: Murtagh, J P | K7: 3 | L7: 0 | M7: 2 | N7: 16 | O7: 6 | P7: 10.852561 | Q7: 0.092144149 | R7: 4 | S7: =IF(AND(ISNUMBER(R7),R7>1,P7>0),R7/P7-1,"") -> -0.6314234 | T7: =IF(AND(ISNUMBER(P7),P7>0),P7*EXP('Read me'!$B$22),"") -> 13.255348
A8: 1:55 | B8: Cork | C8: Irish Stallion Farms EBF Maiden | E8: 5 | F8: Yielding | G8: 13 | H8: Lion Of Fortune (IRE) | I8: Whelan, R P | J8: Cotter, Kieran P | K8: 8 | L8: 0 | M8: 2 | N8: 44 | O8: 7 | P8: 16.182722 | Q8: 0.061794301 | R8: 12 | S8: =IF(AND(ISNUMBER(R8),R8>1,P8>0),R8/P8-1,"") -> -0.25846838 | T8: =IF(AND(ISNUMBER(P8),P8>0),P8*EXP('Read me'!$B$22),"") -> 19.765621
A9: 1:55 | B9: Cork | C9: Irish Stallion Farms EBF Maiden | E9: 5 | F9: Yielding | G9: 13 | H9: Spirit Of The Nite (IRE) | I9: Ryan, J J G | J9: McCourt, T G | K9: 11 | L9: 0 | M9: 2 | N9: 11 | O9: 8 | P9: 30.375508 | Q9: 0.032921261 | R9: 11 | S9: =IF(AND(ISNUMBER(R9),R9>1,P9>0),R9/P9-1,"") -> -0.63786613 | T9: =IF(AND(ISNUMBER(P9),P9>0),P9*EXP('Read me'!$B$22),"") -> 37.100729
A10: 1:55 | B10: Cork | C10: Irish Stallion Farms EBF Maiden | E10: 5 | F10: Yielding | G10: 13 | H10: Sorrento Sunset (IRE) | I10: Powell, J A | J10: McLoughlin, Daniel | K10: 6 | L10: 0 | M10: 2 | N10: 25 | O10: 9 | P10: 58.116284 | Q10: 0.017206881 | R10: 51 | S10: =IF(AND(ISNUMBER(R10),R10>1,P10>0),R10/P10-1,"") -> -0.12244906 | T10: =IF(AND(ISNUMBER(P10),P10>0),P10*EXP('Read me'!$B$22),"") -> 70.98339
A11: 1:55 | B11: Cork | C11: Irish Stallion Farms EBF Maiden | E11: 5 | F11: Yielding | G11: 13 | H11: Lolapipa (IRE) | I11: Persse, A C | J11: Cahill, Mark | K11: 1 | L11: 0 | M11: 2 | O11: 10 | P11: 99.062393 | Q11: 0.010094648 | R11: 151 | S11: =IF(AND(ISNUMBER(R11),R11>1,P11>0),R11/P11-1,"") -> 0.52429187 | T11: =IF(AND(ISNUMBER(P11),P11>0),P11*EXP('Read me'!$B$22),"") -> 120.99508
A12: 1:55 | B12: Cork | C12: Irish Stallion Farms EBF Maiden | E12: 5 | F12: Yielding | G12: 13 | H12: Habu (IRE) | I12: Tynan, Orla | J12: Tynan, M J | K12: 2 | L12: 0 | M12: 2 | N12: 12 | O12: 11 | P12: 334.04285 | Q12: 0.0029936279 | R12: 81 | S12: =IF(AND(ISNUMBER(R12),R12>1,P12>0),R12/P12-1,"") -> -0.75751614 | T12: =IF(AND(ISNUMBER(P12),P12>0),P12*EXP('Read me'!$B$22),"") -> 408.00086
A13: 1:55 | B13: Cork | C13: Irish Stallion Farms EBF Maiden | E13: 5 | F13: Yielding | G13: 13 | H13: Imply (IRE) | I13: Mulligan, R M | J13: Weld, Charles | K13: 10 | L13: 0 | M13: 2 | N13: 12 | O13: 12 | P13: 361.67997 | Q13: 0.0027648752 | R13: 151 | S13: =IF(AND(ISNUMBER(R13),R13>1,P13>0),R13/P13-1,"") -> -0.58250384 | T13: =IF(AND(ISNUMBER(P13),P13>0),P13*EXP('Read me'!$B$22),"") -> 441.75692
A14: 1:55 | B14: Cork | C14: Irish Stallion Farms EBF Maiden | E14: 5 | F14: Yielding | G14: 13 | H14: Bettercalltheboss (IRE) | I14: Cleary, R P | J14: Lynch, Miss Jennifer Anne | K14: 13 | L14: 0 | M14: 2 | N14: 69 | O14: 13 | P14: 392.78351 | Q14: 0.0025459318 | R14: 151 | S14: =IF(AND(ISNUMBER(R14),R14>1,P14>0),R14/P14-1,"") -> -0.61556431 | T14: =IF(AND(ISNUMBER(P14),P14>0),P14*EXP('Read me'!$B$22),"") -> 479.74686
A15: 2:02 | B15: Bath | C15: JDL Consultants Ltd Apprentice Handicap | D15: Class 5 | E15: 10 | F15: Good To Firm | G15: 11 | H15: Decalogue (USA) | I15: Paetel, Mason | J15: Osborne, J A | K15: 1 | L15: 73 | M15: 3 | N15: 15 | O15: 1 | P15: 5.5561386 | Q15: 0.17998111 | R15: 4.5 | S15: =IF(AND(ISNUMBER(R15),R15>1,P15>0),R15/P15-1,"") -> -0.190085 | T15: =IF(AND(ISNUMBER(P15),P15>0),P15*EXP('Read me'!$B$22),"") -> 6.786283
A16: 2:02 | B16: Bath | C16: JDL Consultants Ltd Apprentice Handicap | D16: Class 5 | E16: 10 | F16: Good To Firm | G16: 11 | H16: Pangbourne | I16: Haines, Olivia | J16: Teal, R A | K16: 3 | L16: 56 | M16: 3 | N16: 13 | O16: 2 | P16: 6.4064338 | Q16: 0.15609308 | R16: 6 | S16: =IF(AND(ISNUMBER(R16),R16>1,P16>0),R16/P16-1,"") -> -0.063441498 | T16: =IF(AND(ISNUMBER(P16),P16>0),P16*EXP('Read me'!$B$22),"") -> 7.8248359
A17: 2:02 | B17: Bath | C17: JDL Consultants Ltd Apprentice Handicap | D17: Class 5 | E17: 10 | F17: Good To Firm | G17: 11 | H17: Shady Bay (IRE) | I17: Lewis, Ashley | J17: Ward, Tom | K17: 4 | L17: 74 | M17: 5 | N17: 32 | O17: 3 | P17: 6.6128169 | Q17: 0.15122149 | R17: 4 | S17: =IF(AND(ISNUMBER(R17),R17>1,P17>0),R17/P17-1,"") -> -0.39511406 | T17: =IF(AND(ISNUMBER(P17),P17>0),P17*EXP('Read me'!$B$22),"") -> 8.0769128
A18: 2:02 | B18: Bath | C18: JDL Consultants Ltd Apprentice Handicap | D18: Class 5 | E18: 10 | F18: Good To Firm | G18: 11 | H18: Oman (IRE) | I18: Coppins, Myla | J18: Carroll, A W | K18: 2 | L18: 68 | M18: 8 | N18: 18 | O18: 4 | P18: 10.638227 | Q18: 0.094000622 | R18: 7.5 | S18: =IF(AND(ISNUMBER(R18),R18>1,P18>0),R18/P18-1,"") -> -0.29499533 | T18: =IF(AND(ISNUMBER(P18),P18>0),P18*EXP('Read me'!$B$22),"") -> 12.99356
A19: 2:02 | B19: Bath | C19: JDL Consultants Ltd Apprentice Handicap | D19: Class 5 | E19: 10 | F19: Good To Firm | G19: 11 | H19: Dryburgh (IRE) | I19: Catton, Luke | J19: Rix, Oli | K19: 6 | L19: 75 | M19: 3 | N19: 52 | O19: 5 | P19: 11.172339 | Q19: 0.089506772 | R19: 8 | S19: =IF(AND(ISNUMBER(R19),R19>1,P19>0),R19/P19-1,"") -> -0.28394583 | T19: =IF(AND(ISNUMBER(P19),P19>0),P19*EXP('Read me'!$B$22),"") -> 13.645926
A20: 2:02 | B20: Bath | C20: JDL Consultants Ltd Apprentice Handicap | D20: Class 5 | E20: 10 | F20: Good To Firm | G20: 11 | H20: Captain Fox (IRE) | I20: Murphy, D J | J20: Hughes, Richard | K20: 11 | L20: 72 | M20: 3 | N20: 17 | O20: 6 | P20: 12.059594 | Q20: 0.082921534 | R20: 8.5 | S20: =IF(AND(ISNUMBER(R20),R20>1,P20>0),R20/P20-1,"") -> -0.29516696 | T20: =IF(AND(ISNUMBER(P20),P20>0),P20*EXP('Read me'!$B$22),"") -> 14.729621
A21: 2:02 | B21: Bath | C21: JDL Consultants Ltd Apprentice Handicap | D21: Class 5 | E21: 10 | F21: Good To Firm | G21: 11 | H21: Its Life | J21: Turner, Kathy | K21: 5 | L21: 56 | M21: 4 | N21: 36 | O21: 7 | P21: 13.008317 | Q21: 0.076873894 | R21: 13 | S21: =IF(AND(ISNUMBER(R21),R21>1,P21>0),R21/P21-1,"") -> -0.0006393754 | T21: =IF(AND(ISNUMBER(P21),P21>0),P21*EXP('Read me'!$B$22),"") -> 15.888395
A22: 2:02 | B22: Bath | C22: JDL Consultants Ltd Apprentice Handicap | D22: Class 5 | E22: 10 | F22: Good To Firm | G22: 11 | H22: Pomme Pomme (IRE) | I22: Dace, Jack | J22: Channon, Jack | K22: 7 | L22: 72 | M22: 4 | N22: 26 | O22: 8 | P22: 14.159192 | Q22: 0.070625499 | R22: 13 | S22: =IF(AND(ISNUMBER(R22),R22>1,P22>0),R22/P22-1,"") -> -0.081868507 | T22: =IF(AND(ISNUMBER(P22),P22>0),P22*EXP('Read me'!$B$22),"") -> 17.294076
A23: 2:02 | B23: Bath | C23: JDL Consultants Ltd Apprentice Handicap | D23: Class 5 | E23: 10 | F23: Good To Firm | G23: 11 | H23: Gallant Pioneer (IRE) | I23: Vigors, Harry | J23: Pike, Charlie | K23: 8 | L23: 64 | M23: 3 | N23: 43 | O23: 9 | P23: 18.845741 | Q23: 0.053062388 | R23: 17 | S23: =IF(AND(ISNUMBER(R23),R23>1,P23>0),R23/P23-1,"") -> -0.09793941 | T23: =IF(AND(ISNUMBER(P23),P23>0),P23*EXP('Read me'!$B$22),"") -> 23.01824
A24: 2:02 | B24: Bath | C24: JDL Consultants Ltd Apprentice Handicap | D24: Class 5 | E24: 10 | F24: Good To Firm | G24: 11 | H24: Rascallion (FR) | I24: Langley, Taryn | J24: Knight, Miss H C | K24: 10 | L24: 70 | M24: 7 | N24: 508 | O24: 10 | P24: 43.218903 | Q24: 0.023138024 | R24: 26 | S24: =IF(AND(ISNUMBER(R24),R24>1,P24>0),R24/P24-1,"") -> -0.39841139 | T24: =IF(AND(ISNUMBER(P24),P24>0),P24*EXP('Read me'!$B$22),"") -> 52.787687
A25: 2:02 | B25: Bath | C25: JDL Consultants Ltd Apprentice Handicap | D25: Class 5 | E25: 10 | F25: Good To Firm | G25: 11 | H25: Arcadian Nights | I25: Regan, Hope | J25: Loughnane, Daniel Mark | K25: 9 | L25: 72 | M25: 8 | N25: 26 | O25: 11 | P25: 44.295637 | Q25: 0.022575587 | R25: 51 | S25: =IF(AND(ISNUMBER(R25),R25>1,P25>0),R25/P25-1,"") -> 0.15135492 | T25: =IF(AND(ISNUMBER(P25),P25>0),P25*EXP('Read me'!$B$22),"") -> 54.102814
A26: 2:08 | B26: Ayr | C26: Christmas Party Day Dancing At Ayr Racecourse Apprentice Handicap | D26: Class 5 | E26: 8 | F26: Heavy | G26: 8 | H26: Empirestateofmind (IRE) | I26: Callan, Jack | J26: Quinn, J J | K26: 2 | L26: 71 | M26: 8 | N26: 9 | O26: 1 | P26: 3.2135037 | Q26: 0.31118682 | R26: 2.75 | S26: =IF(AND(ISNUMBER(R26),R26>1,P26>0),R26/P26-1,"") -> -0.14423624 | T26: =IF(AND(ISNUMBER(P26),P26>0),P26*EXP('Read me'!$B$22),"") -> 3.9249823
A27: 2:08 | B27: Ayr | C27: Christmas Party Day Dancing At Ayr Racecourse Apprentice Handicap | D27: Class 5 | E27: 8 | F27: Heavy | G27: 8 | H27: Motawaared | I27: Young, Lauren | J27: Goldie, J S | K27: 3 | L27: 60 | M27: 4 | N27: 9 | O27: 2 | P27: 5.1649624 | Q27: 0.19361225 | R27: 3.75 | S27: =IF(AND(ISNUMBER(R27),R27>1,P27>0),R27/P27-1,"") -> -0.27395405 | T27: =IF(AND(ISNUMBER(P27),P27>0),P27*EXP('Read me'!$B$22),"") -> 6.3084993
A28: 2:08 | B28: Ayr | C28: Christmas Party Day Dancing At Ayr Racecourse Apprentice Handicap | D28: Class 5 | E28: 8 | F28: Heavy | G28: 8 | H28: Penelopes Sister (IRE) | I28: Farmer, Shay | J28: Goldie, J S | K28: 6 | L28: 57 | M28: 6 | N28: 11 | O28: 3 | P28: 7.8295143 | Q28: 0.12772184 | R28: 5 | S28: =IF(AND(ISNUMBER(R28),R28>1,P28>0),R28/P28-1,"") -> -0.36139078 | T28: =IF(AND(ISNUMBER(P28),P28>0),P28*EXP('Read me'!$B$22),"") -> 9.5629903
A29: 2:08 | B29: Ayr | C29: Christmas Party Day Dancing At Ayr Racecourse Apprentice Handicap | D29: Class 5 | E29: 8 | F29: Heavy | G29: 8 | H29: Leopards Rock | I29: Horgan, C | J29: Bethell, Ed | K29: 8 | L29: 72 | M29: 3 | N29: 20 | O29: 4 | P29: 9.9009327 | Q29: 0.10100059 | R29: 7.5 | S29: =IF(AND(ISNUMBER(R29),R29>1,P29>0),R29/P29-1,"") -> -0.24249561 | T29: =IF(AND(ISNUMBER(P29),P29>0),P29*EXP('Read me'!$B$22),"") -> 12.093026
A30: 2:08 | B30: Ayr | C30: Christmas Party Day Dancing At Ayr Racecourse Apprentice Handicap | D30: Class 5 | E30: 8 | F30: Heavy | G30: 8 | H30: Kindest Nation (IRE) | I30: Nicholls, Jack | J30: Palmer, Hugo | K30: 5 | L30: 69 | M30: 5 | N30: 17 | O30: 5 | P30: 11.509629 | Q30: 0.086883773 | R30: 26 | S30: =IF(AND(ISNUMBER(R30),R30>1,P30>0),R30/P30-1,"") -> 1.2589781 | T30: =IF(AND(ISNUMBER(P30),P30>0),P30*EXP('Read me'!$B$22),"") -> 14.057893
A31: 2:08 | B31: Ayr | C31: Christmas Party Day Dancing At Ayr Racecourse Apprentice Handicap | D31: Class 5 | E31: 8 | F31: Heavy | G31: 8 | H31: Swift Salian (IRE) | I31: Pyle, William | J31: Barron, T D | K31: 1 | L31: 72 | M31: 5 | N31: 20 | O31: 6 | P31: 12.682362 | Q31: 0.078849665 | R31: 13 | S31: =IF(AND(ISNUMBER(R31),R31>1,P31>0),R31/P31-1,"") -> 0.02504565 | T31: =IF(AND(ISNUMBER(P31),P31>0),P31*EXP('Read me'!$B$22),"") -> 15.490272
A32: 2:08 | B32: Ayr | C32: Christmas Party Day Dancing At Ayr Racecourse Apprentice Handicap | D32: Class 5 | E32: 8 | F32: Heavy | G32: 8 | H32: Runninsonofagun (IRE) | I32: Jary, Alex | J32: Davidson, Tristan | K32: 4 | L32: 70 | M32: 4 | N32: 12 | O32: 7 | P32: 13.851606 | Q32: 0.072193794 | R32: 19 | S32: =IF(AND(ISNUMBER(R32),R32>1,P32>0),R32/P32-1,"") -> 0.3716821 | T32: =IF(AND(ISNUMBER(P32),P32>0),P32*EXP('Read me'!$B$22),"") -> 16.91839
A33: 2:08 | B33: Ayr | C33: Christmas Party Day Dancing At Ayr Racecourse Apprentice Handicap | D33: Class 5 | E33: 8 | F33: Heavy | G33: 8 | H33: Arkenstaar | I33: Elliott, Rhys | J33: Dods, M | K33: 7 | L33: 69 | M33: 6 | N33: 20 | O33: 8 | P33: 35.024721 | Q33: 0.028551262 | R33: 23 | S33: =IF(AND(ISNUMBER(R33),R33>1,P33>0),R33/P33-1,"") -> -0.34332097 | T33: =IF(AND(ISNUMBER(P33),P33>0),P33*EXP('Read me'!$B$22),"") -> 42.779291
... A40: 2:15 | B40: Sedgefield | C40: Happy 96th Birthday John Conditional Jockeys Handicap Hurdle | D40: Class 5 | E40: 16.5 | F40: Good | G40: 7 | H40: Mr Globalist (IRE) | I40: Noreci, Leah | J40: Quinlan, Elizabeth | K40: 7 | L40: 79 | M40: 7 | N40: 15 | O40: 7 | P40: 20.530267 | Q40: 0.048708573 | R40: 21 | S40: =IF(AND(ISNUMBER(R40),R40>1,P40>0),R40/P40-1,"") -> 0.022880042 | T40: =IF(AND(ISNUMBER(P40),P40>0),P40*EXP('Read me'!$B$22),"") -> 25.075724
A41: 2:25 | B41: Cork | C41: Irish Stallion Farms EBF Nursery Handicap (Birdcatcher Series) | E41: 6 | F41: Yielding | G41: 7 | H41: Pink Venom (IRE) | I41: Coen, Ben M | J41: Murtagh, J P | K41: 5 | L41: 76 | M41: 2 | N41: 8 | O41: 1 | P41: 2.9968914 | Q41: 0.33367909 | R41: 2 | S41: =IF(AND(ISNUMBER(R41),R41>1,P41>0),R41/P41-1,"") -> -0.33264182 | T41: =IF(AND(ISNUMBER(P41),P41>0),P41*EXP('Read me'!$B$22),"") -> 3.6604114
A42: 2:25 | B42: Cork | C42: Irish Stallion Farms EBF Nursery Handicap (Birdcatcher Series) | E42: 6 | F42: Yielding | G42: 7 | H42: Fine Line (IRE) | J42: Hogan, Denis Gerard | K42: 6 | L42: 79 | M42: 2 | N42: 2 | O42: 2 | P42: 5.8739402 | Q42: 0.17024348 | R42: 9.5 | S42: =IF(AND(ISNUMBER(R42),R42>1,P42>0),R42/P42-1,"") -> 0.61731302 | T42: =IF(AND(ISNUMBER(P42),P42>0),P42*EXP('Read me'!$B$22),"") -> 7.1744468
A43: 2:25 | B43: Cork | C43: Irish Stallion Farms EBF Nursery Handicap (Birdcatcher Series) | E43: 6 | F43: Yielding | G43: 7 | H43: Howlin Wolf (IRE) | I43: Ryan, J J G | J43: Davison, Jack W | K43: 4 | L43: 75 | M43: 2 | N43: 24 | O43: 3 | P43: 7.1324058 | Q43: 0.14020515 | R43: 6 | S43: =IF(AND(ISNUMBER(R43),R43>1,P43>0),R43/P43-1,"") -> -0.15876912 | T43: =IF(AND(ISNUMBER(P43),P43>0),P43*EXP('Read me'!$B$22),"") -> 8.7115401
A44: 2:25 | B44: Cork | C44: Irish Stallion Farms EBF Nursery Handicap (Birdcatcher Series) | E44: 6 | F44: Yielding | G44: 7 | H44: Captain James Cook | I44: Lordan, W M | J44: OBrien, A P | K44: 7 | L44: 63 | M44: 2 | N44: 8 | O44: 4 | P44: 8.4926245 | Q44: 0.11774923 | R44: 5.5 | S44: =IF(AND(ISNUMBER(R44),R44>1,P44>0),R44/P44-1,"") -> -0.35237923 | T44: =IF(AND(ISNUMBER(P44),P44>0),P44*EXP('Read me'!$B$22),"") -> 10.372915
A45: 2:25 | B45: Cork | C45: Irish Stallion Farms EBF Nursery Handicap (Birdcatcher Series) | E45: 6 | F45: Yielding | G45: 7 | H45: Best Love (IRE) | I45: McDonogh, D P | J45: Harty, Edward and Patrick | K45: 3 | L45: 75 | M45: 2 | N45: 27 | O45: 5 | P45: 10.211733 | Q45: 0.097926567 | R45: 12 | S45: =IF(AND(ISNUMBER(R45),R45>1,P45>0),R45/P45-1,"") -> 0.1751188 | T45: =IF(AND(ISNUMBER(P45),P45>0),P45*EXP('Read me'!$B$22),"") -> 12.472639
A46: 2:25 | B46: Cork | C46: Irish Stallion Farms EBF Nursery Handicap (Birdcatcher Series) | E46: 6 | F46: Yielding | G46: 7 | H46: Whosinterviewinwho (IRE) | I46: Coen, S | J46: Slattery, Andrew | K46: 1 | L46: 79 | M46: 2 | N46: 25 | O46: 6 | P46: 10.700093 | Q46: 0.093457129 | R46: 6 | S46: =IF(AND(ISNUMBER(R46),R46>1,P46>0),R46/P46-1,"") -> -0.43925723 | T46: =IF(AND(ISNUMBER(P46),P46>0),P46*EXP('Read me'!$B$22),"") -> 13.069123
A47: 2:25 | B47: Cork | C47: Irish Stallion Farms EBF Nursery Handicap (Birdcatcher Series) | E47: 6 | F47: Yielding | G47: 7 | H47: Cyclone Code (IRE) | I47: OConnor, Donagh | J47: Cavanagh, S | K47: 2 | L47: 77 | M47: 2 | N47: 12 | O47: 7 | P47: 21.395243 | Q47: 0.046739361 | R47: 17 | S47: =IF(AND(ISNUMBER(R47),R47>1,P47>0),R47/P47-1,"") -> -0.20543087 | T47: =IF(AND(ISNUMBER(P47),P47>0),P47*EXP('Read me'!$B$22),"") -> 26.132209
A48: 2:32 | B48: Bath | C48: MJ Church Handicap | D48: Class 5 | E48: 13 | F48: Good To Firm | G48: 13 | H48: Cosmo Brown (IRE) | I48: Edmunds, Lewis | J48: Muir, W R & Grassick, C | K48: 13 | L48: 69 | M48: 3 | N48: 34 | O48: 1 | P48: 6.0547482 | Q48: 0.16515963 | R48: 6 | S48: =IF(AND(ISNUMBER(R48),R48>1,P48>0),R48/P48-1,"") -> -0.0090421993 | T48: =IF(AND(ISNUMBER(P48),P48>0),P48*EXP('Read me'!$B$22),"") -> 7.3952862
A49: 2:32 | B49: Bath | C49: MJ Church Handicap | D49: Class 5 | E49: 13 | F49: Good To Firm | G49: 13 | H49: Zarco | I49: Cosgrave, Pat | J49: Eustace, Harry | K49: 14 | L49: 67 | M49: 3 | N49: 17 | O49: 2 | P49: 7.0423239 | Q49: 0.14199858 | R49: 6.5 | S49: =IF(AND(ISNUMBER(R49),R49>1,P49>0),R49/P49-1,"") -> -0.07700923 | T49: =IF(AND(ISNUMBER(P49),P49>0),P49*EXP('Read me'!$B$22),"") -> 8.6015139
A50: 2:32 | B50: Bath | C50: MJ Church Handicap | D50: Class 5 | E50: 13 | F50: Good To Firm | G50: 13 | H50: Moab (IRE) | I50: Marquand, Tom | J50: Knight, Miss H C | K50: 6 | L50: 62 | M50: 6 | N50: 23 | O50: 3 | P50: 7.2670325 | Q50: 0.13760775 | R50: 7 | S50: =IF(AND(ISNUMBER(R50),R50>1,P50>0),R50/P50-1,"") -> -0.036745743 | T50: =IF(AND(ISNUMBER(P50),P50>0),P50*EXP('Read me'!$B$22),"") -> 8.8759735
A51: 2:32 | B51: Bath | C51: MJ Church Handicap | D51: Class 5 | E51: 13 | F51: Good To Firm | G51: 13 | H51: Society Girl | I51: Shoemark, Kieran | J51: Walker, Ed | K51: 1 | L51: 70 | M51: 3 | N51: 40 | O51: 4 | P51: 8.0548454 | Q51: 0.12414888 | R51: 7 | S51: =IF(AND(ISNUMBER(R51),R51>1,P51>0),R51/P51-1,"") -> -0.13095787 | T51: =IF(AND(ISNUMBER(P51),P51>0),P51*EXP('Read me'!$B$22),"") -> 9.8382104
A52: 2:32 | B52: Bath | C52: MJ Church Handicap | D52: Class 5 | E52: 13 | F52: Good To Firm | G52: 13 | H52: Percy Jones | I52: Fisher, Taylor | J52: Loughnane, Daniel Mark | K52: 10 | L52: 70 | M52: 7 | N52: 16 | O52: 5 | P52: 11.515531 | Q52: 0.086839244 | R52: 10 | S52: =IF(AND(ISNUMBER(R52),R52>1,P52>0),R52/P52-1,"") -> -0.13160756 | T52: =IF(AND(ISNUMBER(P52),P52>0),P52*EXP('Read me'!$B$22),"") -> 14.065101
A53: 2:32 | B53: Bath | C53: MJ Church Handicap | D53: Class 5 | E53: 13 | F53: Good To Firm | G53: 13 | H53: Two Plus Two (IRE) | I53: Ryan, Rossa | J53: De Giles, Ed | K53: 7 | L53: 59 | M53: 6 | N53: 16 | O53: 6 | P53: 12.208096 | Q53: 0.081912857 | R53: 8 | S53: =IF(AND(ISNUMBER(R53),R53>1,P53>0),R53/P53-1,"") -> -0.34469715 | T53: =IF(AND(ISNUMBER(P53),P53>0),P53*EXP('Read me'!$B$22),"") -> 14.911002
A54: 2:32 | B54: Bath | C54: MJ Church Handicap | D54: Class 5 | E54: 13 | F54: Good To Firm | G54: 13 | H54: Belle Of Kt | I54: Wonnacott, Millie | J54: Moore, J S | K54: 8 | L54: 68 | M54: 5 | N54: 16 | O54: 7 | P54: 13.011534 | Q54: 0.07685489 | R54: 10 | S54: =IF(AND(ISNUMBER(R54),R54>1,P54>0),R54/P54-1,"") -> -0.2314511 | T54: =IF(AND(ISNUMBER(P54),P54>0),P54*EXP('Read me'!$B$22),"") -> 15.892323
A55: 2:32 | B55: Bath | C55: MJ Church Handicap | D55: Class 5 | E55: 13 | F55: Good To Firm | G55: 13 | H55: Hebridean Nomad | I55: Tucker, Charlie | J55: Balding, A M | K55: 5 | L55: 67 | M55: 5 | N55: 17 | O55: 8 | P55: 13.019335 | Q55: 0.076808841 | R55: 7 | S55: =IF(AND(ISNUMBER(R55),R55>1,P55>0),R55/P55-1,"") -> -0.46233812 | T55: =IF(AND(ISNUMBER(P55),P55>0),P55*EXP('Read me'!$B$22),"") -> 15.901851
A56: 2:32 | B56: Bath | C56: MJ Church Handicap | D56: Class 5 | E56: 13 | F56: Good To Firm | G56: 13 | H56: Beggarman | I56: Probert, David | J56: Morrison, H | K56: 9 | L56: 58 | M56: 9 | N56: 45 | O56: 9 | P56: 29.466369 | Q56: 0.033936995 | R56: 21 | S56: =IF(AND(ISNUMBER(R56),R56>1,P56>0),R56/P56-1,"") -> -0.28732312 | T56: =IF(AND(ISNUMBER(P56),P56>0),P56*EXP('Read me'!$B$22),"") -> 35.990304
A57: 2:32 | B57: Bath | C57: MJ Church Handicap | D57: Class 5 | E57: 13 | F57: Good To Firm | G57: 13 | H57: Yokkell (IRE) | I57: Marsh, Finley | J57: Wintle, A | K57: 4 | L57: 63 | M57: 7 | N57: 19 | O57: 10 | P57: 36.707664 | Q57: 0.027242268 | R57: 19 | S57: =IF(AND(ISNUMBER(R57),R57>1,P57>0),R57/P57-1,"") -> -0.48239691 | T57: =IF(AND(ISNUMBER(P57),P57>0),P57*EXP('Read me'!$B$22),"") -> 44.834842
A58: 2:32 | B58: Bath | C58: MJ Church Handicap | D58: Class 5 | E58: 13 | F58: Good To Firm | G58: 13 | H58: Calshot Spit (IRE) | I58: Bishop, Charles | J58: West, Miss Sheena | K58: 3 | L58: 60 | M58: 6 | N58: 158 | O58: 11 | P58: 55.289344 | Q58: 0.018086668 | R58: 15 | S58: =IF(AND(ISNUMBER(R58),R58>1,P58>0),R58/P58-1,"") -> -0.72869998 | T58: =IF(AND(ISNUMBER(P58),P58>0),P58*EXP('Read me'!$B$22),"") -> 67.530557
A59: 2:32 | B59: Bath | C59: MJ Church Handicap | D59: Class 5 | E59: 13 | F59: Good To Firm | G59: 13 | H59: Virtue Diligence | I59: Hornby, Rob | J59: Perrett, Mrs A J | K59: 12 | L59: 65 | M59: 3 | N59: 38 | O59: 12 | P59: 59.487503 | Q59: 0.016810253 | R59: 41 | S59: =IF(AND(ISNUMBER(R59),R59>1,P59>0),R59/P59-1,"") -> -0.31077961 | T59: =IF(AND(ISNUMBER(P59),P59>0),P59*EXP('Read me'!$B$22),"") -> 72.6582
... A62: 2:38 | B62: Ayr | C62: Weddings At Western House Hotel Maiden Stakes (GBB Race) | D62: Class 4 | E62: 6 | F62: Heavy | G62: 6 | H62: What A Girl Wants (IRE) | I62: Scott, Rowan | J62: Tinkler, N | K62: 6 | L62: 75 | M62: 2 | N62: 12 | O62: 2 | P62: 3.9448211 | Q62: 0.25349692 | R62: 3 | S62: =IF(AND(ISNUMBER(R62),R62>1,P62>0),R62/P62-1,"") -> -0.23950924 | T62: =IF(AND(ISNUMBER(P62),P62>0),P62*EXP('Read me'!$B$22),"") -> 4.8182154
A63: 2:38 | B63: Ayr | C63: Weddings At Western House Hotel Maiden Stakes (GBB Race) | D63: Class 4 | E63: 6 | F63: Heavy | G63: 6 | H63: Naval Architect (IRE) | I63: Sheehy, M P | J63: Keatley, Adrian Paul | K63: 4 | L63: 0 | M63: 2 | O63: 3 | P63: 4.4823551 | Q63: 0.223097 | R63: 2 | S63: =IF(AND(ISNUMBER(R63),R63>1,P63>0),R63/P63-1,"") -> -0.55380599 | T63: =IF(AND(ISNUMBER(P63),P63>0),P63*EXP('Read me'!$B$22),"") -> 5.4747609
A64: 2:38 | B64: Ayr | C64: Weddings At Western House Hotel Maiden Stakes (GBB Race) | D64: Class 4 | E64: 6 | F64: Heavy | G64: 6 | H64: Luna Lacy (IRE) | I64: Garritty, Jack | J64: Nicholls, Adrian | K64: 3 | L64: 0 | M64: 2 | N64: 17 | O64: 4 | P64: 5.3339501 | Q64: 0.18747832 | R64: 8 | S64: =IF(AND(ISNUMBER(R64),R64>1,P64>0),R64/P64-1,"") -> 0.49982656 | T64: =IF(AND(ISNUMBER(P64),P64>0),P64*EXP('Read me'!$B$22),"") -> 6.5149014
A65: 2:38 | B65: Ayr | C65: Weddings At Western House Hotel Maiden Stakes (GBB Race) | D65: Class 4 | E65: 6 | F65: Heavy | G65: 6 | H65: Pirates Whisper (IRE) | I65: Elliott, Rhys | J65: Smith, R Michael | K65: 5 | L65: 0 | M65: 2 | N65: 17 | O65: 5 | P65: 135.75723 | Q65: 0.0073660902 | R65: 41 | S65: =IF(AND(ISNUMBER(R65),R65>1,P65>0),R65/P65-1,"") -> -0.6979903 | T65: =IF(AND(ISNUMBER(P65),P65>0),P65*EXP('Read me'!$B$22),"") -> 165.81425
A66: 2:38 | B66: Ayr | C66: Weddings At Western House Hotel Maiden Stakes (GBB Race) | D66: Class 4 | E66: 6 | F66: Heavy | G66: 6 | H66: Sneakin Pete | I66: Mullen, Andrew | J66: Smith, R Michael | K66: 1 | L66: 0 | M66: 2 | N66: 27 | O66: 6 | P66: 209.12641 | Q66: 0.0047817969 | R66: 101 | S66: =IF(AND(ISNUMBER(R66),R66>1,P66>0),R66/P66-1,"") -> -0.51703851 | T66: =IF(AND(ISNUMBER(P66),P66>0),P66*EXP('Read me'!$B$22),"") -> 255.42757
A67: 2:45 | B67: Sedgefield | C67: Roxyfet Sports Lounge For Private Hire Juvenile Maiden Hurdle (GBB Race) | D67: Class 4 | E67: 16.5 | F67: Good | G67: 7 | H67: Steel Raven (IRE) | I67: Hughes, Brian | J67: Keatley, Adrian Paul | K67: 4 | L67: 0 | M67: 3 | N67: 12 | O67: 1 | P67: 1.3730685 | Q67: 0.72829576 | R67: 1.6153846 | S67: =IF(AND(ISNUMBER(R67),R67>1,P67>0),R67/P67-1,"") -> 0.17647777 | T67: =IF(AND(ISNUMBER(P67),P67>0),P67*EXP('Read me'!$B$22),"") -> 1.6770697
A68: 2:45 | B68: Sedgefield | C68: Roxyfet Sports Lounge For Private Hire Juvenile Maiden Hurdle (GBB Race) | D68: Class 4 | E68: 16.5 | F68: Good | G68: 7 | H68: Jerseygeordie | I68: OBrien, P V | J68: Derham, Harry | K68: 2 | L68: 0 | M68: 3 | N68: 22 | O68: 2 | P68: 9.9272015 | Q68: 0.10073332 | R68: 4.3333333 | S68: =IF(AND(ISNUMBER(R68),R68>1,P68>0),R68/P68-1,"") -> -0.56348893 | T68: =IF(AND(ISNUMBER(P68),P68>0),P68*EXP('Read me'!$B$22),"") -> 12.125111
A69: 2:45 | B69: Sedgefield | C69: Roxyfet Sports Lounge For Private Hire Juvenile Maiden Hurdle (GBB Race) | D69: Class 4 | E69: 16.5 | F69: Good | G69: 7 | H69: Watcha Snoop (IRE) | I69: Mania, Ryan | J69: Nicol, Adam | K69: 6 | L69: 0 | M69: 3 | N69: 29 | O69: 3 | P69: 11.084038 | Q69: 0.090219829 | R69: 10 | S69: =IF(AND(ISNUMBER(R69),R69>1,P69>0),R69/P69-1,"") -> -0.097801707 | T69: =IF(AND(ISNUMBER(P69),P69>0),P69*EXP('Read me'!$B$22),"") -> 13.538074
A70: 2:45 | B70: Sedgefield | C70: Roxyfet Sports Lounge For Private Hire Juvenile Maiden Hurdle (GBB Race) | D70: Class 4 | E70: 16.5 | F70: Good | G70: 7 | H70: Time Twister | I70: Hamilton, Jamie | J70: Easterby, M W | K70: 5 | L70: 0 | M70: 3 | N70: 15 | O70: 4 | P70: 31.209913 | Q70: 0.032041102 | R70: 15 | S70: =IF(AND(ISNUMBER(R70),R70>1,P70>0),R70/P70-1,"") -> -0.51938347 | T70: =IF(AND(ISNUMBER(P70),P70>0),P70*EXP('Read me'!$B$22),"") -> 38.119873
A71: 2:45 | B71: Sedgefield | C71: Roxyfet Sports Lounge For Private Hire Juvenile Maiden Hurdle (GBB Race) | D71: Class 4 | E71: 16.5 | F71: Good | G71: 7 | H71: Al Khawaaneej (IRE) | I71: Gillard, Theo | J71: McCain Jnr, D | K71: 1 | L71: 0 | M71: 3 | N71: 330 | O71: 5 | P71: 31.440401 | Q71: 0.03180621 | R71: 15 | S71: =IF(AND(ISNUMBER(R71),R71>1,P71>0),R71/P71-1,"") -> -0.52290685 | T71: =IF(AND(ISNUMBER(P71),P71>0),P71*EXP('Read me'!$B$22),"") -> 38.401393
A72: 2:45 | B72: Sedgefield | C72: Roxyfet Sports Lounge For Private Hire Juvenile Maiden Hurdle (GBB Race) | D72: Class 4 | E72: 16.5 | F72: Good | G72: 7 | H72: Royal Baroness | I72: Smith, Ben | J72: Smith, R Michael | K72: 7 | L72: 0 | M72: 3 | N72: 116 | O72: 6 | P72: 105.29826 | Q72: 0.0094968327 | R72: 101 | S72: =IF(AND(ISNUMBER(R72),R72>1,P72>0),R72/P72-1,"") -> -0.040819898 | T72: =IF(AND(ISNUMBER(P72),P72>0),P72*EXP('Read me'!$B$22),"") -> 128.61159
A73: 2:45 | B73: Sedgefield | C73: Roxyfet Sports Lounge For Private Hire Juvenile Maiden Hurdle (GBB Race) | D73: Class 4 | E73: 16.5 | F73: Good | G73: 7 | H73: Keep Under Wraps | I73: Tudor, Jack | J73: Greenall, O / Guerriero, J | K73: 3 | L73: 0 | M73: 3 | N73: 65 | O73: 7 | P73: 135.00855 | Q73: 0.0074069385 | R73: 26 | S73: =IF(AND(ISNUMBER(R73),R73>1,P73>0),R73/P73-1,"") -> -0.8074196 | T73: =IF(AND(ISNUMBER(P73),P73>0),P73*EXP('Read me'!$B$22),"") -> 164.89981
A74: 2:55 | B74: Cork | C74: Irish Stallion Farms EBF Fillies Handicap | E74: 6 | F74: Yielding | G74: 9 | H74: By The Lake (IRE) | I74: Keane, C T | J74: McCormack, Derek | K74: 6 | L74: 79 | M74: 3 | N74: 33 | O74: 1 | P74: 4.7378235 | Q74: 0.21106738 | R74: 7.5 | S74: =IF(AND(ISNUMBER(R74),R74>1,P74>0),R74/P74-1,"") -> 0.58300535 | T74: =IF(AND(ISNUMBER(P74),P74>0),P74*EXP('Read me'!$B$22),"") -> 5.7867907
A75: 2:55 | B75: Cork | C75: Irish Stallion Farms EBF Fillies Handicap | E75: 6 | F75: Yielding | G75: 9 | H75: Forza Magico | I75: Whelan, R P | J75: Feane, John James | K75: 5 | L75: 70 | M75: 3 | N75: 25 | O75: 2 | P75: 6.5293068 | Q75: 0.15315562 | R75: 5 | S75: =IF(AND(ISNUMBER(R75),R75>1,P75>0),R75/P75-1,"") -> -0.23422192 | T75: =IF(AND(ISNUMBER(P75),P75>0),P75*EXP('Read me'!$B$22),"") -> 7.9749133
A76: 2:55 | B76: Cork | C76: Irish Stallion Farms EBF Fillies Handicap | E76: 6 | F76: Yielding | G76: 9 | H76: Motta Alta (IRE) | I76: McCullagh, Scott | J76: Harrington, Mrs John | K76: 9 | L76: 77 | M76: 3 | N76: 14 | O76: 3 | P76: 8.7498092 | Q76: 0.11428821 | R76: 5 | S76: =IF(AND(ISNUMBER(R76),R76>1,P76>0),R76/P76-1,"") -> -0.42855897 | T76: =IF(AND(ISNUMBER(P76),P76>0),P76*EXP('Read me'!$B$22),"") -> 10.687041
A77: 2:55 | B77: Cork | C77: Irish Stallion Farms EBF Fillies Handicap | E77: 6 | F77: Yielding | G77: 9 | H77: Baiana (GER) | I77: Sheridan, J M | J77: OBrien, Joseph Patrick | K77: 2 | L77: 71 | M77: 3 | N77: 124 | O77: 4 | P77: 9.3177277 | Q77: 0.1073223 | R77: 11 | S77: =IF(AND(ISNUMBER(R77),R77>1,P77>0),R77/P77-1,"") -> 0.18054534 | T77: =IF(AND(ISNUMBER(P77),P77>0),P77*EXP('Read me'!$B$22),"") -> 11.380698
A78: 2:55 | B78: Cork | C78: Irish Stallion Farms EBF Fillies Handicap | E78: 6 | F78: Yielding | G78: 9 | H78: Staysound Susie (IRE) | I78: Dalton, J S | J78: Slattery, Andrew | K78: 3 | L78: 84 | M78: 5 | N78: 16 | O78: 5 | P78: 9.7754413 | Q78: 0.10229717 | R78: 4.5 | S78: =IF(AND(ISNUMBER(R78),R78>1,P78>0),R78/P78-1,"") -> -0.53966272 | T78: =IF(AND(ISNUMBER(P78),P78>0),P78*EXP('Read me'!$B$22),"") -> 11.939751
A79: 2:55 | B79: Cork | C79: Irish Stallion Farms EBF Fillies Handicap | E79: 6 | F79: Yielding | G79: 9 | H79: Rosato (IRE) | I79: Mulligan, R M | J79: Weld, Charles | K79: 1 | L79: 58 | M79: 5 | N79: 24 | O79: 6 | P79: 10.038118 | Q79: 0.099620266 | R79: 7.5 | S79: =IF(AND(ISNUMBER(R79),R79>1,P79>0),R79/P79-1,"") -> -0.25284801 | T79: =IF(AND(ISNUMBER(P79),P79>0),P79*EXP('Read me'!$B$22),"") -> 12.260585
A80: 2:55 | B80: Cork | C80: Irish Stallion Farms EBF Fillies Handicap | E80: 6 | F80: Yielding | G80: 9 | H80: Flash Of Fire | I80: Coen, Ben M | J80: Murtagh, J P | K80: 8 | L80: 79 | M80: 3 | N80: 14 | O80: 7 | P80: 11.929759 | Q80: 0.083823991 | R80: 8.5 | S80: =IF(AND(ISNUMBER(R80),R80>1,P80>0),R80/P80-1,"") -> -0.28749607 | T80: =IF(AND(ISNUMBER(P80),P80>0),P80*EXP('Read me'!$B$22),"") -> 14.57104
A81: 2:55 | B81: Cork | C81: Irish Stallion Farms EBF Fillies Handicap | E81: 6 | F81: Yielding | G81: 9 | H81: Saint Agatha (IRE) | I81: Heffernan, J A | J81: Stack, J A | K81: 7 | L81: 68 | M81: 3 | N81: 30 | O81: 8 | P81: 13.301551 | Q81: 0.075179205 | R81: 15 | S81: =IF(AND(ISNUMBER(R81),R81>1,P81>0),R81/P81-1,"") -> 0.12768808 | T81: =IF(AND(ISNUMBER(P81),P81>0),P81*EXP('Read me'!$B$22),"") -> 16.24655
A82: 2:55 | B82: Cork | C82: Irish Stallion Farms EBF Fillies Handicap | E82: 6 | F82: Yielding | G82: 9 | H82: My Cubby Bear (IRE) | I82: Lee, W J | J82: Bromhead, Henry De | K82: 4 | L82: 70 | M82: 3 | N82: 319 | O82: 9 | P82: 18.780803 | Q82: 0.053245859 | R82: 19 | S82: =IF(AND(ISNUMBER(R82),R82>1,P82>0),R82/P82-1,"") -> 0.011671318 | T82: =IF(AND(ISNUMBER(P82),P82>0),P82*EXP('Read me'!$B$22),"") -> 22.938925
A83: 3:02 | B83: Bath | C83: AEL Solutions Handicap | D83: Class 6 | E83: 8 | F83: Good To Firm | G83: 12 | H83: Buckland Belle | I83: Marquand, Tom | J83: Sangster, Ollie | K83: 13 | L83: 63 | M83: 3 | N83: 7 | O83: 1 | P83: 3.2266287 | Q83: 0.309921 | R83: 2.875 | S83: =IF(AND(ISNUMBER(R83),R83>1,P83>0),R83/P83-1,"") -> -0.10897712 | T83: =IF(AND(ISNUMBER(P83),P83>0),P83*EXP('Read me'!$B$22),"") -> 3.9410132
A84: 3:02 | B84: Bath | C84: AEL Solutions Handicap | D84: Class 6 | E84: 8 | F84: Good To Firm | G84: 12 | H84: Rating (IRE) | I84: Ryan, Rossa | J84: Harris, Miss G | K84: 2 | L84: 65 | M84: 5 | N84: 16 | O84: 2 | P84: 6.9381041 | Q84: 0.14413159 | R84: 5.5 | S84: =IF(AND(ISNUMBER(R84),R84>1,P84>0),R84/P84-1,"") -> -0.20727623 | T84: =IF(AND(ISNUMBER(P84),P84>0),P84*EXP('Read me'!$B$22),"") -> 8.4742195
A85: 3:02 | B85: Bath | C85: AEL Solutions Handicap | D85: Class 6 | E85: 8 | F85: Good To Firm | G85: 12 | H85: Amarachi (IRE) | I85: Mitchell, Jack | J85: Parr, Joseph | K85: 6 | L85: 62 | M85: 4 | N85: 14 | O85: 3 | P85: 7.9966822 | Q85: 0.12505186 | R85: 5 | S85: =IF(AND(ISNUMBER(R85),R85>1,P85>0),R85/P85-1,"") -> -0.37474069 | T85: =IF(AND(ISNUMBER(P85),P85>0),P85*EXP('Read me'!$B$22),"") -> 9.7671697
A86: 3:02 | B86: Bath | C86: AEL Solutions Handicap | D86: Class 6 | E86: 8 | F86: Good To Firm | G86: 12 | H86: Chilly Breeze | I86: Sousa, Silvestre De | J86: Williams, Ian | K86: 9 | L86: 65 | M86: 4 | N86: 18 | O86: 4 | P86: 10.551711 | Q86: 0.094771362 | R86: 7.5 | S86: =IF(AND(ISNUMBER(R86),R86>1,P86>0),R86/P86-1,"") -> -0.28921478 | T86: =IF(AND(ISNUMBER(P86),P86>0),P86*EXP('Read me'!$B$22),"") -> 12.887889
A87: 3:02 | B87: Bath | C87: AEL Solutions Handicap | D87: Class 6 | E87: 8 | F87: Good To Firm | G87: 12 | H87: Fizzy Bear (IRE) | I87: Dace, Jack | J87: Baker, George | K87: 10 | L87: 58 | M87: 3 | N87: 19 | O87: 5 | P87: 11.193064 | Q87: 0.089341039 | R87: 10 | S87: =IF(AND(ISNUMBER(R87),R87>1,P87>0),R87/P87-1,"") -> -0.10658961 | T87: =IF(AND(ISNUMBER(P87),P87>0),P87*EXP('Read me'!$B$22),"") -> 13.67124
A88: 3:02 | B88: Bath | C88: AEL Solutions Handicap | D88: Class 6 | E88: 8 | F88: Good To Firm | G88: 12 | H88: Dappled Light | I88: Marsh, Finley | J88: Wintle, A | K88: 12 | L88: 64 | M88: 6 | N88: 16 | O88: 6 | P88: 18.833281 | Q88: 0.053097492 | R88: 17 | S88: =IF(AND(ISNUMBER(R88),R88>1,P88>0),R88/P88-1,"") -> -0.097342642 | T88: =IF(AND(ISNUMBER(P88),P88>0),P88*EXP('Read me'!$B$22),"") -> 23.003022
A89: 3:02 | B89: Bath | C89: AEL Solutions Handicap | D89: Class 6 | E89: 8 | F89: Good To Firm | G89: 12 | H89: Thiscouldbefun (IRE) | I89: Fisher, Taylor | J89: Moore, J S | K89: 3 | L89: 65 | M89: 4 | N89: 26 | O89: 7 | P89: 26.350655 | Q89: 0.037949721 | R89: 21 | S89: =IF(AND(ISNUMBER(R89),R89>1,P89>0),R89/P89-1,"") -> -0.20305587 | T89: =IF(AND(ISNUMBER(P89),P89>0),P89*EXP('Read me'!$B$22),"") -> 32.184763
A90: 3:02 | B90: Bath | C90: AEL Solutions Handicap | D90: Class 6 | E90: 8 | F90: Good To Firm | G90: 12 | H90: Denbys Dream | I90: Currie, Nicola | J90: Pike, Charlie | K90: 5 | L90: 59 | M90: 3 | N90: 16 | O90: 8 | P90: 28.238422 | Q90: 0.035412744 | R90: 19 | S90: =IF(AND(ISNUMBER(R90),R90>1,P90>0),R90/P90-1,"") -> -0.32715787 | T90: =IF(AND(ISNUMBER(P90),P90>0),P90*EXP('Read me'!$B$22),"") -> 34.490487
A91: 3:02 | B91: Bath | C91: AEL Solutions Handicap | D91: Class 6 | E91: 8 | F91: Good To Firm | G91: 12 | H91: Havana Club | I91: Murphy, D J | J91: Wintle, A | K91: 8 | L91: 56 | M91: 4 | N91: 27 | O91: 9 | P91: 29.16783 | Q91: 0.034284347 | R91: 26 | S91: =IF(AND(ISNUMBER(R91),R91>1,P91>0),R91/P91-1,"") -> -0.10860697 | T91: =IF(AND(ISNUMBER(P91),P91>0),P91*EXP('Read me'!$B$22),"") -> 35.625668
A92: 3:02 | B92: Bath | C92: AEL Solutions Handicap | D92: Class 6 | E92: 8 | F92: Good To Firm | G92: 12 | H92: Blue Hero (CAN) | I92: Leavy, Joe | J92: Wintle, A | K92: 14 | L92: 59 | M92: 8 | N92: 16 | O92: 10 | P92: 31.946278 | Q92: 0.031302551 | R92: 13 | S92: =IF(AND(ISNUMBER(R92),R92>1,P92>0),R92/P92-1,"") -> -0.59306684 | T92: =IF(AND(ISNUMBER(P92),P92>0),P92*EXP('Read me'!$B$22),"") -> 39.019272
A93: 3:02 | B93: Bath | C93: AEL Solutions Handicap | D93: Class 6 | E93: 8 | F93: Good To Firm | G93: 12 | H93: Man From Havana | I93: Ffrench Davis, Ben | J93: Davis, D J S Ffrench | K93: 4 | L93: 62 | M93: 4 | N93: 111 | O93: 11 | P93: 42.853041 | Q93: 0.023335567 | R93: 51 | S93: =IF(AND(ISNUMBER(R93),R93>1,P93>0),R93/P93-1,"") -> 0.19011392 | T93: =IF(AND(ISNUMBER(P93),P93>0),P93*EXP('Read me'!$B$22),"") -> 52.340822
A94: 3:02 | B94: Bath | C94: AEL Solutions Handicap | D94: Class 6 | E94: 8 | F94: Good To Firm | G94: 12 | H94: Afta Party (IRE) | I94: Tucker, Charlie | J94: Turner, Kathy | K94: 11 | L94: 59 | M94: 8 | N94: 396 | O94: 12 | P94: 46.727399 | Q94: 0.02140072 | R94: 67 | S94: =IF(AND(ISNUMBER(R94),R94>1,P94>0),R94/P94-1,"") -> 0.43384827 | T94: =IF(AND(ISNUMBER(P94),P94>0),P94*EXP('Read me'!$B$22),"") -> 57.072974
... A107: 3:15 | B107: Sedgefield | C107: Paxtons No1 CaseIH Dealer Handicap Chase (GBB Race) | D107: Class 4 | E107: 21.5 | F107: Good | G107: 4 | H107: Four Decades | I107: Andrews, Jack | J107: Ellis, T | K107: 4 | L107: 89 | M107: 5 | N107: 25 | O107: 4 | P107: 10.850962 | Q107: 0.092157725 | R107: 8 | S107: =IF(AND(ISNUMBER(R107),R107>1,P107>0),R107/P107-1,"") -> -0.2627382 | T107: =IF(AND(ISNUMBER(P107),P107>0),P107*EXP('Read me'!$B$22),"") -> 13.253395
A108: 3:25 | B108: Cork | C108: WTW Willis Handicap (0-60) | E108: 6 | F108: Yielding | G108: 19 | H108: Simmering Seas (IRE) | I108: Coen, Ben M | J108: Murphy, Daniel | K108: 14 | L108: 58 | M108: 3 | N108: 24 | O108: 1 | P108: 7.7836966 | Q108: 0.12847366 | R108: 7.5 | S108: =IF(AND(ISNUMBER(R108),R108>1,P108>0),R108/P108-1,"") -> -0.036447547 | T108: =IF(AND(ISNUMBER(P108),P108>0),P108*EXP('Read me'!$B$22),"") -> 9.5070286
A109: 3:25 | B109: Cork | C109: WTW Willis Handicap (0-60) | E109: 6 | F109: Yielding | G109: 19 | H109: El Fontenaro (IRE) | I109: Whelan, R P | J109: Fahey, Jarlath P | K109: 2 | L109: 57 | M109: 4 | N109: 67 | O109: 2 | P109: 9.1305864 | Q109: 0.10952199 | R109: 5.5 | S109: =IF(AND(ISNUMBER(R109),R109>1,P109>0),R109/P109-1,"") -> -0.39762905 | T109: =IF(AND(ISNUMBER(P109),P109>0),P109*EXP('Read me'!$B$22),"") -> 11.152123
A110: 3:25 | B110: Cork | C110: WTW Willis Handicap (0-60) | E110: 6 | F110: Yielding | G110: 19 | H110: Carrigans Grove (IRE) | I110: Donaghue-Leahy, R | J110: Flynn, Patrick J | K110: 6 | L110: 56 | M110: 5 | N110: 73 | O110: 3 | P110: 10.003928 | Q110: 0.099960735 | R110: 11 | S110: =IF(AND(ISNUMBER(R110),R110>1,P110>0),R110/P110-1,"") -> 0.09956808 | T110: =IF(AND(ISNUMBER(P110),P110>0),P110*EXP('Read me'!$B$22),"") -> 12.218825
A111: 3:25 | B111: Cork | C111: WTW Willis Handicap (0-60) | E111: 6 | F111: Yielding | G111: 19 | H111: Brains (IRE) | I111: Coen, S | J111: Donohoe, R | K111: 11 | L111: 54 | M111: 10 | N111: 7 | O111: 4 | P111: 10.157291 | Q111: 0.098451447 | R111: 9 | S111: =IF(AND(ISNUMBER(R111),R111>1,P111>0),R111/P111-1,"") -> -0.11393698 | T111: =IF(AND(ISNUMBER(P111),P111>0),P111*EXP('Read me'!$B$22),"") -> 12.406143
A112: 3:25 | B112: Cork | C112: WTW Willis Handicap (0-60) | E112: 6 | F112: Yielding | G112: 19 | H112: Run Forrest Run (IRE) | I112: Lordan, W M | J112: Hourigan, Laura | K112: 18 | L112: 32 | M112: 8 | N112: 90 | O112: 5 | P112: 13.382915 | Q112: 0.074722139 | R112: 26 | S112: =IF(AND(ISNUMBER(R112),R112>1,P112>0),R112/P112-1,"") -> 0.94277561 | T112: =IF(AND(ISNUMBER(P112),P112>0),P112*EXP('Read me'!$B$22),"") -> 16.345929
A113: 3:25 | B113: Cork | C113: WTW Willis Handicap (0-60) | E113: 6 | F113: Yielding | G113: 19 | H113: Verified (IRE) | I113: Carroll, G F | J113: Keane, Gerard | K113: 7 | L113: 52 | M113: 5 | N113: 80 | O113: 6 | P113: 13.689826 | Q113: 0.073046947 | R113: 5 | S113: =IF(AND(ISNUMBER(R113),R113>1,P113>0),R113/P113-1,"") -> -0.63476527 | T113: =IF(AND(ISNUMBER(P113),P113>0),P113*EXP('Read me'!$B$22),"") -> 16.720791
A114: 3:25 | B114: Cork | C114: WTW Willis Handicap (0-60) | E114: 6 | F114: Yielding | G114: 19 | H114: Sand Art (IRE) | I114: Pietropaolo, J | J114: Coleman, Kevin | K114: 17 | L114: 42 | M114: 3 | N114: 7 | O114: 7 | P114: 13.701448 | Q114: 0.072984986 | R114: 7.5 | S114: =IF(AND(ISNUMBER(R114),R114>1,P114>0),R114/P114-1,"") -> -0.4526126 | T114: =IF(AND(ISNUMBER(P114),P114>0),P114*EXP('Read me'!$B$22),"") -> 16.734986
A115: 3:25 | B115: Cork | C115: WTW Willis Handicap (0-60) | E115: 6 | F115: Yielding | G115: 19 | H115: Sceitimini (IRE) | I115: Sheridan, J M | J115: Sweeney, Rodger | K115: 15 | L115: 45 | M115: 3 | N115: 7 | O115: 8 | P115: 17.499616 | Q115: 0.057144112 | R115: 9.5 | S115: =IF(AND(ISNUMBER(R115),R115>1,P115>0),R115/P115-1,"") -> -0.45713094 | T115: =IF(AND(ISNUMBER(P115),P115>0),P115*EXP('Read me'!$B$22),"") -> 21.374079
A116: 3:25 | B116: Cork | C116: WTW Willis Handicap (0-60) | E116: 6 | F116: Yielding | G116: 19 | H116: Akashaa (IRE) | I116: McNally, Kian | J116: Lupini, Miss Natalia | K116: 20 | L116: 43 | M116: 4 | N116: 19 | O116: 9 | P116: 21.428664 | Q116: 0.046666465 | R116: 11 | S116: =IF(AND(ISNUMBER(R116),R116>1,P116>0),R116/P116-1,"") -> -0.48666888 | T116: =IF(AND(ISNUMBER(P116),P116>0),P116*EXP('Read me'!$B$22),"") -> 26.173029
A117: 3:25 | B117: Cork | C117: WTW Willis Handicap (0-60) | E117: 6 | F117: Yielding | G117: 19 | H117: Bright Image (IRE) | I117: Cleary, R P | J117: Donoghue, C P | K117: 10 | L117: 40 | M117: 7 | N117: 102 | O117: 10 | P117: 24.722712 | Q117: 0.040448637 | R117: 15 | S117: =IF(AND(ISNUMBER(R117),R117>1,P117>0),R117/P117-1,"") -> -0.39327044 | T117: =IF(AND(ISNUMBER(P117),P117>0),P117*EXP('Read me'!$B$22),"") -> 30.196388
A118: 3:25 | B118: Cork | C118: WTW Willis Handicap (0-60) | E118: 6 | F118: Yielding | G118: 19 | H118: Jordan Breeze (IRE) | I118: Persse, A C | J118: Flynn, Patrick J | K118: 16 | L118: 57 | M118: 4 | N118: 87 | O118: 11 | P118: 24.858036 | Q118: 0.040228439 | R118: 13 | S118: =IF(AND(ISNUMBER(R118),R118>1,P118>0),R118/P118-1,"") -> -0.47703029 | T118: =IF(AND(ISNUMBER(P118),P118>0),P118*EXP('Read me'!$B$22),"") -> 30.361674
A119: 3:25 | B119: Cork | C119: WTW Willis Handicap (0-60) | E119: 6 | F119: Yielding | G119: 19 | H119: Linger For Longer (IRE) | I119: Lee, W J | J119: Leahy, Augustine | K119: 1 | L119: 43 | M119: 7 | N119: 20 | O119: 12 | P119: 26.19322 | Q119: 0.038177818 | R119: 26 | S119: =IF(AND(ISNUMBER(R119),R119>1,P119>0),R119/P119-1,"") -> -0.0073767272 | T119: =IF(AND(ISNUMBER(P119),P119>0),P119*EXP('Read me'!$B$22),"") -> 31.992471
... A126: 3:25 | B126: Cork | C126: WTW Willis Handicap (0-60) | E126: 6 | F126: Yielding | G126: 19 | H126: Three Sixteen (IRE) | I126: McAteer, L T | J126: McIntyre, Alan | K126: 12 | L126: 56 | M126: 4 | N126: 114 | O126: 19 | P126: 175.02812 | Q126: 0.0057133677 | R126: 126 | S126: =IF(AND(ISNUMBER(R126),R126>1,P126>0),R126/P126-1,"") -> -0.28011567 | T126: =IF(AND(ISNUMBER(P126),P126>0),P126*EXP('Read me'!$B$22),"") -> 213.77983
...

Sheet Cork
A1: Time | B1: Course | C1: Race | D1: Class | E1: Furlongs | F1: Going | G1: Runners | H1: Horse | I1: Jockey | J1: Trainer | K1: Draw | L1: OR | M1: Age | N1: Days since run | O1: Model rank | P1: Predicted BSP | Q1: Win probability | R1: Card odds (HRB) | S1: Card odds vs model | T1: Rule: back at Betfair ≥
A2: 1:55 | B2: Cork | C2: Irish Stallion Farms EBF Maiden | E2: 5 | F2: Yielding | G2: 13 | H2: Bold Commander (IRE) | I2: Lordan, W M | J2: OBrien, A P | K2: 4 | L2: 78 | M2: 2 | N2: 12 | O2: 1 | P2: 4.6201822 | Q2: 0.21644168 | R2: 2.5 | S2: =IF(AND(ISNUMBER(R2),R2>1,P2>0),R2/P2-1,"") -> -0.45889579 | T2: =IF(AND(ISNUMBER(P2),P2>0),P2*EXP('Read me'!$B$22),"") -> 5.6431032
A3: 1:55 | B3: Cork | C3: Irish Stallion Farms EBF Maiden | E3: 5 | F3: Yielding | G3: 13 | H3: Sonny Hayes (IRE) | I3: OConnor, Donagh | J3: Aguiar, Robson | K3: 7 | L3: 0 | M3: 2 | O3: 2 | P3: 5.1099387 | Q3: 0.19569706 | R3: 6 | S3: =IF(AND(ISNUMBER(R3),R3>1,P3>0),R3/P3-1,"") -> 0.17418239 | T3: =IF(AND(ISNUMBER(P3),P3>0),P3*EXP('Read me'!$B$22),"") -> 6.2412932
A4: 1:55 | B4: Cork | C4: Irish Stallion Farms EBF Maiden | E4: 5 | F4: Yielding | G4: 13 | H4: El Domino | I4: Slattery, A J | J4: Slattery, Andrew | K4: 9 | L4: 75 | M4: 2 | N4: 20 | O4: 3 | P4: 6.8919554 | Q4: 0.1450967 | R4: 5.5 | S4: =IF(AND(ISNUMBER(R4),R4>1,P4>0),R4/P4-1,"") -> -0.20196814 | T4: =IF(AND(ISNUMBER(P4),P4>0),P4*EXP('Read me'!$B$22),"") -> 8.4178533
A5: 1:55 | B5: Cork | C5: Irish Stallion Farms EBF Maiden | E5: 5 | F5: Yielding | G5: 13 | H5: Alfresco (IRE) | I5: Ryan, Gavin | J5: Obrien, Donnacha | K5: 5 | L5: 0 | M5: 2 | N5: 12 | O5: 4 | P5: 8.3317733 | Q5: 0.12002247 | R5: 7 | S5: =IF(AND(ISNUMBER(R5),R5>1,P5>0),R5/P5-1,"") -> -0.15984272 | T5: =IF(AND(ISNUMBER(P5),P5>0),P5*EXP('Read me'!$B$22),"") -> 10.176451
A6: 1:55 | B6: Cork | C6: Irish Stallion Farms EBF Maiden | E6: 5 | F6: Yielding | G6: 13 | H6: Anthony Of Lisbon | I6: Frain, Freya | J6: OBrien, A P | K6: 12 | L6: 0 | M6: 2 | N6: 109 | O6: 5 | P6: 9.9724355 | Q6: 0.10027641 | R6: 7 | S6: =IF(AND(ISNUMBER(R6),R6>1,P6>0),R6/P6-1,"") -> -0.29806515 | T6: =IF(AND(ISNUMBER(P6),P6>0),P6*EXP('Read me'!$B$22),"") -> 12.18036
A7: 1:55 | B7: Cork | C7: Irish Stallion Farms EBF Maiden | E7: 5 | F7: Yielding | G7: 13 | H7: Sapphire Sun (IRE) | J7: Murtagh, J P | K7: 3 | L7: 0 | M7: 2 | N7: 16 | O7: 6 | P7: 10.852561 | Q7: 0.092144149 | R7: 4 | S7: =IF(AND(ISNUMBER(R7),R7>1,P7>0),R7/P7-1,"") -> -0.6314234 | T7: =IF(AND(ISNUMBER(P7),P7>0),P7*EXP('Read me'!$B$22),"") -> 13.255348
A8: 1:55 | B8: Cork | C8: Irish Stallion Farms EBF Maiden | E8: 5 | F8: Yielding | G8: 13 | H8: Lion Of Fortune (IRE) | I8: Whelan, R P | J8: Cotter, Kieran P | K8: 8 | L8: 0 | M8: 2 | N8: 44 | O8: 7 | P8: 16.182722 | Q8: 0.061794301 | R8: 12 | S8: =IF(AND(ISNUMBER(R8),R8>1,P8>0),R8/P8-1,"") -> -0.25846838 | T8: =IF(AND(ISNUMBER(P8),P8>0),P8*EXP('Read me'!$B$22),"") -> 19.765621
A9: 1:55 | B9: Cork | C9: Irish Stallion Farms EBF Maiden | E9: 5 | F9: Yielding | G9: 13 | H9: Spirit Of The Nite (IRE) | I9: Ryan, J J G | J9: McCourt, T G | K9: 11 | L9: 0 | M9: 2 | N9: 11 | O9: 8 | P9: 30.375508 | Q9: 0.032921261 | R9: 11 | S9: =IF(AND(ISNUMBER(R9),R9>1,P9>0),R9/P9-1,"") -> -0.63786613 | T9: =IF(AND(ISNUMBER(P9),P9>0),P9*EXP('Read me'!$B$22),"") -> 37.100729
A10: 1:55 | B10: Cork | C10: Irish Stallion Farms EBF Maiden | E10: 5 | F10: Yielding | G10: 13 | H10: Sorrento Sunset (IRE) | I10: Powell, J A | J10: McLoughlin, Daniel | K10: 6 | L10: 0 | M10: 2 | N10: 25 | O10: 9 | P10: 58.116284 | Q10: 0.017206881 | R10: 51 | S10: =IF(AND(ISNUMBER(R10),R10>1,P10>0),R10/P10-1,"") -> -0.12244906 | T10: =IF(AND(ISNUMBER(P10),P10>0),P10*EXP('Read me'!$B$22),"") -> 70.98339
A11: 1:55 | B11: Cork | C11: Irish Stallion Farms EBF Maiden | E11: 5 | F11: Yielding | G11: 13 | H11: Lolapipa (IRE) | I11: Persse, A C | J11: Cahill, Mark | K11: 1 | L11: 0 | M11: 2 | O11: 10 | P11: 99.062393 | Q11: 0.010094648 | R11: 151 | S11: =IF(AND(ISNUMBER(R11),R11>1,P11>0),R11/P11-1,"") -> 0.52429187 | T11: =IF(AND(ISNUMBER(P11),P11>0),P11*EXP('Read me'!$B$22),"") -> 120.99508
A12: 1:55 | B12: Cork | C12: Irish Stallion Farms EBF Maiden | E12: 5 | F12: Yielding | G12: 13 | H12: Habu (IRE) | I12: Tynan, Orla | J12: Tynan, M J | K12: 2 | L12: 0 | M12: 2 | N12: 12 | O12: 11 | P12: 334.04285 | Q12: 0.0029936279 | R12: 81 | S12: =IF(AND(ISNUMBER(R12),R12>1,P12>0),R12/P12-1,"") -> -0.75751614 | T12: =IF(AND(ISNUMBER(P12),P12>0),P12*EXP('Read me'!$B$22),"") -> 408.00086
A13: 1:55 | B13: Cork | C13: Irish Stallion Farms EBF Maiden | E13: 5 | F13: Yielding | G13: 13 | H13: Imply (IRE) | I13: Mulligan, R M | J13: Weld, Charles | K13: 10 | L13: 0 | M13: 2 | N13: 12 | O13: 12 | P13: 361.67997 | Q13: 0.0027648752 | R13: 151 | S13: =IF(AND(ISNUMBER(R13),R13>1,P13>0),R13/P13-1,"") -> -0.58250384 | T13: =IF(AND(ISNUMBER(P13),P13>0),P13*EXP('Read me'!$B$22),"") -> 441.75692
A14: 1:55 | B14: Cork | C14: Irish Stallion Farms EBF Maiden | E14: 5 | F14: Yielding | G14: 13 | H14: Bettercalltheboss (IRE) | I14: Cleary, R P | J14: Lynch, Miss Jennifer Anne | K14: 13 | L14: 0 | M14: 2 | N14: 69 | O14: 13 | P14: 392.78351 | Q14: 0.0025459318 | R14: 151 | S14: =IF(AND(ISNUMBER(R14),R14>1,P14>0),R14/P14-1,"") -> -0.61556431 | T14: =IF(AND(ISNUMBER(P14),P14>0),P14*EXP('Read me'!$B$22),"") -> 479.74686
A15: 2:25 | B15: Cork | C15: Irish Stallion Farms EBF Nursery Handicap (Birdcatcher Series) | E15: 6 | F15: Yielding | G15: 7 | H15: Pink Venom (IRE) | I15: Coen, Ben M | J15: Murtagh, J P | K15: 5 | L15: 76 | M15: 2 | N15: 8 | O15: 1 | P15: 2.9968914 | Q15: 0.33367909 | R15: 2 | S15: =IF(AND(ISNUMBER(R15),R15>1,P15>0),R15/P15-1,"") -> -0.33264182 | T15: =IF(AND(ISNUMBER(P15),P15>0),P15*EXP('Read me'!$B$22),"") -> 3.6604114
A16: 2:25 | B16: Cork | C16: Irish Stallion Farms EBF Nursery Handicap (Birdcatcher Series) | E16: 6 | F16: Yielding | G16: 7 | H16: Fine Line (IRE) | J16: Hogan, Denis Gerard | K16: 6 | L16: 79 | M16: 2 | N16: 2 | O16: 2 | P16: 5.8739402 | Q16: 0.17024348 | R16: 9.5 | S16: =IF(AND(ISNUMBER(R16),R16>1,P16>0),R16/P16-1,"") -> 0.61731302 | T16: =IF(AND(ISNUMBER(P16),P16>0),P16*EXP('Read me'!$B$22),"") -> 7.1744468
A17: 2:25 | B17: Cork | C17: Irish Stallion Farms EBF Nursery Handicap (Birdcatcher Series) | E17: 6 | F17: Yielding | G17: 7 | H17: Howlin Wolf (IRE) | I17: Ryan, J J G | J17: Davison, Jack W | K17: 4 | L17: 75 | M17: 2 | N17: 24 | O17: 3 | P17: 7.1324058 | Q17: 0.14020515 | R17: 6 | S17: =IF(AND(ISNUMBER(R17),R17>1,P17>0),R17/P17-1,"") -> -0.15876912 | T17: =IF(AND(ISNUMBER(P17),P17>0),P17*EXP('Read me'!$B$22),"") -> 8.7115401
A18: 2:25 | B18: Cork | C18: Irish Stallion Farms EBF Nursery Handicap (Birdcatcher Series) | E18: 6 | F18: Yielding | G18: 7 | H18: Captain James Cook | I18: Lordan, W M | J18: OBrien, A P | K18: 7 | L18: 63 | M18: 2 | N18: 8 | O18: 4 | P18: 8.4926245 | Q18: 0.11774923 | R18: 5.5 | S18: =IF(AND(ISNUMBER(R18),R18>1,P18>0),R18/P18-1,"") -> -0.35237923 | T18: =IF(AND(ISNUMBER(P18),P18>0),P18*EXP('Read me'!$B$22),"") -> 10.372915
A19: 2:25 | B19: Cork | C19: Irish Stallion Farms EBF Nursery Handicap (Birdcatcher Series) | E19: 6 | F19: Yielding | G19: 7 | H19: Best Love (IRE) | I19: McDonogh, D P | J19: Harty, Edward and Patrick | K19: 3 | L19: 75 | M19: 2 | N19: 27 | O19: 5 | P19: 10.211733 | Q19: 0.097926567 | R19: 12 | S19: =IF(AND(ISNUMBER(R19),R19>1,P19>0),R19/P19-1,"") -> 0.1751188 | T19: =IF(AND(ISNUMBER(P19),P19>0),P19*EXP('Read me'!$B$22),"") -> 12.472639
A20: 2:25 | B20: Cork | C20: Irish Stallion Farms EBF Nursery Handicap (Birdcatcher Series) | E20: 6 | F20: Yielding | G20: 7 | H20: Whosinterviewinwho (IRE) | I20: Coen, S | J20: Slattery, Andrew | K20: 1 | L20: 79 | M20: 2 | N20: 25 | O20: 6 | P20: 10.700093 | Q20: 0.093457129 | R20: 6 | S20: =IF(AND(ISNUMBER(R20),R20>1,P20>0),R20/P20-1,"") -> -0.43925723 | T20: =IF(AND(ISNUMBER(P20),P20>0),P20*EXP('Read me'!$B$22),"") -> 13.069123
A21: 2:25 | B21: Cork | C21: Irish Stallion Farms EBF Nursery Handicap (Birdcatcher Series) | E21: 6 | F21: Yielding | G21: 7 | H21: Cyclone Code (IRE) | I21: OConnor, Donagh | J21: Cavanagh, S | K21: 2 | L21: 77 | M21: 2 | N21: 12 | O21: 7 | P21: 21.395243 | Q21: 0.046739361 | R21: 17 | S21: =IF(AND(ISNUMBER(R21),R21>1,P21>0),R21/P21-1,"") -> -0.20543087 | T21: =IF(AND(ISNUMBER(P21),P21>0),P21*EXP('Read me'!$B$22),"") -> 26.132209
A22: 2:55 | B22: Cork | C22: Irish Stallion Farms EBF Fillies Handicap | E22: 6 | F22: Yielding | G22: 9 | H22: By The Lake (IRE) | I22: Keane, C T | J22: McCormack, Derek | K22: 6 | L22: 79 | M22: 3 | N22: 33 | O22: 1 | P22: 4.7378235 | Q22: 0.21106738 | R22: 7.5 | S22: =IF(AND(ISNUMBER(R22),R22>1,P22>0),R22/P22-1,"") -> 0.58300535 | T22: =IF(AND(ISNUMBER(P22),P22>0),P22*EXP('Read me'!$B$22),"") -> 5.7867907
A23: 2:55 | B23: Cork | C23: Irish Stallion Farms EBF Fillies Handicap | E23: 6 | F23: Yielding | G23: 9 | H23: Forza Magico | I23: Whelan, R P | J23: Feane, John James | K23: 5 | L23: 70 | M23: 3 | N23: 25 | O23: 2 | P23: 6.5293068 | Q23: 0.15315562 | R23: 5 | S23: =IF(AND(ISNUMBER(R23),R23>1,P23>0),R23/P23-1,"") -> -0.23422192 | T23: =IF(AND(ISNUMBER(P23),P23>0),P23*EXP('Read me'!$B$22),"") -> 7.9749133
A24: 2:55 | B24: Cork | C24: Irish Stallion Farms EBF Fillies Handicap | E24: 6 | F24: Yielding | G24: 9 | H24: Motta Alta (IRE) | I24: McCullagh, Scott | J24: Harrington, Mrs John | K24: 9 | L24: 77 | M24: 3 | N24: 14 | O24: 3 | P24: 8.7498092 | Q24: 0.11428821 | R24: 5 | S24: =IF(AND(ISNUMBER(R24),R24>1,P24>0),R24/P24-1,"") -> -0.42855897 | T24: =IF(AND(ISNUMBER(P24),P24>0),P24*EXP('Read me'!$B$22),"") -> 10.687041
A25: 2:55 | B25: Cork | C25: Irish Stallion Farms EBF Fillies Handicap | E25: 6 | F25: Yielding | G25: 9 | H25: Baiana (GER) | I25: Sheridan, J M | J25: OBrien, Joseph Patrick | K25: 2 | L25: 71 | M25: 3 | N25: 124 | O25: 4 | P25: 9.3177277 | Q25: 0.1073223 | R25: 11 | S25: =IF(AND(ISNUMBER(R25),R25>1,P25>0),R25/P25-1,"") -> 0.18054534 | T25: =IF(AND(ISNUMBER(P25),P25>0),P25*EXP('Read me'!$B$22),"") -> 11.380698
A26: 2:55 | B26: Cork | C26: Irish Stallion Farms EBF Fillies Handicap | E26: 6 | F26: Yielding | G26: 9 | H26: Staysound Susie (IRE) | I26: Dalton, J S | J26: Slattery, Andrew | K26: 3 | L26: 84 | M26: 5 | N26: 16 | O26: 5 | P26: 9.7754413 | Q26: 0.10229717 | R26: 4.5 | S26: =IF(AND(ISNUMBER(R26),R26>1,P26>0),R26/P26-1,"") -> -0.53966272 | T26: =IF(AND(ISNUMBER(P26),P26>0),P26*EXP('Read me'!$B$22),"") -> 11.939751
A27: 2:55 | B27: Cork | C27: Irish Stallion Farms EBF Fillies Handicap | E27: 6 | F27: Yielding | G27: 9 | H27: Rosato (IRE) | I27: Mulligan, R M | J27: Weld, Charles | K27: 1 | L27: 58 | M27: 5 | N27: 24 | O27: 6 | P27: 10.038118 | Q27: 0.099620266 | R27: 7.5 | S27: =IF(AND(ISNUMBER(R27),R27>1,P27>0),R27/P27-1,"") -> -0.25284801 | T27: =IF(AND(ISNUMBER(P27),P27>0),P27*EXP('Read me'!$B$22),"") -> 12.260585
A28: 2:55 | B28: Cork | C28: Irish Stallion Farms EBF Fillies Handicap | E28: 6 | F28: Yielding | G28: 9 | H28: Flash Of Fire | I28: Coen, Ben M | J28: Murtagh, J P | K28: 8 | L28: 79 | M28: 3 | N28: 14 | O28: 7 | P28: 11.929759 | Q28: 0.083823991 | R28: 8.5 | S28: =IF(AND(ISNUMBER(R28),R28>1,P28>0),R28/P28-1,"") -> -0.28749607 | T28: =IF(AND(ISNUMBER(P28),P28>0),P28*EXP('Read me'!$B$22),"") -> 14.57104
... A53: 3:55 | B53: Cork | C53: Irish Stallion Farms EBF Navigation Stakes (Listed) | E53: 10.5 | F53: Yielding | G53: 12 | H53: Shaihaan (IRE) | I53: Hayes, C D | J53: Obrien, Donnacha | K53: 6 | L53: 102 | M53: 3 | N53: 61 | O53: 4 | P53: 9.5513545 | Q53: 0.10469719 | R53: 6.5 | S53: =IF(AND(ISNUMBER(R53),R53>1,P53>0),R53/P53-1,"") -> -0.31946825 | T53: =IF(AND(ISNUMBER(P53),P53>0),P53*EXP('Read me'!$B$22),"") -> 11.666051
A54: 3:55 | B54: Cork | C54: Irish Stallion Farms EBF Navigation Stakes (Listed) | E54: 10.5 | F54: Yielding | G54: 12 | H54: Magnum Cor (IRE) | J54: OBrien, Joseph Patrick | K54: 8 | L54: 95 | M54: 3 | N54: 42 | O54: 5 | P54: 10.84934 | Q54: 0.092171509 | R54: 10 | S54: =IF(AND(ISNUMBER(R54),R54>1,P54>0),R54/P54-1,"") -> -0.078284912 | T54: =IF(AND(ISNUMBER(P54),P54>0),P54*EXP('Read me'!$B$22),"") -> 13.251413
A55: 3:55 | B55: Cork | C55: Irish Stallion Farms EBF Navigation Stakes (Listed) | E55: 10.5 | F55: Yielding | G55: 12 | H55: Latin America (IRE) | I55: Coen, Ben M | J55: Murtagh, J P | K55: 1 | L55: 95 | M55: 3 | N55: 135 | O55: 6 | P55: 12.351965 | Q55: 0.080958776 | R55: 9.5 | S55: =IF(AND(ISNUMBER(R55),R55>1,P55>0),R55/P55-1,"") -> -0.23089163 | T55: =IF(AND(ISNUMBER(P55),P55>0),P55*EXP('Read me'!$B$22),"") -> 15.086725
A56: 3:55 | B56: Cork | C56: Irish Stallion Farms EBF Navigation Stakes (Listed) | E56: 10.5 | F56: Yielding | G56: 12 | H56: Back Straight | I56: Heffernan, J A | J56: OCallaghan, M D | K56: 4 | L56: 88 | M56: 3 | N56: 14 | O56: 7 | P56: 14.034531 | Q56: 0.071252829 | R56: 21 | S56: =IF(AND(ISNUMBER(R56),R56>1,P56>0),R56/P56-1,"") -> 0.4963094 | T56: =IF(AND(ISNUMBER(P56),P56>0),P56*EXP('Read me'!$B$22),"") -> 17.141814
A57: 3:55 | B57: Cork | C57: Irish Stallion Farms EBF Navigation Stakes (Listed) | E57: 10.5 | F57: Yielding | G57: 12 | H57: Action (IRE) | I57: Lordan, W M | J57: OBrien, A P | K57: 12 | L57: 109 | M57: 3 | N57: 17 | O57: 8 | P57: 17.176746 | Q57: 0.058218243 | R57: 3.25 | S57: =IF(AND(ISNUMBER(R57),R57>1,P57>0),R57/P57-1,"") -> -0.81079071 | T57: =IF(AND(ISNUMBER(P57),P57>0),P57*EXP('Read me'!$B$22),"") -> 20.979725
A58: 3:55 | B58: Cork | C58: Irish Stallion Farms EBF Navigation Stakes (Listed) | E58: 10.5 | F58: Yielding | G58: 12 | H58: Alphecca (IRE) | I58: Carroll, G F | J58: Murphy, Joseph G | K58: 2 | L58: 91 | M58: 3 | N58: 8 | O58: 9 | P58: 30.859873 | Q58: 0.03240454 | R58: 26 | S58: =IF(AND(ISNUMBER(R58),R58>1,P58>0),R58/P58-1,"") -> -0.15748195 | T58: =IF(AND(ISNUMBER(P58),P58>0),P58*EXP('Read me'!$B$22),"") -> 37.692334
A59: 3:55 | B59: Cork | C59: Irish Stallion Farms EBF Navigation Stakes (Listed) | E59: 10.5 | F59: Yielding | G59: 12 | H59: Garden Party (IRE) | I59: Whelan, R P | J59: OBrien, A P | K59: 5 | L59: 85 | M59: 3 | N59: 31 | O59: 10 | P59: 33.593562 | Q59: 0.029767609 | R59: 41 | S59: =IF(AND(ISNUMBER(R59),R59>1,P59>0),R59/P59-1,"") -> 0.22047196 | T59: =IF(AND(ISNUMBER(P59),P59>0),P59*EXP('Read me'!$B$22),"") -> 41.031269
A60: 3:55 | B60: Cork | C60: Irish Stallion Farms EBF Navigation Stakes (Listed) | E60: 10.5 | F60: Yielding | G60: 12 | H60: Mr Vettori (IRE) | I60: McCullagh, Scott | J60: Harrington, Mrs John | K60: 3 | L60: 98 | M60: 3 | N60: 60 | O60: 11 | P60: 42.757596 | Q60: 0.023387657 | R60: 41 | S60: =IF(AND(ISNUMBER(R60),R60>1,P60>0),R60/P60-1,"") -> -0.041106045 | T60: =IF(AND(ISNUMBER(P60),P60>0),P60*EXP('Read me'!$B$22),"") -> 52.224245
A61: 3:55 | B61: Cork | C61: Irish Stallion Farms EBF Navigation Stakes (Listed) | E61: 10.5 | F61: Yielding | G61: 12 | H61: Fallacy (USA) | I61: Slattery, A J | J61: Slattery, Andrew | K61: 11 | L61: 84 | M61: 3 | N61: 109 | O61: 12 | P61: 64.827228 | Q61: 0.015425617 | R61: 26 | S61: =IF(AND(ISNUMBER(R61),R61>1,P61>0),R61/P61-1,"") -> -0.59893395 | T61: =IF(AND(ISNUMBER(P61),P61>0),P61*EXP('Read me'!$B$22),"") -> 79.180155
A62: 4:25 | B62: Cork | C62: Irish EBF Fillies Maiden (Smullen Series) | E62: 8 | F62: Yielding | G62: 14 | H62: Golden Ring (IRE) | I62: Lordan, W M | J62: OBrien, A P | K62: 12 | L62: 0 | M62: 2 | N62: 20 | O62: 1 | P62: 4.1816566 | Q62: 0.23913967 | R62: 2.2 | S62: =IF(AND(ISNUMBER(R62),R62>1,P62>0),R62/P62-1,"") -> -0.47389272 | T62: =IF(AND(ISNUMBER(P62),P62>0),P62*EXP('Read me'!$B$22),"") -> 5.107487
A63: 4:25 | B63: Cork | C63: Irish EBF Fillies Maiden (Smullen Series) | E63: 8 | F63: Yielding | G63: 14 | H63: Duchessofaquitaine (IRE) | I63: Lee, W J | J63: Twomey, P | K63: 8 | L63: 0 | M63: 2 | O63: 2 | P63: 4.3883636 | Q63: 0.22787537 | R63: 5 | S63: =IF(AND(ISNUMBER(R63),R63>1,P63>0),R63/P63-1,"") -> 0.13937687 | T63: =IF(AND(ISNUMBER(P63),P63>0),P63*EXP('Read me'!$B$22),"") -> 5.3599594
A64: 4:25 | B64: Cork | C64: Irish EBF Fillies Maiden (Smullen Series) | E64: 8 | F64: Yielding | G64: 14 | H64: Gods Love | I64: Keane, C T | J64: Lyons, G M | K64: 2 | L64: 0 | M64: 2 | O64: 3 | P64: 7.193698 | Q64: 0.13901056 | R64: 6 | S64: =IF(AND(ISNUMBER(R64),R64>1,P64>0),R64/P64-1,"") -> -0.16593663 | T64: =IF(AND(ISNUMBER(P64),P64>0),P64*EXP('Read me'!$B$22),"") -> 8.7864026
A65: 4:25 | B65: Cork | C65: Irish EBF Fillies Maiden (Smullen Series) | E65: 8 | F65: Yielding | G65: 14 | H65: Alaraza (IRE) | I65: Hayes, C D | J65: Weld, D K | K65: 11 | L65: 0 | M65: 2 | O65: 4 | P65: 9.876143 | Q65: 0.1012541 | R65: 26 | S65: =IF(AND(ISNUMBER(R65),R65>1,P65>0),R65/P65-1,"") -> 1.6326067 | T65: =IF(AND(ISNUMBER(P65),P65>0),P65*EXP('Read me'!$B$22),"") -> 12.062748
A66: 4:25 | B66: Cork | C66: Irish EBF Fillies Maiden (Smullen Series) | E66: 8 | F66: Yielding | G66: 14 | H66: Cross Of Stars (IRE) | I66: Carroll, G F | J66: Murphy, Joseph G | K66: 7 | L66: 0 | M66: 2 | N66: 14 | O66: 5 | P66: 13.874081 | Q66: 0.072076844 | R66: 4.5 | S66: =IF(AND(ISNUMBER(R66),R66>1,P66>0),R66/P66-1,"") -> -0.6756542 | T66: =IF(AND(ISNUMBER(P66),P66>0),P66*EXP('Read me'!$B$22),"") -> 16.945841
A67: 4:25 | B67: Cork | C67: Irish EBF Fillies Maiden (Smullen Series) | E67: 8 | F67: Yielding | G67: 14 | H67: Somebody Loves Me | I67: Whelan, R P | J67: OBrien, A P | K67: 13 | L67: 0 | M67: 2 | O67: 6 | P67: 16.072015 | Q67: 0.062219953 | R67: 17 | S67: =IF(AND(ISNUMBER(R67),R67>1,P67>0),R67/P67-1,"") -> 0.057739205 | T67: =IF(AND(ISNUMBER(P67),P67>0),P67*EXP('Read me'!$B$22),"") -> 19.630403
A68: 4:25 | B68: Cork | C68: Irish EBF Fillies Maiden (Smullen Series) | E68: 8 | F68: Yielding | G68: 14 | H68: Captivating (IRE) | I68: Cleary, Jack | J68: OBrien, A P | K68: 6 | L68: 0 | M68: 2 | O68: 7 | P68: 17.652731 | Q68: 0.056648459 | R68: 23 | S68: =IF(AND(ISNUMBER(R68),R68>1,P68>0),R68/P68-1,"") -> 0.30291456 | T68: =IF(AND(ISNUMBER(P68),P68>0),P68*EXP('Read me'!$B$22),"") -> 21.561094
A69: 4:25 | B69: Cork | C69: Irish EBF Fillies Maiden (Smullen Series) | E69: 8 | F69: Yielding | G69: 14 | H69: Anymore (IRE) | I69: Ryan, Gavin | J69: OBrien, A P | K69: 10 | L69: 0 | M69: 2 | O69: 8 | P69: 28.654026 | Q69: 0.03489911 | R69: 41 | S69: =IF(AND(ISNUMBER(R69),R69>1,P69>0),R69/P69-1,"") -> 0.43086352 | T69: =IF(AND(ISNUMBER(P69),P69>0),P69*EXP('Read me'!$B$22),"") -> 34.998106
A70: 4:25 | B70: Cork | C70: Irish EBF Fillies Maiden (Smullen Series) | E70: 8 | F70: Yielding | G70: 14 | H70: State Of Clarity (IRE) | I70: Heffernan, J A | J70: Harrington, Mrs John | K70: 1 | L70: 0 | M70: 2 | O70: 9 | P70: 39.852697 | Q70: 0.025092405 | R70: 26 | S70: =IF(AND(ISNUMBER(R70),R70>1,P70>0),R70/P70-1,"") -> -0.34759747 | T70: =IF(AND(ISNUMBER(P70),P70>0),P70*EXP('Read me'!$B$22),"") -> 48.676194
A71: 4:25 | B71: Cork | C71: Irish EBF Fillies Maiden (Smullen Series) | E71: 8 | F71: Yielding | G71: 14 | H71: Torvella (IRE) | I71: Slattery, A J | J71: Slattery, Andrew | K71: 4 | L71: 0 | M71: 2 | N71: 20 | O71: 10 | P71: 48.233603 | Q71: 0.020732434 | R71: 34 | S71: =IF(AND(ISNUMBER(R71),R71>1,P71>0),R71/P71-1,"") -> -0.29509723 | T71: =IF(AND(ISNUMBER(P71),P71>0),P71*EXP('Read me'!$B$22),"") -> 58.912655
A72: 4:25 | B72: Cork | C72: Irish EBF Fillies Maiden (Smullen Series) | E72: 8 | F72: Yielding | G72: 14 | H72: Angel Invincible (IRE) | I72: Coen, Ben M | J72: McLoughlin, Daniel | K72: 9 | L72: 0 | M72: 2 | O72: 11 | P72: 135.68892 | Q72: 0.0073697987 | R72: 151 | S72: =IF(AND(ISNUMBER(R72),R72>1,P72>0),R72/P72-1,"") -> 0.11283961 | T72: =IF(AND(ISNUMBER(P72),P72>0),P72*EXP('Read me'!$B$22),"") -> 165.73082
A73: 4:25 | B73: Cork | C73: Irish EBF Fillies Maiden (Smullen Series) | E73: 8 | F73: Yielding | G73: 14 | H73: Tequila Belle (IRE) | I73: Browne-Souza, A | J73: Slattery, Andrew | K73: 5 | L73: 0 | M73: 2 | O73: 12 | P73: 162.27521 | Q73: 0.0061623707 | R73: 101 | S73: =IF(AND(ISNUMBER(R73),R73>1,P73>0),R73/P73-1,"") -> -0.37760056 | T73: =IF(AND(ISNUMBER(P73),P73>0),P73*EXP('Read me'!$B$22),"") -> 198.20339
A74: 4:25 | B74: Cork | C74: Irish EBF Fillies Maiden (Smullen Series) | E74: 8 | F74: Yielding | G74: 14 | H74: Lady Chancalot (FR) | I74: Ryan, J J G | J74: Davison, Jack W | K74: 3 | L74: 0 | M74: 2 | N74: 28 | O74: 13 | P74: 204.10306 | Q74: 0.0048994857 | R74: 201 | S74: =IF(AND(ISNUMBER(R74),R74>1,P74>0),R74/P74-1,"") -> -0.015203378 | T74: =IF(AND(ISNUMBER(P74),P74>0),P74*EXP('Read me'!$B$22),"") -> 249.29204
A75: 4:25 | B75: Cork | C75: Irish EBF Fillies Maiden (Smullen Series) | E75: 8 | F75: Yielding | G75: 14 | H75: Drumbinion Lass (IRE) | I75: Caffrey, Adam | J75: McCourt, T G | K75: 14 | L75: 0 | M75: 2 | O75: 14 | P75: 381.76263 | Q75: 0.0026194287 | R75: 201 | S75: =IF(AND(ISNUMBER(R75),R75>1,P75>0),R75/P75-1,"") -> -0.47349483 | T75: =IF(AND(ISNUMBER(P75),P75>0),P75*EXP('Read me'!$B$22),"") -> 466.28593
A76: 4:55 | B76: Cork | C76: Follow Us On X Handicap | E76: 8 | F76: Yielding | G76: 9 | H76: Karrygrant (IRE) | I76: Coen, Ben M | J76: Murtagh, J P | K76: 8 | L76: 77 | M76: 3 | N76: 35 | O76: 1 | P76: 5.8004211 | Q76: 0.17240128 | R76: 4 | S76: =IF(AND(ISNUMBER(R76),R76>1,P76>0),R76/P76-1,"") -> -0.3103949 | T76: =IF(AND(ISNUMBER(P76),P76>0),P76*EXP('Read me'!$B$22),"") -> 7.0846504
A77: 4:55 | B77: Cork | C77: Follow Us On X Handicap | E77: 8 | F77: Yielding | G77: 9 | H77: Hellorhighwater | I77: Heffernan, J A | J77: Lupini, Miss Natalia | K77: 7 | L77: 86 | M77: 4 | N77: 31 | O77: 2 | P77: 6.3690457 | Q77: 0.15700939 | R77: 7 | S77: =IF(AND(ISNUMBER(R77),R77>1,P77>0),R77/P77-1,"") -> 0.099065745 | T77: =IF(AND(ISNUMBER(P77),P77>0),P77*EXP('Read me'!$B$22),"") -> 7.77917
A78: 4:55 | B78: Cork | C78: Follow Us On X Handicap | E78: 8 | F78: Yielding | G78: 9 | H78: Oro Blanco (IRE) | I78: McCullagh, Scott | J78: Harrington, Mrs John | K78: 9 | L78: 84 | M78: 3 | N78: 3 | O78: 3 | P78: 7.1170122 | Q78: 0.1405084 | R78: 5 | S78: =IF(AND(ISNUMBER(R78),R78>1,P78>0),R78/P78-1,"") -> -0.297458 | T78: =IF(AND(ISNUMBER(P78),P78>0),P78*EXP('Read me'!$B$22),"") -> 8.6927384
A79: 4:55 | B79: Cork | C79: Follow Us On X Handicap | E79: 8 | F79: Yielding | G79: 9 | H79: Daler (IRE) | I79: Keane, C T | J79: Lyons, G M | K79: 3 | L79: 81 | M79: 4 | N79: 27 | O79: 4 | P79: 7.1722624 | Q79: 0.13942602 | R79: 8 | S79: =IF(AND(ISNUMBER(R79),R79>1,P79>0),R79/P79-1,"") -> 0.11540816 | T79: =IF(AND(ISNUMBER(P79),P79>0),P79*EXP('Read me'!$B$22),"") -> 8.7602211
A80: 4:55 | B80: Cork | C80: Follow Us On X Handicap | E80: 8 | F80: Yielding | G80: 9 | H80: Playin Cool (IRE) | I80: McAteer, L T | J80: Feane, John James | K80: 6 | L80: 81 | M80: 4 | N80: 31 | O80: 5 | P80: 7.9710553 | Q80: 0.1254539 | R80: 5 | S80: =IF(AND(ISNUMBER(R80),R80>1,P80>0),R80/P80-1,"") -> -0.37273048 | T80: =IF(AND(ISNUMBER(P80),P80>0),P80*EXP('Read me'!$B$22),"") -> 9.7358689
A81: 4:55 | B81: Cork | C81: Follow Us On X Handicap | E81: 8 | F81: Yielding | G81: 9 | H81: Lady Lilac (IRE) | I81: Carroll, G F | J81: Murphy, Joseph G | K81: 5 | L81: 85 | M81: 4 | N81: 63 | O81: 6 | P81: 10.855755 | Q81: 0.092117038 | R81: 9 | S81: =IF(AND(ISNUMBER(R81),R81>1,P81>0),R81/P81-1,"") -> -0.17094666 | T81: =IF(AND(ISNUMBER(P81),P81>0),P81*EXP('Read me'!$B$22),"") -> 13.259249
A82: 4:55 | B82: Cork | C82: Follow Us On X Handicap | E82: 8 | F82: Yielding | G82: 9 | H82: Victory Tip (IRE) | I82: Lee, W J | J82: Bromhead, Henry De | K82: 2 | L82: 91 | M82: 3 | N82: 103 | O82: 7 | P82: 12.517474 | Q82: 0.079888325 | R82: 12 | S82: =IF(AND(ISNUMBER(R82),R82>1,P82>0),R82/P82-1,"") -> -0.041340101 | T82: =IF(AND(ISNUMBER(P82),P82>0),P82*EXP('Read me'!$B$22),"") -> 15.288877
A83: 4:55 | B83: Cork | C83: Follow Us On X Handicap | E83: 8 | F83: Yielding | G83: 9 | H83: Son Of Beauty (IRE) | I83: Kearney, J | J83: Thorne, Stephen | K83: 4 | L83: 81 | M83: 3 | N83: 109 | O83: 8 | P83: 13.933257 | Q83: 0.071770731 | R83: 15 | S83: =IF(AND(ISNUMBER(R83),R83>1,P83>0),R83/P83-1,"") -> 0.076560959 | T83: =IF(AND(ISNUMBER(P83),P83>0),P83*EXP('Read me'!$B$22),"") -> 17.018118
A84: 4:55 | B84: Cork | C84: Follow Us On X Handicap | E84: 8 | F84: Yielding | G84: 9 | H84: Bold Style | I84: Browne-Souza, A | J84: Slattery, Andrew | K84: 1 | L84: 89 | M84: 5 | N84: 30 | O84: 9 | P84: 46.674626 | Q84: 0.021424917 | R84: 67 | S84: =IF(AND(ISNUMBER(R84),R84>1,P84>0),R84/P84-1,"") -> 0.43546947 | T84: =IF(AND(ISNUMBER(P84),P84>0),P84*EXP('Read me'!$B$22),"") -> 57.008517
A85: 5:25 | B85: Cork | C85: Fitzgeralds Woodlands House Hotel Handicap (0-60) | E85: 8 | F85: Yielding | G85: 18 | H85: Medieval Night (IRE) | I85: Sheridan, J M | J85: Hogan, Denis Gerard | K85: 1 | L85: 56 | M85: 4 | N85: 13 | O85: 1 | P85: 8.3424453 | Q85: 0.11986893 | R85: 7 | S85: =IF(AND(ISNUMBER(R85),R85>1,P85>0),R85/P85-1,"") -> -0.16091749 | T85: =IF(AND(ISNUMBER(P85),P85>0),P85*EXP('Read me'!$B$22),"") -> 10.189486
A86: 5:25 | B86: Cork | C86: Fitzgeralds Woodlands House Hotel Handicap (0-60) | E86: 8 | F86: Yielding | G86: 18 | H86: Movin And Groovin (IRE) | I86: Carroll, G F | J86: Marnane, David | K86: 21 | L86: 45 | M86: 4 | N86: 19 | O86: 2 | P86: 9.3624936 | Q86: 0.10680915 | R86: 12 | S86: =IF(AND(ISNUMBER(R86),R86>1,P86>0),R86/P86-1,"") -> 0.28170982 | T86: =IF(AND(ISNUMBER(P86),P86>0),P86*EXP('Read me'!$B$22),"") -> 11.435376
A87: 5:25 | B87: Cork | C87: Fitzgeralds Woodlands House Hotel Handicap (0-60) | E87: 8 | F87: Yielding | G87: 18 | H87: Concaire (IRE) | I87: McCullagh, Scott | J87: OBrien, Richard John | K87: 11 | L87: 55 | M87: 3 | N87: 13 | O87: 3 | P87: 11.58471 | Q87: 0.086320675 | R87: 8 | S87: =IF(AND(ISNUMBER(R87),R87>1,P87>0),R87/P87-1,"") -> -0.3094346 | T87: =IF(AND(ISNUMBER(P87),P87>0),P87*EXP('Read me'!$B$22),"") -> 14.149597
... A102: 5:25 | B102: Cork | C102: Fitzgeralds Woodlands House Hotel Handicap (0-60) | E102: 8 | F102: Yielding | G102: 18 | H102: Ramair (IRE) | I102: Wallace, S A | J102: Foley, Richard Anthony | K102: 20 | L102: 40 | M102: 3 | N102: 77 | O102: 18 | P102: 100.49155 | Q102: 0.0099510856 | R102: 101 | S102: =IF(AND(ISNUMBER(R102),R102>1,P102>0),R102/P102-1,"") -> 0.0050596437 | T102: =IF(AND(ISNUMBER(P102),P102>0),P102*EXP('Read me'!$B$22),"") -> 122.74065

Sheet Bath
A1: Time | B1: Course | C1: Race | D1: Class | E1: Furlongs | F1: Going | G1: Runners | H1: Horse | I1: Jockey | J1: Trainer | K1: Draw | L1: OR | M1: Age | N1: Days since run | O1: Model rank | P1: Predicted BSP | Q1: Win probability | R1: Card odds (HRB) | S1: Card odds vs model | T1: Rule: back at Betfair ≥
A2: 2:02 | B2: Bath | C2: JDL Consultants Ltd Apprentice Handicap | D2: Class 5 | E2: 10 | F2: Good To Firm | G2: 11 | H2: Decalogue (USA) | I2: Paetel, Mason | J2: Osborne, J A | K2: 1 | L2: 73 | M2: 3 | N2: 15 | O2: 1 | P2: 5.5561386 | Q2: 0.17998111 | R2: 4.5 | S2: =IF(AND(ISNUMBER(R2),R2>1,P2>0),R2/P2-1,"") -> -0.190085 | T2: =IF(AND(ISNUMBER(P2),P2>0),P2*EXP('Read me'!$B$22),"") -> 6.786283
A3: 2:02 | B3: Bath | C3: JDL Consultants Ltd Apprentice Handicap | D3: Class 5 | E3: 10 | F3: Good To Firm | G3: 11 | H3: Pangbourne | I3: Haines, Olivia | J3: Teal, R A | K3: 3 | L3: 56 | M3: 3 | N3: 13 | O3: 2 | P3: 6.4064338 | Q3: 0.15609308 | R3: 6 | S3: =IF(AND(ISNUMBER(R3),R3>1,P3>0),R3/P3-1,"") -> -0.063441498 | T3: =IF(AND(ISNUMBER(P3),P3>0),P3*EXP('Read me'!$B$22),"") -> 7.8248359
A4: 2:02 | B4: Bath | C4: JDL Consultants Ltd Apprentice Handicap | D4: Class 5 | E4: 10 | F4: Good To Firm | G4: 11 | H4: Shady Bay (IRE) | I4: Lewis, Ashley | J4: Ward, Tom | K4: 4 | L4: 74 | M4: 5 | N4: 32 | O4: 3 | P4: 6.6128169 | Q4: 0.15122149 | R4: 4 | S4: =IF(AND(ISNUMBER(R4),R4>1,P4>0),R4/P4-1,"") -> -0.39511406 | T4: =IF(AND(ISNUMBER(P4),P4>0),P4*EXP('Read me'!$B$22),"") -> 8.0769128
A5: 2:02 | B5: Bath | C5: JDL Consultants Ltd Apprentice Handicap | D5: Class 5 | E5: 10 | F5: Good To Firm | G5: 11 | H5: Oman (IRE) | I5: Coppins, Myla | J5: Carroll, A W | K5: 2 | L5: 68 | M5: 8 | N5: 18 | O5: 4 | P5: 10.638227 | Q5: 0.094000622 | R5: 7.5 | S5: =IF(AND(ISNUMBER(R5),R5>1,P5>0),R5/P5-1,"") -> -0.29499533 | T5: =IF(AND(ISNUMBER(P5),P5>0),P5*EXP('Read me'!$B$22),"") -> 12.99356
A6: 2:02 | B6: Bath | C6: JDL Consultants Ltd Apprentice Handicap | D6: Class 5 | E6: 10 | F6: Good To Firm | G6: 11 | H6: Dryburgh (IRE) | I6: Catton, Luke | J6: Rix, Oli | K6: 6 | L6: 75 | M6: 3 | N6: 52 | O6: 5 | P6: 11.172339 | Q6: 0.089506772 | R6: 8 | S6: =IF(AND(ISNUMBER(R6),R6>1,P6>0),R6/P6-1,"") -> -0.28394583 | T6: =IF(AND(ISNUMBER(P6),P6>0),P6*EXP('Read me'!$B$22),"") -> 13.645926
A7: 2:02 | B7: Bath | C7: JDL Consultants Ltd Apprentice Handicap | D7: Class 5 | E7: 10 | F7: Good To Firm | G7: 11 | H7: Captain Fox (IRE) | I7: Murphy, D J | J7: Hughes, Richard | K7: 11 | L7: 72 | M7: 3 | N7: 17 | O7: 6 | P7: 12.059594 | Q7: 0.082921534 | R7: 8.5 | S7: =IF(AND(ISNUMBER(R7),R7>1,P7>0),R7/P7-1,"") -> -0.29516696 | T7: =IF(AND(ISNUMBER(P7),P7>0),P7*EXP('Read me'!$B$22),"") -> 14.729621
A8: 2:02 | B8: Bath | C8: JDL Consultants Ltd Apprentice Handicap | D8: Class 5 | E8: 10 | F8: Good To Firm | G8: 11 | H8: Its Life | J8: Turner, Kathy | K8: 5 | L8: 56 | M8: 4 | N8: 36 | O8: 7 | P8: 13.008317 | Q8: 0.076873894 | R8: 13 | S8: =IF(AND(ISNUMBER(R8),R8>1,P8>0),R8/P8-1,"") -> -0.0006393754 | T8: =IF(AND(ISNUMBER(P8),P8>0),P8*EXP('Read me'!$B$22),"") -> 15.888395
A9: 2:02 | B9: Bath | C9: JDL Consultants Ltd Apprentice Handicap | D9: Class 5 | E9: 10 | F9: Good To Firm | G9: 11 | H9: Pomme Pomme (IRE) | I9: Dace, Jack | J9: Channon, Jack | K9: 7 | L9: 72 | M9: 4 | N9: 26 | O9: 8 | P9: 14.159192 | Q9: 0.070625499 | R9: 13 | S9: =IF(AND(ISNUMBER(R9),R9>1,P9>0),R9/P9-1,"") -> -0.081868507 | T9: =IF(AND(ISNUMBER(P9),P9>0),P9*EXP('Read me'!$B$22),"") -> 17.294076
A10: 2:02 | B10: Bath | C10: JDL Consultants Ltd Apprentice Handicap | D10: Class 5 | E10: 10 | F10: Good To Firm | G10: 11 | H10: Gallant Pioneer (IRE) | I10: Vigors, Harry | J10: Pike, Charlie | K10: 8 | L10: 64 | M10: 3 | N10: 43 | O10: 9 | P10: 18.845741 | Q10: 0.053062388 | R10: 17 | S10: =IF(AND(ISNUMBER(R10),R10>1,P10>0),R10/P10-1,"") -> -0.09793941 | T10: =IF(AND(ISNUMBER(P10),P10>0),P10*EXP('Read me'!$B$22),"") -> 23.01824
A11: 2:02 | B11: Bath | C11: JDL Consultants Ltd Apprentice Handicap | D11: Class 5 | E11: 10 | F11: Good To Firm | G11: 11 | H11: Rascallion (FR) | I11: Langley, Taryn | J11: Knight, Miss H C | K11: 10 | L11: 70 | M11: 7 | N11: 508 | O11: 10 | P11: 43.218903 | Q11: 0.023138024 | R11: 26 | S11: =IF(AND(ISNUMBER(R11),R11>1,P11>0),R11/P11-1,"") -> -0.39841139 | T11: =IF(AND(ISNUMBER(P11),P11>0),P11*EXP('Read me'!$B$22),"") -> 52.787687
A12: 2:02 | B12: Bath | C12: JDL Consultants Ltd Apprentice Handicap | D12: Class 5 | E12: 10 | F12: Good To Firm | G12: 11 | H12: Arcadian Nights | I12: Regan, Hope | J12: Loughnane, Daniel Mark | K12: 9 | L12: 72 | M12: 8 | N12: 26 | O12: 11 | P12: 44.295637 | Q12: 0.022575587 | R12: 51 | S12: =IF(AND(ISNUMBER(R12),R12>1,P12>0),R12/P12-1,"") -> 0.15135492 | T12: =IF(AND(ISNUMBER(P12),P12>0),P12*EXP('Read me'!$B$22),"") -> 54.102814
A13: 2:32 | B13: Bath | C13: MJ Church Handicap | D13: Class 5 | E13: 13 | F13: Good To Firm | G13: 13 | H13: Cosmo Brown (IRE) | I13: Edmunds, Lewis | J13: Muir, W R & Grassick, C | K13: 13 | L13: 69 | M13: 3 | N13: 34 | O13: 1 | P13: 6.0547482 | Q13: 0.16515963 | R13: 6 | S13: =IF(AND(ISNUMBER(R13),R13>1,P13>0),R13/P13-1,"") -> -0.0090421993 | T13: =IF(AND(ISNUMBER(P13),P13>0),P13*EXP('Read me'!$B$22),"") -> 7.3952862
A14: 2:32 | B14: Bath | C14: MJ Church Handicap | D14: Class 5 | E14: 13 | F14: Good To Firm | G14: 13 | H14: Zarco | I14: Cosgrave, Pat | J14: Eustace, Harry | K14: 14 | L14: 67 | M14: 3 | N14: 17 | O14: 2 | P14: 7.0423239 | Q14: 0.14199858 | R14: 6.5 | S14: =IF(AND(ISNUMBER(R14),R14>1,P14>0),R14/P14-1,"") -> -0.07700923 | T14: =IF(AND(ISNUMBER(P14),P14>0),P14*EXP('Read me'!$B$22),"") -> 8.6015139
A15: 2:32 | B15: Bath | C15: MJ Church Handicap | D15: Class 5 | E15: 13 | F15: Good To Firm | G15: 13 | H15: Moab (IRE) | I15: Marquand, Tom | J15: Knight, Miss H C | K15: 6 | L15: 62 | M15: 6 | N15: 23 | O15: 3 | P15: 7.2670325 | Q15: 0.13760775 | R15: 7 | S15: =IF(AND(ISNUMBER(R15),R15>1,P15>0),R15/P15-1,"") -> -0.036745743 | T15: =IF(AND(ISNUMBER(P15),P15>0),P15*EXP('Read me'!$B$22),"") -> 8.8759735
A16: 2:32 | B16: Bath | C16: MJ Church Handicap | D16: Class 5 | E16: 13 | F16: Good To Firm | G16: 13 | H16: Society Girl | I16: Shoemark, Kieran | J16: Walker, Ed | K16: 1 | L16: 70 | M16: 3 | N16: 40 | O16: 4 | P16: 8.0548454 | Q16: 0.12414888 | R16: 7 | S16: =IF(AND(ISNUMBER(R16),R16>1,P16>0),R16/P16-1,"") -> -0.13095787 | T16: =IF(AND(ISNUMBER(P16),P16>0),P16*EXP('Read me'!$B$22),"") -> 9.8382104
A17: 2:32 | B17: Bath | C17: MJ Church Handicap | D17: Class 5 | E17: 13 | F17: Good To Firm | G17: 13 | H17: Percy Jones | I17: Fisher, Taylor | J17: Loughnane, Daniel Mark | K17: 10 | L17: 70 | M17: 7 | N17: 16 | O17: 5 | P17: 11.515531 | Q17: 0.086839244 | R17: 10 | S17: =IF(AND(ISNUMBER(R17),R17>1,P17>0),R17/P17-1,"") -> -0.13160756 | T17: =IF(AND(ISNUMBER(P17),P17>0),P17*EXP('Read me'!$B$22),"") -> 14.065101
A18: 2:32 | B18: Bath | C18: MJ Church Handicap | D18: Class 5 | E18: 13 | F18: Good To Firm | G18: 13 | H18: Two Plus Two (IRE) | I18: Ryan, Rossa | J18: De Giles, Ed | K18: 7 | L18: 59 | M18: 6 | N18: 16 | O18: 6 | P18: 12.208096 | Q18: 0.081912857 | R18: 8 | S18: =IF(AND(ISNUMBER(R18),R18>1,P18>0),R18/P18-1,"") -> -0.34469715 | T18: =IF(AND(ISNUMBER(P18),P18>0),P18*EXP('Read me'!$B$22),"") -> 14.911002
A19: 2:32 | B19: Bath | C19: MJ Church Handicap | D19: Class 5 | E19: 13 | F19: Good To Firm | G19: 13 | H19: Belle Of Kt | I19: Wonnacott, Millie | J19: Moore, J S | K19: 8 | L19: 68 | M19: 5 | N19: 16 | O19: 7 | P19: 13.011534 | Q19: 0.07685489 | R19: 10 | S19: =IF(AND(ISNUMBER(R19),R19>1,P19>0),R19/P19-1,"") -> -0.2314511 | T19: =IF(AND(ISNUMBER(P19),P19>0),P19*EXP('Read me'!$B$22),"") -> 15.892323
A20: 2:32 | B20: Bath | C20: MJ Church Handicap | D20: Class 5 | E20: 13 | F20: Good To Firm | G20: 13 | H20: Hebridean Nomad | I20: Tucker, Charlie | J20: Balding, A M | K20: 5 | L20: 67 | M20: 5 | N20: 17 | O20: 8 | P20: 13.019335 | Q20: 0.076808841 | R20: 7 | S20: =IF(AND(ISNUMBER(R20),R20>1,P20>0),R20/P20-1,"") -> -0.46233812 | T20: =IF(AND(ISNUMBER(P20),P20>0),P20*EXP('Read me'!$B$22),"") -> 15.901851
... A39: 3:32 | B39: Bath | C39: British EBF Future Stayers Novice Stakes (GBB/GBBPlus Race) | D39: Class 3 | E39: 8 | F39: Good To Firm | G39: 6 | H39: Al Qayed (IRE) | I39: Marquand, Tom | J39: Haggas, W J | K39: 3 | L39: 82 | M39: 2 | N39: 21 | O39: 2 | P39: 3.7044469 | Q39: 0.26994583 | R39: 5 | S39: =IF(AND(ISNUMBER(R39),R39>1,P39>0),R39/P39-1,"") -> 0.34972917 | T39: =IF(AND(ISNUMBER(P39),P39>0),P39*EXP('Read me'!$B$22),"") -> 4.5246216
A40: 3:32 | B40: Bath | C40: British EBF Future Stayers Novice Stakes (GBB/GBBPlus Race) | D40: Class 3 | E40: 8 | F40: Good To Firm | G40: 6 | H40: Political Resident | I40: Probert, David | J40: Balding, A M | K40: 4 | L40: 0 | M40: 2 | O40: 3 | P40: 11.938033 | Q40: 0.083765895 | R40: 11 | S40: =IF(AND(ISNUMBER(R40),R40>1,P40>0),R40/P40-1,"") -> -0.078575155 | T40: =IF(AND(ISNUMBER(P40),P40>0),P40*EXP('Read me'!$B$22),"") -> 14.581146
A41: 3:32 | B41: Bath | C41: British EBF Future Stayers Novice Stakes (GBB/GBBPlus Race) | D41: Class 3 | E41: 8 | F41: Good To Firm | G41: 6 | H41: Next Best | I41: Bishop, Charles | J41: Houghton, Eve Johnson | K41: 6 | L41: 0 | M41: 2 | O41: 4 | P41: 19.001702 | Q41: 0.052626864 | R41: 21 | S41: =IF(AND(ISNUMBER(R41),R41>1,P41>0),R41/P41-1,"") -> 0.10516413 | T41: =IF(AND(ISNUMBER(P41),P41>0),P41*EXP('Read me'!$B$22),"") -> 23.208732
A42: 3:32 | B42: Bath | C42: British EBF Future Stayers Novice Stakes (GBB/GBBPlus Race) | D42: Class 3 | E42: 8 | F42: Good To Firm | G42: 6 | H42: First Class Lad | I42: Carson, William | J42: Evans, P D | K42: 5 | L42: 0 | M42: 2 | N42: 8 | O42: 5 | P42: 329.74691 | Q42: 0.0030326289 | R42: 101 | S42: =IF(AND(ISNUMBER(R42),R42>1,P42>0),R42/P42-1,"") -> -0.69370448 | T42: =IF(AND(ISNUMBER(P42),P42>0),P42*EXP('Read me'!$B$22),"") -> 402.75379
A43: 3:32 | B43: Bath | C43: British EBF Future Stayers Novice Stakes (GBB/GBBPlus Race) | D43: Class 3 | E43: 8 | F43: Good To Firm | G43: 6 | H43: Dust My Broom | I43: ONeill, K T | J43: Attwater, M J | K43: 1 | L43: 0 | M43: 2 | N43: 40 | O43: 6 | P43: 579.32652 | Q43: 0.0017261423 | R43: 201 | S43: =IF(AND(ISNUMBER(R43),R43>1,P43>0),R43/P43-1,"") -> -0.6530454 | T43: =IF(AND(ISNUMBER(P43),P43>0),P43*EXP('Read me'!$B$22),"") -> 707.59101
A44: 4:02 | B44: Bath | C44: SW Hire Handicap | D44: Class 4 | E44: 5 | F44: Good To Firm | G44: 12 | H44: Maharajas Express | I44: Probert, David | J44: Williams, Ian | K44: 8 | L44: 72 | M44: 6 | N44: 16 | O44: 1 | P44: 4.95019 | Q44: 0.20201245 | R44: 5 | S44: =IF(AND(ISNUMBER(R44),R44>1,P44>0),R44/P44-1,"") -> 0.010062239 | T44: =IF(AND(ISNUMBER(P44),P44>0),P44*EXP('Read me'!$B$22),"") -> 6.0461757
A45: 4:02 | B45: Bath | C45: SW Hire Handicap | D45: Class 4 | E45: 5 | F45: Good To Firm | G45: 12 | H45: South Shore | I45: Marquand, Tom | J45: Cowell, R M H | K45: 2 | L45: 75 | M45: 5 | N45: 32 | O45: 2 | P45: 5.2990735 | Q45: 0.18871223 | R45: 4 | S45: =IF(AND(ISNUMBER(R45),R45>1,P45>0),R45/P45-1,"") -> -0.24515107 | T45: =IF(AND(ISNUMBER(P45),P45>0),P45*EXP('Read me'!$B$22),"") -> 6.472303
A46: 4:02 | B46: Bath | C46: SW Hire Handicap | D46: Class 4 | E46: 5 | F46: Good To Firm | G46: 12 | H46: Jax Edge | I46: Mangan, Gina | J46: Mason, Christopher | K46: 3 | L46: 77 | M46: 6 | N46: 21 | O46: 3 | P46: 7.0877236 | Q46: 0.14108902 | R46: 7 | S46: =IF(AND(ISNUMBER(R46),R46>1,P46>0),R46/P46-1,"") -> -0.012376836 | T46: =IF(AND(ISNUMBER(P46),P46>0),P46*EXP('Read me'!$B$22),"") -> 8.6569651
A47: 4:02 | B47: Bath | C47: SW Hire Handicap | D47: Class 4 | E47: 5 | F47: Good To Firm | G47: 12 | H47: Toolatetonegotiate | I47: Wonnacott, Millie | J47: Hitchins, Daisy | K47: 10 | L47: 79 | M47: 4 | N47: 26 | O47: 4 | P47: 11.578193 | Q47: 0.086369265 | R47: 9.5 | S47: =IF(AND(ISNUMBER(R47),R47>1,P47>0),R47/P47-1,"") -> -0.17949198 | T47: =IF(AND(ISNUMBER(P47),P47>0),P47*EXP('Read me'!$B$22),"") -> 14.141637
A48: 4:02 | B48: Bath | C48: SW Hire Handicap | D48: Class 4 | E48: 5 | F48: Good To Firm | G48: 12 | H48: Coyy (IRE) | I48: Bishop, Charles | J48: Houghton, Eve Johnson | K48: 4 | L48: 73 | M48: 3 | N48: 39 | O48: 5 | P48: 14.27969 | Q48: 0.070029533 | R48: 11 | S48: =IF(AND(ISNUMBER(R48),R48>1,P48>0),R48/P48-1,"") -> -0.22967514 | T48: =IF(AND(ISNUMBER(P48),P48>0),P48*EXP('Read me'!$B$22),"") -> 17.441252
A49: 4:02 | B49: Bath | C49: SW Hire Handicap | D49: Class 4 | E49: 5 | F49: Good To Firm | G49: 12 | H49: Alondra | I49: ONeill, K T | J49: Dixon, Scott | K49: 6 | L49: 76 | M49: 4 | N49: 88 | O49: 6 | P49: 18.198025 | Q49: 0.054951017 | R49: 10 | S49: =IF(AND(ISNUMBER(R49),R49>1,P49>0),R49/P49-1,"") -> -0.45048983 | T49: =IF(AND(ISNUMBER(P49),P49>0),P49*EXP('Read me'!$B$22),"") -> 22.227118
A50: 4:02 | B50: Bath | C50: SW Hire Handicap | D50: Class 4 | E50: 5 | F50: Good To Firm | G50: 12 | H50: Forager | I50: Mitchell, Jack | J50: Pearce, Simon | K50: 7 | L50: 77 | M50: 4 | N50: 26 | O50: 7 | P50: 19.221198 | Q50: 0.052025894 | R50: 17 | S50: =IF(AND(ISNUMBER(R50),R50>1,P50>0),R50/P50-1,"") -> -0.1155598 | T50: =IF(AND(ISNUMBER(P50),P50>0),P50*EXP('Read me'!$B$22),"") -> 23.476824
A51: 4:02 | B51: Bath | C51: SW Hire Handicap | D51: Class 4 | E51: 5 | F51: Good To Firm | G51: 12 | H51: Carefree Dream | I51: Lewis, Ashley | J51: Moore, J S | K51: 9 | L51: 67 | M51: 3 | N51: 52 | O51: 8 | P51: 20.148845 | Q51: 0.049630637 | R51: 19 | S51: =IF(AND(ISNUMBER(R51),R51>1,P51>0),R51/P51-1,"") -> -0.057017898 | T51: =IF(AND(ISNUMBER(P51),P51>0),P51*EXP('Read me'!$B$22),"") -> 24.609855
A52: 4:02 | B52: Bath | C52: SW Hire Handicap | D52: Class 4 | E52: 5 | F52: Good To Firm | G52: 12 | H52: Brave Nation (IRE) | I52: Carson, William | J52: Attwater, M J | K52: 5 | L52: 76 | M52: 6 | N52: 32 | O52: 9 | P52: 20.554844 | Q52: 0.048650332 | R52: 15 | S52: =IF(AND(ISNUMBER(R52),R52>1,P52>0),R52/P52-1,"") -> -0.27024502 | T52: =IF(AND(ISNUMBER(P52),P52>0),P52*EXP('Read me'!$B$22),"") -> 25.105744
A53: 4:02 | B53: Bath | C53: SW Hire Handicap | D53: Class 4 | E53: 5 | F53: Good To Firm | G53: 12 | H53: Correspondence | I53: Ryan, Rossa | J53: Carroll, A W | K53: 1 | L53: 67 | M53: 4 | N53: 68 | O53: 10 | P53: 23.661214 | Q53: 0.042263258 | R53: 15 | S53: =IF(AND(ISNUMBER(R53),R53>1,P53>0),R53/P53-1,"") -> -0.36605113 | T53: =IF(AND(ISNUMBER(P53),P53>0),P53*EXP('Read me'!$B$22),"") -> 28.899872
... A55: 4:02 | B55: Bath | C55: SW Hire Handicap | D55: Class 4 | E55: 5 | F55: Good To Firm | G55: 12 | H55: Aces Wild (IRE) | I55: Langley, Taryn | J55: Wintle, A | K55: 12 | L55: 79 | M55: 7 | N55: 18 | O55: 12 | P55: 31.182908 | Q55: 0.03206885 | R55: 12 | S55: =IF(AND(ISNUMBER(R55),R55>1,P55>0),R55/P55-1,"") -> -0.6151738 | T55: =IF(AND(ISNUMBER(P55),P55>0),P55*EXP('Read me'!$B$22),"") -> 38.08689
A56: 4:35 | B56: Bath | C56: Power Logistics Nursery | D56: Class 6 | F56: Good To Firm | G56: 12 | H56: Past Passion | I56: Hornby, Rob | J56: Portman, J G | K56: 2 | L56: 64 | M56: 2 | N56: 22 | O56: 1 | P56: 4.6301575 | Q56: 0.21597538 | R56: 4.5 | S56: =IF(AND(ISNUMBER(R56),R56>1,P56>0),R56/P56-1,"") -> -0.028110807 | T56: =IF(AND(ISNUMBER(P56),P56>0),P56*EXP('Read me'!$B$22),"") -> 5.6552871
A57: 4:35 | B57: Bath | C57: Power Logistics Nursery | D57: Class 6 | F57: Good To Firm | G57: 12 | H57: Devon Angel | I57: Sousa, Silvestre De | J57: Millman, B R | K57: 3 | L57: 48 | M57: 2 | N57: 22 | O57: 2 | P57: 5.8406986 | Q57: 0.1712124 | R57: 5.5 | S57: =IF(AND(ISNUMBER(R57),R57>1,P57>0),R57/P57-1,"") -> -0.058331826 | T57: =IF(AND(ISNUMBER(P57),P57>0),P57*EXP('Read me'!$B$22),"") -> 7.1338454
A58: 4:35 | B58: Bath | C58: Power Logistics Nursery | D58: Class 6 | F58: Good To Firm | G58: 12 | H58: Hemustbeanangel (IRE) | I58: Leavy, Joe | J58: Teal, R A | K58: 4 | L58: 63 | M58: 2 | N58: 21 | O58: 3 | P58: 7.034904 | Q58: 0.14214835 | R58: 2.875 | S58: =IF(AND(ISNUMBER(R58),R58>1,P58>0),R58/P58-1,"") -> -0.59132349 | T58: =IF(AND(ISNUMBER(P58),P58>0),P58*EXP('Read me'!$B$22),"") -> 8.5924512
A59: 4:35 | B59: Bath | C59: Power Logistics Nursery | D59: Class 6 | F59: Good To Firm | G59: 12 | H59: Snow On The Beach | I59: Ryan, Rossa | J59: Owen, J P | K59: 10 | L59: 62 | M59: 2 | N59: 27 | O59: 4 | P59: 10.049061 | Q59: 0.099511786 | R59: 6 | S59: =IF(AND(ISNUMBER(R59),R59>1,P59>0),R59/P59-1,"") -> -0.40292928 | T59: =IF(AND(ISNUMBER(P59),P59>0),P59*EXP('Read me'!$B$22),"") -> 12.273951
A60: 4:35 | B60: Bath | C60: Power Logistics Nursery | D60: Class 6 | F60: Good To Firm | G60: 12 | H60: Last Dandelion | I60: Dace, Jack | J60: Williams, S C | K60: 5 | L60: 59 | M60: 2 | N60: 30 | O60: 5 | P60: 10.2113 | Q60: 0.097930721 | R60: 19 | S60: =IF(AND(ISNUMBER(R60),R60>1,P60>0),R60/P60-1,"") -> 0.8606837 | T60: =IF(AND(ISNUMBER(P60),P60>0),P60*EXP('Read me'!$B$22),"") -> 12.47211
A61: 4:35 | B61: Bath | C61: Power Logistics Nursery | D61: Class 6 | F61: Good To Firm | G61: 12 | H61: Polly The Sniper | I61: Cox, William | J61: Dascombe, Tom | K61: 9 | L61: 62 | M61: 2 | N61: 12 | O61: 6 | P61: 15.761779 | Q61: 0.063444614 | R61: 11 | S61: =IF(AND(ISNUMBER(R61),R61>1,P61>0),R61/P61-1,"") -> -0.30210924 | T61: =IF(AND(ISNUMBER(P61),P61>0),P61*EXP('Read me'!$B$22),"") -> 19.251481
A62: 4:35 | B62: Bath | C62: Power Logistics Nursery | D62: Class 6 | F62: Good To Firm | G62: 12 | H62: So Tempting | I62: Lewis, Ashley | J62: Ward, Tom | K62: 6 | L62: 50 | M62: 2 | N62: 22 | O62: 7 | P62: 17.113859 | Q62: 0.058432176 | R62: 12 | S62: =IF(AND(ISNUMBER(R62),R62>1,P62>0),R62/P62-1,"") -> -0.29881389 | T62: =IF(AND(ISNUMBER(P62),P62>0),P62*EXP('Read me'!$B$22),"") -> 20.902914
A63: 4:35 | B63: Bath | C63: Power Logistics Nursery | D63: Class 6 | F63: Good To Firm | G63: 12 | H63: Good Fighter | I63: Tubb, Olivia | J63: Mohammed, Ismail | K63: 7 | L63: 46 | M63: 2 | N63: 22 | O63: 8 | P63: 17.435903 | Q63: 0.057352923 | R63: 26 | S63: =IF(AND(ISNUMBER(R63),R63>1,P63>0),R63/P63-1,"") -> 0.491176 | T63: =IF(AND(ISNUMBER(P63),P63>0),P63*EXP('Read me'!$B$22),"") -> 21.29626
A64: 4:35 | B64: Bath | C64: Power Logistics Nursery | D64: Class 6 | F64: Good To Firm | G64: 12 | H64: Premium Seat | I64: Fisher, Taylor | J64: Moore, J S | K64: 8 | L64: 61 | M64: 2 | N64: 14 | O64: 9 | P64: 22.488232 | Q64: 0.044467703 | R64: 23 | S64: =IF(AND(ISNUMBER(R64),R64>1,P64>0),R64/P64-1,"") -> 0.022757168 | T64: =IF(AND(ISNUMBER(P64),P64>0),P64*EXP('Read me'!$B$22),"") -> 27.467188
A65: 4:35 | B65: Bath | C65: Power Logistics Nursery | D65: Class 6 | F65: Good To Firm | G65: 12 | H65: Its A Dream | I65: Ffrench Davis, Ben | J65: Davis, D J S Ffrench | K65: 12 | L65: 52 | M65: 2 | N65: 42 | O65: 10 | P65: 41.001259 | Q65: 0.024389495 | R65: 41 | S65: =IF(AND(ISNUMBER(R65),R65>1,P65>0),R65/P65-1,"") -> -3.0715783e-05 | T65: =IF(AND(ISNUMBER(P65),P65>0),P65*EXP('Read me'!$B$22),"") -> 50.079051
A66: 4:35 | B66: Bath | C66: Power Logistics Nursery | D66: Class 6 | F66: Good To Firm | G66: 12 | H66: Courseyoudo (FR) | I66: Bishop, Charles | J66: Lacey, T | K66: 11 | L66: 61 | M66: 2 | N66: 29 | O66: 11 | P66: 59.579065 | Q66: 0.016784419 | R66: 34 | S66: =IF(AND(ISNUMBER(R66),R66>1,P66>0),R66/P66-1,"") -> -0.42932975 | T66: =IF(AND(ISNUMBER(P66),P66>0),P66*EXP('Read me'!$B$22),"") -> 72.770034
A67: 4:35 | B67: Bath | C67: Power Logistics Nursery | D67: Class 6 | F67: Good To Firm | G67: 12 | H67: Foxsbrush | I67: Bond, Alice | J67: Ryan, J | K67: 1 | L67: 45 | M67: 2 | N67: 29 | O67: 12 | P67: 119.75989 | Q67: 0.0083500407 | R67: 51 | S67: =IF(AND(ISNUMBER(R67),R67>1,P67>0),R67/P67-1,"") -> -0.57414792 | T67: =IF(AND(ISNUMBER(P67),P67>0),P67*EXP('Read me'!$B$22),"") -> 146.27507
... A86: 5:37 | B86: Bath | C86: Clyde And Co Handicap (Div 2) | D86: Class 5 | F86: Good To Firm | G86: 9 | H86: Savannah Smiles (IRE) | I86: Lewis, Ashley | J86: Harris, Miss G | K86: 5 | L86: 61 | M86: 6 | N86: 29 | O86: 9 | P86: 32.483617 | Q86: 0.030784749 | R86: 34 | S86: =IF(AND(ISNUMBER(R86),R86>1,P86>0),R86/P86-1,"") -> 0.046681478 | T86: =IF(AND(ISNUMBER(P86),P86>0),P86*EXP('Read me'!$B$22),"") -> 39.675579

Sheet Ayr
A1: Time | B1: Course | C1: Race | D1: Class | E1: Furlongs | F1: Going | G1: Runners | H1: Horse | I1: Jockey | J1: Trainer | K1: Draw | L1: OR | M1: Age | N1: Days since run | O1: Model rank | P1: Predicted BSP | Q1: Win probability | R1: Card odds (HRB) | S1: Card odds vs model | T1: Rule: back at Betfair ≥
A2: 2:08 | B2: Ayr | C2: Christmas Party Day Dancing At Ayr Racecourse Apprentice Handicap | D2: Class 5 | E2: 8 | F2: Heavy | G2: 8 | H2: Empirestateofmind (IRE) | I2: Callan, Jack | J2: Quinn, J J | K2: 2 | L2: 71 | M2: 8 | N2: 9 | O2: 1 | P2: 3.2135037 | Q2: 0.31118682 | R2: 2.75 | S2: =IF(AND(ISNUMBER(R2),R2>1,P2>0),R2/P2-1,"") -> -0.14423624 | T2: =IF(AND(ISNUMBER(P2),P2>0),P2*EXP('Read me'!$B$22),"") -> 3.9249823
A3: 2:08 | B3: Ayr | C3: Christmas Party Day Dancing At Ayr Racecourse Apprentice Handicap | D3: Class 5 | E3: 8 | F3: Heavy | G3: 8 | H3: Motawaared | I3: Young, Lauren | J3: Goldie, J S | K3: 3 | L3: 60 | M3: 4 | N3: 9 | O3: 2 | P3: 5.1649624 | Q3: 0.19361225 | R3: 3.75 | S3: =IF(AND(ISNUMBER(R3),R3>1,P3>0),R3/P3-1,"") -> -0.27395405 | T3: =IF(AND(ISNUMBER(P3),P3>0),P3*EXP('Read me'!$B$22),"") -> 6.3084993
A4: 2:08 | B4: Ayr | C4: Christmas Party Day Dancing At Ayr Racecourse Apprentice Handicap | D4: Class 5 | E4: 8 | F4: Heavy | G4: 8 | H4: Penelopes Sister (IRE) | I4: Farmer, Shay | J4: Goldie, J S | K4: 6 | L4: 57 | M4: 6 | N4: 11 | O4: 3 | P4: 7.8295143 | Q4: 0.12772184 | R4: 5 | S4: =IF(AND(ISNUMBER(R4),R4>1,P4>0),R4/P4-1,"") -> -0.36139078 | T4: =IF(AND(ISNUMBER(P4),P4>0),P4*EXP('Read me'!$B$22),"") -> 9.5629903
A5: 2:08 | B5: Ayr | C5: Christmas Party Day Dancing At Ayr Racecourse Apprentice Handicap | D5: Class 5 | E5: 8 | F5: Heavy | G5: 8 | H5: Leopards Rock | I5: Horgan, C | J5: Bethell, Ed | K5: 8 | L5: 72 | M5: 3 | N5: 20 | O5: 4 | P5: 9.9009327 | Q5: 0.10100059 | R5: 7.5 | S5: =IF(AND(ISNUMBER(R5),R5>1,P5>0),R5/P5-1,"") -> -0.24249561 | T5: =IF(AND(ISNUMBER(P5),P5>0),P5*EXP('Read me'!$B$22),"") -> 12.093026
A6: 2:08 | B6: Ayr | C6: Christmas Party Day Dancing At Ayr Racecourse Apprentice Handicap | D6: Class 5 | E6: 8 | F6: Heavy | G6: 8 | H6: Kindest Nation (IRE) | I6: Nicholls, Jack | J6: Palmer, Hugo | K6: 5 | L6: 69 | M6: 5 | N6: 17 | O6: 5 | P6: 11.509629 | Q6: 0.086883773 | R6: 26 | S6: =IF(AND(ISNUMBER(R6),R6>1,P6>0),R6/P6-1,"") -> 1.2589781 | T6: =IF(AND(ISNUMBER(P6),P6>0),P6*EXP('Read me'!$B$22),"") -> 14.057893
A7: 2:08 | B7: Ayr | C7: Christmas Party Day Dancing At Ayr Racecourse Apprentice Handicap | D7: Class 5 | E7: 8 | F7: Heavy | G7: 8 | H7: Swift Salian (IRE) | I7: Pyle, William | J7: Barron, T D | K7: 1 | L7: 72 | M7: 5 | N7: 20 | O7: 6 | P7: 12.682362 | Q7: 0.078849665 | R7: 13 | S7: =IF(AND(ISNUMBER(R7),R7>1,P7>0),R7/P7-1,"") -> 0.02504565 | T7: =IF(AND(ISNUMBER(P7),P7>0),P7*EXP('Read me'!$B$22),"") -> 15.490272
A8: 2:08 | B8: Ayr | C8: Christmas Party Day Dancing At Ayr Racecourse Apprentice Handicap | D8: Class 5 | E8: 8 | F8: Heavy | G8: 8 | H8: Runninsonofagun (IRE) | I8: Jary, Alex | J8: Davidson, Tristan | K8: 4 | L8: 70 | M8: 4 | N8: 12 | O8: 7 | P8: 13.851606 | Q8: 0.072193794 | R8: 19 | S8: =IF(AND(ISNUMBER(R8),R8>1,P8>0),R8/P8-1,"") -> 0.3716821 | T8: =IF(AND(ISNUMBER(P8),P8>0),P8*EXP('Read me'!$B$22),"") -> 16.91839
A9: 2:08 | B9: Ayr | C9: Christmas Party Day Dancing At Ayr Racecourse Apprentice Handicap | D9: Class 5 | E9: 8 | F9: Heavy | G9: 8 | H9: Arkenstaar | I9: Elliott, Rhys | J9: Dods, M | K9: 7 | L9: 69 | M9: 6 | N9: 20 | O9: 8 | P9: 35.024721 | Q9: 0.028551262 | R9: 23 | S9: =IF(AND(ISNUMBER(R9),R9>1,P9>0),R9/P9-1,"") -> -0.34332097 | T9: =IF(AND(ISNUMBER(P9),P9>0),P9*EXP('Read me'!$B$22),"") -> 42.779291
A10: 2:38 | B10: Ayr | C10: Weddings At Western House Hotel Maiden Stakes (GBB Race) | D10: Class 4 | E10: 6 | F10: Heavy | G10: 6 | H10: Melody Man | I10: Hart, Jason | J10: Quinn, J J | K10: 2 | L10: 0 | M10: 2 | N10: 46 | O10: 1 | P10: 3.0885181 | Q10: 0.32377987 | R10: 7 | S10: =IF(AND(ISNUMBER(R10),R10>1,P10>0),R10/P10-1,"") -> 1.2664591 | T10: =IF(AND(ISNUMBER(P10),P10>0),P10*EXP('Read me'!$B$22),"") -> 3.7723246
A11: 2:38 | B11: Ayr | C11: Weddings At Western House Hotel Maiden Stakes (GBB Race) | D11: Class 4 | E11: 6 | F11: Heavy | G11: 6 | H11: What A Girl Wants (IRE) | I11: Scott, Rowan | J11: Tinkler, N | K11: 6 | L11: 75 | M11: 2 | N11: 12 | O11: 2 | P11: 3.9448211 | Q11: 0.25349692 | R11: 3 | S11: =IF(AND(ISNUMBER(R11),R11>1,P11>0),R11/P11-1,"") -> -0.23950924 | T11: =IF(AND(ISNUMBER(P11),P11>0),P11*EXP('Read me'!$B$22),"") -> 4.8182154
A12: 2:38 | B12: Ayr | C12: Weddings At Western House Hotel Maiden Stakes (GBB Race) | D12: Class 4 | E12: 6 | F12: Heavy | G12: 6 | H12: Naval Architect (IRE) | I12: Sheehy, M P | J12: Keatley, Adrian Paul | K12: 4 | L12: 0 | M12: 2 | O12: 3 | P12: 4.4823551 | Q12: 0.223097 | R12: 2 | S12: =IF(AND(ISNUMBER(R12),R12>1,P12>0),R12/P12-1,"") -> -0.55380599 | T12: =IF(AND(ISNUMBER(P12),P12>0),P12*EXP('Read me'!$B$22),"") -> 5.4747609
A13: 2:38 | B13: Ayr | C13: Weddings At Western House Hotel Maiden Stakes (GBB Race) | D13: Class 4 | E13: 6 | F13: Heavy | G13: 6 | H13: Luna Lacy (IRE) | I13: Garritty, Jack | J13: Nicholls, Adrian | K13: 3 | L13: 0 | M13: 2 | N13: 17 | O13: 4 | P13: 5.3339501 | Q13: 0.18747832 | R13: 8 | S13: =IF(AND(ISNUMBER(R13),R13>1,P13>0),R13/P13-1,"") -> 0.49982656 | T13: =IF(AND(ISNUMBER(P13),P13>0),P13*EXP('Read me'!$B$22),"") -> 6.5149014
A14: 2:38 | B14: Ayr | C14: Weddings At Western House Hotel Maiden Stakes (GBB Race) | D14: Class 4 | E14: 6 | F14: Heavy | G14: 6 | H14: Pirates Whisper (IRE) | I14: Elliott, Rhys | J14: Smith, R Michael | K14: 5 | L14: 0 | M14: 2 | N14: 17 | O14: 5 | P14: 135.75723 | Q14: 0.0073660902 | R14: 41 | S14: =IF(AND(ISNUMBER(R14),R14>1,P14>0),R14/P14-1,"") -> -0.6979903 | T14: =IF(AND(ISNUMBER(P14),P14>0),P14*EXP('Read me'!$B$22),"") -> 165.81425
A15: 2:38 | B15: Ayr | C15: Weddings At Western House Hotel Maiden Stakes (GBB Race) | D15: Class 4 | E15: 6 | F15: Heavy | G15: 6 | H15: Sneakin Pete | I15: Mullen, Andrew | J15: Smith, R Michael | K15: 1 | L15: 0 | M15: 2 | N15: 27 | O15: 6 | P15: 209.12641 | Q15: 0.0047817969 | R15: 101 | S15: =IF(AND(ISNUMBER(R15),R15>1,P15>0),R15/P15-1,"") -> -0.51703851 | T15: =IF(AND(ISNUMBER(P15),P15>0),P15*EXP('Read me'!$B$22),"") -> 255.42757
A16: 3:08 | B16: Ayr | C16: Nairnss Oatcakes Handicap (GBBPlus Race) | D16: Class 4 | E16: 10 | F16: Heavy | G16: 9 | H16: Star Cast | I16: Dickson, Jake | J16: Tutty, Gemma | K16: 7 | L16: 80 | M16: 4 | N16: 17 | O16: 1 | P16: 5.2588233 | Q16: 0.19015661 | R16: 4 | S16: =IF(AND(ISNUMBER(R16),R16>1,P16>0),R16/P16-1,"") -> -0.23937357 | T16: =IF(AND(ISNUMBER(P16),P16>0),P16*EXP('Read me'!$B$22),"") -> 6.4231413
A17: 3:08 | B17: Ayr | C17: Nairnss Oatcakes Handicap (GBBPlus Race) | D17: Class 4 | E17: 10 | F17: Heavy | G17: 9 | H17: Keep An Eye On It | I17: Nolan, D | J17: Coyle, Tony | K17: 1 | L17: 76 | M17: 3 | N17: 41 | O17: 2 | P17: 5.3288144 | Q17: 0.187659 | R17: 5 | S17: =IF(AND(ISNUMBER(R17),R17>1,P17>0),R17/P17-1,"") -> -0.061704988 | T17: =IF(AND(ISNUMBER(P17),P17>0),P17*EXP('Read me'!$B$22),"") -> 6.5086286
A18: 3:08 | B18: Ayr | C18: Nairnss Oatcakes Handicap (GBBPlus Race) | D18: Class 4 | E18: 10 | F18: Heavy | G18: 9 | H18: Mehmas Champion (IRE) | I18: Tudhope, Daniel | J18: OMeara, D | K18: 3 | L18: 80 | M18: 4 | N18: 26 | O18: 3 | P18: 6.2505337 | Q18: 0.15998634 | R18: 7 | S18: =IF(AND(ISNUMBER(R18),R18>1,P18>0),R18/P18-1,"") -> 0.11990436 | T18: =IF(AND(ISNUMBER(P18),P18>0),P18*EXP('Read me'!$B$22),"") -> 7.6344192
A19: 3:08 | B19: Ayr | C19: Nairnss Oatcakes Handicap (GBBPlus Race) | D19: Class 4 | E19: 10 | F19: Heavy | G19: 9 | H19: Tipsy Tiger | I19: Gray, S A | J19: Stone, W B | K19: 8 | L19: 74 | M19: 5 | N19: 18 | O19: 4 | P19: 8.4625307 | Q19: 0.11816796 | R19: 4.3333333 | S19: =IF(AND(ISNUMBER(R19),R19>1,P19>0),R19/P19-1,"") -> -0.48793884 | T19: =IF(AND(ISNUMBER(P19),P19>0),P19*EXP('Read me'!$B$22),"") -> 10.336158
A20: 3:08 | B20: Ayr | C20: Nairnss Oatcakes Handicap (GBBPlus Race) | D20: Class 4 | E20: 10 | F20: Heavy | G20: 9 | H20: Krissy (IRE) | I20: Elliott, Rhys | J20: Goldie, J S | K20: 4 | L20: 76 | M20: 5 | N20: 9 | O20: 5 | P20: 9.9634461 | Q20: 0.10036688 | R20: 9.5 | S20: =IF(AND(ISNUMBER(R20),R20>1,P20>0),R20/P20-1,"") -> -0.04651464 | T20: =IF(AND(ISNUMBER(P20),P20>0),P20*EXP('Read me'!$B$22),"") -> 12.169381
A21: 3:08 | B21: Ayr | C21: Nairnss Oatcakes Handicap (GBBPlus Race) | D21: Class 4 | E21: 10 | F21: Heavy | G21: 9 | H21: Zowal (FR) | I21: Hart, Jason | J21: Quinn, J J | K21: 2 | L21: 75 | M21: 4 | N21: 12 | O21: 6 | P21: 11.175479 | Q21: 0.089481625 | R21: 13 | S21: =IF(AND(ISNUMBER(R21),R21>1,P21>0),R21/P21-1,"") -> 0.16326112 | T21: =IF(AND(ISNUMBER(P21),P21>0),P21*EXP('Read me'!$B$22),"") -> 13.649761
A22: 3:08 | B22: Ayr | C22: Nairnss Oatcakes Handicap (GBBPlus Race) | D22: Class 4 | E22: 10 | F22: Heavy | G22: 9 | H22: Kokanee (IRE) | I22: Scott, Rowan | J22: Dunlop, E A L | K22: 5 | L22: 76 | M22: 4 | N22: 14 | O22: 7 | P22: 17.247344 | Q22: 0.057979943 | R22: 12 | S22: =IF(AND(ISNUMBER(R22),R22>1,P22>0),R22/P22-1,"") -> -0.30424068 | T22: =IF(AND(ISNUMBER(P22),P22>0),P22*EXP('Read me'!$B$22),"") -> 21.065953
A23: 3:08 | B23: Ayr | C23: Nairnss Oatcakes Handicap (GBBPlus Race) | D23: Class 4 | E23: 10 | F23: Heavy | G23: 9 | H23: Mano Chicago (IRE) | I23: Mullen, Andrew | J23: Jardine, I | K23: 6 | L23: 78 | M23: 4 | N23: 17 | O23: 8 | P23: 17.745205 | Q23: 0.056353251 | R23: 15 | S23: =IF(AND(ISNUMBER(R23),R23>1,P23>0),R23/P23-1,"") -> -0.15470124 | T23: =IF(AND(ISNUMBER(P23),P23>0),P23*EXP('Read me'!$B$22),"") -> 21.674043
A24: 3:08 | B24: Ayr | C24: Nairnss Oatcakes Handicap (GBBPlus Race) | D24: Class 4 | E24: 10 | F24: Heavy | G24: 9 | H24: Yermanthere (IRE) | I24: Allan, David | J24: Easterby, T D | K24: 9 | L24: 73 | M24: 8 | N24: 17 | O24: 9 | P24: 25.095114 | Q24: 0.039848395 | R24: 26 | S24: =IF(AND(ISNUMBER(R24),R24>1,P24>0),R24/P24-1,"") -> 0.036058262 | T24: =IF(AND(ISNUMBER(P24),P24>0),P24*EXP('Read me'!$B$22),"") -> 30.651241
... A60: 5:13 | B60: Ayr | C60: Racing TV Handicap | D60: Class 6 | E60: 15 | F60: Heavy | G60: 7 | H60: Speechman (USA) | I60: Marshall, Tom Kiely | J60: Kirby, P A | K60: 4 | L60: 45 | M60: 6 | N60: 33 | O60: 7 | P60: 51.329229 | Q60: 0.019482077 | R60: 51 | S60: =IF(AND(ISNUMBER(R60),R60>1,P60>0),R60/P60-1,"") -> -0.0064140577 | T60: =IF(AND(ISNUMBER(P60),P60>0),P60*EXP('Read me'!$B$22),"") -> 62.693661

Sheet Sedgefield
A1: Time | B1: Course | C1: Race | D1: Class | E1: Furlongs | F1: Going | G1: Runners | H1: Horse | I1: Jockey | J1: Trainer | K1: Draw | L1: OR | M1: Age | N1: Days since run | O1: Model rank | P1: Predicted BSP | Q1: Win probability | R1: Card odds (HRB) | S1: Card odds vs model | T1: Rule: back at Betfair ≥
A2: 2:15 | B2: Sedgefield | C2: Happy 96th Birthday John Conditional Jockeys Handicap Hurdle | D2: Class 5 | E2: 16.5 | F2: Good | G2: 7 | H2: Spartan Times | I2: Scott, Luke | J2: Candlish, Jennie | K2: 1 | L2: 105 | M2: 5 | N2: 10 | O2: 1 | P2: 3.3706659 | Q2: 0.29667728 | R2: 2.875 | S2: =IF(AND(ISNUMBER(R2),R2>1,P2>0),R2/P2-1,"") -> -0.14705282 | T2: =IF(AND(ISNUMBER(P2),P2>0),P2*EXP('Read me'!$B$22),"") -> 4.1169407
A3: 2:15 | B3: Sedgefield | C3: Happy 96th Birthday John Conditional Jockeys Handicap Hurdle | D3: Class 5 | E3: 16.5 | F3: Good | G3: 7 | H3: Jolie Coeur Allen (FR) | I3: Maggs, Charlie | J3: Haslam, B M R | K3: 3 | L3: 102 | M3: 7 | N3: 32 | O3: 2 | P3: 5.2106078 | Q3: 0.19191619 | R3: 4.5 | S3: =IF(AND(ISNUMBER(R3),R3>1,P3>0),R3/P3-1,"") -> -0.13637714 | T3: =IF(AND(ISNUMBER(P3),P3>0),P3*EXP('Read me'!$B$22),"") -> 6.3642507
A4: 2:15 | B4: Sedgefield | C4: Happy 96th Birthday John Conditional Jockeys Handicap Hurdle | D4: Class 5 | E4: 16.5 | F4: Good | G4: 7 | H4: Cawthorne Cracker (IRE) | I4: Smith, Ben | J4: Greenall, O / Guerriero, J | K4: 6 | L4: 83 | M4: 7 | N4: 13 | O4: 3 | P4: 5.8461996 | Q4: 0.17105129 | R4: 4.5 | S4: =IF(AND(ISNUMBER(R4),R4>1,P4>0),R4/P4-1,"") -> -0.23026918 | T4: =IF(AND(ISNUMBER(P4),P4>0),P4*EXP('Read me'!$B$22),"") -> 7.1405643
A5: 2:15 | B5: Sedgefield | C5: Happy 96th Birthday John Conditional Jockeys Handicap Hurdle | D5: Class 5 | E5: 16.5 | F5: Good | G5: 7 | H5: Alibey | I5: Keighley, Freddie | J5: Cunha, Dylan | K5: 2 | L5: 105 | M5: 4 | N5: 18 | O5: 4 | P5: 6.7247629 | Q5: 0.14870413 | R5: 11 | S5: =IF(AND(ISNUMBER(R5),R5>1,P5>0),R5/P5-1,"") -> 0.6357454 | T5: =IF(AND(ISNUMBER(P5),P5>0),P5*EXP('Read me'!$B$22),"") -> 8.213644
A6: 2:15 | B6: Sedgefield | C6: Happy 96th Birthday John Conditional Jockeys Handicap Hurdle | D6: Class 5 | E6: 16.5 | F6: Good | G6: 7 | H6: Made All | I6: Hitchen, Miss Rebecca | J6: England, Sam | K6: 5 | L6: 94 | M6: 5 | N6: 25 | O6: 5 | P6: 12.088665 | Q6: 0.08272212 | R6: 7 | S6: =IF(AND(ISNUMBER(R6),R6>1,P6>0),R6/P6-1,"") -> -0.42094516 | T6: =IF(AND(ISNUMBER(P6),P6>0),P6*EXP('Read me'!$B$22),"") -> 14.765129
A7: 2:15 | B7: Sedgefield | C7: Happy 96th Birthday John Conditional Jockeys Handicap Hurdle | D7: Class 5 | E7: 16.5 | F7: Good | G7: 7 | H7: Langton Wold (IRE) | I7: Brown, Oakley | J7: Ellison, B | K7: 4 | L7: 94 | M7: 7 | N7: 24 | O7: 6 | P7: 16.605664 | Q7: 0.060220416 | R7: 15 | S7: =IF(AND(ISNUMBER(R7),R7>1,P7>0),R7/P7-1,"") -> -0.096693757 | T7: =IF(AND(ISNUMBER(P7),P7>0),P7*EXP('Read me'!$B$22),"") -> 20.282204
A8: 2:15 | B8: Sedgefield | C8: Happy 96th Birthday John Conditional Jockeys Handicap Hurdle | D8: Class 5 | E8: 16.5 | F8: Good | G8: 7 | H8: Mr Globalist (IRE) | I8: Noreci, Leah | J8: Quinlan, Elizabeth | K8: 7 | L8: 79 | M8: 7 | N8: 15 | O8: 7 | P8: 20.530267 | Q8: 0.048708573 | R8: 21 | S8: =IF(AND(ISNUMBER(R8),R8>1,P8>0),R8/P8-1,"") -> 0.022880042 | T8: =IF(AND(ISNUMBER(P8),P8>0),P8*EXP('Read me'!$B$22),"") -> 25.075724
A9: 2:45 | B9: Sedgefield | C9: Roxyfet Sports Lounge For Private Hire Juvenile Maiden Hurdle (GBB Race) | D9: Class 4 | E9: 16.5 | F9: Good | G9: 7 | H9: Steel Raven (IRE) | I9: Hughes, Brian | J9: Keatley, Adrian Paul | K9: 4 | L9: 0 | M9: 3 | N9: 12 | O9: 1 | P9: 1.3730685 | Q9: 0.72829576 | R9: 1.6153846 | S9: =IF(AND(ISNUMBER(R9),R9>1,P9>0),R9/P9-1,"") -> 0.17647777 | T9: =IF(AND(ISNUMBER(P9),P9>0),P9*EXP('Read me'!$B$22),"") -> 1.6770697
A10: 2:45 | B10: Sedgefield | C10: Roxyfet Sports Lounge For Private Hire Juvenile Maiden Hurdle (GBB Race) | D10: Class 4 | E10: 16.5 | F10: Good | G10: 7 | H10: Jerseygeordie | I10: OBrien, P V | J10: Derham, Harry | K10: 2 | L10: 0 | M10: 3 | N10: 22 | O10: 2 | P10: 9.9272015 | Q10: 0.10073332 | R10: 4.3333333 | S10: =IF(AND(ISNUMBER(R10),R10>1,P10>0),R10/P10-1,"") -> -0.56348893 | T10: =IF(AND(ISNUMBER(P10),P10>0),P10*EXP('Read me'!$B$22),"") -> 12.125111
A11: 2:45 | B11: Sedgefield | C11: Roxyfet Sports Lounge For Private Hire Juvenile Maiden Hurdle (GBB Race) | D11: Class 4 | E11: 16.5 | F11: Good | G11: 7 | H11: Watcha Snoop (IRE) | I11: Mania, Ryan | J11: Nicol, Adam | K11: 6 | L11: 0 | M11: 3 | N11: 29 | O11: 3 | P11: 11.084038 | Q11: 0.090219829 | R11: 10 | S11: =IF(AND(ISNUMBER(R11),R11>1,P11>0),R11/P11-1,"") -> -0.097801707 | T11: =IF(AND(ISNUMBER(P11),P11>0),P11*EXP('Read me'!$B$22),"") -> 13.538074
A12: 2:45 | B12: Sedgefield | C12: Roxyfet Sports Lounge For Private Hire Juvenile Maiden Hurdle (GBB Race) | D12: Class 4 | E12: 16.5 | F12: Good | G12: 7 | H12: Time Twister | I12: Hamilton, Jamie | J12: Easterby, M W | K12: 5 | L12: 0 | M12: 3 | N12: 15 | O12: 4 | P12: 31.209913 | Q12: 0.032041102 | R12: 15 | S12: =IF(AND(ISNUMBER(R12),R12>1,P12>0),R12/P12-1,"") -> -0.51938347 | T12: =IF(AND(ISNUMBER(P12),P12>0),P12*EXP('Read me'!$B$22),"") -> 38.119873
A13: 2:45 | B13: Sedgefield | C13: Roxyfet Sports Lounge For Private Hire Juvenile Maiden Hurdle (GBB Race) | D13: Class 4 | E13: 16.5 | F13: Good | G13: 7 | H13: Al Khawaaneej (IRE) | I13: Gillard, Theo | J13: McCain Jnr, D | K13: 1 | L13: 0 | M13: 3 | N13: 330 | O13: 5 | P13: 31.440401 | Q13: 0.03180621 | R13: 15 | S13: =IF(AND(ISNUMBER(R13),R13>1,P13>0),R13/P13-1,"") -> -0.52290685 | T13: =IF(AND(ISNUMBER(P13),P13>0),P13*EXP('Read me'!$B$22),"") -> 38.401393
... A34: 4:45 | B34: Sedgefield | C34: Fairlight Studios Cafe At Sedgefield Racecourse Open NH Flat Race (GBB Race) | D34: Class 4 | E34: 16.5 | F34: Good | G34: 3 | H34: Close House (IRE) | I34: McMenamin, Daniel | J34: Grant, C | K34: 1 | L34: 0 | M34: 5 | N34: 164 | O34: 2 | P34: 3.2014926 | Q34: 0.3123543 | R34: 1.9090909 | S34: =IF(AND(ISNUMBER(R34),R34>1,P34>0),R34/P34-1,"") -> -0.40368724 | T34: =IF(AND(ISNUMBER(P34),P34>0),P34*EXP('Read me'!$B$22),"") -> 3.9103119
A35: 4:45 | B35: Sedgefield | C35: Fairlight Studios Cafe At Sedgefield Racecourse Open NH Flat Race (GBB Race) | D35: Class 4 | E35: 16.5 | F35: Good | G35: 3 | H35: Rescheduled | I35: Gillard, Theo | J35: McCain Jnr, D | K35: 3 | L35: 0 | M35: 4 | O35: 3 | P35: 9.4895152 | Q35: 0.10537946 | R35: 6 | S35: =IF(AND(ISNUMBER(R35),R35>1,P35>0),R35/P35-1,"") -> -0.36772323 | T35: =IF(AND(ISNUMBER(P35),P35>0),P35*EXP('Read me'!$B$22),"") -> 11.59052

Sheet Wolverhampton
A1: Time | B1: Course | C1: Race | D1: Class | E1: Furlongs | F1: Going | G1: Runners | H1: Horse | I1: Jockey | J1: Trainer | K1: Draw | L1: OR | M1: Age | N1: Days since run | O1: Model rank | P1: Predicted BSP | Q1: Win probability | R1: Card odds (HRB) | S1: Card odds vs model | T1: Rule: back at Betfair ≥
A2: 4:30 | B2: Wolverhampton | C2: Hotel & Conferencing At Wolverhampton Handicap | D2: Class 6 | E2: 9.5 | F2: Standard | G2: 13 | H2: Manton Road | I2: Fox, Kieren | J2: Phillips, R T | K2: 5 | L2: 54 | M2: 4 | N2: 14 | O2: 1 | P2: 6.3384349 | Q2: 0.15776765 | R2: 4 | S2: =IF(AND(ISNUMBER(R2),R2>1,P2>0),R2/P2-1,"") -> -0.36892938 | T2: =IF(AND(ISNUMBER(P2),P2>0),P2*EXP('Read me'!$B$22),"") -> 7.7417818
A3: 4:30 | B3: Wolverhampton | C3: Hotel & Conferencing At Wolverhampton Handicap | D3: Class 6 | E3: 9.5 | F3: Standard | G3: 13 | H3: Love You More | I3: Loughnane, Billy | J3: Parr, Joseph | K3: 13 | L3: 52 | M3: 4 | N3: 13 | O3: 2 | P3: 8.5712595 | Q3: 0.11666897 | R3: 6.5 | S3: =IF(AND(ISNUMBER(R3),R3>1,P3>0),R3/P3-1,"") -> -0.24165171 | T3: =IF(AND(ISNUMBER(P3),P3>0),P3*EXP('Read me'!$B$22),"") -> 10.46896
A4: 4:30 | B4: Wolverhampton | C4: Hotel & Conferencing At Wolverhampton Handicap | D4: Class 6 | E4: 9.5 | F4: Standard | G4: 13 | H4: Read All About It | I4: Crouch, Hector | J4: Muir, W R & Grassick, C | K4: 11 | L4: 49 | M4: 4 | N4: 51 | O4: 3 | P4: 8.7366873 | Q4: 0.11445986 | R4: 8 | S4: =IF(AND(ISNUMBER(R4),R4>1,P4>0),R4/P4-1,"") -> -0.084321121 | T4: =IF(AND(ISNUMBER(P4),P4>0),P4*EXP('Read me'!$B$22),"") -> 10.671014
A5: 4:30 | B5: Wolverhampton | C5: Hotel & Conferencing At Wolverhampton Handicap | D5: Class 6 | E5: 9.5 | F5: Standard | G5: 13 | H5: Its A Love Thing | I5: Peate, Jonny | J5: England, Sam | K5: 10 | L5: 55 | M5: 8 | N5: 27 | O5: 4 | P5: 10.227544 | Q5: 0.097775184 | R5: 7.5 | S5: =IF(AND(ISNUMBER(R5),R5>1,P5>0),R5/P5-1,"") -> -0.26668612 | T5: =IF(AND(ISNUMBER(P5),P5>0),P5*EXP('Read me'!$B$22),"") -> 12.49195
A6: 4:30 | B6: Wolverhampton | C6: Hotel & Conferencing At Wolverhampton Handicap | D6: Class 6 | E6: 9.5 | F6: Standard | G6: 13 | H6: Henfield | I6: Havlin, Robert | J6: Jewell, Karen | K6: 12 | L6: 51 | M6: 3 | N6: 17 | O6: 5 | P6: 11.102377 | Q6: 0.090070799 | R6: 5.5 | S6: =IF(AND(ISNUMBER(R6),R6>1,P6>0),R6/P6-1,"") -> -0.5046106 | T6: =IF(AND(ISNUMBER(P6),P6>0),P6*EXP('Read me'!$B$22),"") -> 13.560474
A7: 4:30 | B7: Wolverhampton | C7: Hotel & Conferencing At Wolverhampton Handicap | D7: Class 6 | E7: 9.5 | F7: Standard | G7: 13 | H7: Magic Runner (GER) | I7: Sullivan, James P | J7: Carr, Mrs R A | K7: 4 | L7: 50 | M7: 4 | N7: 14 | O7: 6 | P7: 12.322109 | Q7: 0.081154941 | R7: 11 | S7: =IF(AND(ISNUMBER(R7),R7>1,P7>0),R7/P7-1,"") -> -0.10729564 | T7: =IF(AND(ISNUMBER(P7),P7>0),P7*EXP('Read me'!$B$22),"") -> 15.050257
A8: 4:30 | B8: Wolverhampton | C8: Hotel & Conferencing At Wolverhampton Handicap | D8: Class 6 | E8: 9.5 | F8: Standard | G8: 13 | H8: Rajendra | I8: Shepherd, Callum | J8: Simcock, D M | K8: 9 | L8: 50 | M8: 3 | N8: 22 | O8: 7 | P8: 12.956644 | Q8: 0.07718048 | R8: 13 | S8: =IF(AND(ISNUMBER(R8),R8>1,P8>0),R8/P8-1,"") -> 0.0033462446 | T8: =IF(AND(ISNUMBER(P8),P8>0),P8*EXP('Read me'!$B$22),"") -> 15.825281
A9: 4:30 | B9: Wolverhampton | C9: Hotel & Conferencing At Wolverhampton Handicap | D9: Class 6 | E9: 9.5 | F9: Standard | G9: 13 | H9: Marveling | I9: Lee, Clifford | J9: Evans, H J | K9: 6 | L9: 48 | M9: 3 | N9: 22 | O9: 8 | P9: 14.001695 | Q9: 0.071419923 | R9: 23 | S9: =IF(AND(ISNUMBER(R9),R9>1,P9>0),R9/P9-1,"") -> 0.64265822 | T9: =IF(AND(ISNUMBER(P9),P9>0),P9*EXP('Read me'!$B$22),"") -> 17.101709
A10: 4:30 | B10: Wolverhampton | C10: Hotel & Conferencing At Wolverhampton Handicap | D10: Class 6 | E10: 9.5 | F10: Standard | G10: 13 | H10: Implied Volatility (IRE) | I10: Wood, George | J10: Candlish, Jennie | K10: 1 | L10: 50 | M10: 4 | N10: 44 | O10: 9 | P10: 18.320132 | Q10: 0.054584759 | R10: 8.5 | S10: =IF(AND(ISNUMBER(R10),R10>1,P10>0),R10/P10-1,"") -> -0.53602955 | T10: =IF(AND(ISNUMBER(P10),P10>0),P10*EXP('Read me'!$B$22),"") -> 22.37626
A11: 4:30 | B11: Wolverhampton | C11: Hotel & Conferencing At Wolverhampton Handicap | D11: Class 6 | E11: 9.5 | F11: Standard | G11: 13 | H11: Galactic Glow (IRE) | I11: Hutchinson, Callum | J11: Tickle, J | K11: 7 | L11: 50 | M11: 9 | N11: 16 | O11: 10 | P11: 19.301806 | Q11: 0.051808623 | R11: 26 | S11: =IF(AND(ISNUMBER(R11),R11>1,P11>0),R11/P11-1,"") -> 0.34702419 | T11: =IF(AND(ISNUMBER(P11),P11>0),P11*EXP('Read me'!$B$22),"") -> 23.575279
A12: 4:30 | B12: Wolverhampton | C12: Hotel & Conferencing At Wolverhampton Handicap | D12: Class 6 | E12: 9.5 | F12: Standard | G12: 13 | H12: Lady Delila (IRE) | I12: Bradley, Paddy | J12: Morris, Patrick | K12: 2 | L12: 46 | M12: 6 | N12: 27 | O12: 11 | P12: 20.847469 | Q12: 0.047967454 | R12: 34 | S12: =IF(AND(ISNUMBER(R12),R12>1,P12>0),R12/P12-1,"") -> 0.63089344 | T12: =IF(AND(ISNUMBER(P12),P12>0),P12*EXP('Read me'!$B$22),"") -> 25.463156
A13: 4:30 | B13: Wolverhampton | C13: Hotel & Conferencing At Wolverhampton Handicap | D13: Class 6 | E13: 9.5 | F13: Standard | G13: 13 | H13: Port Noir | I13: Morris, Luke | J13: Stephens, Robert | K13: 3 | L13: 53 | M13: 9 | N13: 119 | O13: 12 | P13: 37.505425 | Q13: 0.02666281 | R13: 34 | S13: =IF(AND(ISNUMBER(R13),R13>1,P13>0),R13/P13-1,"") -> -0.093464467 | T13: =IF(AND(ISNUMBER(P13),P13>0),P13*EXP('Read me'!$B$22),"") -> 45.809229
... A23: 5:30 | B23: Wolverhampton | C23: attheraces.com/marketmovers Maiden Stakes (GBB Race) | D23: Class 4 | E23: 7 | F23: Standard | G23: 10 | H23: Gold Star Gazing (IRE) | I23: Muscutt, D | J23: Fanshawe, J R | K23: 11 | L23: 75 | M23: 3 | N23: 28 | O23: 3 | P23: 4.9114566 | Q23: 0.20360559 | R23: 5 | S23: =IF(AND(ISNUMBER(R23),R23>1,P23>0),R23/P23-1,"") -> 0.018027931 | T23: =IF(AND(ISNUMBER(P23),P23>0),P23*EXP('Read me'!$B$22),"") -> 5.9988666
A24: 5:30 | B24: Wolverhampton | C24: attheraces.com/marketmovers Maiden Stakes (GBB Race) | D24: Class 4 | E24: 7 | F24: Standard | G24: 10 | H24: Soft Landing | I24: Rawlinson, Ali | J24: Suroor, Saeed Bin | K24: 6 | L24: 0 | M24: 3 | O24: 4 | P24: 8.7964977 | Q24: 0.11368161 | R24: 4.3333333 | S24: =IF(AND(ISNUMBER(R24),R24>1,P24>0),R24/P24-1,"") -> -0.5073797 | T24: =IF(AND(ISNUMBER(P24),P24>0),P24*EXP('Read me'!$B$22),"") -> 10.744067
A25: 5:30 | B25: Wolverhampton | C25: attheraces.com/marketmovers Maiden Stakes (GBB Race) | D25: Class 4 | E25: 7 | F25: Standard | G25: 10 | H25: Missmisfortune (IRE) | I25: Fox, Kieren | J25: Pike, Charlie | K25: 5 | L25: 0 | M25: 4 | N25: 15 | O25: 5 | P25: 36.978697 | Q25: 0.027042597 | R25: 13 | S25: =IF(AND(ISNUMBER(R25),R25>1,P25>0),R25/P25-1,"") -> -0.64844624 | T25: =IF(AND(ISNUMBER(P25),P25>0),P25*EXP('Read me'!$B$22),"") -> 45.165882
A26: 5:30 | B26: Wolverhampton | C26: attheraces.com/marketmovers Maiden Stakes (GBB Race) | D26: Class 4 | E26: 7 | F26: Standard | G26: 10 | H26: Palliser | I26: Morris, Luke | J26: Watson, Archie | K26: 7 | L26: 0 | M26: 3 | N26: 34 | O26: 6 | P26: 38.105444 | Q26: 0.026242969 | R26: 51 | S26: =IF(AND(ISNUMBER(R26),R26>1,P26>0),R26/P26-1,"") -> 0.33839143 | T26: =IF(AND(ISNUMBER(P26),P26>0),P26*EXP('Read me'!$B$22),"") -> 46.542095
A27: 5:30 | B27: Wolverhampton | C27: attheraces.com/marketmovers Maiden Stakes (GBB Race) | D27: Class 4 | E27: 7 | F27: Standard | G27: 10 | H27: Byerley Lady | I27: Fallon, Cieren | J27: Williams, Ian | K27: 4 | L27: 0 | M27: 4 | O27: 7 | P27: 69.464257 | Q27: 0.014395893 | R27: 29 | S27: =IF(AND(ISNUMBER(R27),R27>1,P27>0),R27/P27-1,"") -> -0.58251911 | T27: =IF(AND(ISNUMBER(P27),P27>0),P27*EXP('Read me'!$B$22),"") -> 84.843835
A28: 5:30 | B28: Wolverhampton | C28: attheraces.com/marketmovers Maiden Stakes (GBB Race) | D28: Class 4 | E28: 7 | F28: Standard | G28: 10 | H28: Barachiel (IRE) | I28: Keenan, Darragh | J28: Stephens, Robert | K28: 2 | L28: 0 | M28: 5 | N28: 20 | O28: 8 | P28: 106.22351 | Q28: 0.0094141122 | R28: 126 | S28: =IF(AND(ISNUMBER(R28),R28>1,P28>0),R28/P28-1,"") -> 0.18617814 | T28: =IF(AND(ISNUMBER(P28),P28>0),P28*EXP('Read me'!$B$22),"") -> 129.74168
A29: 5:30 | B29: Wolverhampton | C29: attheraces.com/marketmovers Maiden Stakes (GBB Race) | D29: Class 4 | E29: 7 | F29: Standard | G29: 10 | H29: Pink Pyjamas (IRE) | I29: Lee, Clifford | J29: Chapple-Hyam, P W | K29: 3 | L29: 0 | M29: 3 | N29: 15 | O29: 9 | P29: 357.81433 | Q29: 0.0027947455 | R29: 126 | S29: =IF(AND(ISNUMBER(R29),R29>1,P29>0),R29/P29-1,"") -> -0.64786206 | T29: =IF(AND(ISNUMBER(P29),P29>0),P29*EXP('Read me'!$B$22),"") -> 437.03541
A30: 5:30 | B30: Wolverhampton | C30: attheraces.com/marketmovers Maiden Stakes (GBB Race) | D30: Class 4 | E30: 7 | F30: Standard | G30: 10 | H30: Heavens Hope | I30: Wood, George | J30: Hollinshead, Steph | K30: 10 | L30: 0 | M30: 3 | N30: 68 | O30: 10 | P30: 767.11026 | Q30: 0.0013035936 | R30: 251 | S30: =IF(AND(ISNUMBER(R30),R30>1,P30>0),R30/P30-1,"") -> -0.67279801 | T30: =IF(AND(ISNUMBER(P30),P30>0),P30*EXP('Read me'!$B$22),"") -> 936.95058
A31: 6:00 | B31: Wolverhampton | C31: Free Tips On attheraces.com Handicap | D31: Class 6 | E31: 7 | F31: Standard | G31: 10 | H31: Distillation (FR) | I31: Dawes, Rose | J31: Usher, M D I | K31: 6 | L31: 64 | M31: 3 | N31: 8 | O31: 1 | P31: 1.9555402 | Q31: 0.51136765 | R31: 2.2 | S31: =IF(AND(ISNUMBER(R31),R31>1,P31>0),R31/P31-1,"") -> 0.12500883 | T31: =IF(AND(ISNUMBER(P31),P31>0),P31*EXP('Read me'!$B$22),"") -> 2.3885022
A32: 6:00 | B32: Wolverhampton | C32: Free Tips On attheraces.com Handicap | D32: Class 6 | E32: 7 | F32: Standard | G32: 10 | H32: Dark Mandate | I32: Loughnane, Billy | J32: Houghton, Eve Johnson | K32: 2 | L32: 58 | M32: 3 | N32: 17 | O32: 2 | P32: 4.0778554 | Q32: 0.24522694 | R32: 2.5 | S32: =IF(AND(ISNUMBER(R32),R32>1,P32>0),R32/P32-1,"") -> -0.38693265 | T32: =IF(AND(ISNUMBER(P32),P32>0),P32*EXP('Read me'!$B$22),"") -> 4.9807038
A33: 6:00 | B33: Wolverhampton | C33: Free Tips On attheraces.com Handicap | D33: Class 6 | E33: 7 | F33: Standard | G33: 10 | H33: Deadline (FR) | I33: Levey, S M | J33: Greatrex, W J | K33: 7 | L33: 60 | M33: 3 | N33: 30 | O33: 3 | P33: 15.106878 | Q33: 0.066195013 | R33: 9 | S33: =IF(AND(ISNUMBER(R33),R33>1,P33>0),R33/P33-1,"") -> -0.40424488 | T33: =IF(AND(ISNUMBER(P33),P33>0),P33*EXP('Read me'!$B$22),"") -> 18.451583
A34: 6:00 | B34: Wolverhampton | C34: Free Tips On attheraces.com Handicap | D34: Class 6 | E34: 7 | F34: Standard | G34: 10 | H34: Roccobear (IRE) | I34: Lee, Clifford | J34: Jenkins, J R | K34: 8 | L34: 60 | M34: 3 | N34: 83 | O34: 4 | P34: 19.118969 | Q34: 0.052304074 | R34: 12 | S34: =IF(AND(ISNUMBER(R34),R34>1,P34>0),R34/P34-1,"") -> -0.37235111 | T34: =IF(AND(ISNUMBER(P34),P34>0),P34*EXP('Read me'!$B$22),"") -> 23.351962
A35: 6:00 | B35: Wolverhampton | C35: Free Tips On attheraces.com Handicap | D35: Class 6 | E35: 7 | F35: Standard | G35: 10 | H35: Able Astra (IRE) | I35: Crouch, Hector | J35: Cox, C G | K35: 3 | L35: 54 | M35: 3 | N35: 69 | O35: 5 | P35: 30.533735 | Q35: 0.032750661 | R35: 51 | S35: =IF(AND(ISNUMBER(R35),R35>1,P35>0),R35/P35-1,"") -> 0.6702837 | T35: =IF(AND(ISNUMBER(P35),P35>0),P35*EXP('Read me'!$B$22),"") -> 37.293988
A36: 6:00 | B36: Wolverhampton | C36: Free Tips On attheraces.com Handicap | D36: Class 6 | E36: 7 | F36: Standard | G36: 10 | H36: Caitlin G | I36: Fallon, Cieren | J36: Fenton, M P | K36: 5 | L36: 50 | M36: 3 | N36: 30 | O36: 6 | P36: 33.185389 | Q36: 0.030133744 | R36: 23 | S36: =IF(AND(ISNUMBER(R36),R36>1,P36>0),R36/P36-1,"") -> -0.30692389 | T36: =IF(AND(ISNUMBER(P36),P36>0),P36*EXP('Read me'!$B$22),"") -> 40.532725
A37: 6:00 | B37: Wolverhampton | C37: Free Tips On attheraces.com Handicap | D37: Class 6 | E37: 7 | F37: Standard | G37: 10 | H37: Sup Of Red (IRE) | I37: Keenan, Darragh | J37: Wintle, A | K37: 1 | L37: 58 | M37: 3 | N37: 36 | O37: 7 | P37: 44.761952 | Q37: 0.022340402 | R37: 26 | S37: =IF(AND(ISNUMBER(R37),R37>1,P37>0),R37/P37-1,"") -> -0.41914955 | T37: =IF(AND(ISNUMBER(P37),P37>0),P37*EXP('Read me'!$B$22),"") -> 54.672372
A38: 6:00 | B38: Wolverhampton | C38: Free Tips On attheraces.com Handicap | D38: Class 6 | E38: 7 | F38: Standard | G38: 10 | H38: Golden Mabel | I38: Morris, Luke | J38: Williamson, Mrs L | K38: 11 | L38: 54 | M38: 3 | N38: 3 | O38: 8 | P38: 45.064509 | Q38: 0.022190412 | R38: 26 | S38: =IF(AND(ISNUMBER(R38),R38>1,P38>0),R38/P38-1,"") -> -0.4230493 | T38: =IF(AND(ISNUMBER(P38),P38>0),P38*EXP('Read me'!$B$22),"") -> 55.041915
A39: 6:00 | B39: Wolverhampton | C39: Free Tips On attheraces.com Handicap | D39: Class 6 | E39: 7 | F39: Standard | G39: 10 | H39: Shes Crafty (IRE) | I39: Davies, Harry | J39: Margarson, G G | K39: 9 | L39: 47 | M39: 3 | N39: 42 | O39: 9 | P39: 67.402356 | Q39: 0.014836277 | R39: 67 | S39: =IF(AND(ISNUMBER(R39),R39>1,P39>0),R39/P39-1,"") -> -0.0059694672 | T39: =IF(AND(ISNUMBER(P39),P39>0),P39*EXP('Read me'!$B$22),"") -> 82.325424
A40: 6:00 | B40: Wolverhampton | C40: Free Tips On attheraces.com Handicap | D40: Class 6 | E40: 7 | F40: Standard | G40: 10 | H40: Independent Angel | I40: Sullivan, James P | J40: Williamson, Mrs L | K40: 4 | L40: 46 | M40: 3 | N40: 7 | O40: 10 | P40: 376.67196 | Q40: 0.0026548299 | R40: 201 | S40: =IF(AND(ISNUMBER(R40),R40>1,P40>0),R40/P40-1,"") -> -0.46637919 | T40: =IF(AND(ISNUMBER(P40),P40>0),P40*EXP('Read me'!$B$22),"") -> 460.06818
A41: 6:30 | B41: Wolverhampton | C41: Sky Sports Racing Virgin 512 EBF Novice Stakes (GBB Race) | D41: Class 4 | E41: 6 | F41: Standard | G41: 8 | H41: Oxbridge (IRE) | I41: Loughnane, Billy | J41: Boughey, George | K41: 3 | L41: 0 | M41: 2 | O41: 1 | P41: 1.9005061 | Q41: 0.52617563 | R41: 1.5333333 | S41: =IF(AND(ISNUMBER(R41),R41>1,P41>0),R41/P41-1,"") -> -0.19319736 | T41: =IF(AND(ISNUMBER(P41),P41>0),P41*EXP('Read me'!$B$22),"") -> 2.3212834
A42: 6:30 | B42: Wolverhampton | C42: Sky Sports Racing Virgin 512 EBF Novice Stakes (GBB Race) | D42: Class 4 | E42: 6 | F42: Standard | G42: 8 | H42: Urumita (IRE) | I42: Levey, S M | J42: Hannon (Jnr), Richard | K42: 2 | L42: 0 | M42: 2 | N42: 15 | O42: 2 | P42: 5.0778133 | Q42: 0.19693516 | R42: 9.5 | S42: =IF(AND(ISNUMBER(R42),R42>1,P42>0),R42/P42-1,"") -> 0.87088406 | T42: =IF(AND(ISNUMBER(P42),P42>0),P42*EXP('Read me'!$B$22),"") -> 6.2020552
A43: 6:30 | B43: Wolverhampton | C43: Sky Sports Racing Virgin 512 EBF Novice Stakes (GBB Race) | D43: Class 4 | E43: 6 | F43: Standard | G43: 8 | H43: Gilded Call (IRE) | I43: Crouch, Hector | J43: Meehan, B J | K43: 8 | L43: 0 | M43: 2 | N43: 8 | O43: 3 | P43: 8.2034105 | Q43: 0.12190052 | R43: 4.5 | S43: =IF(AND(ISNUMBER(R43),R43>1,P43>0),R43/P43-1,"") -> -0.45144766 | T43: =IF(AND(ISNUMBER(P43),P43>0),P43*EXP('Read me'!$B$22),"") -> 10.019668
A44: 6:30 | B44: Wolverhampton | C44: Sky Sports Racing Virgin 512 EBF Novice Stakes (GBB Race) | D44: Class 4 | E44: 6 | F44: Standard | G44: 8 | H44: Nightbloom (IRE) | I44: Lee, Clifford | J44: Foy, Kevin | K44: 1 | L44: 0 | M44: 2 | N44: 67 | O44: 4 | P44: 15.776655 | Q44: 0.063384791 | R44: 8 | S44: =IF(AND(ISNUMBER(R44),R44>1,P44>0),R44/P44-1,"") -> -0.49292167 | T44: =IF(AND(ISNUMBER(P44),P44>0),P44*EXP('Read me'!$B$22),"") -> 19.26965
A45: 6:30 | B45: Wolverhampton | C45: Sky Sports Racing Virgin 512 EBF Novice Stakes (GBB Race) | D45: Class 4 | E45: 6 | F45: Standard | G45: 8 | H45: Hidden Layers (USA) | I45: Carver, William | J45: Osborne, J A | K45: 6 | L45: 0 | M45: 2 | O45: 5 | P45: 19.715494 | Q45: 0.050721529 | R45: 15 | S45: =IF(AND(ISNUMBER(R45),R45>1,P45>0),R45/P45-1,"") -> -0.23917707 | T45: =IF(AND(ISNUMBER(P45),P45>0),P45*EXP('Read me'!$B$22),"") -> 24.080559
A46: 6:30 | B46: Wolverhampton | C46: Sky Sports Racing Virgin 512 EBF Novice Stakes (GBB Race) | D46: Class 4 | E46: 6 | F46: Standard | G46: 8 | H46: Starbolt (IRE) | I46: Havlin, Robert | J46: Dunlop, E A L | K46: 4 | L46: 0 | M46: 2 | N46: 11 | O46: 6 | P46: 36.833425 | Q46: 0.027149254 | R46: 34 | S46: =IF(AND(ISNUMBER(R46),R46>1,P46>0),R46/P46-1,"") -> -0.076925362 | T46: =IF(AND(ISNUMBER(P46),P46>0),P46*EXP('Read me'!$B$22),"") -> 44.988446
A47: 6:30 | B47: Wolverhampton | C47: Sky Sports Racing Virgin 512 EBF Novice Stakes (GBB Race) | D47: Class 4 | E47: 6 | F47: Standard | G47: 8 | H47: Goldtrader | I47: Downing, George | J47: Walker, Ed | K47: 7 | L47: 0 | M47: 2 | N47: 31 | O47: 7 | P47: 85.761823 | Q47: 0.0116602 | R47: 51 | S47: =IF(AND(ISNUMBER(R47),R47>1,P47>0),R47/P47-1,"") -> -0.40532981 | T47: =IF(AND(ISNUMBER(P47),P47>0),P47*EXP('Read me'!$B$22),"") -> 104.74973
A48: 6:30 | B48: Wolverhampton | C48: Sky Sports Racing Virgin 512 EBF Novice Stakes (GBB Race) | D48: Class 4 | E48: 6 | F48: Standard | G48: 8 | H48: Black Treasure (FR) | I48: Bowen, S D | J48: Sangster, Ollie | K48: 5 | L48: 0 | M48: 2 | N48: 14 | O48: 8 | P48: 482.41392 | Q48: 0.0020729087 | R48: 201 | S48: =IF(AND(ISNUMBER(R48),R48>1,P48>0),R48/P48-1,"") -> -0.58334536 | T48: =IF(AND(ISNUMBER(P48),P48>0),P48*EXP('Read me'!$B$22),"") -> 589.22169
A49: 7:00 | B49: Wolverhampton | C49: Race & Rest - Wolverhampton Holiday Inn Handicap | D49: Class 6 | E49: 6 | F49: Standard | G49: 11 | H49: Methgal (IRE) | I49: Levey, S M | J49: Cunha, Dylan | K49: 8 | L49: 68 | M49: 4 | N49: 6 | O49: 1 | P49: 4.1194879 | Q49: 0.24274862 | R49: 1.8333333 | S49: =IF(AND(ISNUMBER(R49),R49>1,P49>0),R49/P49-1,"") -> -0.55496086 | T49: =IF(AND(ISNUMBER(P49),P49>0),P49*EXP('Read me'!$B$22),"") -> 5.0315539
A50: 7:00 | B50: Wolverhampton | C50: Race & Rest - Wolverhampton Holiday Inn Handicap | D50: Class 6 | E50: 6 | F50: Standard | G50: 11 | H50: Rye | I50: Loughnane, Billy | J50: Carroll, A W | K50: 5 | L50: 61 | M50: 4 | N50: 28 | O50: 2 | P50: 6.0219457 | Q50: 0.16605929 | R50: 9 | S50: =IF(AND(ISNUMBER(R50),R50>1,P50>0),R50/P50-1,"") -> 0.49453358 | T50: =IF(AND(ISNUMBER(P50),P50>0),P50*EXP('Read me'!$B$22),"") -> 7.3552211
A51: 7:00 | B51: Wolverhampton | C51: Race & Rest - Wolverhampton Holiday Inn Handicap | D51: Class 6 | E51: 6 | F51: Standard | G51: 11 | H51: Trust Sergei | I51: Peate, Jonny | J51: Hanmer, G D | K51: 7 | L51: 58 | M51: 4 | N51: 8 | O51: 3 | P51: 6.0527136 | Q51: 0.16521515 | R51: 8 | S51: =IF(AND(ISNUMBER(R51),R51>1,P51>0),R51/P51-1,"") -> 0.32172122 | T51: =IF(AND(ISNUMBER(P51),P51>0),P51*EXP('Read me'!$B$22),"") -> 7.3928011
A52: 7:00 | B52: Wolverhampton | C52: Race & Rest - Wolverhampton Holiday Inn Handicap | D52: Class 6 | E52: 6 | F52: Standard | G52: 11 | H52: Molly Mac (IRE) | I52: Fallon, Cieren | J52: Fenton, M P | K52: 2 | L52: 63 | M52: 3 | N52: 13 | O52: 4 | P52: 7.2316539 | Q52: 0.13828095 | R52: 7 | S52: =IF(AND(ISNUMBER(R52),R52>1,P52>0),R52/P52-1,"") -> -0.032033316 | T52: =IF(AND(ISNUMBER(P52),P52>0),P52*EXP('Read me'!$B$22),"") -> 8.832762
A53: 7:00 | B53: Wolverhampton | C53: Race & Rest - Wolverhampton Holiday Inn Handicap | D53: Class 6 | E53: 6 | F53: Standard | G53: 11 | H53: Go Lockers Go | I53: Crouch, Hector | J53: Bell, M L W | K53: 6 | L53: 64 | M53: 3 | N53: 26 | O53: 5 | P53: 11.029055 | Q53: 0.090669601 | R53: 15 | S53: =IF(AND(ISNUMBER(R53),R53>1,P53>0),R53/P53-1,"") -> 0.36004402 | T53: =IF(AND(ISNUMBER(P53),P53>0),P53*EXP('Read me'!$B$22),"") -> 13.470918
A54: 7:00 | B54: Wolverhampton | C54: Race & Rest - Wolverhampton Holiday Inn Handicap | D54: Class 6 | E54: 6 | F54: Standard | G54: 11 | H54: Court Alert (IRE) | I54: Lee, Clifford | J54: Houghton, Eve Johnson | K54: 3 | L54: 63 | M54: 3 | N54: 21 | O54: 6 | P54: 14.848016 | Q54: 0.067349065 | R54: 15 | S54: =IF(AND(ISNUMBER(R54),R54>1,P54>0),R54/P54-1,"") -> 0.010235981 | T54: =IF(AND(ISNUMBER(P54),P54>0),P54*EXP('Read me'!$B$22),"") -> 18.135408
A55: 7:00 | B55: Wolverhampton | C55: Race & Rest - Wolverhampton Holiday Inn Handicap | D55: Class 6 | E55: 6 | F55: Standard | G55: 11 | H55: Von Krolock (IRE) | I55: Howarth, Christian | J55: Owen, J P | K55: 4 | L55: 62 | M55: 7 | N55: 12 | O55: 7 | P55: 15.215665 | Q55: 0.06572174 | R55: 17 | S55: =IF(AND(ISNUMBER(R55),R55>1,P55>0),R55/P55-1,"") -> 0.11726959 | T55: =IF(AND(ISNUMBER(P55),P55>0),P55*EXP('Read me'!$B$22),"") -> 18.584455
A56: 7:00 | B56: Wolverhampton | C56: Race & Rest - Wolverhampton Holiday Inn Handicap | D56: Class 6 | E56: 6 | F56: Standard | G56: 11 | H56: Dark Alley | I56: Morris, Luke | J56: Greatrex, W J | K56: 12 | L56: 65 | M56: 3 | N56: 32 | O56: 8 | P56: 22.699839 | Q56: 0.044053177 | R56: 34 | S56: =IF(AND(ISNUMBER(R56),R56>1,P56>0),R56/P56-1,"") -> 0.497808 | T56: =IF(AND(ISNUMBER(P56),P56>0),P56*EXP('Read me'!$B$22),"") -> 27.725646
A57: 7:00 | B57: Wolverhampton | C57: Race & Rest - Wolverhampton Holiday Inn Handicap | D57: Class 6 | E57: 6 | F57: Standard | G57: 11 | H57: Saeculamation (IRE) | I57: Sullivan, James P | J57: Mackie, J | K57: 1 | L57: 46 | M57: 3 | N57: 43 | O57: 9 | P57: 94.032497 | Q57: 0.010634621 | R57: 23 | S57: =IF(AND(ISNUMBER(R57),R57>1,P57>0),R57/P57-1,"") -> -0.75540371 | T57: =IF(AND(ISNUMBER(P57),P57>0),P57*EXP('Read me'!$B$22),"") -> 114.85155
... A86: 8:30 | B86: Wolverhampton | C86: Sky Sports Racing Sky 415 Handicap (Div 2) | D86: Class 6 | E86: 8.5 | F86: Standard | G86: 8 | H86: Hammal (IRE) | I86: Hutchinson, Callum | J86: Young, Maxwell | K86: 1 | L86: 46 | M86: 5 | N86: 34 | O86: 8 | P86: 126.70636 | Q86: 0.0078922637 | R86: 201 | S86: =IF(AND(ISNUMBER(R86),R86>1,P86>0),R86/P86-1,"") -> 0.586345 | T86: =IF(AND(ISNUMBER(P86),P86>0),P86*EXP('Read me'!$B$22),"") -> 154.7595
