Workbook

Sheet Read me
A1: Predictions for 2026-09-26
A3: Runners | B3: 575
A4: Races | B4: 53
A5: Meetings | B5: 7
A7: The model | B7: 944
A8: Features | B8: 944
A9: Trained through | B9: 2026-09-22
A10: Boosting rounds | B10: 6000
A11: Target | B11: logit_norm_prob
A12: Feature code hash | B12: f879b10c8369467a
A14: How to read it
A15: Predicted BSP | B15: The model's forecast of the Betfair Starting Price, from pre-race information only. The prices in each race make a book of exactly 100%.
A16: Win probability | B16: 1 / predicted BSP: the model's chance for the horse, normalised within the race.
A17: Model rank | B17: 1 = the model's shortest price in the race (highlighted green).
A18: Card odds (HRB) | B18: The odds printed on the horseracebase card when it was fetched: a bookmaker forecast, not the Betfair morning price the early-price rule was tested against.
A19: Card odds vs model | B19: Card odds / predicted BSP - 1. Positive: the card is longer than the model.
A21: The early-price rule
A22: Margin (log) | B22: 0.2
A23: Rule: back at Betfair ≥ | B23: Predicted BSP × e^margin: at 0.2, a Betfair price at least 1.22 times the model's (the model at least 22% shorter). The rule was fixed before it was first tested (reports/clv_betfair_2026q1.md): back at Betfair's morning volume-weighted price, where at least £100 has been matched in the morning, and close the position at BSP (lay at BSP to level the book). It is a trade on the price, not a bet held to the result. The margin (blue) is the one input: change it to see the prices at another threshold.
A25: Note | B25: The 944: the model recommended to serve from 27 Sep (reports/serving_note_2026-09-27.md), priced here by predict-now run 12 on the card fetched at 09:44 UTC (575 runners in 53 races; non-runners declared by then are out, and each race's book is 100% of those left). It is not yet the served model: the 06:00 job priced today with the 615, whose picks are on the '944 vs 615' sheet. Out of sample (Jan-Mar 2026), the 944's early-price rule returned +8.44% per trade (90% interval +7.17 to +9.82) on 4,602 trades, traded out at BSP and net of commission; its top pick traded out at BSP +1.19% (+0.44 to +1.96), and +5.18% where the rule also picks it. Held to the result, the top pick lost (-7.56% at BSP): the edge is in the price, not the result. The rule's forward test (pre-registered, from 25 Sep) has not reported yet.

Sheet Top picks
A1: Time | B1: Course | C1: Race | D1: Runners | E1: Top pick | F1: Jockey | G1: Trainer | H1: Predicted BSP | I1: Win probability | J1: Second choice | K1: Second's BSP | L1: Second's probability | M1: Probability gap | N1: Card odds (HRB) | O1: Rule: back at Betfair ≥
A2: 1:22 | B2: Newmarket (Rowley) | C2: British Stallion Studs EBF Jersey Lily Fillies Nursery | D2: 10 | E2: Al Samsama (IRE) | F2: Loughnane, Billy | G2: Hughes, Richard | H2: 5.4223912 | I2: 0.18442048 | J2: Next Of Kin | K2: 7.3693735 | L2: 0.13569675 | M2: =IF(AND(ISNUMBER(I2),ISNUMBER(L2)),I2-L2,"") -> 0.048723738 | N2: 7.5 | O2: =IF(AND(ISNUMBER(H2),H2>0),H2*EXP('Read me'!$B$22),"") -> 6.6229235
A3: 1:30 | B3: Curragh | C3: Market Square Monasterevin Irish European Breeders Fund Maiden | D3: 13 | E3: Benown (IRE) | F3: Sheridan, J M | G3: OBrien, Joseph Patrick | H3: 1.9022607 | I3: 0.52569029 | J3: Heralds March (IRE) | K3: 5.3234689 | L3: 0.18784744 | M3: =IF(AND(ISNUMBER(I3),ISNUMBER(L3)),I3-L3,"") -> 0.33784285 | N3: 1.7272727 | O3: =IF(AND(ISNUMBER(H3),H3>0),H3*EXP('Read me'!$B$22),"") -> 2.3234265
A4: 1:35 | B4: Haydock | C4: William Hill Epic Boosts Handicap | D4: 10 | E4: Eternal Force | F4: Fallon, Cieren | G4: Haggas, W J | H4: 5.2683602 | I4: 0.18981238 | J4: Centigrade (IRE) | K4: 5.8434044 | L4: 0.17113311 | M4: =IF(AND(ISNUMBER(I4),ISNUMBER(L4)),I4-L4,"") -> 0.018679269 | N4: 4.5 | O4: =IF(AND(ISNUMBER(H4),H4>0),H4*EXP('Read me'!$B$22),"") -> 6.4347896
A5: 1:44 | B5: Ripon | C5: Theakston Brewing Legends Since 1827 EBF Novice Stakes (GBB Race) | D5: 9 | E5: Scenic Route (IRE) | F5: Orr, Oisin | G5: Fahey, R A | H5: 2.1969837 | I5: 0.45516951 | J5: Bulletsnap (IRE) | K5: 2.6507783 | L5: 0.37724769 | M5: =IF(AND(ISNUMBER(I5),ISNUMBER(L5)),I5-L5,"") -> 0.077921817 | N5: 1.9090909 | O5: =IF(AND(ISNUMBER(H5),H5>0),H5*EXP('Read me'!$B$22),"") -> 2.683402
A6: 1:55 | B6: Newmarket (Rowley) | C6: Tattersalls Online Royal Lodge Stakes (Group 2) | D6: 7 | E6: Haffner (USA) | F6: Moore, Ryan | G6: OBrien, A P | H6: 4.1555937 | I6: 0.2406395 | J6: First Law (IRE) | K6: 4.324806 | L6: 0.23122425 | M6: =IF(AND(ISNUMBER(I6),ISNUMBER(L6)),I6-L6,"") -> 0.0094152549 | N6: 4.5 | O6: =IF(AND(ISNUMBER(H6),H6>0),H6*EXP('Read me'!$B$22),"") -> 5.0756537
A7: 2:00 | B7: Curragh | C7: Kwiff More Bang For Your Bet Rated Race | D7: 9 | E7: Oro Blanco (IRE) | F7: Kennedy, K G | G7: Harrington, Mrs John | H7: 4.4337459 | I7: 0.22554292 | J7: Killashee Warrior | K7: 5.0561504 | L7: 0.19777893 | M7: =IF(AND(ISNUMBER(I7),ISNUMBER(L7)),I7-L7,"") -> 0.027763992 | N7: 3.75 | O7: =IF(AND(ISNUMBER(H7),H7>0),H7*EXP('Read me'!$B$22),"") -> 5.4153895
A8: 2:10 | B8: Haydock | C8: William Hill Best Odds Guaranteed Handicap | D8: 10 | E8: Trilby | F8: McDonald, P J | G8: England, Sam | H8: 4.5888249 | I8: 0.21792071 | J8: King Of Light | K8: 4.8875045 | L8: 0.20460339 | M8: =IF(AND(ISNUMBER(I8),ISNUMBER(L8)),I8-L8,"") -> 0.013317322 | N8: 3.25 | O8: =IF(AND(ISNUMBER(H8),H8>0),H8*EXP('Read me'!$B$22),"") -> 5.6048034
A9: 2:16 | B9: Ripon | C9: Lloyd Landrover Ripon Nursery (GBBPlus Race) | D9: 6 | E9: Aphra Behn | F9: Hart, Jason | G9: Beckett, R M | H9: 3.9137923 | I9: 0.25550666 | J9: Zarakova | K9: 4.3249916 | L9: 0.23121432 | M9: =IF(AND(ISNUMBER(I9),ISNUMBER(L9)),I9-L9,"") -> 0.02429234 | N9: 2.625 | O9: =IF(AND(ISNUMBER(H9),H9>0),H9*EXP('Read me'!$B$22),"") -> 4.7803167
A10: 2:27 | B10: Newmarket (Rowley) | C10: Tattersalls Sceptre Sessions Cheveley Park Stakes (Fillies Group 1) | D10: 6 | E10: Sun Goddess (IRE) | F10: Moore, Ryan | G10: OBrien, A P | H10: 1.8278127 | I10: 0.547102 | J10: Libertango (IRE) | K10: 6.5055108 | L10: 0.15371583 | M10: =IF(AND(ISNUMBER(I10),ISNUMBER(L10)),I10-L10,"") -> 0.39338617 | N10: 2.5 | O10: =IF(AND(ISNUMBER(H10),H10>0),H10*EXP('Read me'!$B$22),"") -> 2.2324955
A11: 2:30 | B11: Market Rasen | C11: Market Rasen Racecourse Conference & Events Mares Maiden Hurdle (GBB Race) | D11: 9 | E11: Elated | F11: Jones, Ben R | G11: Pauling, Ben | H11: 1.7522701 | I11: 0.57068828 | J11: No More Teardrops | K11: 3.6316584 | L11: 0.2753563 | M11: =IF(AND(ISNUMBER(I11),ISNUMBER(L11)),I11-L11,"") -> 0.29533199 | N11: 2.2 | O11: =IF(AND(ISNUMBER(H11),H11>0),H11*EXP('Read me'!$B$22),"") -> 2.1402275
A12: 2:35 | B12: Curragh | C12: Kwiff Supercharged Joe McGrath Handicap (Premier Handicap) | D12: 20 | E12: Red Evolution (IRE) | F12: Holohan, Reese | G12: OCallaghan, M D | H12: 6.6003902 | I12: 0.15150619 | J12: Dark Ace (IRE) | K12: 8.7366641 | L12: 0.11446016 | M12: =IF(AND(ISNUMBER(I12),ISNUMBER(L12)),I12-L12,"") -> 0.037046032 | N12: 5.5 | O12: =IF(AND(ISNUMBER(H12),H12>0),H12*EXP('Read me'!$B$22),"") -> 8.0617348
A13: 2:40 | B13: Haydock | C13: British EBF Fillies Novice Stakes (GBB Race) | D13: 9 | E13: Kaguyahime (IRE) | F13: Bowen, S D | G13: Varian, Roger | H13: 2.5250319 | I13: 0.3960346 | J13: My Girl Dee Mo (IRE) | K13: 7.0988927 | L13: 0.14086704 | M13: =IF(AND(ISNUMBER(I13),ISNUMBER(L13)),I13-L13,"") -> 0.25516756 | N13: 1.7272727 | O13: =IF(AND(ISNUMBER(H13),H13>0),H13*EXP('Read me'!$B$22),"") -> 3.0840809
... A54: 8:30 | B54: Southwell | C54: Golf & Gallop Southwell Golf Club Handicap | D54: 13 | E54: Massimo Blue | F54: Callan, Jack | G54: Cunha, Dylan | H54: 4.352474 | I54: 0.22975439 | J54: Ormolulu (IRE) | K54: 6.1152374 | L54: 0.16352595 | M54: =IF(AND(ISNUMBER(I54),ISNUMBER(L54)),I54-L54,"") -> 0.066228438 | N54: 3.25 | O54: =IF(AND(ISNUMBER(H54),H54>0),H54*EXP('Read me'!$B$22),"") -> 5.3161238

Sheet 944 vs 615
A1: Time | B1: Course | C1: Race | D1: Runners (now) | E1: 944 top pick | F1: 944 BSP | G1: Its 615 BSP | H1: 615 top pick (runners still declared) | I1: 615 BSP | J1: Same pick? | K1: 944 vs 615 on the 944's pick
A2: 1:22 | B2: Newmarket (Rowley) | C2: British Stallion Studs EBF Jersey Lily Fillies Nursery | D2: 10 | E2: Al Samsama (IRE) | F2: 5.4223912 | G2: 5.0320897 | H2: Al Samsama (IRE) | I2: 5.0320897 | J2: =IF(E2=H2,"yes","no") -> yes | K2: =IF(AND(ISNUMBER(F2),ISNUMBER(G2)),F2/G2-1,"") -> 0.077562512
A3: 1:30 | B3: Curragh | C3: Market Square Monasterevin Irish European Breeders Fund Maiden | D3: 13 | E3: Benown (IRE) | F3: 1.9022607 | G3: 1.8188856 | H3: Benown (IRE) | I3: 1.8188856 | J3: =IF(E3=H3,"yes","no") -> yes | K3: =IF(AND(ISNUMBER(F3),ISNUMBER(G3)),F3/G3-1,"") -> 0.045838587
A4: 1:35 | B4: Haydock | C4: William Hill Epic Boosts Handicap | D4: 10 | E4: Eternal Force | F4: 5.2683602 | G4: 5.0720579 | H4: Eternal Force | I4: 5.0720579 | J4: =IF(E4=H4,"yes","no") -> yes | K4: =IF(AND(ISNUMBER(F4),ISNUMBER(G4)),F4/G4-1,"") -> 0.038702687
A5: 1:44 | B5: Ripon | C5: Theakston Brewing Legends Since 1827 EBF Novice Stakes (GBB Race) | D5: 9 | E5: Scenic Route (IRE) | F5: 2.1969837 | G5: 2.3162732 | H5: Scenic Route (IRE) | I5: 2.3162732 | J5: =IF(E5=H5,"yes","no") -> yes | K5: =IF(AND(ISNUMBER(F5),ISNUMBER(G5)),F5/G5-1,"") -> -0.051500622
A6: 1:55 | B6: Newmarket (Rowley) | C6: Tattersalls Online Royal Lodge Stakes (Group 2) | D6: 7 | E6: Haffner (USA) | F6: 4.1555937 | G6: 4.0725504 | H6: Haffner (USA) | I6: 4.0725504 | J6: =IF(E6=H6,"yes","no") -> yes | K6: =IF(AND(ISNUMBER(F6),ISNUMBER(G6)),F6/G6-1,"") -> 0.020390992
A7: 2:00 | B7: Curragh | C7: Kwiff More Bang For Your Bet Rated Race | D7: 9 | E7: Oro Blanco (IRE) | F7: 4.4337459 | G7: 5.5956726 | H7: Lewis Carroll (IRE) | I7: 4.302178 | J7: =IF(E7=H7,"yes","no") -> no | K7: =IF(AND(ISNUMBER(F7),ISNUMBER(G7)),F7/G7-1,"") -> -0.20764736
A8: 2:10 | B8: Haydock | C8: William Hill Best Odds Guaranteed Handicap | D8: 10 | E8: Trilby | F8: 4.5888249 | G8: 5.5491618 | H8: King Of Light | I8: 4.8977923 | J8: =IF(E8=H8,"yes","no") -> no | K8: =IF(AND(ISNUMBER(F8),ISNUMBER(G8)),F8/G8-1,"") -> -0.17305981
A9: 2:16 | B9: Ripon | C9: Lloyd Landrover Ripon Nursery (GBBPlus Race) | D9: 6 | E9: Aphra Behn | F9: 3.9137923 | G9: 3.8802742 | H9: Aphra Behn | I9: 3.8802742 | J9: =IF(E9=H9,"yes","no") -> yes | K9: =IF(AND(ISNUMBER(F9),ISNUMBER(G9)),F9/G9-1,"") -> 0.0086380832
A10: 2:27 | B10: Newmarket (Rowley) | C10: Tattersalls Sceptre Sessions Cheveley Park Stakes (Fillies Group 1) | D10: 6 | E10: Sun Goddess (IRE) | F10: 1.8278127 | G10: 1.5874357 | H10: Sun Goddess (IRE) | I10: 1.5874357 | J10: =IF(E10=H10,"yes","no") -> yes | K10: =IF(AND(ISNUMBER(F10),ISNUMBER(G10)),F10/G10-1,"") -> 0.1514247
A11: 2:30 | B11: Market Rasen | C11: Market Rasen Racecourse Conference & Events Mares Maiden Hurdle (GBB Race) | D11: 9 | E11: Elated | F11: 1.7522701 | G11: 1.8536781 | H11: Elated | I11: 1.8536781 | J11: =IF(E11=H11,"yes","no") -> yes | K11: =IF(AND(ISNUMBER(F11),ISNUMBER(G11)),F11/G11-1,"") -> -0.054706397
A12: 2:35 | B12: Curragh | C12: Kwiff Supercharged Joe McGrath Handicap (Premier Handicap) | D12: 20 | E12: Red Evolution (IRE) | F12: 6.6003902 | G12: 6.5999215 | H12: Red Evolution (IRE) | I12: 6.5999215 | J12: =IF(E12=H12,"yes","no") -> yes | K12: =IF(AND(ISNUMBER(F12),ISNUMBER(G12)),F12/G12-1,"") -> 7.1018879e-05
A13: 2:40 | B13: Haydock | C13: British EBF Fillies Novice Stakes (GBB Race) | D13: 9 | E13: Kaguyahime (IRE) | F13: 2.5250319 | G13: 2.6092316 | H13: Kaguyahime (IRE) | I13: 2.6092316 | J13: =IF(E13=H13,"yes","no") -> yes | K13: =IF(AND(ISNUMBER(F13),ISNUMBER(G13)),F13/G13-1,"") -> -0.032269937
... A54: 8:30 | B54: Southwell | C54: Golf & Gallop Southwell Golf Club Handicap | D54: 13 | E54: Massimo Blue | F54: 4.352474 | G54: 4.5114719 | H54: Massimo Blue | I54: 4.5114719 | J54: =IF(E54=H54,"yes","no") -> yes | K54: =IF(AND(ISNUMBER(F54),ISNUMBER(G54)),F54/G54-1,"") -> -0.035243011
A56: Races with the same top pick | E56: =COUNTIF(J2:J54,"yes")&" of "&COUNTA(J2:J54) -> 44 of 53
A57: The 615's prices are this morning's 06:00 record (Daily Predictions run 197, the forward test's file); the 944's are from the card fetched at 09:44 UTC, so a race that lost a runner since 06:00 is priced on the smaller field.

Sheet All runners
A1: Time | B1: Course | C1: Race | D1: Class | E1: Furlongs | F1: Going | G1: Runners | H1: Horse | I1: Jockey | J1: Trainer | K1: Draw | L1: OR | M1: Age | N1: Days since run | O1: Model rank | P1: Predicted BSP | Q1: Win probability | R1: Card odds (HRB) | S1: Card odds vs model | T1: Rule: back at Betfair ≥
A2: 1:22 | B2: Newmarket (Rowley) | C2: British Stallion Studs EBF Jersey Lily Fillies Nursery | D2: Class 2 | E2: 7 | F2: Good To Firm | G2: 10 | H2: Al Samsama (IRE) | I2: Loughnane, Billy | J2: Hughes, Richard | K2: 2 | L2: 85 | M2: 2 | N2: 18 | O2: 1 | P2: 5.4223912 | Q2: 0.18442048 | R2: 7.5 | S2: =IF(AND(ISNUMBER(R2),R2>1,P2>0),R2/P2-1,"") -> 0.38315362 | T2: =IF(AND(ISNUMBER(P2),P2>0),P2*EXP('Read me'!$B$22),"") -> 6.6229235
A3: 1:22 | B3: Newmarket (Rowley) | C3: British Stallion Studs EBF Jersey Lily Fillies Nursery | D3: Class 2 | E3: 7 | F3: Good To Firm | G3: 10 | H3: Next Of Kin | I3: Marquand, Tom | J3: Haggas, W J | K3: 3 | L3: 76 | M3: 2 | N3: 8 | O3: 2 | P3: 7.3693735 | Q3: 0.13569675 | R3: 8.5 | S3: =IF(AND(ISNUMBER(R3),R3>1,P3>0),R3/P3-1,"") -> 0.15342234 | T3: =IF(AND(ISNUMBER(P3),P3>0),P3*EXP('Read me'!$B$22),"") -> 9.0009731
A4: 1:22 | B4: Newmarket (Rowley) | C4: British Stallion Studs EBF Jersey Lily Fillies Nursery | D4: Class 2 | E4: 7 | F4: Good To Firm | G4: 10 | H4: Zephyra | I4: Murphy, Oisin | J4: Botti, M | K4: 4 | L4: 77 | M4: 2 | N4: 10 | O4: 3 | P4: 7.8795883 | Q4: 0.12691018 | R4: 10 | S4: =IF(AND(ISNUMBER(R4),R4>1,P4>0),R4/P4-1,"") -> 0.26910183 | T4: =IF(AND(ISNUMBER(P4),P4>0),P4*EXP('Read me'!$B$22),"") -> 9.6241509
A5: 1:22 | B5: Newmarket (Rowley) | C5: British Stallion Studs EBF Jersey Lily Fillies Nursery | D5: Class 2 | E5: 7 | F5: Good To Firm | G5: 10 | H5: Marsala (IRE) | I5: Ryan, Rossa | J5: Beckett, R M | K5: 6 | L5: 74 | M5: 2 | N5: 22 | O5: 4 | P5: 8.3992734 | Q5: 0.11905792 | R5: 7 | S5: =IF(AND(ISNUMBER(R5),R5>1,P5>0),R5/P5-1,"") -> -0.16659457 | T5: =IF(AND(ISNUMBER(P5),P5>0),P5*EXP('Read me'!$B$22),"") -> 10.258896
A6: 1:22 | B6: Newmarket (Rowley) | C6: British Stallion Studs EBF Jersey Lily Fillies Nursery | D6: Class 2 | E6: 7 | F6: Good To Firm | G6: 10 | H6: Fire Thunder (IRE) | I6: Sousa, Silvestre De | J6: Botti, M | K6: 8 | L6: 70 | M6: 2 | N6: 42 | O6: 5 | P6: 9.2469802 | Q6: 0.10814341 | R6: 4.5 | S6: =IF(AND(ISNUMBER(R6),R6>1,P6>0),R6/P6-1,"") -> -0.51335464 | T6: =IF(AND(ISNUMBER(P6),P6>0),P6*EXP('Read me'!$B$22),"") -> 11.294287
A7: 1:22 | B7: Newmarket (Rowley) | C7: British Stallion Studs EBF Jersey Lily Fillies Nursery | D7: Class 2 | E7: 7 | F7: Good To Firm | G7: 10 | H7: Bymiddaytomorrow (IRE) | I7: Lee, Clifford | J7: Walker, Ed | K7: 9 | L7: 82 | M7: 2 | N7: 16 | O7: 6 | P7: 10.374905 | Q7: 0.096386429 | R7: 9.5 | S7: =IF(AND(ISNUMBER(R7),R7>1,P7>0),R7/P7-1,"") -> -0.084328923 | T7: =IF(AND(ISNUMBER(P7),P7>0),P7*EXP('Read me'!$B$22),"") -> 12.671937
A8: 1:22 | B8: Newmarket (Rowley) | C8: British Stallion Studs EBF Jersey Lily Fillies Nursery | D8: Class 2 | E8: 7 | F8: Good To Firm | G8: 10 | H8: Polyxena (IRE) | I8: Ghiani, Marco | J8: Williams, S C | K8: 1 | L8: 82 | M8: 2 | N8: 19 | O8: 7 | P8: 11.21555 | Q8: 0.089161921 | R8: 7 | S8: =IF(AND(ISNUMBER(R8),R8>1,P8>0),R8/P8-1,"") -> -0.37586655 | T8: =IF(AND(ISNUMBER(P8),P8>0),P8*EXP('Read me'!$B$22),"") -> 13.698704
A9: 1:22 | B9: Newmarket (Rowley) | C9: British Stallion Studs EBF Jersey Lily Fillies Nursery | D9: Class 2 | E9: 7 | F9: Good To Firm | G9: 10 | H9: Tansy Lane | I9: Havlin, Robert | J9: Owen, J P | K9: 7 | L9: 74 | M9: 2 | N9: 43 | O9: 8 | P9: 11.866381 | Q9: 0.084271692 | R9: 13 | S9: =IF(AND(ISNUMBER(R9),R9>1,P9>0),R9/P9-1,"") -> 0.095531993 | T9: =IF(AND(ISNUMBER(P9),P9>0),P9*EXP('Read me'!$B$22),"") -> 14.49363
A10: 1:22 | B10: Newmarket (Rowley) | C10: British Stallion Studs EBF Jersey Lily Fillies Nursery | D10: Class 2 | E10: 7 | F10: Good To Firm | G10: 10 | H10: Kiah (IRE) | I10: Egan, David | J10: Meehan, B J | K10: 5 | L10: 76 | M10: 2 | N10: 30 | O10: 9 | P10: 34.251046 | Q10: 0.029196189 | R10: 13 | S10: =IF(AND(ISNUMBER(R10),R10>1,P10>0),R10/P10-1,"") -> -0.62044955 | T10: =IF(AND(ISNUMBER(P10),P10>0),P10*EXP('Read me'!$B$22),"") -> 41.834322
A11: 1:22 | B11: Newmarket (Rowley) | C11: British Stallion Studs EBF Jersey Lily Fillies Nursery | D11: Class 2 | E11: 7 | F11: Good To Firm | G11: 10 | H11: Tie A Navyribbon | I11: Gordon, Josephine | J11: Stone, W B | K11: 10 | L11: 80 | M11: 2 | N11: 16 | O11: 10 | P11: 37.376154 | Q11: 0.026755027 | R11: 29 | S11: =IF(AND(ISNUMBER(R11),R11>1,P11>0),R11/P11-1,"") -> -0.22410423 | T11: =IF(AND(ISNUMBER(P11),P11>0),P11*EXP('Read me'!$B$22),"") -> 45.651338
A12: 1:30 | B12: Curragh | C12: Market Square Monasterevin Irish European Breeders Fund Maiden | E12: 6 | F12: Good | G12: 13 | H12: Benown (IRE) | I12: Sheridan, J M | J12: OBrien, Joseph Patrick | K12: 14 | L12: 0 | M12: 2 | N12: 48 | O12: 1 | P12: 1.9022607 | Q12: 0.52569029 | R12: 1.7272727 | S12: =IF(AND(ISNUMBER(R12),R12>1,P12>0),R12/P12-1,"") -> -0.091989498 | T12: =IF(AND(ISNUMBER(P12),P12>0),P12*EXP('Read me'!$B$22),"") -> 2.3234265
A13: 1:30 | B13: Curragh | C13: Market Square Monasterevin Irish European Breeders Fund Maiden | E13: 6 | F13: Good | G13: 13 | H13: Heralds March (IRE) | I13: Keane, C T | J13: Lyons, G M | K13: 12 | L13: 0 | M13: 2 | N13: 35 | O13: 2 | P13: 5.3234689 | Q13: 0.18784744 | R13: 5.5 | S13: =IF(AND(ISNUMBER(R13),R13>1,P13>0),R13/P13-1,"") -> 0.033160919 | T13: =IF(AND(ISNUMBER(P13),P13>0),P13*EXP('Read me'!$B$22),"") -> 6.5020996
A14: 1:30 | B14: Curragh | C14: Market Square Monasterevin Irish European Breeders Fund Maiden | E14: 6 | F14: Good | G14: 13 | H14: Controlla (IRE) | I14: OConnor, Donagh | J14: Aguiar, Robson | K14: 11 | L14: 96 | M14: 2 | N14: 13 | O14: 3 | P14: 8.4672894 | Q14: 0.11810155 | R14: 3.25 | S14: =IF(AND(ISNUMBER(R14),R14>1,P14>0),R14/P14-1,"") -> -0.61616996 | T14: =IF(AND(ISNUMBER(P14),P14>0),P14*EXP('Read me'!$B$22),"") -> 10.341971
A15: 1:30 | B15: Curragh | C15: Market Square Monasterevin Irish European Breeders Fund Maiden | E15: 6 | F15: Good | G15: 13 | H15: Jungle Wise (IRE) | I15: Coen, Ben M | J15: Murphy, Daniel | K15: 8 | L15: 0 | M15: 2 | N15: 17 | O15: 4 | P15: 11.692526 | Q15: 0.085524719 | R15: 11 | S15: =IF(AND(ISNUMBER(R15),R15>1,P15>0),R15/P15-1,"") -> -0.059228091 | T15: =IF(AND(ISNUMBER(P15),P15>0),P15*EXP('Read me'!$B$22),"") -> 14.281283
A16: 1:30 | B16: Curragh | C16: Market Square Monasterevin Irish European Breeders Fund Maiden | E16: 6 | F16: Good | G16: 13 | H16: Shake It Out | I16: Whelan, R P | J16: Cotter, Kieran P | K16: 10 | L16: 0 | M16: 2 | O16: 5 | P16: 53.338562 | Q16: 0.018748162 | R16: 51 | S16: =IF(AND(ISNUMBER(R16),R16>1,P16>0),R16/P16-1,"") -> -0.043843731 | T16: =IF(AND(ISNUMBER(P16),P16>0),P16*EXP('Read me'!$B$22),"") -> 65.147866
A17: 1:30 | B17: Curragh | C17: Market Square Monasterevin Irish European Breeders Fund Maiden | E17: 6 | F17: Good | G17: 13 | H17: Moon Gypsy (IRE) | I17: Mulligan, R M | J17: Burns, J G | K17: 9 | L17: 0 | M17: 2 | O17: 6 | P17: 59.575275 | Q17: 0.016785487 | R17: 201 | S17: =IF(AND(ISNUMBER(R17),R17>1,P17>0),R17/P17-1,"") -> 2.3738829 | T17: =IF(AND(ISNUMBER(P17),P17>0),P17*EXP('Read me'!$B$22),"") -> 72.765406
A18: 1:30 | B18: Curragh | C18: Market Square Monasterevin Irish European Breeders Fund Maiden | E18: 6 | F18: Good | G18: 13 | H18: Katty (IRE) | I18: Heffernan, J A | J18: Sexton, Adrian | K18: 5 | L18: 0 | M18: 2 | N18: 37 | O18: 7 | P18: 62.059397 | Q18: 0.016113595 | R18: 29 | S18: =IF(AND(ISNUMBER(R18),R18>1,P18>0),R18/P18-1,"") -> -0.53270574 | T18: =IF(AND(ISNUMBER(P18),P18>0),P18*EXP('Read me'!$B$22),"") -> 75.799519
A19: 1:30 | B19: Curragh | C19: Market Square Monasterevin Irish European Breeders Fund Maiden | E19: 6 | F19: Good | G19: 13 | H19: Royal Sovereign (IRE) | I19: Joyce, Wesley | J19: Mulvany, Michael | K19: 3 | L19: 0 | M19: 2 | O19: 8 | P19: 91.538823 | Q19: 0.010924327 | R19: 51 | S19: =IF(AND(ISNUMBER(R19),R19>1,P19>0),R19/P19-1,"") -> -0.44285935 | T19: =IF(AND(ISNUMBER(P19),P19>0),P19*EXP('Read me'!$B$22),"") -> 111.80577
A20: 1:30 | B20: Curragh | C20: Market Square Monasterevin Irish European Breeders Fund Maiden | E20: 6 | F20: Good | G20: 13 | H20: Starlit (IRE) | I20: Kennedy, K G | J20: Harrington, Mrs John | K20: 7 | L20: 0 | M20: 2 | N20: 42 | O20: 9 | P20: 105.08303 | Q20: 0.0095162848 | R20: 26 | S20: =IF(AND(ISNUMBER(R20),R20>1,P20>0),R20/P20-1,"") -> -0.75257659 | T20: =IF(AND(ISNUMBER(P20),P20>0),P20*EXP('Read me'!$B$22),"") -> 128.3487
A21: 1:30 | B21: Curragh | C21: Market Square Monasterevin Irish European Breeders Fund Maiden | E21: 6 | F21: Good | G21: 13 | H21: Champion Basma (IRE) | I21: Hayes, C D | J21: ONeill, E J | K21: 2 | L21: 0 | M21: 2 | N21: 9 | O21: 10 | P21: 213.77245 | Q21: 0.0046778712 | R21: 67 | S21: =IF(AND(ISNUMBER(R21),R21>1,P21>0),R21/P21-1,"") -> -0.68658263 | T21: =IF(AND(ISNUMBER(P21),P21>0),P21*EXP('Read me'!$B$22),"") -> 261.10226
A22: 1:30 | B22: Curragh | C22: Market Square Monasterevin Irish European Breeders Fund Maiden | E22: 6 | F22: Good | G22: 13 | H22: Fen Phasee (IRE) | I22: Cleary, R P | J22: Davis, Sean | K22: 4 | L22: 0 | M22: 2 | O22: 11 | P22: 393.51875 | Q22: 0.002541175 | R22: 126 | S22: =IF(AND(ISNUMBER(R22),R22>1,P22>0),R22/P22-1,"") -> -0.67981195 | T22: =IF(AND(ISNUMBER(P22),P22>0),P22*EXP('Read me'!$B$22),"") -> 480.64489
A23: 1:30 | B23: Curragh | C23: Market Square Monasterevin Irish European Breeders Fund Maiden | E23: 6 | F23: Good | G23: 13 | H23: Ar Son Na Cuise (IRE) | I23: McDonogh, D P | J23: OBrien, Joseph Patrick | K23: 13 | L23: 0 | M23: 2 | N23: 17 | O23: 12 | P23: 402.27202 | Q23: 0.0024858801 | R23: 101 | S23: =IF(AND(ISNUMBER(R23),R23>1,P23>0),R23/P23-1,"") -> -0.74892611 | T23: =IF(AND(ISNUMBER(P23),P23>0),P23*EXP('Read me'!$B$22),"") -> 491.33615
A24: 1:30 | B24: Curragh | C24: Market Square Monasterevin Irish European Breeders Fund Maiden | E24: 6 | F24: Good | G24: 13 | H24: Brageiro (IRE) | I24: McAteer, L T | J24: OSullivan, Ross | K24: 1 | L24: 0 | M24: 2 | N24: 9 | O24: 13 | P24: 958.57182 | Q24: 0.0010432186 | R24: 201 | S24: =IF(AND(ISNUMBER(R24),R24>1,P24>0),R24/P24-1,"") -> -0.79031305 | T24: =IF(AND(ISNUMBER(P24),P24>0),P24*EXP('Read me'!$B$22),"") -> 1170.8023
A25: 1:35 | B25: Haydock | C25: William Hill Epic Boosts Handicap | D25: Class 2 | E25: 8 | F25: Heavy | G25: 10 | H25: Eternal Force | I25: Fallon, Cieren | J25: Haggas, W J | K25: 4 | L25: 96 | M25: 4 | N25: 37 | O25: 1 | P25: 5.2683602 | Q25: 0.18981238 | R25: 4.5 | S25: =IF(AND(ISNUMBER(R25),R25>1,P25>0),R25/P25-1,"") -> -0.14584427 | T25: =IF(AND(ISNUMBER(P25),P25>0),P25*EXP('Read me'!$B$22),"") -> 6.4347896
A26: 1:35 | B26: Haydock | C26: William Hill Epic Boosts Handicap | D26: Class 2 | E26: 8 | F26: Heavy | G26: 10 | H26: Centigrade (IRE) | I26: Crouch, Hector | J26: Beckett, R M | K26: 9 | L26: 100 | M26: 4 | N26: 10 | O26: 2 | P26: 5.8434044 | Q26: 0.17113311 | R26: 6.5 | S26: =IF(AND(ISNUMBER(R26),R26>1,P26>0),R26/P26-1,"") -> 0.11236525 | T26: =IF(AND(ISNUMBER(P26),P26>0),P26*EXP('Read me'!$B$22),"") -> 7.1371503
A27: 1:35 | B27: Haydock | C27: William Hill Epic Boosts Handicap | D27: Class 2 | E27: 8 | F27: Heavy | G27: 10 | H27: Looka (USA) | I27: Levey, S M | J27: Botti, M | K27: 3 | L27: 93 | M27: 3 | N27: 23 | O27: 3 | P27: 7.4300309 | Q27: 0.13458894 | R27: 7 | S27: =IF(AND(ISNUMBER(R27),R27>1,P27>0),R27/P27-1,"") -> -0.057877408 | T27: =IF(AND(ISNUMBER(P27),P27>0),P27*EXP('Read me'!$B$22),"") -> 9.0750603
A28: 1:35 | B28: Haydock | C28: William Hill Epic Boosts Handicap | D28: Class 2 | E28: 8 | F28: Heavy | G28: 10 | H28: Cerulean Bay (IRE) | I28: Tudhope, Daniel | J28: OMeara, D | K28: 1 | L28: 104 | M28: 5 | N28: 37 | O28: 4 | P28: 7.6360691 | Q28: 0.13095743 | R28: 7.5 | S28: =IF(AND(ISNUMBER(R28),R28>1,P28>0),R28/P28-1,"") -> -0.017819255 | T28: =IF(AND(ISNUMBER(P28),P28>0),P28*EXP('Read me'!$B$22),"") -> 9.3267158
A29: 1:35 | B29: Haydock | C29: William Hill Epic Boosts Handicap | D29: Class 2 | E29: 8 | F29: Heavy | G29: 10 | H29: Arctic Thunder (IRE) | I29: Lewis, Ashley | J29: Walker, Ed | K29: 10 | L29: 96 | M29: 5 | N29: 22 | O29: 5 | P29: 12.16776 | Q29: 0.082184395 | R29: 11 | S29: =IF(AND(ISNUMBER(R29),R29>1,P29>0),R29/P29-1,"") -> -0.095971651 | T29: =IF(AND(ISNUMBER(P29),P29>0),P29*EXP('Read me'!$B$22),"") -> 14.861736
A30: 1:35 | B30: Haydock | C30: William Hill Epic Boosts Handicap | D30: Class 2 | E30: 8 | F30: Heavy | G30: 10 | H30: Godwinson | I30: Probert, David | J30: Channon, Jack | K30: 5 | L30: 96 | M30: 6 | N30: 57 | O30: 6 | P30: 14.699878 | Q30: 0.068027777 | R30: 10 | S30: =IF(AND(ISNUMBER(R30),R30>1,P30>0),R30/P30-1,"") -> -0.31972223 | T30: =IF(AND(ISNUMBER(P30),P30>0),P30*EXP('Read me'!$B$22),"") -> 17.954471
A31: 1:35 | B31: Haydock | C31: William Hill Epic Boosts Handicap | D31: Class 2 | E31: 8 | F31: Heavy | G31: 10 | H31: Mister Winston | I31: McDonald, P J | J31: Balding, A M | K31: 6 | L31: 100 | M31: 4 | N31: 14 | O31: 7 | P31: 14.954557 | Q31: 0.06686925 | R31: 10 | S31: =IF(AND(ISNUMBER(R31),R31>1,P31>0),R31/P31-1,"") -> -0.3313075 | T31: =IF(AND(ISNUMBER(P31),P31>0),P31*EXP('Read me'!$B$22),"") -> 18.265537
A32: 1:35 | B32: Haydock | C32: William Hill Epic Boosts Handicap | D32: Class 2 | E32: 8 | F32: Heavy | G32: 10 | H32: Commanders Intent (FR) | I32: Rodriguez, Callum | J32: Scott, George | K32: 2 | L32: 100 | M32: 3 | N32: 163 | O32: 8 | P32: 17.48279 | Q32: 0.057199107 | R32: 10 | S32: =IF(AND(ISNUMBER(R32),R32>1,P32>0),R32/P32-1,"") -> -0.42800893 | T32: =IF(AND(ISNUMBER(P32),P32>0),P32*EXP('Read me'!$B$22),"") -> 21.353529
A33: 1:35 | B33: Haydock | C33: William Hill Epic Boosts Handicap | D33: Class 2 | E33: 8 | F33: Heavy | G33: 10 | H33: Desperate Dan (IRE) | I33: Wood, George | J33: Chapple-Hyam, P W | K33: 7 | L33: 85 | M33: 5 | N33: 106 | O33: 9 | P33: 18.929647 | Q33: 0.052827187 | R33: 23 | S33: =IF(AND(ISNUMBER(R33),R33>1,P33>0),R33/P33-1,"") -> 0.2150253 | T33: =IF(AND(ISNUMBER(P33),P33>0),P33*EXP('Read me'!$B$22),"") -> 23.120723
A34: 1:35 | B34: Haydock | C34: William Hill Epic Boosts Handicap | D34: Class 2 | E34: 8 | F34: Heavy | G34: 10 | H34: Checkandchallenge | I34: Shepherd, Callum | J34: Knight, W J | K34: 8 | L34: 96 | M34: 7 | N34: 14 | O34: 10 | P34: 21.551533 | Q34: 0.046400412 | R34: 17 | S34: =IF(AND(ISNUMBER(R34),R34>1,P34>0),R34/P34-1,"") -> -0.211193 | T34: =IF(AND(ISNUMBER(P34),P34>0),P34*EXP('Read me'!$B$22),"") -> 26.323102
A35: 1:44 | B35: Ripon | C35: Theakston Brewing Legends Since 1827 EBF Novice Stakes (GBB Race) | D35: Class 4 | E35: 6 | F35: Good | G35: 9 | H35: Scenic Route (IRE) | I35: Orr, Oisin | J35: Fahey, R A | K35: 3 | L35: 78 | M35: 2 | N35: 20 | O35: 1 | P35: 2.1969837 | Q35: 0.45516951 | R35: 1.9090909 | S35: =IF(AND(ISNUMBER(R35),R35>1,P35>0),R35/P35-1,"") -> -0.13104004 | T35: =IF(AND(ISNUMBER(P35),P35>0),P35*EXP('Read me'!$B$22),"") -> 2.683402
A36: 1:44 | B36: Ripon | C36: Theakston Brewing Legends Since 1827 EBF Novice Stakes (GBB Race) | D36: Class 4 | E36: 6 | F36: Good | G36: 9 | H36: Bulletsnap (IRE) | I36: Hart, Jason | J36: Haggas, W J | K36: 9 | L36: 78 | M36: 2 | N36: 28 | O36: 2 | P36: 2.6507783 | Q36: 0.37724769 | R36: 2.5 | S36: =IF(AND(ISNUMBER(R36),R36>1,P36>0),R36/P36-1,"") -> -0.056880779 | T36: =IF(AND(ISNUMBER(P36),P36>0),P36*EXP('Read me'!$B$22),"") -> 3.237668
... A39: 1:44 | B39: Ripon | C39: Theakston Brewing Legends Since 1827 EBF Novice Stakes (GBB Race) | D39: Class 4 | E39: 6 | F39: Good | G39: 9 | H39: Commander Keith (IRE) | I39: Stammers, Oliver | J39: Frost, Kevin | K39: 2 | L39: 0 | M39: 2 | N39: 35 | O39: 5 | P39: 55.715171 | Q39: 0.017948433 | R39: 34 | S39: =IF(AND(ISNUMBER(R39),R39>1,P39>0),R39/P39-1,"") -> -0.38975329 | T39: =IF(AND(ISNUMBER(P39),P39>0),P39*EXP('Read me'!$B$22),"") -> 68.050664
A40: 1:44 | B40: Ripon | C40: Theakston Brewing Legends Since 1827 EBF Novice Stakes (GBB Race) | D40: Class 4 | E40: 6 | F40: Good | G40: 9 | H40: Jeans Tipple (FR) | I40: Beasley, Connor | J40: Kirby, P A | K40: 4 | L40: 0 | M40: 2 | O40: 6 | P40: 93.029003 | Q40: 0.010749336 | R40: 26 | S40: =IF(AND(ISNUMBER(R40),R40>1,P40>0),R40/P40-1,"") -> -0.72051727 | T40: =IF(AND(ISNUMBER(P40),P40>0),P40*EXP('Read me'!$B$22),"") -> 113.62588
A41: 1:44 | B41: Ripon | C41: Theakston Brewing Legends Since 1827 EBF Novice Stakes (GBB Race) | D41: Class 4 | E41: 6 | F41: Good | G41: 9 | H41: Cracking Toast | I41: Sexton, Ryan | J41: Hanmer, G D | K41: 8 | L41: 0 | M41: 2 | N41: 15 | O41: 7 | P41: 265.23782 | Q41: 0.0037702013 | R41: 67 | S41: =IF(AND(ISNUMBER(R41),R41>1,P41>0),R41/P41-1,"") -> -0.74739651 | T41: =IF(AND(ISNUMBER(P41),P41>0),P41*EXP('Read me'!$B$22),"") -> 323.96221
A42: 1:44 | B42: Ripon | C42: Theakston Brewing Legends Since 1827 EBF Novice Stakes (GBB Race) | D42: Class 4 | E42: 6 | F42: Good | G42: 9 | H42: Harry Akoya | I42: McManoman, Faye | J42: Tinkler, N | K42: 5 | L42: 0 | M42: 2 | N42: 10 | O42: 8 | P42: 711.80747 | Q42: 0.0014048743 | R42: 51 | S42: =IF(AND(ISNUMBER(R42),R42>1,P42>0),R42/P42-1,"") -> -0.92835141 | T42: =IF(AND(ISNUMBER(P42),P42>0),P42*EXP('Read me'!$B$22),"") -> 869.4036
A43: 1:44 | B43: Ripon | C43: Theakston Brewing Legends Since 1827 EBF Novice Stakes (GBB Race) | D43: Class 4 | E43: 6 | F43: Good | G43: 9 | H43: Ubettanotblink | I43: Eaves, Tom | J43: Lidster, Craig | K43: 1 | L43: 0 | M43: 2 | N43: 9 | O43: 9 | P43: 1138.902 | Q43: 0.00087803869 | R43: 201 | S43: =IF(AND(ISNUMBER(R43),R43>1,P43>0),R43/P43-1,"") -> -0.82351422 | T43: =IF(AND(ISNUMBER(P43),P43>0),P43*EXP('Read me'!$B$22),"") -> 1391.058
A44: 1:55 | B44: Newmarket (Rowley) | C44: Tattersalls Online Royal Lodge Stakes (Group 2) | E44: 8 | F44: Good To Firm | G44: 7 | H44: Haffner (USA) | I44: Moore, Ryan | J44: OBrien, A P | K44: 4 | L44: 110 | M44: 2 | N44: 13 | O44: 1 | P44: 4.1555937 | Q44: 0.2406395 | R44: 4.5 | S44: =IF(AND(ISNUMBER(R44),R44>1,P44>0),R44/P44-1,"") -> 0.082877751 | T44: =IF(AND(ISNUMBER(P44),P44>0),P44*EXP('Read me'!$B$22),"") -> 5.0756537
A45: 1:55 | B45: Newmarket (Rowley) | C45: Tattersalls Online Royal Lodge Stakes (Group 2) | E45: 8 | F45: Good To Firm | G45: 7 | H45: First Law (IRE) | I45: Buick, William | J45: Appleby, Charlie | K45: 2 | L45: 101 | M45: 2 | N45: 21 | O45: 2 | P45: 4.324806 | Q45: 0.23122425 | R45: 4.5 | S45: =IF(AND(ISNUMBER(R45),R45>1,P45>0),R45/P45-1,"") -> 0.040509104 | T45: =IF(AND(ISNUMBER(P45),P45>0),P45*EXP('Read me'!$B$22),"") -> 5.28233
A46: 1:55 | B46: Newmarket (Rowley) | C46: Tattersalls Online Royal Lodge Stakes (Group 2) | E46: 8 | F46: Good To Firm | G46: 7 | H46: Quest For Stars (FR) | I46: Loughnane, Billy | J46: Appleby, Charlie | K46: 6 | L46: 105 | M46: 2 | N46: 14 | O46: 3 | P46: 4.8755087 | Q46: 0.2051068 | R46: 5 | S46: =IF(AND(ISNUMBER(R46),R46>1,P46>0),R46/P46-1,"") -> 0.025534021 | T46: =IF(AND(ISNUMBER(P46),P46>0),P46*EXP('Read me'!$B$22),"") -> 5.9549597
A47: 1:55 | B47: Newmarket (Rowley) | C47: Tattersalls Online Royal Lodge Stakes (Group 2) | E47: 8 | F47: Good To Firm | G47: 7 | H47: Burning Up | I47: Lee, Clifford | J47: Burke, K R | K47: 7 | L47: 97 | M47: 2 | N47: 23 | O47: 4 | P47: 7.4636157 | Q47: 0.13398332 | R47: 4.5 | S47: =IF(AND(ISNUMBER(R47),R47>1,P47>0),R47/P47-1,"") -> -0.39707507 | T47: =IF(AND(ISNUMBER(P47),P47>0),P47*EXP('Read me'!$B$22),"") -> 9.1160808
A48: 1:55 | B48: Newmarket (Rowley) | C48: Tattersalls Online Royal Lodge Stakes (Group 2) | E48: 8 | F48: Good To Firm | G48: 7 | H48: Quicken Away (USA) | I48: Murphy, Oisin | J48: Balding, A M | K48: 5 | L48: 0 | M48: 2 | N48: 18 | O48: 5 | P48: 9.0785 | Q48: 0.11015036 | R48: 7 | S48: =IF(AND(ISNUMBER(R48),R48>1,P48>0),R48/P48-1,"") -> -0.22894751 | T48: =IF(AND(ISNUMBER(P48),P48>0),P48*EXP('Read me'!$B$22),"") -> 11.088505
A49: 1:55 | B49: Newmarket (Rowley) | C49: Tattersalls Online Royal Lodge Stakes (Group 2) | E49: 8 | F49: Good To Firm | G49: 7 | H49: Rocket Boy (IRE) | I49: Ghiani, Marco | J49: Botti, M | K49: 3 | L49: 100 | M49: 2 | N49: 21 | O49: 6 | P49: 19.160325 | Q49: 0.052191181 | R49: 17 | S49: =IF(AND(ISNUMBER(R49),R49>1,P49>0),R49/P49-1,"") -> -0.11274993 | T49: =IF(AND(ISNUMBER(P49),P49>0),P49*EXP('Read me'!$B$22),"") -> 23.402474
A50: 1:55 | B50: Newmarket (Rowley) | C50: Tattersalls Online Royal Lodge Stakes (Group 2) | E50: 8 | F50: Good To Firm | G50: 7 | H50: Iwasjustsaying | I50: Mitchell, Jack | J50: Johnston, Charlie | K50: 1 | L50: 86 | M50: 2 | N50: 18 | O50: 7 | P50: 37.446739 | Q50: 0.026704595 | R50: 23 | S50: =IF(AND(ISNUMBER(R50),R50>1,P50>0),R50/P50-1,"") -> -0.38579431 | T50: =IF(AND(ISNUMBER(P50),P50>0),P50*EXP('Read me'!$B$22),"") -> 45.73755
A51: 2:00 | B51: Curragh | C51: Kwiff More Bang For Your Bet Rated Race | E51: 7 | F51: Good | G51: 9 | H51: Oro Blanco (IRE) | I51: Kennedy, K G | J51: Harrington, Mrs John | K51: 7 | L51: 84 | M51: 3 | N51: 14 | O51: 1 | P51: 4.4337459 | Q51: 0.22554292 | R51: 3.75 | S51: =IF(AND(ISNUMBER(R51),R51>1,P51>0),R51/P51-1,"") -> -0.15421405 | T51: =IF(AND(ISNUMBER(P51),P51>0),P51*EXP('Read me'!$B$22),"") -> 5.4153895
A52: 2:00 | B52: Curragh | C52: Kwiff More Bang For Your Bet Rated Race | E52: 7 | F52: Good | G52: 9 | H52: Killashee Warrior | I52: Hayes, C D | J52: Harty, Edward and Patrick | K52: 8 | L52: 91 | M52: 3 | N52: 14 | O52: 2 | P52: 5.0561504 | Q52: 0.19777893 | R52: 6 | S52: =IF(AND(ISNUMBER(R52),R52>1,P52>0),R52/P52-1,"") -> 0.18667357 | T52: =IF(AND(ISNUMBER(P52),P52>0),P52*EXP('Read me'!$B$22),"") -> 6.175596
A53: 2:00 | B53: Curragh | C53: Kwiff More Bang For Your Bet Rated Race | E53: 7 | F53: Good | G53: 9 | H53: Lewis Carroll (IRE) | I53: Lordan, W M | J53: OBrien, A P | K53: 3 | L53: 87 | M53: 3 | N53: 182 | O53: 3 | P53: 5.8560056 | Q53: 0.17076486 | R53: 5.5 | S53: =IF(AND(ISNUMBER(R53),R53>1,P53>0),R53/P53-1,"") -> -0.060793244 | T53: =IF(AND(ISNUMBER(P53),P53>0),P53*EXP('Read me'!$B$22),"") -> 7.1525414
A54: 2:00 | B54: Curragh | C54: Kwiff More Bang For Your Bet Rated Race | E54: 7 | F54: Good | G54: 9 | H54: Invincible Will (IRE) | I54: Carroll, G F | J54: Cromwell, Gavin Patrick | K54: 5 | L54: 87 | M54: 3 | N54: 13 | O54: 4 | P54: 6.6813851 | Q54: 0.14966956 | R54: 4.3333333 | S54: =IF(AND(ISNUMBER(R54),R54>1,P54>0),R54/P54-1,"") -> -0.35143189 | T54: =IF(AND(ISNUMBER(P54),P54>0),P54*EXP('Read me'!$B$22),"") -> 8.1606622
A55: 2:00 | B55: Curragh | C55: Kwiff More Bang For Your Bet Rated Race | E55: 7 | F55: Good | G55: 9 | H55: Chapel Lane (IRE) | I55: Lee, W J | J55: McCreery, W | K55: 6 | L55: 81 | M55: 3 | N55: 24 | O55: 5 | P55: 8.5280476 | Q55: 0.11726013 | R55: 8 | S55: =IF(AND(ISNUMBER(R55),R55>1,P55>0),R55/P55-1,"") -> -0.061918928 | T55: =IF(AND(ISNUMBER(P55),P55>0),P55*EXP('Read me'!$B$22),"") -> 10.416181
... A59: 2:00 | B59: Curragh | C59: Kwiff More Bang For Your Bet Rated Race | E59: 7 | F59: Good | G59: 9 | H59: Lohoobb | I59: McCullagh, N G | J59: Grassick, M C | K59: 9 | L59: 78 | M59: 3 | N59: 13 | O59: 9 | P59: 41.200788 | Q59: 0.024271381 | R59: 29 | S59: =IF(AND(ISNUMBER(R59),R59>1,P59>0),R59/P59-1,"") -> -0.29612996 | T59: =IF(AND(ISNUMBER(P59),P59>0),P59*EXP('Read me'!$B$22),"") -> 50.322756
A60: 2:10 | B60: Haydock | C60: William Hill Best Odds Guaranteed Handicap | D60: Class 2 | E60: 5 | F60: Heavy | G60: 10 | H60: Trilby | I60: McDonald, P J | J60: England, Sam | K60: 4 | L60: 89 | M60: 6 | N60: 7 | O60: 1 | P60: 4.5888249 | Q60: 0.21792071 | R60: 3.25 | S60: =IF(AND(ISNUMBER(R60),R60>1,P60>0),R60/P60-1,"") -> -0.29175768 | T60: =IF(AND(ISNUMBER(P60),P60>0),P60*EXP('Read me'!$B$22),"") -> 5.6048034
A61: 2:10 | B61: Haydock | C61: William Hill Best Odds Guaranteed Handicap | D61: Class 2 | E61: 5 | F61: Heavy | G61: 10 | H61: King Of Light | I61: Tudhope, Daniel | J61: Williams, S C | K61: 11 | L61: 94 | M61: 4 | N61: 14 | O61: 2 | P61: 4.8875045 | Q61: 0.20460339 | R61: 4 | S61: =IF(AND(ISNUMBER(R61),R61>1,P61>0),R61/P61-1,"") -> -0.18158644 | T61: =IF(AND(ISNUMBER(P61),P61>0),P61*EXP('Read me'!$B$22),"") -> 5.9696115
A62: 2:10 | B62: Haydock | C62: William Hill Best Odds Guaranteed Handicap | D62: Class 2 | E62: 5 | F62: Heavy | G62: 10 | H62: Ancient State (IRE) | I62: Rodriguez, Callum | J62: Kirby, Adam | K62: 7 | L62: 90 | M62: 4 | N62: 13 | O62: 3 | P62: 6.7301026 | Q62: 0.14858614 | R62: 7.5 | S62: =IF(AND(ISNUMBER(R62),R62>1,P62>0),R62/P62-1,"") -> 0.11439608 | T62: =IF(AND(ISNUMBER(P62),P62>0),P62*EXP('Read me'!$B$22),"") -> 8.2201659
A63: 2:10 | B63: Haydock | C63: William Hill Best Odds Guaranteed Handicap | D63: Class 2 | E63: 5 | F63: Heavy | G63: 10 | H63: Hucklesbrook | I63: Mason, Joanna | J63: Teal, R A | K63: 3 | L63: 86 | M63: 4 | N63: 42 | O63: 4 | P63: 9.8056789 | Q63: 0.10198172 | R63: 12 | S63: =IF(AND(ISNUMBER(R63),R63>1,P63>0),R63/P63-1,"") -> 0.22378063 | T63: =IF(AND(ISNUMBER(P63),P63>0),P63*EXP('Read me'!$B$22),"") -> 11.976683
A64: 2:10 | B64: Haydock | C64: William Hill Best Odds Guaranteed Handicap | D64: Class 2 | E64: 5 | F64: Heavy | G64: 10 | H64: Boston Dan (IRE) | I64: Kirrane, Sean | J64: Easterby, T D | K64: 1 | L64: 82 | M64: 3 | N64: 8 | O64: 5 | P64: 11.051231 | Q64: 0.09048766 | R64: 13 | S64: =IF(AND(ISNUMBER(R64),R64>1,P64>0),R64/P64-1,"") -> 0.17633958 | T64: =IF(AND(ISNUMBER(P64),P64>0),P64*EXP('Read me'!$B$22),"") -> 13.498004
A65: 2:10 | B65: Haydock | C65: William Hill Best Odds Guaranteed Handicap | D65: Class 2 | E65: 5 | F65: Heavy | G65: 10 | H65: Fandom | I65: Levey, S M | J65: Hannon (Jnr), Richard | K65: 8 | L65: 96 | M65: 5 | N65: 27 | O65: 6 | P65: 14.476809 | Q65: 0.069075997 | R65: 15 | S65: =IF(AND(ISNUMBER(R65),R65>1,P65>0),R65/P65-1,"") -> 0.036139961 | T65: =IF(AND(ISNUMBER(P65),P65>0),P65*EXP('Read me'!$B$22),"") -> 17.682014
A66: 2:10 | B66: Haydock | C66: William Hill Best Odds Guaranteed Handicap | D66: Class 2 | E66: 5 | F66: Heavy | G66: 10 | H66: Elara May | I66: Lewis, Ashley | J66: McBride, P J | K66: 12 | L66: 83 | M66: 3 | N66: 21 | O66: 7 | P66: 14.606343 | Q66: 0.068463407 | R66: 10 | S66: =IF(AND(ISNUMBER(R66),R66>1,P66>0),R66/P66-1,"") -> -0.31536593 | T66: =IF(AND(ISNUMBER(P66),P66>0),P66*EXP('Read me'!$B$22),"") -> 17.840228
A67: 2:10 | B67: Haydock | C67: William Hill Best Odds Guaranteed Handicap | D67: Class 2 | E67: 5 | F67: Heavy | G67: 10 | H67: Stargazed | I67: James, S H | J67: Burke, K R | K67: 10 | L67: 83 | M67: 3 | N67: 38 | O67: 8 | P67: 16.332699 | Q67: 0.061226866 | R67: 11 | S67: =IF(AND(ISNUMBER(R67),R67>1,P67>0),R67/P67-1,"") -> -0.32650447 | T67: =IF(AND(ISNUMBER(P67),P67>0),P67*EXP('Read me'!$B$22),"") -> 19.948804
A68: 2:10 | B68: Haydock | C68: William Hill Best Odds Guaranteed Handicap | D68: Class 2 | E68: 5 | F68: Heavy | G68: 10 | H68: Roach Power (IRE) | I68: Egan, John | J68: Wigham, M | K68: 5 | L68: 72 | M68: 7 | N68: 20 | O68: 9 | P68: 46.569204 | Q68: 0.021473419 | R68: 23 | S68: =IF(AND(ISNUMBER(R68),R68>1,P68>0),R68/P68-1,"") -> -0.50611137 | T68: =IF(AND(ISNUMBER(P68),P68>0),P68*EXP('Read me'!$B$22),"") -> 56.879754
A69: 2:10 | B69: Haydock | C69: William Hill Best Odds Guaranteed Handicap | D69: Class 2 | E69: 5 | F69: Heavy | G69: 10 | H69: Jel Pepper (IRE) | I69: Jamin, Pierre-Louis | J69: Williams, S C | K69: 6 | L69: 87 | M69: 3 | N69: 14 | O69: 10 | P69: 61.802086 | Q69: 0.016180684 | R69: 51 | S69: =IF(AND(ISNUMBER(R69),R69>1,P69>0),R69/P69-1,"") -> -0.17478513 | T69: =IF(AND(ISNUMBER(P69),P69>0),P69*EXP('Read me'!$B$22),"") -> 75.485238
A70: 2:16 | B70: Ripon | C70: Lloyd Landrover Ripon Nursery (GBBPlus Race) | D70: Class 4 | E70: 8 | F70: Good | G70: 6 | H70: Aphra Behn | I70: Hart, Jason | J70: Beckett, R M | K70: 6 | L70: 66 | M70: 2 | N70: 50 | O70: 1 | P70: 3.9137923 | Q70: 0.25550666 | R70: 2.625 | S70: =IF(AND(ISNUMBER(R70),R70>1,P70>0),R70/P70-1,"") -> -0.32929502 | T70: =IF(AND(ISNUMBER(P70),P70>0),P70*EXP('Read me'!$B$22),"") -> 4.7803167
A71: 2:16 | B71: Ripon | C71: Lloyd Landrover Ripon Nursery (GBBPlus Race) | D71: Class 4 | E71: 8 | F71: Good | G71: 6 | H71: Zarakova | I71: Rawlinson, Ali | J71: Balding, A M | K71: 4 | L71: 80 | M71: 2 | N71: 16 | O71: 2 | P71: 4.3249916 | Q71: 0.23121432 | R71: 5.5 | S71: =IF(AND(ISNUMBER(R71),R71>1,P71>0),R71/P71-1,"") -> 0.27167876 | T71: =IF(AND(ISNUMBER(P71),P71>0),P71*EXP('Read me'!$B$22),"") -> 5.2825567
... A75: 2:16 | B75: Ripon | C75: Lloyd Landrover Ripon Nursery (GBBPlus Race) | D75: Class 4 | E75: 8 | F75: Good | G75: 6 | H75: Cash Cove (IRE) | I75: Scott, Rowan | J75: Johnston, Charlie | K75: 5 | L75: 72 | M75: 2 | N75: 42 | O75: 6 | P75: 15.837833 | Q75: 0.063139953 | R75: 13 | S75: =IF(AND(ISNUMBER(R75),R75>1,P75>0),R75/P75-1,"") -> -0.17918061 | T75: =IF(AND(ISNUMBER(P75),P75>0),P75*EXP('Read me'!$B$22),"") -> 19.344372
A76: 2:27 | B76: Newmarket (Rowley) | C76: Tattersalls Sceptre Sessions Cheveley Park Stakes (Fillies Group 1) | E76: 6 | F76: Good To Firm | G76: 6 | H76: Sun Goddess (IRE) | I76: Moore, Ryan | J76: OBrien, A P | K76: 6 | L76: 119 | M76: 2 | N76: 13 | O76: 1 | P76: 1.8278127 | Q76: 0.547102 | R76: 2.5 | S76: =IF(AND(ISNUMBER(R76),R76>1,P76>0),R76/P76-1,"") -> 0.36775501 | T76: =IF(AND(ISNUMBER(P76),P76>0),P76*EXP('Read me'!$B$22),"") -> 2.2324955
A77: 2:27 | B77: Newmarket (Rowley) | C77: Tattersalls Sceptre Sessions Cheveley Park Stakes (Fillies Group 1) | E77: 6 | F77: Good To Firm | G77: 6 | H77: Libertango (IRE) | I77: Loughnane, Billy | J77: Boughey, George | K77: 2 | L77: 107 | M77: 2 | N77: 37 | O77: 2 | P77: 6.5055108 | Q77: 0.15371583 | R77: 5.5 | S77: =IF(AND(ISNUMBER(R77),R77>1,P77>0),R77/P77-1,"") -> -0.15456293 | T77: =IF(AND(ISNUMBER(P77),P77>0),P77*EXP('Read me'!$B$22),"") -> 7.9458488
A78: 2:27 | B78: Newmarket (Rowley) | C78: Tattersalls Sceptre Sessions Cheveley Park Stakes (Fillies Group 1) | E78: 6 | F78: Good To Firm | G78: 6 | H78: Senorita Bonita (IRE) | I78: Murphy, Oisin | J78: Crisford, Simon | K78: 1 | L78: 117 | M78: 2 | N78: 78 | O78: 3 | P78: 6.5580225 | Q78: 0.15248499 | R78: 3 | S78: =IF(AND(ISNUMBER(R78),R78>1,P78>0),R78/P78-1,"") -> -0.54254503 | T78: =IF(AND(ISNUMBER(P78),P78>0),P78*EXP('Read me'!$B$22),"") -> 8.0099868
A79: 2:27 | B79: Newmarket (Rowley) | C79: Tattersalls Sceptre Sessions Cheveley Park Stakes (Fillies Group 1) | E79: 6 | F79: Good To Firm | G79: 6 | H79: Alwaysanangel (IRE) | I79: Buick, William | J79: OBrien, Joseph Patrick | K79: 3 | L79: 104 | M79: 2 | N79: 43 | O79: 4 | P79: 12.459672 | Q79: 0.080258936 | R79: 11 | S79: =IF(AND(ISNUMBER(R79),R79>1,P79>0),R79/P79-1,"") -> -0.11715171 | T79: =IF(AND(ISNUMBER(P79),P79>0),P79*EXP('Read me'!$B$22),"") -> 15.218278
A80: 2:27 | B80: Newmarket (Rowley) | C80: Tattersalls Sceptre Sessions Cheveley Park Stakes (Fillies Group 1) | E80: 6 | F80: Good To Firm | G80: 6 | H80: Moonrise (IRE) | I80: Marquand, Tom | J80: Balding, A M | K80: 5 | L80: 109 | M80: 2 | N80: 21 | O80: 5 | P80: 16.851917 | Q80: 0.05934043 | R80: 17 | S80: =IF(AND(ISNUMBER(R80),R80>1,P80>0),R80/P80-1,"") -> 0.0087873064 | T80: =IF(AND(ISNUMBER(P80),P80>0),P80*EXP('Read me'!$B$22),"") -> 20.582978
A81: 2:27 | B81: Newmarket (Rowley) | C81: Tattersalls Sceptre Sessions Cheveley Park Stakes (Fillies Group 1) | E81: 6 | F81: Good To Firm | G81: 6 | H81: Snowing (IRE) | I81: Ryan, Rossa | J81: OBrien, A P | K81: 4 | L81: 98 | M81: 2 | N81: 14 | O81: 6 | P81: 140.88853 | Q81: 0.00709781 | R81: 126 | S81: =IF(AND(ISNUMBER(R81),R81>1,P81>0),R81/P81-1,"") -> -0.10567595 | T81: =IF(AND(ISNUMBER(P81),P81>0),P81*EXP('Read me'!$B$22),"") -> 172.08164
A82: 2:30 | B82: Market Rasen | C82: Market Rasen Racecourse Conference & Events Mares Maiden Hurdle (GBB Race) | D82: Class 4 | E82: 17.5 | F82: Good | G82: 9 | H82: Elated | I82: Jones, Ben R | J82: Pauling, Ben | K82: 1 | L82: 98 | M82: 5 | N82: 22 | O82: 1 | P82: 1.7522701 | Q82: 0.57068828 | R82: 2.2 | S82: =IF(AND(ISNUMBER(R82),R82>1,P82>0),R82/P82-1,"") -> 0.25551423 | T82: =IF(AND(ISNUMBER(P82),P82>0),P82*EXP('Read me'!$B$22),"") -> 2.1402275
A83: 2:30 | B83: Market Rasen | C83: Market Rasen Racecourse Conference & Events Mares Maiden Hurdle (GBB Race) | D83: Class 4 | E83: 17.5 | F83: Good | G83: 9 | H83: No More Teardrops | I83: Sheehan, Gavin | J83: Snowden, Jamie | K83: 6 | L83: 0 | M83: 4 | N83: 178 | O83: 2 | P83: 3.6316584 | Q83: 0.2753563 | R83: 2.5 | S83: =IF(AND(ISNUMBER(R83),R83>1,P83>0),R83/P83-1,"") -> -0.31160926 | T83: =IF(AND(ISNUMBER(P83),P83>0),P83*EXP('Read me'!$B$22),"") -> 4.4357175
A84: 2:30 | B84: Market Rasen | C84: Market Rasen Racecourse Conference & Events Mares Maiden Hurdle (GBB Race) | D84: Class 4 | E84: 17.5 | F84: Good | G84: 9 | H84: Poets Pearl (IRE) | I84: OBrien, P V | J84: Derham, Harry | K84: 7 | L84: 0 | M84: 4 | O84: 3 | P84: 9.6612298 | Q84: 0.10350649 | R84: 5 | S84: =IF(AND(ISNUMBER(R84),R84>1,P84>0),R84/P84-1,"") -> -0.48246754 | T84: =IF(AND(ISNUMBER(P84),P84>0),P84*EXP('Read me'!$B$22),"") -> 11.800253
A85: 2:30 | B85: Market Rasen | C85: Market Rasen Racecourse Conference & Events Mares Maiden Hurdle (GBB Race) | D85: Class 4 | E85: 17.5 | F85: Good | G85: 9 | H85: Adba (FR) | I85: Kimber, Harry | J85: Bramley, Faye | K85: 9 | L85: 0 | M85: 3 | N85: 38 | O85: 4 | P85: 55.943883 | Q85: 0.017875055 | R85: 41 | S85: =IF(AND(ISNUMBER(R85),R85>1,P85>0),R85/P85-1,"") -> -0.26712274 | T85: =IF(AND(ISNUMBER(P85),P85>0),P85*EXP('Read me'!$B$22),"") -> 68.330013
A86: 2:30 | B86: Market Rasen | C86: Market Rasen Racecourse Conference & Events Mares Maiden Hurdle (GBB Race) | D86: Class 4 | E86: 17.5 | F86: Good | G86: 9 | H86: Mighty Dink | I86: Skelton, Harry | J86: Skelton, Daniel | K86: 5 | L86: 0 | M86: 4 | N86: 12 | O86: 5 | P86: 63.32879 | Q86: 0.015790606 | R86: 34 | S86: =IF(AND(ISNUMBER(R86),R86>1,P86>0),R86/P86-1,"") -> -0.46311938 | T86: =IF(AND(ISNUMBER(P86),P86>0),P86*EXP('Read me'!$B$22),"") -> 77.349959
A87: 2:30 | B87: Market Rasen | C87: Market Rasen Racecourse Conference & Events Mares Maiden Hurdle (GBB Race) | D87: Class 4 | E87: 17.5 | F87: Good | G87: 9 | H87: Georgies Lady (IRE) | I87: Todd, C J | J87: Dennis, David | K87: 4 | L87: 0 | M87: 4 | N87: 22 | O87: 6 | P87: 128.79552 | Q87: 0.0077642455 | R87: 34 | S87: =IF(AND(ISNUMBER(R87),R87>1,P87>0),R87/P87-1,"") -> -0.73601565 | T87: =IF(AND(ISNUMBER(P87),P87>0),P87*EXP('Read me'!$B$22),"") -> 157.3112
A88: 2:30 | B88: Market Rasen | C88: Market Rasen Racecourse Conference & Events Mares Maiden Hurdle (GBB Race) | D88: Class 4 | E88: 17.5 | F88: Good | G88: 9 | H88: Chloes Courage | I88: Noonan, David G | J88: Ryan, J | K88: 3 | L88: 0 | M88: 4 | N88: 16 | O88: 7 | P88: 179.57599 | Q88: 0.0055686733 | R88: 34 | S88: =IF(AND(ISNUMBER(R88),R88>1,P88>0),R88/P88-1,"") -> -0.81066511 | T88: =IF(AND(ISNUMBER(P88),P88>0),P88*EXP('Read me'!$B$22),"") -> 219.3346
A89: 2:30 | B89: Market Rasen | C89: Market Rasen Racecourse Conference & Events Mares Maiden Hurdle (GBB Race) | D89: Class 4 | E89: 17.5 | F89: Good | G89: 9 | H89: Lara K (IRE) | I89: Ring, C V | J89: Williams, Mrs C | K89: 2 | L89: 0 | M89: 5 | N89: 8 | O89: 8 | P89: 476.59983 | Q89: 0.0020981963 | R89: 201 | S89: =IF(AND(ISNUMBER(R89),R89>1,P89>0),R89/P89-1,"") -> -0.57826254 | T89: =IF(AND(ISNUMBER(P89),P89>0),P89*EXP('Read me'!$B$22),"") -> 582.12034
A90: 2:30 | B90: Market Rasen | C90: Market Rasen Racecourse Conference & Events Mares Maiden Hurdle (GBB Race) | D90: Class 4 | E90: 17.5 | F90: Good | G90: 9 | H90: Sweet Cicely | I90: Maggs, Charlie | J90: Sowersby, M E | K90: 8 | L90: 0 | M90: 4 | N90: 12 | O90: 9 | P90: 739.56322 | Q90: 0.0013521494 | R90: 201 | S90: =IF(AND(ISNUMBER(R90),R90>1,P90>0),R90/P90-1,"") -> -0.72821796 | T90: =IF(AND(ISNUMBER(P90),P90>0),P90*EXP('Read me'!$B$22),"") -> 903.30456
A91: 2:35 | B91: Curragh | C91: Kwiff Supercharged Joe McGrath Handicap (Premier Handicap) | E91: 5 | F91: Good | G91: 20 | H91: Red Evolution (IRE) | I91: Holohan, Reese | J91: OCallaghan, M D | K91: 20 | L91: 85 | M91: 4 | N91: 13 | O91: 1 | P91: 6.6003902 | Q91: 0.15150619 | R91: 5.5 | S91: =IF(AND(ISNUMBER(R91),R91>1,P91>0),R91/P91-1,"") -> -0.16671593 | T91: =IF(AND(ISNUMBER(P91),P91>0),P91*EXP('Read me'!$B$22),"") -> 8.0617348
A92: 2:35 | B92: Curragh | C92: Kwiff Supercharged Joe McGrath Handicap (Premier Handicap) | E92: 5 | F92: Good | G92: 20 | H92: Dark Ace (IRE) | I92: Caffrey, Adam | J92: McGuinness, Adrian | K92: 1 | L92: 88 | M92: 4 | N92: 13 | O92: 2 | P92: 8.7366641 | Q92: 0.11446016 | R92: 5.5 | S92: =IF(AND(ISNUMBER(R92),R92>1,P92>0),R92/P92-1,"") -> -0.3704691 | T92: =IF(AND(ISNUMBER(P92),P92>0),P92*EXP('Read me'!$B$22),"") -> 10.670986
A93: 2:35 | B93: Curragh | C93: Kwiff Supercharged Joe McGrath Handicap (Premier Handicap) | E93: 5 | F93: Good | G93: 20 | H93: Moltophino (IRE) | I93: McDonogh, D P | J93: Kinsella, J A | K93: 11 | L93: 84 | M93: 5 | N93: 21 | O93: 3 | P93: 10.566071 | Q93: 0.094642557 | R93: 9 | S93: =IF(AND(ISNUMBER(R93),R93>1,P93>0),R93/P93-1,"") -> -0.14821699 | T93: =IF(AND(ISNUMBER(P93),P93>0),P93*EXP('Read me'!$B$22),"") -> 12.905429
A94: 2:35 | B94: Curragh | C94: Kwiff Supercharged Joe McGrath Handicap (Premier Handicap) | E94: 5 | F94: Good | G94: 20 | H94: Namiid (IRE) | I94: Coen, Ben M | J94: Murtagh, J P | K94: 10 | L94: 85 | M94: 3 | N94: 21 | O94: 4 | P94: 11.318948 | Q94: 0.088347429 | R94: 8 | S94: =IF(AND(ISNUMBER(R94),R94>1,P94>0),R94/P94-1,"") -> -0.29322057 | T94: =IF(AND(ISNUMBER(P94),P94>0),P94*EXP('Read me'!$B$22),"") -> 13.824995
A95: 2:35 | B95: Curragh | C95: Kwiff Supercharged Joe McGrath Handicap (Premier Handicap) | E95: 5 | F95: Good | G95: 20 | H95: Keke | I95: Keane, C T | J95: Lynam, Edward | K95: 9 | L95: 94 | M95: 6 | N95: 13 | O95: 5 | P95: 11.734683 | Q95: 0.085217468 | R95: 8 | S95: =IF(AND(ISNUMBER(R95),R95>1,P95>0),R95/P95-1,"") -> -0.31826026 | T95: =IF(AND(ISNUMBER(P95),P95>0),P95*EXP('Read me'!$B$22),"") -> 14.332775
A96: 2:35 | B96: Curragh | C96: Kwiff Supercharged Joe McGrath Handicap (Premier Handicap) | E96: 5 | F96: Good | G96: 20 | H96: Amerilis | I96: Burns, Nicola | J96: Scott, Gillian | K96: 5 | L96: 82 | M96: 3 | N96: 24 | O96: 6 | P96: 13.60835 | Q96: 0.073484293 | R96: 17 | S96: =IF(AND(ISNUMBER(R96),R96>1,P96>0),R96/P96-1,"") -> 0.24923299 | T96: =IF(AND(ISNUMBER(P96),P96>0),P96*EXP('Read me'!$B$22),"") -> 16.621277
A97: 2:35 | B97: Curragh | C97: Kwiff Supercharged Joe McGrath Handicap (Premier Handicap) | E97: 5 | F97: Good | G97: 20 | H97: Gazelle Dor (IRE) | I97: Lordan, W M | J97: Grassick, M C | K97: 3 | L97: 92 | M97: 4 | N97: 13 | O97: 7 | P97: 15.492831 | Q97: 0.064545984 | R97: 17 | S97: =IF(AND(ISNUMBER(R97),R97>1,P97>0),R97/P97-1,"") -> 0.097281725 | T97: =IF(AND(ISNUMBER(P97),P97>0),P97*EXP('Read me'!$B$22),"") -> 18.922986
A98: 2:35 | B98: Curragh | C98: Kwiff Supercharged Joe McGrath Handicap (Premier Handicap) | E98: 5 | F98: Good | G98: 20 | H98: Erosandpsyche (IRE) | I98: Carroll, G F | J98: Murphy, Daniel | K98: 7 | L98: 97 | M98: 8 | N98: 21 | O98: 8 | P98: 24.378979 | Q98: 0.041018945 | R98: 29 | S98: =IF(AND(ISNUMBER(R98),R98>1,P98>0),R98/P98-1,"") -> 0.1895494 | T98: =IF(AND(ISNUMBER(P98),P98>0),P98*EXP('Read me'!$B$22),"") -> 29.776552
A99: 2:35 | B99: Curragh | C99: Kwiff Supercharged Joe McGrath Handicap (Premier Handicap) | E99: 5 | F99: Good | G99: 20 | H99: Kendall Roy | I99: Hayes, C D | J99: McGivern, Miss | K99: 6 | L99: 99 | M99: 5 | N99: 27 | O99: 9 | P99: 24.641344 | Q99: 0.040582202 | R99: 21 | S99: =IF(AND(ISNUMBER(R99),R99>1,P99>0),R99/P99-1,"") -> -0.14777376 | T99: =IF(AND(ISNUMBER(P99),P99>0),P99*EXP('Read me'!$B$22),"") -> 30.097006
A100: 2:35 | B100: Curragh | C100: Kwiff Supercharged Joe McGrath Handicap (Premier Handicap) | E100: 5 | F100: Good | G100: 20 | H100: Stag Night (IRE) | I100: Lee, W J | J100: McCreery, W | K100: 2 | L100: 90 | M100: 8 | N100: 90 | O100: 10 | P100: 25.558611 | Q100: 0.039125757 | R100: 11 | S100: =IF(AND(ISNUMBER(R100),R100>1,P100>0),R100/P100-1,"") -> -0.56961668 | T100: =IF(AND(ISNUMBER(P100),P100>0),P100*EXP('Read me'!$B$22),"") -> 31.217358
A101: 2:35 | B101: Curragh | C101: Kwiff Supercharged Joe McGrath Handicap (Premier Handicap) | E101: 5 | F101: Good | G101: 20 | H101: Cuban Grey | I101: Mulligan, R M | J101: McKenna, P J | K101: 12 | L101: 75 | M101: 6 | N101: 24 | O101: 11 | P101: 27.074333 | Q101: 0.036935351 | R101: 19 | S101: =IF(AND(ISNUMBER(R101),R101>1,P101>0),R101/P101-1,"") -> -0.29822833 | T101: =IF(AND(ISNUMBER(P101),P101>0),P101*EXP('Read me'!$B$22),"") -> 33.068665
A102: 2:35 | B102: Curragh | C102: Kwiff Supercharged Joe McGrath Handicap (Premier Handicap) | E102: 5 | F102: Good | G102: 20 | H102: The Highway Rat (IRE) | I102: Sheridan, J M | J102: Oliver, Andrew | K102: 17 | L102: 93 | M102: 8 | N102: 13 | O102: 12 | P102: 35.240684 | Q102: 0.028376293 | R102: 21 | S102: =IF(AND(ISNUMBER(R102),R102>1,P102>0),R102/P102-1,"") -> -0.40409784 | T102: =IF(AND(ISNUMBER(P102),P102>0),P102*EXP('Read me'!$B$22),"") -> 43.043069
... A110: 2:35 | B110: Curragh | C110: Kwiff Supercharged Joe McGrath Handicap (Premier Handicap) | E110: 5 | F110: Good | G110: 20 | H110: Heddon Street (IRE) | I110: Joyce, Wesley | J110: Flynn, Leonard | K110: 15 | L110: 76 | M110: 3 | N110: 100 | O110: 20 | P110: 157.21209 | Q110: 0.0063608338 | R110: 51 | S110: =IF(AND(ISNUMBER(R110),R110>1,P110>0),R110/P110-1,"") -> -0.67559748 | T110: =IF(AND(ISNUMBER(P110),P110>0),P110*EXP('Read me'!$B$22),"") -> 192.01929
A111: 2:40 | B111: Haydock | C111: British EBF Fillies Novice Stakes (GBB Race) | D111: Class 3 | E111: 8 | F111: Heavy | G111: 9 | H111: Kaguyahime (IRE) | I111: Bowen, S D | J111: Varian, Roger | K111: 7 | L111: 0 | M111: 2 | N111: 22 | O111: 1 | P111: 2.5250319 | Q111: 0.3960346 | R111: 1.7272727 | S111: =IF(AND(ISNUMBER(R111),R111>1,P111>0),R111/P111-1,"") -> -0.31594024 | T111: =IF(AND(ISNUMBER(P111),P111>0),P111*EXP('Read me'!$B$22),"") -> 3.0840809
A112: 2:40 | B112: Haydock | C112: British EBF Fillies Novice Stakes (GBB Race) | D112: Class 3 | E112: 8 | F112: Heavy | G112: 9 | H112: My Girl Dee Mo (IRE) | I112: Probert, David | J112: Palmer, Hugo | K112: 4 | L112: 0 | M112: 2 | N112: 22 | O112: 2 | P112: 7.0988927 | Q112: 0.14086704 | R112: 10 | S112: =IF(AND(ISNUMBER(R112),R112>1,P112>0),R112/P112-1,"") -> 0.4086704 | T112: =IF(AND(ISNUMBER(P112),P112>0),P112*EXP('Read me'!$B$22),"") -> 8.6706071
A113: 2:40 | B113: Haydock | C113: British EBF Fillies Novice Stakes (GBB Race) | D113: Class 3 | E113: 8 | F113: Heavy | G113: 9 | H113: Shes Got A Way (IRE) | I113: James, S H | J113: Burke, K R | K113: 9 | L113: 0 | M113: 2 | N113: 15 | O113: 3 | P113: 7.9784821 | Q113: 0.12533712 | R113: 8.5 | S113: =IF(AND(ISNUMBER(R113),R113>1,P113>0),R113/P113-1,"") -> 0.065365553 | T113: =IF(AND(ISNUMBER(P113),P113>0),P113*EXP('Read me'!$B$22),"") -> 9.74494
A114: 2:40 | B114: Haydock | C114: British EBF Fillies Novice Stakes (GBB Race) | D114: Class 3 | E114: 8 | F114: Heavy | G114: 9 | H114: Perfect Gal (IRE) | I114: Fallon, Cieren | J114: Menzies, Rebecca | K114: 3 | L114: 0 | M114: 2 | N114: 23 | O114: 4 | P114: 11.223043 | Q114: 0.089102391 | R114: 15 | S114: =IF(AND(ISNUMBER(R114),R114>1,P114>0),R114/P114-1,"") -> 0.33653586 | T114: =IF(AND(ISNUMBER(P114),P114>0),P114*EXP('Read me'!$B$22),"") -> 13.707856
A115: 2:40 | B115: Haydock | C115: British EBF Fillies Novice Stakes (GBB Race) | D115: Class 3 | E115: 8 | F115: Heavy | G115: 9 | H115: Woollahra (IRE) | I115: Rodriguez, Callum | J115: Morland, Jack | K115: 6 | L115: 0 | M115: 2 | N115: 36 | O115: 5 | P115: 13.317788 | Q115: 0.075087542 | R115: 11 | S115: =IF(AND(ISNUMBER(R115),R115>1,P115>0),R115/P115-1,"") -> -0.17403704 | T115: =IF(AND(ISNUMBER(P115),P115>0),P115*EXP('Read me'!$B$22),"") -> 16.266384
...

Sheet Newmarket (Rowley)
A1: Time | B1: Course | C1: Race | D1: Class | E1: Furlongs | F1: Going | G1: Runners | H1: Horse | I1: Jockey | J1: Trainer | K1: Draw | L1: OR | M1: Age | N1: Days since run | O1: Model rank | P1: Predicted BSP | Q1: Win probability | R1: Card odds (HRB) | S1: Card odds vs model | T1: Rule: back at Betfair ≥
A2: 1:22 | B2: Newmarket (Rowley) | C2: British Stallion Studs EBF Jersey Lily Fillies Nursery | D2: Class 2 | E2: 7 | F2: Good To Firm | G2: 10 | H2: Al Samsama (IRE) | I2: Loughnane, Billy | J2: Hughes, Richard | K2: 2 | L2: 85 | M2: 2 | N2: 18 | O2: 1 | P2: 5.4223912 | Q2: 0.18442048 | R2: 7.5 | S2: =IF(AND(ISNUMBER(R2),R2>1,P2>0),R2/P2-1,"") -> 0.38315362 | T2: =IF(AND(ISNUMBER(P2),P2>0),P2*EXP('Read me'!$B$22),"") -> 6.6229235
A3: 1:22 | B3: Newmarket (Rowley) | C3: British Stallion Studs EBF Jersey Lily Fillies Nursery | D3: Class 2 | E3: 7 | F3: Good To Firm | G3: 10 | H3: Next Of Kin | I3: Marquand, Tom | J3: Haggas, W J | K3: 3 | L3: 76 | M3: 2 | N3: 8 | O3: 2 | P3: 7.3693735 | Q3: 0.13569675 | R3: 8.5 | S3: =IF(AND(ISNUMBER(R3),R3>1,P3>0),R3/P3-1,"") -> 0.15342234 | T3: =IF(AND(ISNUMBER(P3),P3>0),P3*EXP('Read me'!$B$22),"") -> 9.0009731
A4: 1:22 | B4: Newmarket (Rowley) | C4: British Stallion Studs EBF Jersey Lily Fillies Nursery | D4: Class 2 | E4: 7 | F4: Good To Firm | G4: 10 | H4: Zephyra | I4: Murphy, Oisin | J4: Botti, M | K4: 4 | L4: 77 | M4: 2 | N4: 10 | O4: 3 | P4: 7.8795883 | Q4: 0.12691018 | R4: 10 | S4: =IF(AND(ISNUMBER(R4),R4>1,P4>0),R4/P4-1,"") -> 0.26910183 | T4: =IF(AND(ISNUMBER(P4),P4>0),P4*EXP('Read me'!$B$22),"") -> 9.6241509
A5: 1:22 | B5: Newmarket (Rowley) | C5: British Stallion Studs EBF Jersey Lily Fillies Nursery | D5: Class 2 | E5: 7 | F5: Good To Firm | G5: 10 | H5: Marsala (IRE) | I5: Ryan, Rossa | J5: Beckett, R M | K5: 6 | L5: 74 | M5: 2 | N5: 22 | O5: 4 | P5: 8.3992734 | Q5: 0.11905792 | R5: 7 | S5: =IF(AND(ISNUMBER(R5),R5>1,P5>0),R5/P5-1,"") -> -0.16659457 | T5: =IF(AND(ISNUMBER(P5),P5>0),P5*EXP('Read me'!$B$22),"") -> 10.258896
A6: 1:22 | B6: Newmarket (Rowley) | C6: British Stallion Studs EBF Jersey Lily Fillies Nursery | D6: Class 2 | E6: 7 | F6: Good To Firm | G6: 10 | H6: Fire Thunder (IRE) | I6: Sousa, Silvestre De | J6: Botti, M | K6: 8 | L6: 70 | M6: 2 | N6: 42 | O6: 5 | P6: 9.2469802 | Q6: 0.10814341 | R6: 4.5 | S6: =IF(AND(ISNUMBER(R6),R6>1,P6>0),R6/P6-1,"") -> -0.51335464 | T6: =IF(AND(ISNUMBER(P6),P6>0),P6*EXP('Read me'!$B$22),"") -> 11.294287
A7: 1:22 | B7: Newmarket (Rowley) | C7: British Stallion Studs EBF Jersey Lily Fillies Nursery | D7: Class 2 | E7: 7 | F7: Good To Firm | G7: 10 | H7: Bymiddaytomorrow (IRE) | I7: Lee, Clifford | J7: Walker, Ed | K7: 9 | L7: 82 | M7: 2 | N7: 16 | O7: 6 | P7: 10.374905 | Q7: 0.096386429 | R7: 9.5 | S7: =IF(AND(ISNUMBER(R7),R7>1,P7>0),R7/P7-1,"") -> -0.084328923 | T7: =IF(AND(ISNUMBER(P7),P7>0),P7*EXP('Read me'!$B$22),"") -> 12.671937
A8: 1:22 | B8: Newmarket (Rowley) | C8: British Stallion Studs EBF Jersey Lily Fillies Nursery | D8: Class 2 | E8: 7 | F8: Good To Firm | G8: 10 | H8: Polyxena (IRE) | I8: Ghiani, Marco | J8: Williams, S C | K8: 1 | L8: 82 | M8: 2 | N8: 19 | O8: 7 | P8: 11.21555 | Q8: 0.089161921 | R8: 7 | S8: =IF(AND(ISNUMBER(R8),R8>1,P8>0),R8/P8-1,"") -> -0.37586655 | T8: =IF(AND(ISNUMBER(P8),P8>0),P8*EXP('Read me'!$B$22),"") -> 13.698704
A9: 1:22 | B9: Newmarket (Rowley) | C9: British Stallion Studs EBF Jersey Lily Fillies Nursery | D9: Class 2 | E9: 7 | F9: Good To Firm | G9: 10 | H9: Tansy Lane | I9: Havlin, Robert | J9: Owen, J P | K9: 7 | L9: 74 | M9: 2 | N9: 43 | O9: 8 | P9: 11.866381 | Q9: 0.084271692 | R9: 13 | S9: =IF(AND(ISNUMBER(R9),R9>1,P9>0),R9/P9-1,"") -> 0.095531993 | T9: =IF(AND(ISNUMBER(P9),P9>0),P9*EXP('Read me'!$B$22),"") -> 14.49363
A10: 1:22 | B10: Newmarket (Rowley) | C10: British Stallion Studs EBF Jersey Lily Fillies Nursery | D10: Class 2 | E10: 7 | F10: Good To Firm | G10: 10 | H10: Kiah (IRE) | I10: Egan, David | J10: Meehan, B J | K10: 5 | L10: 76 | M10: 2 | N10: 30 | O10: 9 | P10: 34.251046 | Q10: 0.029196189 | R10: 13 | S10: =IF(AND(ISNUMBER(R10),R10>1,P10>0),R10/P10-1,"") -> -0.62044955 | T10: =IF(AND(ISNUMBER(P10),P10>0),P10*EXP('Read me'!$B$22),"") -> 41.834322
A11: 1:22 | B11: Newmarket (Rowley) | C11: British Stallion Studs EBF Jersey Lily Fillies Nursery | D11: Class 2 | E11: 7 | F11: Good To Firm | G11: 10 | H11: Tie A Navyribbon | I11: Gordon, Josephine | J11: Stone, W B | K11: 10 | L11: 80 | M11: 2 | N11: 16 | O11: 10 | P11: 37.376154 | Q11: 0.026755027 | R11: 29 | S11: =IF(AND(ISNUMBER(R11),R11>1,P11>0),R11/P11-1,"") -> -0.22410423 | T11: =IF(AND(ISNUMBER(P11),P11>0),P11*EXP('Read me'!$B$22),"") -> 45.651338
A12: 1:55 | B12: Newmarket (Rowley) | C12: Tattersalls Online Royal Lodge Stakes (Group 2) | E12: 8 | F12: Good To Firm | G12: 7 | H12: Haffner (USA) | I12: Moore, Ryan | J12: OBrien, A P | K12: 4 | L12: 110 | M12: 2 | N12: 13 | O12: 1 | P12: 4.1555937 | Q12: 0.2406395 | R12: 4.5 | S12: =IF(AND(ISNUMBER(R12),R12>1,P12>0),R12/P12-1,"") -> 0.082877751 | T12: =IF(AND(ISNUMBER(P12),P12>0),P12*EXP('Read me'!$B$22),"") -> 5.0756537
A13: 1:55 | B13: Newmarket (Rowley) | C13: Tattersalls Online Royal Lodge Stakes (Group 2) | E13: 8 | F13: Good To Firm | G13: 7 | H13: First Law (IRE) | I13: Buick, William | J13: Appleby, Charlie | K13: 2 | L13: 101 | M13: 2 | N13: 21 | O13: 2 | P13: 4.324806 | Q13: 0.23122425 | R13: 4.5 | S13: =IF(AND(ISNUMBER(R13),R13>1,P13>0),R13/P13-1,"") -> 0.040509104 | T13: =IF(AND(ISNUMBER(P13),P13>0),P13*EXP('Read me'!$B$22),"") -> 5.28233
A14: 1:55 | B14: Newmarket (Rowley) | C14: Tattersalls Online Royal Lodge Stakes (Group 2) | E14: 8 | F14: Good To Firm | G14: 7 | H14: Quest For Stars (FR) | I14: Loughnane, Billy | J14: Appleby, Charlie | K14: 6 | L14: 105 | M14: 2 | N14: 14 | O14: 3 | P14: 4.8755087 | Q14: 0.2051068 | R14: 5 | S14: =IF(AND(ISNUMBER(R14),R14>1,P14>0),R14/P14-1,"") -> 0.025534021 | T14: =IF(AND(ISNUMBER(P14),P14>0),P14*EXP('Read me'!$B$22),"") -> 5.9549597
A15: 1:55 | B15: Newmarket (Rowley) | C15: Tattersalls Online Royal Lodge Stakes (Group 2) | E15: 8 | F15: Good To Firm | G15: 7 | H15: Burning Up | I15: Lee, Clifford | J15: Burke, K R | K15: 7 | L15: 97 | M15: 2 | N15: 23 | O15: 4 | P15: 7.4636157 | Q15: 0.13398332 | R15: 4.5 | S15: =IF(AND(ISNUMBER(R15),R15>1,P15>0),R15/P15-1,"") -> -0.39707507 | T15: =IF(AND(ISNUMBER(P15),P15>0),P15*EXP('Read me'!$B$22),"") -> 9.1160808
A16: 1:55 | B16: Newmarket (Rowley) | C16: Tattersalls Online Royal Lodge Stakes (Group 2) | E16: 8 | F16: Good To Firm | G16: 7 | H16: Quicken Away (USA) | I16: Murphy, Oisin | J16: Balding, A M | K16: 5 | L16: 0 | M16: 2 | N16: 18 | O16: 5 | P16: 9.0785 | Q16: 0.11015036 | R16: 7 | S16: =IF(AND(ISNUMBER(R16),R16>1,P16>0),R16/P16-1,"") -> -0.22894751 | T16: =IF(AND(ISNUMBER(P16),P16>0),P16*EXP('Read me'!$B$22),"") -> 11.088505
A17: 1:55 | B17: Newmarket (Rowley) | C17: Tattersalls Online Royal Lodge Stakes (Group 2) | E17: 8 | F17: Good To Firm | G17: 7 | H17: Rocket Boy (IRE) | I17: Ghiani, Marco | J17: Botti, M | K17: 3 | L17: 100 | M17: 2 | N17: 21 | O17: 6 | P17: 19.160325 | Q17: 0.052191181 | R17: 17 | S17: =IF(AND(ISNUMBER(R17),R17>1,P17>0),R17/P17-1,"") -> -0.11274993 | T17: =IF(AND(ISNUMBER(P17),P17>0),P17*EXP('Read me'!$B$22),"") -> 23.402474
A18: 1:55 | B18: Newmarket (Rowley) | C18: Tattersalls Online Royal Lodge Stakes (Group 2) | E18: 8 | F18: Good To Firm | G18: 7 | H18: Iwasjustsaying | I18: Mitchell, Jack | J18: Johnston, Charlie | K18: 1 | L18: 86 | M18: 2 | N18: 18 | O18: 7 | P18: 37.446739 | Q18: 0.026704595 | R18: 23 | S18: =IF(AND(ISNUMBER(R18),R18>1,P18>0),R18/P18-1,"") -> -0.38579431 | T18: =IF(AND(ISNUMBER(P18),P18>0),P18*EXP('Read me'!$B$22),"") -> 45.73755
A19: 2:27 | B19: Newmarket (Rowley) | C19: Tattersalls Sceptre Sessions Cheveley Park Stakes (Fillies Group 1) | E19: 6 | F19: Good To Firm | G19: 6 | H19: Sun Goddess (IRE) | I19: Moore, Ryan | J19: OBrien, A P | K19: 6 | L19: 119 | M19: 2 | N19: 13 | O19: 1 | P19: 1.8278127 | Q19: 0.547102 | R19: 2.5 | S19: =IF(AND(ISNUMBER(R19),R19>1,P19>0),R19/P19-1,"") -> 0.36775501 | T19: =IF(AND(ISNUMBER(P19),P19>0),P19*EXP('Read me'!$B$22),"") -> 2.2324955
A20: 2:27 | B20: Newmarket (Rowley) | C20: Tattersalls Sceptre Sessions Cheveley Park Stakes (Fillies Group 1) | E20: 6 | F20: Good To Firm | G20: 6 | H20: Libertango (IRE) | I20: Loughnane, Billy | J20: Boughey, George | K20: 2 | L20: 107 | M20: 2 | N20: 37 | O20: 2 | P20: 6.5055108 | Q20: 0.15371583 | R20: 5.5 | S20: =IF(AND(ISNUMBER(R20),R20>1,P20>0),R20/P20-1,"") -> -0.15456293 | T20: =IF(AND(ISNUMBER(P20),P20>0),P20*EXP('Read me'!$B$22),"") -> 7.9458488
A21: 2:27 | B21: Newmarket (Rowley) | C21: Tattersalls Sceptre Sessions Cheveley Park Stakes (Fillies Group 1) | E21: 6 | F21: Good To Firm | G21: 6 | H21: Senorita Bonita (IRE) | I21: Murphy, Oisin | J21: Crisford, Simon | K21: 1 | L21: 117 | M21: 2 | N21: 78 | O21: 3 | P21: 6.5580225 | Q21: 0.15248499 | R21: 3 | S21: =IF(AND(ISNUMBER(R21),R21>1,P21>0),R21/P21-1,"") -> -0.54254503 | T21: =IF(AND(ISNUMBER(P21),P21>0),P21*EXP('Read me'!$B$22),"") -> 8.0099868
A22: 2:27 | B22: Newmarket (Rowley) | C22: Tattersalls Sceptre Sessions Cheveley Park Stakes (Fillies Group 1) | E22: 6 | F22: Good To Firm | G22: 6 | H22: Alwaysanangel (IRE) | I22: Buick, William | J22: OBrien, Joseph Patrick | K22: 3 | L22: 104 | M22: 2 | N22: 43 | O22: 4 | P22: 12.459672 | Q22: 0.080258936 | R22: 11 | S22: =IF(AND(ISNUMBER(R22),R22>1,P22>0),R22/P22-1,"") -> -0.11715171 | T22: =IF(AND(ISNUMBER(P22),P22>0),P22*EXP('Read me'!$B$22),"") -> 15.218278
A23: 2:27 | B23: Newmarket (Rowley) | C23: Tattersalls Sceptre Sessions Cheveley Park Stakes (Fillies Group 1) | E23: 6 | F23: Good To Firm | G23: 6 | H23: Moonrise (IRE) | I23: Marquand, Tom | J23: Balding, A M | K23: 5 | L23: 109 | M23: 2 | N23: 21 | O23: 5 | P23: 16.851917 | Q23: 0.05934043 | R23: 17 | S23: =IF(AND(ISNUMBER(R23),R23>1,P23>0),R23/P23-1,"") -> 0.0087873064 | T23: =IF(AND(ISNUMBER(P23),P23>0),P23*EXP('Read me'!$B$22),"") -> 20.582978
... A31: 3:00 | B31: Newmarket (Rowley) | C31: Tattersalls Middle Park Stakes (Group 1) | E31: 6 | F31: Good To Firm | G31: 7 | H31: Force Noir (IRE) | I31: Egan, David | J31: Aguiar, Robson | K31: 3 | L31: 94 | M31: 2 | N31: 8 | O31: 7 | P31: 107.78667 | Q31: 0.0092775848 | R31: 67 | S31: =IF(AND(ISNUMBER(R31),R31>1,P31>0),R31/P31-1,"") -> -0.37840182 | T31: =IF(AND(ISNUMBER(P31),P31>0),P31*EXP('Read me'!$B$22),"") -> 131.65094
A32: 3:40 | B32: Newmarket (Rowley) | C32: bet365 Cambridgeshire (Heritage Handicap) | D32: Class 2 | E32: 9 | F32: Good To Firm | G32: 27 | H32: Gavriel | I32: Havlin, Robert | J32: Gosden, John and Thady | K32: 28 | L32: 99 | M32: 3 | N32: 21 | O32: 1 | P32: 8.5823655 | Q32: 0.11651799 | R32: 5 | S32: =IF(AND(ISNUMBER(R32),R32>1,P32>0),R32/P32-1,"") -> -0.41741004 | T32: =IF(AND(ISNUMBER(P32),P32>0),P32*EXP('Read me'!$B$22),"") -> 10.482525
A33: 3:40 | B33: Newmarket (Rowley) | C33: bet365 Cambridgeshire (Heritage Handicap) | D33: Class 2 | E33: 9 | F33: Good To Firm | G33: 27 | H33: Bourbon Blues | I33: Moore, Ryan | J33: Meehan, B J | K33: 13 | L33: 105 | M33: 3 | N33: 16 | O33: 2 | P33: 10.901632 | Q33: 0.091729387 | R33: 11 | S33: =IF(AND(ISNUMBER(R33),R33>1,P33>0),R33/P33-1,"") -> 0.0090232517 | T33: =IF(AND(ISNUMBER(P33),P33>0),P33*EXP('Read me'!$B$22),"") -> 13.315283
A34: 3:40 | B34: Newmarket (Rowley) | C34: bet365 Cambridgeshire (Heritage Handicap) | D34: Class 2 | E34: 9 | F34: Good To Firm | G34: 27 | H34: Shafdar (IRE) | I34: Buick, William | J34: Williams, Ian | K34: 5 | L34: 93 | M34: 4 | N34: 14 | O34: 3 | P34: 12.89285 | Q34: 0.07756237 | R34: 26 | S34: =IF(AND(ISNUMBER(R34),R34>1,P34>0),R34/P34-1,"") -> 1.0166216 | T34: =IF(AND(ISNUMBER(P34),P34>0),P34*EXP('Read me'!$B$22),"") -> 15.747362
A35: 3:40 | B35: Newmarket (Rowley) | C35: bet365 Cambridgeshire (Heritage Handicap) | D35: Class 2 | E35: 9 | F35: Good To Firm | G35: 27 | H35: Indalo (IRE) | I35: Dawson, R | J35: Varian, Roger | K35: 26 | L35: 104 | M35: 5 | N35: 57 | O35: 4 | P35: 13.646506 | Q35: 0.073278829 | R35: 9.5 | S35: =IF(AND(ISNUMBER(R35),R35>1,P35>0),R35/P35-1,"") -> -0.30385112 | T35: =IF(AND(ISNUMBER(P35),P35>0),P35*EXP('Read me'!$B$22),"") -> 16.66788
A36: 3:40 | B36: Newmarket (Rowley) | C36: bet365 Cambridgeshire (Heritage Handicap) | D36: Class 2 | E36: 9 | F36: Good To Firm | G36: 27 | H36: Hand Of God | I36: Edmunds, Lewis | J36: Charlton, Roger/Harry | K36: 24 | L36: 106 | M36: 5 | N36: 77 | O36: 5 | P36: 15.73198 | Q36: 0.063564792 | R36: 9.5 | S36: =IF(AND(ISNUMBER(R36),R36>1,P36>0),R36/P36-1,"") -> -0.39613448 | T36: =IF(AND(ISNUMBER(P36),P36>0),P36*EXP('Read me'!$B$22),"") -> 19.215083
A37: 3:40 | B37: Newmarket (Rowley) | C37: bet365 Cambridgeshire (Heritage Handicap) | D37: Class 2 | E37: 9 | F37: Good To Firm | G37: 27 | H37: Alcarath (IRE) | I37: Ryan, Rossa | J37: King, A | K37: 1 | L37: 92 | M37: 4 | N37: 28 | O37: 6 | P37: 18.156636 | Q37: 0.055076281 | R37: 13 | S37: =IF(AND(ISNUMBER(R37),R37>1,P37>0),R37/P37-1,"") -> -0.28400835 | T37: =IF(AND(ISNUMBER(P37),P37>0),P37*EXP('Read me'!$B$22),"") -> 22.176566
A38: 3:40 | B38: Newmarket (Rowley) | C38: bet365 Cambridgeshire (Heritage Handicap) | D38: Class 2 | E38: 9 | F38: Good To Firm | G38: 27 | H38: Harmonics (IRE) | I38: Foley, Shane | J38: Gosden, John and Thady | K38: 18 | L38: 97 | M38: 3 | N38: 19 | O38: 7 | P38: 18.309284 | Q38: 0.0546171 | R38: 13 | S38: =IF(AND(ISNUMBER(R38),R38>1,P38>0),R38/P38-1,"") -> -0.2899777 | T38: =IF(AND(ISNUMBER(P38),P38>0),P38*EXP('Read me'!$B$22),"") -> 22.36301
A39: 3:40 | B39: Newmarket (Rowley) | C39: bet365 Cambridgeshire (Heritage Handicap) | D39: Class 2 | E39: 9 | F39: Good To Firm | G39: 27 | H39: Pierre Royal (IRE) | I39: Sheehy, M P | J39: McGuinness, Adrian | K39: 9 | L39: 91 | M39: 4 | N39: 13 | O39: 8 | P39: 20.336599 | Q39: 0.04917243 | R39: 34 | S39: =IF(AND(ISNUMBER(R39),R39>1,P39>0),R39/P39-1,"") -> 0.6718626 | T39: =IF(AND(ISNUMBER(P39),P39>0),P39*EXP('Read me'!$B$22),"") -> 24.839179
A40: 3:40 | B40: Newmarket (Rowley) | C40: bet365 Cambridgeshire (Heritage Handicap) | D40: Class 2 | E40: 9 | F40: Good To Firm | G40: 27 | H40: Spanish Voice | I40: Murphy, Oisin | J40: Balding, A M | K40: 11 | L40: 94 | M40: 4 | N40: 22 | O40: 9 | P40: 23.522031 | Q40: 0.042513336 | R40: 15 | S40: =IF(AND(ISNUMBER(R40),R40>1,P40>0),R40/P40-1,"") -> -0.36229996 | T40: =IF(AND(ISNUMBER(P40),P40>0),P40*EXP('Read me'!$B$22),"") -> 28.729873
A41: 3:40 | B41: Newmarket (Rowley) | C41: bet365 Cambridgeshire (Heritage Handicap) | D41: Class 2 | E41: 9 | F41: Good To Firm | G41: 27 | H41: Erzindjan (IRE) | I41: Loughnane, Billy | J41: Kent, T J | K41: 25 | L41: 100 | M41: 8 | N41: 35 | O41: 10 | P41: 24.327207 | Q41: 0.04110624 | R41: 9 | S41: =IF(AND(ISNUMBER(R41),R41>1,P41>0),R41/P41-1,"") -> -0.63004384 | T41: =IF(AND(ISNUMBER(P41),P41>0),P41*EXP('Read me'!$B$22),"") -> 29.713317
A42: 3:40 | B42: Newmarket (Rowley) | C42: bet365 Cambridgeshire (Heritage Handicap) | D42: Class 2 | E42: 9 | F42: Good To Firm | G42: 27 | H42: Thunder Run (IRE) | I42: Lee, Clifford | J42: Burke, K R | K42: 16 | L42: 108 | M42: 5 | N42: 14 | O42: 11 | P42: 24.975489 | Q42: 0.040039257 | R42: 26 | S42: =IF(AND(ISNUMBER(R42),R42>1,P42>0),R42/P42-1,"") -> 0.041020678 | T42: =IF(AND(ISNUMBER(P42),P42>0),P42*EXP('Read me'!$B$22),"") -> 30.505131
A43: 3:40 | B43: Newmarket (Rowley) | C43: bet365 Cambridgeshire (Heritage Handicap) | D43: Class 2 | E43: 9 | F43: Good To Firm | G43: 27 | H43: Wild Thoughts (IRE) | I43: Osborne, Saffie | J43: Spencer, Richard | K43: 19 | L43: 93 | M43: 3 | N43: 9 | O43: 12 | P43: 28.305055 | Q43: 0.035329378 | R43: 17 | S43: =IF(AND(ISNUMBER(R43),R43>1,P43>0),R43/P43-1,"") -> -0.39940057 | T43: =IF(AND(ISNUMBER(P43),P43>0),P43*EXP('Read me'!$B$22),"") -> 34.571873
... A61: 4:15 | B61: Newmarket (Rowley) | C61: Blandford Bloodstock 25th Anniversary EBF Maiden Fillies Stakes (GBB Race) | D61: Class 2 | E61: 7 | F61: Good To Firm | G61: 11 | H61: La Pittura | I61: Murphy, Oisin | J61: Balding, A M | K61: 10 | L61: 0 | M61: 2 | N61: 21 | O61: 3 | P61: 7.5001601 | Q61: 0.13333049 | R61: 4.3333333 | S61: =IF(AND(ISNUMBER(R61),R61>1,P61>0),R61/P61-1,"") -> -0.42223456 | T61: =IF(AND(ISNUMBER(P61),P61>0),P61*EXP('Read me'!$B$22),"") -> 9.1607163
A62: 4:15 | B62: Newmarket (Rowley) | C62: Blandford Bloodstock 25th Anniversary EBF Maiden Fillies Stakes (GBB Race) | D62: Class 2 | E62: 7 | F62: Good To Firm | G62: 11 | H62: Miss Jane Hadley (IRE) | I62: Mitchell, Jack | J62: Varian, Roger | K62: 11 | L62: 0 | M62: 2 | O62: 4 | P62: 7.9730899 | Q62: 0.12542189 | R62: 9.5 | S62: =IF(AND(ISNUMBER(R62),R62>1,P62>0),R62/P62-1,"") -> 0.19150794 | T62: =IF(AND(ISNUMBER(P62),P62>0),P62*EXP('Read me'!$B$22),"") -> 9.7383541
A63: 4:15 | B63: Newmarket (Rowley) | C63: Blandford Bloodstock 25th Anniversary EBF Maiden Fillies Stakes (GBB Race) | D63: Class 2 | E63: 7 | F63: Good To Firm | G63: 11 | H63: Out Late (IRE) | I63: Dawson, R | J63: Varian, Roger | K63: 8 | L63: 0 | M63: 2 | O63: 5 | P63: 9.8741007 | Q63: 0.10127505 | R63: 8 | S63: =IF(AND(ISNUMBER(R63),R63>1,P63>0),R63/P63-1,"") -> -0.18979963 | T63: =IF(AND(ISNUMBER(P63),P63>0),P63*EXP('Read me'!$B$22),"") -> 12.060254
A64: 4:15 | B64: Newmarket (Rowley) | C64: Blandford Bloodstock 25th Anniversary EBF Maiden Fillies Stakes (GBB Race) | D64: Class 2 | E64: 7 | F64: Good To Firm | G64: 11 | H64: Queen Of The Gulf | I64: Loughnane, Billy | J64: Hughes, Richard | K64: 5 | L64: 0 | M64: 2 | O64: 6 | P64: 14.716009 | Q64: 0.067953205 | R64: 6 | S64: =IF(AND(ISNUMBER(R64),R64>1,P64>0),R64/P64-1,"") -> -0.59228077 | T64: =IF(AND(ISNUMBER(P64),P64>0),P64*EXP('Read me'!$B$22),"") -> 17.974174
A65: 4:15 | B65: Newmarket (Rowley) | C65: Blandford Bloodstock 25th Anniversary EBF Maiden Fillies Stakes (GBB Race) | D65: Class 2 | E65: 7 | F65: Good To Firm | G65: 11 | H65: Aquila Doro | I65: Osborne, Saffie | J65: Cole, Oliver | K65: 3 | L65: 0 | M65: 2 | O65: 7 | P65: 22.077978 | Q65: 0.045294002 | R65: 10 | S65: =IF(AND(ISNUMBER(R65),R65>1,P65>0),R65/P65-1,"") -> -0.54705998 | T65: =IF(AND(ISNUMBER(P65),P65>0),P65*EXP('Read me'!$B$22),"") -> 26.966104
A66: 4:15 | B66: Newmarket (Rowley) | C66: Blandford Bloodstock 25th Anniversary EBF Maiden Fillies Stakes (GBB Race) | D66: Class 2 | E66: 7 | F66: Good To Firm | G66: 11 | H66: Friendly Force | I66: Egan, David | J66: Foy, Kevin | K66: 9 | L66: 0 | M66: 2 | N66: 45 | O66: 8 | P66: 23.470791 | Q66: 0.042606148 | R66: 23 | S66: =IF(AND(ISNUMBER(R66),R66>1,P66>0),R66/P66-1,"") -> -0.020058605 | T66: =IF(AND(ISNUMBER(P66),P66>0),P66*EXP('Read me'!$B$22),"") -> 28.667289
A67: 4:15 | B67: Newmarket (Rowley) | C67: Blandford Bloodstock 25th Anniversary EBF Maiden Fillies Stakes (GBB Race) | D67: Class 2 | E67: 7 | F67: Good To Firm | G67: 11 | H67: Lady Jemima | I67: Ghiani, Marco | J67: Owen, J P | K67: 2 | L67: 0 | M67: 2 | N67: 12 | O67: 9 | P67: 25.734175 | Q67: 0.038858833 | R67: 41 | S67: =IF(AND(ISNUMBER(R67),R67>1,P67>0),R67/P67-1,"") -> 0.59321214 | T67: =IF(AND(ISNUMBER(P67),P67>0),P67*EXP('Read me'!$B$22),"") -> 31.431792
A68: 4:15 | B68: Newmarket (Rowley) | C68: Blandford Bloodstock 25th Anniversary EBF Maiden Fillies Stakes (GBB Race) | D68: Class 2 | E68: 7 | F68: Good To Firm | G68: 11 | H68: Via Star (IRE) | I68: Leavy, Joe | J68: Hannon (Jnr), Richard | K68: 6 | L68: 0 | M68: 2 | O68: 10 | P68: 40.707171 | Q68: 0.024565696 | R68: 12 | S68: =IF(AND(ISNUMBER(R68),R68>1,P68>0),R68/P68-1,"") -> -0.70521165 | T68: =IF(AND(ISNUMBER(P68),P68>0),P68*EXP('Read me'!$B$22),"") -> 49.719851
A69: 4:15 | B69: Newmarket (Rowley) | C69: Blandford Bloodstock 25th Anniversary EBF Maiden Fillies Stakes (GBB Race) | D69: Class 2 | E69: 7 | F69: Good To Firm | G69: 11 | H69: Reveillez (GER) | I69: Fraser, Kaiya | J69: Eustace, Harry | K69: 1 | L69: 0 | M69: 2 | N69: 23 | O69: 11 | P69: 120.84571 | Q69: 0.0082750146 | R69: 51 | S69: =IF(AND(ISNUMBER(R69),R69>1,P69>0),R69/P69-1,"") -> -0.57797425 | T69: =IF(AND(ISNUMBER(P69),P69>0),P69*EXP('Read me'!$B$22),"") -> 147.60128
A70: 4:50 | B70: Newmarket (Rowley) | C70: Hunt Family Fund Handicap | D70: Class 2 | E70: 7 | F70: Good To Firm | G70: 12 | H70: Addison Grey | I70: Ryan, Rossa | J70: Cox, C G | K70: 13 | L70: 97 | M70: 4 | N70: 21 | O70: 1 | P70: 5.1314532 | Q70: 0.19487657 | R70: 5 | S70: =IF(AND(ISNUMBER(R70),R70>1,P70>0),R70/P70-1,"") -> -0.025617152 | T70: =IF(AND(ISNUMBER(P70),P70>0),P70*EXP('Read me'!$B$22),"") -> 6.2675711
A71: 4:50 | B71: Newmarket (Rowley) | C71: Hunt Family Fund Handicap | D71: Class 2 | E71: 7 | F71: Good To Firm | G71: 12 | H71: The Fingal Raven (IRE) | I71: Osborne, Saffie | J71: Osborne, J A | K71: 7 | L71: 92 | M71: 4 | N71: 7 | O71: 2 | P71: 6.7842406 | Q71: 0.14740043 | R71: 5.5 | S71: =IF(AND(ISNUMBER(R71),R71>1,P71>0),R71/P71-1,"") -> -0.18929761 | T71: =IF(AND(ISNUMBER(P71),P71>0),P71*EXP('Read me'!$B$22),"") -> 8.2862901
A72: 4:50 | B72: Newmarket (Rowley) | C72: Hunt Family Fund Handicap | D72: Class 2 | E72: 7 | F72: Good To Firm | G72: 12 | H72: Arctic Dawn | I72: Loughnane, Billy | J72: Kubler, Daniel | K72: 10 | L72: 102 | M72: 5 | N72: 37 | O72: 3 | P72: 7.1671781 | Q72: 0.13952493 | R72: 6 | S72: =IF(AND(ISNUMBER(R72),R72>1,P72>0),R72/P72-1,"") -> -0.16285044 | T72: =IF(AND(ISNUMBER(P72),P72>0),P72*EXP('Read me'!$B$22),"") -> 8.7540111
A73: 4:50 | B73: Newmarket (Rowley) | C73: Hunt Family Fund Handicap | D73: Class 2 | E73: 7 | F73: Good To Firm | G73: 12 | H73: Huscal (IRE) | I73: Ghiani, Marco | J73: Hills, Charles | K73: 5 | L73: 88 | M73: 4 | N73: 15 | O73: 4 | P73: 9.2046114 | Q73: 0.1086412 | R73: 8 | S73: =IF(AND(ISNUMBER(R73),R73>1,P73>0),R73/P73-1,"") -> -0.13087043 | T73: =IF(AND(ISNUMBER(P73),P73>0),P73*EXP('Read me'!$B$22),"") -> 11.242538
A74: 4:50 | B74: Newmarket (Rowley) | C74: Hunt Family Fund Handicap | D74: Class 2 | E74: 7 | F74: Good To Firm | G74: 12 | H74: Sword Maker (IRE) | I74: Murphy, Oisin | J74: Suroor, Saeed Bin | K74: 8 | L74: 96 | M74: 3 | N74: 359 | O74: 5 | P74: 9.2803103 | Q74: 0.10775502 | R74: 4.5 | S74: =IF(AND(ISNUMBER(R74),R74>1,P74>0),R74/P74-1,"") -> -0.51510242 | T74: =IF(AND(ISNUMBER(P74),P74>0),P74*EXP('Read me'!$B$22),"") -> 11.334997
A75: 4:50 | B75: Newmarket (Rowley) | C75: Hunt Family Fund Handicap | D75: Class 2 | E75: 7 | F75: Good To Firm | G75: 12 | H75: Aqpan (IRE) | I75: Dawson, R | J75: Varian, Roger | K75: 3 | L75: 94 | M75: 3 | N75: 35 | O75: 6 | P75: 16.620758 | Q75: 0.060165727 | R75: 29 | S75: =IF(AND(ISNUMBER(R75),R75>1,P75>0),R75/P75-1,"") -> 0.74480608 | T75: =IF(AND(ISNUMBER(P75),P75>0),P75*EXP('Read me'!$B$22),"") -> 20.30064
A76: 4:50 | B76: Newmarket (Rowley) | C76: Hunt Family Fund Handicap | D76: Class 2 | E76: 7 | F76: Good To Firm | G76: 12 | H76: Sword | I76: Haines, Olivia | J76: Williams, S C | K76: 2 | L76: 86 | M76: 5 | N76: 21 | O76: 7 | P76: 17.254866 | Q76: 0.057954667 | R76: 17 | S76: =IF(AND(ISNUMBER(R76),R76>1,P76>0),R76/P76-1,"") -> -0.014770655 | T76: =IF(AND(ISNUMBER(P76),P76>0),P76*EXP('Read me'!$B$22),"") -> 21.075141
A77: 4:50 | B77: Newmarket (Rowley) | C77: Hunt Family Fund Handicap | D77: Class 2 | E77: 7 | F77: Good To Firm | G77: 12 | H77: Five Ways | I77: Watson, Jason | J77: Balding, A M | K77: 11 | L77: 104 | M77: 3 | N77: 35 | O77: 8 | P77: 18.136589 | Q77: 0.05513716 | R77: 11 | S77: =IF(AND(ISNUMBER(R77),R77>1,P77>0),R77/P77-1,"") -> -0.39349124 | T77: =IF(AND(ISNUMBER(P77),P77>0),P77*EXP('Read me'!$B$22),"") -> 22.15208
A78: 4:50 | B78: Newmarket (Rowley) | C78: Hunt Family Fund Handicap | D78: Class 2 | E78: 7 | F78: Good To Firm | G78: 12 | H78: Native American (IRE) | I78: Mitchell, Jack | J78: Jehani, H Al | K78: 9 | L78: 99 | M78: 5 | N78: 349 | O78: 9 | P78: 21.66933 | Q78: 0.046148173 | R78: 13 | S78: =IF(AND(ISNUMBER(R78),R78>1,P78>0),R78/P78-1,"") -> -0.40007375 | T78: =IF(AND(ISNUMBER(P78),P78>0),P78*EXP('Read me'!$B$22),"") -> 26.466979
A79: 4:50 | B79: Newmarket (Rowley) | C79: Hunt Family Fund Handicap | D79: Class 2 | E79: 7 | F79: Good To Firm | G79: 12 | H79: Dapper Guest (IRE) | I79: Nicholls, Jack | J79: Margarson, G G | K79: 6 | L79: 86 | M79: 4 | N79: 16 | O79: 10 | P79: 24.03822 | Q79: 0.041600418 | R79: 17 | S79: =IF(AND(ISNUMBER(R79),R79>1,P79>0),R79/P79-1,"") -> -0.29279289 | T79: =IF(AND(ISNUMBER(P79),P79>0),P79*EXP('Read me'!$B$22),"") -> 29.360348
A80: 4:50 | B80: Newmarket (Rowley) | C80: Hunt Family Fund Handicap | D80: Class 2 | E80: 7 | F80: Good To Firm | G80: 12 | H80: Rocking Ends | I80: Egan, David | J80: Clover, Tom | K80: 12 | L80: 86 | M80: 6 | N80: 7 | O80: 11 | P80: 29.993479 | Q80: 0.03334058 | R80: 17 | S80: =IF(AND(ISNUMBER(R80),R80>1,P80>0),R80/P80-1,"") -> -0.43321014 | T80: =IF(AND(ISNUMBER(P80),P80>0),P80*EXP('Read me'!$B$22),"") -> 36.634119
A81: 4:50 | B81: Newmarket (Rowley) | C81: Hunt Family Fund Handicap | D81: Class 2 | E81: 7 | F81: Good To Firm | G81: 12 | H81: Utmost Good Faith | I81: Doughty, Jack | J81: Williams, S C | K81: 1 | L81: 90 | M81: 3 | N81: 20 | O81: 12 | P81: 134.13583 | Q81: 0.0074551297 | R81: 67 | S81: =IF(AND(ISNUMBER(R81),R81>1,P81>0),R81/P81-1,"") -> -0.50050631 | T81: =IF(AND(ISNUMBER(P81),P81>0),P81*EXP('Read me'!$B$22),"") -> 163.83387

Sheet Curragh
A1: Time | B1: Course | C1: Race | D1: Class | E1: Furlongs | F1: Going | G1: Runners | H1: Horse | I1: Jockey | J1: Trainer | K1: Draw | L1: OR | M1: Age | N1: Days since run | O1: Model rank | P1: Predicted BSP | Q1: Win probability | R1: Card odds (HRB) | S1: Card odds vs model | T1: Rule: back at Betfair ≥
A2: 1:30 | B2: Curragh | C2: Market Square Monasterevin Irish European Breeders Fund Maiden | E2: 6 | F2: Good | G2: 13 | H2: Benown (IRE) | I2: Sheridan, J M | J2: OBrien, Joseph Patrick | K2: 14 | L2: 0 | M2: 2 | N2: 48 | O2: 1 | P2: 1.9022607 | Q2: 0.52569029 | R2: 1.7272727 | S2: =IF(AND(ISNUMBER(R2),R2>1,P2>0),R2/P2-1,"") -> -0.091989498 | T2: =IF(AND(ISNUMBER(P2),P2>0),P2*EXP('Read me'!$B$22),"") -> 2.3234265
A3: 1:30 | B3: Curragh | C3: Market Square Monasterevin Irish European Breeders Fund Maiden | E3: 6 | F3: Good | G3: 13 | H3: Heralds March (IRE) | I3: Keane, C T | J3: Lyons, G M | K3: 12 | L3: 0 | M3: 2 | N3: 35 | O3: 2 | P3: 5.3234689 | Q3: 0.18784744 | R3: 5.5 | S3: =IF(AND(ISNUMBER(R3),R3>1,P3>0),R3/P3-1,"") -> 0.033160919 | T3: =IF(AND(ISNUMBER(P3),P3>0),P3*EXP('Read me'!$B$22),"") -> 6.5020996
A4: 1:30 | B4: Curragh | C4: Market Square Monasterevin Irish European Breeders Fund Maiden | E4: 6 | F4: Good | G4: 13 | H4: Controlla (IRE) | I4: OConnor, Donagh | J4: Aguiar, Robson | K4: 11 | L4: 96 | M4: 2 | N4: 13 | O4: 3 | P4: 8.4672894 | Q4: 0.11810155 | R4: 3.25 | S4: =IF(AND(ISNUMBER(R4),R4>1,P4>0),R4/P4-1,"") -> -0.61616996 | T4: =IF(AND(ISNUMBER(P4),P4>0),P4*EXP('Read me'!$B$22),"") -> 10.341971
A5: 1:30 | B5: Curragh | C5: Market Square Monasterevin Irish European Breeders Fund Maiden | E5: 6 | F5: Good | G5: 13 | H5: Jungle Wise (IRE) | I5: Coen, Ben M | J5: Murphy, Daniel | K5: 8 | L5: 0 | M5: 2 | N5: 17 | O5: 4 | P5: 11.692526 | Q5: 0.085524719 | R5: 11 | S5: =IF(AND(ISNUMBER(R5),R5>1,P5>0),R5/P5-1,"") -> -0.059228091 | T5: =IF(AND(ISNUMBER(P5),P5>0),P5*EXP('Read me'!$B$22),"") -> 14.281283
A6: 1:30 | B6: Curragh | C6: Market Square Monasterevin Irish European Breeders Fund Maiden | E6: 6 | F6: Good | G6: 13 | H6: Shake It Out | I6: Whelan, R P | J6: Cotter, Kieran P | K6: 10 | L6: 0 | M6: 2 | O6: 5 | P6: 53.338562 | Q6: 0.018748162 | R6: 51 | S6: =IF(AND(ISNUMBER(R6),R6>1,P6>0),R6/P6-1,"") -> -0.043843731 | T6: =IF(AND(ISNUMBER(P6),P6>0),P6*EXP('Read me'!$B$22),"") -> 65.147866
A7: 1:30 | B7: Curragh | C7: Market Square Monasterevin Irish European Breeders Fund Maiden | E7: 6 | F7: Good | G7: 13 | H7: Moon Gypsy (IRE) | I7: Mulligan, R M | J7: Burns, J G | K7: 9 | L7: 0 | M7: 2 | O7: 6 | P7: 59.575275 | Q7: 0.016785487 | R7: 201 | S7: =IF(AND(ISNUMBER(R7),R7>1,P7>0),R7/P7-1,"") -> 2.3738829 | T7: =IF(AND(ISNUMBER(P7),P7>0),P7*EXP('Read me'!$B$22),"") -> 72.765406
A8: 1:30 | B8: Curragh | C8: Market Square Monasterevin Irish European Breeders Fund Maiden | E8: 6 | F8: Good | G8: 13 | H8: Katty (IRE) | I8: Heffernan, J A | J8: Sexton, Adrian | K8: 5 | L8: 0 | M8: 2 | N8: 37 | O8: 7 | P8: 62.059397 | Q8: 0.016113595 | R8: 29 | S8: =IF(AND(ISNUMBER(R8),R8>1,P8>0),R8/P8-1,"") -> -0.53270574 | T8: =IF(AND(ISNUMBER(P8),P8>0),P8*EXP('Read me'!$B$22),"") -> 75.799519
A9: 1:30 | B9: Curragh | C9: Market Square Monasterevin Irish European Breeders Fund Maiden | E9: 6 | F9: Good | G9: 13 | H9: Royal Sovereign (IRE) | I9: Joyce, Wesley | J9: Mulvany, Michael | K9: 3 | L9: 0 | M9: 2 | O9: 8 | P9: 91.538823 | Q9: 0.010924327 | R9: 51 | S9: =IF(AND(ISNUMBER(R9),R9>1,P9>0),R9/P9-1,"") -> -0.44285935 | T9: =IF(AND(ISNUMBER(P9),P9>0),P9*EXP('Read me'!$B$22),"") -> 111.80577
A10: 1:30 | B10: Curragh | C10: Market Square Monasterevin Irish European Breeders Fund Maiden | E10: 6 | F10: Good | G10: 13 | H10: Starlit (IRE) | I10: Kennedy, K G | J10: Harrington, Mrs John | K10: 7 | L10: 0 | M10: 2 | N10: 42 | O10: 9 | P10: 105.08303 | Q10: 0.0095162848 | R10: 26 | S10: =IF(AND(ISNUMBER(R10),R10>1,P10>0),R10/P10-1,"") -> -0.75257659 | T10: =IF(AND(ISNUMBER(P10),P10>0),P10*EXP('Read me'!$B$22),"") -> 128.3487
A11: 1:30 | B11: Curragh | C11: Market Square Monasterevin Irish European Breeders Fund Maiden | E11: 6 | F11: Good | G11: 13 | H11: Champion Basma (IRE) | I11: Hayes, C D | J11: ONeill, E J | K11: 2 | L11: 0 | M11: 2 | N11: 9 | O11: 10 | P11: 213.77245 | Q11: 0.0046778712 | R11: 67 | S11: =IF(AND(ISNUMBER(R11),R11>1,P11>0),R11/P11-1,"") -> -0.68658263 | T11: =IF(AND(ISNUMBER(P11),P11>0),P11*EXP('Read me'!$B$22),"") -> 261.10226
A12: 1:30 | B12: Curragh | C12: Market Square Monasterevin Irish European Breeders Fund Maiden | E12: 6 | F12: Good | G12: 13 | H12: Fen Phasee (IRE) | I12: Cleary, R P | J12: Davis, Sean | K12: 4 | L12: 0 | M12: 2 | O12: 11 | P12: 393.51875 | Q12: 0.002541175 | R12: 126 | S12: =IF(AND(ISNUMBER(R12),R12>1,P12>0),R12/P12-1,"") -> -0.67981195 | T12: =IF(AND(ISNUMBER(P12),P12>0),P12*EXP('Read me'!$B$22),"") -> 480.64489
A13: 1:30 | B13: Curragh | C13: Market Square Monasterevin Irish European Breeders Fund Maiden | E13: 6 | F13: Good | G13: 13 | H13: Ar Son Na Cuise (IRE) | I13: McDonogh, D P | J13: OBrien, Joseph Patrick | K13: 13 | L13: 0 | M13: 2 | N13: 17 | O13: 12 | P13: 402.27202 | Q13: 0.0024858801 | R13: 101 | S13: =IF(AND(ISNUMBER(R13),R13>1,P13>0),R13/P13-1,"") -> -0.74892611 | T13: =IF(AND(ISNUMBER(P13),P13>0),P13*EXP('Read me'!$B$22),"") -> 491.33615
A14: 1:30 | B14: Curragh | C14: Market Square Monasterevin Irish European Breeders Fund Maiden | E14: 6 | F14: Good | G14: 13 | H14: Brageiro (IRE) | I14: McAteer, L T | J14: OSullivan, Ross | K14: 1 | L14: 0 | M14: 2 | N14: 9 | O14: 13 | P14: 958.57182 | Q14: 0.0010432186 | R14: 201 | S14: =IF(AND(ISNUMBER(R14),R14>1,P14>0),R14/P14-1,"") -> -0.79031305 | T14: =IF(AND(ISNUMBER(P14),P14>0),P14*EXP('Read me'!$B$22),"") -> 1170.8023
A15: 2:00 | B15: Curragh | C15: Kwiff More Bang For Your Bet Rated Race | E15: 7 | F15: Good | G15: 9 | H15: Oro Blanco (IRE) | I15: Kennedy, K G | J15: Harrington, Mrs John | K15: 7 | L15: 84 | M15: 3 | N15: 14 | O15: 1 | P15: 4.4337459 | Q15: 0.22554292 | R15: 3.75 | S15: =IF(AND(ISNUMBER(R15),R15>1,P15>0),R15/P15-1,"") -> -0.15421405 | T15: =IF(AND(ISNUMBER(P15),P15>0),P15*EXP('Read me'!$B$22),"") -> 5.4153895
A16: 2:00 | B16: Curragh | C16: Kwiff More Bang For Your Bet Rated Race | E16: 7 | F16: Good | G16: 9 | H16: Killashee Warrior | I16: Hayes, C D | J16: Harty, Edward and Patrick | K16: 8 | L16: 91 | M16: 3 | N16: 14 | O16: 2 | P16: 5.0561504 | Q16: 0.19777893 | R16: 6 | S16: =IF(AND(ISNUMBER(R16),R16>1,P16>0),R16/P16-1,"") -> 0.18667357 | T16: =IF(AND(ISNUMBER(P16),P16>0),P16*EXP('Read me'!$B$22),"") -> 6.175596
A17: 2:00 | B17: Curragh | C17: Kwiff More Bang For Your Bet Rated Race | E17: 7 | F17: Good | G17: 9 | H17: Lewis Carroll (IRE) | I17: Lordan, W M | J17: OBrien, A P | K17: 3 | L17: 87 | M17: 3 | N17: 182 | O17: 3 | P17: 5.8560056 | Q17: 0.17076486 | R17: 5.5 | S17: =IF(AND(ISNUMBER(R17),R17>1,P17>0),R17/P17-1,"") -> -0.060793244 | T17: =IF(AND(ISNUMBER(P17),P17>0),P17*EXP('Read me'!$B$22),"") -> 7.1525414
A18: 2:00 | B18: Curragh | C18: Kwiff More Bang For Your Bet Rated Race | E18: 7 | F18: Good | G18: 9 | H18: Invincible Will (IRE) | I18: Carroll, G F | J18: Cromwell, Gavin Patrick | K18: 5 | L18: 87 | M18: 3 | N18: 13 | O18: 4 | P18: 6.6813851 | Q18: 0.14966956 | R18: 4.3333333 | S18: =IF(AND(ISNUMBER(R18),R18>1,P18>0),R18/P18-1,"") -> -0.35143189 | T18: =IF(AND(ISNUMBER(P18),P18>0),P18*EXP('Read me'!$B$22),"") -> 8.1606622
A19: 2:00 | B19: Curragh | C19: Kwiff More Bang For Your Bet Rated Race | E19: 7 | F19: Good | G19: 9 | H19: Chapel Lane (IRE) | I19: Lee, W J | J19: McCreery, W | K19: 6 | L19: 81 | M19: 3 | N19: 24 | O19: 5 | P19: 8.5280476 | Q19: 0.11726013 | R19: 8 | S19: =IF(AND(ISNUMBER(R19),R19>1,P19>0),R19/P19-1,"") -> -0.061918928 | T19: =IF(AND(ISNUMBER(P19),P19>0),P19*EXP('Read me'!$B$22),"") -> 10.416181
A20: 2:00 | B20: Curragh | C20: Kwiff More Bang For Your Bet Rated Race | E20: 7 | F20: Good | G20: 9 | H20: Mumhan (IRE) | I20: McDonogh, D P | J20: Bolger, J S | K20: 4 | L20: 86 | M20: 3 | N20: 7 | O20: 6 | P20: 22.209543 | Q20: 0.04502569 | R20: 11 | S20: =IF(AND(ISNUMBER(R20),R20>1,P20>0),R20/P20-1,"") -> -0.5047174 | T20: =IF(AND(ISNUMBER(P20),P20>0),P20*EXP('Read me'!$B$22),"") -> 27.126797
A21: 2:00 | B21: Curragh | C21: Kwiff More Bang For Your Bet Rated Race | E21: 7 | F21: Good | G21: 9 | H21: Unauthorized (IRE) | I21: Holohan, Reese | J21: Melia, Aidan | K21: 1 | L21: 83 | M21: 3 | N21: 91 | O21: 7 | P21: 26.177001 | Q21: 0.038201474 | R21: 21 | S21: =IF(AND(ISNUMBER(R21),R21>1,P21>0),R21/P21-1,"") -> -0.19776905 | T21: =IF(AND(ISNUMBER(P21),P21>0),P21*EXP('Read me'!$B$22),"") -> 31.972661
A22: 2:00 | B22: Curragh | C22: Kwiff More Bang For Your Bet Rated Race | E22: 7 | F22: Good | G22: 9 | H22: Kindergarten (IRE) | I22: McCullagh, Scott | J22: Harrington, Mrs John | K22: 2 | L22: 87 | M22: 3 | N22: 113 | O22: 8 | P22: 31.761112 | Q22: 0.031485044 | R22: 26 | S22: =IF(AND(ISNUMBER(R22),R22>1,P22>0),R22/P22-1,"") -> -0.18138885 | T22: =IF(AND(ISNUMBER(P22),P22>0),P22*EXP('Read me'!$B$22),"") -> 38.793109
A23: 2:00 | B23: Curragh | C23: Kwiff More Bang For Your Bet Rated Race | E23: 7 | F23: Good | G23: 9 | H23: Lohoobb | I23: McCullagh, N G | J23: Grassick, M C | K23: 9 | L23: 78 | M23: 3 | N23: 13 | O23: 9 | P23: 41.200788 | Q23: 0.024271381 | R23: 29 | S23: =IF(AND(ISNUMBER(R23),R23>1,P23>0),R23/P23-1,"") -> -0.29612996 | T23: =IF(AND(ISNUMBER(P23),P23>0),P23*EXP('Read me'!$B$22),"") -> 50.322756
A24: 2:35 | B24: Curragh | C24: Kwiff Supercharged Joe McGrath Handicap (Premier Handicap) | E24: 5 | F24: Good | G24: 20 | H24: Red Evolution (IRE) | I24: Holohan, Reese | J24: OCallaghan, M D | K24: 20 | L24: 85 | M24: 4 | N24: 13 | O24: 1 | P24: 6.6003902 | Q24: 0.15150619 | R24: 5.5 | S24: =IF(AND(ISNUMBER(R24),R24>1,P24>0),R24/P24-1,"") -> -0.16671593 | T24: =IF(AND(ISNUMBER(P24),P24>0),P24*EXP('Read me'!$B$22),"") -> 8.0617348
... A63: 4:20 | B63: Curragh | C63: Goffs Million | E63: 7 | F63: Good | G63: 19 | H63: Dorigo (IRE) | I63: Stott, Kevin | J63: Ryan, K A | K63: 9 | L63: 95 | M63: 2 | N63: 16 | O63: 3 | P63: 9.9999383 | Q63: 0.10000062 | R63: 12 | S63: =IF(AND(ISNUMBER(R63),R63>1,P63>0),R63/P63-1,"") -> 0.2000074 | T63: =IF(AND(ISNUMBER(P63),P63>0),P63*EXP('Read me'!$B$22),"") -> 12.213952
A64: 4:20 | B64: Curragh | C64: Goffs Million | E64: 7 | F64: Good | G64: 19 | H64: Critical Reason (IRE) | I64: Keane, C T | J64: Lyons, G M | K64: 3 | L64: 0 | M64: 2 | O64: 4 | P64: 11.980279 | Q64: 0.083470508 | R64: 19 | S64: =IF(AND(ISNUMBER(R64),R64>1,P64>0),R64/P64-1,"") -> 0.58593964 | T64: =IF(AND(ISNUMBER(P64),P64>0),P64*EXP('Read me'!$B$22),"") -> 14.632746
A65: 4:20 | B65: Curragh | C65: Goffs Million | E65: 7 | F65: Good | G65: 19 | H65: Bayside View (IRE) | I65: Coen, Ben M | J65: Bell, M L W | K65: 13 | L65: 93 | M65: 2 | N65: 27 | O65: 5 | P65: 12.461388 | Q65: 0.080247884 | R65: 9 | S65: =IF(AND(ISNUMBER(R65),R65>1,P65>0),R65/P65-1,"") -> -0.27776904 | T65: =IF(AND(ISNUMBER(P65),P65>0),P65*EXP('Read me'!$B$22),"") -> 15.220373
A66: 4:20 | B66: Curragh | C66: Goffs Million | E66: 7 | F66: Good | G66: 19 | H66: King Of Cloughan (IRE) | I66: Sheridan, J M | J66: OBrien, Joseph Patrick | K66: 20 | L66: 102 | M66: 2 | N66: 48 | O66: 6 | P66: 14.633931 | Q66: 0.06833434 | R66: 9.5 | S66: =IF(AND(ISNUMBER(R66),R66>1,P66>0),R66/P66-1,"") -> -0.35082377 | T66: =IF(AND(ISNUMBER(P66),P66>0),P66*EXP('Read me'!$B$22),"") -> 17.873924
A67: 4:20 | B67: Curragh | C67: Goffs Million | E67: 7 | F67: Good | G67: 19 | H67: Carry The Flag (IRE) | I67: Lordan, W M | J67: OBrien, A P | K67: 10 | L67: 110 | M67: 2 | N67: 15 | O67: 7 | P67: 20.671917 | Q67: 0.048374808 | R67: 8.5 | S67: =IF(AND(ISNUMBER(R67),R67>1,P67>0),R67/P67-1,"") -> -0.58881413 | T67: =IF(AND(ISNUMBER(P67),P67>0),P67*EXP('Read me'!$B$22),"") -> 25.248736
A68: 4:20 | B68: Curragh | C68: Goffs Million | E68: 7 | F68: Good | G68: 19 | H68: Ballinea Star (IRE) | I68: OConnor, Donagh | J68: Aguiar, Robson | K68: 12 | L68: 100 | M68: 2 | N68: 13 | O68: 8 | P68: 26.341548 | Q68: 0.037962842 | R68: 12 | S68: =IF(AND(ISNUMBER(R68),R68>1,P68>0),R68/P68-1,"") -> -0.5444459 | T68: =IF(AND(ISNUMBER(P68),P68>0),P68*EXP('Read me'!$B$22),"") -> 32.173639
A69: 4:20 | B69: Curragh | C69: Goffs Million | E69: 7 | F69: Good | G69: 19 | H69: Thomas Chippendale (IRE) | I69: Cleary, Jack | J69: OBrien, A P | K69: 17 | L69: 0 | M69: 2 | N69: 41 | O69: 9 | P69: 27.498525 | Q69: 0.036365587 | R69: 26 | S69: =IF(AND(ISNUMBER(R69),R69>1,P69>0),R69/P69-1,"") -> -0.054494725 | T69: =IF(AND(ISNUMBER(P69),P69>0),P69*EXP('Read me'!$B$22),"") -> 33.586774
A70: 4:20 | B70: Curragh | C70: Goffs Million | E70: 7 | F70: Good | G70: 19 | H70: Love Is (IRE) | I70: Marsh, Finley | J70: Hughes, Richard | K70: 5 | L70: 89 | M70: 2 | N70: 23 | O70: 10 | P70: 29.067045 | Q70: 0.034403222 | R70: 34 | S70: =IF(AND(ISNUMBER(R70),R70>1,P70>0),R70/P70-1,"") -> 0.16970954 | T70: =IF(AND(ISNUMBER(P70),P70>0),P70*EXP('Read me'!$B$22),"") -> 35.502569
A71: 4:20 | B71: Curragh | C71: Goffs Million | E71: 7 | F71: Good | G71: 19 | H71: Hi Corbett Court (IRE) | I71: Rutledge, Siobhan | J71: Twomey, P | K71: 19 | L71: 86 | M71: 2 | N71: 52 | O71: 11 | P71: 32.523332 | Q71: 0.030747157 | R71: 29 | S71: =IF(AND(ISNUMBER(R71),R71>1,P71>0),R71/P71-1,"") -> -0.10833244 | T71: =IF(AND(ISNUMBER(P71),P71>0),P71*EXP('Read me'!$B$22),"") -> 39.724087
A72: 4:20 | B72: Curragh | C72: Goffs Million | E72: 7 | F72: Good | G72: 19 | H72: My Lucky Journey (IRE) | I72: Heffernan, J A | J72: Stack, J A | K72: 15 | L72: 0 | M72: 2 | N72: 48 | O72: 12 | P72: 35.693464 | Q72: 0.028016334 | R72: 29 | S72: =IF(AND(ISNUMBER(R72),R72>1,P72>0),R72/P72-1,"") -> -0.18752632 | T72: =IF(AND(ISNUMBER(P72),P72>0),P72*EXP('Read me'!$B$22),"") -> 43.596096
A73: 4:20 | B73: Curragh | C73: Goffs Million | E73: 7 | F73: Good | G73: 19 | H73: Blessed Voyager (IRE) | I73: Carroll, G F | J73: Beckett, R M | K73: 8 | L73: 88 | M73: 2 | N73: 46 | O73: 13 | P73: 40.124489 | Q73: 0.024922436 | R73: 29 | S73: =IF(AND(ISNUMBER(R73),R73>1,P73>0),R73/P73-1,"") -> -0.27724937 | T73: =IF(AND(ISNUMBER(P73),P73>0),P73*EXP('Read me'!$B$22),"") -> 49.008162
A74: 4:20 | B74: Curragh | C74: Goffs Million | E74: 7 | F74: Good | G74: 19 | H74: Nobelos (IRE) | I74: Hornby, Rob | J74: Hills, Charles | K74: 11 | L74: 81 | M74: 2 | N74: 22 | O74: 14 | P74: 42.573975 | Q74: 0.023488528 | R74: 23 | S74: =IF(AND(ISNUMBER(R74),R74>1,P74>0),R74/P74-1,"") -> -0.45976386 | T74: =IF(AND(ISNUMBER(P74),P74>0),P74*EXP('Read me'!$B$22),"") -> 51.999971
A75: 4:20 | B75: Curragh | C75: Goffs Million | E75: 7 | F75: Good | G75: 19 | H75: Roeillaun (IRE) | I75: Caffrey, Adam | J75: Meade, Noel | K75: 1 | L75: 84 | M75: 2 | N75: 21 | O75: 15 | P75: 45.184382 | Q75: 0.022131541 | R75: 34 | S75: =IF(AND(ISNUMBER(R75),R75>1,P75>0),R75/P75-1,"") -> -0.24752761 | T75: =IF(AND(ISNUMBER(P75),P75>0),P75*EXP('Read me'!$B$22),"") -> 55.188329
A76: 4:20 | B76: Curragh | C76: Goffs Million | E76: 7 | F76: Good | G76: 19 | H76: Nation Blaze (IRE) | I76: Slattery, A J | J76: Slattery, Andrew | K76: 7 | L76: 0 | M76: 2 | N76: 17 | O76: 16 | P76: 71.642684 | Q76: 0.013958159 | R76: 81 | S76: =IF(AND(ISNUMBER(R76),R76>1,P76>0),R76/P76-1,"") -> 0.1306109 | T76: =IF(AND(ISNUMBER(P76),P76>0),P76*EXP('Read me'!$B$22),"") -> 87.504572
... A83: 4:55 | B83: Curragh | C83: Gra Chocolates Maiden | E83: 10 | F83: Good | G83: 18 | H83: Lets Smash It (IRE) | I83: OConnor, Donagh | J83: Aguiar, Robson | K83: 6 | L83: 80 | M83: 3 | N83: 24 | O83: 4 | P83: 8.8641712 | Q83: 0.11281371 | R83: 9 | S83: =IF(AND(ISNUMBER(R83),R83>1,P83>0),R83/P83-1,"") -> 0.015323349 | T83: =IF(AND(ISNUMBER(P83),P83>0),P83*EXP('Read me'!$B$22),"") -> 10.826723
A84: 4:55 | B84: Curragh | C84: Gra Chocolates Maiden | E84: 10 | F84: Good | G84: 18 | H84: Come What May (IRE) | I84: Lordan, W M | J84: OBrien, A P | K84: 13 | L84: 0 | M84: 3 | O84: 5 | P84: 13.365101 | Q84: 0.074821732 | R84: 6 | S84: =IF(AND(ISNUMBER(R84),R84>1,P84>0),R84/P84-1,"") -> -0.55106961 | T84: =IF(AND(ISNUMBER(P84),P84>0),P84*EXP('Read me'!$B$22),"") -> 16.324171
A85: 4:55 | B85: Curragh | C85: Gra Chocolates Maiden | E85: 10 | F85: Good | G85: 18 | H85: Copper Dog (IRE) | I85: Coen, Ben M | J85: Murtagh, J P | K85: 2 | L85: 0 | M85: 3 | O85: 6 | P85: 20.37974 | Q85: 0.049068339 | R85: 15 | S85: =IF(AND(ISNUMBER(R85),R85>1,P85>0),R85/P85-1,"") -> -0.26397491 | T85: =IF(AND(ISNUMBER(P85),P85>0),P85*EXP('Read me'!$B$22),"") -> 24.891871
A86: 4:55 | B86: Curragh | C86: Gra Chocolates Maiden | E86: 10 | F86: Good | G86: 18 | H86: Vico Road (IRE) | I86: Carroll, G F | J86: Murphy, John Joseph | K86: 10 | L86: 0 | M86: 3 | N86: 11 | O86: 7 | P86: 23.353912 | Q86: 0.042819378 | R86: 26 | S86: =IF(AND(ISNUMBER(R86),R86>1,P86>0),R86/P86-1,"") -> 0.11330383 | T86: =IF(AND(ISNUMBER(P86),P86>0),P86*EXP('Read me'!$B$22),"") -> 28.524533
A87: 4:55 | B87: Curragh | C87: Gra Chocolates Maiden | E87: 10 | F87: Good | G87: 18 | H87: Royal Ballet Blue (IRE) | I87: Pietropaolo, J | J87: Foley, Jack | K87: 11 | L87: 0 | M87: 3 | N87: 35 | O87: 8 | P87: 29.274794 | Q87: 0.034159079 | R87: 21 | S87: =IF(AND(ISNUMBER(R87),R87>1,P87>0),R87/P87-1,"") -> -0.28265934 | T87: =IF(AND(ISNUMBER(P87),P87>0),P87*EXP('Read me'!$B$22),"") -> 35.756314
A88: 4:55 | B88: Curragh | C88: Gra Chocolates Maiden | E88: 10 | F88: Good | G88: 18 | H88: Leopold The First (IRE) | I88: Colgan, R C | J88: Lee, Andrew | K88: 15 | L88: 87 | M88: 4 | N88: 63 | O88: 9 | P88: 31.928982 | Q88: 0.031319508 | R88: 11 | S88: =IF(AND(ISNUMBER(R88),R88>1,P88>0),R88/P88-1,"") -> -0.65548541 | T88: =IF(AND(ISNUMBER(P88),P88>0),P88*EXP('Read me'!$B$22),"") -> 38.998146
A89: 4:55 | B89: Curragh | C89: Gra Chocolates Maiden | E89: 10 | F89: Good | G89: 18 | H89: Big Jake (IRE) | I89: Keane, C T | J89: Oliver, Andrew | K89: 3 | L89: 0 | M89: 4 | N89: 17 | O89: 10 | P89: 35.955931 | Q89: 0.027811823 | R89: 13 | S89: =IF(AND(ISNUMBER(R89),R89>1,P89>0),R89/P89-1,"") -> -0.6384463 | T89: =IF(AND(ISNUMBER(P89),P89>0),P89*EXP('Read me'!$B$22),"") -> 43.916673
A90: 4:55 | B90: Curragh | C90: Gra Chocolates Maiden | E90: 10 | F90: Good | G90: 18 | H90: Positive Thinking (IRE) | I90: Heffernan, J A | J90: Lupini, Miss Natalia | K90: 1 | L90: 0 | M90: 3 | O90: 11 | P90: 46.624115 | Q90: 0.021448128 | R90: 13 | S90: =IF(AND(ISNUMBER(R90),R90>1,P90>0),R90/P90-1,"") -> -0.72117433 | T90: =IF(AND(ISNUMBER(P90),P90>0),P90*EXP('Read me'!$B$22),"") -> 56.946823
A91: 4:55 | B91: Curragh | C91: Gra Chocolates Maiden | E91: 10 | F91: Good | G91: 18 | H91: Conrad (IRE) | I91: McAteer, L T | J91: Feane, John James | K91: 14 | L91: 0 | M91: 3 | O91: 12 | P91: 91.235741 | Q91: 0.010960617 | R91: 34 | S91: =IF(AND(ISNUMBER(R91),R91>1,P91>0),R91/P91-1,"") -> -0.62733903 | T91: =IF(AND(ISNUMBER(P91),P91>0),P91*EXP('Read me'!$B$22),"") -> 111.43559
A92: 4:55 | B92: Curragh | C92: Gra Chocolates Maiden | E92: 10 | F92: Good | G92: 18 | H92: Plug In Hybrid (IRE) | I92: Caffrey, Adam | J92: Meade, Noel | K92: 9 | L92: 0 | M92: 3 | N92: 26 | O92: 13 | P92: 119.09527 | Q92: 0.0083966389 | R92: 23 | S92: =IF(AND(ISNUMBER(R92),R92>1,P92>0),R92/P92-1,"") -> -0.80687731 | T92: =IF(AND(ISNUMBER(P92),P92>0),P92*EXP('Read me'!$B$22),"") -> 145.46329
A93: 4:55 | B93: Curragh | C93: Gra Chocolates Maiden | E93: 10 | F93: Good | G93: 18 | H93: Toristar (IRE) | I93: Whelan, R P | J93: Timmons, C D | K93: 4 | L93: 0 | M93: 3 | O93: 14 | P93: 253.48449 | Q93: 0.0039450146 | R93: 51 | S93: =IF(AND(ISNUMBER(R93),R93>1,P93>0),R93/P93-1,"") -> -0.79880426 | T93: =IF(AND(ISNUMBER(P93),P93>0),P93*EXP('Read me'!$B$22),"") -> 309.60665
A94: 4:55 | B94: Curragh | C94: Gra Chocolates Maiden | E94: 10 | F94: Good | G94: 18 | H94: Desert Swing (IRE) | I94: Holohan, Reese | J94: Kinirons, A | K94: 5 | L94: 0 | M94: 4 | N94: 10 | O94: 15 | P94: 378.73481 | Q94: 0.0026403699 | R94: 101 | S94: =IF(AND(ISNUMBER(R94),R94>1,P94>0),R94/P94-1,"") -> -0.73332264 | T94: =IF(AND(ISNUMBER(P94),P94>0),P94*EXP('Read me'!$B$22),"") -> 462.58774
A95: 4:55 | B95: Curragh | C95: Gra Chocolates Maiden | E95: 10 | F95: Good | G95: 18 | H95: What Do You Say (IRE) | I95: Ryan, J J G | J95: Oliver, Andrew | K95: 12 | L95: 0 | M95: 3 | N95: 24 | O95: 16 | P95: 458.02192 | Q95: 0.0021833016 | R95: 101 | S95: =IF(AND(ISNUMBER(R95),R95>1,P95>0),R95/P95-1,"") -> -0.77948654 | T95: =IF(AND(ISNUMBER(P95),P95>0),P95*EXP('Read me'!$B$22),"") -> 559.42924
A96: 4:55 | B96: Curragh | C96: Gra Chocolates Maiden | E96: 10 | F96: Good | G96: 18 | H96: Griselinia (IRE) | I96: Cleary, R P | J96: Coleman, Kevin | K96: 7 | L96: 0 | M96: 3 | N96: 10 | O96: 17 | P96: 937.57572 | Q96: 0.0010665805 | R96: 201 | S96: =IF(AND(ISNUMBER(R96),R96>1,P96>0),R96/P96-1,"") -> -0.78561731 | T96: =IF(AND(ISNUMBER(P96),P96>0),P96*EXP('Read me'!$B$22),"") -> 1145.1576
A97: 4:55 | B97: Curragh | C97: Gra Chocolates Maiden | E97: 10 | F97: Good | G97: 18 | H97: Silverhillsox (IRE) | I97: Cleary, Jack | J97: Egan, Kieran P | K97: 17 | L97: 0 | M97: 5 | N97: 117 | O97: 18 | P97: 1026.5066 | Q97: 0.00097417784 | R97: 201 | S97: =IF(AND(ISNUMBER(R97),R97>1,P97>0),R97/P97-1,"") -> -0.80419025 | T97: =IF(AND(ISNUMBER(P97),P97>0),P97*EXP('Read me'!$B$22),"") -> 1253.778
A98: 5:25 | B98: Curragh | C98: Equiwinner Patches Fillies Maiden | E98: 9 | F98: Good | G98: 17 | H98: Sunatia (FR) | I98: Hayes, C D | J98: Weld, D K | K98: 6 | L98: 77 | M98: 3 | N98: 24 | O98: 1 | P98: 5.504738 | Q98: 0.18166169 | R98: 6.5 | S98: =IF(AND(ISNUMBER(R98),R98>1,P98>0),R98/P98-1,"") -> 0.18080097 | T98: =IF(AND(ISNUMBER(P98),P98>0),P98*EXP('Read me'!$B$22),"") -> 6.7235022
A99: 5:25 | B99: Curragh | C99: Equiwinner Patches Fillies Maiden | E99: 9 | F99: Good | G99: 17 | H99: Together Now (USA) | I99: Whelan, R P | J99: OBrien, A P | K99: 19 | L99: 0 | M99: 3 | N99: 357 | O99: 2 | P99: 5.9207082 | Q99: 0.16889871 | R99: 3.25 | S99: =IF(AND(ISNUMBER(R99),R99>1,P99>0),R99/P99-1,"") -> -0.45107918 | T99: =IF(AND(ISNUMBER(P99),P99>0),P99*EXP('Read me'!$B$22),"") -> 7.2315693
A100: 5:25 | B100: Curragh | C100: Equiwinner Patches Fillies Maiden | E100: 9 | F100: Good | G100: 17 | H100: Sangreal (IRE) | I100: Sheridan, J M | J100: OBrien, Joseph Patrick | K100: 18 | L100: 77 | M100: 3 | N100: 106 | O100: 3 | P100: 6.2491329 | Q100: 0.1600222 | R100: 6.5 | S100: =IF(AND(ISNUMBER(R100),R100>1,P100>0),R100/P100-1,"") -> 0.040144301 | T100: =IF(AND(ISNUMBER(P100),P100>0),P100*EXP('Read me'!$B$22),"") -> 7.6327082
A101: 5:25 | B101: Curragh | C101: Equiwinner Patches Fillies Maiden | E101: 9 | F101: Good | G101: 17 | H101: Saxony Charms (IRE) | I101: Carroll, G F | J101: Oliver, Andrew | K101: 8 | L101: 75 | M101: 3 | N101: 24 | O101: 4 | P101: 7.7992117 | Q101: 0.12821809 | R101: 9 | S101: =IF(AND(ISNUMBER(R101),R101>1,P101>0),R101/P101-1,"") -> 0.15396278 | T101: =IF(AND(ISNUMBER(P101),P101>0),P101*EXP('Read me'!$B$22),"") -> 9.5259786
A102: 5:25 | B102: Curragh | C102: Equiwinner Patches Fillies Maiden | E102: 9 | F102: Good | G102: 17 | H102: Lookingforarainbow (USA) | I102: Ryan, Gavin | J102: Obrien, Donnacha | K102: 16 | L102: 84 | M102: 3 | N102: 21 | O102: 5 | P102: 9.1406096 | Q102: 0.10940189 | R102: 7 | S102: =IF(AND(ISNUMBER(R102),R102>1,P102>0),R102/P102-1,"") -> -0.23418675 | T102: =IF(AND(ISNUMBER(P102),P102>0),P102*EXP('Read me'!$B$22),"") -> 11.164366
A103: 5:25 | B103: Curragh | C103: Equiwinner Patches Fillies Maiden | E103: 9 | F103: Good | G103: 17 | H103: Serendipia (IRE) | I103: Lee, W J | J103: McCreery, W | K103: 1 | L103: 72 | M103: 3 | N103: 24 | O103: 6 | P103: 14.49897 | Q103: 0.068970417 | R103: 13 | S103: =IF(AND(ISNUMBER(R103),R103>1,P103>0),R103/P103-1,"") -> -0.10338458 | T103: =IF(AND(ISNUMBER(P103),P103>0),P103*EXP('Read me'!$B$22),"") -> 17.709082
A104: 5:25 | B104: Curragh | C104: Equiwinner Patches Fillies Maiden | E104: 9 | F104: Good | G104: 17 | H104: Camelot Queen (IRE) | I104: Lordan, W M | J104: OBrien, A P | K104: 4 | L104: 72 | M104: 3 | N104: 71 | O104: 7 | P104: 19.558938 | Q104: 0.051127521 | R104: 9 | S104: =IF(AND(ISNUMBER(R104),R104>1,P104>0),R104/P104-1,"") -> -0.53985231 | T104: =IF(AND(ISNUMBER(P104),P104>0),P104*EXP('Read me'!$B$22),"") -> 23.889341
A105: 5:25 | B105: Curragh | C105: Equiwinner Patches Fillies Maiden | E105: 9 | F105: Good | G105: 17 | H105: Emberelle (IRE) | I105: Keane, C T | J105: Murphy, John Joseph | K105: 2 | L105: 0 | M105: 3 | N105: 21 | O105: 8 | P105: 22.860639 | Q105: 0.043743309 | R105: 13 | S105: =IF(AND(ISNUMBER(R105),R105>1,P105>0),R105/P105-1,"") -> -0.43133698 | T105: =IF(AND(ISNUMBER(P105),P105>0),P105*EXP('Read me'!$B$22),"") -> 27.922048
A106: 5:25 | B106: Curragh | C106: Equiwinner Patches Fillies Maiden | E106: 9 | F106: Good | G106: 17 | H106: Goddess Of War (SAF) | I106: Crosse, Nathan | J106: Harrington, Mrs John | K106: 5 | L106: 0 | M106: 4 | N106: 37 | O106: 9 | P106: 23.752346 | Q106: 0.042101105 | R106: 7.5 | S106: =IF(AND(ISNUMBER(R106),R106>1,P106>0),R106/P106-1,"") -> -0.68424171 | T106: =IF(AND(ISNUMBER(P106),P106>0),P106*EXP('Read me'!$B$22),"") -> 29.011181
A107: 5:25 | B107: Curragh | C107: Equiwinner Patches Fillies Maiden | E107: 9 | F107: Good | G107: 17 | H107: Seventh Sea (GER) | I107: Caffrey, Adam | J107: Weld, D K | K107: 17 | L107: 0 | M107: 3 | O107: 10 | P107: 37.796993 | Q107: 0.026457131 | R107: 41 | S107: =IF(AND(ISNUMBER(R107),R107>1,P107>0),R107/P107-1,"") -> 0.084742389 | T107: =IF(AND(ISNUMBER(P107),P107>0),P107*EXP('Read me'!$B$22),"") -> 46.165351
A108: 5:25 | B108: Curragh | C108: Equiwinner Patches Fillies Maiden | E108: 9 | F108: Good | G108: 17 | H108: Socratea (IRE) | I108: McDonogh, D P | J108: McCreery, W | K108: 7 | L108: 0 | M108: 3 | N108: 24 | O108: 11 | P108: 76.291965 | Q108: 0.01310754 | R108: 51 | S108: =IF(AND(ISNUMBER(R108),R108>1,P108>0),R108/P108-1,"") -> -0.33151545 | T108: =IF(AND(ISNUMBER(P108),P108>0),P108*EXP('Read me'!$B$22),"") -> 93.183217
A109: 5:25 | B109: Curragh | C109: Equiwinner Patches Fillies Maiden | E109: 9 | F109: Good | G109: 17 | H109: Brigids Charm (IRE) | I109: Holohan, Reese | J109: Fahey, Mark | K109: 10 | L109: 0 | M109: 3 | N109: 42 | O109: 12 | P109: 684.39952 | Q109: 0.0014611349 | R109: 81 | S109: =IF(AND(ISNUMBER(R109),R109>1,P109>0),R109/P109-1,"") -> -0.88164808 | T109: =IF(AND(ISNUMBER(P109),P109>0),P109*EXP('Read me'!$B$22),"") -> 835.92747
A110: 5:25 | B110: Curragh | C110: Equiwinner Patches Fillies Maiden | E110: 9 | F110: Good | G110: 17 | H110: Molls Gap (IRE) | I110: Powell, J A | J110: Murtagh, J P | K110: 13 | L110: 0 | M110: 3 | N110: 21 | O110: 13 | P110: 686.24816 | Q110: 0.0014571988 | R110: 101 | S110: =IF(AND(ISNUMBER(R110),R110>1,P110>0),R110/P110-1,"") -> -0.85282292 | T110: =IF(AND(ISNUMBER(P110),P110>0),P110*EXP('Read me'!$B$22),"") -> 838.18539
A111: 5:25 | B111: Curragh | C111: Equiwinner Patches Fillies Maiden | E111: 9 | F111: Good | G111: 17 | H111: Ballysax Boo | I111: Ryan, J J G | J111: Brown, Miss Katy | K111: 3 | L111: 0 | M111: 3 | N111: 63 | O111: 14 | P111: 919.06361 | Q111: 0.001088064 | R111: 151 | S111: =IF(AND(ISNUMBER(R111),R111>1,P111>0),R111/P111-1,"") -> -0.83570234 | T111: =IF(AND(ISNUMBER(P111),P111>0),P111*EXP('Read me'!$B$22),"") -> 1122.5468
A112: 5:25 | B112: Curragh | C112: Equiwinner Patches Fillies Maiden | E112: 9 | F112: Good | G112: 17 | H112: Pattyandselma (IRE) | I112: Cleary, R P | J112: McGuinness, Adrian | K112: 11 | L112: 0 | M112: 3 | N112: 8 | O112: 15 | P112: 1053.251 | Q112: 0.00094944131 | R112: 151 | S112: =IF(AND(ISNUMBER(R112),R112>1,P112>0),R112/P112-1,"") -> -0.85663436 | T112: =IF(AND(ISNUMBER(P112),P112>0),P112*EXP('Read me'!$B$22),"") -> 1286.4437
A113: 5:25 | B113: Curragh | C113: Equiwinner Patches Fillies Maiden | E113: 9 | F113: Good | G113: 17 | H113: Isthatrightkatie (IRE) | I113: Joyce, Wesley | J113: Brown, Miss Katy | K113: 12 | L113: 0 | M113: 6 | N113: 22 | O113: 16 | P113: 1237.1405 | Q113: 0.00080831561 | R113: 151 | S113: =IF(AND(ISNUMBER(R113),R113>1,P113>0),R113/P113-1,"") -> -0.87794434 | T113: =IF(AND(ISNUMBER(P113),P113>0),P113*EXP('Read me'!$B$22),"") -> 1511.0469
A114: 5:25 | B114: Curragh | C114: Equiwinner Patches Fillies Maiden | E114: 9 | F114: Good | G114: 17 | H114: Queen Of Chenab (IRE) | I114: Abbas, G | J114: Flynn, Patrick J | K114: 9 | L114: 0 | M114: 6 | N114: 10 | O114: 17 | P114: 1900.2788 | Q114: 0.00052623856 | R114: 67 | S114: =IF(AND(ISNUMBER(R114),R114>1,P114>0),R114/P114-1,"") -> -0.96474202 | T114: =IF(AND(ISNUMBER(P114),P114>0),P114*EXP('Read me'!$B$22),"") -> 2321.0058

Sheet Haydock
A1: Time | B1: Course | C1: Race | D1: Class | E1: Furlongs | F1: Going | G1: Runners | H1: Horse | I1: Jockey | J1: Trainer | K1: Draw | L1: OR | M1: Age | N1: Days since run | O1: Model rank | P1: Predicted BSP | Q1: Win probability | R1: Card odds (HRB) | S1: Card odds vs model | T1: Rule: back at Betfair ≥
A2: 1:35 | B2: Haydock | C2: William Hill Epic Boosts Handicap | D2: Class 2 | E2: 8 | F2: Heavy | G2: 10 | H2: Eternal Force | I2: Fallon, Cieren | J2: Haggas, W J | K2: 4 | L2: 96 | M2: 4 | N2: 37 | O2: 1 | P2: 5.2683602 | Q2: 0.18981238 | R2: 4.5 | S2: =IF(AND(ISNUMBER(R2),R2>1,P2>0),R2/P2-1,"") -> -0.14584427 | T2: =IF(AND(ISNUMBER(P2),P2>0),P2*EXP('Read me'!$B$22),"") -> 6.4347896
A3: 1:35 | B3: Haydock | C3: William Hill Epic Boosts Handicap | D3: Class 2 | E3: 8 | F3: Heavy | G3: 10 | H3: Centigrade (IRE) | I3: Crouch, Hector | J3: Beckett, R M | K3: 9 | L3: 100 | M3: 4 | N3: 10 | O3: 2 | P3: 5.8434044 | Q3: 0.17113311 | R3: 6.5 | S3: =IF(AND(ISNUMBER(R3),R3>1,P3>0),R3/P3-1,"") -> 0.11236525 | T3: =IF(AND(ISNUMBER(P3),P3>0),P3*EXP('Read me'!$B$22),"") -> 7.1371503
A4: 1:35 | B4: Haydock | C4: William Hill Epic Boosts Handicap | D4: Class 2 | E4: 8 | F4: Heavy | G4: 10 | H4: Looka (USA) | I4: Levey, S M | J4: Botti, M | K4: 3 | L4: 93 | M4: 3 | N4: 23 | O4: 3 | P4: 7.4300309 | Q4: 0.13458894 | R4: 7 | S4: =IF(AND(ISNUMBER(R4),R4>1,P4>0),R4/P4-1,"") -> -0.057877408 | T4: =IF(AND(ISNUMBER(P4),P4>0),P4*EXP('Read me'!$B$22),"") -> 9.0750603
A5: 1:35 | B5: Haydock | C5: William Hill Epic Boosts Handicap | D5: Class 2 | E5: 8 | F5: Heavy | G5: 10 | H5: Cerulean Bay (IRE) | I5: Tudhope, Daniel | J5: OMeara, D | K5: 1 | L5: 104 | M5: 5 | N5: 37 | O5: 4 | P5: 7.6360691 | Q5: 0.13095743 | R5: 7.5 | S5: =IF(AND(ISNUMBER(R5),R5>1,P5>0),R5/P5-1,"") -> -0.017819255 | T5: =IF(AND(ISNUMBER(P5),P5>0),P5*EXP('Read me'!$B$22),"") -> 9.3267158
A6: 1:35 | B6: Haydock | C6: William Hill Epic Boosts Handicap | D6: Class 2 | E6: 8 | F6: Heavy | G6: 10 | H6: Arctic Thunder (IRE) | I6: Lewis, Ashley | J6: Walker, Ed | K6: 10 | L6: 96 | M6: 5 | N6: 22 | O6: 5 | P6: 12.16776 | Q6: 0.082184395 | R6: 11 | S6: =IF(AND(ISNUMBER(R6),R6>1,P6>0),R6/P6-1,"") -> -0.095971651 | T6: =IF(AND(ISNUMBER(P6),P6>0),P6*EXP('Read me'!$B$22),"") -> 14.861736
A7: 1:35 | B7: Haydock | C7: William Hill Epic Boosts Handicap | D7: Class 2 | E7: 8 | F7: Heavy | G7: 10 | H7: Godwinson | I7: Probert, David | J7: Channon, Jack | K7: 5 | L7: 96 | M7: 6 | N7: 57 | O7: 6 | P7: 14.699878 | Q7: 0.068027777 | R7: 10 | S7: =IF(AND(ISNUMBER(R7),R7>1,P7>0),R7/P7-1,"") -> -0.31972223 | T7: =IF(AND(ISNUMBER(P7),P7>0),P7*EXP('Read me'!$B$22),"") -> 17.954471
A8: 1:35 | B8: Haydock | C8: William Hill Epic Boosts Handicap | D8: Class 2 | E8: 8 | F8: Heavy | G8: 10 | H8: Mister Winston | I8: McDonald, P J | J8: Balding, A M | K8: 6 | L8: 100 | M8: 4 | N8: 14 | O8: 7 | P8: 14.954557 | Q8: 0.06686925 | R8: 10 | S8: =IF(AND(ISNUMBER(R8),R8>1,P8>0),R8/P8-1,"") -> -0.3313075 | T8: =IF(AND(ISNUMBER(P8),P8>0),P8*EXP('Read me'!$B$22),"") -> 18.265537
A9: 1:35 | B9: Haydock | C9: William Hill Epic Boosts Handicap | D9: Class 2 | E9: 8 | F9: Heavy | G9: 10 | H9: Commanders Intent (FR) | I9: Rodriguez, Callum | J9: Scott, George | K9: 2 | L9: 100 | M9: 3 | N9: 163 | O9: 8 | P9: 17.48279 | Q9: 0.057199107 | R9: 10 | S9: =IF(AND(ISNUMBER(R9),R9>1,P9>0),R9/P9-1,"") -> -0.42800893 | T9: =IF(AND(ISNUMBER(P9),P9>0),P9*EXP('Read me'!$B$22),"") -> 21.353529
A10: 1:35 | B10: Haydock | C10: William Hill Epic Boosts Handicap | D10: Class 2 | E10: 8 | F10: Heavy | G10: 10 | H10: Desperate Dan (IRE) | I10: Wood, George | J10: Chapple-Hyam, P W | K10: 7 | L10: 85 | M10: 5 | N10: 106 | O10: 9 | P10: 18.929647 | Q10: 0.052827187 | R10: 23 | S10: =IF(AND(ISNUMBER(R10),R10>1,P10>0),R10/P10-1,"") -> 0.2150253 | T10: =IF(AND(ISNUMBER(P10),P10>0),P10*EXP('Read me'!$B$22),"") -> 23.120723
A11: 1:35 | B11: Haydock | C11: William Hill Epic Boosts Handicap | D11: Class 2 | E11: 8 | F11: Heavy | G11: 10 | H11: Checkandchallenge | I11: Shepherd, Callum | J11: Knight, W J | K11: 8 | L11: 96 | M11: 7 | N11: 14 | O11: 10 | P11: 21.551533 | Q11: 0.046400412 | R11: 17 | S11: =IF(AND(ISNUMBER(R11),R11>1,P11>0),R11/P11-1,"") -> -0.211193 | T11: =IF(AND(ISNUMBER(P11),P11>0),P11*EXP('Read me'!$B$22),"") -> 26.323102
A12: 2:10 | B12: Haydock | C12: William Hill Best Odds Guaranteed Handicap | D12: Class 2 | E12: 5 | F12: Heavy | G12: 10 | H12: Trilby | I12: McDonald, P J | J12: England, Sam | K12: 4 | L12: 89 | M12: 6 | N12: 7 | O12: 1 | P12: 4.5888249 | Q12: 0.21792071 | R12: 3.25 | S12: =IF(AND(ISNUMBER(R12),R12>1,P12>0),R12/P12-1,"") -> -0.29175768 | T12: =IF(AND(ISNUMBER(P12),P12>0),P12*EXP('Read me'!$B$22),"") -> 5.6048034
A13: 2:10 | B13: Haydock | C13: William Hill Best Odds Guaranteed Handicap | D13: Class 2 | E13: 5 | F13: Heavy | G13: 10 | H13: King Of Light | I13: Tudhope, Daniel | J13: Williams, S C | K13: 11 | L13: 94 | M13: 4 | N13: 14 | O13: 2 | P13: 4.8875045 | Q13: 0.20460339 | R13: 4 | S13: =IF(AND(ISNUMBER(R13),R13>1,P13>0),R13/P13-1,"") -> -0.18158644 | T13: =IF(AND(ISNUMBER(P13),P13>0),P13*EXP('Read me'!$B$22),"") -> 5.9696115
... A26: 2:40 | B26: Haydock | C26: British EBF Fillies Novice Stakes (GBB Race) | D26: Class 3 | E26: 8 | F26: Heavy | G26: 9 | H26: Woollahra (IRE) | I26: Rodriguez, Callum | J26: Morland, Jack | K26: 6 | L26: 0 | M26: 2 | N26: 36 | O26: 5 | P26: 13.317788 | Q26: 0.075087542 | R26: 11 | S26: =IF(AND(ISNUMBER(R26),R26>1,P26>0),R26/P26-1,"") -> -0.17403704 | T26: =IF(AND(ISNUMBER(P26),P26>0),P26*EXP('Read me'!$B$22),"") -> 16.266384
A27: 2:40 | B27: Haydock | C27: British EBF Fillies Novice Stakes (GBB Race) | D27: Class 3 | E27: 8 | F27: Heavy | G27: 9 | H27: Hotterthanjuly (IRE) | I27: Levey, S M | J27: Hannon (Jnr), Richard | K27: 1 | L27: 0 | M27: 2 | O27: 6 | P27: 17.558908 | Q27: 0.056951149 | R27: 9.5 | S27: =IF(AND(ISNUMBER(R27),R27>1,P27>0),R27/P27-1,"") -> -0.45896409 | T27: =IF(AND(ISNUMBER(P27),P27>0),P27*EXP('Read me'!$B$22),"") -> 21.446499
A28: 2:40 | B28: Haydock | C28: British EBF Fillies Novice Stakes (GBB Race) | D28: Class 3 | E28: 8 | F28: Heavy | G28: 9 | H28: Miss Faithfull (IRE) | I28: Bradley, Paddy | J28: Fellowes, Charlie | K28: 2 | L28: 0 | M28: 2 | N28: 23 | O28: 7 | P28: 20.912652 | Q28: 0.047817943 | R28: 29 | S28: =IF(AND(ISNUMBER(R28),R28>1,P28>0),R28/P28-1,"") -> 0.38672034 | T28: =IF(AND(ISNUMBER(P28),P28>0),P28*EXP('Read me'!$B$22),"") -> 25.542771
A29: 2:40 | B29: Haydock | C29: British EBF Fillies Novice Stakes (GBB Race) | D29: Class 3 | E29: 8 | F29: Heavy | G29: 9 | H29: Shabby | I29: Shepherd, Callum | J29: Bell, M L W | K29: 5 | L29: 0 | M29: 2 | O29: 8 | P29: 27.209766 | Q29: 0.03675151 | R29: 26 | S29: =IF(AND(ISNUMBER(R29),R29>1,P29>0),R29/P29-1,"") -> -0.044460737 | T29: =IF(AND(ISNUMBER(P29),P29>0),P29*EXP('Read me'!$B$22),"") -> 33.234084
A30: 2:40 | B30: Haydock | C30: British EBF Fillies Novice Stakes (GBB Race) | D30: Class 3 | E30: 8 | F30: Heavy | G30: 9 | H30: Zirconic | I30: Lewis, Ashley | J30: Palmer, Hugo | K30: 8 | L30: 0 | M30: 2 | N30: 18 | O30: 9 | P30: 31.200565 | Q30: 0.032050702 | R30: 23 | S30: =IF(AND(ISNUMBER(R30),R30>1,P30>0),R30/P30-1,"") -> -0.26283387 | T30: =IF(AND(ISNUMBER(P30),P30>0),P30*EXP('Read me'!$B$22),"") -> 38.108456
A31: 3:15 | B31: Haydock | C31: Forever Our Mike Handicap | D31: Class 3 | E31: 6 | F31: Heavy | G31: 11 | H31: Art Lover (IRE) | I31: Fallon, Cieren | J31: Haggas, W J | K31: 1 | L31: 85 | M31: 3 | N31: 9 | O31: 1 | P31: 6.4053292 | Q31: 0.15612 | R31: 7.5 | S31: =IF(AND(ISNUMBER(R31),R31>1,P31>0),R31/P31-1,"") -> 0.17090001 | T31: =IF(AND(ISNUMBER(P31),P31>0),P31*EXP('Read me'!$B$22),"") -> 7.8234867
A32: 3:15 | B32: Haydock | C32: Forever Our Mike Handicap | D32: Class 3 | E32: 6 | F32: Heavy | G32: 11 | H32: Rousing Encore (IRE) | I32: Sullivan, James P | J32: Carr, Mrs R A | K32: 11 | L32: 85 | M32: 6 | N32: 8 | O32: 2 | P32: 6.4773548 | Q32: 0.15438401 | R32: 4.5 | S32: =IF(AND(ISNUMBER(R32),R32>1,P32>0),R32/P32-1,"") -> -0.30527196 | T32: =IF(AND(ISNUMBER(P32),P32>0),P32*EXP('Read me'!$B$22),"") -> 7.911459
A33: 3:15 | B33: Haydock | C33: Forever Our Mike Handicap | D33: Class 3 | E33: 6 | F33: Heavy | G33: 11 | H33: Angel Gabriel (IRE) | I33: Crouch, Hector | J33: Beckett, R M | K33: 13 | L33: 83 | M33: 3 | N33: 28 | O33: 3 | P33: 7.5516046 | Q33: 0.13242219 | R33: 5.5 | S33: =IF(AND(ISNUMBER(R33),R33>1,P33>0),R33/P33-1,"") -> -0.27167797 | T33: =IF(AND(ISNUMBER(P33),P33>0),P33*EXP('Read me'!$B$22),"") -> 9.2235507
A34: 3:15 | B34: Haydock | C34: Forever Our Mike Handicap | D34: Class 3 | E34: 6 | F34: Heavy | G34: 11 | H34: Miraculous (IRE) | I34: Kirrane, Sean | J34: Easterby, T D | K34: 10 | L34: 83 | M34: 4 | N34: 7 | O34: 4 | P34: 9.0592392 | Q34: 0.11038454 | R34: 13 | S34: =IF(AND(ISNUMBER(R34),R34>1,P34>0),R34/P34-1,"") -> 0.43499908 | T34: =IF(AND(ISNUMBER(P34),P34>0),P34*EXP('Read me'!$B$22),"") -> 11.06498
A35: 3:15 | B35: Haydock | C35: Forever Our Mike Handicap | D35: Class 3 | E35: 6 | F35: Heavy | G35: 11 | H35: Dandy Magic (IRE) | I35: Tudhope, Daniel | J35: Goldie, J S | K35: 9 | L35: 77 | M35: 4 | N35: 13 | O35: 5 | P35: 10.181786 | Q35: 0.098214592 | R35: 8.5 | S35: =IF(AND(ISNUMBER(R35),R35>1,P35>0),R35/P35-1,"") -> -0.16517596 | T35: =IF(AND(ISNUMBER(P35),P35>0),P35*EXP('Read me'!$B$22),"") -> 12.436062
A36: 3:15 | B36: Haydock | C36: Forever Our Mike Handicap | D36: Class 3 | E36: 6 | F36: Heavy | G36: 11 | H36: So Darn Hot | I36: Downing, George | J36: Walker, Ed | K36: 6 | L36: 90 | M36: 4 | N36: 45 | O36: 6 | P36: 10.874345 | Q36: 0.091959566 | R36: 12 | S36: =IF(AND(ISNUMBER(R36),R36>1,P36>0),R36/P36-1,"") -> 0.10351479 | T36: =IF(AND(ISNUMBER(P36),P36>0),P36*EXP('Read me'!$B$22),"") -> 13.281954
A37: 3:15 | B37: Haydock | C37: Forever Our Mike Handicap | D37: Class 3 | E37: 6 | F37: Heavy | G37: 11 | H37: Golden Long (AUS) | I37: Wood, George | J37: Souza, Lemos | K37: 5 | L37: 90 | M37: 6 | N37: 42 | O37: 7 | P37: 16.171208 | Q37: 0.0618383 | R37: 10 | S37: =IF(AND(ISNUMBER(R37),R37>1,P37>0),R37/P37-1,"") -> -0.381617 | T37: =IF(AND(ISNUMBER(P37),P37>0),P37*EXP('Read me'!$B$22),"") -> 19.751558
A38: 3:15 | B38: Haydock | C38: Forever Our Mike Handicap | D38: Class 3 | E38: 6 | F38: Heavy | G38: 11 | H38: Black Star Boy (IRE) | I38: Lewis, Ashley | J38: Walker, Ed | K38: 8 | L38: 88 | M38: 3 | N38: 21 | O38: 8 | P38: 18.03771 | Q38: 0.055439411 | R38: 17 | S38: =IF(AND(ISNUMBER(R38),R38>1,P38>0),R38/P38-1,"") -> -0.057530016 | T38: =IF(AND(ISNUMBER(P38),P38>0),P38*EXP('Read me'!$B$22),"") -> 22.031308
A39: 3:15 | B39: Haydock | C39: Forever Our Mike Handicap | D39: Class 3 | E39: 6 | F39: Heavy | G39: 11 | H39: Figjam (IRE) | I39: Mason, Joanna | J39: Scott, Miss Katie | K39: 12 | L39: 85 | M39: 3 | N39: 21 | O39: 9 | P39: 19.740185 | Q39: 0.050658087 | R39: 13 | S39: =IF(AND(ISNUMBER(R39),R39>1,P39>0),R39/P39-1,"") -> -0.34144487 | T39: =IF(AND(ISNUMBER(P39),P39>0),P39*EXP('Read me'!$B$22),"") -> 24.110716
A40: 3:15 | B40: Haydock | C40: Forever Our Mike Handicap | D40: Class 3 | E40: 6 | F40: Heavy | G40: 11 | H40: Proof | I40: Probert, David | J40: Hills, Charles | K40: 2 | L40: 77 | M40: 3 | N40: 7 | O40: 10 | P40: 21.233234 | Q40: 0.047095982 | R40: 9.5 | S40: =IF(AND(ISNUMBER(R40),R40>1,P40>0),R40/P40-1,"") -> -0.55258817 | T40: =IF(AND(ISNUMBER(P40),P40>0),P40*EXP('Read me'!$B$22),"") -> 25.93433
A41: 3:15 | B41: Haydock | C41: Forever Our Mike Handicap | D41: Class 3 | E41: 6 | F41: Heavy | G41: 11 | H41: Zain Primus | I41: Levey, S M | J41: Butler, John | K41: 14 | L41: 87 | M41: 3 | N41: 38 | O41: 11 | P41: 24.106075 | Q41: 0.041483319 | R41: 26 | S41: =IF(AND(ISNUMBER(R41),R41>1,P41>0),R41/P41-1,"") -> 0.078566302 | T41: =IF(AND(ISNUMBER(P41),P41>0),P41*EXP('Read me'!$B$22),"") -> 29.443226
... A53: 4:35 | B53: Haydock | C53: J&P Civil Engineering British EBF Maiden Stakes | D53: Class 3 | E53: 8 | F53: Heavy | G53: 6 | H53: Dancing Dunes (GER) | I53: Rodriguez, Callum | J53: Beckett, R M | K53: 5 | L53: 0 | M53: 2 | N53: 23 | O53: 5 | P53: 25.625672 | Q53: 0.039023367 | R53: 26 | S53: =IF(AND(ISNUMBER(R53),R53>1,P53>0),R53/P53-1,"") -> 0.01460753 | T53: =IF(AND(ISNUMBER(P53),P53>0),P53*EXP('Read me'!$B$22),"") -> 31.299267
A54: 4:35 | B54: Haydock | C54: J&P Civil Engineering British EBF Maiden Stakes | D54: Class 3 | E54: 8 | F54: Heavy | G54: 6 | H54: River Glen (IRE) | I54: Tudhope, Daniel | J54: Menzies, Rebecca | K54: 4 | L54: 0 | M54: 2 | O54: 6 | P54: 50.431696 | Q54: 0.0198288 | R54: 151 | S54: =IF(AND(ISNUMBER(R54),R54>1,P54>0),R54/P54-1,"") -> 1.9941488 | T54: =IF(AND(ISNUMBER(P54),P54>0),P54*EXP('Read me'!$B$22),"") -> 61.597413
A55: 5:10 | B55: Haydock | C55: William Hill Daily Winnings Boost Handicap (GBBPlus Race) | D55: Class 4 | E55: 14.5 | F55: Heavy | G55: 9 | H55: Alther Walden (HUN) | I55: Rodriguez, Callum | J55: Scott, George | K55: 10 | L55: 86 | M55: 4 | N55: 153 | O55: 1 | P55: 5.0163146 | Q55: 0.19934954 | R55: 3.5 | S55: =IF(AND(ISNUMBER(R55),R55>1,P55>0),R55/P55-1,"") -> -0.30227662 | T55: =IF(AND(ISNUMBER(P55),P55>0),P55*EXP('Read me'!$B$22),"") -> 6.1269405
A56: 5:10 | B56: Haydock | C56: William Hill Daily Winnings Boost Handicap (GBBPlus Race) | D56: Class 4 | E56: 14.5 | F56: Heavy | G56: 9 | H56: Sharp Move (IRE) | I56: Fallon, Cieren | J56: Haggas, W J | K56: 8 | L56: 76 | M56: 4 | N56: 23 | O56: 2 | P56: 5.7989509 | Q56: 0.17244498 | R56: 9 | S56: =IF(AND(ISNUMBER(R56),R56>1,P56>0),R56/P56-1,"") -> 0.55200486 | T56: =IF(AND(ISNUMBER(P56),P56>0),P56*EXP('Read me'!$B$22),"") -> 7.0828546
A57: 5:10 | B57: Haydock | C57: William Hill Daily Winnings Boost Handicap (GBBPlus Race) | D57: Class 4 | E57: 14.5 | F57: Heavy | G57: 9 | H57: Trojan Sun | I57: Mason, Joanna | J57: Goldie, J S | K57: 3 | L57: 71 | M57: 6 | N57: 14 | O57: 3 | P57: 6.3146148 | Q57: 0.15836279 | R57: 4.5 | S57: =IF(AND(ISNUMBER(R57),R57>1,P57>0),R57/P57-1,"") -> -0.28736745 | T57: =IF(AND(ISNUMBER(P57),P57>0),P57*EXP('Read me'!$B$22),"") -> 7.7126879
A58: 5:10 | B58: Haydock | C58: William Hill Daily Winnings Boost Handicap (GBBPlus Race) | D58: Class 4 | E58: 14.5 | F58: Heavy | G58: 9 | H58: Gentle Warrior (IRE) | I58: Jamin, Pierre-Louis | J58: Burke, K R | K58: 2 | L58: 71 | M58: 4 | N58: 14 | O58: 4 | P58: 6.517708 | Q58: 0.15342817 | R58: 7 | S58: =IF(AND(ISNUMBER(R58),R58>1,P58>0),R58/P58-1,"") -> 0.073997177 | T58: =IF(AND(ISNUMBER(P58),P58>0),P58*EXP('Read me'!$B$22),"") -> 7.9607465
A59: 5:10 | B59: Haydock | C59: William Hill Daily Winnings Boost Handicap (GBBPlus Race) | D59: Class 4 | E59: 14.5 | F59: Heavy | G59: 9 | H59: Mick Collins (IRE) | I59: McDonald, P J | J59: Todhunter, M | K59: 9 | L59: 78 | M59: 5 | N59: 14 | O59: 5 | P59: 7.0117428 | Q59: 0.14261789 | R59: 5 | S59: =IF(AND(ISNUMBER(R59),R59>1,P59>0),R59/P59-1,"") -> -0.28691053 | T59: =IF(AND(ISNUMBER(P59),P59>0),P59*EXP('Read me'!$B$22),"") -> 8.564162
A60: 5:10 | B60: Haydock | C60: William Hill Daily Winnings Boost Handicap (GBBPlus Race) | D60: Class 4 | E60: 14.5 | F60: Heavy | G60: 9 | H60: Shadow Dance | I60: Bradley, Paddy | J60: Menzies, Rebecca | K60: 5 | L60: 83 | M60: 6 | N60: 20 | O60: 6 | P60: 16.035138 | Q60: 0.062363044 | R60: 29 | S60: =IF(AND(ISNUMBER(R60),R60>1,P60>0),R60/P60-1,"") -> 0.80852829 | T60: =IF(AND(ISNUMBER(P60),P60>0),P60*EXP('Read me'!$B$22),"") -> 19.585361
A61: 5:10 | B61: Haydock | C61: William Hill Daily Winnings Boost Handicap (GBBPlus Race) | D61: Class 4 | E61: 14.5 | F61: Heavy | G61: 9 | H61: Soul Limbo (IRE) | I61: Levey, S M | J61: Fry, Harry | K61: 7 | L61: 74 | M61: 6 | N61: 355 | O61: 7 | P61: 16.760989 | Q61: 0.059662349 | R61: 12 | S61: =IF(AND(ISNUMBER(R61),R61>1,P61>0),R61/P61-1,"") -> -0.28405181 | T61: =IF(AND(ISNUMBER(P61),P61>0),P61*EXP('Read me'!$B$22),"") -> 20.471919
A62: 5:10 | B62: Haydock | C62: William Hill Daily Winnings Boost Handicap (GBBPlus Race) | D62: Class 4 | E62: 14.5 | F62: Heavy | G62: 9 | H62: Yaa Min | I62: Moore, Toby | J62: Burton, Hayley | K62: 6 | L62: 78 | M62: 4 | N62: 26 | O62: 8 | P62: 23.660336 | Q62: 0.042264827 | R62: 15 | S62: =IF(AND(ISNUMBER(R62),R62>1,P62>0),R62/P62-1,"") -> -0.3660276 | T62: =IF(AND(ISNUMBER(P62),P62>0),P62*EXP('Read me'!$B$22),"") -> 28.898799
A63: 5:10 | B63: Haydock | C63: William Hill Daily Winnings Boost Handicap (GBBPlus Race) | D63: Class 4 | E63: 14.5 | F63: Heavy | G63: 9 | H63: Evaluation | I63: Gray, S A | J63: Nicol, Adam | K63: 4 | L63: 85 | M63: 8 | N63: 36 | O63: 9 | P63: 105.19222 | Q63: 0.0095064067 | R63: 81 | S63: =IF(AND(ISNUMBER(R63),R63>1,P63>0),R63/P63-1,"") -> -0.22998105 | T63: =IF(AND(ISNUMBER(P63),P63>0),P63*EXP('Read me'!$B$22),"") -> 128.48206

Sheet Ripon
A1: Time | B1: Course | C1: Race | D1: Class | E1: Furlongs | F1: Going | G1: Runners | H1: Horse | I1: Jockey | J1: Trainer | K1: Draw | L1: OR | M1: Age | N1: Days since run | O1: Model rank | P1: Predicted BSP | Q1: Win probability | R1: Card odds (HRB) | S1: Card odds vs model | T1: Rule: back at Betfair ≥
A2: 1:44 | B2: Ripon | C2: Theakston Brewing Legends Since 1827 EBF Novice Stakes (GBB Race) | D2: Class 4 | E2: 6 | F2: Good | G2: 9 | H2: Scenic Route (IRE) | I2: Orr, Oisin | J2: Fahey, R A | K2: 3 | L2: 78 | M2: 2 | N2: 20 | O2: 1 | P2: 2.1969837 | Q2: 0.45516951 | R2: 1.9090909 | S2: =IF(AND(ISNUMBER(R2),R2>1,P2>0),R2/P2-1,"") -> -0.13104004 | T2: =IF(AND(ISNUMBER(P2),P2>0),P2*EXP('Read me'!$B$22),"") -> 2.683402
A3: 1:44 | B3: Ripon | C3: Theakston Brewing Legends Since 1827 EBF Novice Stakes (GBB Race) | D3: Class 4 | E3: 6 | F3: Good | G3: 9 | H3: Bulletsnap (IRE) | I3: Hart, Jason | J3: Haggas, W J | K3: 9 | L3: 78 | M3: 2 | N3: 28 | O3: 2 | P3: 2.6507783 | Q3: 0.37724769 | R3: 2.5 | S3: =IF(AND(ISNUMBER(R3),R3>1,P3>0),R3/P3-1,"") -> -0.056880779 | T3: =IF(AND(ISNUMBER(P3),P3>0),P3*EXP('Read me'!$B$22),"") -> 3.237668
A4: 1:44 | B4: Ripon | C4: Theakston Brewing Legends Since 1827 EBF Novice Stakes (GBB Race) | D4: Class 4 | E4: 6 | F4: Good | G4: 9 | H4: Time To Play (IRE) | I4: Mulrennan, Paul | J4: Burke, K R | K4: 6 | L4: 0 | M4: 2 | N4: 23 | O4: 3 | P4: 8.7746445 | Q4: 0.11396473 | R4: 6 | S4: =IF(AND(ISNUMBER(R4),R4>1,P4>0),R4/P4-1,"") -> -0.31621162 | T4: =IF(AND(ISNUMBER(P4),P4>0),P4*EXP('Read me'!$B$22),"") -> 10.717375
A5: 1:44 | B5: Ripon | C5: Theakston Brewing Legends Since 1827 EBF Novice Stakes (GBB Race) | D5: Class 4 | E5: 6 | F5: Good | G5: 9 | H5: Alfa Hoodini (IRE) | I5: Nolan, D | J5: Furtado, Ivan | K5: 7 | L5: 0 | M5: 2 | N5: 16 | O5: 4 | P5: 53.002055 | Q5: 0.018867193 | R5: 29 | S5: =IF(AND(ISNUMBER(R5),R5>1,P5>0),R5/P5-1,"") -> -0.4528514 | T5: =IF(AND(ISNUMBER(P5),P5>0),P5*EXP('Read me'!$B$22),"") -> 64.736856
A6: 1:44 | B6: Ripon | C6: Theakston Brewing Legends Since 1827 EBF Novice Stakes (GBB Race) | D6: Class 4 | E6: 6 | F6: Good | G6: 9 | H6: Commander Keith (IRE) | I6: Stammers, Oliver | J6: Frost, Kevin | K6: 2 | L6: 0 | M6: 2 | N6: 35 | O6: 5 | P6: 55.715171 | Q6: 0.017948433 | R6: 34 | S6: =IF(AND(ISNUMBER(R6),R6>1,P6>0),R6/P6-1,"") -> -0.38975329 | T6: =IF(AND(ISNUMBER(P6),P6>0),P6*EXP('Read me'!$B$22),"") -> 68.050664
A7: 1:44 | B7: Ripon | C7: Theakston Brewing Legends Since 1827 EBF Novice Stakes (GBB Race) | D7: Class 4 | E7: 6 | F7: Good | G7: 9 | H7: Jeans Tipple (FR) | I7: Beasley, Connor | J7: Kirby, P A | K7: 4 | L7: 0 | M7: 2 | O7: 6 | P7: 93.029003 | Q7: 0.010749336 | R7: 26 | S7: =IF(AND(ISNUMBER(R7),R7>1,P7>0),R7/P7-1,"") -> -0.72051727 | T7: =IF(AND(ISNUMBER(P7),P7>0),P7*EXP('Read me'!$B$22),"") -> 113.62588
A8: 1:44 | B8: Ripon | C8: Theakston Brewing Legends Since 1827 EBF Novice Stakes (GBB Race) | D8: Class 4 | E8: 6 | F8: Good | G8: 9 | H8: Cracking Toast | I8: Sexton, Ryan | J8: Hanmer, G D | K8: 8 | L8: 0 | M8: 2 | N8: 15 | O8: 7 | P8: 265.23782 | Q8: 0.0037702013 | R8: 67 | S8: =IF(AND(ISNUMBER(R8),R8>1,P8>0),R8/P8-1,"") -> -0.74739651 | T8: =IF(AND(ISNUMBER(P8),P8>0),P8*EXP('Read me'!$B$22),"") -> 323.96221
A9: 1:44 | B9: Ripon | C9: Theakston Brewing Legends Since 1827 EBF Novice Stakes (GBB Race) | D9: Class 4 | E9: 6 | F9: Good | G9: 9 | H9: Harry Akoya | I9: McManoman, Faye | J9: Tinkler, N | K9: 5 | L9: 0 | M9: 2 | N9: 10 | O9: 8 | P9: 711.80747 | Q9: 0.0014048743 | R9: 51 | S9: =IF(AND(ISNUMBER(R9),R9>1,P9>0),R9/P9-1,"") -> -0.92835141 | T9: =IF(AND(ISNUMBER(P9),P9>0),P9*EXP('Read me'!$B$22),"") -> 869.4036
A10: 1:44 | B10: Ripon | C10: Theakston Brewing Legends Since 1827 EBF Novice Stakes (GBB Race) | D10: Class 4 | E10: 6 | F10: Good | G10: 9 | H10: Ubettanotblink | I10: Eaves, Tom | J10: Lidster, Craig | K10: 1 | L10: 0 | M10: 2 | N10: 9 | O10: 9 | P10: 1138.902 | Q10: 0.00087803869 | R10: 201 | S10: =IF(AND(ISNUMBER(R10),R10>1,P10>0),R10/P10-1,"") -> -0.82351422 | T10: =IF(AND(ISNUMBER(P10),P10>0),P10*EXP('Read me'!$B$22),"") -> 1391.058
A11: 2:16 | B11: Ripon | C11: Lloyd Landrover Ripon Nursery (GBBPlus Race) | D11: Class 4 | E11: 8 | F11: Good | G11: 6 | H11: Aphra Behn | I11: Hart, Jason | J11: Beckett, R M | K11: 6 | L11: 66 | M11: 2 | N11: 50 | O11: 1 | P11: 3.9137923 | Q11: 0.25550666 | R11: 2.625 | S11: =IF(AND(ISNUMBER(R11),R11>1,P11>0),R11/P11-1,"") -> -0.32929502 | T11: =IF(AND(ISNUMBER(P11),P11>0),P11*EXP('Read me'!$B$22),"") -> 4.7803167
A12: 2:16 | B12: Ripon | C12: Lloyd Landrover Ripon Nursery (GBBPlus Race) | D12: Class 4 | E12: 8 | F12: Good | G12: 6 | H12: Zarakova | I12: Rawlinson, Ali | J12: Balding, A M | K12: 4 | L12: 80 | M12: 2 | N12: 16 | O12: 2 | P12: 4.3249916 | Q12: 0.23121432 | R12: 5.5 | S12: =IF(AND(ISNUMBER(R12),R12>1,P12>0),R12/P12-1,"") -> 0.27167876 | T12: =IF(AND(ISNUMBER(P12),P12>0),P12*EXP('Read me'!$B$22),"") -> 5.2825567
A13: 2:16 | B13: Ripon | C13: Lloyd Landrover Ripon Nursery (GBBPlus Race) | D13: Class 4 | E13: 8 | F13: Good | G13: 6 | H13: Forest Berry | I13: Morris, Luke | J13: Prescott, Sir Mark | K13: 1 | L13: 77 | M13: 2 | N13: 21 | O13: 3 | P13: 4.4351286 | Q13: 0.2254726 | R13: 5 | S13: =IF(AND(ISNUMBER(R13),R13>1,P13>0),R13/P13-1,"") -> 0.12736302 | T13: =IF(AND(ISNUMBER(P13),P13>0),P13*EXP('Read me'!$B$22),"") -> 5.4170784
A14: 2:16 | B14: Ripon | C14: Lloyd Landrover Ripon Nursery (GBBPlus Race) | D14: Class 4 | E14: 8 | F14: Good | G14: 6 | H14: Palace Legacy | I14: Beasley, Connor | J14: Tate, James | K14: 2 | L14: 75 | M14: 2 | N14: 18 | O14: 4 | P14: 6.2403187 | Q14: 0.16024823 | R14: 4.5 | S14: =IF(AND(ISNUMBER(R14),R14>1,P14>0),R14/P14-1,"") -> -0.27888298 | T14: =IF(AND(ISNUMBER(P14),P14>0),P14*EXP('Read me'!$B$22),"") -> 7.6219425
A15: 2:16 | B15: Ripon | C15: Lloyd Landrover Ripon Nursery (GBBPlus Race) | D15: Class 4 | E15: 8 | F15: Good | G15: 6 | H15: Statten Island (IRE) | I15: Eaves, Tom | J15: Ryan, K A | K15: 3 | L15: 72 | M15: 2 | N15: 30 | O15: 5 | P15: 15.523554 | Q15: 0.064418239 | R15: 21 | S15: =IF(AND(ISNUMBER(R15),R15>1,P15>0),R15/P15-1,"") -> 0.35278301 | T15: =IF(AND(ISNUMBER(P15),P15>0),P15*EXP('Read me'!$B$22),"") -> 18.960512
A16: 2:16 | B16: Ripon | C16: Lloyd Landrover Ripon Nursery (GBBPlus Race) | D16: Class 4 | E16: 8 | F16: Good | G16: 6 | H16: Cash Cove (IRE) | I16: Scott, Rowan | J16: Johnston, Charlie | K16: 5 | L16: 72 | M16: 2 | N16: 42 | O16: 6 | P16: 15.837833 | Q16: 0.063139953 | R16: 13 | S16: =IF(AND(ISNUMBER(R16),R16>1,P16>0),R16/P16-1,"") -> -0.17918061 | T16: =IF(AND(ISNUMBER(P16),P16>0),P16*EXP('Read me'!$B$22),"") -> 19.344372
A17: 2:49 | B17: Ripon | C17: Napoleons Casino And Restaurant Leeds Handicap | D17: Class 4 | E17: 5 | F17: Good | G17: 14 | H17: Tiva (IRE) | I17: Whiteley, C J | J17: OMeara, D | K17: 1 | L17: 85 | M17: 4 | N17: 13 | O17: 1 | P17: 6.4114403 | Q17: 0.15597119 | R17: 7 | S17: =IF(AND(ISNUMBER(R17),R17>1,P17>0),R17/P17-1,"") -> 0.091798357 | T17: =IF(AND(ISNUMBER(P17),P17>0),P17*EXP('Read me'!$B$22),"") -> 7.8309509
A18: 2:49 | B18: Ripon | C18: Napoleons Casino And Restaurant Leeds Handicap | D18: Class 4 | E18: 5 | F18: Good | G18: 14 | H18: Mighty Magnus (IRE) | I18: Beasley, Connor | J18: Dods, M | K18: 12 | L18: 81 | M18: 3 | N18: 13 | O18: 2 | P18: 8.5150373 | Q18: 0.1174393 | R18: 9.5 | S18: =IF(AND(ISNUMBER(R18),R18>1,P18>0),R18/P18-1,"") -> 0.11567333 | T18: =IF(AND(ISNUMBER(P18),P18>0),P18*EXP('Read me'!$B$22),"") -> 10.40029
A19: 2:49 | B19: Ripon | C19: Napoleons Casino And Restaurant Leeds Handicap | D19: Class 4 | E19: 5 | F19: Good | G19: 14 | H19: Equity Law | I19: Allan, David | J19: Easterby, T D | K19: 14 | L19: 80 | M19: 5 | N19: 13 | O19: 3 | P19: 8.8845463 | Q19: 0.11255499 | R19: 8.5 | S19: =IF(AND(ISNUMBER(R19),R19>1,P19>0),R19/P19-1,"") -> -0.043282608 | T19: =IF(AND(ISNUMBER(P19),P19>0),P19*EXP('Read me'!$B$22),"") -> 10.851609
... A69: 5:15 | B69: Ripon | C69: Jozef White Last Day Of Freedom Novice Stakes (GBB/GBBPlus Race) | D69: Class 3 | E69: 12 | F69: Good | G69: 10 | H69: Emtinan (IRE) | I69: Eaves, Tom | J69: Williams, S C | K69: 3 | L69: 0 | M69: 3 | N69: 324 | O69: 6 | P69: 48.916757 | Q69: 0.020442892 | R69: 17 | S69: =IF(AND(ISNUMBER(R69),R69>1,P69>0),R69/P69-1,"") -> -0.65247083 | T69: =IF(AND(ISNUMBER(P69),P69>0),P69*EXP('Read me'!$B$22),"") -> 59.747062
A70: 5:15 | B70: Ripon | C70: Jozef White Last Day Of Freedom Novice Stakes (GBB/GBBPlus Race) | D70: Class 3 | E70: 12 | F70: Good | G70: 10 | H70: Medran (IRE) | I70: Stammers, Oliver | J70: Tuer, Grant | K70: 9 | L70: 0 | M70: 3 | O70: 7 | P70: 51.437962 | Q70: 0.019440895 | R70: 67 | S70: =IF(AND(ISNUMBER(R70),R70>1,P70>0),R70/P70-1,"") -> 0.30253993 | T70: =IF(AND(ISNUMBER(P70),P70>0),P70*EXP('Read me'!$B$22),"") -> 62.826469
A71: 5:15 | B71: Ripon | C71: Jozef White Last Day Of Freedom Novice Stakes (GBB/GBBPlus Race) | D71: Class 3 | E71: 12 | F71: Good | G71: 10 | H71: Whos The Goat (IRE) | I71: Brookes, Aiden | J71: Hammond, Micky | K71: 5 | L71: 0 | M71: 6 | N71: 17 | O71: 8 | P71: 91.631139 | Q71: 0.010913321 | R71: 17 | S71: =IF(AND(ISNUMBER(R71),R71>1,P71>0),R71/P71-1,"") -> -0.81447355 | T71: =IF(AND(ISNUMBER(P71),P71>0),P71*EXP('Read me'!$B$22),"") -> 111.91853
A72: 5:15 | B72: Ripon | C72: Jozef White Last Day Of Freedom Novice Stakes (GBB/GBBPlus Race) | D72: Class 3 | E72: 12 | F72: Good | G72: 10 | H72: Going To Graceland (IRE) | I72: Scott, Rowan | J72: Johnston, Charlie | K72: 7 | L72: 0 | M72: 3 | N72: 32 | O72: 9 | P72: 95.362876 | Q72: 0.010486261 | R72: 51 | S72: =IF(AND(ISNUMBER(R72),R72>1,P72>0),R72/P72-1,"") -> -0.46520069 | T72: =IF(AND(ISNUMBER(P72),P72>0),P72*EXP('Read me'!$B$22),"") -> 116.47648
A73: 5:15 | B73: Ripon | C73: Jozef White Last Day Of Freedom Novice Stakes (GBB/GBBPlus Race) | D73: Class 3 | E73: 12 | F73: Good | G73: 10 | H73: Brittunculi | I73: Pyle, William | J73: Waggott, Miss Tracy | K73: 6 | L73: 0 | M73: 3 | N73: 23 | O73: 10 | P73: 1179.9103 | Q73: 0.00084752204 | R73: 251 | S73: =IF(AND(ISNUMBER(R73),R73>1,P73>0),R73/P73-1,"") -> -0.78727197 | T73: =IF(AND(ISNUMBER(P73),P73>0),P73*EXP('Read me'!$B$22),"") -> 1441.1457
A74: 5:45 | B74: Ripon | C74: Thank You To Our Groundstaff Handicap (GBBPlus Race) | D74: Class 4 | E74: 16 | F74: Good | G74: 5 | H74: Talismans Time | I74: Beasley, Connor | J74: Bethell, Ed | K74: 5 | L74: 79 | M74: 4 | N74: 46 | O74: 1 | P74: 2.7553851 | Q74: 0.36292568 | R74: 2.625 | S74: =IF(AND(ISNUMBER(R74),R74>1,P74>0),R74/P74-1,"") -> -0.047320092 | T74: =IF(AND(ISNUMBER(P74),P74>0),P74*EXP('Read me'!$B$22),"") -> 3.3654349
A75: 5:45 | B75: Ripon | C75: Thank You To Our Groundstaff Handicap (GBBPlus Race) | D75: Class 4 | E75: 16 | F75: Good | G75: 5 | H75: Zimmerman | I75: Allan, David | J75: Easterby, T D | K75: 4 | L75: 71 | M75: 7 | N75: 7 | O75: 2 | P75: 3.5634852 | Q75: 0.28062415 | R75: 4 | S75: =IF(AND(ISNUMBER(R75),R75>1,P75>0),R75/P75-1,"") -> 0.1224966 | T75: =IF(AND(ISNUMBER(P75),P75>0),P75*EXP('Read me'!$B$22),"") -> 4.3524506
A76: 5:45 | B76: Ripon | C76: Thank You To Our Groundstaff Handicap (GBBPlus Race) | D76: Class 4 | E76: 16 | F76: Good | G76: 5 | H76: Sax Appeal | I76: Scott, Rowan | J76: Johnston, Charlie | K76: 2 | L76: 82 | M76: 6 | N76: 14 | O76: 3 | P76: 5.406529 | Q76: 0.18496155 | R76: 5 | S76: =IF(AND(ISNUMBER(R76),R76>1,P76>0),R76/P76-1,"") -> -0.075192238 | T76: =IF(AND(ISNUMBER(P76),P76>0),P76*EXP('Read me'!$B$22),"") -> 6.6035495
A77: 5:45 | B77: Ripon | C77: Thank You To Our Groundstaff Handicap (GBBPlus Race) | D77: Class 4 | E77: 16 | F77: Good | G77: 5 | H77: Tarbat Ness | I77: Mulrennan, Paul | J77: Berry, John | K77: 1 | L77: 72 | M77: 7 | N77: 23 | O77: 4 | P77: 10.81851 | Q77: 0.092434171 | R77: 7.5 | S77: =IF(AND(ISNUMBER(R77),R77>1,P77>0),R77/P77-1,"") -> -0.30674372 | T77: =IF(AND(ISNUMBER(P77),P77>0),P77*EXP('Read me'!$B$22),"") -> 13.213758
A78: 5:45 | B78: Ripon | C78: Thank You To Our Groundstaff Handicap (GBBPlus Race) | D78: Class 4 | E78: 16 | F78: Good | G78: 5 | H78: Gibside | I78: Dickson, Jake | J78: Easterby, T D | K78: 3 | L78: 68 | M78: 7 | N78: 46 | O78: 5 | P78: 12.64951 | Q78: 0.079054447 | R78: 8 | S78: =IF(AND(ISNUMBER(R78),R78>1,P78>0),R78/P78-1,"") -> -0.36756442 | T78: =IF(AND(ISNUMBER(P78),P78>0),P78*EXP('Read me'!$B$22),"") -> 15.450146

Sheet Market Rasen
A1: Time | B1: Course | C1: Race | D1: Class | E1: Furlongs | F1: Going | G1: Runners | H1: Horse | I1: Jockey | J1: Trainer | K1: Draw | L1: OR | M1: Age | N1: Days since run | O1: Model rank | P1: Predicted BSP | Q1: Win probability | R1: Card odds (HRB) | S1: Card odds vs model | T1: Rule: back at Betfair ≥
A2: 2:30 | B2: Market Rasen | C2: Market Rasen Racecourse Conference & Events Mares Maiden Hurdle (GBB Race) | D2: Class 4 | E2: 17.5 | F2: Good | G2: 9 | H2: Elated | I2: Jones, Ben R | J2: Pauling, Ben | K2: 1 | L2: 98 | M2: 5 | N2: 22 | O2: 1 | P2: 1.7522701 | Q2: 0.57068828 | R2: 2.2 | S2: =IF(AND(ISNUMBER(R2),R2>1,P2>0),R2/P2-1,"") -> 0.25551423 | T2: =IF(AND(ISNUMBER(P2),P2>0),P2*EXP('Read me'!$B$22),"") -> 2.1402275
A3: 2:30 | B3: Market Rasen | C3: Market Rasen Racecourse Conference & Events Mares Maiden Hurdle (GBB Race) | D3: Class 4 | E3: 17.5 | F3: Good | G3: 9 | H3: No More Teardrops | I3: Sheehan, Gavin | J3: Snowden, Jamie | K3: 6 | L3: 0 | M3: 4 | N3: 178 | O3: 2 | P3: 3.6316584 | Q3: 0.2753563 | R3: 2.5 | S3: =IF(AND(ISNUMBER(R3),R3>1,P3>0),R3/P3-1,"") -> -0.31160926 | T3: =IF(AND(ISNUMBER(P3),P3>0),P3*EXP('Read me'!$B$22),"") -> 4.4357175
A4: 2:30 | B4: Market Rasen | C4: Market Rasen Racecourse Conference & Events Mares Maiden Hurdle (GBB Race) | D4: Class 4 | E4: 17.5 | F4: Good | G4: 9 | H4: Poets Pearl (IRE) | I4: OBrien, P V | J4: Derham, Harry | K4: 7 | L4: 0 | M4: 4 | O4: 3 | P4: 9.6612298 | Q4: 0.10350649 | R4: 5 | S4: =IF(AND(ISNUMBER(R4),R4>1,P4>0),R4/P4-1,"") -> -0.48246754 | T4: =IF(AND(ISNUMBER(P4),P4>0),P4*EXP('Read me'!$B$22),"") -> 11.800253
A5: 2:30 | B5: Market Rasen | C5: Market Rasen Racecourse Conference & Events Mares Maiden Hurdle (GBB Race) | D5: Class 4 | E5: 17.5 | F5: Good | G5: 9 | H5: Adba (FR) | I5: Kimber, Harry | J5: Bramley, Faye | K5: 9 | L5: 0 | M5: 3 | N5: 38 | O5: 4 | P5: 55.943883 | Q5: 0.017875055 | R5: 41 | S5: =IF(AND(ISNUMBER(R5),R5>1,P5>0),R5/P5-1,"") -> -0.26712274 | T5: =IF(AND(ISNUMBER(P5),P5>0),P5*EXP('Read me'!$B$22),"") -> 68.330013
A6: 2:30 | B6: Market Rasen | C6: Market Rasen Racecourse Conference & Events Mares Maiden Hurdle (GBB Race) | D6: Class 4 | E6: 17.5 | F6: Good | G6: 9 | H6: Mighty Dink | I6: Skelton, Harry | J6: Skelton, Daniel | K6: 5 | L6: 0 | M6: 4 | N6: 12 | O6: 5 | P6: 63.32879 | Q6: 0.015790606 | R6: 34 | S6: =IF(AND(ISNUMBER(R6),R6>1,P6>0),R6/P6-1,"") -> -0.46311938 | T6: =IF(AND(ISNUMBER(P6),P6>0),P6*EXP('Read me'!$B$22),"") -> 77.349959
A7: 2:30 | B7: Market Rasen | C7: Market Rasen Racecourse Conference & Events Mares Maiden Hurdle (GBB Race) | D7: Class 4 | E7: 17.5 | F7: Good | G7: 9 | H7: Georgies Lady (IRE) | I7: Todd, C J | J7: Dennis, David | K7: 4 | L7: 0 | M7: 4 | N7: 22 | O7: 6 | P7: 128.79552 | Q7: 0.0077642455 | R7: 34 | S7: =IF(AND(ISNUMBER(R7),R7>1,P7>0),R7/P7-1,"") -> -0.73601565 | T7: =IF(AND(ISNUMBER(P7),P7>0),P7*EXP('Read me'!$B$22),"") -> 157.3112
A8: 2:30 | B8: Market Rasen | C8: Market Rasen Racecourse Conference & Events Mares Maiden Hurdle (GBB Race) | D8: Class 4 | E8: 17.5 | F8: Good | G8: 9 | H8: Chloes Courage | I8: Noonan, David G | J8: Ryan, J | K8: 3 | L8: 0 | M8: 4 | N8: 16 | O8: 7 | P8: 179.57599 | Q8: 0.0055686733 | R8: 34 | S8: =IF(AND(ISNUMBER(R8),R8>1,P8>0),R8/P8-1,"") -> -0.81066511 | T8: =IF(AND(ISNUMBER(P8),P8>0),P8*EXP('Read me'!$B$22),"") -> 219.3346
A9: 2:30 | B9: Market Rasen | C9: Market Rasen Racecourse Conference & Events Mares Maiden Hurdle (GBB Race) | D9: Class 4 | E9: 17.5 | F9: Good | G9: 9 | H9: Lara K (IRE) | I9: Ring, C V | J9: Williams, Mrs C | K9: 2 | L9: 0 | M9: 5 | N9: 8 | O9: 8 | P9: 476.59983 | Q9: 0.0020981963 | R9: 201 | S9: =IF(AND(ISNUMBER(R9),R9>1,P9>0),R9/P9-1,"") -> -0.57826254 | T9: =IF(AND(ISNUMBER(P9),P9>0),P9*EXP('Read me'!$B$22),"") -> 582.12034
A10: 2:30 | B10: Market Rasen | C10: Market Rasen Racecourse Conference & Events Mares Maiden Hurdle (GBB Race) | D10: Class 4 | E10: 17.5 | F10: Good | G10: 9 | H10: Sweet Cicely | I10: Maggs, Charlie | J10: Sowersby, M E | K10: 8 | L10: 0 | M10: 4 | N10: 12 | O10: 9 | P10: 739.56322 | Q10: 0.0013521494 | R10: 201 | S10: =IF(AND(ISNUMBER(R10),R10>1,P10>0),R10/P10-1,"") -> -0.72821796 | T10: =IF(AND(ISNUMBER(P10),P10>0),P10*EXP('Read me'!$B$22),"") -> 903.30456
A11: 3:05 | B11: Market Rasen | C11: Market Rasen Racecourse Caravan Site Juvenile Hurdle (GBB Race) | D11: Class 3 | E11: 17.5 | F11: Good | G11: 7 | H11: Moment Of Light | I11: Skelton, Harry | J11: Skelton, Daniel | K11: 1 | L11: 0 | M11: 3 | N11: 19 | O11: 1 | P11: 2.3418649 | Q11: 0.42701011 | R11: 1.9090909 | S11: =IF(AND(ISNUMBER(R11),R11>1,P11>0),R11/P11-1,"") -> -0.18479887 | T11: =IF(AND(ISNUMBER(P11),P11>0),P11*EXP('Read me'!$B$22),"") -> 2.8603603
A12: 3:05 | B12: Market Rasen | C12: Market Rasen Racecourse Caravan Site Juvenile Hurdle (GBB Race) | D12: Class 3 | E12: 17.5 | F12: Good | G12: 7 | H12: Pass The Buck (IRE) | I12: OBrien, P V | J12: Derham, Harry | K12: 5 | L12: 0 | M12: 3 | N12: 80 | O12: 2 | P12: 3.350969 | Q12: 0.29842115 | R12: 4 | S12: =IF(AND(ISNUMBER(R12),R12>1,P12>0),R12/P12-1,"") -> 0.19368458 | T12: =IF(AND(ISNUMBER(P12),P12>0),P12*EXP('Read me'!$B$22),"") -> 4.0928827
A13: 3:05 | B13: Market Rasen | C13: Market Rasen Racecourse Caravan Site Juvenile Hurdle (GBB Race) | D13: Class 3 | E13: 17.5 | F13: Good | G13: 7 | H13: Vietnorm (IRE) | I13: Brown, Oakley | J13: Keatley, Adrian Paul | K13: 2 | L13: 108 | M13: 3 | N13: 26 | O13: 3 | P13: 5.0598735 | Q13: 0.1976334 | R13: 5.5 | S13: =IF(AND(ISNUMBER(R13),R13>1,P13>0),R13/P13-1,"") -> 0.086983692 | T13: =IF(AND(ISNUMBER(P13),P13>0),P13*EXP('Read me'!$B$22),"") -> 6.1801435
A14: 3:05 | B14: Market Rasen | C14: Market Rasen Racecourse Caravan Site Juvenile Hurdle (GBB Race) | D14: Class 3 | E14: 17.5 | F14: Good | G14: 7 | H14: Blue To Blue (IRE) | I14: Hughes, Brian | J14: Jefferson, Ruth | K14: 3 | L14: 0 | M14: 3 | N14: 23 | O14: 4 | P14: 14.536445 | Q14: 0.068792612 | R14: 6.5 | S14: =IF(AND(ISNUMBER(R14),R14>1,P14>0),R14/P14-1,"") -> -0.55284802 | T14: =IF(AND(ISNUMBER(P14),P14>0),P14*EXP('Read me'!$B$22),"") -> 17.754854
A15: 3:05 | B15: Market Rasen | C15: Market Rasen Racecourse Caravan Site Juvenile Hurdle (GBB Race) | D15: Class 3 | E15: 17.5 | F15: Good | G15: 7 | H15: Two Steppin (IRE) | I15: Pritchard, Callum | J15: Murphy, Barry John | K15: 7 | L15: 0 | M15: 3 | O15: 5 | P15: 251.88031 | Q15: 0.0039701396 | R15: 126 | S15: =IF(AND(ISNUMBER(R15),R15>1,P15>0),R15/P15-1,"") -> -0.49976242 | T15: =IF(AND(ISNUMBER(P15),P15>0),P15*EXP('Read me'!$B$22),"") -> 307.64731
A16: 3:05 | B16: Market Rasen | C16: Market Rasen Racecourse Caravan Site Juvenile Hurdle (GBB Race) | D16: Class 3 | E16: 17.5 | F16: Good | G16: 7 | H16: Steel Fixer | I16: Moscrop, Nathan | J16: Ellison, B | K16: 6 | L16: 0 | M16: 3 | N16: 66 | O16: 6 | P16: 371.89215 | Q16: 0.0026889516 | R16: 81 | S16: =IF(AND(ISNUMBER(R16),R16>1,P16>0),R16/P16-1,"") -> -0.78219492 | T16: =IF(AND(ISNUMBER(P16),P16>0),P16*EXP('Read me'!$B$22),"") -> 454.2301
A17: 3:05 | B17: Market Rasen | C17: Market Rasen Racecourse Caravan Site Juvenile Hurdle (GBB Race) | D17: Class 3 | E17: 17.5 | F17: Good | G17: 7 | H17: Lynxman (IRE) | I17: Maggs, Charlie | J17: Sowersby, M E | K17: 4 | L17: 0 | M17: 3 | N17: 26 | O17: 7 | P17: 674.01876 | Q17: 0.0014836382 | R17: 126 | S17: =IF(AND(ISNUMBER(R17),R17>1,P17>0),R17/P17-1,"") -> -0.81306158 | T17: =IF(AND(ISNUMBER(P17),P17>0),P17*EXP('Read me'!$B$22),"") -> 823.24838
A18: 3:50 | B18: Market Rasen | C18: Summer Plate Ladies Day 2027 On Sale Handicap Chase (GBB Race) | D18: Class 3 | E18: 22.5 | F18: Good | G18: 4 | H18: Nickelforce (IRE) | I18: Bannister, Harry A A | J18: Case, B I | K18: 4 | L18: 118 | M18: 7 | N18: 70 | O18: 1 | P18: 3.0334405 | Q18: 0.32965869 | R18: 2.75 | S18: =IF(AND(ISNUMBER(R18),R18>1,P18>0),R18/P18-1,"") -> -0.093438609 | T18: =IF(AND(ISNUMBER(P18),P18>0),P18*EXP('Read me'!$B$22),"") -> 3.7050525
A19: 3:50 | B19: Market Rasen | C19: Summer Plate Ladies Day 2027 On Sale Handicap Chase (GBB Race) | D19: Class 3 | E19: 22.5 | F19: Good | G19: 4 | H19: Jet To Vegas (IRE) | I19: Hughes, Brian | J19: Russell, Lucinda / Scudamore, M | K19: 2 | L19: 131 | M19: 7 | N19: 148 | O19: 2 | P19: 3.5063595 | Q19: 0.28519609 | R19: 3.5 | S19: =IF(AND(ISNUMBER(R19),R19>1,P19>0),R19/P19-1,"") -> -0.0018136923 | T19: =IF(AND(ISNUMBER(P19),P19>0),P19*EXP('Read me'!$B$22),"") -> 4.2826771
A20: 3:50 | B20: Market Rasen | C20: Summer Plate Ladies Day 2027 On Sale Handicap Chase (GBB Race) | D20: Class 3 | E20: 22.5 | F20: Good | G20: 4 | H20: Sure Touch | I20: Saunders, Lewis | J20: Murphy, Olly | K20: 1 | L20: 132 | M20: 10 | N20: 22 | O20: 3 | P20: 5.0934388 | Q20: 0.19633101 | R20: 4.5 | S20: =IF(AND(ISNUMBER(R20),R20>1,P20>0),R20/P20-1,"") -> -0.11651044 | T20: =IF(AND(ISNUMBER(P20),P20>0),P20*EXP('Read me'!$B$22),"") -> 6.2211402
A21: 3:50 | B21: Market Rasen | C21: Summer Plate Ladies Day 2027 On Sale Handicap Chase (GBB Race) | D21: Class 3 | E21: 22.5 | F21: Good | G21: 4 | H21: Fringill Dike (IRE) | I21: Quinlan, Sean | J21: OKeeffe, Jedd | K21: 3 | L21: 127 | M21: 9 | N21: 83 | O21: 4 | P21: 5.2962115 | Q21: 0.18881421 | R21: 4.5 | S21: =IF(AND(ISNUMBER(R21),R21>1,P21>0),R21/P21-1,"") -> -0.15033605 | T21: =IF(AND(ISNUMBER(P21),P21>0),P21*EXP('Read me'!$B$22),"") -> 6.4688073
A22: 4:25 | B22: Market Rasen | C22: Dine In Altiors Restaurant Handicap Chase | D22: Class 5 | E22: 25 | F22: Good | G22: 8 | H22: Galway Reel (IRE) | I22: Bowen, Sean P | J22: Murphy, Olly | K22: 3 | L22: 95 | M22: 7 | N22: 83 | O22: 1 | P22: 2.9778043 | Q22: 0.3358179 | R22: 2.1 | S22: =IF(AND(ISNUMBER(R22),R22>1,P22>0),R22/P22-1,"") -> -0.29478241 | T22: =IF(AND(ISNUMBER(P22),P22>0),P22*EXP('Read me'!$B$22),"") -> 3.6370984
A23: 4:25 | B23: Market Rasen | C23: Dine In Altiors Restaurant Handicap Chase | D23: Class 5 | E23: 25 | F23: Good | G23: 8 | H23: Huckleberry Sting | I23: Andrews, Jack | J23: Ellis, T | K23: 1 | L23: 98 | M23: 7 | N23: 21 | O23: 2 | P23: 3.7133197 | Q23: 0.26930081 | R23: 4.5 | S23: =IF(AND(ISNUMBER(R23),R23>1,P23>0),R23/P23-1,"") -> 0.21185363 | T23: =IF(AND(ISNUMBER(P23),P23>0),P23*EXP('Read me'!$B$22),"") -> 4.535459
A24: 4:25 | B24: Market Rasen | C24: Dine In Altiors Restaurant Handicap Chase | D24: Class 5 | E24: 25 | F24: Good | G24: 8 | H24: Hardy Buck (IRE) | I24: Mitchell, Freddie | J24: Comley, Max | K24: 7 | L24: 76 | M24: 8 | N24: 35 | O24: 3 | P24: 7.1151649 | Q24: 0.14054488 | R24: 7.5 | S24: =IF(AND(ISNUMBER(R24),R24>1,P24>0),R24/P24-1,"") -> 0.054086609 | T24: =IF(AND(ISNUMBER(P24),P24>0),P24*EXP('Read me'!$B$22),"") -> 8.690482
A25: 4:25 | B25: Market Rasen | C25: Dine In Altiors Restaurant Handicap Chase | D25: Class 5 | E25: 25 | F25: Good | G25: 8 | H25: Ribeye | I25: Bewley, Callum | J25: Atkinson, P G | K25: 2 | L25: 97 | M25: 11 | N25: 42 | O25: 4 | P25: 9.6723589 | Q25: 0.1033874 | R25: 9.5 | S25: =IF(AND(ISNUMBER(R25),R25>1,P25>0),R25/P25-1,"") -> -0.017819736 | T25: =IF(AND(ISNUMBER(P25),P25>0),P25*EXP('Read me'!$B$22),"") -> 11.813846
A26: 4:25 | B26: Market Rasen | C26: Dine In Altiors Restaurant Handicap Chase | D26: Class 5 | E26: 25 | F26: Good | G26: 8 | H26: Fane Court (IRE) | I26: Stones, Lewis | J26: Jeffreys, D J | K26: 8 | L26: 75 | M26: 8 | N26: 18 | O26: 5 | P26: 11.420699 | Q26: 0.087560318 | R26: 7 | S26: =IF(AND(ISNUMBER(R26),R26>1,P26>0),R26/P26-1,"") -> -0.38707777 | T26: =IF(AND(ISNUMBER(P26),P26>0),P26*EXP('Read me'!$B$22),"") -> 13.949273
A27: 4:25 | B27: Market Rasen | C27: Dine In Altiors Restaurant Handicap Chase | D27: Class 5 | E27: 25 | F27: Good | G27: 8 | H27: Deadly Missile (IRE) | I27: Poste, Ben J | J27: Gasson, Mrs Rosemary | K27: 6 | L27: 76 | M27: 9 | N27: 428 | O27: 6 | P27: 25.210546 | Q27: 0.03966594 | R27: 26 | S27: =IF(AND(ISNUMBER(R27),R27>1,P27>0),R27/P27-1,"") -> 0.031314445 | T27: =IF(AND(ISNUMBER(P27),P27>0),P27*EXP('Read me'!$B$22),"") -> 30.79223
... A62: 6:00 | B62: Market Rasen | C62: Agriculture Raceday Returns On 12th November Handicap Hurdle | D62: Class 5 | E62: 24 | F62: Good | G62: 10 | H62: Destination Unkown (IRE) | I62: Stevenson, J W | J62: Chapman, M C | K62: 10 | L62: 72 | M62: 5 | N62: 28 | O62: 10 | P62: 392.20344 | Q62: 0.0025496972 | R62: 67 | S62: =IF(AND(ISNUMBER(R62),R62>1,P62>0),R62/P62-1,"") -> -0.82917029 | T62: =IF(AND(ISNUMBER(P62),P62>0),P62*EXP('Read me'!$B$22),"") -> 479.03836

Sheet Listowel
A1: Time | B1: Course | C1: Race | D1: Class | E1: Furlongs | F1: Going | G1: Runners | H1: Horse | I1: Jockey | J1: Trainer | K1: Draw | L1: OR | M1: Age | N1: Days since run | O1: Model rank | P1: Predicted BSP | Q1: Win probability | R1: Card odds (HRB) | S1: Card odds vs model | T1: Rule: back at Betfair ≥
A2: 2:45 | B2: Listowel | C2: John Lynch Memorial Maiden Hurdle | E2: 16 | F2: Good | G2: 12 | H2: Trubshaw | I2: OKeeffe, Darragh | J2: Bromhead, Henry De | K2: 10 | L2: 0 | M2: 4 | N2: 22 | O2: 1 | P2: 1.6389393 | Q2: 0.61015074 | R2: 1.7272727 | S2: =IF(AND(ISNUMBER(R2),R2>1,P2>0),R2/P2-1,"") -> 0.05389673 | T2: =IF(AND(ISNUMBER(P2),P2>0),P2*EXP('Read me'!$B$22),"") -> 2.0018049
A3: 2:45 | B3: Listowel | C3: John Lynch Memorial Maiden Hurdle | E3: 16 | F3: Good | G3: 12 | H3: Blue Johnl (IRE) | I3: Slevin, J J | J3: Ryan, John Patrick | K3: 1 | L3: 100 | M3: 4 | N3: 23 | O3: 2 | P3: 5.31062 | Q3: 0.18830193 | R3: 8.5 | S3: =IF(AND(ISNUMBER(R3),R3>1,P3>0),R3/P3-1,"") -> 0.60056642 | T3: =IF(AND(ISNUMBER(P3),P3>0),P3*EXP('Read me'!$B$22),"") -> 6.4864059
A4: 2:45 | B4: Listowel | C4: John Lynch Memorial Maiden Hurdle | E4: 16 | F4: Good | G4: 12 | H4: Local Resident (IRE) | I4: Gilligan, D J | J4: Collins, C M | K4: 7 | L4: 0 | M4: 4 | N4: 35 | O4: 3 | P4: 14.642791 | Q4: 0.068292992 | R4: 4.3333333 | S4: =IF(AND(ISNUMBER(R4),R4>1,P4>0),R4/P4-1,"") -> -0.7040637 | T4: =IF(AND(ISNUMBER(P4),P4>0),P4*EXP('Read me'!$B$22),"") -> 17.884745
A5: 2:45 | B5: Listowel | C5: John Lynch Memorial Maiden Hurdle | E5: 16 | F5: Good | G5: 12 | H5: Little An Often (IRE) | I5: OConnor, Thomas | J5: Fahey, Mark | K5: 6 | L5: 0 | M5: 4 | O5: 4 | P5: 24.133451 | Q5: 0.041436263 | R5: 26 | S5: =IF(AND(ISNUMBER(R5),R5>1,P5>0),R5/P5-1,"") -> 0.077342828 | T5: =IF(AND(ISNUMBER(P5),P5>0),P5*EXP('Read me'!$B$22),"") -> 29.476663
A6: 2:45 | B6: Listowel | C6: John Lynch Memorial Maiden Hurdle | E6: 16 | F6: Good | G6: 12 | H6: Parisian Dream (IRE) | I6: Markey, S R | J6: OSullivan, Ross | K6: 8 | L6: 0 | M6: 4 | O6: 5 | P6: 28.993091 | Q6: 0.034490976 | R6: 17 | S6: =IF(AND(ISNUMBER(R6),R6>1,P6>0),R6/P6-1,"") -> -0.41365341 | T6: =IF(AND(ISNUMBER(P6),P6>0),P6*EXP('Read me'!$B$22),"") -> 35.412241
A7: 2:45 | B7: Listowel | C7: John Lynch Memorial Maiden Hurdle | E7: 16 | F7: Good | G7: 12 | H7: Je Suis Celebre | I7: King, D | J7: McCarthy, Eoin Christopher | K7: 5 | L7: 0 | M7: 4 | N7: 35 | O7: 6 | P7: 40.025154 | Q7: 0.024984289 | R7: 6 | S7: =IF(AND(ISNUMBER(R7),R7>1,P7>0),R7/P7-1,"") -> -0.85009427 | T7: =IF(AND(ISNUMBER(P7),P7>0),P7*EXP('Read me'!$B$22),"") -> 48.886834
A8: 2:45 | B8: Listowel | C8: John Lynch Memorial Maiden Hurdle | E8: 16 | F8: Good | G8: 12 | H8: The Two Marys (IRE) | I8: Sexton, Harry | J8: Hanlon, John Joseph | K8: 14 | L8: 0 | M8: 4 | N8: 41 | O8: 7 | P8: 91.92594 | Q8: 0.010878322 | R8: 51 | S8: =IF(AND(ISNUMBER(R8),R8>1,P8>0),R8/P8-1,"") -> -0.44520556 | T8: =IF(AND(ISNUMBER(P8),P8>0),P8*EXP('Read me'!$B$22),"") -> 112.2786
A9: 2:45 | B9: Listowel | C9: John Lynch Memorial Maiden Hurdle | E9: 16 | F9: Good | G9: 12 | H9: Lennora (IRE) | I9: Meyler, D | J9: OLeary, Daniel Joseph | K9: 12 | L9: 0 | M9: 4 | O9: 8 | P9: 97.999325 | Q9: 0.010204152 | R9: 81 | S9: =IF(AND(ISNUMBER(R9),R9>1,P9>0),R9/P9-1,"") -> -0.1734637 | T9: =IF(AND(ISNUMBER(P9),P9>0),P9*EXP('Read me'!$B$22),"") -> 119.69665
A10: 2:45 | B10: Listowel | C10: John Lynch Memorial Maiden Hurdle | E10: 16 | F10: Good | G10: 12 | H10: Hidden Hurricane (IRE) | I10: Burke-Ott, Luke | J10: Ott, Alexander | K10: 4 | L10: 0 | M10: 4 | O10: 9 | P10: 316.56779 | Q10: 0.0031588811 | R10: 41 | S10: =IF(AND(ISNUMBER(R10),R10>1,P10>0),R10/P10-1,"") -> -0.87048588 | T10: =IF(AND(ISNUMBER(P10),P10>0),P10*EXP('Read me'!$B$22),"") -> 386.65677
A11: 2:45 | B11: Listowel | C11: John Lynch Memorial Maiden Hurdle | E11: 16 | F11: Good | G11: 12 | H11: Devine Genius (FR) | I11: Fitzgerald, Shane | J11: Morrison, J | K11: 3 | L11: 0 | M11: 4 | N11: 44 | O11: 10 | P11: 339.1552 | Q11: 0.0029485026 | R11: 101 | S11: =IF(AND(ISNUMBER(R11),R11>1,P11>0),R11/P11-1,"") -> -0.70220124 | T11: =IF(AND(ISNUMBER(P11),P11>0),P11*EXP('Read me'!$B$22),"") -> 414.2451
A12: 2:45 | B12: Listowel | C12: John Lynch Memorial Maiden Hurdle | E12: 16 | F12: Good | G12: 12 | H12: You Lift Me Up (IRE) | I12: OCallaghan, Shane | J12: Rothwell, P J | K12: 11 | L12: 0 | M12: 4 | N12: 19 | O12: 11 | P12: 359.11711 | Q12: 0.002784607 | R12: 101 | S12: =IF(AND(ISNUMBER(R12),R12>1,P12>0),R12/P12-1,"") -> -0.71875469 | T12: =IF(AND(ISNUMBER(P12),P12>0),P12*EXP('Read me'!$B$22),"") -> 438.62662
A13: 2:45 | B13: Listowel | C13: John Lynch Memorial Maiden Hurdle | E13: 16 | F13: Good | G13: 12 | H13: Out West (IRE) | I13: Healy, Kevin | J13: Obrien, Daniel | K13: 13 | L13: 0 | M13: 4 | N13: 29 | O13: 12 | P13: 422.23562 | Q13: 0.0023683459 | R13: 101 | S13: =IF(AND(ISNUMBER(R13),R13>1,P13>0),R13/P13-1,"") -> -0.76079706 | T13: =IF(AND(ISNUMBER(P13),P13>0),P13*EXP('Read me'!$B$22),"") -> 515.71975
A14: 3:21 | B14: Listowel | C14: Allman Contracts Novice Hurdle | E14: 20 | F14: Good | G14: 6 | H14: Roc Dino (FR) | I14: Townend, P | J14: Mullins, W P | K14: 3 | L14: 125 | M14: 5 | N14: 58 | O14: 1 | P14: 1.725236 | Q14: 0.57963084 | R14: 1.7272727 | S14: =IF(AND(ISNUMBER(R14),R14>1,P14>0),R14/P14-1,"") -> 0.0011805337 | T14: =IF(AND(ISNUMBER(P14),P14>0),P14*EXP('Read me'!$B$22),"") -> 2.107208
A15: 3:21 | B15: Listowel | C15: Allman Contracts Novice Hurdle | E15: 20 | F15: Good | G15: 6 | H15: Dad Sez (IRE) | I15: Kennedy, J W | J15: Elliott, Gordon | K15: 2 | L15: 0 | M15: 6 | N15: 36 | O15: 2 | P15: 4.4066327 | Q15: 0.22693065 | R15: 4.5 | S15: =IF(AND(ISNUMBER(R15),R15>1,P15>0),R15/P15-1,"") -> 0.021187911 | T15: =IF(AND(ISNUMBER(P15),P15>0),P15*EXP('Read me'!$B$22),"") -> 5.3822733
A16: 3:21 | B16: Listowel | C16: Allman Contracts Novice Hurdle | E16: 20 | F16: Good | G16: 6 | H16: Rosies Wings (IRE) | I16: Gilligan, D J | J16: OSullivan, Ross | K16: 4 | L16: 120 | M16: 6 | N16: 36 | O16: 3 | P16: 9.4422604 | Q16: 0.10590684 | R16: 6 | S16: =IF(AND(ISNUMBER(R16),R16>1,P16>0),R16/P16-1,"") -> -0.36455894 | T16: =IF(AND(ISNUMBER(P16),P16>0),P16*EXP('Read me'!$B$22),"") -> 11.532803
A17: 3:21 | B17: Listowel | C17: Allman Contracts Novice Hurdle | E17: 20 | F17: Good | G17: 6 | H17: Clay Pigeons (IRE) | I17: Hayes, Brian | J17: Mullins, W P | K17: 1 | L17: 122 | M17: 6 | N17: 29 | O17: 4 | P17: 18.556576 | Q17: 0.053889252 | R17: 12 | S17: =IF(AND(ISNUMBER(R17),R17>1,P17>0),R17/P17-1,"") -> -0.35332897 | T17: =IF(AND(ISNUMBER(P17),P17>0),P17*EXP('Read me'!$B$22),"") -> 22.665053
A18: 3:21 | B18: Listowel | C18: Allman Contracts Novice Hurdle | E18: 20 | F18: Good | G18: 6 | H18: Goeasyonme (FR) | I18: King, D | J18: Ryan, John Patrick | K18: 5 | L18: 0 | M18: 5 | N18: 23 | O18: 5 | P18: 32.344609 | Q18: 0.030917053 | R18: 13 | S18: =IF(AND(ISNUMBER(R18),R18>1,P18>0),R18/P18-1,"") -> -0.59807831 | T18: =IF(AND(ISNUMBER(P18),P18>0),P18*EXP('Read me'!$B$22),"") -> 39.505795
A19: 3:21 | B19: Listowel | C19: Allman Contracts Novice Hurdle | E19: 20 | F19: Good | G19: 6 | H19: I Can Find Em (IRE) | I19: McGill, Mr O | J19: McGill, Gary | K19: 6 | L19: 0 | M19: 5 | N19: 7 | O19: 6 | P19: 366.92281 | Q19: 0.0027253689 | R19: 201 | S19: =IF(AND(ISNUMBER(R19),R19>1,P19>0),R19/P19-1,"") -> -0.45220086 | T19: =IF(AND(ISNUMBER(P19),P19>0),P19*EXP('Read me'!$B$22),"") -> 448.16053
A20: 3:55 | B20: Listowel | C20: M.J. Carroll ARRO Handicap Hurdle | E20: 20 | F20: Good | G20: 14 | H20: Livio (FR) | I20: Townend, P | J20: Mullins, W P | K20: 8 | L20: 122 | M20: 5 | N20: 54 | O20: 1 | P20: 3.4155192 | Q20: 0.29278126 | R20: 2.75 | S20: =IF(AND(ISNUMBER(R20),R20>1,P20>0),R20/P20-1,"") -> -0.19485155 | T20: =IF(AND(ISNUMBER(P20),P20>0),P20*EXP('Read me'!$B$22),"") -> 4.1717246
A21: 3:55 | B21: Listowel | C21: M.J. Carroll ARRO Handicap Hurdle | E21: 20 | F21: Good | G21: 14 | H21: Avalo (IRE) | I21: Ewing, Sam | J21: Fahey, Peter | K21: 9 | L21: 121 | M21: 7 | N21: 31 | O21: 2 | P21: 9.0344624 | Q21: 0.11068727 | R21: 12 | S21: =IF(AND(ISNUMBER(R21),R21>1,P21>0),R21/P21-1,"") -> 0.32824727 | T21: =IF(AND(ISNUMBER(P21),P21>0),P21*EXP('Read me'!$B$22),"") -> 11.034717
A22: 3:55 | B22: Listowel | C22: M.J. Carroll ARRO Handicap Hurdle | E22: 20 | F22: Good | G22: 14 | H22: Ifiwerearichman (IRE) | I22: OSullivan, Alan | J22: Nolan, Paul | K22: 6 | L22: 125 | M22: 8 | N22: 56 | O22: 3 | P22: 10.158106 | Q22: 0.098443549 | R22: 7.5 | S22: =IF(AND(ISNUMBER(R22),R22>1,P22>0),R22/P22-1,"") -> -0.26167338 | T22: =IF(AND(ISNUMBER(P22),P22>0),P22*EXP('Read me'!$B$22),"") -> 12.407139
... A82: 6:05 | B82: Listowel | C82: Listowel Printing Works Slan Abhaile (Pro/Am) Flat Race | E82: 16 | F82: Good | G82: 6 | H82: Distraction (IRE) | I82: Gleeson, Mr J L | J82: Kiely, David A | K82: 4 | L82: 0 | M82: 5 | N82: 65 | O82: 3 | P82: 7.2112177 | Q82: 0.13867284 | R82: 15 | S82: =IF(AND(ISNUMBER(R82),R82>1,P82>0),R82/P82-1,"") -> 1.0800925 | T82: =IF(AND(ISNUMBER(P82),P82>0),P82*EXP('Read me'!$B$22),"") -> 8.8078012
A83: 6:05 | B83: Listowel | C83: Listowel Printing Works Slan Abhaile (Pro/Am) Flat Race | E83: 16 | F83: Good | G83: 6 | H83: Imboundtosay (IRE) | I83: Swan, H C | J83: Roper, W M | K83: 5 | L83: 0 | M83: 6 | O83: 4 | P83: 52.844876 | Q83: 0.018923311 | R83: 26 | S83: =IF(AND(ISNUMBER(R83),R83>1,P83>0),R83/P83-1,"") -> -0.50799392 | T83: =IF(AND(ISNUMBER(P83),P83>0),P83*EXP('Read me'!$B$22),"") -> 64.544877
A84: 6:05 | B84: Listowel | C84: Listowel Printing Works Slan Abhaile (Pro/Am) Flat Race | E84: 16 | F84: Good | G84: 6 | H84: Pats Charm (IRE) | I84: Chute, Mr J G | J84: OConnor, Thomas P | K84: 6 | L84: 0 | M84: 4 | O84: 5 | P84: 177.45182 | Q84: 0.0056353323 | R84: 41 | S84: =IF(AND(ISNUMBER(R84),R84>1,P84>0),R84/P84-1,"") -> -0.76895138 | T84: =IF(AND(ISNUMBER(P84),P84>0),P84*EXP('Read me'!$B$22),"") -> 216.74015
A85: 6:05 | B85: Listowel | C85: Listowel Printing Works Slan Abhaile (Pro/Am) Flat Race | E85: 16 | F85: Good | G85: 6 | H85: Without Deception (IRE) | I85: Leahy, Miss Sarah | J85: Odoherty, William Joseph | K85: 7 | L85: 0 | M85: 4 | N85: 72 | O85: 6 | P85: 211.304 | Q85: 0.004732518 | R85: 41 | S85: =IF(AND(ISNUMBER(R85),R85>1,P85>0),R85/P85-1,"") -> -0.80596676 | T85: =IF(AND(ISNUMBER(P85),P85>0),P85*EXP('Read me'!$B$22),"") -> 258.08729

Sheet Southwell
A1: Time | B1: Course | C1: Race | D1: Class | E1: Furlongs | F1: Going | G1: Runners | H1: Horse | I1: Jockey | J1: Trainer | K1: Draw | L1: OR | M1: Age | N1: Days since run | O1: Model rank | P1: Predicted BSP | Q1: Win probability | R1: Card odds (HRB) | S1: Card odds vs model | T1: Rule: back at Betfair ≥
A2: 4:10 | B2: Southwell | C2: Gents Night Sat 24th October Handicap | D2: Class 6 | E2: 5 | F2: Standard | G2: 9 | H2: Mimime (IRE) | I2: Vigors, Harry | J2: Appleby, M | K2: 5 | L2: 46 | M2: 3 | N2: 9 | O2: 1 | P2: 5.0517322 | Q2: 0.1979519 | R2: 4 | S2: =IF(AND(ISNUMBER(R2),R2>1,P2>0),R2/P2-1,"") -> -0.20819239 | T2: =IF(AND(ISNUMBER(P2),P2>0),P2*EXP('Read me'!$B$22),"") -> 6.1701996
A3: 4:10 | B3: Southwell | C3: Gents Night Sat 24th October Handicap | D3: Class 6 | E3: 5 | F3: Standard | G3: 9 | H3: Lets Go Hugo (IRE) | I3: Marshall, Tom Kiely | J3: Pears, Ollie | K3: 8 | L3: 62 | M3: 6 | N3: 16 | O3: 2 | P3: 5.4991354 | Q3: 0.18184677 | R3: 5.5 | S3: =IF(AND(ISNUMBER(R3),R3>1,P3>0),R3/P3-1,"") -> 0.00015721879 | T3: =IF(AND(ISNUMBER(P3),P3>0),P3*EXP('Read me'!$B$22),"") -> 6.7166592
A4: 4:10 | B4: Southwell | C4: Gents Night Sat 24th October Handicap | D4: Class 6 | E4: 5 | F4: Standard | G4: 9 | H4: Protest Rally (IRE) | I4: Garritty, Billy | J4: Bailey, Liam | K4: 7 | L4: 65 | M4: 6 | N4: 18 | O4: 3 | P4: 6.2256625 | Q4: 0.16062547 | R4: 8 | S4: =IF(AND(ISNUMBER(R4),R4>1,P4>0),R4/P4-1,"") -> 0.2850038 | T4: =IF(AND(ISNUMBER(P4),P4>0),P4*EXP('Read me'!$B$22),"") -> 7.6040414
A5: 4:10 | B5: Southwell | C5: Gents Night Sat 24th October Handicap | D5: Class 6 | E5: 5 | F5: Standard | G5: 9 | H5: Tomarlo | I5: Keenan, Darragh | J5: Candlish, Jennie | K5: 1 | L5: 55 | M5: 4 | N5: 18 | O5: 4 | P5: 6.5879457 | Q5: 0.15179239 | R5: 6.5 | S5: =IF(AND(ISNUMBER(R5),R5>1,P5>0),R5/P5-1,"") -> -0.013349494 | T5: =IF(AND(ISNUMBER(P5),P5>0),P5*EXP('Read me'!$B$22),"") -> 8.0465351
A6: 4:10 | B6: Southwell | C6: Gents Night Sat 24th October Handicap | D6: Class 6 | E6: 5 | F6: Standard | G6: 9 | H6: Sams Xpress (IRE) | I6: Hogan, D E | J6: Birkett, Julia/Shelley | K6: 9 | L6: 60 | M6: 6 | N6: 27 | O6: 5 | P6: 9.2076287 | Q6: 0.1086056 | R6: 5.5 | S6: =IF(AND(ISNUMBER(R6),R6>1,P6>0),R6/P6-1,"") -> -0.40266922 | T6: =IF(AND(ISNUMBER(P6),P6>0),P6*EXP('Read me'!$B$22),"") -> 11.246223
A7: 4:10 | B7: Southwell | C7: Gents Night Sat 24th October Handicap | D7: Class 6 | E7: 5 | F7: Standard | G7: 9 | H7: Torfrida | I7: ONeill, K T | J7: Sly, Mrs P | K7: 3 | L7: 55 | M7: 6 | N7: 41 | O7: 6 | P7: 10.655218 | Q7: 0.093850735 | R7: 6 | S7: =IF(AND(ISNUMBER(R7),R7>1,P7>0),R7/P7-1,"") -> -0.43689559 | T7: =IF(AND(ISNUMBER(P7),P7>0),P7*EXP('Read me'!$B$22),"") -> 13.014312
A8: 4:10 | B8: Southwell | C8: Gents Night Sat 24th October Handicap | D8: Class 6 | E8: 5 | F8: Standard | G8: 9 | H8: Popular Dream | I8: Jary, Alex | J8: Shaw, D | K8: 6 | L8: 57 | M8: 6 | N8: 128 | O8: 7 | P8: 16.753804 | Q8: 0.059687936 | R8: 15 | S8: =IF(AND(ISNUMBER(R8),R8>1,P8>0),R8/P8-1,"") -> -0.10468097 | T8: =IF(AND(ISNUMBER(P8),P8>0),P8*EXP('Read me'!$B$22),"") -> 20.463143
A9: 4:10 | B9: Southwell | C9: Gents Night Sat 24th October Handicap | D9: Class 6 | E9: 5 | F9: Standard | G9: 9 | H9: Hellcat | I9: Carver, William | J9: Burdon, R | K9: 2 | L9: 52 | M9: 3 | N9: 33 | O9: 8 | P9: 41.396424 | Q9: 0.024156676 | R9: 41 | S9: =IF(AND(ISNUMBER(R9),R9>1,P9>0),R9/P9-1,"") -> -0.0095762813 | T9: =IF(AND(ISNUMBER(P9),P9>0),P9*EXP('Read me'!$B$22),"") -> 50.561706
A10: 4:10 | B10: Southwell | C10: Gents Night Sat 24th October Handicap | D10: Class 6 | E10: 5 | F10: Standard | G10: 9 | H10: Crypto Quest (IRE) | I10: Howarth, Christian | J10: Dixon, Scott | K10: 4 | L10: 55 | M10: 7 | N10: 25 | O10: 9 | P10: 46.54946 | Q10: 0.021482526 | R10: 34 | S10: =IF(AND(ISNUMBER(R10),R10>1,P10>0),R10/P10-1,"") -> -0.2695941 | T10: =IF(AND(ISNUMBER(P10),P10>0),P10*EXP('Read me'!$B$22),"") -> 56.855638
A11: 4:45 | B11: Southwell | C11: Dance Through The Decades Christmas Parties EBF Restricted Maiden Fillies Stakes (GBB Race) | D11: Class 5 | E11: 5 | F11: Standard | G11: 10 | H11: Romotoso | I11: Vigors, Harry | J11: Knight, W J | K11: 6 | L11: 70 | M11: 2 | N11: 19 | O11: 1 | P11: 2.3142154 | Q11: 0.43211189 | R11: 2.875 | S11: =IF(AND(ISNUMBER(R11),R11>1,P11>0),R11/P11-1,"") -> 0.24232168 | T11: =IF(AND(ISNUMBER(P11),P11>0),P11*EXP('Read me'!$B$22),"") -> 2.8265891
A12: 4:45 | B12: Southwell | C12: Dance Through The Decades Christmas Parties EBF Restricted Maiden Fillies Stakes (GBB Race) | D12: Class 5 | E12: 5 | F12: Standard | G12: 10 | H12: Inglewood | I12: Marshall, Tom Kiely | J12: Camacho, Miss J A | K12: 3 | L12: 68 | M12: 2 | N12: 37 | O12: 2 | P12: 5.8202585 | Q12: 0.17181368 | R12: 4.5 | S12: =IF(AND(ISNUMBER(R12),R12>1,P12>0),R12/P12-1,"") -> -0.22683846 | T12: =IF(AND(ISNUMBER(P12),P12>0),P12*EXP('Read me'!$B$22),"") -> 7.1088797
A13: 4:45 | B13: Southwell | C13: Dance Through The Decades Christmas Parties EBF Restricted Maiden Fillies Stakes (GBB Race) | D13: Class 5 | E13: 5 | F13: Standard | G13: 10 | H13: Plastic Dream | I13: Muscutt, D | J13: Dwyer, C A | K13: 7 | L13: 69 | M13: 2 | N13: 10 | O13: 3 | P13: 7.5572084 | Q13: 0.13232399 | R13: 6.5 | S13: =IF(AND(ISNUMBER(R13),R13>1,P13>0),R13/P13-1,"") -> -0.13989404 | T13: =IF(AND(ISNUMBER(P13),P13>0),P13*EXP('Read me'!$B$22),"") -> 9.2303952
... A15: 4:45 | B15: Southwell | C15: Dance Through The Decades Christmas Parties EBF Restricted Maiden Fillies Stakes (GBB Race) | D15: Class 5 | E15: 5 | F15: Standard | G15: 10 | H15: Mollisha (IRE) | I15: Garritty, Billy | J15: Ellison, B | K15: 4 | L15: 70 | M15: 2 | N15: 7 | O15: 5 | P15: 13.245986 | Q15: 0.075494571 | R15: 8.5 | S15: =IF(AND(ISNUMBER(R15),R15>1,P15>0),R15/P15-1,"") -> -0.35829615 | T15: =IF(AND(ISNUMBER(P15),P15>0),P15*EXP('Read me'!$B$22),"") -> 16.178683
A16: 4:45 | B16: Southwell | C16: Dance Through The Decades Christmas Parties EBF Restricted Maiden Fillies Stakes (GBB Race) | D16: Class 5 | E16: 5 | F16: Standard | G16: 10 | H16: Nushga (IRE) | I16: Fentiman, Warren | J16: Fahey, R A | K16: 1 | L16: 0 | M16: 2 | O16: 6 | P16: 26.146962 | Q16: 0.038245361 | R16: 13 | S16: =IF(AND(ISNUMBER(R16),R16>1,P16>0),R16/P16-1,"") -> -0.5028103 | T16: =IF(AND(ISNUMBER(P16),P16>0),P16*EXP('Read me'!$B$22),"") -> 31.935971
A17: 4:45 | B17: Southwell | C17: Dance Through The Decades Christmas Parties EBF Restricted Maiden Fillies Stakes (GBB Race) | D17: Class 5 | E17: 5 | F17: Standard | G17: 10 | H17: So Sexy Me | I17: Bishop, Charles | J17: Kirby, Adam | K17: 5 | L17: 0 | M17: 2 | N17: 5 | O17: 7 | P17: 31.264911 | Q17: 0.031984738 | R17: 17 | S17: =IF(AND(ISNUMBER(R17),R17>1,P17>0),R17/P17-1,"") -> -0.45625945 | T17: =IF(AND(ISNUMBER(P17),P17>0),P17*EXP('Read me'!$B$22),"") -> 38.187049
A18: 4:45 | B18: Southwell | C18: Dance Through The Decades Christmas Parties EBF Restricted Maiden Fillies Stakes (GBB Race) | D18: Class 5 | E18: 5 | F18: Standard | G18: 10 | H18: Ghazalia (IRE) | I18: Langley, Taryn | J18: Kobeissi, Hilal | K18: 9 | L18: 0 | M18: 2 | N18: 11 | O18: 8 | P18: 60.861731 | Q18: 0.016430686 | R18: 26 | S18: =IF(AND(ISNUMBER(R18),R18>1,P18>0),R18/P18-1,"") -> -0.57280216 | T18: =IF(AND(ISNUMBER(P18),P18>0),P18*EXP('Read me'!$B$22),"") -> 74.336686
A19: 4:45 | B19: Southwell | C19: Dance Through The Decades Christmas Parties EBF Restricted Maiden Fillies Stakes (GBB Race) | D19: Class 5 | E19: 5 | F19: Standard | G19: 10 | H19: Picnic Princess | I19: McHugh, B | J19: Fahey, R A | K19: 10 | L19: 0 | M19: 2 | N19: 11 | O19: 9 | P19: 404.06342 | Q19: 0.002474859 | R19: 67 | S19: =IF(AND(ISNUMBER(R19),R19>1,P19>0),R19/P19-1,"") -> -0.83418444 | T19: =IF(AND(ISNUMBER(P19),P19>0),P19*EXP('Read me'!$B$22),"") -> 493.52417
A20: 4:45 | B20: Southwell | C20: Dance Through The Decades Christmas Parties EBF Restricted Maiden Fillies Stakes (GBB Race) | D20: Class 5 | E20: 5 | F20: Standard | G20: 10 | H20: Love Always | I20: Swallow, Libby | J20: Sangster, Ollie | K20: 2 | L20: 0 | M20: 2 | N20: 24 | O20: 10 | P20: 934.93539 | Q20: 0.0010695926 | R20: 101 | S20: =IF(AND(ISNUMBER(R20),R20>1,P20>0),R20/P20-1,"") -> -0.89197114 | T20: =IF(AND(ISNUMBER(P20),P20>0),P20*EXP('Read me'!$B$22),"") -> 1141.9327
A21: 5:20 | B21: Southwell | C21: Celebrate With Sponsorship At Southwell Racecourse Handicap (Div 1) | D21: Class 4 | E21: 5 | F21: Standard | G21: 10 | H21: Elyam | I21: Keenan, Darragh | J21: Herrington,M | K21: 10 | L21: 84 | M21: 4 | N21: 23 | O21: 1 | P21: 3.5231028 | Q21: 0.28384071 | R21: 2.625 | S21: =IF(AND(ISNUMBER(R21),R21>1,P21>0),R21/P21-1,"") -> -0.25491814 | T21: =IF(AND(ISNUMBER(P21),P21>0),P21*EXP('Read me'!$B$22),"") -> 4.3031275
A22: 5:20 | B22: Southwell | C22: Celebrate With Sponsorship At Southwell Racecourse Handicap (Div 1) | D22: Class 4 | E22: 5 | F22: Standard | G22: 10 | H22: Ziggys Triton (IRE) | I22: Muscutt, D | J22: OMeara, D | K22: 9 | L22: 86 | M22: 4 | N22: 38 | O22: 2 | P22: 4.7053049 | Q22: 0.21252608 | R22: 5.5 | S22: =IF(AND(ISNUMBER(R22),R22>1,P22>0),R22/P22-1,"") -> 0.16889343 | T22: =IF(AND(ISNUMBER(P22),P22>0),P22*EXP('Read me'!$B$22),"") -> 5.7470724
A23: 5:20 | B23: Southwell | C23: Celebrate With Sponsorship At Southwell Racecourse Handicap (Div 1) | D23: Class 4 | E23: 5 | F23: Standard | G23: 10 | H23: Paddys Day (IRE) | I23: Jary, Alex | J23: Tinkler, N | K23: 4 | L23: 82 | M23: 6 | N23: 13 | O23: 3 | P23: 6.8433375 | Q23: 0.14612753 | R23: 5.5 | S23: =IF(AND(ISNUMBER(R23),R23>1,P23>0),R23/P23-1,"") -> -0.19629859 | T23: =IF(AND(ISNUMBER(P23),P23>0),P23*EXP('Read me'!$B$22),"") -> 8.3584713
A24: 5:20 | B24: Southwell | C24: Celebrate With Sponsorship At Southwell Racecourse Handicap (Div 1) | D24: Class 4 | E24: 5 | F24: Standard | G24: 10 | H24: Spring Is Sprung (FR) | I24: ONeill, K T | J24: Midgley, P T | K24: 1 | L24: 84 | M24: 7 | N24: 49 | O24: 4 | P24: 8.931255 | Q24: 0.11196635 | R24: 7.5 | S24: =IF(AND(ISNUMBER(R24),R24>1,P24>0),R24/P24-1,"") -> -0.16025239 | T24: =IF(AND(ISNUMBER(P24),P24>0),P24*EXP('Read me'!$B$22),"") -> 10.908659
A25: 5:20 | B25: Southwell | C25: Celebrate With Sponsorship At Southwell Racecourse Handicap (Div 1) | D25: Class 4 | E25: 5 | F25: Standard | G25: 10 | H25: Juan Les Pins | I25: Paetel, Mason | J25: Appleby, M | K25: 2 | L25: 76 | M25: 9 | N25: 35 | O25: 5 | P25: 13.744365 | Q25: 0.072757088 | R25: 10 | S25: =IF(AND(ISNUMBER(R25),R25>1,P25>0),R25/P25-1,"") -> -0.27242912 | T25: =IF(AND(ISNUMBER(P25),P25>0),P25*EXP('Read me'!$B$22),"") -> 16.787406
A26: 5:20 | B26: Southwell | C26: Celebrate With Sponsorship At Southwell Racecourse Handicap (Div 1) | D26: Class 4 | E26: 5 | F26: Standard | G26: 10 | H26: Bassenthwaite | I26: Dobie, Georgia | J26: Cox, C G | K26: 8 | L26: 86 | M26: 3 | N26: 63 | O26: 6 | P26: 17.496929 | Q26: 0.057152887 | R26: 10 | S26: =IF(AND(ISNUMBER(R26),R26>1,P26>0),R26/P26-1,"") -> -0.42847113 | T26: =IF(AND(ISNUMBER(P26),P26>0),P26*EXP('Read me'!$B$22),"") -> 21.370797
A27: 5:20 | B27: Southwell | C27: Celebrate With Sponsorship At Southwell Racecourse Handicap (Div 1) | D27: Class 4 | E27: 5 | F27: Standard | G27: 10 | H27: Noble Vow (IRE) | I27: Voikhansky, Alexander | J27: Hannon (Jnr), Richard | K27: 7 | L27: 80 | M27: 3 | N27: 7 | O27: 7 | P27: 20.899199 | Q27: 0.047848723 | R27: 29 | S27: =IF(AND(ISNUMBER(R27),R27>1,P27>0),R27/P27-1,"") -> 0.38761297 | T27: =IF(AND(ISNUMBER(P27),P27>0),P27*EXP('Read me'!$B$22),"") -> 25.52634
A28: 5:20 | B28: Southwell | C28: Celebrate With Sponsorship At Southwell Racecourse Handicap (Div 1) | D28: Class 4 | E28: 5 | F28: Standard | G28: 10 | H28: Layla Liz (IRE) | I28: Cox, William | J28: Watson, Archie | K28: 3 | L28: 87 | M28: 4 | N28: 14 | O28: 8 | P28: 30.989511 | Q28: 0.032268983 | R28: 34 | S28: =IF(AND(ISNUMBER(R28),R28>1,P28>0),R28/P28-1,"") -> 0.097145425 | T28: =IF(AND(ISNUMBER(P28),P28>0),P28*EXP('Read me'!$B$22),"") -> 37.850674
... A51: 7:00 | B51: Southwell | C51: 3rd And 10th Oktoberfest Race Nights Maiden Stakes (GBB/GBBPlus Race) | D51: Class 3 | E51: 11 | F51: Standard | G51: 13 | H51: Church Wedding (IRE) | I51: Clutterbuck, Rhys | J51: Beckett, R M | K51: 12 | L51: 0 | M51: 3 | N51: 52 | O51: 4 | P51: 13.231782 | Q51: 0.07557561 | R51: 9 | S51: =IF(AND(ISNUMBER(R51),R51>1,P51>0),R51/P51-1,"") -> -0.31981951 | T51: =IF(AND(ISNUMBER(P51),P51>0),P51*EXP('Read me'!$B$22),"") -> 16.161335
A52: 7:00 | B52: Southwell | C52: 3rd And 10th Oktoberfest Race Nights Maiden Stakes (GBB/GBBPlus Race) | D52: Class 3 | E52: 11 | F52: Standard | G52: 13 | H52: Pepperazzi (FR) | I52: Callan, Jack | J52: Cole, Oliver | K52: 1 | L52: 0 | M52: 3 | O52: 5 | P52: 68.260408 | Q52: 0.014649781 | R52: 15 | S52: =IF(AND(ISNUMBER(R52),R52>1,P52>0),R52/P52-1,"") -> -0.78025329 | T52: =IF(AND(ISNUMBER(P52),P52>0),P52*EXP('Read me'!$B$22),"") -> 83.37345
A53: 7:00 | B53: Southwell | C53: 3rd And 10th Oktoberfest Race Nights Maiden Stakes (GBB/GBBPlus Race) | D53: Class 3 | E53: 11 | F53: Standard | G53: 13 | H53: Roxy Power (USA) | I53: Paetel, Mason | J53: Crisford, Simon | K53: 3 | L53: 0 | M53: 3 | N53: 24 | O53: 6 | P53: 167.91327 | Q53: 0.0059554556 | R53: 41 | S53: =IF(AND(ISNUMBER(R53),R53>1,P53>0),R53/P53-1,"") -> -0.75582632 | T53: =IF(AND(ISNUMBER(P53),P53>0),P53*EXP('Read me'!$B$22),"") -> 205.08973
A54: 7:00 | B54: Southwell | C54: 3rd And 10th Oktoberfest Race Nights Maiden Stakes (GBB/GBBPlus Race) | D54: Class 3 | E54: 11 | F54: Standard | G54: 13 | H54: Chilli King | I54: Bishop, Charles | J54: Lavelle, Miss E C | K54: 14 | L54: 0 | M54: 3 | N54: 149 | O54: 7 | P54: 173.53425 | Q54: 0.0057625513 | R54: 51 | S54: =IF(AND(ISNUMBER(R54),R54>1,P54>0),R54/P54-1,"") -> -0.70610988 | T54: =IF(AND(ISNUMBER(P54),P54>0),P54*EXP('Read me'!$B$22),"") -> 211.95521
A55: 7:00 | B55: Southwell | C55: 3rd And 10th Oktoberfest Race Nights Maiden Stakes (GBB/GBBPlus Race) | D55: Class 3 | E55: 11 | F55: Standard | G55: 13 | H55: Crystal Jet (FR) | I55: Garritty, Jack | J55: Bulgin, T S M | K55: 13 | L55: 0 | M55: 4 | N55: 23 | O55: 8 | P55: 180.42009 | Q55: 0.00554262 | R55: 151 | S55: =IF(AND(ISNUMBER(R55),R55>1,P55>0),R55/P55-1,"") -> -0.16306438 | T55: =IF(AND(ISNUMBER(P55),P55>0),P55*EXP('Read me'!$B$22),"") -> 220.3656
A56: 7:00 | B56: Southwell | C56: 3rd And 10th Oktoberfest Race Nights Maiden Stakes (GBB/GBBPlus Race) | D56: Class 3 | E56: 11 | F56: Standard | G56: 13 | H56: Train In Vain | I56: Keenan, Darragh | J56: Macey, Jessica | K56: 7 | L56: 0 | M56: 3 | N56: 17 | O56: 9 | P56: 238.43959 | Q56: 0.0041939344 | R56: 51 | S56: =IF(AND(ISNUMBER(R56),R56>1,P56>0),R56/P56-1,"") -> -0.78610934 | T56: =IF(AND(ISNUMBER(P56),P56>0),P56*EXP('Read me'!$B$22),"") -> 291.23077
A57: 7:00 | B57: Southwell | C57: 3rd And 10th Oktoberfest Race Nights Maiden Stakes (GBB/GBBPlus Race) | D57: Class 3 | E57: 11 | F57: Standard | G57: 13 | H57: Masterly (FR) | I57: Garritty, Billy | J57: Johnston, Charlie | K57: 6 | L57: 0 | M57: 5 | N57: 26 | O57: 10 | P57: 241.30182 | Q57: 0.0041441876 | R57: 67 | S57: =IF(AND(ISNUMBER(R57),R57>1,P57>0),R57/P57-1,"") -> -0.72233943 | T57: =IF(AND(ISNUMBER(P57),P57>0),P57*EXP('Read me'!$B$22),"") -> 294.7267
A58: 7:00 | B58: Southwell | C58: 3rd And 10th Oktoberfest Race Nights Maiden Stakes (GBB/GBBPlus Race) | D58: Class 3 | E58: 11 | F58: Standard | G58: 13 | H58: Emerald Spirit (IRE) | I58: Peate, Jonny | J58: Loughnane, Daniel Mark | K58: 2 | L58: 0 | M58: 3 | N58: 17 | O58: 11 | P58: 541.77247 | Q58: 0.0018457933 | R58: 51 | S58: =IF(AND(ISNUMBER(R58),R58>1,P58>0),R58/P58-1,"") -> -0.90586454 | T58: =IF(AND(ISNUMBER(P58),P58>0),P58*EXP('Read me'!$B$22),"") -> 661.72239
A59: 7:00 | B59: Southwell | C59: 3rd And 10th Oktoberfest Race Nights Maiden Stakes (GBB/GBBPlus Race) | D59: Class 3 | E59: 11 | F59: Standard | G59: 13 | H59: Odriscoll (IRE) | I59: Hogan, D E | J59: Horton, James | K59: 11 | L59: 0 | M59: 3 | N59: 16 | O59: 12 | P59: 895.50707 | Q59: 0.0011166858 | R59: 101 | S59: =IF(AND(ISNUMBER(R59),R59>1,P59>0),R59/P59-1,"") -> -0.88721474 | T59: =IF(AND(ISNUMBER(P59),P59>0),P59*EXP('Read me'!$B$22),"") -> 1093.7748
A60: 7:00 | B60: Southwell | C60: 3rd And 10th Oktoberfest Race Nights Maiden Stakes (GBB/GBBPlus Race) | D60: Class 3 | E60: 11 | F60: Standard | G60: 13 | H60: Indian Mary (FR) | I60: Pearson, Laura | J60: Foy, Kevin | K60: 10 | L60: 0 | M60: 3 | N60: 14 | O60: 13 | P60: 991.50754 | Q60: 0.0010085652 | R60: 101 | S60: =IF(AND(ISNUMBER(R60),R60>1,P60>0),R60/P60-1,"") -> -0.89813492 | T60: =IF(AND(ISNUMBER(P60),P60>0),P60*EXP('Read me'!$B$22),"") -> 1211.03
A61: 7:30 | B61: Southwell | C61: Book The Bistro In Seasons Restaurant Apprentice Handicap | D61: Class 6 | E61: 8 | F61: Standard | G61: 14 | H61: Gladiadora (IRE) | I61: Wright, Liam | J61: Clover, Charlie | K61: 12 | L61: 65 | M61: 5 | N61: 9 | O61: 1 | P61: 5.6775766 | Q61: 0.17613149 | R61: 4.5 | S61: =IF(AND(ISNUMBER(R61),R61>1,P61>0),R61/P61-1,"") -> -0.20740831 | T61: =IF(AND(ISNUMBER(P61),P61>0),P61*EXP('Read me'!$B$22),"") -> 6.9346077
A62: 7:30 | B62: Southwell | C62: Book The Bistro In Seasons Restaurant Apprentice Handicap | D62: Class 6 | E62: 8 | F62: Standard | G62: 14 | H62: Avatar Jet (IRE) | I62: Horgan, C | J62: Carroll, D | K62: 2 | L62: 62 | M62: 5 | N62: 12 | O62: 2 | P62: 9.0141847 | Q62: 0.11093627 | R62: 9.5 | S62: =IF(AND(ISNUMBER(R62),R62>1,P62>0),R62/P62-1,"") -> 0.053894541 | T62: =IF(AND(ISNUMBER(P62),P62>0),P62*EXP('Read me'!$B$22),"") -> 11.00995
A63: 7:30 | B63: Southwell | C63: Book The Bistro In Seasons Restaurant Apprentice Handicap | D63: Class 6 | E63: 8 | F63: Standard | G63: 14 | H63: R P Mcmurphy | I63: Maher, Jude | J63: Appleby, M | K63: 8 | L63: 63 | M63: 4 | N63: 11 | O63: 3 | P63: 9.4361472 | Q63: 0.10597546 | R63: 7 | S63: =IF(AND(ISNUMBER(R63),R63>1,P63>0),R63/P63-1,"") -> -0.25817181 | T63: =IF(AND(ISNUMBER(P63),P63>0),P63*EXP('Read me'!$B$22),"") -> 11.525336
A64: 7:30 | B64: Southwell | C64: Book The Bistro In Seasons Restaurant Apprentice Handicap | D64: Class 6 | E64: 8 | F64: Standard | G64: 14 | H64: Dandy G Boy (IRE) | I64: Vigors, Harry | J64: Greatrex, W J | K64: 3 | L64: 64 | M64: 4 | N64: 17 | O64: 4 | P64: 9.4718767 | Q64: 0.1055757 | R64: 9 | S64: =IF(AND(ISNUMBER(R64),R64>1,P64>0),R64/P64-1,"") -> -0.049818711 | T64: =IF(AND(ISNUMBER(P64),P64>0),P64*EXP('Read me'!$B$22),"") -> 11.568976
... A99: 8:30 | B99: Southwell | C99: Golf & Gallop Southwell Golf Club Handicap | D99: Class 5 | E99: 6 | F99: Standard | G99: 13 | H99: Kings Call (IRE) | I99: Horgan, C | J99: Mullaney, L A | K99: 10 | L99: 74 | M99: 4 | N99: 63 | O99: 13 | P99: 36.649758 | Q99: 0.027285309 | R99: 21 | S99: =IF(AND(ISNUMBER(R99),R99>1,P99>0),R99/P99-1,"") -> -0.4270085 | T99: =IF(AND(ISNUMBER(P99),P99>0),P99*EXP('Read me'!$B$22),"") -> 44.764116
