Workbook

Sheet Read me
A1: Predictions for 2026-09-27
A3: Runners | B3: 221
A4: Races | B4: 23
A5: Meetings | B5: 3
A7: The model | B7: pair500
A8: Features | B8: 968
A9: Trained through | B9: 2026-09-22
A10: Boosting rounds | B10: 11000
A11: Target | B11: logit_norm_prob
A12: Feature code hash | B12: f879b10c8369467a
A14: How to read it
A15: Predicted BSP | B15: The model's forecast of the Betfair Starting Price, from pre-race information only. The prices in each race make a book of exactly 100%.
A16: Win probability | B16: 1 / predicted BSP: the model's chance for the horse, normalised within the race.
A17: Model rank | B17: 1 = the model's shortest price in the race (highlighted green).
A18: Card odds (HRB) | B18: The odds printed on the horseracebase card when it was fetched: a bookmaker forecast, not the Betfair morning price the early-price rule was tested against.
A19: Card odds vs model | B19: Card odds / predicted BSP - 1. Positive: the card is longer than the model.
A21: The early-price rule
A22: Margin (log) | B22: 0.2
A23: Rule: back at Betfair ≥ | B23: Predicted BSP × e^margin: at 0.2, a Betfair price at least 1.22 times the model's (the model at least 22% shorter). The rule was fixed before it was first tested (reports/clv_betfair_2026q1.md): back at Betfair's morning volume-weighted price, where at least £100 has been matched in the morning, and close the position at BSP (lay at BSP to level the book). It is a trade on the price, not a bet held to the result. The margin (blue) is the one input: change it to see the prices at another threshold.
A25: Note | B25: The best model measured: the pair at leaves of 500 (the extra-trees and Huber fits of the 968 at the slow recipe, train-bfsp runs 48 and 49, averaged), priced here by predict-now run 23 on the card fetched at 11:37 UTC (221 runners in 23 races; non-runners declared by then are out, and each race's book is 100% of those left). Out of sample (27 Sep 2025 to 31 Mar 2026) it prices the window at 0.3995 mean log error, the best yet (the 615 serving today: 0.4359). There the early-price rule returned +10.44% per trade and the top pick, backed at the morning price and traded out at BSP, +1.63%. Both are trades closed at BSP: backing the top pick at BSP and holding it to the result has not been shown profitable. It is not the served model: the 06:00 email priced today with the 615. Both members pass verify and this dry run was clean.

Sheet Top picks
A1: Time | B1: Course | C1: Race | D1: Runners | E1: Top pick | F1: Jockey | G1: Trainer | H1: Predicted BSP | I1: Win probability | J1: Second choice | K1: Second's BSP | L1: Second's probability | M1: Probability gap | N1: Card odds (HRB) | O1: Rule: back at Betfair ≥
A2: 1:19 | B2: Ffos Las | C2: Alex And Salvo Welcome You To The Bridge Handicap | D2: 11 | E2: Sub Thirteen | F2: Hutchinson, Callum | G2: Scott, J | H2: 3.0244583 | I2: 0.33063772 | J2: Macarone | K2: 4.3312252 | L2: 0.23088155 | M2: =IF(AND(ISNUMBER(I2),ISNUMBER(L2)),I2-L2,"") -> 0.099756161 | N2: 3.25 | O2: =IF(AND(ISNUMBER(H2),H2>0),H2*EXP('Read me'!$B$22),"") -> 3.6940818
A3: 1:25 | B3: Curragh | C3: Army Equitation Centenary Irish European Breeders Fund Maiden | D3: 13 | E3: Raging Bull (IRE) | F3: Moore, Ryan | G3: OBrien, A P | H3: 1.7510775 | I3: 0.57107694 | J3: Yellow Sky (IRE) | K3: 7.4272181 | L3: 0.13463991 | M3: =IF(AND(ISNUMBER(I3),ISNUMBER(L3)),I3-L3,"") -> 0.43643702 | N3: 1.7272727 | O3: =IF(AND(ISNUMBER(H3),H3>0),H3*EXP('Read me'!$B$22),"") -> 2.1387709
A4: 1:37 | B4: Epsom | C4: Betfred Turbo Boost Nursery | D4: 8 | E4: Regal Tiger | F4: Murphy, Oisin | G4: Palmer, Hugo | H4: 4.5975127 | I4: 0.21750892 | J4: Give Hand (IRE) | K4: 5.8202093 | L4: 0.17181513 | M4: =IF(AND(ISNUMBER(I4),ISNUMBER(L4)),I4-L4,"") -> 0.045693789 | N4: 5.5 | O4: =IF(AND(ISNUMBER(H4),H4>0),H4*EXP('Read me'!$B$22),"") -> 5.6154147
A5: 1:49 | B5: Ffos Las | C5: Bridge, The Home Of The Carvery Nursery | D5: 8 | E5: Rhodes Runner (IRE) | F5: Clutterbuck, Rhys | G5: Beckett, R M | H5: 4.9613223 | I5: 0.20155917 | J5: Perigord Noir (IRE) | K5: 5.5643037 | L5: 0.17971701 | M5: =IF(AND(ISNUMBER(I5),ISNUMBER(L5)),I5-L5,"") -> 0.021842164 | N5: 3.75 | O5: =IF(AND(ISNUMBER(H5),H5>0),H5*EXP('Read me'!$B$22),"") -> 6.0597727
A6: 2:00 | B6: Curragh | C6: Izuzu Ireland Irish European Breeders Fund Maiden | D6: 9 | E6: Kingdom Of Camelot (FR) | F6: Moore, Ryan | G6: OBrien, A P | H6: 2.7097568 | I6: 0.36903681 | J6: Cluster | K6: 4.0075054 | L6: 0.24953179 | M6: =IF(AND(ISNUMBER(I6),ISNUMBER(L6)),I6-L6,"") -> 0.11950502 | N6: 1.9090909 | O6: =IF(AND(ISNUMBER(H6),H6>0),H6*EXP('Read me'!$B$22),"") -> 3.3097044
A7: 2:12 | B7: Epsom | C7: Betfred Derby Wild Card EBF Conditions Stakes (GBB/GBBPlus Race) | D7: 5 | E7: Rose Moon (GER) | F7: Ryan, Rossa | G7: Beckett, R M | H7: 3.3125625 | I7: 0.3018811 | J7: Al Wathba (FR) | K7: 3.524514 | L7: 0.28372706 | M7: =IF(AND(ISNUMBER(I7),ISNUMBER(L7)),I7-L7,"") -> 0.018154037 | N7: 2.375 | O7: =IF(AND(ISNUMBER(H7),H7>0),H7*EXP('Read me'!$B$22),"") -> 4.0459729
A8: 2:24 | B8: Ffos Las | C8: Bridge, Family Run And Proud Handicap | D8: 4 | E8: Call Time (IRE) | F8: Wonnacott, Millie | G8: Moore, J S | H8: 1.8816813 | I8: 0.53143963 | J8: Some Nightmare (IRE) | K8: 3.7883785 | L8: 0.26396518 | M8: =IF(AND(ISNUMBER(I8),ISNUMBER(L8)),I8-L8,"") -> 0.26747446 | N8: 1.6153846 | O8: =IF(AND(ISNUMBER(H8),H8>0),H8*EXP('Read me'!$B$22),"") -> 2.2982907
A9: 2:35 | B9: Curragh | C9: Qatar Racing And Equestrian Club Renaissance Stakes (Group 3) | D9: 8 | E9: Soul Love | F9: Jamin, Pierre-Louis | G9: Burke, K R | H9: 3.6569722 | I9: 0.27345026 | J9: Power Blue (IRE) | K9: 4.4795634 | L9: 0.22323604 | M9: =IF(AND(ISNUMBER(I9),ISNUMBER(L9)),I9-L9,"") -> 0.050214218 | N9: 3.75 | O9: =IF(AND(ISNUMBER(H9),H9>0),H9*EXP('Read me'!$B$22),"") -> 4.4666359
A10: 2:47 | B10: Epsom | C10: Hunt Family Fund Novice Stakes (Sponsored By Betfred) (GBB Race) | D10: 6 | E10: Maestro Del Mar (FR) | F10: Loughnane, Billy | G10: Mohammed, Ismail | H10: 3.4940533 | I10: 0.28620056 | J10: Rowlf | K10: 3.9386 | L10: 0.25389732 | M10: =IF(AND(ISNUMBER(I10),ISNUMBER(L10)),I10-L10,"") -> 0.032303238 | N10: 4 | O10: =IF(AND(ISNUMBER(H10),H10>0),H10*EXP('Read me'!$B$22),"") -> 4.2676463
A11: 2:59 | B11: Ffos Las | C11: Happy Birthday Alex, From The Bridge Handicap | D11: 5 | E11: Campeona | F11: Gilligan, Jack | G11: Prescott, Sir Mark | H11: 2.63875 | I11: 0.37896732 | J11: Carthusian (IRE) | K11: 3.7148957 | L11: 0.26918656 | M11: =IF(AND(ISNUMBER(I11),ISNUMBER(L11)),I11-L11,"") -> 0.10978076 | N11: 2.625 | O11: =IF(AND(ISNUMBER(H11),H11>0),H11*EXP('Read me'!$B$22),"") -> 3.2229765
A12: 3:10 | B12: Curragh | C12: Celebrating County Kildare And Lexington Twinning Maiden | D12: 12 | E12: Valentino Eclipse (IRE) | F12: Heffernan, J A | G12: Stack, J A | H12: 2.4347683 | I12: 0.4107167 | J12: A Good Yarn (IRE) | K12: 3.5987295 | L12: 0.27787584 | M12: =IF(AND(ISNUMBER(I12),ISNUMBER(L12)),I12-L12,"") -> 0.13284086 | N12: 1.7272727 | O12: =IF(AND(ISNUMBER(H12),H12>0),H12*EXP('Read me'!$B$22),"") -> 2.9738327
A13: 3:22 | B13: Epsom | C13: Betfred Nifty 50 Jump Jockeys Derby Handicap (Professional Jump Jockeys) (GBBPlus Race) | D13: 13 | E13: Seeking Charles (FR) | F13: Davies, James | G13: Usher, M D I | H13: 4.8890414 | I13: 0.20453907 | J13: Nibras Gold (IRE) | K13: 6.9023838 | L13: 0.14487748 | M13: =IF(AND(ISNUMBER(I13),ISNUMBER(L13)),I13-L13,"") -> 0.059661588 | N13: 4.5 | O13: =IF(AND(ISNUMBER(H13),H13>0),H13*EXP('Read me'!$B$22),"") -> 5.9714887
... A24: 5:30 | B24: Curragh | C24: Kwiff Supercharged Betting (Q.R.) Handicap | D24: 18 | E24: Chipsrdown (IRE) | F24: Ryan, Mr A P | G24: Slattery, Andrew | H24: 4.4584631 | I24: 0.22429254 | J24: Dark Summit | K24: 6.2954259 | L24: 0.15884549 | M24: =IF(AND(ISNUMBER(I24),ISNUMBER(L24)),I24-L24,"") -> 0.06544705 | N24: 4.3333333 | O24: =IF(AND(ISNUMBER(H24),H24>0),H24*EXP('Read me'!$B$22),"") -> 5.4455791

Sheet All runners
A1: Time | B1: Course | C1: Race | D1: Class | E1: Furlongs | F1: Going | G1: Runners | H1: Horse | I1: Jockey | J1: Trainer | K1: Draw | L1: OR | M1: Age | N1: Days since run | O1: Model rank | P1: Predicted BSP | Q1: Win probability | R1: Card odds (HRB) | S1: Card odds vs model | T1: Rule: back at Betfair ≥
A2: 1:19 | B2: Ffos Las | C2: Alex And Salvo Welcome You To The Bridge Handicap | D2: Class 6 | E2: 6 | F2: Good To Soft | G2: 11 | H2: Sub Thirteen | I2: Hutchinson, Callum | J2: Scott, J | K2: 9 | L2: 53 | M2: 5 | N2: 14 | O2: 1 | P2: 3.0244583 | Q2: 0.33063772 | R2: 3.25 | S2: =IF(AND(ISNUMBER(R2),R2>1,P2>0),R2/P2-1,"") -> 0.074572576 | T2: =IF(AND(ISNUMBER(P2),P2>0),P2*EXP('Read me'!$B$22),"") -> 3.6940818
A3: 1:19 | B3: Ffos Las | C3: Alex And Salvo Welcome You To The Bridge Handicap | D3: Class 6 | E3: 6 | F3: Good To Soft | G3: 11 | H3: Macarone | I3: Ffrench Davis, Ben | J3: Harris, Miss G | K3: 8 | L3: 52 | M3: 5 | N3: 15 | O3: 2 | P3: 4.3312252 | Q3: 0.23088155 | R3: 4 | S3: =IF(AND(ISNUMBER(R3),R3>1,P3>0),R3/P3-1,"") -> -0.07647378 | T3: =IF(AND(ISNUMBER(P3),P3>0),P3*EXP('Read me'!$B$22),"") -> 5.2901704
A4: 1:19 | B4: Ffos Las | C4: Alex And Salvo Welcome You To The Bridge Handicap | D4: Class 6 | E4: 6 | F4: Good To Soft | G4: 11 | H4: Blue Point Express (IRE) | I4: Marsh, Finley | J4: Wintle, A | K4: 7 | L4: 45 | M4: 4 | N4: 27 | O4: 3 | P4: 7.187645 | Q4: 0.13912763 | R4: 6 | S4: =IF(AND(ISNUMBER(R4),R4>1,P4>0),R4/P4-1,"") -> -0.16523424 | T4: =IF(AND(ISNUMBER(P4),P4>0),P4*EXP('Read me'!$B$22),"") -> 8.7790095
A5: 1:19 | B5: Ffos Las | C5: Alex And Salvo Welcome You To The Bridge Handicap | D5: Class 6 | E5: 6 | F5: Good To Soft | G5: 11 | H5: Up The Anti (IRE) | I5: Coppins, Myla | J5: Carroll, A W | K5: 6 | L5: 53 | M5: 4 | N5: 25 | O5: 4 | P5: 10.055959 | Q5: 0.099443529 | R5: 8 | S5: =IF(AND(ISNUMBER(R5),R5>1,P5>0),R5/P5-1,"") -> -0.20445177 | T5: =IF(AND(ISNUMBER(P5),P5>0),P5*EXP('Read me'!$B$22),"") -> 12.282375
A6: 1:19 | B6: Ffos Las | C6: Alex And Salvo Welcome You To The Bridge Handicap | D6: Class 6 | E6: 6 | F6: Good To Soft | G6: 11 | H6: Music And Song (IRE) | I6: Probert, David | J6: Flood, D | K6: 5 | L6: 45 | M6: 3 | N6: 5 | O6: 5 | P6: 15.63988 | Q6: 0.063939107 | R6: 10 | S6: =IF(AND(ISNUMBER(R6),R6>1,P6>0),R6/P6-1,"") -> -0.36060893 | T6: =IF(AND(ISNUMBER(P6),P6>0),P6*EXP('Read me'!$B$22),"") -> 19.102593
A7: 1:19 | B7: Ffos Las | C7: Alex And Salvo Welcome You To The Bridge Handicap | D7: Class 6 | E7: 6 | F7: Good To Soft | G7: 11 | H7: The Bear Of Saints (FR) | I7: Carson, William | J7: Oshea, J G M | K7: 4 | L7: 54 | M7: 4 | N7: 34 | O7: 6 | P7: 16.543067 | Q7: 0.060448284 | R7: 15 | S7: =IF(AND(ISNUMBER(R7),R7>1,P7>0),R7/P7-1,"") -> -0.093275736 | T7: =IF(AND(ISNUMBER(P7),P7>0),P7*EXP('Read me'!$B$22),"") -> 20.205747
A8: 1:19 | B8: Ffos Las | C8: Alex And Salvo Welcome You To The Bridge Handicap | D8: Class 6 | E8: 6 | F8: Good To Soft | G8: 11 | H8: Pacific Prince | I8: Coughlan, Laura | J8: Bennett, J A | K8: 11 | L8: 45 | M8: 5 | N8: 20 | O8: 7 | P8: 44.329774 | Q8: 0.022558202 | R8: 41 | S8: =IF(AND(ISNUMBER(R8),R8>1,P8>0),R8/P8-1,"") -> -0.075113712 | T8: =IF(AND(ISNUMBER(P8),P8>0),P8*EXP('Read me'!$B$22),"") -> 54.144508
A9: 1:19 | B9: Ffos Las | C9: Alex And Salvo Welcome You To The Bridge Handicap | D9: Class 6 | E9: 6 | F9: Good To Soft | G9: 11 | H9: Savvi Row | I9: Heard, Tyler | J9: Millman, B R | K9: 12 | L9: 45 | M9: 3 | N9: 15 | O9: 8 | P9: 59.529493 | Q9: 0.016798396 | R9: 34 | S9: =IF(AND(ISNUMBER(R9),R9>1,P9>0),R9/P9-1,"") -> -0.42885454 | T9: =IF(AND(ISNUMBER(P9),P9>0),P9*EXP('Read me'!$B$22),"") -> 72.709487
A10: 1:19 | B10: Ffos Las | C10: Alex And Salvo Welcome You To The Bridge Handicap | D10: Class 6 | E10: 6 | F10: Good To Soft | G10: 11 | H10: Shush A Minute | I10: Bradley, Paddy | J10: Ryan, J | K10: 1 | L10: 50 | M10: 3 | N10: 306 | O10: 9 | P10: 62.476468 | Q10: 0.016006026 | R10: 7 | S10: =IF(AND(ISNUMBER(R10),R10>1,P10>0),R10/P10-1,"") -> -0.88795782 | T10: =IF(AND(ISNUMBER(P10),P10>0),P10*EXP('Read me'!$B$22),"") -> 76.308931
A11: 1:19 | B11: Ffos Las | C11: Alex And Salvo Welcome You To The Bridge Handicap | D11: Class 6 | E11: 6 | F11: Good To Soft | G11: 11 | H11: Lochaber | I11: ONeill, K T | J11: Dixon, Scott | K11: 10 | L11: 45 | M11: 5 | N11: 14 | O11: 10 | P11: 63.912016 | Q11: 0.01564651 | R11: 51 | S11: =IF(AND(ISNUMBER(R11),R11>1,P11>0),R11/P11-1,"") -> -0.20202799 | T11: =IF(AND(ISNUMBER(P11),P11>0),P11*EXP('Read me'!$B$22),"") -> 78.062313
A12: 1:19 | B12: Ffos Las | C12: Alex And Salvo Welcome You To The Bridge Handicap | D12: Class 6 | E12: 6 | F12: Good To Soft | G12: 11 | H12: Miss Gold | I12: Sayette, B D L | J12: Flood, D | K12: 2 | L12: 45 | M12: 3 | N12: 46 | O12: 11 | P12: 221.57978 | Q12: 0.0045130472 | R12: 81 | S12: =IF(AND(ISNUMBER(R12),R12>1,P12>0),R12/P12-1,"") -> -0.63444318 | T12: =IF(AND(ISNUMBER(P12),P12>0),P12*EXP('Read me'!$B$22),"") -> 270.63815
A13: 1:25 | B13: Curragh | C13: Army Equitation Centenary Irish European Breeders Fund Maiden | E13: 7 | F13: Heavy | G13: 13 | H13: Raging Bull (IRE) | I13: Moore, Ryan | J13: OBrien, A P | K13: 6 | L13: 0 | M13: 2 | N13: 49 | O13: 1 | P13: 1.7510775 | Q13: 0.57107694 | R13: 1.7272727 | S13: =IF(AND(ISNUMBER(R13),R13>1,P13>0),R13/P13-1,"") -> -0.013594385 | T13: =IF(AND(ISNUMBER(P13),P13>0),P13*EXP('Read me'!$B$22),"") -> 2.1387709
A14: 1:25 | B14: Curragh | C14: Army Equitation Centenary Irish European Breeders Fund Maiden | E14: 7 | F14: Heavy | G14: 13 | H14: Yellow Sky (IRE) | I14: Coen, Ben M | J14: Murtagh, J P | K14: 12 | L14: 0 | M14: 2 | N14: 62 | O14: 2 | P14: 7.4272181 | Q14: 0.13463991 | R14: 12 | S14: =IF(AND(ISNUMBER(R14),R14>1,P14>0),R14/P14-1,"") -> 0.61567896 | T14: =IF(AND(ISNUMBER(P14),P14>0),P14*EXP('Read me'!$B$22),"") -> 9.0716247
A15: 1:25 | B15: Curragh | C15: Army Equitation Centenary Irish European Breeders Fund Maiden | E15: 7 | F15: Heavy | G15: 13 | H15: Maximilien Luce (IRE) | I15: Cleary, Jack | J15: OBrien, A P | K15: 1 | L15: 0 | M15: 2 | O15: 3 | P15: 13.08711 | Q15: 0.076411066 | R15: 7 | S15: =IF(AND(ISNUMBER(R15),R15>1,P15>0),R15/P15-1,"") -> -0.46512253 | T15: =IF(AND(ISNUMBER(P15),P15>0),P15*EXP('Read me'!$B$22),"") -> 15.984632
A16: 1:25 | B16: Curragh | C16: Army Equitation Centenary Irish European Breeders Fund Maiden | E16: 7 | F16: Heavy | G16: 13 | H16: Golden Idol (IRE) | I16: Lee, W J | J16: Bromhead, Henry De | K16: 9 | L16: 0 | M16: 2 | O16: 4 | P16: 13.310346 | Q16: 0.075129527 | R16: 5.5 | S16: =IF(AND(ISNUMBER(R16),R16>1,P16>0),R16/P16-1,"") -> -0.5867876 | T16: =IF(AND(ISNUMBER(P16),P16>0),P16*EXP('Read me'!$B$22),"") -> 16.257293
A17: 1:25 | B17: Curragh | C17: Army Equitation Centenary Irish European Breeders Fund Maiden | E17: 7 | F17: Heavy | G17: 13 | H17: Normanton (IRE) | I17: McAteer, L T | J17: Marnane, David | K17: 16 | L17: 0 | M17: 2 | O17: 5 | P17: 26.949884 | Q17: 0.037105911 | R17: 15 | S17: =IF(AND(ISNUMBER(R17),R17>1,P17>0),R17/P17-1,"") -> -0.44341133 | T17: =IF(AND(ISNUMBER(P17),P17>0),P17*EXP('Read me'!$B$22),"") -> 32.916663
A18: 1:25 | B18: Curragh | C18: Army Equitation Centenary Irish European Breeders Fund Maiden | E18: 7 | F18: Heavy | G18: 13 | H18: Overhead Drive (IRE) | I18: Heffernan, J A | J18: Murphy, John Joseph | K18: 14 | L18: 0 | M18: 2 | O18: 6 | P18: 29.584989 | Q18: 0.033800925 | R18: 29 | S18: =IF(AND(ISNUMBER(R18),R18>1,P18>0),R18/P18-1,"") -> -0.019773178 | T18: =IF(AND(ISNUMBER(P18),P18>0),P18*EXP('Read me'!$B$22),"") -> 36.135187
A19: 1:25 | B19: Curragh | C19: Army Equitation Centenary Irish European Breeders Fund Maiden | E19: 7 | F19: Heavy | G19: 13 | H19: Tsali (IRE) | I19: Hayes, C D | J19: Coleman, Kevin | K19: 8 | L19: 0 | M19: 2 | O19: 7 | P19: 36.193559 | Q19: 0.027629225 | R19: 34 | S19: =IF(AND(ISNUMBER(R19),R19>1,P19>0),R19/P19-1,"") -> -0.060606334 | T19: =IF(AND(ISNUMBER(P19),P19>0),P19*EXP('Read me'!$B$22),"") -> 44.206913
A20: 1:25 | B20: Curragh | C20: Army Equitation Centenary Irish European Breeders Fund Maiden | E20: 7 | F20: Heavy | G20: 13 | H20: Ah Sure Look (IRE) | I20: Sheridan, J M | J20: Hassett, Martin | K20: 10 | L20: 0 | M20: 2 | O20: 8 | P20: 87.460693 | Q20: 0.011433708 | R20: 34 | S20: =IF(AND(ISNUMBER(R20),R20>1,P20>0),R20/P20-1,"") -> -0.61125394 | T20: =IF(AND(ISNUMBER(P20),P20>0),P20*EXP('Read me'!$B$22),"") -> 106.82473
A21: 1:25 | B21: Curragh | C21: Army Equitation Centenary Irish European Breeders Fund Maiden | E21: 7 | F21: Heavy | G21: 13 | H21: Johntom | I21: Carroll, G F | J21: Cromwell, Gavin Patrick | K21: 5 | L21: 0 | M21: 2 | N21: 10 | O21: 9 | P21: 95.343068 | Q21: 0.010488439 | R21: 41 | S21: =IF(AND(ISNUMBER(R21),R21>1,P21>0),R21/P21-1,"") -> -0.56997398 | T21: =IF(AND(ISNUMBER(P21),P21>0),P21*EXP('Read me'!$B$22),"") -> 116.45229
A22: 1:25 | B22: Curragh | C22: Army Equitation Centenary Irish European Breeders Fund Maiden | E22: 7 | F22: Heavy | G22: 13 | H22: Activity (IRE) | I22: Crosse, Nathan | J22: Harrington, Mrs John | K22: 3 | L22: 0 | M22: 2 | N22: 52 | O22: 10 | P22: 112.02611 | Q22: 0.0089264903 | R22: 29 | S22: =IF(AND(ISNUMBER(R22),R22>1,P22>0),R22/P22-1,"") -> -0.74113178 | T22: =IF(AND(ISNUMBER(P22),P22>0),P22*EXP('Read me'!$B$22),"") -> 136.829
A23: 1:25 | B23: Curragh | C23: Army Equitation Centenary Irish European Breeders Fund Maiden | E23: 7 | F23: Heavy | G23: 13 | H23: Soho Dragon (IRE) | I23: OConnor, Donagh | J23: Murphy, John Joseph | K23: 7 | L23: 0 | M23: 2 | O23: 11 | P23: 158.85539 | Q23: 0.0062950336 | R23: 34 | S23: =IF(AND(ISNUMBER(R23),R23>1,P23>0),R23/P23-1,"") -> -0.78596886 | T23: =IF(AND(ISNUMBER(P23),P23>0),P23*EXP('Read me'!$B$22),"") -> 194.02641
A24: 1:25 | B24: Curragh | C24: Army Equitation Centenary Irish European Breeders Fund Maiden | E24: 7 | F24: Heavy | G24: 13 | H24: One Flash (IRE) | I24: Joyce, Wesley | J24: Sexton, Adrian | K24: 11 | L24: 0 | M24: 2 | O24: 12 | P24: 282.56065 | Q24: 0.0035390632 | R24: 41 | S24: =IF(AND(ISNUMBER(R24),R24>1,P24>0),R24/P24-1,"") -> -0.85489841 | T24: =IF(AND(ISNUMBER(P24),P24>0),P24*EXP('Read me'!$B$22),"") -> 345.12036
A25: 1:25 | B25: Curragh | C25: Army Equitation Centenary Irish European Breeders Fund Maiden | E25: 7 | F25: Heavy | G25: 13 | H25: Silk Twist (IRE) | I25: McCullagh, Scott | J25: Mullins, Thomas | K25: 2 | L25: 0 | M25: 2 | N25: 10 | O25: 13 | P25: 283.78757 | Q25: 0.0035237626 | R25: 41 | S25: =IF(AND(ISNUMBER(R25),R25>1,P25>0),R25/P25-1,"") -> -0.85552574 | T25: =IF(AND(ISNUMBER(P25),P25>0),P25*EXP('Read me'!$B$22),"") -> 346.61892
A26: 1:37 | B26: Epsom | C26: Betfred Turbo Boost Nursery | D26: Class 4 | E26: 7 | F26: Good | G26: 8 | H26: Regal Tiger | I26: Murphy, Oisin | J26: Palmer, Hugo | K26: 7 | L26: 73 | M26: 2 | N26: 69 | O26: 1 | P26: 4.5975127 | Q26: 0.21750892 | R26: 5.5 | S26: =IF(AND(ISNUMBER(R26),R26>1,P26>0),R26/P26-1,"") -> 0.19629903 | T26: =IF(AND(ISNUMBER(P26),P26>0),P26*EXP('Read me'!$B$22),"") -> 5.6154147
A27: 1:37 | B27: Epsom | C27: Betfred Turbo Boost Nursery | D27: Class 4 | E27: 7 | F27: Good | G27: 8 | H27: Give Hand (IRE) | I27: Edmunds, Lewis | J27: Charlton, Roger/Harry | K27: 3 | L27: 76 | M27: 2 | N27: 17 | O27: 2 | P27: 5.8202093 | Q27: 0.17181513 | R27: 3.5 | S27: =IF(AND(ISNUMBER(R27),R27>1,P27>0),R27/P27-1,"") -> -0.39864706 | T27: =IF(AND(ISNUMBER(P27),P27>0),P27*EXP('Read me'!$B$22),"") -> 7.1088197
A28: 1:37 | B28: Epsom | C28: Betfred Turbo Boost Nursery | D28: Class 4 | E28: 7 | F28: Good | G28: 8 | H28: The Ginger Kid (IRE) | I28: Lewis, Ashley | J28: Walker, Ed | K28: 9 | L28: 83 | M28: 2 | N28: 38 | O28: 3 | P28: 6.2737356 | Q28: 0.15939467 | R28: 4.5 | S28: =IF(AND(ISNUMBER(R28),R28>1,P28>0),R28/P28-1,"") -> -0.28272399 | T28: =IF(AND(ISNUMBER(P28),P28>0),P28*EXP('Read me'!$B$22),"") -> 7.662758
A29: 1:37 | B29: Epsom | C29: Betfred Turbo Boost Nursery | D29: Class 4 | E29: 7 | F29: Good | G29: 8 | H29: Telegraphic | I29: Loughnane, Billy | J29: Johnston, Charlie | K29: 8 | L29: 80 | M29: 2 | N29: 38 | O29: 4 | P29: 8.7453849 | Q29: 0.11434603 | R29: 6.5 | S29: =IF(AND(ISNUMBER(R29),R29>1,P29>0),R29/P29-1,"") -> -0.25675084 | T29: =IF(AND(ISNUMBER(P29),P29>0),P29*EXP('Read me'!$B$22),"") -> 10.681637
A30: 1:37 | B30: Epsom | C30: Betfred Turbo Boost Nursery | D30: Class 4 | E30: 7 | F30: Good | G30: 8 | H30: Rogue Imperial | I30: Ryan, Rossa | J30: Watson, Archie | K30: 5 | L30: 78 | M30: 2 | N30: 34 | O30: 5 | P30: 9.1388947 | Q30: 0.10942242 | R30: 17 | S30: =IF(AND(ISNUMBER(R30),R30>1,P30>0),R30/P30-1,"") -> 0.86018119 | T30: =IF(AND(ISNUMBER(P30),P30>0),P30*EXP('Read me'!$B$22),"") -> 11.162271
A31: 1:37 | B31: Epsom | C31: Betfred Turbo Boost Nursery | D31: Class 4 | E31: 7 | F31: Good | G31: 8 | H31: Clive The Writer (IRE) | I31: Crouch, Hector | J31: Muir, W R & Grassick, C | K31: 1 | L31: 78 | M31: 2 | N31: 16 | O31: 6 | P31: 9.3350044 | Q31: 0.10712368 | R31: 9.5 | S31: =IF(AND(ISNUMBER(R31),R31>1,P31>0),R31/P31-1,"") -> 0.017674937 | T31: =IF(AND(ISNUMBER(P31),P31>0),P31*EXP('Read me'!$B$22),"") -> 11.4018
A32: 1:37 | B32: Epsom | C32: Betfred Turbo Boost Nursery | D32: Class 4 | E32: 7 | F32: Good | G32: 8 | H32: Angel Of Desire | I32: Fallon, Cieren | J32: Perrett, Mrs A J | K32: 6 | L32: 71 | M32: 2 | N32: 27 | O32: 7 | P32: 13.811546 | Q32: 0.07240319 | R32: 11 | S32: =IF(AND(ISNUMBER(R32),R32>1,P32>0),R32/P32-1,"") -> -0.20356492 | T32: =IF(AND(ISNUMBER(P32),P32>0),P32*EXP('Read me'!$B$22),"") -> 16.869461
A33: 1:37 | B33: Epsom | C33: Betfred Turbo Boost Nursery | D33: Class 4 | E33: 7 | F33: Good | G33: 8 | H33: Leucothea (IRE) | I33: Levey, S M | J33: Hannon (Jnr), Richard | K33: 2 | L33: 71 | M33: 2 | N33: 17 | O33: 8 | P33: 20.839422 | Q33: 0.047985976 | R33: 19 | S33: =IF(AND(ISNUMBER(R33),R33>1,P33>0),R33/P33-1,"") -> -0.088266455 | T33: =IF(AND(ISNUMBER(P33),P33>0),P33*EXP('Read me'!$B$22),"") -> 25.453327
A34: 1:49 | B34: Ffos Las | C34: Bridge, The Home Of The Carvery Nursery | D34: Class 5 | E34: 5 | F34: Good To Soft | G34: 8 | H34: Rhodes Runner (IRE) | I34: Clutterbuck, Rhys | J34: Beckett, R M | K34: 4 | L34: 75 | M34: 2 | N34: 8 | O34: 1 | P34: 4.9613223 | Q34: 0.20155917 | R34: 3.75 | S34: =IF(AND(ISNUMBER(R34),R34>1,P34>0),R34/P34-1,"") -> -0.24415311 | T34: =IF(AND(ISNUMBER(P34),P34>0),P34*EXP('Read me'!$B$22),"") -> 6.0597727
A35: 1:49 | B35: Ffos Las | C35: Bridge, The Home Of The Carvery Nursery | D35: Class 5 | E35: 5 | F35: Good To Soft | G35: 8 | H35: Perigord Noir (IRE) | I35: Sayette, B D L | J35: Baker, George | K35: 8 | L35: 71 | M35: 2 | N35: 15 | O35: 2 | P35: 5.5643037 | Q35: 0.17971701 | R35: 4.5 | S35: =IF(AND(ISNUMBER(R35),R35>1,P35>0),R35/P35-1,"") -> -0.19127347 | T35: =IF(AND(ISNUMBER(P35),P35>0),P35*EXP('Read me'!$B$22),"") -> 6.7962558
A36: 1:49 | B36: Ffos Las | C36: Bridge, The Home Of The Carvery Nursery | D36: Class 5 | E36: 5 | F36: Good To Soft | G36: 8 | H36: Naval Cop | I36: Hutchinson, Callum | J36: Balding, A M | K36: 2 | L36: 65 | M36: 2 | N36: 15 | O36: 3 | P36: 6.3248432 | Q36: 0.15810669 | R36: 4.5 | S36: =IF(AND(ISNUMBER(R36),R36>1,P36>0),R36/P36-1,"") -> -0.28851992 | T36: =IF(AND(ISNUMBER(P36),P36>0),P36*EXP('Read me'!$B$22),"") -> 7.725181
A37: 1:49 | B37: Ffos Las | C37: Bridge, The Home Of The Carvery Nursery | D37: Class 5 | E37: 5 | F37: Good To Soft | G37: 8 | H37: Blondie Larry (IRE) | I37: Carver, William | J37: Osborne, J A | K37: 5 | L37: 73 | M37: 2 | N37: 73 | O37: 4 | P37: 6.8148062 | Q37: 0.14673932 | R37: 9 | S37: =IF(AND(ISNUMBER(R37),R37>1,P37>0),R37/P37-1,"") -> 0.32065384 | T37: =IF(AND(ISNUMBER(P37),P37>0),P37*EXP('Read me'!$B$22),"") -> 8.3236231
... A41: 1:49 | B41: Ffos Las | C41: Bridge, The Home Of The Carvery Nursery | D41: Class 5 | E41: 5 | F41: Good To Soft | G41: 8 | H41: Defiant Dream | I41: Heard, Tyler | J41: Usher, M D I | K41: 3 | L41: 54 | M41: 2 | N41: 10 | O41: 8 | P41: 49.851691 | Q41: 0.0200595 | R41: 29 | S41: =IF(AND(ISNUMBER(R41),R41>1,P41>0),R41/P41-1,"") -> -0.4182745 | T41: =IF(AND(ISNUMBER(P41),P41>0),P41*EXP('Read me'!$B$22),"") -> 60.888993
A42: 2:00 | B42: Curragh | C42: Izuzu Ireland Irish European Breeders Fund Maiden | E42: 9 | F42: Heavy | G42: 9 | H42: Kingdom Of Camelot (FR) | I42: Moore, Ryan | J42: OBrien, A P | K42: 12 | L42: 0 | M42: 2 | N42: 29 | O42: 1 | P42: 2.7097568 | Q42: 0.36903681 | R42: 1.9090909 | S42: =IF(AND(ISNUMBER(R42),R42>1,P42>0),R42/P42-1,"") -> -0.29547519 | T42: =IF(AND(ISNUMBER(P42),P42>0),P42*EXP('Read me'!$B$22),"") -> 3.3097044
A43: 2:00 | B43: Curragh | C43: Izuzu Ireland Irish European Breeders Fund Maiden | E43: 9 | F43: Heavy | G43: 9 | H43: Cluster | I43: Keane, C T | J43: OBrien, Joseph Patrick | K43: 6 | L43: 0 | M43: 2 | N43: 29 | O43: 2 | P43: 4.0075054 | Q43: 0.24953179 | R43: 2.75 | S43: =IF(AND(ISNUMBER(R43),R43>1,P43>0),R43/P43-1,"") -> -0.31378758 | T43: =IF(AND(ISNUMBER(P43),P43>0),P43*EXP('Read me'!$B$22),"") -> 4.8947782
A44: 2:00 | B44: Curragh | C44: Izuzu Ireland Irish European Breeders Fund Maiden | E44: 9 | F44: Heavy | G44: 9 | H44: Capability Brown (IRE) | I44: Lordan, W M | J44: OBrien, A P | K44: 1 | L44: 0 | M44: 2 | N44: 26 | O44: 3 | P44: 4.4751775 | Q44: 0.22345482 | R44: 6.5 | S44: =IF(AND(ISNUMBER(R44),R44>1,P44>0),R44/P44-1,"") -> 0.45245634 | T44: =IF(AND(ISNUMBER(P44),P44>0),P44*EXP('Read me'!$B$22),"") -> 5.4659942
A45: 2:00 | B45: Curragh | C45: Izuzu Ireland Irish European Breeders Fund Maiden | E45: 9 | F45: Heavy | G45: 9 | H45: Darivan (IRE) | I45: Coen, Ben M | J45: Murtagh, J P | K45: 5 | L45: 0 | M45: 2 | N45: 92 | O45: 4 | P45: 11.9565 | Q45: 0.083636516 | R45: 19 | S45: =IF(AND(ISNUMBER(R45),R45>1,P45>0),R45/P45-1,"") -> 0.58909381 | T45: =IF(AND(ISNUMBER(P45),P45>0),P45*EXP('Read me'!$B$22),"") -> 14.603702
A46: 2:00 | B46: Curragh | C46: Izuzu Ireland Irish European Breeders Fund Maiden | E46: 9 | F46: Heavy | G46: 9 | H46: Greatest Knight (IRE) | I46: Cleary, Jack | J46: OBrien, A P | K46: 10 | L46: 0 | M46: 2 | O46: 5 | P46: 25.267991 | Q46: 0.039575762 | R46: 21 | S46: =IF(AND(ISNUMBER(R46),R46>1,P46>0),R46/P46-1,"") -> -0.168909 | T46: =IF(AND(ISNUMBER(P46),P46>0),P46*EXP('Read me'!$B$22),"") -> 30.862394
A47: 2:00 | B47: Curragh | C47: Izuzu Ireland Irish European Breeders Fund Maiden | E47: 9 | F47: Heavy | G47: 9 | H47: Silent Kingdom (IRE) | I47: Lee, W J | J47: Dias, Diego | K47: 2 | L47: 0 | M47: 2 | O47: 6 | P47: 60.524576 | Q47: 0.016522214 | R47: 34 | S47: =IF(AND(ISNUMBER(R47),R47>1,P47>0),R47/P47-1,"") -> -0.43824472 | T47: =IF(AND(ISNUMBER(P47),P47>0),P47*EXP('Read me'!$B$22),"") -> 73.924884
A48: 2:00 | B48: Curragh | C48: Izuzu Ireland Irish European Breeders Fund Maiden | E48: 9 | F48: Heavy | G48: 9 | H48: Warrawood | I48: McCullagh, Scott | J48: McLoughlin, Daniel | K48: 11 | L48: 0 | M48: 2 | O48: 7 | P48: 74.440977 | Q48: 0.013433461 | R48: 67 | S48: =IF(AND(ISNUMBER(R48),R48>1,P48>0),R48/P48-1,"") -> -0.099958084 | T48: =IF(AND(ISNUMBER(P48),P48>0),P48*EXP('Read me'!$B$22),"") -> 90.922415
A49: 2:00 | B49: Curragh | C49: Izuzu Ireland Irish European Breeders Fund Maiden | E49: 9 | F49: Heavy | G49: 9 | H49: Lumierebleu (IRE) | I49: Heffernan, J A | J49: Murtagh, J P | K49: 3 | L49: 0 | M49: 2 | N49: 29 | O49: 8 | P49: 264.02961 | Q49: 0.0037874539 | R49: 201 | S49: =IF(AND(ISNUMBER(R49),R49>1,P49>0),R49/P49-1,"") -> -0.23872176 | T49: =IF(AND(ISNUMBER(P49),P49>0),P49*EXP('Read me'!$B$22),"") -> 322.4865
A50: 2:00 | B50: Curragh | C50: Izuzu Ireland Irish European Breeders Fund Maiden | E50: 9 | F50: Heavy | G50: 9 | H50: Alone All Alone | I50: Whelan, R P | J50: ONeill, E J | K50: 9 | L50: 0 | M50: 2 | N50: 10 | O50: 9 | P50: 979.26571 | Q50: 0.0010211733 | R50: 151 | S50: =IF(AND(ISNUMBER(R50),R50>1,P50>0),R50/P50-1,"") -> -0.84580283 | T50: =IF(AND(ISNUMBER(P50),P50>0),P50*EXP('Read me'!$B$22),"") -> 1196.0778
A51: 2:12 | B51: Epsom | C51: Betfred Derby Wild Card EBF Conditions Stakes (GBB/GBBPlus Race) | D51: Class 2 | E51: 8.5 | F51: Good | G51: 5 | H51: Rose Moon (GER) | I51: Ryan, Rossa | J51: Beckett, R M | K51: 5 | L51: 0 | M51: 2 | N51: 24 | O51: 1 | P51: 3.3125625 | Q51: 0.3018811 | R51: 2.375 | S51: =IF(AND(ISNUMBER(R51),R51>1,P51>0),R51/P51-1,"") -> -0.28303239 | T51: =IF(AND(ISNUMBER(P51),P51>0),P51*EXP('Read me'!$B$22),"") -> 4.0459729
A52: 2:12 | B52: Epsom | C52: Betfred Derby Wild Card EBF Conditions Stakes (GBB/GBBPlus Race) | D52: Class 2 | E52: 8.5 | F52: Good | G52: 5 | H52: Al Wathba (FR) | I52: Loughnane, Billy | J52: Appleby, Charlie | K52: 4 | L52: 89 | M52: 2 | N52: 17 | O52: 2 | P52: 3.524514 | Q52: 0.28372706 | R52: 4 | S52: =IF(AND(ISNUMBER(R52),R52>1,P52>0),R52/P52-1,"") -> 0.13490825 | T52: =IF(AND(ISNUMBER(P52),P52>0),P52*EXP('Read me'!$B$22),"") -> 4.3048511
A53: 2:12 | B53: Epsom | C53: Betfred Derby Wild Card EBF Conditions Stakes (GBB/GBBPlus Race) | D53: Class 2 | E53: 8.5 | F53: Good | G53: 5 | H53: Quite Cheeky (IRE) | I53: Fallon, Cieren | J53: Haggas, W J | K53: 1 | L53: 0 | M53: 2 | N53: 17 | O53: 3 | P53: 5.3391219 | Q53: 0.18729672 | R53: 3.5 | S53: =IF(AND(ISNUMBER(R53),R53>1,P53>0),R53/P53-1,"") -> -0.34446149 | T53: =IF(AND(ISNUMBER(P53),P53>0),P53*EXP('Read me'!$B$22),"") -> 6.5212182
A54: 2:12 | B54: Epsom | C54: Betfred Derby Wild Card EBF Conditions Stakes (GBB/GBBPlus Race) | D54: Class 2 | E54: 8.5 | F54: Good | G54: 5 | H54: Sword Salute (USA) | I54: Scott, Rowan | J54: Johnston, Charlie | K54: 2 | L54: 91 | M54: 2 | N54: 59 | O54: 4 | P54: 8.016342 | Q54: 0.12474518 | R54: 13 | S54: =IF(AND(ISNUMBER(R54),R54>1,P54>0),R54/P54-1,"") -> 0.62168729 | T54: =IF(AND(ISNUMBER(P54),P54>0),P54*EXP('Read me'!$B$22),"") -> 9.7911823
A55: 2:12 | B55: Epsom | C55: Betfred Derby Wild Card EBF Conditions Stakes (GBB/GBBPlus Race) | D55: Class 2 | E55: 8.5 | F55: Good | G55: 5 | H55: Bincimbal (IRE) | I55: Edmunds, Lewis | J55: Charlton, Roger/Harry | K55: 3 | L55: 81 | M55: 2 | N55: 31 | O55: 5 | P55: 9.7704012 | Q55: 0.10234994 | R55: 17 | S55: =IF(AND(ISNUMBER(R55),R55>1,P55>0),R55/P55-1,"") -> 0.73994902 | T55: =IF(AND(ISNUMBER(P55),P55>0),P55*EXP('Read me'!$B$22),"") -> 11.933595
A56: 2:24 | B56: Ffos Las | C56: Bridge, Family Run And Proud Handicap | D56: Class 6 | E56: 5 | F56: Good To Soft | G56: 4 | H56: Call Time (IRE) | I56: Wonnacott, Millie | J56: Moore, J S | K56: 5 | L56: 55 | M56: 5 | N56: 6 | O56: 1 | P56: 1.8816813 | Q56: 0.53143963 | R56: 1.6153846 | S56: =IF(AND(ISNUMBER(R56),R56>1,P56>0),R56/P56-1,"") -> -0.14152059 | T56: =IF(AND(ISNUMBER(P56),P56>0),P56*EXP('Read me'!$B$22),"") -> 2.2982907
A57: 2:24 | B57: Ffos Las | C57: Bridge, Family Run And Proud Handicap | D57: Class 6 | E57: 5 | F57: Good To Soft | G57: 4 | H57: Some Nightmare (IRE) | I57: Carson, William | J57: Oshea, J G M | K57: 1 | L57: 49 | M57: 9 | N57: 15 | O57: 2 | P57: 3.7883785 | Q57: 0.26396518 | R57: 3.75 | S57: =IF(AND(ISNUMBER(R57),R57>1,P57>0),R57/P57-1,"") -> -0.010130581 | T57: =IF(AND(ISNUMBER(P57),P57>0),P57*EXP('Read me'!$B$22),"") -> 4.6271359
A58: 2:24 | B58: Ffos Las | C58: Bridge, Family Run And Proud Handicap | D58: Class 6 | E58: 5 | F58: Good To Soft | G58: 4 | H58: Bama Lama | I58: Osborne, Saffie | J58: Millman, B R | K58: 4 | L58: 45 | M58: 8 | N58: 6 | O58: 3 | P58: 5.6707553 | Q58: 0.17634335 | R58: 5.5 | S58: =IF(AND(ISNUMBER(R58),R58>1,P58>0),R58/P58-1,"") -> -0.03011157 | T58: =IF(AND(ISNUMBER(P58),P58>0),P58*EXP('Read me'!$B$22),"") -> 6.9262762
A59: 2:24 | B59: Ffos Las | C59: Bridge, Family Run And Proud Handicap | D59: Class 6 | E59: 5 | F59: Good To Soft | G59: 4 | H59: Snow Day | I59: Doughty, Jack | J59: Carroll, A W | K59: 2 | L59: 45 | M59: 3 | N59: 27 | O59: 4 | P59: 35.395928 | Q59: 0.028251837 | R59: 23 | S59: =IF(AND(ISNUMBER(R59),R59>1,P59>0),R59/P59-1,"") -> -0.35020774 | T59: =IF(AND(ISNUMBER(P59),P59>0),P59*EXP('Read me'!$B$22),"") -> 43.232684
A60: 2:35 | B60: Curragh | C60: Qatar Racing And Equestrian Club Renaissance Stakes (Group 3) | E60: 6 | F60: Heavy | G60: 8 | H60: Soul Love | I60: Jamin, Pierre-Louis | J60: Burke, K R | K60: 9 | L60: 101 | M60: 3 | N60: 35 | O60: 1 | P60: 3.6569722 | Q60: 0.27345026 | R60: 3.75 | S60: =IF(AND(ISNUMBER(R60),R60>1,P60>0),R60/P60-1,"") -> 0.02543848 | T60: =IF(AND(ISNUMBER(P60),P60>0),P60*EXP('Read me'!$B$22),"") -> 4.4666359
A61: 2:35 | B61: Curragh | C61: Qatar Racing And Equestrian Club Renaissance Stakes (Group 3) | E61: 6 | F61: Heavy | G61: 8 | H61: Power Blue (IRE) | I61: Lee, W J | J61: Aguiar, Robson | K61: 8 | L61: 110 | M61: 3 | N61: 36 | O61: 2 | P61: 4.4795634 | Q61: 0.22323604 | R61: 3.75 | S61: =IF(AND(ISNUMBER(R61),R61>1,P61>0),R61/P61-1,"") -> -0.16286484 | T61: =IF(AND(ISNUMBER(P61),P61>0),P61*EXP('Read me'!$B$22),"") -> 5.471351
A62: 2:35 | B62: Curragh | C62: Qatar Racing And Equestrian Club Renaissance Stakes (Group 3) | E62: 6 | F62: Heavy | G62: 8 | H62: Brussels | I62: Moore, Ryan | J62: OBrien, A P | K62: 2 | L62: 101 | M62: 3 | N62: 14 | O62: 3 | P62: 5.4711503 | Q62: 0.18277692 | R62: 7 | S62: =IF(AND(ISNUMBER(R62),R62>1,P62>0),R62/P62-1,"") -> 0.27943844 | T62: =IF(AND(ISNUMBER(P62),P62>0),P62*EXP('Read me'!$B$22),"") -> 6.682478
A63: 2:35 | B63: Curragh | C63: Qatar Racing And Equestrian Club Renaissance Stakes (Group 3) | E63: 6 | F63: Heavy | G63: 8 | H63: Royal Bay Cen (IRE) | I63: Coen, Ben M | J63: Murtagh, J P | K63: 7 | L63: 104 | M63: 3 | N63: 133 | O63: 4 | P63: 6.2935973 | Q63: 0.15889164 | R63: 3.75 | S63: =IF(AND(ISNUMBER(R63),R63>1,P63>0),R63/P63-1,"") -> -0.40415634 | T63: =IF(AND(ISNUMBER(P63),P63>0),P63*EXP('Read me'!$B$22),"") -> 7.687017
A64: 2:35 | B64: Curragh | C64: Qatar Racing And Equestrian Club Renaissance Stakes (Group 3) | E64: 6 | F64: Heavy | G64: 8 | H64: Charles Darwin (IRE) | I64: Lordan, W M | J64: OBrien, A P | K64: 4 | L64: 103 | M64: 3 | N64: 71 | O64: 5 | P64: 15.720531 | Q64: 0.063611083 | R64: 29 | S64: =IF(AND(ISNUMBER(R64),R64>1,P64>0),R64/P64-1,"") -> 0.84472141 | T64: =IF(AND(ISNUMBER(P64),P64>0),P64*EXP('Read me'!$B$22),"") -> 19.2011
A65: 2:35 | B65: Curragh | C65: Qatar Racing And Equestrian Club Renaissance Stakes (Group 3) | E65: 6 | F65: Heavy | G65: 8 | H65: Big Gossey (IRE) | I65: Whearty, R | J65: OBrien, Charles | K65: 1 | L65: 104 | M65: 9 | N65: 14 | O65: 6 | P65: 22.91847 | Q65: 0.04363293 | R65: 9 | S65: =IF(AND(ISNUMBER(R65),R65>1,P65>0),R65/P65-1,"") -> -0.60730363 | T65: =IF(AND(ISNUMBER(P65),P65>0),P65*EXP('Read me'!$B$22),"") -> 27.992682
A66: 2:35 | B66: Curragh | C66: Qatar Racing And Equestrian Club Renaissance Stakes (Group 3) | E66: 6 | F66: Heavy | G66: 8 | H66: East Hampton | I66: Colgan, R C | J66: Marnane, David | K66: 6 | L66: 104 | M66: 4 | N66: 37 | O66: 7 | P66: 31.253591 | Q66: 0.031996323 | R66: 19 | S66: =IF(AND(ISNUMBER(R66),R66>1,P66>0),R66/P66-1,"") -> -0.39206987 | T66: =IF(AND(ISNUMBER(P66),P66>0),P66*EXP('Read me'!$B$22),"") -> 38.173223
A67: 2:35 | B67: Curragh | C67: Qatar Racing And Equestrian Club Renaissance Stakes (Group 3) | E67: 6 | F67: Heavy | G67: 8 | H67: Tango Flare (IRE) | I67: McAteer, L T | J67: Foley, Patrick T | K67: 3 | L67: 96 | M67: 7 | N67: 14 | O67: 8 | P67: 44.633301 | Q67: 0.022404796 | R67: 34 | S67: =IF(AND(ISNUMBER(R67),R67>1,P67>0),R67/P67-1,"") -> -0.23823693 | T67: =IF(AND(ISNUMBER(P67),P67>0),P67*EXP('Read me'!$B$22),"") -> 54.515237
A68: 2:47 | B68: Epsom | C68: Hunt Family Fund Novice Stakes (Sponsored By Betfred) (GBB Race) | D68: Class 3 | E68: 10 | F68: Good | G68: 6 | H68: Maestro Del Mar (FR) | I68: Loughnane, Billy | J68: Mohammed, Ismail | K68: 5 | L68: 75 | M68: 4 | N68: 24 | O68: 1 | P68: 3.4940533 | Q68: 0.28620056 | R68: 4 | S68: =IF(AND(ISNUMBER(R68),R68>1,P68>0),R68/P68-1,"") -> 0.14480224 | T68: =IF(AND(ISNUMBER(P68),P68>0),P68*EXP('Read me'!$B$22),"") -> 4.2676463
A69: 2:47 | B69: Epsom | C69: Hunt Family Fund Novice Stakes (Sponsored By Betfred) (GBB Race) | D69: Class 3 | E69: 10 | F69: Good | G69: 6 | H69: Rowlf | I69: Fallon, Cieren | J69: Haggas, W J | K69: 3 | L69: 0 | M69: 3 | O69: 2 | P69: 3.9386 | Q69: 0.25389732 | R69: 3.5 | S69: =IF(AND(ISNUMBER(R69),R69>1,P69>0),R69/P69-1,"") -> -0.11135937 | T69: =IF(AND(ISNUMBER(P69),P69>0),P69*EXP('Read me'!$B$22),"") -> 4.810617
A70: 2:47 | B70: Epsom | C70: Hunt Family Fund Novice Stakes (Sponsored By Betfred) (GBB Race) | D70: Class 3 | E70: 10 | F70: Good | G70: 6 | H70: Blue Noon (IRE) | I70: Levey, S M | J70: Hannon (Jnr), Richard | K70: 2 | L70: 74 | M70: 3 | N70: 30 | O70: 3 | P70: 4.0394346 | Q70: 0.2475594 | R70: 2.75 | S70: =IF(AND(ISNUMBER(R70),R70>1,P70>0),R70/P70-1,"") -> -0.31921166 | T70: =IF(AND(ISNUMBER(P70),P70>0),P70*EXP('Read me'!$B$22),"") -> 4.9337766
A71: 2:47 | B71: Epsom | C71: Hunt Family Fund Novice Stakes (Sponsored By Betfred) (GBB Race) | D71: Class 3 | E71: 10 | F71: Good | G71: 6 | H71: Seacole (IRE) | I71: Ryan, Rossa | J71: Beckett, R M | K71: 6 | L71: 73 | M71: 3 | N71: 13 | O71: 4 | P71: 5.6436686 | Q71: 0.17718971 | R71: 6 | S71: =IF(AND(ISNUMBER(R71),R71>1,P71>0),R71/P71-1,"") -> 0.063138263 | T71: =IF(AND(ISNUMBER(P71),P71>0),P71*EXP('Read me'!$B$22),"") -> 6.8931924
A72: 2:47 | B72: Epsom | C72: Hunt Family Fund Novice Stakes (Sponsored By Betfred) (GBB Race) | D72: Class 3 | E72: 10 | F72: Good | G72: 6 | H72: Red Red | I72: Crouch, Hector | J72: Moore, Gary and Josh | K72: 4 | L72: 0 | M72: 3 | O72: 5 | P72: 29.562588 | Q72: 0.033826537 | R72: 19 | S72: =IF(AND(ISNUMBER(R72),R72>1,P72>0),R72/P72-1,"") -> -0.35729579 | T72: =IF(AND(ISNUMBER(P72),P72>0),P72*EXP('Read me'!$B$22),"") -> 36.107827
A73: 2:47 | B73: Epsom | C73: Hunt Family Fund Novice Stakes (Sponsored By Betfred) (GBB Race) | D73: Class 3 | E73: 10 | F73: Good | G73: 6 | H73: Paraone | I73: Wood, George | J73: Main, Mrs H S | K73: 1 | L73: 0 | M73: 3 | N73: 13 | O73: 6 | P73: 753.8789 | Q73: 0.001326473 | R73: 151 | S73: =IF(AND(ISNUMBER(R73),R73>1,P73>0),R73/P73-1,"") -> -0.79970258 | T73: =IF(AND(ISNUMBER(P73),P73>0),P73*EXP('Read me'!$B$22),"") -> 920.78977
A74: 2:59 | B74: Ffos Las | C74: Happy Birthday Alex, From The Bridge Handicap | D74: Class 5 | E74: 16 | F74: Good To Soft | G74: 5 | H74: Campeona | I74: Gilligan, Jack | J74: Prescott, Sir Mark | K74: 3 | L74: 74 | M74: 3 | N74: 22 | O74: 1 | P74: 2.63875 | Q74: 0.37896732 | R74: 2.625 | S74: =IF(AND(ISNUMBER(R74),R74>1,P74>0),R74/P74-1,"") -> -0.00521079 | T74: =IF(AND(ISNUMBER(P74),P74>0),P74*EXP('Read me'!$B$22),"") -> 3.2229765
A75: 2:59 | B75: Ffos Las | C75: Happy Birthday Alex, From The Bridge Handicap | D75: Class 5 | E75: 16 | F75: Good To Soft | G75: 5 | H75: Carthusian (IRE) | I75: Wright, Liam | J75: Candlish, Jennie | K75: 2 | L75: 75 | M75: 4 | N75: 8 | O75: 2 | P75: 3.7148957 | Q75: 0.26918656 | R75: 4 | S75: =IF(AND(ISNUMBER(R75),R75>1,P75>0),R75/P75-1,"") -> 0.076746251 | T75: =IF(AND(ISNUMBER(P75),P75>0),P75*EXP('Read me'!$B$22),"") -> 4.5373838
A76: 2:59 | B76: Ffos Las | C76: Happy Birthday Alex, From The Bridge Handicap | D76: Class 5 | E76: 16 | F76: Good To Soft | G76: 5 | H76: Queenie St Clair (IRE) | I76: Wonnacott, Millie | J76: Scholfield, Nick | K76: 1 | L76: 60 | M76: 6 | N76: 162 | O76: 3 | P76: 4.8242014 | Q76: 0.2072882 | R76: 2.875 | S76: =IF(AND(ISNUMBER(R76),R76>1,P76>0),R76/P76-1,"") -> -0.40404643 | T76: =IF(AND(ISNUMBER(P76),P76>0),P76*EXP('Read me'!$B$22),"") -> 5.8922928
A77: 2:59 | B77: Ffos Las | C77: Happy Birthday Alex, From The Bridge Handicap | D77: Class 5 | E77: 16 | F77: Good To Soft | G77: 5 | H77: A Daughters Love | I77: Probert, David | J77: Flood, D | K77: 5 | L77: 63 | M77: 3 | N77: 6 | O77: 4 | P77: 9.5448334 | Q77: 0.10476872 | R77: 10 | S77: =IF(AND(ISNUMBER(R77),R77>1,P77>0),R77/P77-1,"") -> 0.04768722 | T77: =IF(AND(ISNUMBER(P77),P77>0),P77*EXP('Read me'!$B$22),"") -> 11.658086
A78: 2:59 | B78: Ffos Las | C78: Happy Birthday Alex, From The Bridge Handicap | D78: Class 5 | E78: 16 | F78: Good To Soft | G78: 5 | H78: No Ordinary Joe (IRE) | I78: Marsh, Finley | J78: Stephens, Robert | K78: 4 | L78: 65 | M78: 10 | N78: 15 | O78: 5 | P78: 25.132448 | Q78: 0.0397892 | R78: 13 | S78: =IF(AND(ISNUMBER(R78),R78>1,P78>0),R78/P78-1,"") -> -0.4827404 | T78: =IF(AND(ISNUMBER(P78),P78>0),P78*EXP('Read me'!$B$22),"") -> 30.696841
A79: 3:10 | B79: Curragh | C79: Celebrating County Kildare And Lexington Twinning Maiden | E79: 6 | F79: Heavy | G79: 12 | H79: Valentino Eclipse (IRE) | I79: Heffernan, J A | J79: Stack, J A | K79: 11 | L79: 0 | M79: 3 | N79: 93 | O79: 1 | P79: 2.4347683 | Q79: 0.4107167 | R79: 1.7272727 | S79: =IF(AND(ISNUMBER(R79),R79>1,P79>0),R79/P79-1,"") -> -0.29058024 | T79: =IF(AND(ISNUMBER(P79),P79>0),P79*EXP('Read me'!$B$22),"") -> 2.9738327
A80: 3:10 | B80: Curragh | C80: Celebrating County Kildare And Lexington Twinning Maiden | E80: 6 | F80: Heavy | G80: 12 | H80: A Good Yarn (IRE) | I80: Lordan, W M | J80: Howard, Aidan Anthony | K80: 1 | L80: 0 | M80: 3 | N80: 161 | O80: 2 | P80: 3.5987295 | Q80: 0.27787584 | R80: 3.5 | S80: =IF(AND(ISNUMBER(R80),R80>1,P80>0),R80/P80-1,"") -> -0.027434553 | T80: =IF(AND(ISNUMBER(P80),P80>0),P80*EXP('Read me'!$B$22),"") -> 4.3954982
A81: 3:10 | B81: Curragh | C81: Celebrating County Kildare And Lexington Twinning Maiden | E81: 6 | F81: Heavy | G81: 12 | H81: Tourin (IRE) | I81: Ryan, Gavin | J81: Stack, J A | K81: 12 | L81: 0 | M81: 3 | N81: 26 | O81: 3 | P81: 7.1742156 | Q81: 0.13938806 | R81: 9 | S81: =IF(AND(ISNUMBER(R81),R81>1,P81>0),R81/P81-1,"") -> 0.25449254 | T81: =IF(AND(ISNUMBER(P81),P81>0),P81*EXP('Read me'!$B$22),"") -> 8.7626068
A82: 3:10 | B82: Curragh | C82: Celebrating County Kildare And Lexington Twinning Maiden | E82: 6 | F82: Heavy | G82: 12 | H82: The Hidden Garden (IRE) | I82: McDonogh, D P | J82: Harty, Edward and Patrick | K82: 13 | L82: 0 | M82: 3 | O82: 4 | P82: 14.010672 | Q82: 0.071374163 | R82: 26 | S82: =IF(AND(ISNUMBER(R82),R82>1,P82>0),R82/P82-1,"") -> 0.85572823 | T82: =IF(AND(ISNUMBER(P82),P82>0),P82*EXP('Read me'!$B$22),"") -> 17.112674
A83: 3:10 | B83: Curragh | C83: Celebrating County Kildare And Lexington Twinning Maiden | E83: 6 | F83: Heavy | G83: 12 | H83: Saga Lucia (IRE) | I83: Holohan, Reese | J83: OCallaghan, M D | K83: 6 | L83: 73 | M83: 3 | N83: 37 | O83: 5 | P83: 34.106586 | Q83: 0.029319851 | R83: 13 | S83: =IF(AND(ISNUMBER(R83),R83>1,P83>0),R83/P83-1,"") -> -0.61884194 | T83: =IF(AND(ISNUMBER(P83),P83>0),P83*EXP('Read me'!$B$22),"") -> 41.657878
A84: 3:10 | B84: Curragh | C84: Celebrating County Kildare And Lexington Twinning Maiden | E84: 6 | F84: Heavy | G84: 12 | H84: Port Arthur (IRE) | I84: Colgan, R C | J84: Grassick, M C | K84: 7 | L84: 74 | M84: 3 | N84: 12 | O84: 6 | P84: 35.727312 | Q84: 0.027989791 | R84: 21 | S84: =IF(AND(ISNUMBER(R84),R84>1,P84>0),R84/P84-1,"") -> -0.41221439 | T84: =IF(AND(ISNUMBER(P84),P84>0),P84*EXP('Read me'!$B$22),"") -> 43.637438
A85: 3:10 | B85: Curragh | C85: Celebrating County Kildare And Lexington Twinning Maiden | E85: 6 | F85: Heavy | G85: 12 | H85: Caislean Ni Cuan (IRE) | I85: McCullagh, N G | J85: Mullins, Thomas | K85: 2 | L85: 57 | M85: 3 | N85: 36 | O85: 7 | P85: 40.791335 | Q85: 0.02451501 | R85: 23 | S85: =IF(AND(ISNUMBER(R85),R85>1,P85>0),R85/P85-1,"") -> -0.43615476 | T85: =IF(AND(ISNUMBER(P85),P85>0),P85*EXP('Read me'!$B$22),"") -> 49.822649
A86: 3:10 | B86: Curragh | C86: Celebrating County Kildare And Lexington Twinning Maiden | E86: 6 | F86: Heavy | G86: 12 | H86: Tribal Belle (IRE) | I86: Hayes, C D | J86: Bunyan, Darren / OLeary, G | K86: 4 | L86: 0 | M86: 3 | N86: 26 | O86: 8 | P86: 107.1561 | Q86: 0.0093321802 | R86: 34 | S86: =IF(AND(ISNUMBER(R86),R86>1,P86>0),R86/P86-1,"") -> -0.68270587 | T86: =IF(AND(ISNUMBER(P86),P86>0),P86*EXP('Read me'!$B$22),"") -> 130.88075
A87: 3:10 | B87: Curragh | C87: Celebrating County Kildare And Lexington Twinning Maiden | E87: 6 | F87: Heavy | G87: 12 | H87: Gaineamh Min (IRE) | I87: Joyce, Wesley | J87: Byrne, Sean | K87: 10 | L87: 0 | M87: 3 | N87: 23 | O87: 9 | P87: 265.76376 | Q87: 0.0037627403 | R87: 41 | S87: =IF(AND(ISNUMBER(R87),R87>1,P87>0),R87/P87-1,"") -> -0.84572765 | T87: =IF(AND(ISNUMBER(P87),P87>0),P87*EXP('Read me'!$B$22),"") -> 324.60458
A88: 3:10 | B88: Curragh | C88: Celebrating County Kildare And Lexington Twinning Maiden | E88: 6 | F88: Heavy | G88: 12 | H88: Spider Star (IRE) | I88: Browne-Souza, A | J88: Kelly, David Harry | K88: 3 | L88: 0 | M88: 3 | N88: 28 | O88: 10 | P88: 386.81483 | Q88: 0.0025852163 | R88: 126 | S88: =IF(AND(ISNUMBER(R88),R88>1,P88>0),R88/P88-1,"") -> -0.67426275 | T88: =IF(AND(ISNUMBER(P88),P88>0),P88*EXP('Read me'!$B$22),"") -> 472.4567
A89: 3:10 | B89: Curragh | C89: Celebrating County Kildare And Lexington Twinning Maiden | E89: 6 | F89: Heavy | G89: 12 | H89: Upper West Side (IRE) | I89: Ryan, J J G | J89: Lynam, Edward | K89: 14 | L89: 0 | M89: 5 | N89: 18 | O89: 11 | P89: 573.55532 | Q89: 0.001743511 | R89: 126 | S89: =IF(AND(ISNUMBER(R89),R89>1,P89>0),R89/P89-1,"") -> -0.78031761 | T89: =IF(AND(ISNUMBER(P89),P89>0),P89*EXP('Read me'!$B$22),"") -> 700.54205
A90: 3:10 | B90: Curragh | C90: Celebrating County Kildare And Lexington Twinning Maiden | E90: 6 | F90: Heavy | G90: 12 | H90: Petticoat Pilot (IRE) | I90: OSullivan, Darragh | J90: Finn, David Edward | K90: 8 | L90: 0 | M90: 5 | N90: 793 | O90: 12 | P90: 715.85325 | Q90: 0.0013969344 | R90: 126 | S90: =IF(AND(ISNUMBER(R90),R90>1,P90>0),R90/P90-1,"") -> -0.82398627 | T90: =IF(AND(ISNUMBER(P90),P90>0),P90*EXP('Read me'!$B$22),"") -> 874.34513
A91: 3:22 | B91: Epsom | C91: Betfred Nifty 50 Jump Jockeys Derby Handicap (Professional Jump Jockeys) (GBBPlus Race) | D91: Class 4 | E91: 12 | F91: Good | G91: 13 | H91: Seeking Charles (FR) | I91: Davies, James | J91: Usher, M D I | K91: 11 | L91: 75 | M91: 5 | N91: 27 | O91: 1 | P91: 4.8890414 | Q91: 0.20453907 | R91: 4.5 | S91: =IF(AND(ISNUMBER(R91),R91>1,P91>0),R91/P91-1,"") -> -0.079574171 | T91: =IF(AND(ISNUMBER(P91),P91>0),P91*EXP('Read me'!$B$22),"") -> 5.9714887
A92: 3:22 | B92: Epsom | C92: Betfred Nifty 50 Jump Jockeys Derby Handicap (Professional Jump Jockeys) (GBBPlus Race) | D92: Class 4 | E92: 12 | F92: Good | G92: 13 | H92: Nibras Gold (IRE) | I92: Burke, Jonathan | J92: Owen, J P | K92: 3 | L92: 79 | M92: 8 | N92: 15 | O92: 2 | P92: 6.9023838 | Q92: 0.14487748 | R92: 8 | S92: =IF(AND(ISNUMBER(R92),R92>1,P92>0),R92/P92-1,"") -> 0.15901988 | T92: =IF(AND(ISNUMBER(P92),P92>0),P92*EXP('Read me'!$B$22),"") -> 8.4305906
A93: 3:22 | B93: Epsom | C93: Betfred Nifty 50 Jump Jockeys Derby Handicap (Professional Jump Jockeys) (GBBPlus Race) | D93: Class 4 | E93: 12 | F93: Good | G93: 13 | H93: Tiger (FR) | I93: Cobden, Harry | J93: Williams, Ian | K93: 8 | L93: 84 | M93: 4 | N93: 28 | O93: 3 | P93: 7.2981959 | Q93: 0.13702016 | R93: 8 | S93: =IF(AND(ISNUMBER(R93),R93>1,P93>0),R93/P93-1,"") -> 0.096161312 | T93: =IF(AND(ISNUMBER(P93),P93>0),P93*EXP('Read me'!$B$22),"") -> 8.9140366
A94: 3:22 | B94: Epsom | C94: Betfred Nifty 50 Jump Jockeys Derby Handicap (Professional Jump Jockeys) (GBBPlus Race) | D94: Class 4 | E94: 12 | F94: Good | G94: 13 | H94: Fox Avatar (IRE) | I94: Powell, Brendan | J94: Varian, Roger | K94: 12 | L94: 81 | M94: 5 | N94: 18 | O94: 4 | P94: 7.6624859 | Q94: 0.13050595 | R94: 7.5 | S94: =IF(AND(ISNUMBER(R94),R94>1,P94>0),R94/P94-1,"") -> -0.02120538 | T94: =IF(AND(ISNUMBER(P94),P94>0),P94*EXP('Read me'!$B$22),"") -> 9.3589814
A95: 3:22 | B95: Epsom | C95: Betfred Nifty 50 Jump Jockeys Derby Handicap (Professional Jump Jockeys) (GBBPlus Race) | D95: Class 4 | E95: 12 | F95: Good | G95: 13 | H95: Damascus Steel (IRE) | I95: Hughes, Brian | J95: Arnolda, Gihan | K95: 9 | L95: 77 | M95: 6 | N95: 15 | O95: 5 | P95: 15.267406 | Q95: 0.065499009 | R95: 12 | S95: =IF(AND(ISNUMBER(R95),R95>1,P95>0),R95/P95-1,"") -> -0.21401189 | T95: =IF(AND(ISNUMBER(P95),P95>0),P95*EXP('Read me'!$B$22),"") -> 18.647652
A96: 3:22 | B96: Epsom | C96: Betfred Nifty 50 Jump Jockeys Derby Handicap (Professional Jump Jockeys) (GBBPlus Race) | D96: Class 4 | E96: 12 | F96: Good | G96: 13 | H96: Marnier (IRE) | I96: Quinn, Caoilin | J96: Moore, Gary and Josh | K96: 10 | L96: 86 | M96: 4 | N96: 28 | O96: 6 | P96: 16.774456 | Q96: 0.059614453 | R96: 6.5 | S96: =IF(AND(ISNUMBER(R96),R96>1,P96>0),R96/P96-1,"") -> -0.61250606 | T96: =IF(AND(ISNUMBER(P96),P96>0),P96*EXP('Read me'!$B$22),"") -> 20.488367
A97: 3:22 | B97: Epsom | C97: Betfred Nifty 50 Jump Jockeys Derby Handicap (Professional Jump Jockeys) (GBBPlus Race) | D97: Class 4 | E97: 12 | F97: Good | G97: 13 | H97: Zarakerjack (FR) | I97: Mitchell, Freddie | J97: Moore, Gary and Josh | K97: 7 | L97: 70 | M97: 4 | N97: 13 | O97: 7 | P97: 17.731917 | Q97: 0.056395481 | R97: 12 | S97: =IF(AND(ISNUMBER(R97),R97>1,P97>0),R97/P97-1,"") -> -0.32325423 | T97: =IF(AND(ISNUMBER(P97),P97>0),P97*EXP('Read me'!$B$22),"") -> 21.657813
A98: 3:22 | B98: Epsom | C98: Betfred Nifty 50 Jump Jockeys Derby Handicap (Professional Jump Jockeys) (GBBPlus Race) | D98: Class 4 | E98: 12 | F98: Good | G98: 13 | H98: Oneforthegutter | I98: Todd, C J | J98: Williams, Ian | K98: 6 | L98: 82 | M98: 7 | N98: 8 | O98: 8 | P98: 21.725843 | Q98: 0.046028132 | R98: 11 | S98: =IF(AND(ISNUMBER(R98),R98>1,P98>0),R98/P98-1,"") -> -0.49369054 | T98: =IF(AND(ISNUMBER(P98),P98>0),P98*EXP('Read me'!$B$22),"") -> 26.536005
A99: 3:22 | B99: Epsom | C99: Betfred Nifty 50 Jump Jockeys Derby Handicap (Professional Jump Jockeys) (GBBPlus Race) | D99: Class 4 | E99: 12 | F99: Good | G99: 13 | H99: Taritino (IRE) | I99: Fisher, Taylor | J99: Tickle, J | K99: 1 | L99: 75 | M99: 6 | N99: 14 | O99: 9 | P99: 26.356445 | Q99: 0.037941384 | R99: 15 | S99: =IF(AND(ISNUMBER(R99),R99>1,P99>0),R99/P99-1,"") -> -0.43087924 | T99: =IF(AND(ISNUMBER(P99),P99>0),P99*EXP('Read me'!$B$22),"") -> 32.191835
A100: 3:22 | B100: Epsom | C100: Betfred Nifty 50 Jump Jockeys Derby Handicap (Professional Jump Jockeys) (GBBPlus Race) | D100: Class 4 | E100: 12 | F100: Good | G100: 13 | H100: Gordon Grey (IRE) | I100: Cannon, Tom J | J100: Baker, George | K100: 5 | L100: 83 | M100: 6 | N100: 17 | O100: 10 | P100: 27.921993 | Q100: 0.035814062 | R100: 13 | S100: =IF(AND(ISNUMBER(R100),R100>1,P100>0),R100/P100-1,"") -> -0.53441719 | T100: =IF(AND(ISNUMBER(P100),P100>0),P100*EXP('Read me'!$B$22),"") -> 34.104
A101: 3:22 | B101: Epsom | C101: Betfred Nifty 50 Jump Jockeys Derby Handicap (Professional Jump Jockeys) (GBBPlus Race) | D101: Class 4 | E101: 12 | F101: Good | G101: 13 | H101: Hengest | I101: Edwards, Lee | J101: Cunha, Dylan | K101: 2 | L101: 79 | M101: 4 | N101: 8 | O101: 11 | P101: 29.472138 | Q101: 0.033930351 | R101: 21 | S101: =IF(AND(ISNUMBER(R101),R101>1,P101>0),R101/P101-1,"") -> -0.28746262 | T101: =IF(AND(ISNUMBER(P101),P101>0),P101*EXP('Read me'!$B$22),"") -> 35.997351
A102: 3:22 | B102: Epsom | C102: Betfred Nifty 50 Jump Jockeys Derby Handicap (Professional Jump Jockeys) (GBBPlus Race) | D102: Class 4 | E102: 12 | F102: Good | G102: 13 | H102: Flash Man (FR) | I102: Brogan, Kevin | J102: Lawes, T | K102: 4 | L102: 78 | M102: 4 | N102: 126 | O102: 12 | P102: 39.908989 | Q102: 0.025057012 | R102: 41 | S102: =IF(AND(ISNUMBER(R102),R102>1,P102>0),R102/P102-1,"") -> 0.027337477 | T102: =IF(AND(ISNUMBER(P102),P102>0),P102*EXP('Read me'!$B$22),"") -> 48.744949
A103: 3:22 | B103: Epsom | C103: Betfred Nifty 50 Jump Jockeys Derby Handicap (Professional Jump Jockeys) (GBBPlus Race) | D103: Class 4 | E103: 12 | F103: Good | G103: 13 | H103: Oasis Sunrise (IRE) | I103: Anderson, Joe | J103: Harris, Miss G | K103: 13 | L103: 68 | M103: 4 | N103: 19 | O103: 13 | P103: 43.903081 | Q103: 0.022777445 | R103: 26 | S103: =IF(AND(ISNUMBER(R103),R103>1,P103>0),R103/P103-1,"") -> -0.40778643 | T103: =IF(AND(ISNUMBER(P103),P103>0),P103*EXP('Read me'!$B$22),"") -> 53.623344
...

Sheet Ffos Las
A1: Time | B1: Course | C1: Race | D1: Class | E1: Furlongs | F1: Going | G1: Runners | H1: Horse | I1: Jockey | J1: Trainer | K1: Draw | L1: OR | M1: Age | N1: Days since run | O1: Model rank | P1: Predicted BSP | Q1: Win probability | R1: Card odds (HRB) | S1: Card odds vs model | T1: Rule: back at Betfair ≥
A2: 1:19 | B2: Ffos Las | C2: Alex And Salvo Welcome You To The Bridge Handicap | D2: Class 6 | E2: 6 | F2: Good To Soft | G2: 11 | H2: Sub Thirteen | I2: Hutchinson, Callum | J2: Scott, J | K2: 9 | L2: 53 | M2: 5 | N2: 14 | O2: 1 | P2: 3.0244583 | Q2: 0.33063772 | R2: 3.25 | S2: =IF(AND(ISNUMBER(R2),R2>1,P2>0),R2/P2-1,"") -> 0.074572576 | T2: =IF(AND(ISNUMBER(P2),P2>0),P2*EXP('Read me'!$B$22),"") -> 3.6940818
A3: 1:19 | B3: Ffos Las | C3: Alex And Salvo Welcome You To The Bridge Handicap | D3: Class 6 | E3: 6 | F3: Good To Soft | G3: 11 | H3: Macarone | I3: Ffrench Davis, Ben | J3: Harris, Miss G | K3: 8 | L3: 52 | M3: 5 | N3: 15 | O3: 2 | P3: 4.3312252 | Q3: 0.23088155 | R3: 4 | S3: =IF(AND(ISNUMBER(R3),R3>1,P3>0),R3/P3-1,"") -> -0.07647378 | T3: =IF(AND(ISNUMBER(P3),P3>0),P3*EXP('Read me'!$B$22),"") -> 5.2901704
A4: 1:19 | B4: Ffos Las | C4: Alex And Salvo Welcome You To The Bridge Handicap | D4: Class 6 | E4: 6 | F4: Good To Soft | G4: 11 | H4: Blue Point Express (IRE) | I4: Marsh, Finley | J4: Wintle, A | K4: 7 | L4: 45 | M4: 4 | N4: 27 | O4: 3 | P4: 7.187645 | Q4: 0.13912763 | R4: 6 | S4: =IF(AND(ISNUMBER(R4),R4>1,P4>0),R4/P4-1,"") -> -0.16523424 | T4: =IF(AND(ISNUMBER(P4),P4>0),P4*EXP('Read me'!$B$22),"") -> 8.7790095
A5: 1:19 | B5: Ffos Las | C5: Alex And Salvo Welcome You To The Bridge Handicap | D5: Class 6 | E5: 6 | F5: Good To Soft | G5: 11 | H5: Up The Anti (IRE) | I5: Coppins, Myla | J5: Carroll, A W | K5: 6 | L5: 53 | M5: 4 | N5: 25 | O5: 4 | P5: 10.055959 | Q5: 0.099443529 | R5: 8 | S5: =IF(AND(ISNUMBER(R5),R5>1,P5>0),R5/P5-1,"") -> -0.20445177 | T5: =IF(AND(ISNUMBER(P5),P5>0),P5*EXP('Read me'!$B$22),"") -> 12.282375
A6: 1:19 | B6: Ffos Las | C6: Alex And Salvo Welcome You To The Bridge Handicap | D6: Class 6 | E6: 6 | F6: Good To Soft | G6: 11 | H6: Music And Song (IRE) | I6: Probert, David | J6: Flood, D | K6: 5 | L6: 45 | M6: 3 | N6: 5 | O6: 5 | P6: 15.63988 | Q6: 0.063939107 | R6: 10 | S6: =IF(AND(ISNUMBER(R6),R6>1,P6>0),R6/P6-1,"") -> -0.36060893 | T6: =IF(AND(ISNUMBER(P6),P6>0),P6*EXP('Read me'!$B$22),"") -> 19.102593
A7: 1:19 | B7: Ffos Las | C7: Alex And Salvo Welcome You To The Bridge Handicap | D7: Class 6 | E7: 6 | F7: Good To Soft | G7: 11 | H7: The Bear Of Saints (FR) | I7: Carson, William | J7: Oshea, J G M | K7: 4 | L7: 54 | M7: 4 | N7: 34 | O7: 6 | P7: 16.543067 | Q7: 0.060448284 | R7: 15 | S7: =IF(AND(ISNUMBER(R7),R7>1,P7>0),R7/P7-1,"") -> -0.093275736 | T7: =IF(AND(ISNUMBER(P7),P7>0),P7*EXP('Read me'!$B$22),"") -> 20.205747
A8: 1:19 | B8: Ffos Las | C8: Alex And Salvo Welcome You To The Bridge Handicap | D8: Class 6 | E8: 6 | F8: Good To Soft | G8: 11 | H8: Pacific Prince | I8: Coughlan, Laura | J8: Bennett, J A | K8: 11 | L8: 45 | M8: 5 | N8: 20 | O8: 7 | P8: 44.329774 | Q8: 0.022558202 | R8: 41 | S8: =IF(AND(ISNUMBER(R8),R8>1,P8>0),R8/P8-1,"") -> -0.075113712 | T8: =IF(AND(ISNUMBER(P8),P8>0),P8*EXP('Read me'!$B$22),"") -> 54.144508
A9: 1:19 | B9: Ffos Las | C9: Alex And Salvo Welcome You To The Bridge Handicap | D9: Class 6 | E9: 6 | F9: Good To Soft | G9: 11 | H9: Savvi Row | I9: Heard, Tyler | J9: Millman, B R | K9: 12 | L9: 45 | M9: 3 | N9: 15 | O9: 8 | P9: 59.529493 | Q9: 0.016798396 | R9: 34 | S9: =IF(AND(ISNUMBER(R9),R9>1,P9>0),R9/P9-1,"") -> -0.42885454 | T9: =IF(AND(ISNUMBER(P9),P9>0),P9*EXP('Read me'!$B$22),"") -> 72.709487
A10: 1:19 | B10: Ffos Las | C10: Alex And Salvo Welcome You To The Bridge Handicap | D10: Class 6 | E10: 6 | F10: Good To Soft | G10: 11 | H10: Shush A Minute | I10: Bradley, Paddy | J10: Ryan, J | K10: 1 | L10: 50 | M10: 3 | N10: 306 | O10: 9 | P10: 62.476468 | Q10: 0.016006026 | R10: 7 | S10: =IF(AND(ISNUMBER(R10),R10>1,P10>0),R10/P10-1,"") -> -0.88795782 | T10: =IF(AND(ISNUMBER(P10),P10>0),P10*EXP('Read me'!$B$22),"") -> 76.308931
A11: 1:19 | B11: Ffos Las | C11: Alex And Salvo Welcome You To The Bridge Handicap | D11: Class 6 | E11: 6 | F11: Good To Soft | G11: 11 | H11: Lochaber | I11: ONeill, K T | J11: Dixon, Scott | K11: 10 | L11: 45 | M11: 5 | N11: 14 | O11: 10 | P11: 63.912016 | Q11: 0.01564651 | R11: 51 | S11: =IF(AND(ISNUMBER(R11),R11>1,P11>0),R11/P11-1,"") -> -0.20202799 | T11: =IF(AND(ISNUMBER(P11),P11>0),P11*EXP('Read me'!$B$22),"") -> 78.062313
A12: 1:19 | B12: Ffos Las | C12: Alex And Salvo Welcome You To The Bridge Handicap | D12: Class 6 | E12: 6 | F12: Good To Soft | G12: 11 | H12: Miss Gold | I12: Sayette, B D L | J12: Flood, D | K12: 2 | L12: 45 | M12: 3 | N12: 46 | O12: 11 | P12: 221.57978 | Q12: 0.0045130472 | R12: 81 | S12: =IF(AND(ISNUMBER(R12),R12>1,P12>0),R12/P12-1,"") -> -0.63444318 | T12: =IF(AND(ISNUMBER(P12),P12>0),P12*EXP('Read me'!$B$22),"") -> 270.63815
A13: 1:49 | B13: Ffos Las | C13: Bridge, The Home Of The Carvery Nursery | D13: Class 5 | E13: 5 | F13: Good To Soft | G13: 8 | H13: Rhodes Runner (IRE) | I13: Clutterbuck, Rhys | J13: Beckett, R M | K13: 4 | L13: 75 | M13: 2 | N13: 8 | O13: 1 | P13: 4.9613223 | Q13: 0.20155917 | R13: 3.75 | S13: =IF(AND(ISNUMBER(R13),R13>1,P13>0),R13/P13-1,"") -> -0.24415311 | T13: =IF(AND(ISNUMBER(P13),P13>0),P13*EXP('Read me'!$B$22),"") -> 6.0597727
... A29: 2:59 | B29: Ffos Las | C29: Happy Birthday Alex, From The Bridge Handicap | D29: Class 5 | E29: 16 | F29: Good To Soft | G29: 5 | H29: No Ordinary Joe (IRE) | I29: Marsh, Finley | J29: Stephens, Robert | K29: 4 | L29: 65 | M29: 10 | N29: 15 | O29: 5 | P29: 25.132448 | Q29: 0.0397892 | R29: 13 | S29: =IF(AND(ISNUMBER(R29),R29>1,P29>0),R29/P29-1,"") -> -0.4827404 | T29: =IF(AND(ISNUMBER(P29),P29>0),P29*EXP('Read me'!$B$22),"") -> 30.696841
A30: 3:34 | B30: Ffos Las | C30: Celebrate In Style At The Bridge Novice Stakes (GBB Race) | D30: Class 3 | F30: Good To Soft | G30: 5 | H30: Silent Force (IRE) | I30: Hutchinson, Callum | J30: Balding, A M | K30: 2 | L30: 0 | M30: 2 | N30: 43 | O30: 1 | P30: 1.720155 | Q30: 0.58134297 | R30: 1.3636364 | S30: =IF(AND(ISNUMBER(R30),R30>1,P30>0),R30/P30-1,"") -> -0.20725958 | T30: =IF(AND(ISNUMBER(P30),P30>0),P30*EXP('Read me'!$B$22),"") -> 2.101002
A31: 3:34 | B31: Ffos Las | C31: Celebrate In Style At The Bridge Novice Stakes (GBB Race) | D31: Class 3 | F31: Good To Soft | G31: 5 | H31: Ghost Raider (IRE) | I31: Clutterbuck, Rhys | J31: Beckett, R M | K31: 5 | L31: 77 | M31: 2 | N31: 21 | O31: 2 | P31: 2.8890443 | Q31: 0.34613522 | R31: 3.25 | S31: =IF(AND(ISNUMBER(R31),R31>1,P31>0),R31/P31-1,"") -> 0.12493947 | T31: =IF(AND(ISNUMBER(P31),P31>0),P31*EXP('Read me'!$B$22),"") -> 3.5286867
A32: 3:34 | B32: Ffos Las | C32: Celebrate In Style At The Bridge Novice Stakes (GBB Race) | D32: Class 3 | F32: Good To Soft | G32: 5 | H32: Naval Empire (IRE) | I32: Doughty, Jack | J32: Williams, S C | K32: 3 | L32: 0 | M32: 2 | O32: 3 | P32: 35.458939 | Q32: 0.028201633 | R32: 13 | S32: =IF(AND(ISNUMBER(R32),R32>1,P32>0),R32/P32-1,"") -> -0.63337877 | T32: =IF(AND(ISNUMBER(P32),P32>0),P32*EXP('Read me'!$B$22),"") -> 43.309646
A33: 3:34 | B33: Ffos Las | C33: Celebrate In Style At The Bridge Novice Stakes (GBB Race) | D33: Class 3 | F33: Good To Soft | G33: 5 | H33: Time Glory (IRE) | I33: Probert, David | J33: Llewellyn, B J | K33: 4 | L33: 65 | M33: 2 | N33: 29 | O33: 4 | P33: 42.061684 | Q33: 0.023774607 | R33: 29 | S33: =IF(AND(ISNUMBER(R33),R33>1,P33>0),R33/P33-1,"") -> -0.3105364 | T33: =IF(AND(ISNUMBER(P33),P33>0),P33*EXP('Read me'!$B$22),"") -> 51.374257
A34: 3:34 | B34: Ffos Las | C34: Celebrate In Style At The Bridge Novice Stakes (GBB Race) | D34: Class 3 | F34: Good To Soft | G34: 5 | H34: Fourth Crusade (IRE) | I34: Gilligan, Jack | J34: Prescott, Sir Mark | K34: 1 | L34: 0 | M34: 2 | N34: 17 | O34: 5 | P34: 48.672304 | Q34: 0.020545565 | R34: 23 | S34: =IF(AND(ISNUMBER(R34),R34>1,P34>0),R34/P34-1,"") -> -0.527452 | T34: =IF(AND(ISNUMBER(P34),P34>0),P34*EXP('Read me'!$B$22),"") -> 59.448486
A35: 4:09 | B35: Ffos Las | C35: Bridge, For All Family Occasions Handicap (Div 1) | D35: Class 6 | E35: 8 | F35: Good To Soft | G35: 9 | H35: Homeland | I35: Marsh, Finley | J35: Faulkner, T | K35: 7 | L35: 56 | M35: 4 | N35: 27 | O35: 1 | P35: 4.8554186 | Q35: 0.20595546 | R35: 5 | S35: =IF(AND(ISNUMBER(R35),R35>1,P35>0),R35/P35-1,"") -> 0.029777321 | T35: =IF(AND(ISNUMBER(P35),P35>0),P35*EXP('Read me'!$B$22),"") -> 5.9304217
A36: 4:09 | B36: Ffos Las | C36: Bridge, For All Family Occasions Handicap (Div 1) | D36: Class 6 | E36: 8 | F36: Good To Soft | G36: 9 | H36: Rosemarys Rose (IRE) | I36: Osborne, Saffie | J36: Millman, B R | K36: 6 | L36: 58 | M36: 4 | N36: 29 | O36: 2 | P36: 5.4159125 | Q36: 0.18464109 | R36: 4.5 | S36: =IF(AND(ISNUMBER(R36),R36>1,P36>0),R36/P36-1,"") -> -0.16911509 | T36: =IF(AND(ISNUMBER(P36),P36>0),P36*EXP('Read me'!$B$22),"") -> 6.6150105
A37: 4:09 | B37: Ffos Las | C37: Bridge, For All Family Occasions Handicap (Div 1) | D37: Class 6 | E37: 8 | F37: Good To Soft | G37: 9 | H37: Scarfo (IRE) | I37: Tucker, Charlie | J37: Llewellyn, B J | K37: 3 | L37: 55 | M37: 5 | N37: 6 | O37: 3 | P37: 6.1514869 | Q37: 0.16256232 | R37: 5 | S37: =IF(AND(ISNUMBER(R37),R37>1,P37>0),R37/P37-1,"") -> -0.18718839 | T37: =IF(AND(ISNUMBER(P37),P37>0),P37*EXP('Read me'!$B$22),"") -> 7.5134431
A38: 4:09 | B38: Ffos Las | C38: Bridge, For All Family Occasions Handicap (Div 1) | D38: Class 6 | E38: 8 | F38: Good To Soft | G38: 9 | H38: Grand Vista (IRE) | I38: Bradley, Paddy | J38: Muir, W R & Grassick, C | K38: 4 | L38: 53 | M38: 3 | N38: 32 | O38: 4 | P38: 9.6766345 | Q38: 0.10334171 | R38: 10 | S38: =IF(AND(ISNUMBER(R38),R38>1,P38>0),R38/P38-1,"") -> 0.033417145 | T38: =IF(AND(ISNUMBER(P38),P38>0),P38*EXP('Read me'!$B$22),"") -> 11.819068
A39: 4:09 | B39: Ffos Las | C39: Bridge, For All Family Occasions Handicap (Div 1) | D39: Class 6 | E39: 8 | F39: Good To Soft | G39: 9 | H39: A Rose Adaay | I39: Ffrench Davis, Ben | J39: Harris, Miss G | K39: 8 | L39: 50 | M39: 4 | N39: 15 | O39: 5 | P39: 11.048524 | Q39: 0.090509824 | R39: 15 | S39: =IF(AND(ISNUMBER(R39),R39>1,P39>0),R39/P39-1,"") -> 0.35764737 | T39: =IF(AND(ISNUMBER(P39),P39>0),P39*EXP('Read me'!$B$22),"") -> 13.494698
A40: 4:09 | B40: Ffos Las | C40: Bridge, For All Family Occasions Handicap (Div 1) | D40: Class 6 | E40: 8 | F40: Good To Soft | G40: 9 | H40: Cosmic Girl | I40: Hutchinson, Callum | J40: Balding, A M | K40: 9 | L40: 58 | M40: 3 | N40: 18 | O40: 6 | P40: 12.439083 | Q40: 0.08039178 | R40: 9.5 | S40: =IF(AND(ISNUMBER(R40),R40>1,P40>0),R40/P40-1,"") -> -0.23627809 | T40: =IF(AND(ISNUMBER(P40),P40>0),P40*EXP('Read me'!$B$22),"") -> 15.19313
A41: 4:09 | B41: Ffos Las | C41: Bridge, For All Family Occasions Handicap (Div 1) | D41: Class 6 | E41: 8 | F41: Good To Soft | G41: 9 | H41: Prince Ali | I41: Lewis, Zoe | J41: Faulkner, T | K41: 1 | L41: 57 | M41: 8 | N41: 27 | O41: 7 | P41: 15.487309 | Q41: 0.064568997 | R41: 6.5 | S41: =IF(AND(ISNUMBER(R41),R41>1,P41>0),R41/P41-1,"") -> -0.58030152 | T41: =IF(AND(ISNUMBER(P41),P41>0),P41*EXP('Read me'!$B$22),"") -> 18.916242
A42: 4:09 | B42: Ffos Las | C42: Bridge, For All Family Occasions Handicap (Div 1) | D42: Class 6 | E42: 8 | F42: Good To Soft | G42: 9 | H42: Pebble Dash (IRE) | I42: ONeill, K T | J42: Llewellyn, B J | K42: 2 | L42: 46 | M42: 4 | N42: 6 | O42: 8 | P42: 17.62177 | Q42: 0.056747988 | R42: 13 | S42: =IF(AND(ISNUMBER(R42),R42>1,P42>0),R42/P42-1,"") -> -0.26227616 | T42: =IF(AND(ISNUMBER(P42),P42>0),P42*EXP('Read me'!$B$22),"") -> 21.523279
A43: 4:09 | B43: Ffos Las | C43: Bridge, For All Family Occasions Handicap (Div 1) | D43: Class 6 | E43: 8 | F43: Good To Soft | G43: 9 | H43: Thestral | I43: Coppins, Myla | J43: Carroll, A W | K43: 10 | L43: 60 | M43: 3 | N43: 54 | O43: 9 | P43: 19.500469 | Q43: 0.051280818 | R43: 21 | S43: =IF(AND(ISNUMBER(R43),R43>1,P43>0),R43/P43-1,"") -> 0.076897174 | T43: =IF(AND(ISNUMBER(P43),P43>0),P43*EXP('Read me'!$B$22),"") -> 23.817927
A44: 4:44 | B44: Ffos Las | C44: Bridge, For All Family Occasions Handicap (Div 2) | D44: Class 6 | E44: 8 | F44: Good To Soft | G44: 10 | H44: Arvana Belle (IRE) | I44: Osborne, Saffie | J44: Millman, B R | K44: 5 | L44: 47 | M44: 3 | N44: 6 | O44: 1 | P44: 3.8925234 | Q44: 0.25690276 | R44: 2.625 | S44: =IF(AND(ISNUMBER(R44),R44>1,P44>0),R44/P44-1,"") -> -0.32563025 | T44: =IF(AND(ISNUMBER(P44),P44>0),P44*EXP('Read me'!$B$22),"") -> 4.7543388
A45: 4:44 | B45: Ffos Las | C45: Bridge, For All Family Occasions Handicap (Div 2) | D45: Class 6 | E45: 8 | F45: Good To Soft | G45: 10 | H45: Freedom Bay | I45: Hutchinson, Callum | J45: Hawkins, Zoe | K45: 7 | L45: 48 | M45: 4 | N45: 15 | O45: 2 | P45: 6.0008733 | Q45: 0.16664241 | R45: 8.5 | S45: =IF(AND(ISNUMBER(R45),R45>1,P45>0),R45/P45-1,"") -> 0.4164605 | T45: =IF(AND(ISNUMBER(P45),P45>0),P45*EXP('Read me'!$B$22),"") -> 7.3294832
A46: 4:44 | B46: Ffos Las | C46: Bridge, For All Family Occasions Handicap (Div 2) | D46: Class 6 | E46: 8 | F46: Good To Soft | G46: 10 | H46: King of The Dance (IRE) | I46: Probert, David | J46: Llewellyn, B J | K46: 8 | L46: 54 | M46: 7 | N46: 6 | O46: 3 | P46: 6.9588768 | Q46: 0.14370135 | R46: 6.5 | S46: =IF(AND(ISNUMBER(R46),R46>1,P46>0),R46/P46-1,"") -> -0.065941223 | T46: =IF(AND(ISNUMBER(P46),P46>0),P46*EXP('Read me'!$B$22),"") -> 8.4995914
... A58: 5:19 | B58: Ffos Las | C58: Bridge Llangennech Open Daily Amateur Jockeys Handicap | D58: Class 6 | E58: 10 | F58: Good To Soft | G58: 5 | H58: The Ormer Gatherer | I58: Hills, Mr James | J58: Bramley, Faye | K58: 2 | L58: 47 | M58: 7 | N58: 15 | O58: 5 | P58: 13.764773 | Q58: 0.072649219 | R58: 4.5 | S58: =IF(AND(ISNUMBER(R58),R58>1,P58>0),R58/P58-1,"") -> -0.67307851 | T58: =IF(AND(ISNUMBER(P58),P58>0),P58*EXP('Read me'!$B$22),"") -> 16.812332

Sheet Curragh
A1: Time | B1: Course | C1: Race | D1: Class | E1: Furlongs | F1: Going | G1: Runners | H1: Horse | I1: Jockey | J1: Trainer | K1: Draw | L1: OR | M1: Age | N1: Days since run | O1: Model rank | P1: Predicted BSP | Q1: Win probability | R1: Card odds (HRB) | S1: Card odds vs model | T1: Rule: back at Betfair ≥
A2: 1:25 | B2: Curragh | C2: Army Equitation Centenary Irish European Breeders Fund Maiden | E2: 7 | F2: Heavy | G2: 13 | H2: Raging Bull (IRE) | I2: Moore, Ryan | J2: OBrien, A P | K2: 6 | L2: 0 | M2: 2 | N2: 49 | O2: 1 | P2: 1.7510775 | Q2: 0.57107694 | R2: 1.7272727 | S2: =IF(AND(ISNUMBER(R2),R2>1,P2>0),R2/P2-1,"") -> -0.013594385 | T2: =IF(AND(ISNUMBER(P2),P2>0),P2*EXP('Read me'!$B$22),"") -> 2.1387709
A3: 1:25 | B3: Curragh | C3: Army Equitation Centenary Irish European Breeders Fund Maiden | E3: 7 | F3: Heavy | G3: 13 | H3: Yellow Sky (IRE) | I3: Coen, Ben M | J3: Murtagh, J P | K3: 12 | L3: 0 | M3: 2 | N3: 62 | O3: 2 | P3: 7.4272181 | Q3: 0.13463991 | R3: 12 | S3: =IF(AND(ISNUMBER(R3),R3>1,P3>0),R3/P3-1,"") -> 0.61567896 | T3: =IF(AND(ISNUMBER(P3),P3>0),P3*EXP('Read me'!$B$22),"") -> 9.0716247
A4: 1:25 | B4: Curragh | C4: Army Equitation Centenary Irish European Breeders Fund Maiden | E4: 7 | F4: Heavy | G4: 13 | H4: Maximilien Luce (IRE) | I4: Cleary, Jack | J4: OBrien, A P | K4: 1 | L4: 0 | M4: 2 | O4: 3 | P4: 13.08711 | Q4: 0.076411066 | R4: 7 | S4: =IF(AND(ISNUMBER(R4),R4>1,P4>0),R4/P4-1,"") -> -0.46512253 | T4: =IF(AND(ISNUMBER(P4),P4>0),P4*EXP('Read me'!$B$22),"") -> 15.984632
A5: 1:25 | B5: Curragh | C5: Army Equitation Centenary Irish European Breeders Fund Maiden | E5: 7 | F5: Heavy | G5: 13 | H5: Golden Idol (IRE) | I5: Lee, W J | J5: Bromhead, Henry De | K5: 9 | L5: 0 | M5: 2 | O5: 4 | P5: 13.310346 | Q5: 0.075129527 | R5: 5.5 | S5: =IF(AND(ISNUMBER(R5),R5>1,P5>0),R5/P5-1,"") -> -0.5867876 | T5: =IF(AND(ISNUMBER(P5),P5>0),P5*EXP('Read me'!$B$22),"") -> 16.257293
A6: 1:25 | B6: Curragh | C6: Army Equitation Centenary Irish European Breeders Fund Maiden | E6: 7 | F6: Heavy | G6: 13 | H6: Normanton (IRE) | I6: McAteer, L T | J6: Marnane, David | K6: 16 | L6: 0 | M6: 2 | O6: 5 | P6: 26.949884 | Q6: 0.037105911 | R6: 15 | S6: =IF(AND(ISNUMBER(R6),R6>1,P6>0),R6/P6-1,"") -> -0.44341133 | T6: =IF(AND(ISNUMBER(P6),P6>0),P6*EXP('Read me'!$B$22),"") -> 32.916663
A7: 1:25 | B7: Curragh | C7: Army Equitation Centenary Irish European Breeders Fund Maiden | E7: 7 | F7: Heavy | G7: 13 | H7: Overhead Drive (IRE) | I7: Heffernan, J A | J7: Murphy, John Joseph | K7: 14 | L7: 0 | M7: 2 | O7: 6 | P7: 29.584989 | Q7: 0.033800925 | R7: 29 | S7: =IF(AND(ISNUMBER(R7),R7>1,P7>0),R7/P7-1,"") -> -0.019773178 | T7: =IF(AND(ISNUMBER(P7),P7>0),P7*EXP('Read me'!$B$22),"") -> 36.135187
A8: 1:25 | B8: Curragh | C8: Army Equitation Centenary Irish European Breeders Fund Maiden | E8: 7 | F8: Heavy | G8: 13 | H8: Tsali (IRE) | I8: Hayes, C D | J8: Coleman, Kevin | K8: 8 | L8: 0 | M8: 2 | O8: 7 | P8: 36.193559 | Q8: 0.027629225 | R8: 34 | S8: =IF(AND(ISNUMBER(R8),R8>1,P8>0),R8/P8-1,"") -> -0.060606334 | T8: =IF(AND(ISNUMBER(P8),P8>0),P8*EXP('Read me'!$B$22),"") -> 44.206913
A9: 1:25 | B9: Curragh | C9: Army Equitation Centenary Irish European Breeders Fund Maiden | E9: 7 | F9: Heavy | G9: 13 | H9: Ah Sure Look (IRE) | I9: Sheridan, J M | J9: Hassett, Martin | K9: 10 | L9: 0 | M9: 2 | O9: 8 | P9: 87.460693 | Q9: 0.011433708 | R9: 34 | S9: =IF(AND(ISNUMBER(R9),R9>1,P9>0),R9/P9-1,"") -> -0.61125394 | T9: =IF(AND(ISNUMBER(P9),P9>0),P9*EXP('Read me'!$B$22),"") -> 106.82473
A10: 1:25 | B10: Curragh | C10: Army Equitation Centenary Irish European Breeders Fund Maiden | E10: 7 | F10: Heavy | G10: 13 | H10: Johntom | I10: Carroll, G F | J10: Cromwell, Gavin Patrick | K10: 5 | L10: 0 | M10: 2 | N10: 10 | O10: 9 | P10: 95.343068 | Q10: 0.010488439 | R10: 41 | S10: =IF(AND(ISNUMBER(R10),R10>1,P10>0),R10/P10-1,"") -> -0.56997398 | T10: =IF(AND(ISNUMBER(P10),P10>0),P10*EXP('Read me'!$B$22),"") -> 116.45229
A11: 1:25 | B11: Curragh | C11: Army Equitation Centenary Irish European Breeders Fund Maiden | E11: 7 | F11: Heavy | G11: 13 | H11: Activity (IRE) | I11: Crosse, Nathan | J11: Harrington, Mrs John | K11: 3 | L11: 0 | M11: 2 | N11: 52 | O11: 10 | P11: 112.02611 | Q11: 0.0089264903 | R11: 29 | S11: =IF(AND(ISNUMBER(R11),R11>1,P11>0),R11/P11-1,"") -> -0.74113178 | T11: =IF(AND(ISNUMBER(P11),P11>0),P11*EXP('Read me'!$B$22),"") -> 136.829
A12: 1:25 | B12: Curragh | C12: Army Equitation Centenary Irish European Breeders Fund Maiden | E12: 7 | F12: Heavy | G12: 13 | H12: Soho Dragon (IRE) | I12: OConnor, Donagh | J12: Murphy, John Joseph | K12: 7 | L12: 0 | M12: 2 | O12: 11 | P12: 158.85539 | Q12: 0.0062950336 | R12: 34 | S12: =IF(AND(ISNUMBER(R12),R12>1,P12>0),R12/P12-1,"") -> -0.78596886 | T12: =IF(AND(ISNUMBER(P12),P12>0),P12*EXP('Read me'!$B$22),"") -> 194.02641
A13: 1:25 | B13: Curragh | C13: Army Equitation Centenary Irish European Breeders Fund Maiden | E13: 7 | F13: Heavy | G13: 13 | H13: One Flash (IRE) | I13: Joyce, Wesley | J13: Sexton, Adrian | K13: 11 | L13: 0 | M13: 2 | O13: 12 | P13: 282.56065 | Q13: 0.0035390632 | R13: 41 | S13: =IF(AND(ISNUMBER(R13),R13>1,P13>0),R13/P13-1,"") -> -0.85489841 | T13: =IF(AND(ISNUMBER(P13),P13>0),P13*EXP('Read me'!$B$22),"") -> 345.12036
A14: 1:25 | B14: Curragh | C14: Army Equitation Centenary Irish European Breeders Fund Maiden | E14: 7 | F14: Heavy | G14: 13 | H14: Silk Twist (IRE) | I14: McCullagh, Scott | J14: Mullins, Thomas | K14: 2 | L14: 0 | M14: 2 | N14: 10 | O14: 13 | P14: 283.78757 | Q14: 0.0035237626 | R14: 41 | S14: =IF(AND(ISNUMBER(R14),R14>1,P14>0),R14/P14-1,"") -> -0.85552574 | T14: =IF(AND(ISNUMBER(P14),P14>0),P14*EXP('Read me'!$B$22),"") -> 346.61892
A15: 2:00 | B15: Curragh | C15: Izuzu Ireland Irish European Breeders Fund Maiden | E15: 9 | F15: Heavy | G15: 9 | H15: Kingdom Of Camelot (FR) | I15: Moore, Ryan | J15: OBrien, A P | K15: 12 | L15: 0 | M15: 2 | N15: 29 | O15: 1 | P15: 2.7097568 | Q15: 0.36903681 | R15: 1.9090909 | S15: =IF(AND(ISNUMBER(R15),R15>1,P15>0),R15/P15-1,"") -> -0.29547519 | T15: =IF(AND(ISNUMBER(P15),P15>0),P15*EXP('Read me'!$B$22),"") -> 3.3097044
A16: 2:00 | B16: Curragh | C16: Izuzu Ireland Irish European Breeders Fund Maiden | E16: 9 | F16: Heavy | G16: 9 | H16: Cluster | I16: Keane, C T | J16: OBrien, Joseph Patrick | K16: 6 | L16: 0 | M16: 2 | N16: 29 | O16: 2 | P16: 4.0075054 | Q16: 0.24953179 | R16: 2.75 | S16: =IF(AND(ISNUMBER(R16),R16>1,P16>0),R16/P16-1,"") -> -0.31378758 | T16: =IF(AND(ISNUMBER(P16),P16>0),P16*EXP('Read me'!$B$22),"") -> 4.8947782
A17: 2:00 | B17: Curragh | C17: Izuzu Ireland Irish European Breeders Fund Maiden | E17: 9 | F17: Heavy | G17: 9 | H17: Capability Brown (IRE) | I17: Lordan, W M | J17: OBrien, A P | K17: 1 | L17: 0 | M17: 2 | N17: 26 | O17: 3 | P17: 4.4751775 | Q17: 0.22345482 | R17: 6.5 | S17: =IF(AND(ISNUMBER(R17),R17>1,P17>0),R17/P17-1,"") -> 0.45245634 | T17: =IF(AND(ISNUMBER(P17),P17>0),P17*EXP('Read me'!$B$22),"") -> 5.4659942
A18: 2:00 | B18: Curragh | C18: Izuzu Ireland Irish European Breeders Fund Maiden | E18: 9 | F18: Heavy | G18: 9 | H18: Darivan (IRE) | I18: Coen, Ben M | J18: Murtagh, J P | K18: 5 | L18: 0 | M18: 2 | N18: 92 | O18: 4 | P18: 11.9565 | Q18: 0.083636516 | R18: 19 | S18: =IF(AND(ISNUMBER(R18),R18>1,P18>0),R18/P18-1,"") -> 0.58909381 | T18: =IF(AND(ISNUMBER(P18),P18>0),P18*EXP('Read me'!$B$22),"") -> 14.603702
A19: 2:00 | B19: Curragh | C19: Izuzu Ireland Irish European Breeders Fund Maiden | E19: 9 | F19: Heavy | G19: 9 | H19: Greatest Knight (IRE) | I19: Cleary, Jack | J19: OBrien, A P | K19: 10 | L19: 0 | M19: 2 | O19: 5 | P19: 25.267991 | Q19: 0.039575762 | R19: 21 | S19: =IF(AND(ISNUMBER(R19),R19>1,P19>0),R19/P19-1,"") -> -0.168909 | T19: =IF(AND(ISNUMBER(P19),P19>0),P19*EXP('Read me'!$B$22),"") -> 30.862394
A20: 2:00 | B20: Curragh | C20: Izuzu Ireland Irish European Breeders Fund Maiden | E20: 9 | F20: Heavy | G20: 9 | H20: Silent Kingdom (IRE) | I20: Lee, W J | J20: Dias, Diego | K20: 2 | L20: 0 | M20: 2 | O20: 6 | P20: 60.524576 | Q20: 0.016522214 | R20: 34 | S20: =IF(AND(ISNUMBER(R20),R20>1,P20>0),R20/P20-1,"") -> -0.43824472 | T20: =IF(AND(ISNUMBER(P20),P20>0),P20*EXP('Read me'!$B$22),"") -> 73.924884
A21: 2:00 | B21: Curragh | C21: Izuzu Ireland Irish European Breeders Fund Maiden | E21: 9 | F21: Heavy | G21: 9 | H21: Warrawood | I21: McCullagh, Scott | J21: McLoughlin, Daniel | K21: 11 | L21: 0 | M21: 2 | O21: 7 | P21: 74.440977 | Q21: 0.013433461 | R21: 67 | S21: =IF(AND(ISNUMBER(R21),R21>1,P21>0),R21/P21-1,"") -> -0.099958084 | T21: =IF(AND(ISNUMBER(P21),P21>0),P21*EXP('Read me'!$B$22),"") -> 90.922415
A22: 2:00 | B22: Curragh | C22: Izuzu Ireland Irish European Breeders Fund Maiden | E22: 9 | F22: Heavy | G22: 9 | H22: Lumierebleu (IRE) | I22: Heffernan, J A | J22: Murtagh, J P | K22: 3 | L22: 0 | M22: 2 | N22: 29 | O22: 8 | P22: 264.02961 | Q22: 0.0037874539 | R22: 201 | S22: =IF(AND(ISNUMBER(R22),R22>1,P22>0),R22/P22-1,"") -> -0.23872176 | T22: =IF(AND(ISNUMBER(P22),P22>0),P22*EXP('Read me'!$B$22),"") -> 322.4865
A23: 2:00 | B23: Curragh | C23: Izuzu Ireland Irish European Breeders Fund Maiden | E23: 9 | F23: Heavy | G23: 9 | H23: Alone All Alone | I23: Whelan, R P | J23: ONeill, E J | K23: 9 | L23: 0 | M23: 2 | N23: 10 | O23: 9 | P23: 979.26571 | Q23: 0.0010211733 | R23: 151 | S23: =IF(AND(ISNUMBER(R23),R23>1,P23>0),R23/P23-1,"") -> -0.84580283 | T23: =IF(AND(ISNUMBER(P23),P23>0),P23*EXP('Read me'!$B$22),"") -> 1196.0778
A24: 2:35 | B24: Curragh | C24: Qatar Racing And Equestrian Club Renaissance Stakes (Group 3) | E24: 6 | F24: Heavy | G24: 8 | H24: Soul Love | I24: Jamin, Pierre-Louis | J24: Burke, K R | K24: 9 | L24: 101 | M24: 3 | N24: 35 | O24: 1 | P24: 3.6569722 | Q24: 0.27345026 | R24: 3.75 | S24: =IF(AND(ISNUMBER(R24),R24>1,P24>0),R24/P24-1,"") -> 0.02543848 | T24: =IF(AND(ISNUMBER(P24),P24>0),P24*EXP('Read me'!$B$22),"") -> 4.4666359
A25: 2:35 | B25: Curragh | C25: Qatar Racing And Equestrian Club Renaissance Stakes (Group 3) | E25: 6 | F25: Heavy | G25: 8 | H25: Power Blue (IRE) | I25: Lee, W J | J25: Aguiar, Robson | K25: 8 | L25: 110 | M25: 3 | N25: 36 | O25: 2 | P25: 4.4795634 | Q25: 0.22323604 | R25: 3.75 | S25: =IF(AND(ISNUMBER(R25),R25>1,P25>0),R25/P25-1,"") -> -0.16286484 | T25: =IF(AND(ISNUMBER(P25),P25>0),P25*EXP('Read me'!$B$22),"") -> 5.471351
A26: 2:35 | B26: Curragh | C26: Qatar Racing And Equestrian Club Renaissance Stakes (Group 3) | E26: 6 | F26: Heavy | G26: 8 | H26: Brussels | I26: Moore, Ryan | J26: OBrien, A P | K26: 2 | L26: 101 | M26: 3 | N26: 14 | O26: 3 | P26: 5.4711503 | Q26: 0.18277692 | R26: 7 | S26: =IF(AND(ISNUMBER(R26),R26>1,P26>0),R26/P26-1,"") -> 0.27943844 | T26: =IF(AND(ISNUMBER(P26),P26>0),P26*EXP('Read me'!$B$22),"") -> 6.682478
A27: 2:35 | B27: Curragh | C27: Qatar Racing And Equestrian Club Renaissance Stakes (Group 3) | E27: 6 | F27: Heavy | G27: 8 | H27: Royal Bay Cen (IRE) | I27: Coen, Ben M | J27: Murtagh, J P | K27: 7 | L27: 104 | M27: 3 | N27: 133 | O27: 4 | P27: 6.2935973 | Q27: 0.15889164 | R27: 3.75 | S27: =IF(AND(ISNUMBER(R27),R27>1,P27>0),R27/P27-1,"") -> -0.40415634 | T27: =IF(AND(ISNUMBER(P27),P27>0),P27*EXP('Read me'!$B$22),"") -> 7.687017
A28: 2:35 | B28: Curragh | C28: Qatar Racing And Equestrian Club Renaissance Stakes (Group 3) | E28: 6 | F28: Heavy | G28: 8 | H28: Charles Darwin (IRE) | I28: Lordan, W M | J28: OBrien, A P | K28: 4 | L28: 103 | M28: 3 | N28: 71 | O28: 5 | P28: 15.720531 | Q28: 0.063611083 | R28: 29 | S28: =IF(AND(ISNUMBER(R28),R28>1,P28>0),R28/P28-1,"") -> 0.84472141 | T28: =IF(AND(ISNUMBER(P28),P28>0),P28*EXP('Read me'!$B$22),"") -> 19.2011
A29: 2:35 | B29: Curragh | C29: Qatar Racing And Equestrian Club Renaissance Stakes (Group 3) | E29: 6 | F29: Heavy | G29: 8 | H29: Big Gossey (IRE) | I29: Whearty, R | J29: OBrien, Charles | K29: 1 | L29: 104 | M29: 9 | N29: 14 | O29: 6 | P29: 22.91847 | Q29: 0.04363293 | R29: 9 | S29: =IF(AND(ISNUMBER(R29),R29>1,P29>0),R29/P29-1,"") -> -0.60730363 | T29: =IF(AND(ISNUMBER(P29),P29>0),P29*EXP('Read me'!$B$22),"") -> 27.992682
A30: 2:35 | B30: Curragh | C30: Qatar Racing And Equestrian Club Renaissance Stakes (Group 3) | E30: 6 | F30: Heavy | G30: 8 | H30: East Hampton | I30: Colgan, R C | J30: Marnane, David | K30: 6 | L30: 104 | M30: 4 | N30: 37 | O30: 7 | P30: 31.253591 | Q30: 0.031996323 | R30: 19 | S30: =IF(AND(ISNUMBER(R30),R30>1,P30>0),R30/P30-1,"") -> -0.39206987 | T30: =IF(AND(ISNUMBER(P30),P30>0),P30*EXP('Read me'!$B$22),"") -> 38.173223
A31: 2:35 | B31: Curragh | C31: Qatar Racing And Equestrian Club Renaissance Stakes (Group 3) | E31: 6 | F31: Heavy | G31: 8 | H31: Tango Flare (IRE) | I31: McAteer, L T | J31: Foley, Patrick T | K31: 3 | L31: 96 | M31: 7 | N31: 14 | O31: 8 | P31: 44.633301 | Q31: 0.022404796 | R31: 34 | S31: =IF(AND(ISNUMBER(R31),R31>1,P31>0),R31/P31-1,"") -> -0.23823693 | T31: =IF(AND(ISNUMBER(P31),P31>0),P31*EXP('Read me'!$B$22),"") -> 54.515237
A32: 3:10 | B32: Curragh | C32: Celebrating County Kildare And Lexington Twinning Maiden | E32: 6 | F32: Heavy | G32: 12 | H32: Valentino Eclipse (IRE) | I32: Heffernan, J A | J32: Stack, J A | K32: 11 | L32: 0 | M32: 3 | N32: 93 | O32: 1 | P32: 2.4347683 | Q32: 0.4107167 | R32: 1.7272727 | S32: =IF(AND(ISNUMBER(R32),R32>1,P32>0),R32/P32-1,"") -> -0.29058024 | T32: =IF(AND(ISNUMBER(P32),P32>0),P32*EXP('Read me'!$B$22),"") -> 2.9738327
A33: 3:10 | B33: Curragh | C33: Celebrating County Kildare And Lexington Twinning Maiden | E33: 6 | F33: Heavy | G33: 12 | H33: A Good Yarn (IRE) | I33: Lordan, W M | J33: Howard, Aidan Anthony | K33: 1 | L33: 0 | M33: 3 | N33: 161 | O33: 2 | P33: 3.5987295 | Q33: 0.27787584 | R33: 3.5 | S33: =IF(AND(ISNUMBER(R33),R33>1,P33>0),R33/P33-1,"") -> -0.027434553 | T33: =IF(AND(ISNUMBER(P33),P33>0),P33*EXP('Read me'!$B$22),"") -> 4.3954982
A34: 3:10 | B34: Curragh | C34: Celebrating County Kildare And Lexington Twinning Maiden | E34: 6 | F34: Heavy | G34: 12 | H34: Tourin (IRE) | I34: Ryan, Gavin | J34: Stack, J A | K34: 12 | L34: 0 | M34: 3 | N34: 26 | O34: 3 | P34: 7.1742156 | Q34: 0.13938806 | R34: 9 | S34: =IF(AND(ISNUMBER(R34),R34>1,P34>0),R34/P34-1,"") -> 0.25449254 | T34: =IF(AND(ISNUMBER(P34),P34>0),P34*EXP('Read me'!$B$22),"") -> 8.7626068
A35: 3:10 | B35: Curragh | C35: Celebrating County Kildare And Lexington Twinning Maiden | E35: 6 | F35: Heavy | G35: 12 | H35: The Hidden Garden (IRE) | I35: McDonogh, D P | J35: Harty, Edward and Patrick | K35: 13 | L35: 0 | M35: 3 | O35: 4 | P35: 14.010672 | Q35: 0.071374163 | R35: 26 | S35: =IF(AND(ISNUMBER(R35),R35>1,P35>0),R35/P35-1,"") -> 0.85572823 | T35: =IF(AND(ISNUMBER(P35),P35>0),P35*EXP('Read me'!$B$22),"") -> 17.112674
A36: 3:10 | B36: Curragh | C36: Celebrating County Kildare And Lexington Twinning Maiden | E36: 6 | F36: Heavy | G36: 12 | H36: Saga Lucia (IRE) | I36: Holohan, Reese | J36: OCallaghan, M D | K36: 6 | L36: 73 | M36: 3 | N36: 37 | O36: 5 | P36: 34.106586 | Q36: 0.029319851 | R36: 13 | S36: =IF(AND(ISNUMBER(R36),R36>1,P36>0),R36/P36-1,"") -> -0.61884194 | T36: =IF(AND(ISNUMBER(P36),P36>0),P36*EXP('Read me'!$B$22),"") -> 41.657878
A37: 3:10 | B37: Curragh | C37: Celebrating County Kildare And Lexington Twinning Maiden | E37: 6 | F37: Heavy | G37: 12 | H37: Port Arthur (IRE) | I37: Colgan, R C | J37: Grassick, M C | K37: 7 | L37: 74 | M37: 3 | N37: 12 | O37: 6 | P37: 35.727312 | Q37: 0.027989791 | R37: 21 | S37: =IF(AND(ISNUMBER(R37),R37>1,P37>0),R37/P37-1,"") -> -0.41221439 | T37: =IF(AND(ISNUMBER(P37),P37>0),P37*EXP('Read me'!$B$22),"") -> 43.637438
A38: 3:10 | B38: Curragh | C38: Celebrating County Kildare And Lexington Twinning Maiden | E38: 6 | F38: Heavy | G38: 12 | H38: Caislean Ni Cuan (IRE) | I38: McCullagh, N G | J38: Mullins, Thomas | K38: 2 | L38: 57 | M38: 3 | N38: 36 | O38: 7 | P38: 40.791335 | Q38: 0.02451501 | R38: 23 | S38: =IF(AND(ISNUMBER(R38),R38>1,P38>0),R38/P38-1,"") -> -0.43615476 | T38: =IF(AND(ISNUMBER(P38),P38>0),P38*EXP('Read me'!$B$22),"") -> 49.822649
A39: 3:10 | B39: Curragh | C39: Celebrating County Kildare And Lexington Twinning Maiden | E39: 6 | F39: Heavy | G39: 12 | H39: Tribal Belle (IRE) | I39: Hayes, C D | J39: Bunyan, Darren / OLeary, G | K39: 4 | L39: 0 | M39: 3 | N39: 26 | O39: 8 | P39: 107.1561 | Q39: 0.0093321802 | R39: 34 | S39: =IF(AND(ISNUMBER(R39),R39>1,P39>0),R39/P39-1,"") -> -0.68270587 | T39: =IF(AND(ISNUMBER(P39),P39>0),P39*EXP('Read me'!$B$22),"") -> 130.88075
A40: 3:10 | B40: Curragh | C40: Celebrating County Kildare And Lexington Twinning Maiden | E40: 6 | F40: Heavy | G40: 12 | H40: Gaineamh Min (IRE) | I40: Joyce, Wesley | J40: Byrne, Sean | K40: 10 | L40: 0 | M40: 3 | N40: 23 | O40: 9 | P40: 265.76376 | Q40: 0.0037627403 | R40: 41 | S40: =IF(AND(ISNUMBER(R40),R40>1,P40>0),R40/P40-1,"") -> -0.84572765 | T40: =IF(AND(ISNUMBER(P40),P40>0),P40*EXP('Read me'!$B$22),"") -> 324.60458
A41: 3:10 | B41: Curragh | C41: Celebrating County Kildare And Lexington Twinning Maiden | E41: 6 | F41: Heavy | G41: 12 | H41: Spider Star (IRE) | I41: Browne-Souza, A | J41: Kelly, David Harry | K41: 3 | L41: 0 | M41: 3 | N41: 28 | O41: 10 | P41: 386.81483 | Q41: 0.0025852163 | R41: 126 | S41: =IF(AND(ISNUMBER(R41),R41>1,P41>0),R41/P41-1,"") -> -0.67426275 | T41: =IF(AND(ISNUMBER(P41),P41>0),P41*EXP('Read me'!$B$22),"") -> 472.4567
A42: 3:10 | B42: Curragh | C42: Celebrating County Kildare And Lexington Twinning Maiden | E42: 6 | F42: Heavy | G42: 12 | H42: Upper West Side (IRE) | I42: Ryan, J J G | J42: Lynam, Edward | K42: 14 | L42: 0 | M42: 5 | N42: 18 | O42: 11 | P42: 573.55532 | Q42: 0.001743511 | R42: 126 | S42: =IF(AND(ISNUMBER(R42),R42>1,P42>0),R42/P42-1,"") -> -0.78031761 | T42: =IF(AND(ISNUMBER(P42),P42>0),P42*EXP('Read me'!$B$22),"") -> 700.54205
A43: 3:10 | B43: Curragh | C43: Celebrating County Kildare And Lexington Twinning Maiden | E43: 6 | F43: Heavy | G43: 12 | H43: Petticoat Pilot (IRE) | I43: OSullivan, Darragh | J43: Finn, David Edward | K43: 8 | L43: 0 | M43: 5 | N43: 793 | O43: 12 | P43: 715.85325 | Q43: 0.0013969344 | R43: 126 | S43: =IF(AND(ISNUMBER(R43),R43>1,P43>0),R43/P43-1,"") -> -0.82398627 | T43: =IF(AND(ISNUMBER(P43),P43>0),P43*EXP('Read me'!$B$22),"") -> 874.34513
A44: 3:45 | B44: Curragh | C44: Darley Fillies Stakes (Group 3) | E44: 7 | F44: Heavy | G44: 8 | H44: Curracloe (USA) | I44: Coen, Ben M | J44: Murtagh, J P | K44: 8 | L44: 0 | M44: 2 | N44: 26 | O44: 1 | P44: 3.6309839 | Q44: 0.27540745 | R44: 2.5 | S44: =IF(AND(ISNUMBER(R44),R44>1,P44>0),R44/P44-1,"") -> -0.31148138 | T44: =IF(AND(ISNUMBER(P44),P44>0),P44*EXP('Read me'!$B$22),"") -> 4.4348937
A45: 3:45 | B45: Curragh | C45: Darley Fillies Stakes (Group 3) | E45: 7 | F45: Heavy | G45: 8 | H45: Damsel In Distress (IRE) | I45: Keane, C T | J45: McLoughlin, Daniel | K45: 5 | L45: 95 | M45: 2 | N45: 29 | O45: 2 | P45: 3.8856512 | Q45: 0.25735712 | R45: 4.3333333 | S45: =IF(AND(ISNUMBER(R45),R45>1,P45>0),R45/P45-1,"") -> 0.11521419 | T45: =IF(AND(ISNUMBER(P45),P45>0),P45*EXP('Read me'!$B$22),"") -> 4.7459451
A46: 3:45 | B46: Curragh | C46: Darley Fillies Stakes (Group 3) | E46: 7 | F46: Heavy | G46: 8 | H46: Alpine Wedding (IRE) | I46: Lee, W J | J46: Twomey, P | K46: 6 | L46: 90 | M46: 2 | N46: 18 | O46: 3 | P46: 5.1823078 | Q46: 0.19296422 | R46: 3.25 | S46: =IF(AND(ISNUMBER(R46),R46>1,P46>0),R46/P46-1,"") -> -0.37286628 | T46: =IF(AND(ISNUMBER(P46),P46>0),P46*EXP('Read me'!$B$22),"") -> 6.3296851
A47: 3:45 | B47: Curragh | C47: Darley Fillies Stakes (Group 3) | E47: 7 | F47: Heavy | G47: 8 | H47: Film Set (USA) | I47: Moore, Ryan | J47: OBrien, A P | K47: 3 | L47: 0 | M47: 2 | N47: 35 | O47: 4 | P47: 8.2884026 | Q47: 0.12065051 | R47: 15 | S47: =IF(AND(ISNUMBER(R47),R47>1,P47>0),R47/P47-1,"") -> 0.80975766 | T47: =IF(AND(ISNUMBER(P47),P47>0),P47*EXP('Read me'!$B$22),"") -> 10.123478
... A103: 5:30 | B103: Curragh | C103: Kwiff Supercharged Betting (Q.R.) Handicap | E103: 10 | F103: Heavy | G103: 18 | H103: Alfalfa (IRE) | I103: Doyle, Mr D | J103: Doyle, Timothy | K103: 10 | L103: 66 | M103: 8 | N103: 341 | O103: 12 | P103: 52.939538 | Q103: 0.018889473 | R103: 23 | S103: =IF(AND(ISNUMBER(R103),R103>1,P103>0),R103/P103-1,"") -> -0.56554211 | T103: =IF(AND(ISNUMBER(P103),P103>0),P103*EXP('Read me'!$B$22),"") -> 64.660498
A104: 5:30 | B104: Curragh | C104: Kwiff Supercharged Betting (Q.R.) Handicap | E104: 10 | F104: Heavy | G104: 18 | H104: Out On Friday (IRE) | J104: Byrne, Philip Michael | K104: 12 | L104: 60 | M104: 10 | N104: 28 | O104: 13 | P104: 59.247364 | Q104: 0.016878388 | R104: 67 | S104: =IF(AND(ISNUMBER(R104),R104>1,P104>0),R104/P104-1,"") -> 0.13085199 | T104: =IF(AND(ISNUMBER(P104),P104>0),P104*EXP('Read me'!$B$22),"") -> 72.364894
A105: 5:30 | B105: Curragh | C105: Kwiff Supercharged Betting (Q.R.) Handicap | E105: 10 | F105: Heavy | G105: 18 | H105: Palace Tyne (IRE) | I105: OConnor, Miss A B | J105: Roche, Padraig | K105: 22 | L105: 57 | M105: 3 | N105: 181 | O105: 14 | P105: 73.4189 | Q105: 0.013620471 | R105: 34 | S105: =IF(AND(ISNUMBER(R105),R105>1,P105>0),R105/P105-1,"") -> -0.53690398 | T105: =IF(AND(ISNUMBER(P105),P105>0),P105*EXP('Read me'!$B$22),"") -> 89.674047
A106: 5:30 | B106: Curragh | C106: Kwiff Supercharged Betting (Q.R.) Handicap | E106: 10 | F106: Heavy | G106: 18 | H106: Its Good To Talk (IRE) | I106: Queally, Miss O M | J106: Mullins, Emmet | K106: 16 | L106: 64 | M106: 5 | N106: 22 | O106: 15 | P106: 82.650175 | Q106: 0.012099188 | R106: 19 | S106: =IF(AND(ISNUMBER(R106),R106>1,P106>0),R106/P106-1,"") -> -0.77011543 | T106: =IF(AND(ISNUMBER(P106),P106>0),P106*EXP('Read me'!$B$22),"") -> 100.94915
A107: 5:30 | B107: Curragh | C107: Kwiff Supercharged Betting (Q.R.) Handicap | E107: 10 | F107: Heavy | G107: 18 | H107: Lamberella (IRE) | I107: Merrigan, Mr T B | J107: Marnane, David | K107: 5 | L107: 64 | M107: 3 | N107: 42 | O107: 16 | P107: 88.960841 | Q107: 0.011240901 | R107: 41 | S107: =IF(AND(ISNUMBER(R107),R107>1,P107>0),R107/P107-1,"") -> -0.53912306 | T107: =IF(AND(ISNUMBER(P107),P107>0),P107*EXP('Read me'!$B$22),"") -> 108.65702
A108: 5:30 | B108: Curragh | C108: Kwiff Supercharged Betting (Q.R.) Handicap | E108: 10 | F108: Heavy | G108: 18 | H108: Kimy (FR) | I108: Mullins, Mr C | J108: Mullins, Thomas | K108: 9 | L108: 72 | M108: 6 | N108: 45 | O108: 17 | P108: 93.043876 | Q108: 0.010747618 | R108: 51 | S108: =IF(AND(ISNUMBER(R108),R108>1,P108>0),R108/P108-1,"") -> -0.4518715 | T108: =IF(AND(ISNUMBER(P108),P108>0),P108*EXP('Read me'!$B$22),"") -> 113.64405
A109: 5:30 | B109: Curragh | C109: Kwiff Supercharged Betting (Q.R.) Handicap | E109: 10 | F109: Heavy | G109: 18 | H109: If Not For Grace (IRE) | I109: Joubert, Ms S | J109: Cusack, Liam P | K109: 1 | L109: 56 | M109: 4 | N109: 22 | O109: 18 | P109: 120.30655 | Q109: 0.0083120995 | R109: 34 | S109: =IF(AND(ISNUMBER(R109),R109>1,P109>0),R109/P109-1,"") -> -0.71738862 | T109: =IF(AND(ISNUMBER(P109),P109>0),P109*EXP('Read me'!$B$22),"") -> 146.94275

Sheet Epsom
A1: Time | B1: Course | C1: Race | D1: Class | E1: Furlongs | F1: Going | G1: Runners | H1: Horse | I1: Jockey | J1: Trainer | K1: Draw | L1: OR | M1: Age | N1: Days since run | O1: Model rank | P1: Predicted BSP | Q1: Win probability | R1: Card odds (HRB) | S1: Card odds vs model | T1: Rule: back at Betfair ≥
A2: 1:37 | B2: Epsom | C2: Betfred Turbo Boost Nursery | D2: Class 4 | E2: 7 | F2: Good | G2: 8 | H2: Regal Tiger | I2: Murphy, Oisin | J2: Palmer, Hugo | K2: 7 | L2: 73 | M2: 2 | N2: 69 | O2: 1 | P2: 4.5975127 | Q2: 0.21750892 | R2: 5.5 | S2: =IF(AND(ISNUMBER(R2),R2>1,P2>0),R2/P2-1,"") -> 0.19629903 | T2: =IF(AND(ISNUMBER(P2),P2>0),P2*EXP('Read me'!$B$22),"") -> 5.6154147
A3: 1:37 | B3: Epsom | C3: Betfred Turbo Boost Nursery | D3: Class 4 | E3: 7 | F3: Good | G3: 8 | H3: Give Hand (IRE) | I3: Edmunds, Lewis | J3: Charlton, Roger/Harry | K3: 3 | L3: 76 | M3: 2 | N3: 17 | O3: 2 | P3: 5.8202093 | Q3: 0.17181513 | R3: 3.5 | S3: =IF(AND(ISNUMBER(R3),R3>1,P3>0),R3/P3-1,"") -> -0.39864706 | T3: =IF(AND(ISNUMBER(P3),P3>0),P3*EXP('Read me'!$B$22),"") -> 7.1088197
A4: 1:37 | B4: Epsom | C4: Betfred Turbo Boost Nursery | D4: Class 4 | E4: 7 | F4: Good | G4: 8 | H4: The Ginger Kid (IRE) | I4: Lewis, Ashley | J4: Walker, Ed | K4: 9 | L4: 83 | M4: 2 | N4: 38 | O4: 3 | P4: 6.2737356 | Q4: 0.15939467 | R4: 4.5 | S4: =IF(AND(ISNUMBER(R4),R4>1,P4>0),R4/P4-1,"") -> -0.28272399 | T4: =IF(AND(ISNUMBER(P4),P4>0),P4*EXP('Read me'!$B$22),"") -> 7.662758
A5: 1:37 | B5: Epsom | C5: Betfred Turbo Boost Nursery | D5: Class 4 | E5: 7 | F5: Good | G5: 8 | H5: Telegraphic | I5: Loughnane, Billy | J5: Johnston, Charlie | K5: 8 | L5: 80 | M5: 2 | N5: 38 | O5: 4 | P5: 8.7453849 | Q5: 0.11434603 | R5: 6.5 | S5: =IF(AND(ISNUMBER(R5),R5>1,P5>0),R5/P5-1,"") -> -0.25675084 | T5: =IF(AND(ISNUMBER(P5),P5>0),P5*EXP('Read me'!$B$22),"") -> 10.681637
A6: 1:37 | B6: Epsom | C6: Betfred Turbo Boost Nursery | D6: Class 4 | E6: 7 | F6: Good | G6: 8 | H6: Rogue Imperial | I6: Ryan, Rossa | J6: Watson, Archie | K6: 5 | L6: 78 | M6: 2 | N6: 34 | O6: 5 | P6: 9.1388947 | Q6: 0.10942242 | R6: 17 | S6: =IF(AND(ISNUMBER(R6),R6>1,P6>0),R6/P6-1,"") -> 0.86018119 | T6: =IF(AND(ISNUMBER(P6),P6>0),P6*EXP('Read me'!$B$22),"") -> 11.162271
A7: 1:37 | B7: Epsom | C7: Betfred Turbo Boost Nursery | D7: Class 4 | E7: 7 | F7: Good | G7: 8 | H7: Clive The Writer (IRE) | I7: Crouch, Hector | J7: Muir, W R & Grassick, C | K7: 1 | L7: 78 | M7: 2 | N7: 16 | O7: 6 | P7: 9.3350044 | Q7: 0.10712368 | R7: 9.5 | S7: =IF(AND(ISNUMBER(R7),R7>1,P7>0),R7/P7-1,"") -> 0.017674937 | T7: =IF(AND(ISNUMBER(P7),P7>0),P7*EXP('Read me'!$B$22),"") -> 11.4018
A8: 1:37 | B8: Epsom | C8: Betfred Turbo Boost Nursery | D8: Class 4 | E8: 7 | F8: Good | G8: 8 | H8: Angel Of Desire | I8: Fallon, Cieren | J8: Perrett, Mrs A J | K8: 6 | L8: 71 | M8: 2 | N8: 27 | O8: 7 | P8: 13.811546 | Q8: 0.07240319 | R8: 11 | S8: =IF(AND(ISNUMBER(R8),R8>1,P8>0),R8/P8-1,"") -> -0.20356492 | T8: =IF(AND(ISNUMBER(P8),P8>0),P8*EXP('Read me'!$B$22),"") -> 16.869461
A9: 1:37 | B9: Epsom | C9: Betfred Turbo Boost Nursery | D9: Class 4 | E9: 7 | F9: Good | G9: 8 | H9: Leucothea (IRE) | I9: Levey, S M | J9: Hannon (Jnr), Richard | K9: 2 | L9: 71 | M9: 2 | N9: 17 | O9: 8 | P9: 20.839422 | Q9: 0.047985976 | R9: 19 | S9: =IF(AND(ISNUMBER(R9),R9>1,P9>0),R9/P9-1,"") -> -0.088266455 | T9: =IF(AND(ISNUMBER(P9),P9>0),P9*EXP('Read me'!$B$22),"") -> 25.453327
A10: 2:12 | B10: Epsom | C10: Betfred Derby Wild Card EBF Conditions Stakes (GBB/GBBPlus Race) | D10: Class 2 | E10: 8.5 | F10: Good | G10: 5 | H10: Rose Moon (GER) | I10: Ryan, Rossa | J10: Beckett, R M | K10: 5 | L10: 0 | M10: 2 | N10: 24 | O10: 1 | P10: 3.3125625 | Q10: 0.3018811 | R10: 2.375 | S10: =IF(AND(ISNUMBER(R10),R10>1,P10>0),R10/P10-1,"") -> -0.28303239 | T10: =IF(AND(ISNUMBER(P10),P10>0),P10*EXP('Read me'!$B$22),"") -> 4.0459729
A11: 2:12 | B11: Epsom | C11: Betfred Derby Wild Card EBF Conditions Stakes (GBB/GBBPlus Race) | D11: Class 2 | E11: 8.5 | F11: Good | G11: 5 | H11: Al Wathba (FR) | I11: Loughnane, Billy | J11: Appleby, Charlie | K11: 4 | L11: 89 | M11: 2 | N11: 17 | O11: 2 | P11: 3.524514 | Q11: 0.28372706 | R11: 4 | S11: =IF(AND(ISNUMBER(R11),R11>1,P11>0),R11/P11-1,"") -> 0.13490825 | T11: =IF(AND(ISNUMBER(P11),P11>0),P11*EXP('Read me'!$B$22),"") -> 4.3048511
A12: 2:12 | B12: Epsom | C12: Betfred Derby Wild Card EBF Conditions Stakes (GBB/GBBPlus Race) | D12: Class 2 | E12: 8.5 | F12: Good | G12: 5 | H12: Quite Cheeky (IRE) | I12: Fallon, Cieren | J12: Haggas, W J | K12: 1 | L12: 0 | M12: 2 | N12: 17 | O12: 3 | P12: 5.3391219 | Q12: 0.18729672 | R12: 3.5 | S12: =IF(AND(ISNUMBER(R12),R12>1,P12>0),R12/P12-1,"") -> -0.34446149 | T12: =IF(AND(ISNUMBER(P12),P12>0),P12*EXP('Read me'!$B$22),"") -> 6.5212182
A13: 2:12 | B13: Epsom | C13: Betfred Derby Wild Card EBF Conditions Stakes (GBB/GBBPlus Race) | D13: Class 2 | E13: 8.5 | F13: Good | G13: 5 | H13: Sword Salute (USA) | I13: Scott, Rowan | J13: Johnston, Charlie | K13: 2 | L13: 91 | M13: 2 | N13: 59 | O13: 4 | P13: 8.016342 | Q13: 0.12474518 | R13: 13 | S13: =IF(AND(ISNUMBER(R13),R13>1,P13>0),R13/P13-1,"") -> 0.62168729 | T13: =IF(AND(ISNUMBER(P13),P13>0),P13*EXP('Read me'!$B$22),"") -> 9.7911823
... A15: 2:47 | B15: Epsom | C15: Hunt Family Fund Novice Stakes (Sponsored By Betfred) (GBB Race) | D15: Class 3 | E15: 10 | F15: Good | G15: 6 | H15: Maestro Del Mar (FR) | I15: Loughnane, Billy | J15: Mohammed, Ismail | K15: 5 | L15: 75 | M15: 4 | N15: 24 | O15: 1 | P15: 3.4940533 | Q15: 0.28620056 | R15: 4 | S15: =IF(AND(ISNUMBER(R15),R15>1,P15>0),R15/P15-1,"") -> 0.14480224 | T15: =IF(AND(ISNUMBER(P15),P15>0),P15*EXP('Read me'!$B$22),"") -> 4.2676463
A16: 2:47 | B16: Epsom | C16: Hunt Family Fund Novice Stakes (Sponsored By Betfred) (GBB Race) | D16: Class 3 | E16: 10 | F16: Good | G16: 6 | H16: Rowlf | I16: Fallon, Cieren | J16: Haggas, W J | K16: 3 | L16: 0 | M16: 3 | O16: 2 | P16: 3.9386 | Q16: 0.25389732 | R16: 3.5 | S16: =IF(AND(ISNUMBER(R16),R16>1,P16>0),R16/P16-1,"") -> -0.11135937 | T16: =IF(AND(ISNUMBER(P16),P16>0),P16*EXP('Read me'!$B$22),"") -> 4.810617
A17: 2:47 | B17: Epsom | C17: Hunt Family Fund Novice Stakes (Sponsored By Betfred) (GBB Race) | D17: Class 3 | E17: 10 | F17: Good | G17: 6 | H17: Blue Noon (IRE) | I17: Levey, S M | J17: Hannon (Jnr), Richard | K17: 2 | L17: 74 | M17: 3 | N17: 30 | O17: 3 | P17: 4.0394346 | Q17: 0.2475594 | R17: 2.75 | S17: =IF(AND(ISNUMBER(R17),R17>1,P17>0),R17/P17-1,"") -> -0.31921166 | T17: =IF(AND(ISNUMBER(P17),P17>0),P17*EXP('Read me'!$B$22),"") -> 4.9337766
A18: 2:47 | B18: Epsom | C18: Hunt Family Fund Novice Stakes (Sponsored By Betfred) (GBB Race) | D18: Class 3 | E18: 10 | F18: Good | G18: 6 | H18: Seacole (IRE) | I18: Ryan, Rossa | J18: Beckett, R M | K18: 6 | L18: 73 | M18: 3 | N18: 13 | O18: 4 | P18: 5.6436686 | Q18: 0.17718971 | R18: 6 | S18: =IF(AND(ISNUMBER(R18),R18>1,P18>0),R18/P18-1,"") -> 0.063138263 | T18: =IF(AND(ISNUMBER(P18),P18>0),P18*EXP('Read me'!$B$22),"") -> 6.8931924
A19: 2:47 | B19: Epsom | C19: Hunt Family Fund Novice Stakes (Sponsored By Betfred) (GBB Race) | D19: Class 3 | E19: 10 | F19: Good | G19: 6 | H19: Red Red | I19: Crouch, Hector | J19: Moore, Gary and Josh | K19: 4 | L19: 0 | M19: 3 | O19: 5 | P19: 29.562588 | Q19: 0.033826537 | R19: 19 | S19: =IF(AND(ISNUMBER(R19),R19>1,P19>0),R19/P19-1,"") -> -0.35729579 | T19: =IF(AND(ISNUMBER(P19),P19>0),P19*EXP('Read me'!$B$22),"") -> 36.107827
A20: 2:47 | B20: Epsom | C20: Hunt Family Fund Novice Stakes (Sponsored By Betfred) (GBB Race) | D20: Class 3 | E20: 10 | F20: Good | G20: 6 | H20: Paraone | I20: Wood, George | J20: Main, Mrs H S | K20: 1 | L20: 0 | M20: 3 | N20: 13 | O20: 6 | P20: 753.8789 | Q20: 0.001326473 | R20: 151 | S20: =IF(AND(ISNUMBER(R20),R20>1,P20>0),R20/P20-1,"") -> -0.79970258 | T20: =IF(AND(ISNUMBER(P20),P20>0),P20*EXP('Read me'!$B$22),"") -> 920.78977
A21: 3:22 | B21: Epsom | C21: Betfred Nifty 50 Jump Jockeys Derby Handicap (Professional Jump Jockeys) (GBBPlus Race) | D21: Class 4 | E21: 12 | F21: Good | G21: 13 | H21: Seeking Charles (FR) | I21: Davies, James | J21: Usher, M D I | K21: 11 | L21: 75 | M21: 5 | N21: 27 | O21: 1 | P21: 4.8890414 | Q21: 0.20453907 | R21: 4.5 | S21: =IF(AND(ISNUMBER(R21),R21>1,P21>0),R21/P21-1,"") -> -0.079574171 | T21: =IF(AND(ISNUMBER(P21),P21>0),P21*EXP('Read me'!$B$22),"") -> 5.9714887
A22: 3:22 | B22: Epsom | C22: Betfred Nifty 50 Jump Jockeys Derby Handicap (Professional Jump Jockeys) (GBBPlus Race) | D22: Class 4 | E22: 12 | F22: Good | G22: 13 | H22: Nibras Gold (IRE) | I22: Burke, Jonathan | J22: Owen, J P | K22: 3 | L22: 79 | M22: 8 | N22: 15 | O22: 2 | P22: 6.9023838 | Q22: 0.14487748 | R22: 8 | S22: =IF(AND(ISNUMBER(R22),R22>1,P22>0),R22/P22-1,"") -> 0.15901988 | T22: =IF(AND(ISNUMBER(P22),P22>0),P22*EXP('Read me'!$B$22),"") -> 8.4305906
A23: 3:22 | B23: Epsom | C23: Betfred Nifty 50 Jump Jockeys Derby Handicap (Professional Jump Jockeys) (GBBPlus Race) | D23: Class 4 | E23: 12 | F23: Good | G23: 13 | H23: Tiger (FR) | I23: Cobden, Harry | J23: Williams, Ian | K23: 8 | L23: 84 | M23: 4 | N23: 28 | O23: 3 | P23: 7.2981959 | Q23: 0.13702016 | R23: 8 | S23: =IF(AND(ISNUMBER(R23),R23>1,P23>0),R23/P23-1,"") -> 0.096161312 | T23: =IF(AND(ISNUMBER(P23),P23>0),P23*EXP('Read me'!$B$22),"") -> 8.9140366
A24: 3:22 | B24: Epsom | C24: Betfred Nifty 50 Jump Jockeys Derby Handicap (Professional Jump Jockeys) (GBBPlus Race) | D24: Class 4 | E24: 12 | F24: Good | G24: 13 | H24: Fox Avatar (IRE) | I24: Powell, Brendan | J24: Varian, Roger | K24: 12 | L24: 81 | M24: 5 | N24: 18 | O24: 4 | P24: 7.6624859 | Q24: 0.13050595 | R24: 7.5 | S24: =IF(AND(ISNUMBER(R24),R24>1,P24>0),R24/P24-1,"") -> -0.02120538 | T24: =IF(AND(ISNUMBER(P24),P24>0),P24*EXP('Read me'!$B$22),"") -> 9.3589814
A25: 3:22 | B25: Epsom | C25: Betfred Nifty 50 Jump Jockeys Derby Handicap (Professional Jump Jockeys) (GBBPlus Race) | D25: Class 4 | E25: 12 | F25: Good | G25: 13 | H25: Damascus Steel (IRE) | I25: Hughes, Brian | J25: Arnolda, Gihan | K25: 9 | L25: 77 | M25: 6 | N25: 15 | O25: 5 | P25: 15.267406 | Q25: 0.065499009 | R25: 12 | S25: =IF(AND(ISNUMBER(R25),R25>1,P25>0),R25/P25-1,"") -> -0.21401189 | T25: =IF(AND(ISNUMBER(P25),P25>0),P25*EXP('Read me'!$B$22),"") -> 18.647652
A26: 3:22 | B26: Epsom | C26: Betfred Nifty 50 Jump Jockeys Derby Handicap (Professional Jump Jockeys) (GBBPlus Race) | D26: Class 4 | E26: 12 | F26: Good | G26: 13 | H26: Marnier (IRE) | I26: Quinn, Caoilin | J26: Moore, Gary and Josh | K26: 10 | L26: 86 | M26: 4 | N26: 28 | O26: 6 | P26: 16.774456 | Q26: 0.059614453 | R26: 6.5 | S26: =IF(AND(ISNUMBER(R26),R26>1,P26>0),R26/P26-1,"") -> -0.61250606 | T26: =IF(AND(ISNUMBER(P26),P26>0),P26*EXP('Read me'!$B$22),"") -> 20.488367
A27: 3:22 | B27: Epsom | C27: Betfred Nifty 50 Jump Jockeys Derby Handicap (Professional Jump Jockeys) (GBBPlus Race) | D27: Class 4 | E27: 12 | F27: Good | G27: 13 | H27: Zarakerjack (FR) | I27: Mitchell, Freddie | J27: Moore, Gary and Josh | K27: 7 | L27: 70 | M27: 4 | N27: 13 | O27: 7 | P27: 17.731917 | Q27: 0.056395481 | R27: 12 | S27: =IF(AND(ISNUMBER(R27),R27>1,P27>0),R27/P27-1,"") -> -0.32325423 | T27: =IF(AND(ISNUMBER(P27),P27>0),P27*EXP('Read me'!$B$22),"") -> 21.657813
A28: 3:22 | B28: Epsom | C28: Betfred Nifty 50 Jump Jockeys Derby Handicap (Professional Jump Jockeys) (GBBPlus Race) | D28: Class 4 | E28: 12 | F28: Good | G28: 13 | H28: Oneforthegutter | I28: Todd, C J | J28: Williams, Ian | K28: 6 | L28: 82 | M28: 7 | N28: 8 | O28: 8 | P28: 21.725843 | Q28: 0.046028132 | R28: 11 | S28: =IF(AND(ISNUMBER(R28),R28>1,P28>0),R28/P28-1,"") -> -0.49369054 | T28: =IF(AND(ISNUMBER(P28),P28>0),P28*EXP('Read me'!$B$22),"") -> 26.536005
A29: 3:22 | B29: Epsom | C29: Betfred Nifty 50 Jump Jockeys Derby Handicap (Professional Jump Jockeys) (GBBPlus Race) | D29: Class 4 | E29: 12 | F29: Good | G29: 13 | H29: Taritino (IRE) | I29: Fisher, Taylor | J29: Tickle, J | K29: 1 | L29: 75 | M29: 6 | N29: 14 | O29: 9 | P29: 26.356445 | Q29: 0.037941384 | R29: 15 | S29: =IF(AND(ISNUMBER(R29),R29>1,P29>0),R29/P29-1,"") -> -0.43087924 | T29: =IF(AND(ISNUMBER(P29),P29>0),P29*EXP('Read me'!$B$22),"") -> 32.191835
A30: 3:22 | B30: Epsom | C30: Betfred Nifty 50 Jump Jockeys Derby Handicap (Professional Jump Jockeys) (GBBPlus Race) | D30: Class 4 | E30: 12 | F30: Good | G30: 13 | H30: Gordon Grey (IRE) | I30: Cannon, Tom J | J30: Baker, George | K30: 5 | L30: 83 | M30: 6 | N30: 17 | O30: 10 | P30: 27.921993 | Q30: 0.035814062 | R30: 13 | S30: =IF(AND(ISNUMBER(R30),R30>1,P30>0),R30/P30-1,"") -> -0.53441719 | T30: =IF(AND(ISNUMBER(P30),P30>0),P30*EXP('Read me'!$B$22),"") -> 34.104
A31: 3:22 | B31: Epsom | C31: Betfred Nifty 50 Jump Jockeys Derby Handicap (Professional Jump Jockeys) (GBBPlus Race) | D31: Class 4 | E31: 12 | F31: Good | G31: 13 | H31: Hengest | I31: Edwards, Lee | J31: Cunha, Dylan | K31: 2 | L31: 79 | M31: 4 | N31: 8 | O31: 11 | P31: 29.472138 | Q31: 0.033930351 | R31: 21 | S31: =IF(AND(ISNUMBER(R31),R31>1,P31>0),R31/P31-1,"") -> -0.28746262 | T31: =IF(AND(ISNUMBER(P31),P31>0),P31*EXP('Read me'!$B$22),"") -> 35.997351
... A57: 5:07 | B57: Epsom | C57: Betfred Follow Us On X Handicap | D57: Class 4 | E57: 7 | F57: Good | G57: 10 | H57: Our Guy (IRE) | I57: Bass, George | J57: Coakley, D J | K57: 4 | L57: 67 | M57: 3 | N57: 87 | O57: 10 | P57: 53.11325 | Q57: 0.018827694 | R57: 51 | S57: =IF(AND(ISNUMBER(R57),R57>1,P57>0),R57/P57-1,"") -> -0.039787617 | T57: =IF(AND(ISNUMBER(P57),P57>0),P57*EXP('Read me'!$B$22),"") -> 64.87267
