Workbook

Sheet Read me
A1: Predictions for 2026-09-28
A3: Runners | B3: 434
A4: Races | B4: 45
A5: Meetings | B5: 6
A7: The model | B7: gated 13:43
A8: Features | B8: 993
A9: Trained through | B9: 2026-09-22
A10: Boosting rounds | B10: 12000
A11: Target | B11: logit_norm_prob
A12: Feature code hash | B12: f879b10c8369467a
A14: How to read it
A15: Predicted BSP | B15: The model's forecast of the Betfair Starting Price, from pre-race information only. The prices in each race make a book of exactly 100%.
A16: Win probability | B16: 1 / predicted BSP: the model's chance for the horse, normalised within the race.
A17: Model rank | B17: 1 = the model's shortest price in the race (highlighted green).
A18: Card odds (HRB) | B18: The odds printed on the horseracebase card when it was fetched: a bookmaker forecast, not the Betfair morning price the early-price rule was tested against.
A19: Card odds vs model | B19: Card odds / predicted BSP - 1. Positive: the card is longer than the model.
A21: The early-price rule
A22: Margin (log) | B22: 0.2
A23: Rule: back at Betfair ≥ | B23: Predicted BSP × e^margin: at 0.2, a Betfair price at least 1.22 times the model's (the model at least 22% shorter). The rule was fixed before it was first tested (reports/clv_betfair_2026q1.md): back at Betfair's morning volume-weighted price, where at least £100 has been matched in the morning, and close the position at BSP (lay at BSP to level the book). It is a trade on the price, not a bet held to the result. The margin (blue) is the one input: change it to see the prices at another threshold.
A25: Note | B25: The served model from 29 Sep (the complete-careers pair gated with race_xent), re-run in full on horseracebase's card as it stood at 13:43 UTC (predict-now run 34): 434 runners in 45 races, every one priced. Races already run are included for reference. Each non-runner's price and share of the book are from the last run that priced it (05:08 to 12:48 UTC). 34 non-runners since the prices were first made, in 20 races (sheet Non-runners). The prices here are without them, each race a book of 100%: a non-runner's share of the book goes to the rest of its race, whose prices shorten by about that share.

Sheet Top picks
A1: Time | B1: Course | C1: Race | D1: Runners | E1: Top pick | F1: Jockey | G1: Trainer | H1: Predicted BSP | I1: Win probability | J1: Second choice | K1: Second's BSP | L1: Second's probability | M1: Probability gap | N1: Card odds (HRB) | O1: Rule: back at Betfair ≥
A2: 1:24 | B2: Down Royal | C2: Molson Coors Beverage Company Nursery Handicap | D2: 6 | E2: Santo Parvenue (IRE) | F2: Lee, W J | G2: Harty, Edward and Patrick | H2: 2.2147676 | I2: 0.45151465 | J2: Premier View (IRE) | K2: 4.3596875 | L2: 0.22937424 | M2: =IF(AND(ISNUMBER(I2),ISNUMBER(L2)),I2-L2,"") -> 0.22214041 | N2: 1.8 | O2: =IF(AND(ISNUMBER(H2),H2>0),H2*EXP('Read me'!$B$22),"") -> 2.7051232
A3: 1:30 | B3: Brighton | C3: Matchbook SignUp - Get 20% Back On Losses Handicap | D3: 10 | E3: Bated Breeze (IRE) | F3: Marsh, Finley | G3: Moore, Gary and Josh | H3: 5.1776255 | I3: 0.19313873 | J3: Roman Spring (IRE) | K3: 6.3779397 | L3: 0.15679044 | M3: =IF(AND(ISNUMBER(I3),ISNUMBER(L3)),I3-L3,"") -> 0.036348283 | N3: 5.5 | O3: =IF(AND(ISNUMBER(H3),H3>0),H3*EXP('Read me'!$B$22),"") -> 6.3239661
A4: 1:35 | B4: Roscommon | C4: Athleague Maiden Hurdle | D4: 13 | E4: Direct Approach (IRE) | F4: Kennedy, J W | G4: Elliott, Gordon | H4: 3.1862358 | I4: 0.31384997 | J4: Telegram Sam (IRE) | K4: 3.1927228 | L4: 0.31321228 | M4: =IF(AND(ISNUMBER(I4),ISNUMBER(L4)),I4-L4,"") -> 0.00063768222 | N4: 5 | O4: =IF(AND(ISNUMBER(H4),H4>0),H4*EXP('Read me'!$B$22),"") -> 3.8916772
A5: 1:44 | B5: Hamilton | C5: Clearwater DC Ltd Environmental Solutions Amateur Jockeys Handicap | D5: 6 | E5: Annie Edson Taylor | F5: Brown, Pippa | G5: Makin, Phillip | H5: 3.1430511 | I5: 0.31816218 | J5: Bay Breeze | K5: 4.5721161 | L5: 0.21871711 | M5: =IF(AND(ISNUMBER(I5),ISNUMBER(L5)),I5-L5,"") -> 0.099445072 | N5: 2.5 | O5: =IF(AND(ISNUMBER(H5),H5>0),H5*EXP('Read me'!$B$22),"") -> 3.8389313
A6: 1:50 | B6: Newton Abbot | C6: Celebrating Devon Women In Business Handicap Chase (GBB Race) | D6: 3 | E6: Depalma (IRE) | F6: Skelton, Harry | G6: Skelton, Daniel | H6: 2.195562 | I6: 0.45546425 | J6: Muskerry Rock (IRE) | K6: 3.1859008 | L6: 0.31388297 | M6: =IF(AND(ISNUMBER(I6),ISNUMBER(L6)),I6-L6,"") -> 0.14158128 | N6: 1.6666667 | O6: =IF(AND(ISNUMBER(H6),H6>0),H6*EXP('Read me'!$B$22),"") -> 2.6816655
A7: 1:59 | B7: Down Royal | C7: Coors Fillies Handicap | D7: 10 | E7: Nellcote (IRE) | F7: McDonogh, D P | G7: OBrien, Joseph Patrick | H7: 4.9114672 | I7: 0.20360515 | J7: Stellar Moment (IRE) | K7: 5.3404808 | L7: 0.18724906 | M7: =IF(AND(ISNUMBER(I7),ISNUMBER(L7)),I7-L7,"") -> 0.01635609 | N7: 4.5 | O7: =IF(AND(ISNUMBER(H7),H7>0),H7*EXP('Read me'!$B$22),"") -> 5.9988796
A8: 2:05 | B8: Brighton | C8: Matchbook Betting Exchange Supporting UK Racing Maiden Stakes (GBB Race) | D8: 4 | E8: Galileo Star | F8: Ryan, Rossa | G8: Tate, James | H8: 2.5514401 | I8: 0.39193551 | J8: River Nile (IRE) | K8: 2.984331 | L8: 0.33508347 | M8: =IF(AND(ISNUMBER(I8),ISNUMBER(L8)),I8-L8,"") -> 0.056852042 | N8: 1.5714286 | O8: =IF(AND(ISNUMBER(H8),H8>0),H8*EXP('Read me'!$B$22),"") -> 3.116336
A9: 2:10 | B9: Roscommon | C9: Garys Gardening Services Handicap Hurdle (0-100) | D9: 16 | E9: Cool Summer (IRE) | F9: Enright, P T | G9: McLoughlin, Hilary | H9: 3.935622 | I9: 0.25408944 | J9: Colesberg (IRE) | K9: 8.6710864 | L9: 0.1153258 | M9: =IF(AND(ISNUMBER(I9),ISNUMBER(L9)),I9-L9,"") -> 0.13876364 | N9: 4 | O9: =IF(AND(ISNUMBER(H9),H9>0),H9*EXP('Read me'!$B$22),"") -> 4.8069796
A10: 2:19 | B10: Hamilton | C10: Moira Stein Memorial EBF Restricted Maiden Stakes (GBB Race) | D10: 6 | E10: Cyberspace | F10: Mulrennan, Paul | G10: Smart, B | H10: 2.0902903 | I10: 0.47840245 | J10: Ponte Carlo (IRE) | K10: 4.2862463 | L10: 0.23330437 | M10: =IF(AND(ISNUMBER(I10),ISNUMBER(L10)),I10-L10,"") -> 0.24509807 | N10: 2.75 | O10: =IF(AND(ISNUMBER(H10),H10>0),H10*EXP('Read me'!$B$22),"") -> 2.5530864
A11: 2:25 | B11: Newton Abbot | C11: Jodie Standings Point-To-Point Recruits Novices Hurdle (GBB Race) | D11: 6 | E11: Matiwo (FR) | F11: Gethings, Ciaran | G11: Williams, Mrs Jane | H11: 1.3053142 | I11: 0.7660991 | J11: Scotts Legacy (IRE) | K11: 5.188916 | L11: 0.19271848 | M11: =IF(AND(ISNUMBER(I11),ISNUMBER(L11)),I11-L11,"") -> 0.57338062 | N11: 1.2857143 | O11: =IF(AND(ISNUMBER(H11),H11>0),H11*EXP('Read me'!$B$22),"") -> 1.5943143
A12: 2:34 | B12: Down Royal | C12: Irish EBF Auction Series Fillies Maiden | D12: 9 | E12: Essence Of Time | F12: Lordan, W M | G12: Oliver, Andrew | H12: 2.308552 | I12: 0.43317196 | J12: Ladrona (IRE) | K12: 3.9612645 | L12: 0.25244464 | M12: =IF(AND(ISNUMBER(I12),ISNUMBER(L12)),I12-L12,"") -> 0.18072732 | N12: 2.2 | O12: =IF(AND(ISNUMBER(H12),H12>0),H12*EXP('Read me'!$B$22),"") -> 2.8196718
A13: 2:40 | B13: Brighton | C13: Follow Matchbook On X Nursery | D13: 13 | E13: Magical Life | F13: Ryan, Rossa | G13: Moore, J S | H13: 6.7963234 | I13: 0.14713838 | J13: Hello You Ten (IRE) | K13: 8.0427547 | L13: 0.12433551 | M13: =IF(AND(ISNUMBER(I13),ISNUMBER(L13)),I13-L13,"") -> 0.022802869 | N13: 5.5 | O13: =IF(AND(ISNUMBER(H13),H13>0),H13*EXP('Read me'!$B$22),"") -> 8.3010481
... A20: 3:29 | B20: Hamilton | C20: John MacKenzie And Hamish MacGregor Memorial Handicap | D20: 13 | E20: Impartiality | F20: Gray, S A | G20: Makin, Phillip | H20: 5.5218413 | I20: 0.18109901 | J20: El Matador (IRE) | K20: 7.3111805 | L20: 0.13677682 | M20: =IF(AND(ISNUMBER(I20),ISNUMBER(L20)),I20-L20,"") -> 0.044322195 | N20: 5 | O20: =IF(AND(ISNUMBER(H20),H20>0),H20*EXP('Read me'!$B$22),"") -> 6.7443922
A21: 3:35 | B21: Newton Abbot | C21: Final Furlong Before I Do Selling Handicap Hurdle | D21: 6 | E21: Berry Edge (IRE) | G21: Skelton, Daniel | H21: 2.6844746 | I21: 0.37251237 | J21: Saint Polo (FR) | K21: 3.6120282 | L21: 0.27685276 | M21: =IF(AND(ISNUMBER(I21),ISNUMBER(L21)),I21-L21,"") -> 0.095659611 | N21: 2.875 | O21: =IF(AND(ISNUMBER(H21),H21>0),H21*EXP('Read me'!$B$22),"") -> 3.2788247
A22: 3:44 | B22: Down Royal | C22: Molson Coors Beverage Company Handicap | D22: 14 | E22: Send Harry (IRE) | F22: Dalton, J S | G22: McCutcheon, Miss Evanna | H22: 6.9803971 | I22: 0.14325833 | J22: Barbapapa (IRE) | K22: 7.3739447 | L22: 0.13561263 | M22: =IF(AND(ISNUMBER(I22),ISNUMBER(L22)),I22-L22,"") -> 0.0076456995 | N22: 7 | O22: =IF(AND(ISNUMBER(H22),H22>0),H22*EXP('Read me'!$B$22),"") -> 8.5258763
A23: 3:50 | B23: Brighton | C23: Matchbook Monthly Bet-Builder Rebate Handicap | D23: 7 | E23: Love You Back (IRE) | F23: Fentiman, Warren | G23: Moore, Gary and Josh | H23: 5.3994012 | I23: 0.18520572 | J23: Darkest Red | K23: 5.5871826 | L23: 0.17898108 | M23: =IF(AND(ISNUMBER(I23),ISNUMBER(L23)),I23-L23,"") -> 0.0062246378 | N23: 4 | O23: =IF(AND(ISNUMBER(H23),H23>0),H23*EXP('Read me'!$B$22),"") -> 6.5948435
A24: 3:55 | B24: Roscommon | C24: Castlecoote Handicap Hurdle | D24: 11 | E24: Adaliz (GER) | F24: OKeeffe, Darragh | G24: Bromhead, Henry De | H24: 4.580431 | I24: 0.21832007 | J24: Ilbdare (IRE) | K24: 7.9562325 | L24: 0.12568763 | M24: =IF(AND(ISNUMBER(I24),ISNUMBER(L24)),I24-L24,"") -> 0.09263244 | N24: 5.5 | O24: =IF(AND(ISNUMBER(H24),H24>0),H24*EXP('Read me'!$B$22),"") -> 5.594551
A25: 4:04 | B25: Hamilton | C25: Barbara Ann Letham And Son Johnathan Memorial Handicap | D25: 9 | E25: City Captain | F25: Tudhope, Daniel | G25: Bethell, Harriet | H25: 2.6592292 | I25: 0.37604882 | J25: Franciscos Piece | K25: 6.1222196 | L25: 0.16333945 | M25: =IF(AND(ISNUMBER(I25),ISNUMBER(L25)),I25-L25,"") -> 0.21270937 | N25: 2.2 | O25: =IF(AND(ISNUMBER(H25),H25>0),H25*EXP('Read me'!$B$22),"") -> 3.2479899
A26: 4:10 | B26: Newton Abbot | C26: Paul Fergusons Jumpers To Follow Handicap Hurdle | D26: 4 | E26: Kom Tu Voudras (FR) | F26: Cobden, Harry | G26: Bramley, Faye | H26: 3.0587372 | I26: 0.3269323 | J26: Kilnew Supreme (IRE) | K26: 3.2802206 | L26: 0.30485755 | M26: =IF(AND(ISNUMBER(I26),ISNUMBER(L26)),I26-L26,"") -> 0.022074758 | N26: 3.5 | O26: =IF(AND(ISNUMBER(H26),H26>0),H26*EXP('Read me'!$B$22),"") -> 3.73595
A27: 4:19 | B27: Down Royal | C27: Pravha Handicap (0-60) (Div 1) | D27: 14 | E27: No More Hiding | F27: Lee, W J | G27: Oliver, Andrew | H27: 3.5675541 | I27: 0.28030409 | J27: Chapel Island (IRE) | K27: 6.9261387 | L27: 0.14438059 | M27: =IF(AND(ISNUMBER(I27),ISNUMBER(L27)),I27-L27,"") -> 0.1359235 | N27: 3.75 | O27: =IF(AND(ISNUMBER(H27),H27>0),H27*EXP('Read me'!$B$22),"") -> 4.3574204
A28: 4:22 | B28: Wolverhampton | C28: Free Tips On attheraces.com Amateur Jockeys Handicap | D28: 10 | E28: No Knee Never (IRE) | F28: Callan, Mr Henry | G28: Owen, J P | H28: 3.5076096 | I28: 0.28509444 | J28: Pursuit Of Truth (IRE) | K28: 6.5228194 | L28: 0.15330794 | M28: =IF(AND(ISNUMBER(I28),ISNUMBER(L28)),I28-L28,"") -> 0.1317865 | N28: 3.5 | O28: =IF(AND(ISNUMBER(H28),H28>0),H28*EXP('Read me'!$B$22),"") -> 4.2842041
A29: 4:27 | B29: Brighton | C29: Play Your Multiples At matchbook.com Handicap | D29: 11 | E29: Campani | F29: Muscutt, D | G29: Simcock, D M | H29: 4.4476212 | I29: 0.22483929 | J29: Royal County Glory (IRE) | K29: 4.6089462 | L29: 0.21696934 | M29: =IF(AND(ISNUMBER(I29),ISNUMBER(L29)),I29-L29,"") -> 0.0078699557 | N29: 5 | O29: =IF(AND(ISNUMBER(H29),H29>0),H29*EXP('Read me'!$B$22),"") -> 5.4323367
A30: 4:30 | B30: Roscommon | C30: Mon 28th Sep 2026 | D30: 4 | E30: Wild Bill Hickok (IRE) | F30: Finegan, Eoghan | G30: Murphy, Ciaran | H30: 1.8662594 | I30: 0.53583121 | J30: Femme Magnifique (IRE) | K30: 4.1708458 | L30: 0.23975952 | M30: =IF(AND(ISNUMBER(I30),ISNUMBER(L30)),I30-L30,"") -> 0.29607168 | N30: 2.5 | O30: =IF(AND(ISNUMBER(H30),H30>0),H30*EXP('Read me'!$B$22),"") -> 2.2794543
A31: 4:38 | B31: Hamilton | C31: Phoenix Drilling Ground Investigation Handicap | D31: 8 | E31: Roach Power (IRE) | F31: Mulrennan, Paul | G31: Wigham, M | H31: 5.6681008 | I31: 0.17642594 | J31: Thunderstorm Katie | K31: 5.8405577 | L31: 0.17121653 | M31: =IF(AND(ISNUMBER(I31),ISNUMBER(L31)),I31-L31,"") -> 0.0052094108 | N31: 3 | O31: =IF(AND(ISNUMBER(H31),H31>0),H31*EXP('Read me'!$B$22),"") -> 6.923034
A32: 4:43 | B32: Newton Abbot | C32: Par Inn Bulpin Cup Amateur Jockeys Handicap Hurdle | D32: 7 | E32: Pooroldmackley (IRE) | F32: Williams, Eleanor | G32: Williams, Mrs C | H32: 2.9188361 | I32: 0.34260231 | J32: Final Entry (IRE) | K32: 5.1859691 | L32: 0.19282799 | M32: =IF(AND(ISNUMBER(I32),ISNUMBER(L32)),I32-L32,"") -> 0.14977432 | N32: 3.25 | O32: =IF(AND(ISNUMBER(H32),H32>0),H32*EXP('Read me'!$B$22),"") -> 3.5650745
A33: 4:50 | B33: Down Royal | C33: Pravha Handicap (0-60) (Div 2) | D33: 14 | E33: Connecteo (IRE) | F33: Coen, Ben M | G33: Oliver, Andrew | H33: 4.4450288 | I33: 0.22497042 | J33: Flagstone Lady (IRE) | K33: 5.07356 | L33: 0.19710026 | M33: =IF(AND(ISNUMBER(I33),ISNUMBER(L33)),I33-L33,"") -> 0.027870158 | N33: 5 | O33: =IF(AND(ISNUMBER(H33),H33>0),H33*EXP('Read me'!$B$22),"") -> 5.4291705
... A46: 8:30 | B46: Wolverhampton | C46: Free Digital Racecard At raceday-ready.com Handicap | D46: 11 | E46: The Anthony Gover | F46: Loughnane, Billy | G46: Newland, Dr R D P | H46: 3.1856754 | I46: 0.31390518 | J46: Back At One (IRE) | K46: 5.1792391 | L46: 0.19307855 | M46: =IF(AND(ISNUMBER(I46),ISNUMBER(L46)),I46-L46,"") -> 0.12082662 | N46: 2.25 | O46: =IF(AND(ISNUMBER(H46),H46>0),H46*EXP('Read me'!$B$22),"") -> 3.8909927

Sheet Non-runners
A1: Time | B1: Course | C1: Horse | D1: Its predicted BSP | E1: Share of the book | F1: Others' prices ×
A2: 1:24 | B2: Down Royal | C2: Stellar Path (IRE) | D2: 21.296503 | E2: 0.046956066 | F2: =IF(ISNUMBER(E2),1-E2,"") -> 0.95304393
A3: 1:24 | B3: Down Royal | C3: The Drambling Man (IRE) | D3: 7.4336004 | E3: 0.13452432 | F3: =IF(ISNUMBER(E3),1-E3,"") -> 0.86547568
A4: 1:35 | B4: Roscommon | C4: Easy Listening (IRE) | D4: 107.62421 | E4: 0.0092915894 | F4: =IF(ISNUMBER(E4),1-E4,"") -> 0.99070841
A5: 1:35 | B5: Roscommon | C5: The Farmers Bar (IRE) | D5: 121.20971 | E5: 0.0082501642 | F5: =IF(ISNUMBER(E5),1-E5,"") -> 0.99174984
A6: 2:05 | B6: Brighton | C6: Poor Relation (FR) | D6: 12.491807 | E6: 0.080052469 | F6: =IF(ISNUMBER(E6),1-E6,"") -> 0.91994753
A7: 2:05 | B7: Brighton | C7: Sakura Impact (IRE) | D7: 90.401938 | E7: 0.01106171 | F7: =IF(ISNUMBER(E7),1-E7,"") -> 0.98893829
A8: 2:10 | B8: Roscommon | C8: Arctic Piper (IRE) | D8: 77.683457 | E8: 0.012872754 | F8: =IF(ISNUMBER(E8),1-E8,"") -> 0.98712725
A9: 2:10 | B9: Roscommon | C9: Colins Friend (IRE) | D9: 5.2303647 | E9: 0.19119126 | F9: =IF(ISNUMBER(E9),1-E9,"") -> 0.80880874
A10: 2:10 | B10: Roscommon | C10: Kome Dans Un Reve (FR) | D10: 91.885249 | E10: 0.01088314 | F10: =IF(ISNUMBER(E10),1-E10,"") -> 0.98911686
A11: 2:25 | B11: Newton Abbot | C11: Ride Like A Girl (FR) | D11: 4.1022518 | E11: 0.24376855 | F11: =IF(ISNUMBER(E11),1-E11,"") -> 0.75623145
A12: 2:34 | B12: Down Royal | C12: Star Glory (IRE) | D12: 3.4254285 | E12: 0.29193428 | F12: =IF(ISNUMBER(E12),1-E12,"") -> 0.70806572
A13: 2:45 | B13: Roscommon | C13: Bigcitydreams (IRE) | D13: 632.58721 | E13: 0.0015808097 | F13: =IF(ISNUMBER(E13),1-E13,"") -> 0.99841919
... A35: 8:30 | B35: Wolverhampton | C35: Vega Storm (IRE) | D35: 12.320136 | E35: 0.081167938 | F35: =IF(ISNUMBER(E35),1-E35,"") -> 0.91883206

Sheet gated 13.43 vs 12.48
A1: Time | B1: Course | C1: Race | D1: Runners (now) | E1: gated 13:43 top pick | F1: gated 13:43 BSP | G1: Its 12:48 BSP | H1: 12:48 top pick (runners still declared) | I1: 12:48 BSP | J1: Same pick? | K1: gated 13:43 vs 12:48 on the gated 13:43's pick
A2: 1:24 | B2: Down Royal | C2: Molson Coors Beverage Company Nursery Handicap | D2: 6 | E2: Santo Parvenue (IRE) | F2: 2.2147676 | G2: 2.2147676 | H2: Santo Parvenue (IRE) | I2: 2.2147676 | J2: =IF(E2=H2,"yes","no") -> yes | K2: =IF(AND(ISNUMBER(F2),ISNUMBER(G2)),F2/G2-1,"") -> 0
A3: 1:30 | B3: Brighton | C3: Matchbook SignUp - Get 20% Back On Losses Handicap | D3: 10 | E3: Bated Breeze (IRE) | F3: 5.1776255 | G3: 5.1776255 | H3: Bated Breeze (IRE) | I3: 5.1776255 | J3: =IF(E3=H3,"yes","no") -> yes | K3: =IF(AND(ISNUMBER(F3),ISNUMBER(G3)),F3/G3-1,"") -> 0
A4: 1:35 | B4: Roscommon | C4: Athleague Maiden Hurdle | D4: 13 | E4: Direct Approach (IRE) | F4: 3.1862358 | G4: 3.1862358 | H4: Direct Approach (IRE) | I4: 3.1862358 | J4: =IF(E4=H4,"yes","no") -> yes | K4: =IF(AND(ISNUMBER(F4),ISNUMBER(G4)),F4/G4-1,"") -> 0
A5: 1:44 | B5: Hamilton | C5: Clearwater DC Ltd Environmental Solutions Amateur Jockeys Handicap | D5: 6 | E5: Annie Edson Taylor | F5: 3.1430511 | G5: 3.1430511 | H5: Annie Edson Taylor | I5: 3.1430511 | J5: =IF(E5=H5,"yes","no") -> yes | K5: =IF(AND(ISNUMBER(F5),ISNUMBER(G5)),F5/G5-1,"") -> 0
A6: 1:50 | B6: Newton Abbot | C6: Celebrating Devon Women In Business Handicap Chase (GBB Race) | D6: 3 | E6: Depalma (IRE) | F6: 2.195562 | G6: 2.195562 | H6: Depalma (IRE) | I6: 2.195562 | J6: =IF(E6=H6,"yes","no") -> yes | K6: =IF(AND(ISNUMBER(F6),ISNUMBER(G6)),F6/G6-1,"") -> 0
A7: 1:59 | B7: Down Royal | C7: Coors Fillies Handicap | D7: 10 | E7: Nellcote (IRE) | F7: 4.9114672 | G7: 4.9114672 | H7: Nellcote (IRE) | I7: 4.9114672 | J7: =IF(E7=H7,"yes","no") -> yes | K7: =IF(AND(ISNUMBER(F7),ISNUMBER(G7)),F7/G7-1,"") -> 0
A8: 2:05 | B8: Brighton | C8: Matchbook Betting Exchange Supporting UK Racing Maiden Stakes (GBB Race) | D8: 4 | E8: Galileo Star | F8: 2.5514401 | G8: 2.4846291 | H8: Galileo Star | I8: 2.4846291 | J8: =IF(E8=H8,"yes","no") -> yes | K8: =IF(AND(ISNUMBER(F8),ISNUMBER(G8)),F8/G8-1,"") -> 0.026889735
A9: 2:10 | B9: Roscommon | C9: Garys Gardening Services Handicap Hurdle (0-100) | D9: 16 | E9: Cool Summer (IRE) | F9: 3.935622 | G9: 3.935622 | H9: Cool Summer (IRE) | I9: 3.935622 | J9: =IF(E9=H9,"yes","no") -> yes | K9: =IF(AND(ISNUMBER(F9),ISNUMBER(G9)),F9/G9-1,"") -> 0
A10: 2:19 | B10: Hamilton | C10: Moira Stein Memorial EBF Restricted Maiden Stakes (GBB Race) | D10: 6 | E10: Cyberspace | F10: 2.0902903 | G10: 2.0902903 | H10: Cyberspace | I10: 2.0902903 | J10: =IF(E10=H10,"yes","no") -> yes | K10: =IF(AND(ISNUMBER(F10),ISNUMBER(G10)),F10/G10-1,"") -> 0
A11: 2:25 | B11: Newton Abbot | C11: Jodie Standings Point-To-Point Recruits Novices Hurdle (GBB Race) | D11: 6 | E11: Matiwo (FR) | F11: 1.3053142 | G11: 1.3053142 | H11: Matiwo (FR) | I11: 1.3053142 | J11: =IF(E11=H11,"yes","no") -> yes | K11: =IF(AND(ISNUMBER(F11),ISNUMBER(G11)),F11/G11-1,"") -> 0
A12: 2:34 | B12: Down Royal | C12: Irish EBF Auction Series Fillies Maiden | D12: 9 | E12: Essence Of Time | F12: 2.308552 | G12: 2.3326166 | H12: Essence Of Time | I12: 2.3326166 | J12: =IF(E12=H12,"yes","no") -> yes | K12: =IF(AND(ISNUMBER(F12),ISNUMBER(G12)),F12/G12-1,"") -> -0.010316546
A13: 2:40 | B13: Brighton | C13: Follow Matchbook On X Nursery | D13: 13 | E13: Magical Life | F13: 6.7963234 | G13: 6.7963234 | H13: Magical Life | I13: 6.7963234 | J13: =IF(E13=H13,"yes","no") -> yes | K13: =IF(AND(ISNUMBER(F13),ISNUMBER(G13)),F13/G13-1,"") -> 0
... A46: 8:30 | B46: Wolverhampton | C46: Free Digital Racecard At raceday-ready.com Handicap | D46: 11 | E46: The Anthony Gover | F46: 3.1856754 | G46: 3.1856754 | H46: The Anthony Gover | I46: 3.1856754 | J46: =IF(E46=H46,"yes","no") -> yes | K46: =IF(AND(ISNUMBER(F46),ISNUMBER(G46)),F46/G46-1,"") -> 0
A48: Races with the same top pick | E48: =COUNTIF(J2:J46,"yes")&" of "&COUNTA(J2:J46) -> 45 of 45
A49: 12:48: the same model on horseracebase's card at 12:48 UTC (predict-now run 33), the workbook sent then. Since then one non-runner (Sakura Impact, Brighton 2:05, a race already run).

Sheet All runners
A1: Time | B1: Course | C1: Race | D1: Class | E1: Furlongs | F1: Going | G1: Runners | H1: Horse | I1: Jockey | J1: Trainer | K1: Draw | L1: OR | M1: Age | N1: Days since run | O1: Model rank | P1: Predicted BSP | Q1: Win probability | R1: Card odds (HRB) | S1: Card odds vs model | T1: Rule: back at Betfair ≥
A2: 1:24 | B2: Down Royal | C2: Molson Coors Beverage Company Nursery Handicap | E2: 5 | F2: Good | G2: 6 | H2: Santo Parvenue (IRE) | I2: Lee, W J | J2: Harty, Edward and Patrick | K2: 4 | L2: 59 | M2: 2 | N2: 11 | O2: 1 | P2: 2.2147676 | Q2: 0.45151465 | R2: 1.8 | S2: =IF(AND(ISNUMBER(R2),R2>1,P2>0),R2/P2-1,"") -> -0.18727363 | T2: =IF(AND(ISNUMBER(P2),P2>0),P2*EXP('Read me'!$B$22),"") -> 2.7051232
A3: 1:24 | B3: Down Royal | C3: Molson Coors Beverage Company Nursery Handicap | E3: 5 | F3: Good | G3: 6 | H3: Premier View (IRE) | I3: Cusack, C | J3: Bromhead, Henry De | K3: 2 | L3: 74 | M3: 2 | N3: 24 | O3: 2 | P3: 4.3596875 | Q3: 0.22937424 | R3: 4.3333333 | S3: =IF(AND(ISNUMBER(R3),R3>1,P3>0),R3/P3-1,"") -> -0.0060449714 | T3: =IF(AND(ISNUMBER(P3),P3>0),P3*EXP('Read me'!$B$22),"") -> 5.3249344
A4: 1:24 | B4: Down Royal | C4: Molson Coors Beverage Company Nursery Handicap | E4: 5 | F4: Good | G4: 6 | H4: Invincible Irish (IRE) | I4: Coen, Ben M | J4: McLoughlin, Daniel | K4: 1 | L4: 61 | M4: 2 | N4: 11 | O4: 3 | P4: 5.9340624 | Q4: 0.16851862 | R4: 6 | S4: =IF(AND(ISNUMBER(R4),R4>1,P4>0),R4/P4-1,"") -> 0.011111717 | T4: =IF(AND(ISNUMBER(P4),P4>0),P4*EXP('Read me'!$B$22),"") -> 7.2478802
A5: 1:24 | B5: Down Royal | C5: Molson Coors Beverage Company Nursery Handicap | E5: 5 | F5: Good | G5: 6 | H5: Rathbran Lady (IRE) | I5: Joyce, Wesley | J5: Mulvany, Michael | K5: 6 | L5: 47 | M5: 2 | N5: 11 | O5: 4 | P5: 15.302509 | Q5: 0.065348762 | R5: 13 | S5: =IF(AND(ISNUMBER(R5),R5>1,P5>0),R5/P5-1,"") -> -0.15046609 | T5: =IF(AND(ISNUMBER(P5),P5>0),P5*EXP('Read me'!$B$22),"") -> 18.690526
A6: 1:24 | B6: Down Royal | C6: Molson Coors Beverage Company Nursery Handicap | E6: 5 | F6: Good | G6: 6 | H6: Annie Tips (IRE) | I6: McAteer, L T | J6: Dowling, James | K6: 7 | L6: 67 | M6: 2 | N6: 36 | O6: 5 | P6: 19.343344 | Q6: 0.051697369 | R6: 19 | S6: =IF(AND(ISNUMBER(R6),R6>1,P6>0),R6/P6-1,"") -> -0.017749989 | T6: =IF(AND(ISNUMBER(P6),P6>0),P6*EXP('Read me'!$B$22),"") -> 23.626014
A7: 1:24 | B7: Down Royal | C7: Molson Coors Beverage Company Nursery Handicap | E7: 5 | F7: Good | G7: 6 | H7: Syrah (IRE) | I7: Mulligan, R M | J7: Weld, Charles | K7: 5 | L7: 58 | M7: 2 | N7: 11 | O7: 6 | P7: 29.809492 | Q7: 0.033546362 | R7: 23 | S7: =IF(AND(ISNUMBER(R7),R7>1,P7>0),R7/P7-1,"") -> -0.22843368 | T7: =IF(AND(ISNUMBER(P7),P7>0),P7*EXP('Read me'!$B$22),"") -> 36.409396
A8: 1:30 | B8: Brighton | C8: Matchbook SignUp - Get 20% Back On Losses Handicap | D8: Class 6 | F8: Good To Firm | G8: 10 | H8: Bated Breeze (IRE) | I8: Marsh, Finley | J8: Moore, Gary and Josh | K8: 3 | L8: 47 | M8: 5 | N8: 21 | O8: 1 | P8: 5.1776255 | Q8: 0.19313873 | R8: 5.5 | S8: =IF(AND(ISNUMBER(R8),R8>1,P8>0),R8/P8-1,"") -> 0.062263002 | T8: =IF(AND(ISNUMBER(P8),P8>0),P8*EXP('Read me'!$B$22),"") -> 6.3239661
A9: 1:30 | B9: Brighton | C9: Matchbook SignUp - Get 20% Back On Losses Handicap | D9: Class 6 | F9: Good To Firm | G9: 10 | H9: Roman Spring (IRE) | I9: ONeill, K T | J9: Bridger, J / Cook, R | K9: 9 | L9: 50 | M9: 6 | N9: 21 | O9: 2 | P9: 6.3779397 | Q9: 0.15679044 | R9: 5 | S9: =IF(AND(ISNUMBER(R9),R9>1,P9>0),R9/P9-1,"") -> -0.21604778 | T9: =IF(AND(ISNUMBER(P9),P9>0),P9*EXP('Read me'!$B$22),"") -> 7.7900331
A10: 1:30 | B10: Brighton | C10: Matchbook SignUp - Get 20% Back On Losses Handicap | D10: Class 6 | F10: Good To Firm | G10: 10 | H10: Dreambird Dolly | I10: Ryan, Rossa | J10: Gallagher, J | K10: 7 | L10: 53 | M10: 4 | N10: 21 | O10: 3 | P10: 6.7049693 | Q10: 0.14914311 | R10: 7.5 | S10: =IF(AND(ISNUMBER(R10),R10>1,P10>0),R10/P10-1,"") -> 0.11857336 | T10: =IF(AND(ISNUMBER(P10),P10>0),P10*EXP('Read me'!$B$22),"") -> 8.189468
A11: 1:30 | B11: Brighton | C11: Matchbook SignUp - Get 20% Back On Losses Handicap | D11: Class 6 | F11: Good To Firm | G11: 10 | H11: Danger Alert | I11: Langley, Taryn | J11: Kirby, Adam | K11: 1 | L11: 59 | M11: 6 | N11: 4 | O11: 4 | P11: 7.4440022 | Q11: 0.13433634 | R11: 4.5 | S11: =IF(AND(ISNUMBER(R11),R11>1,P11>0),R11/P11-1,"") -> -0.39548648 | T11: =IF(AND(ISNUMBER(P11),P11>0),P11*EXP('Read me'!$B$22),"") -> 9.0921248
A12: 1:30 | B12: Brighton | C12: Matchbook SignUp - Get 20% Back On Losses Handicap | D12: Class 6 | F12: Good To Firm | G12: 10 | H12: Beach Partee | I12: Howarth, Christian | J12: Dixon, Scott | K12: 4 | L12: 52 | M12: 3 | N12: 11 | O12: 5 | P12: 9.0419547 | Q12: 0.11059556 | R12: 10 | S12: =IF(AND(ISNUMBER(R12),R12>1,P12>0),R12/P12-1,"") -> 0.10595555 | T12: =IF(AND(ISNUMBER(P12),P12>0),P12*EXP('Read me'!$B$22),"") -> 11.043868
A13: 1:30 | B13: Brighton | C13: Matchbook SignUp - Get 20% Back On Losses Handicap | D13: Class 6 | F13: Good To Firm | G13: 10 | H13: Harry Brown | I13: Hornby, Rob | J13: Crate, Peter | K13: 2 | L13: 52 | M13: 6 | N13: 12 | O13: 6 | P13: 10.257453 | Q13: 0.097490092 | R13: 4 | S13: =IF(AND(ISNUMBER(R13),R13>1,P13>0),R13/P13-1,"") -> -0.61003963 | T13: =IF(AND(ISNUMBER(P13),P13>0),P13*EXP('Read me'!$B$22),"") -> 12.528481
A14: 1:30 | B14: Brighton | C14: Matchbook SignUp - Get 20% Back On Losses Handicap | D14: Class 6 | F14: Good To Firm | G14: 10 | H14: Diamond Dreamer | I14: Probert, David | J14: Chamings, P R | K14: 10 | L14: 58 | M14: 6 | N14: 41 | O14: 7 | P14: 16.868674 | Q14: 0.059281484 | R14: 23 | S14: =IF(AND(ISNUMBER(R14),R14>1,P14>0),R14/P14-1,"") -> 0.36347413 | T14: =IF(AND(ISNUMBER(P14),P14>0),P14*EXP('Read me'!$B$22),"") -> 20.603444
A15: 1:30 | B15: Brighton | C15: Matchbook SignUp - Get 20% Back On Losses Handicap | D15: Class 6 | F15: Good To Firm | G15: 10 | H15: Stapleford Park | I15: Fox, Kieren | J15: Attwater, M J | K15: 8 | L15: 49 | M15: 4 | N15: 26 | O15: 8 | P15: 22.816178 | Q15: 0.04382855 | R15: 34 | S15: =IF(AND(ISNUMBER(R15),R15>1,P15>0),R15/P15-1,"") -> 0.49017069 | T15: =IF(AND(ISNUMBER(P15),P15>0),P15*EXP('Read me'!$B$22),"") -> 27.867743
A16: 1:30 | B16: Brighton | C16: Matchbook SignUp - Get 20% Back On Losses Handicap | D16: Class 6 | F16: Good To Firm | G16: 10 | H16: Anglesey Lad (IRE) | I16: Cox, William | J16: Dixon, Scott | K16: 5 | L16: 45 | M16: 5 | N16: 138 | O16: 9 | P16: 27.754463 | Q16: 0.036030241 | R16: 34 | S16: =IF(AND(ISNUMBER(R16),R16>1,P16>0),R16/P16-1,"") -> 0.2250282 | T16: =IF(AND(ISNUMBER(P16),P16>0),P16*EXP('Read me'!$B$22),"") -> 33.899378
A17: 1:30 | B17: Brighton | C17: Matchbook SignUp - Get 20% Back On Losses Handicap | D17: Class 6 | F17: Good To Firm | G17: 10 | H17: Desdemona | J17: Attwater, M J | K17: 6 | L17: 56 | M17: 4 | N17: 35 | O17: 10 | P17: 51.638347 | Q17: 0.019365454 | R17: 81 | S17: =IF(AND(ISNUMBER(R17),R17>1,P17>0),R17/P17-1,"") -> 0.56860173 | T17: =IF(AND(ISNUMBER(P17),P17>0),P17*EXP('Read me'!$B$22),"") -> 63.071219
A18: 1:35 | B18: Roscommon | C18: Athleague Maiden Hurdle | E18: 15.5 | F18: Good | G18: 13 | H18: Direct Approach (IRE) | I18: Kennedy, J W | J18: Elliott, Gordon | K18: 2 | L18: 97 | M18: 4 | N18: 10 | O18: 1 | P18: 3.1862358 | Q18: 0.31384997 | R18: 5 | S18: =IF(AND(ISNUMBER(R18),R18>1,P18>0),R18/P18-1,"") -> 0.56924983 | T18: =IF(AND(ISNUMBER(P18),P18>0),P18*EXP('Read me'!$B$22),"") -> 3.8916772
A19: 1:35 | B19: Roscommon | C19: Athleague Maiden Hurdle | E19: 15.5 | F19: Good | G19: 13 | H19: Telegram Sam (IRE) | I19: Flanagan, S W | J19: Murray, Adrian | K19: 7 | L19: 0 | M19: 4 | N19: 25 | O19: 2 | P19: 3.1927228 | Q19: 0.31321228 | R19: 1.6153846 | S19: =IF(AND(ISNUMBER(R19),R19>1,P19>0),R19/P19-1,"") -> -0.49404169 | T19: =IF(AND(ISNUMBER(P19),P19>0),P19*EXP('Read me'!$B$22),"") -> 3.8996004
A20: 1:35 | B20: Roscommon | C20: Athleague Maiden Hurdle | E20: 15.5 | F20: Good | G20: 13 | H20: Sonas (IRE) | I20: OKeeffe, Darragh | J20: Bromhead, Henry De | K20: 15 | L20: 0 | M20: 4 | N20: 31 | O20: 3 | P20: 8.1237049 | Q20: 0.12309654 | R20: 10 | S20: =IF(AND(ISNUMBER(R20),R20>1,P20>0),R20/P20-1,"") -> 0.23096545 | T20: =IF(AND(ISNUMBER(P20),P20>0),P20*EXP('Read me'!$B$22),"") -> 9.9223155
A21: 1:35 | B21: Roscommon | C21: Athleague Maiden Hurdle | E21: 15.5 | F21: Good | G21: 13 | H21: God The Highness (IRE) | I21: Meyler, D | J21: Harrington, Mrs John | K21: 3 | L21: 0 | M21: 4 | N21: 54 | O21: 4 | P21: 10.014695 | Q21: 0.099853265 | R21: 7.5 | S21: =IF(AND(ISNUMBER(R21),R21>1,P21>0),R21/P21-1,"") -> -0.25110051 | T21: =IF(AND(ISNUMBER(P21),P21>0),P21*EXP('Read me'!$B$22),"") -> 12.231976
A22: 1:35 | B22: Roscommon | C22: Athleague Maiden Hurdle | E22: 15.5 | F22: Good | G22: 13 | H22: The Flying Rambler (IRE) | I22: King, D | J22: Dempsey, J P | K22: 9 | L22: 0 | M22: 4 | N22: 58 | O22: 5 | P22: 23.925484 | Q22: 0.041796438 | R22: 21 | S22: =IF(AND(ISNUMBER(R22),R22>1,P22>0),R22/P22-1,"") -> -0.12227481 | T22: =IF(AND(ISNUMBER(P22),P22>0),P22*EXP('Read me'!$B$22),"") -> 29.222652
A23: 1:35 | B23: Roscommon | C23: Athleague Maiden Hurdle | E23: 15.5 | F23: Good | G23: 13 | H23: Pallatine Hills (IRE) | I23: Buckley, Kieran | J23: Harty, Edward and Patrick | K23: 6 | L23: 0 | M23: 4 | N23: 23 | O23: 6 | P23: 26.155292 | Q23: 0.038233181 | R23: 15 | S23: =IF(AND(ISNUMBER(R23),R23>1,P23>0),R23/P23-1,"") -> -0.42650229 | T23: =IF(AND(ISNUMBER(P23),P23>0),P23*EXP('Read me'!$B$22),"") -> 31.946145
A24: 1:35 | B24: Roscommon | C24: Athleague Maiden Hurdle | E24: 15.5 | F24: Good | G24: 13 | H24: Abando (GER) | I24: Smith, James | J24: McCann, Anthony | K24: 1 | L24: 0 | M24: 4 | N24: 97 | O24: 7 | P24: 44.129249 | Q24: 0.022660707 | R24: 34 | S24: =IF(AND(ISNUMBER(R24),R24>1,P24>0),R24/P24-1,"") -> -0.22953595 | T24: =IF(AND(ISNUMBER(P24),P24>0),P24*EXP('Read me'!$B$22),"") -> 53.899587
A25: 1:35 | B25: Roscommon | C25: Athleague Maiden Hurdle | E25: 15.5 | F25: Good | G25: 13 | H25: Lucky Signal (FR) | I25: Ewing, Sam | J25: Elliott, Gordon | K25: 5 | L25: 0 | M25: 4 | N25: 25 | O25: 8 | P25: 75.723937 | Q25: 0.013205864 | R25: 101 | S25: =IF(AND(ISNUMBER(R25),R25>1,P25>0),R25/P25-1,"") -> 0.33379225 | T25: =IF(AND(ISNUMBER(P25),P25>0),P25*EXP('Read me'!$B$22),"") -> 92.489425
A26: 1:35 | B26: Roscommon | C26: Athleague Maiden Hurdle | E26: 15.5 | F26: Good | G26: 13 | H26: Gratitudeforgrace (FR) | I26: Gilligan, D J | J26: Elliott, Gordon | K26: 13 | L26: 0 | M26: 4 | N26: 67 | O26: 9 | P26: 85.68318 | Q26: 0.011670902 | R26: 101 | S26: =IF(AND(ISNUMBER(R26),R26>1,P26>0),R26/P26-1,"") -> 0.1787611 | T26: =IF(AND(ISNUMBER(P26),P26>0),P26*EXP('Read me'!$B$22),"") -> 104.65367
A27: 1:35 | B27: Roscommon | C27: Athleague Maiden Hurdle | E27: 15.5 | F27: Good | G27: 13 | H27: Hill Of Berries (IRE) | I27: Gainford, Jordan | J27: Dempsey, J P | K27: 4 | L27: 0 | M27: 4 | O27: 10 | P27: 131.32591 | Q27: 0.0076146435 | R27: 81 | S27: =IF(AND(ISNUMBER(R27),R27>1,P27>0),R27/P27-1,"") -> -0.38321388 | T27: =IF(AND(ISNUMBER(P27),P27>0),P27*EXP('Read me'!$B$22),"") -> 160.40183
A28: 1:35 | B28: Roscommon | C28: Athleague Maiden Hurdle | E28: 15.5 | F28: Good | G28: 13 | H28: Everin Dream (IRE) | I28: Smithers, P T | J28: Fahey, Jarlath P | K28: 12 | L28: 0 | M28: 4 | O28: 11 | P28: 159.93786 | Q28: 0.0062524284 | R28: 101 | S28: =IF(AND(ISNUMBER(R28),R28>1,P28>0),R28/P28-1,"") -> -0.36850473 | T28: =IF(AND(ISNUMBER(P28),P28>0),P28*EXP('Read me'!$B$22),"") -> 195.34854
A29: 1:35 | B29: Roscommon | C29: Athleague Maiden Hurdle | E29: 15.5 | F29: Good | G29: 13 | H29: Neat As A Pin (IRE) | I29: Lane, R J | J29: Bolger, E | K29: 14 | L29: 0 | M29: 4 | N29: 56 | O29: 12 | P29: 167.62823 | Q29: 0.0059655824 | R29: 151 | S29: =IF(AND(ISNUMBER(R29),R29>1,P29>0),R29/P29-1,"") -> -0.09919706 | T29: =IF(AND(ISNUMBER(P29),P29>0),P29*EXP('Read me'!$B$22),"") -> 204.74158
A30: 1:35 | B30: Roscommon | C30: Athleague Maiden Hurdle | E30: 15.5 | F30: Good | G30: 13 | H30: Emmamia (IRE) | I30: Enright, P T | J30: McNiff, Mark Michael | K30: 11 | L30: 0 | M30: 4 | N30: 69 | O30: 13 | P30: 386.36984 | Q30: 0.0025881937 | R30: 201 | S30: =IF(AND(ISNUMBER(R30),R30>1,P30>0),R30/P30-1,"") -> -0.47977306 | T30: =IF(AND(ISNUMBER(P30),P30>0),P30*EXP('Read me'!$B$22),"") -> 471.91319
A31: 1:44 | B31: Hamilton | C31: Clearwater DC Ltd Environmental Solutions Amateur Jockeys Handicap | D31: Class 5 | E31: 6 | F31: Soft | G31: 6 | H31: Annie Edson Taylor | I31: Brown, Pippa | J31: Makin, Phillip | K31: 2 | L31: 72 | M31: 5 | N31: 8 | O31: 1 | P31: 3.1430511 | Q31: 0.31816218 | R31: 2.5 | S31: =IF(AND(ISNUMBER(R31),R31>1,P31>0),R31/P31-1,"") -> -0.20459455 | T31: =IF(AND(ISNUMBER(P31),P31>0),P31*EXP('Read me'!$B$22),"") -> 3.8389313
A32: 1:44 | B32: Hamilton | C32: Clearwater DC Ltd Environmental Solutions Amateur Jockeys Handicap | D32: Class 5 | E32: 6 | F32: Soft | G32: 6 | H32: Bay Breeze | I32: Burley, Miss Rebecca | J32: Easterby, T D | K32: 1 | L32: 62 | M32: 7 | N32: 7 | O32: 2 | P32: 4.5721161 | Q32: 0.21871711 | R32: 3.75 | S32: =IF(AND(ISNUMBER(R32),R32>1,P32>0),R32/P32-1,"") -> -0.17981085 | T32: =IF(AND(ISNUMBER(P32),P32>0),P32*EXP('Read me'!$B$22),"") -> 5.5843952
A33: 1:44 | B33: Hamilton | C33: Clearwater DC Ltd Environmental Solutions Amateur Jockeys Handicap | D33: Class 5 | E33: 6 | F33: Soft | G33: 6 | H33: Lumenbourg | I33: Barlow, Patrick | J33: Camacho, Miss J A | K33: 6 | L33: 65 | M33: 5 | N33: 26 | O33: 3 | P33: 6.4457915 | Q33: 0.15513999 | R33: 6 | S33: =IF(AND(ISNUMBER(R33),R33>1,P33>0),R33/P33-1,"") -> -0.069160085 | T33: =IF(AND(ISNUMBER(P33),P33>0),P33*EXP('Read me'!$B$22),"") -> 7.8729075
A34: 1:44 | B34: Hamilton | C34: Clearwater DC Ltd Environmental Solutions Amateur Jockeys Handicap | D34: Class 5 | E34: 6 | F34: Soft | G34: 6 | H34: Thistle Nil (IRE) | I34: Cagney, Eireann | J34: Goldie, J S | K34: 3 | L34: 68 | M34: 4 | N34: 7 | O34: 4 | P34: 7.120566 | Q34: 0.14043827 | R34: 10 | S34: =IF(AND(ISNUMBER(R34),R34>1,P34>0),R34/P34-1,"") -> 0.40438275 | T34: =IF(AND(ISNUMBER(P34),P34>0),P34*EXP('Read me'!$B$22),"") -> 8.6970789
A35: 1:44 | B35: Hamilton | C35: Clearwater DC Ltd Environmental Solutions Amateur Jockeys Handicap | D35: Class 5 | E35: 6 | F35: Soft | G35: 6 | H35: Maldevious (IRE) | I35: Brown, Mr M W | J35: Ellison, B | K35: 4 | L35: 69 | M35: 4 | N35: 23 | O35: 5 | P35: 8.7790261 | Q35: 0.11390785 | R35: 8 | S35: =IF(AND(ISNUMBER(R35),R35>1,P35>0),R35/P35-1,"") -> -0.088737194 | T35: =IF(AND(ISNUMBER(P35),P35>0),P35*EXP('Read me'!$B$22),"") -> 10.722727
A36: 1:44 | B36: Hamilton | C36: Clearwater DC Ltd Environmental Solutions Amateur Jockeys Handicap | D36: Class 5 | E36: 6 | F36: Soft | G36: 6 | H36: Punchbowl Flyer (IRE) | I36: Hampson, Brodie | J36: Oshea, J G M | K36: 5 | L36: 64 | M36: 9 | N36: 21 | O36: 6 | P36: 18.64468 | Q36: 0.053634603 | R36: 15 | S36: =IF(AND(ISNUMBER(R36),R36>1,P36>0),R36/P36-1,"") -> -0.19548095 | T36: =IF(AND(ISNUMBER(P36),P36>0),P36*EXP('Read me'!$B$22),"") -> 22.772663
A37: 1:50 | B37: Newton Abbot | C37: Celebrating Devon Women In Business Handicap Chase (GBB Race) | D37: Class 3 | E37: 26 | F37: Good | G37: 3 | H37: Depalma (IRE) | I37: Skelton, Harry | J37: Skelton, Daniel | K37: 3 | L37: 102 | M37: 7 | N37: 10 | O37: 1 | P37: 2.195562 | Q37: 0.45546425 | R37: 1.6666667 | S37: =IF(AND(ISNUMBER(R37),R37>1,P37>0),R37/P37-1,"") -> -0.24089292 | T37: =IF(AND(ISNUMBER(P37),P37>0),P37*EXP('Read me'!$B$22),"") -> 2.6816655
A38: 1:50 | B38: Newton Abbot | C38: Celebrating Devon Women In Business Handicap Chase (GBB Race) | D38: Class 3 | E38: 26 | F38: Good | G38: 3 | H38: Muskerry Rock (IRE) | I38: Bowen, Sean P | J38: Bowen, Mickey | K38: 1 | L38: 120 | M38: 7 | N38: 40 | O38: 2 | P38: 3.1859008 | Q38: 0.31388297 | R38: 5.5 | S38: =IF(AND(ISNUMBER(R38),R38>1,P38>0),R38/P38-1,"") -> 0.72635634 | T38: =IF(AND(ISNUMBER(P38),P38>0),P38*EXP('Read me'!$B$22),"") -> 3.891268
A39: 1:50 | B39: Newton Abbot | C39: Celebrating Devon Women In Business Handicap Chase (GBB Race) | D39: Class 3 | E39: 26 | F39: Good | G39: 3 | H39: Limerick Leader (FR) | I39: Bowen, James C | J39: Scholfield, Nick | K39: 2 | L39: 110 | M39: 9 | N39: 12 | O39: 3 | P39: 4.3355211 | Q39: 0.23065278 | R39: 3.5 | S39: =IF(AND(ISNUMBER(R39),R39>1,P39>0),R39/P39-1,"") -> -0.19271526 | T39: =IF(AND(ISNUMBER(P39),P39>0),P39*EXP('Read me'!$B$22),"") -> 5.2954174
A40: 1:59 | B40: Down Royal | C40: Coors Fillies Handicap | E40: 13 | F40: Good | G40: 10 | H40: Nellcote (IRE) | I40: McDonogh, D P | J40: OBrien, Joseph Patrick | K40: 5 | L40: 82 | M40: 3 | N40: 37 | O40: 1 | P40: 4.9114672 | Q40: 0.20360515 | R40: 4.5 | S40: =IF(AND(ISNUMBER(R40),R40>1,P40>0),R40/P40-1,"") -> -0.083776841 | T40: =IF(AND(ISNUMBER(P40),P40>0),P40*EXP('Read me'!$B$22),"") -> 5.9988796
A41: 1:59 | B41: Down Royal | C41: Coors Fillies Handicap | E41: 13 | F41: Good | G41: 10 | H41: Stellar Moment (IRE) | I41: Whelan, R P | J41: ODonoghue, John | K41: 7 | L41: 79 | M41: 3 | N41: 28 | O41: 2 | P41: 5.3404808 | Q41: 0.18724906 | R41: 4.3333333 | S41: =IF(AND(ISNUMBER(R41),R41>1,P41>0),R41/P41-1,"") -> -0.18858742 | T41: =IF(AND(ISNUMBER(P41),P41>0),P41*EXP('Read me'!$B$22),"") -> 6.522878
A42: 1:59 | B42: Down Royal | C42: Coors Fillies Handicap | E42: 13 | F42: Good | G42: 10 | H42: Lady Plimsoll (IRE) | I42: Holohan, Reese | J42: OCallaghan, M D | K42: 9 | L42: 72 | M42: 4 | N42: 12 | O42: 3 | P42: 6.2110078 | Q42: 0.16100447 | R42: 5.5 | S42: =IF(AND(ISNUMBER(R42),R42>1,P42>0),R42/P42-1,"") -> -0.11447543 | T42: =IF(AND(ISNUMBER(P42),P42>0),P42*EXP('Read me'!$B$22),"") -> 7.5861421
A43: 1:59 | B43: Down Royal | C43: Coors Fillies Handicap | E43: 13 | F43: Good | G43: 10 | H43: Navy Waters (IRE) | I43: Lee, W J | J43: McCreery, W | K43: 2 | L43: 84 | M43: 5 | N43: 20 | O43: 4 | P43: 6.735345 | Q43: 0.14847049 | R43: 5.5 | S43: =IF(AND(ISNUMBER(R43),R43>1,P43>0),R43/P43-1,"") -> -0.18341229 | T43: =IF(AND(ISNUMBER(P43),P43>0),P43*EXP('Read me'!$B$22),"") -> 8.226569
A44: 1:59 | B44: Down Royal | C44: Coors Fillies Handicap | E44: 13 | F44: Good | G44: 10 | H44: Vanir (IRE) | I44: Coen, Ben M | J44: Murtagh, J P | K44: 1 | L44: 84 | M44: 3 | N44: 37 | O44: 5 | P44: 13.041516 | Q44: 0.076678201 | R44: 10 | S44: =IF(AND(ISNUMBER(R44),R44>1,P44>0),R44/P44-1,"") -> -0.23321799 | T44: =IF(AND(ISNUMBER(P44),P44>0),P44*EXP('Read me'!$B$22),"") -> 15.928944
A45: 1:59 | B45: Down Royal | C45: Coors Fillies Handicap | E45: 13 | F45: Good | G45: 10 | H45: Just Keep Flying (USA) | I45: Kennedy, K G | J45: Harrington, Mrs John | K45: 8 | L45: 78 | M45: 4 | N45: 108 | O45: 6 | P45: 13.805392 | Q45: 0.072435466 | R45: 12 | S45: =IF(AND(ISNUMBER(R45),R45>1,P45>0),R45/P45-1,"") -> -0.13077441 | T45: =IF(AND(ISNUMBER(P45),P45>0),P45*EXP('Read me'!$B$22),"") -> 16.861944
A46: 1:59 | B46: Down Royal | C46: Coors Fillies Handicap | E46: 13 | F46: Good | G46: 10 | H46: Denim And Diamonds (IRE) | I46: Sheridan, J M | J46: OBrien, Joseph Patrick | K46: 3 | L46: 84 | M46: 4 | N46: 37 | O46: 7 | P46: 14.919851 | Q46: 0.067024796 | R46: 13 | S46: =IF(AND(ISNUMBER(R46),R46>1,P46>0),R46/P46-1,"") -> -0.12867765 | T46: =IF(AND(ISNUMBER(P46),P46>0),P46*EXP('Read me'!$B$22),"") -> 18.223148
A47: 1:59 | B47: Down Royal | C47: Coors Fillies Handicap | E47: 13 | F47: Good | G47: 10 | H47: Tatum (IRE) | I47: Hayes, C D | J47: Meade, Noel | K47: 4 | L47: 69 | M47: 5 | N47: 59 | O47: 8 | P47: 26.987618 | Q47: 0.037054029 | R47: 21 | S47: =IF(AND(ISNUMBER(R47),R47>1,P47>0),R47/P47-1,"") -> -0.22186539 | T47: =IF(AND(ISNUMBER(P47),P47>0),P47*EXP('Read me'!$B$22),"") -> 32.962752
A48: 1:59 | B48: Down Royal | C48: Coors Fillies Handicap | E48: 13 | F48: Good | G48: 10 | H48: Narlita (GER) | I48: Cusack, C | J48: Rogers, H | K48: 6 | L48: 83 | M48: 7 | N48: 7 | O48: 9 | P48: 36.038321 | Q48: 0.027748241 | R48: 17 | S48: =IF(AND(ISNUMBER(R48),R48>1,P48>0),R48/P48-1,"") -> -0.52827991 | T48: =IF(AND(ISNUMBER(P48),P48>0),P48*EXP('Read me'!$B$22),"") -> 44.017304
A49: 1:59 | B49: Down Royal | C49: Coors Fillies Handicap | E49: 13 | F49: Good | G49: 10 | H49: Ankara (FR) | I49: Wallace, S A | J49: OBrien, Joseph Patrick | K49: 10 | L49: 86 | M49: 4 | N49: 20 | O49: 10 | P49: 53.389988 | Q49: 0.018730103 | R49: 26 | S49: =IF(AND(ISNUMBER(R49),R49>1,P49>0),R49/P49-1,"") -> -0.51301731 | T49: =IF(AND(ISNUMBER(P49),P49>0),P49*EXP('Read me'!$B$22),"") -> 65.210679
A50: 2:05 | B50: Brighton | C50: Matchbook Betting Exchange Supporting UK Racing Maiden Stakes (GBB Race) | D50: Class 4 | E50: 7 | F50: Good To Firm | G50: 4 | H50: Galileo Star | I50: Ryan, Rossa | J50: Tate, James | K50: 6 | L50: 0 | M50: 3 | O50: 1 | P50: 2.5514401 | Q50: 0.39193551 | R50: 1.5714286 | S50: =IF(AND(ISNUMBER(R50),R50>1,P50>0),R50/P50-1,"") -> -0.38410134 | T50: =IF(AND(ISNUMBER(P50),P50>0),P50*EXP('Read me'!$B$22),"") -> 3.116336
A51: 2:05 | B51: Brighton | C51: Matchbook Betting Exchange Supporting UK Racing Maiden Stakes (GBB Race) | D51: Class 4 | E51: 7 | F51: Good To Firm | G51: 4 | H51: River Nile (IRE) | I51: Watson, Jason | J51: Balding, A M | K51: 3 | L51: 74 | M51: 3 | N51: 11 | O51: 2 | P51: 2.984331 | Q51: 0.33508347 | R51: 3 | S51: =IF(AND(ISNUMBER(R51),R51>1,P51>0),R51/P51-1,"") -> 0.0052504123 | T51: =IF(AND(ISNUMBER(P51),P51>0),P51*EXP('Read me'!$B$22),"") -> 3.6450702
A52: 2:05 | B52: Brighton | C52: Matchbook Betting Exchange Supporting UK Racing Maiden Stakes (GBB Race) | D52: Class 4 | E52: 7 | F52: Good To Firm | G52: 4 | H52: All Shall Be Well | I52: Shoemark, Kieran | J52: Jones, Jack | K52: 1 | L52: 0 | M52: 3 | N52: 25 | O52: 3 | P52: 3.807163 | Q52: 0.26266277 | R52: 7 | S52: =IF(AND(ISNUMBER(R52),R52>1,P52>0),R52/P52-1,"") -> 0.83863942 | T52: =IF(AND(ISNUMBER(P52),P52>0),P52*EXP('Read me'!$B$22),"") -> 4.6500794
A53: 2:05 | B53: Brighton | C53: Matchbook Betting Exchange Supporting UK Racing Maiden Stakes (GBB Race) | D53: Class 4 | E53: 7 | F53: Good To Firm | G53: 4 | H53: Irish Spring | I53: Hogan, D E | J53: Jewell, Karen | K53: 5 | L53: 0 | M53: 4 | N53: 32 | O53: 4 | P53: 96.91573 | Q53: 0.010318242 | R53: 101 | S53: =IF(AND(ISNUMBER(R53),R53>1,P53>0),R53/P53-1,"") -> 0.042142488 | T53: =IF(AND(ISNUMBER(P53),P53>0),P53*EXP('Read me'!$B$22),"") -> 118.37314
A54: 2:10 | B54: Roscommon | C54: Garys Gardening Services Handicap Hurdle (0-100) | E54: 15.5 | F54: Good | G54: 16 | H54: Cool Summer (IRE) | I54: Enright, P T | J54: McLoughlin, Hilary | K54: 3 | L54: 95 | M54: 6 | N54: 31 | O54: 1 | P54: 3.935622 | Q54: 0.25408944 | R54: 4 | S54: =IF(AND(ISNUMBER(R54),R54>1,P54>0),R54/P54-1,"") -> 0.016357772 | T54: =IF(AND(ISNUMBER(P54),P54>0),P54*EXP('Read me'!$B$22),"") -> 4.8069796
A55: 2:10 | B55: Roscommon | C55: Garys Gardening Services Handicap Hurdle (0-100) | E55: 15.5 | F55: Good | G55: 16 | H55: Colesberg (IRE) | I55: Canavan, Jordan J | J55: Flavin, J P | K55: 2 | L55: 95 | M55: 5 | N55: 43 | O55: 2 | P55: 8.6710864 | Q55: 0.1153258 | R55: 7 | S55: =IF(AND(ISNUMBER(R55),R55>1,P55>0),R55/P55-1,"") -> -0.19271938 | T55: =IF(AND(ISNUMBER(P55),P55>0),P55*EXP('Read me'!$B$22),"") -> 10.590889
A56: 2:10 | B56: Roscommon | C56: Garys Gardening Services Handicap Hurdle (0-100) | E56: 15.5 | F56: Good | G56: 16 | H56: Patrick Street | I56: King, D | J56: Kinirons, A | K56: 12 | L56: 82 | M56: 7 | N56: 13 | O56: 3 | P56: 10.070653 | Q56: 0.099298423 | R56: 5 | S56: =IF(AND(ISNUMBER(R56),R56>1,P56>0),R56/P56-1,"") -> -0.50350789 | T56: =IF(AND(ISNUMBER(P56),P56>0),P56*EXP('Read me'!$B$22),"") -> 12.300324
A57: 2:10 | B57: Roscommon | C57: Garys Gardening Services Handicap Hurdle (0-100) | E57: 15.5 | F57: Good | G57: 16 | H57: Classy Cc (IRE) | I57: Brassil, C | J57: Brassil, Martin | K57: 1 | L57: 95 | M57: 6 | N57: 139 | O57: 4 | P57: 10.419183 | Q57: 0.095976819 | R57: 12 | S57: =IF(AND(ISNUMBER(R57),R57>1,P57>0),R57/P57-1,"") -> 0.15172183 | T57: =IF(AND(ISNUMBER(P57),P57>0),P57*EXP('Read me'!$B$22),"") -> 12.726018
A58: 2:10 | B58: Roscommon | C58: Garys Gardening Services Handicap Hurdle (0-100) | E58: 15.5 | F58: Good | G58: 16 | H58: Eyetrap | I58: Smithers, C D | J58: Melia, Aidan | K58: 4 | L58: 95 | M58: 6 | N58: 245 | O58: 5 | P58: 12.881168 | Q58: 0.07763271 | R58: 7 | S58: =IF(AND(ISNUMBER(R58),R58>1,P58>0),R58/P58-1,"") -> -0.45657103 | T58: =IF(AND(ISNUMBER(P58),P58>0),P58*EXP('Read me'!$B$22),"") -> 15.733094
A59: 2:10 | B59: Roscommon | C59: Garys Gardening Services Handicap Hurdle (0-100) | E59: 15.5 | F59: Good | G59: 16 | H59: Patty Ofarrell (IRE) | I59: Flanagan, S W | J59: Maher, Peter | K59: 5 | L59: 95 | M59: 8 | N59: 84 | O59: 6 | P59: 14.054189 | Q59: 0.071153165 | R59: 21 | S59: =IF(AND(ISNUMBER(R59),R59>1,P59>0),R59/P59-1,"") -> 0.49421646 | T59: =IF(AND(ISNUMBER(P59),P59>0),P59*EXP('Read me'!$B$22),"") -> 17.165825
A60: 2:10 | B60: Roscommon | C60: Garys Gardening Services Handicap Hurdle (0-100) | E60: 15.5 | F60: Good | G60: 16 | H60: Our Girl Ellie (IRE) | I60: Slevin, J J | J60: Ryan, Stephen | K60: 8 | L60: 92 | M60: 6 | N60: 137 | O60: 7 | P60: 19.598345 | Q60: 0.051024717 | R60: 19 | S60: =IF(AND(ISNUMBER(R60),R60>1,P60>0),R60/P60-1,"") -> -0.030530374 | T60: =IF(AND(ISNUMBER(P60),P60>0),P60*EXP('Read me'!$B$22),"") -> 23.937472
A61: 2:10 | B61: Roscommon | C61: Garys Gardening Services Handicap Hurdle (0-100) | E61: 15.5 | F61: Good | G61: 16 | H61: Avandra (IRE) | I61: OCallaghan, Shane | J61: Rothwell, P J | K61: 16 | L61: 72 | M61: 6 | N61: 33 | O61: 8 | P61: 23.325763 | Q61: 0.042871052 | R61: 13 | S61: =IF(AND(ISNUMBER(R61),R61>1,P61>0),R61/P61-1,"") -> -0.44267632 | T61: =IF(AND(ISNUMBER(P61),P61>0),P61*EXP('Read me'!$B$22),"") -> 28.490151
A62: 2:10 | B62: Roscommon | C62: Garys Gardening Services Handicap Hurdle (0-100) | E62: 15.5 | F62: Good | G62: 16 | H62: Speakasyoufind (IRE) | I62: Sugrue, R | J62: Rothwell, P J | K62: 9 | L62: 89 | M62: 5 | N62: 50 | O62: 9 | P62: 26.804016 | Q62: 0.037307842 | R62: 11 | S62: =IF(AND(ISNUMBER(R62),R62>1,P62>0),R62/P62-1,"") -> -0.58961373 | T62: =IF(AND(ISNUMBER(P62),P62>0),P62*EXP('Read me'!$B$22),"") -> 32.738499
A63: 2:10 | B63: Roscommon | C63: Garys Gardening Services Handicap Hurdle (0-100) | E63: 15.5 | F63: Good | G63: 16 | H63: Dalmatic (IRE) | I63: Byrnes, Philip | J63: Odoherty, William Joseph | K63: 7 | L63: 92 | M63: 6 | N63: 157 | O63: 10 | P63: 28.437064 | Q63: 0.035165374 | R63: 21 | S63: =IF(AND(ISNUMBER(R63),R63>1,P63>0),R63/P63-1,"") -> -0.26152714 | T63: =IF(AND(ISNUMBER(P63),P63>0),P63*EXP('Read me'!$B$22),"") -> 34.733109
A64: 2:10 | B64: Roscommon | C64: Garys Gardening Services Handicap Hurdle (0-100) | E64: 15.5 | F64: Good | G64: 16 | H64: Another Blunder (IRE) | I64: OConnor, M P | J64: Barry, Michael | K64: 14 | L64: 75 | M64: 5 | N64: 31 | O64: 11 | P64: 33.129381 | Q64: 0.030184687 | R64: 17 | S64: =IF(AND(ISNUMBER(R64),R64>1,P64>0),R64/P64-1,"") -> -0.48686032 | T64: =IF(AND(ISNUMBER(P64),P64>0),P64*EXP('Read me'!$B$22),"") -> 40.464318
A65: 2:10 | B65: Roscommon | C65: Garys Gardening Services Handicap Hurdle (0-100) | E65: 15.5 | F65: Good | G65: 16 | H65: Atlantic Wonder (IRE) | I65: Costello, Mr J | J65: Martin, A J | K65: 15 | L65: 75 | M65: 9 | N65: 163 | O65: 12 | P65: 48.027232 | Q65: 0.02082152 | R65: 29 | S65: =IF(AND(ISNUMBER(R65),R65>1,P65>0),R65/P65-1,"") -> -0.39617591 | T65: =IF(AND(ISNUMBER(P65),P65>0),P65*EXP('Read me'!$B$22),"") -> 58.660594
... A69: 2:10 | B69: Roscommon | C69: Garys Gardening Services Handicap Hurdle (0-100) | E69: 15.5 | F69: Good | G69: 16 | H69: Grennanstown Lady (IRE) | I69: Finegan, Eoghan | J69: Keane, Gerard | K69: 10 | L69: 86 | M69: 5 | N69: 90 | O69: 16 | P69: 83.941255 | Q69: 0.011913093 | R69: 34 | S69: =IF(AND(ISNUMBER(R69),R69>1,P69>0),R69/P69-1,"") -> -0.59495483 | T69: =IF(AND(ISNUMBER(P69),P69>0),P69*EXP('Read me'!$B$22),"") -> 102.52608
A70: 2:19 | B70: Hamilton | C70: Moira Stein Memorial EBF Restricted Maiden Stakes (GBB Race) | D70: Class 4 | E70: 5 | F70: Soft | G70: 6 | H70: Cyberspace | I70: Mulrennan, Paul | J70: Smart, B | K70: 6 | L70: 0 | M70: 2 | N70: 13 | O70: 1 | P70: 2.0902903 | Q70: 0.47840245 | R70: 2.75 | S70: =IF(AND(ISNUMBER(R70),R70>1,P70>0),R70/P70-1,"") -> 0.31560672 | T70: =IF(AND(ISNUMBER(P70),P70>0),P70*EXP('Read me'!$B$22),"") -> 2.5530864
A71: 2:19 | B71: Hamilton | C71: Moira Stein Memorial EBF Restricted Maiden Stakes (GBB Race) | D71: Class 4 | E71: 5 | F71: Soft | G71: 6 | H71: Ponte Carlo (IRE) | I71: Allan, David | J71: Easterby, T D | K71: 3 | L71: 63 | M71: 2 | N71: 19 | O71: 2 | P71: 4.2862463 | Q71: 0.23330437 | R71: 2.625 | S71: =IF(AND(ISNUMBER(R71),R71>1,P71>0),R71/P71-1,"") -> -0.38757602 | T71: =IF(AND(ISNUMBER(P71),P71>0),P71*EXP('Read me'!$B$22),"") -> 5.235233
A72: 2:19 | B72: Hamilton | C72: Moira Stein Memorial EBF Restricted Maiden Stakes (GBB Race) | D72: Class 4 | E72: 5 | F72: Soft | G72: 6 | H72: Kompozitor | I72: Beasley, Connor | J72: Barron, T D | K72: 1 | L72: 0 | M72: 2 | N72: 12 | O72: 3 | P72: 7.9445966 | Q72: 0.12587171 | R72: 6 | S72: =IF(AND(ISNUMBER(R72),R72>1,P72>0),R72/P72-1,"") -> -0.24476971 | T72: =IF(AND(ISNUMBER(P72),P72>0),P72*EXP('Read me'!$B$22),"") -> 9.7035522
A73: 2:19 | B73: Hamilton | C73: Moira Stein Memorial EBF Restricted Maiden Stakes (GBB Race) | D73: Class 4 | E73: 5 | F73: Soft | G73: 6 | H73: Youngheartsrunfree (IRE) | I73: Wheatley, Zak | J73: Carroll, D | K73: 2 | L73: 0 | M73: 2 | N73: 12 | O73: 4 | P73: 9.9194898 | Q73: 0.10081164 | R73: 9 | S73: =IF(AND(ISNUMBER(R73),R73>1,P73>0),R73/P73-1,"") -> -0.092695274 | T73: =IF(AND(ISNUMBER(P73),P73>0),P73*EXP('Read me'!$B$22),"") -> 12.115692
A74: 2:19 | B74: Hamilton | C74: Moira Stein Memorial EBF Restricted Maiden Stakes (GBB Race) | D74: Class 4 | E74: 5 | F74: Soft | G74: 6 | H74: Valentina Bonita (IRE) | I74: Garritty, Billy | J74: Easterby, M W | K74: 5 | L74: 0 | M74: 2 | N74: 12 | O74: 5 | P74: 26.097023 | Q74: 0.038318547 | R74: 15 | S74: =IF(AND(ISNUMBER(R74),R74>1,P74>0),R74/P74-1,"") -> -0.42522179 | T74: =IF(AND(ISNUMBER(P74),P74>0),P74*EXP('Read me'!$B$22),"") -> 31.874976
A75: 2:19 | B75: Hamilton | C75: Moira Stein Memorial EBF Restricted Maiden Stakes (GBB Race) | D75: Class 4 | E75: 5 | F75: Soft | G75: 6 | H75: Justice Time (IRE) | I75: Marshall, Tom Kiely | J75: Ellison, B | K75: 4 | L75: 59 | M75: 2 | N75: 12 | O75: 6 | P75: 42.934517 | Q75: 0.023291283 | R75: 19 | S75: =IF(AND(ISNUMBER(R75),R75>1,P75>0),R75/P75-1,"") -> -0.55746562 | T75: =IF(AND(ISNUMBER(P75),P75>0),P75*EXP('Read me'!$B$22),"") -> 52.440337
A76: 2:25 | B76: Newton Abbot | C76: Jodie Standings Point-To-Point Recruits Novices Hurdle (GBB Race) | D76: Class 4 | E76: 17 | F76: Good | G76: 6 | H76: Matiwo (FR) | I76: Gethings, Ciaran | J76: Williams, Mrs Jane | K76: 4 | L76: 119 | M76: 4 | N76: 219 | O76: 1 | P76: 1.3053142 | Q76: 0.7660991 | R76: 1.2857143 | S76: =IF(AND(ISNUMBER(R76),R76>1,P76>0),R76/P76-1,"") -> -0.015015449 | T76: =IF(AND(ISNUMBER(P76),P76>0),P76*EXP('Read me'!$B$22),"") -> 1.5943143
A77: 2:25 | B77: Newton Abbot | C77: Jodie Standings Point-To-Point Recruits Novices Hurdle (GBB Race) | D77: Class 4 | E77: 17 | F77: Good | G77: 6 | H77: Scotts Legacy (IRE) | I77: Twiston-Davies, Sam | J77: Twiston-Davies, N A | K77: 6 | L77: 0 | M77: 4 | N77: 188 | O77: 2 | P77: 5.188916 | Q77: 0.19271848 | R77: 4 | S77: =IF(AND(ISNUMBER(R77),R77>1,P77>0),R77/P77-1,"") -> -0.22912608 | T77: =IF(AND(ISNUMBER(P77),P77>0),P77*EXP('Read me'!$B$22),"") -> 6.3377563
A78: 2:25 | B78: Newton Abbot | C78: Jodie Standings Point-To-Point Recruits Novices Hurdle (GBB Race) | D78: Class 4 | E78: 17 | F78: Good | G78: 6 | H78: Silver Whisper | I78: Noonan, David G | J78: Clarke, Ben | K78: 7 | L78: 0 | M78: 4 | N78: 22 | O78: 3 | P78: 55.960858 | Q78: 0.017869633 | R78: 41 | S78: =IF(AND(ISNUMBER(R78),R78>1,P78>0),R78/P78-1,"") -> -0.26734504 | T78: =IF(AND(ISNUMBER(P78),P78>0),P78*EXP('Read me'!$B$22),"") -> 68.350746
A79: 2:25 | B79: Newton Abbot | C79: Jodie Standings Point-To-Point Recruits Novices Hurdle (GBB Race) | D79: Class 4 | E79: 17 | F79: Good | G79: 6 | H79: Happy Chandler | I79: Reed, Harry | J79: Blake, Michael | K79: 1 | L79: 0 | M79: 5 | N79: 21 | O79: 4 | P79: 80.642014 | Q79: 0.012400484 | R79: 21 | S79: =IF(AND(ISNUMBER(R79),R79>1,P79>0),R79/P79-1,"") -> -0.73958984 | T79: =IF(AND(ISNUMBER(P79),P79>0),P79*EXP('Read me'!$B$22),"") -> 98.496378
A80: 2:25 | B80: Newton Abbot | C80: Jodie Standings Point-To-Point Recruits Novices Hurdle (GBB Race) | D80: Class 4 | E80: 17 | F80: Good | G80: 6 | H80: Savanna Storm (IRE) | I80: Corcoran, Rian | J80: Pipe, D E | K80: 5 | L80: 0 | M80: 4 | N80: 18 | O80: 5 | P80: 155.93307 | Q80: 0.0064130076 | R80: 51 | S80: =IF(AND(ISNUMBER(R80),R80>1,P80>0),R80/P80-1,"") -> -0.67293661 | T80: =IF(AND(ISNUMBER(P80),P80>0),P80*EXP('Read me'!$B$22),"") -> 190.45709
A81: 2:25 | B81: Newton Abbot | C81: Jodie Standings Point-To-Point Recruits Novices Hurdle (GBB Race) | D81: Class 4 | E81: 17 | F81: Good | G81: 6 | H81: Pappano | I81: Collier, Ellis | J81: Hosie, Syd | K81: 2 | L81: 0 | M81: 5 | N81: 10 | O81: 6 | P81: 222.25676 | Q81: 0.0044993008 | R81: 41 | S81: =IF(AND(ISNUMBER(R81),R81>1,P81>0),R81/P81-1,"") -> -0.81552867 | T81: =IF(AND(ISNUMBER(P81),P81>0),P81*EXP('Read me'!$B$22),"") -> 271.46501
A82: 2:34 | B82: Down Royal | C82: Irish EBF Auction Series Fillies Maiden | E82: 7 | F82: Good | G82: 9 | H82: Essence Of Time | I82: Lordan, W M | J82: Oliver, Andrew | K82: 3 | L82: 0 | M82: 2 | N82: 24 | O82: 1 | P82: 2.308552 | Q82: 0.43317196 | R82: 2.2 | S82: =IF(AND(ISNUMBER(R82),R82>1,P82>0),R82/P82-1,"") -> -0.047021693 | T82: =IF(AND(ISNUMBER(P82),P82>0),P82*EXP('Read me'!$B$22),"") -> 2.8196718
A83: 2:34 | B83: Down Royal | C83: Irish EBF Auction Series Fillies Maiden | E83: 7 | F83: Good | G83: 9 | H83: Ladrona (IRE) | I83: Lee, W J | J83: Twomey, P | K83: 9 | L83: 0 | M83: 2 | O83: 2 | P83: 3.9612645 | Q83: 0.25244464 | R83: 4 | S83: =IF(AND(ISNUMBER(R83),R83>1,P83>0),R83/P83-1,"") -> 0.0097785612 | T83: =IF(AND(ISNUMBER(P83),P83>0),P83*EXP('Read me'!$B$22),"") -> 4.8382994
A84: 2:34 | B84: Down Royal | C84: Irish EBF Auction Series Fillies Maiden | E84: 7 | F84: Good | G84: 9 | H84: Hip Hop Chrissy (IRE) | I84: Ryan, Gavin | J84: Obrien, Donnacha | K84: 8 | L84: 78 | M84: 2 | N84: 44 | O84: 3 | P84: 7.6601298 | Q84: 0.13054609 | R84: 6.5 | S84: =IF(AND(ISNUMBER(R84),R84>1,P84>0),R84/P84-1,"") -> -0.15145041 | T84: =IF(AND(ISNUMBER(P84),P84>0),P84*EXP('Read me'!$B$22),"") -> 9.3561037
A85: 2:34 | B85: Down Royal | C85: Irish EBF Auction Series Fillies Maiden | E85: 7 | F85: Good | G85: 9 | H85: Little Scotch (IRE) | I85: Carroll, G F | J85: Cromwell, Gavin Patrick | K85: 7 | L85: 0 | M85: 2 | O85: 4 | P85: 19.326009 | Q85: 0.051743742 | R85: 19 | S85: =IF(AND(ISNUMBER(R85),R85>1,P85>0),R85/P85-1,"") -> -0.016868907 | T85: =IF(AND(ISNUMBER(P85),P85>0),P85*EXP('Read me'!$B$22),"") -> 23.60484
A86: 2:34 | B86: Down Royal | C86: Irish EBF Auction Series Fillies Maiden | E86: 7 | F86: Good | G86: 9 | H86: Leap Of Light (IRE) | I86: Kennedy, K G | J86: Harrington, Mrs John | K86: 6 | L86: 0 | M86: 2 | N86: 11 | O86: 5 | P86: 21.851821 | Q86: 0.045762776 | R86: 7 | S86: =IF(AND(ISNUMBER(R86),R86>1,P86>0),R86/P86-1,"") -> -0.67966057 | T86: =IF(AND(ISNUMBER(P86),P86>0),P86*EXP('Read me'!$B$22),"") -> 26.689874
A87: 2:34 | B87: Down Royal | C87: Irish EBF Auction Series Fillies Maiden | E87: 7 | F87: Good | G87: 9 | H87: Shadowbelle (IRE) | J87: Oliver, Andrew | K87: 10 | L87: 0 | M87: 2 | N87: 11 | O87: 6 | P87: 37.70972 | Q87: 0.026518362 | R87: 51 | S87: =IF(AND(ISNUMBER(R87),R87>1,P87>0),R87/P87-1,"") -> 0.35243645 | T87: =IF(AND(ISNUMBER(P87),P87>0),P87*EXP('Read me'!$B$22),"") -> 46.058756
A88: 2:34 | B88: Down Royal | C88: Irish EBF Auction Series Fillies Maiden | E88: 7 | F88: Good | G88: 9 | H88: Handsoffshesmine (IRE) | I88: Dalton, J S | J88: Slattery, Andrew | K88: 1 | L88: 0 | M88: 2 | O88: 7 | P88: 39.972723 | Q88: 0.02501706 | R88: 34 | S88: =IF(AND(ISNUMBER(R88),R88>1,P88>0),R88/P88-1,"") -> -0.14941996 | T88: =IF(AND(ISNUMBER(P88),P88>0),P88*EXP('Read me'!$B$22),"") -> 48.822794
A89: 2:34 | B89: Down Royal | C89: Irish EBF Auction Series Fillies Maiden | E89: 7 | F89: Good | G89: 9 | H89: Spectrolyte (IRE) | I89: Slattery, A J | J89: Slattery, Andrew | K89: 5 | L89: 0 | M89: 2 | N89: 65 | O89: 8 | P89: 40.672638 | Q89: 0.024586554 | R89: 10 | S89: =IF(AND(ISNUMBER(R89),R89>1,P89>0),R89/P89-1,"") -> -0.75413446 | T89: =IF(AND(ISNUMBER(P89),P89>0),P89*EXP('Read me'!$B$22),"") -> 49.677672
A90: 2:34 | B90: Down Royal | C90: Irish EBF Auction Series Fillies Maiden | E90: 7 | F90: Good | G90: 9 | H90: Alpha Betty (IRE) | I90: Cleary, R P | J90: Farrell, C W J | K90: 2 | L90: 0 | M90: 2 | O90: 9 | P90: 97.954535 | Q90: 0.010208818 | R90: 67 | S90: =IF(AND(ISNUMBER(R90),R90>1,P90>0),R90/P90-1,"") -> -0.31600921 | T90: =IF(AND(ISNUMBER(P90),P90>0),P90*EXP('Read me'!$B$22),"") -> 119.64194
A91: 2:40 | B91: Brighton | C91: Follow Matchbook On X Nursery | D91: Class 6 | E91: 8 | F91: Good To Firm | G91: 13 | H91: Magical Life | I91: Ryan, Rossa | J91: Moore, J S | K91: 5 | L91: 57 | M91: 2 | N91: 15 | O91: 1 | P91: 6.7963234 | Q91: 0.14713838 | R91: 5.5 | S91: =IF(AND(ISNUMBER(R91),R91>1,P91>0),R91/P91-1,"") -> -0.19073892 | T91: =IF(AND(ISNUMBER(P91),P91>0),P91*EXP('Read me'!$B$22),"") -> 8.3010481
A92: 2:40 | B92: Brighton | C92: Follow Matchbook On X Nursery | D92: Class 6 | E92: 8 | F92: Good To Firm | G92: 13 | H92: Hello You Ten (IRE) | I92: Osborne, Saffie | J92: Osborne, J A | K92: 3 | L92: 63 | M92: 2 | N92: 17 | O92: 2 | P92: 8.0427547 | Q92: 0.12433551 | R92: 5 | S92: =IF(AND(ISNUMBER(R92),R92>1,P92>0),R92/P92-1,"") -> -0.37832245 | T92: =IF(AND(ISNUMBER(P92),P92>0),P92*EXP('Read me'!$B$22),"") -> 9.8234428
A93: 2:40 | B93: Brighton | C93: Follow Matchbook On X Nursery | D93: Class 6 | E93: 8 | F93: Good To Firm | G93: 13 | H93: Banged Up | I93: Bishop, Charles | J93: Houghton, Eve Johnson | K93: 13 | L93: 63 | M93: 2 | N93: 35 | O93: 3 | P93: 8.7848286 | Q93: 0.11383261 | R93: 15 | S93: =IF(AND(ISNUMBER(R93),R93>1,P93>0),R93/P93-1,"") -> 0.7074892 | T93: =IF(AND(ISNUMBER(P93),P93>0),P93*EXP('Read me'!$B$22),"") -> 10.729814
A94: 2:40 | B94: Brighton | C94: Follow Matchbook On X Nursery | D94: Class 6 | E94: 8 | F94: Good To Firm | G94: 13 | H94: Wild Orchid | I94: Callan, Jack | J94: Johnston, Charlie | K94: 11 | L94: 50 | M94: 2 | N94: 11 | O94: 4 | P94: 10.888916 | Q94: 0.091836504 | R94: 8 | S94: =IF(AND(ISNUMBER(R94),R94>1,P94>0),R94/P94-1,"") -> -0.26530797 | T94: =IF(AND(ISNUMBER(P94),P94>0),P94*EXP('Read me'!$B$22),"") -> 13.299752
A95: 2:40 | B95: Brighton | C95: Follow Matchbook On X Nursery | D95: Class 6 | E95: 8 | F95: Good To Firm | G95: 13 | H95: Blue Skies Above | I95: Shoemark, Kieran | J95: Cole, Oliver | K95: 12 | L95: 62 | M95: 2 | N95: 21 | O95: 5 | P95: 11.739505 | Q95: 0.085182468 | R95: 6.5 | S95: =IF(AND(ISNUMBER(R95),R95>1,P95>0),R95/P95-1,"") -> -0.44631396 | T95: =IF(AND(ISNUMBER(P95),P95>0),P95*EXP('Read me'!$B$22),"") -> 14.338664
A96: 2:40 | B96: Brighton | C96: Follow Matchbook On X Nursery | D96: Class 6 | E96: 8 | F96: Good To Firm | G96: 13 | H96: Mandolin Rain (IRE) | I96: Probert, David | J96: Cunha, Dylan | K96: 6 | L96: 65 | M96: 2 | N96: 13 | O96: 6 | P96: 12.353536 | Q96: 0.080948485 | R96: 13 | S96: =IF(AND(ISNUMBER(R96),R96>1,P96>0),R96/P96-1,"") -> 0.052330303 | T96: =IF(AND(ISNUMBER(P96),P96>0),P96*EXP('Read me'!$B$22),"") -> 15.088643
A97: 2:40 | B97: Brighton | C97: Follow Matchbook On X Nursery | D97: Class 6 | E97: 8 | F97: Good To Firm | G97: 13 | H97: Allaboutthelunch | I97: Chalmers, Isobelle | J97: Smyth-Osbourne, Edward | K97: 9 | L97: 46 | M97: 2 | N97: 15 | O97: 7 | P97: 14.861761 | Q97: 0.067286778 | R97: 8.5 | S97: =IF(AND(ISNUMBER(R97),R97>1,P97>0),R97/P97-1,"") -> -0.42806239 | T97: =IF(AND(ISNUMBER(P97),P97>0),P97*EXP('Read me'!$B$22),"") -> 18.152196
A98: 2:40 | B98: Brighton | C98: Follow Matchbook On X Nursery | D98: Class 6 | E98: 8 | F98: Good To Firm | G98: 13 | H98: Enhancing | I98: Fallon, Cieren | J98: Palmer, Hugo | K98: 1 | L98: 62 | M98: 2 | N98: 84 | O98: 8 | P98: 16.328806 | Q98: 0.061241465 | R98: 15 | S98: =IF(AND(ISNUMBER(R98),R98>1,P98>0),R98/P98-1,"") -> -0.081378027 | T98: =IF(AND(ISNUMBER(P98),P98>0),P98*EXP('Read me'!$B$22),"") -> 19.944049
A99: 2:40 | B99: Brighton | C99: Follow Matchbook On X Nursery | D99: Class 6 | E99: 8 | F99: Good To Firm | G99: 13 | H99: Best Yet | I99: Marsh, Finley | J99: Hughes, Richard | K99: 4 | L99: 57 | M99: 2 | N99: 33 | O99: 9 | P99: 17.409374 | Q99: 0.057440318 | R99: 29 | S99: =IF(AND(ISNUMBER(R99),R99>1,P99>0),R99/P99-1,"") -> 0.66576923 | T99: =IF(AND(ISNUMBER(P99),P99>0),P99*EXP('Read me'!$B$22),"") -> 21.263858
A100: 2:40 | B100: Brighton | C100: Follow Matchbook On X Nursery | D100: Class 6 | E100: 8 | F100: Good To Firm | G100: 13 | H100: Golden Oasis | I100: Langley, Taryn | J100: Edwards, Robert | K100: 8 | L100: 65 | M100: 2 | N100: 23 | O100: 10 | P100: 19.873282 | Q100: 0.050318814 | R100: 17 | S100: =IF(AND(ISNUMBER(R100),R100>1,P100>0),R100/P100-1,"") -> -0.14458016 | T100: =IF(AND(ISNUMBER(P100),P100>0),P100*EXP('Read me'!$B$22),"") -> 24.273282
A101: 2:40 | B101: Brighton | C101: Follow Matchbook On X Nursery | D101: Class 6 | E101: 8 | F101: Good To Firm | G101: 13 | H101: Beach Ahead | I101: Fentiman, Warren | J101: Moore, Gary and Josh | K101: 7 | L101: 60 | M101: 2 | N101: 40 | O101: 11 | P101: 20.077164 | Q101: 0.049807832 | R101: 9 | S101: =IF(AND(ISNUMBER(R101),R101>1,P101>0),R101/P101-1,"") -> -0.55172951 | T101: =IF(AND(ISNUMBER(P101),P101>0),P101*EXP('Read me'!$B$22),"") -> 24.522303
A102: 2:40 | B102: Brighton | C102: Follow Matchbook On X Nursery | D102: Class 6 | E102: 8 | F102: Good To Firm | G102: 13 | H102: Courage Best (IRE) | I102: Keenan, Darragh | J102: Millman, B R | K102: 10 | L102: 56 | M102: 2 | N102: 17 | O102: 12 | P102: 21.009455 | Q102: 0.047597618 | R102: 17 | S102: =IF(AND(ISNUMBER(R102),R102>1,P102>0),R102/P102-1,"") -> -0.19084049 | T102: =IF(AND(ISNUMBER(P102),P102>0),P102*EXP('Read me'!$B$22),"") -> 25.661006
A103: 2:40 | B103: Brighton | C103: Follow Matchbook On X Nursery | D103: Class 6 | E103: 8 | F103: Good To Firm | G103: 13 | H103: Zonneveld | I103: Egan, John | J103: Moore, J S | K103: 2 | L103: 48 | M103: 2 | N103: 11 | O103: 13 | P103: 43.415558 | Q103: 0.023033218 | R103: 51 | S103: =IF(AND(ISNUMBER(R103),R103>1,P103>0),R103/P103-1,"") -> 0.1746941 | T103: =IF(AND(ISNUMBER(P103),P103>0),P103*EXP('Read me'!$B$22),"") -> 53.027882
...

Sheet Down Royal
A1: Time | B1: Course | C1: Race | D1: Class | E1: Furlongs | F1: Going | G1: Runners | H1: Horse | I1: Jockey | J1: Trainer | K1: Draw | L1: OR | M1: Age | N1: Days since run | O1: Model rank | P1: Predicted BSP | Q1: Win probability | R1: Card odds (HRB) | S1: Card odds vs model | T1: Rule: back at Betfair ≥
A2: 1:24 | B2: Down Royal | C2: Molson Coors Beverage Company Nursery Handicap | E2: 5 | F2: Good | G2: 6 | H2: Santo Parvenue (IRE) | I2: Lee, W J | J2: Harty, Edward and Patrick | K2: 4 | L2: 59 | M2: 2 | N2: 11 | O2: 1 | P2: 2.2147676 | Q2: 0.45151465 | R2: 1.8 | S2: =IF(AND(ISNUMBER(R2),R2>1,P2>0),R2/P2-1,"") -> -0.18727363 | T2: =IF(AND(ISNUMBER(P2),P2>0),P2*EXP('Read me'!$B$22),"") -> 2.7051232
A3: 1:24 | B3: Down Royal | C3: Molson Coors Beverage Company Nursery Handicap | E3: 5 | F3: Good | G3: 6 | H3: Premier View (IRE) | I3: Cusack, C | J3: Bromhead, Henry De | K3: 2 | L3: 74 | M3: 2 | N3: 24 | O3: 2 | P3: 4.3596875 | Q3: 0.22937424 | R3: 4.3333333 | S3: =IF(AND(ISNUMBER(R3),R3>1,P3>0),R3/P3-1,"") -> -0.0060449714 | T3: =IF(AND(ISNUMBER(P3),P3>0),P3*EXP('Read me'!$B$22),"") -> 5.3249344
A4: 1:24 | B4: Down Royal | C4: Molson Coors Beverage Company Nursery Handicap | E4: 5 | F4: Good | G4: 6 | H4: Invincible Irish (IRE) | I4: Coen, Ben M | J4: McLoughlin, Daniel | K4: 1 | L4: 61 | M4: 2 | N4: 11 | O4: 3 | P4: 5.9340624 | Q4: 0.16851862 | R4: 6 | S4: =IF(AND(ISNUMBER(R4),R4>1,P4>0),R4/P4-1,"") -> 0.011111717 | T4: =IF(AND(ISNUMBER(P4),P4>0),P4*EXP('Read me'!$B$22),"") -> 7.2478802
A5: 1:24 | B5: Down Royal | C5: Molson Coors Beverage Company Nursery Handicap | E5: 5 | F5: Good | G5: 6 | H5: Rathbran Lady (IRE) | I5: Joyce, Wesley | J5: Mulvany, Michael | K5: 6 | L5: 47 | M5: 2 | N5: 11 | O5: 4 | P5: 15.302509 | Q5: 0.065348762 | R5: 13 | S5: =IF(AND(ISNUMBER(R5),R5>1,P5>0),R5/P5-1,"") -> -0.15046609 | T5: =IF(AND(ISNUMBER(P5),P5>0),P5*EXP('Read me'!$B$22),"") -> 18.690526
A6: 1:24 | B6: Down Royal | C6: Molson Coors Beverage Company Nursery Handicap | E6: 5 | F6: Good | G6: 6 | H6: Annie Tips (IRE) | I6: McAteer, L T | J6: Dowling, James | K6: 7 | L6: 67 | M6: 2 | N6: 36 | O6: 5 | P6: 19.343344 | Q6: 0.051697369 | R6: 19 | S6: =IF(AND(ISNUMBER(R6),R6>1,P6>0),R6/P6-1,"") -> -0.017749989 | T6: =IF(AND(ISNUMBER(P6),P6>0),P6*EXP('Read me'!$B$22),"") -> 23.626014
A7: 1:24 | B7: Down Royal | C7: Molson Coors Beverage Company Nursery Handicap | E7: 5 | F7: Good | G7: 6 | H7: Syrah (IRE) | I7: Mulligan, R M | J7: Weld, Charles | K7: 5 | L7: 58 | M7: 2 | N7: 11 | O7: 6 | P7: 29.809492 | Q7: 0.033546362 | R7: 23 | S7: =IF(AND(ISNUMBER(R7),R7>1,P7>0),R7/P7-1,"") -> -0.22843368 | T7: =IF(AND(ISNUMBER(P7),P7>0),P7*EXP('Read me'!$B$22),"") -> 36.409396
A8: 1:59 | B8: Down Royal | C8: Coors Fillies Handicap | E8: 13 | F8: Good | G8: 10 | H8: Nellcote (IRE) | I8: McDonogh, D P | J8: OBrien, Joseph Patrick | K8: 5 | L8: 82 | M8: 3 | N8: 37 | O8: 1 | P8: 4.9114672 | Q8: 0.20360515 | R8: 4.5 | S8: =IF(AND(ISNUMBER(R8),R8>1,P8>0),R8/P8-1,"") -> -0.083776841 | T8: =IF(AND(ISNUMBER(P8),P8>0),P8*EXP('Read me'!$B$22),"") -> 5.9988796
A9: 1:59 | B9: Down Royal | C9: Coors Fillies Handicap | E9: 13 | F9: Good | G9: 10 | H9: Stellar Moment (IRE) | I9: Whelan, R P | J9: ODonoghue, John | K9: 7 | L9: 79 | M9: 3 | N9: 28 | O9: 2 | P9: 5.3404808 | Q9: 0.18724906 | R9: 4.3333333 | S9: =IF(AND(ISNUMBER(R9),R9>1,P9>0),R9/P9-1,"") -> -0.18858742 | T9: =IF(AND(ISNUMBER(P9),P9>0),P9*EXP('Read me'!$B$22),"") -> 6.522878
A10: 1:59 | B10: Down Royal | C10: Coors Fillies Handicap | E10: 13 | F10: Good | G10: 10 | H10: Lady Plimsoll (IRE) | I10: Holohan, Reese | J10: OCallaghan, M D | K10: 9 | L10: 72 | M10: 4 | N10: 12 | O10: 3 | P10: 6.2110078 | Q10: 0.16100447 | R10: 5.5 | S10: =IF(AND(ISNUMBER(R10),R10>1,P10>0),R10/P10-1,"") -> -0.11447543 | T10: =IF(AND(ISNUMBER(P10),P10>0),P10*EXP('Read me'!$B$22),"") -> 7.5861421
A11: 1:59 | B11: Down Royal | C11: Coors Fillies Handicap | E11: 13 | F11: Good | G11: 10 | H11: Navy Waters (IRE) | I11: Lee, W J | J11: McCreery, W | K11: 2 | L11: 84 | M11: 5 | N11: 20 | O11: 4 | P11: 6.735345 | Q11: 0.14847049 | R11: 5.5 | S11: =IF(AND(ISNUMBER(R11),R11>1,P11>0),R11/P11-1,"") -> -0.18341229 | T11: =IF(AND(ISNUMBER(P11),P11>0),P11*EXP('Read me'!$B$22),"") -> 8.226569
A12: 1:59 | B12: Down Royal | C12: Coors Fillies Handicap | E12: 13 | F12: Good | G12: 10 | H12: Vanir (IRE) | I12: Coen, Ben M | J12: Murtagh, J P | K12: 1 | L12: 84 | M12: 3 | N12: 37 | O12: 5 | P12: 13.041516 | Q12: 0.076678201 | R12: 10 | S12: =IF(AND(ISNUMBER(R12),R12>1,P12>0),R12/P12-1,"") -> -0.23321799 | T12: =IF(AND(ISNUMBER(P12),P12>0),P12*EXP('Read me'!$B$22),"") -> 15.928944
A13: 1:59 | B13: Down Royal | C13: Coors Fillies Handicap | E13: 13 | F13: Good | G13: 10 | H13: Just Keep Flying (USA) | I13: Kennedy, K G | J13: Harrington, Mrs John | K13: 8 | L13: 78 | M13: 4 | N13: 108 | O13: 6 | P13: 13.805392 | Q13: 0.072435466 | R13: 12 | S13: =IF(AND(ISNUMBER(R13),R13>1,P13>0),R13/P13-1,"") -> -0.13077441 | T13: =IF(AND(ISNUMBER(P13),P13>0),P13*EXP('Read me'!$B$22),"") -> 16.861944
... A18: 2:34 | B18: Down Royal | C18: Irish EBF Auction Series Fillies Maiden | E18: 7 | F18: Good | G18: 9 | H18: Essence Of Time | I18: Lordan, W M | J18: Oliver, Andrew | K18: 3 | L18: 0 | M18: 2 | N18: 24 | O18: 1 | P18: 2.308552 | Q18: 0.43317196 | R18: 2.2 | S18: =IF(AND(ISNUMBER(R18),R18>1,P18>0),R18/P18-1,"") -> -0.047021693 | T18: =IF(AND(ISNUMBER(P18),P18>0),P18*EXP('Read me'!$B$22),"") -> 2.8196718
A19: 2:34 | B19: Down Royal | C19: Irish EBF Auction Series Fillies Maiden | E19: 7 | F19: Good | G19: 9 | H19: Ladrona (IRE) | I19: Lee, W J | J19: Twomey, P | K19: 9 | L19: 0 | M19: 2 | O19: 2 | P19: 3.9612645 | Q19: 0.25244464 | R19: 4 | S19: =IF(AND(ISNUMBER(R19),R19>1,P19>0),R19/P19-1,"") -> 0.0097785612 | T19: =IF(AND(ISNUMBER(P19),P19>0),P19*EXP('Read me'!$B$22),"") -> 4.8382994
A20: 2:34 | B20: Down Royal | C20: Irish EBF Auction Series Fillies Maiden | E20: 7 | F20: Good | G20: 9 | H20: Hip Hop Chrissy (IRE) | I20: Ryan, Gavin | J20: Obrien, Donnacha | K20: 8 | L20: 78 | M20: 2 | N20: 44 | O20: 3 | P20: 7.6601298 | Q20: 0.13054609 | R20: 6.5 | S20: =IF(AND(ISNUMBER(R20),R20>1,P20>0),R20/P20-1,"") -> -0.15145041 | T20: =IF(AND(ISNUMBER(P20),P20>0),P20*EXP('Read me'!$B$22),"") -> 9.3561037
A21: 2:34 | B21: Down Royal | C21: Irish EBF Auction Series Fillies Maiden | E21: 7 | F21: Good | G21: 9 | H21: Little Scotch (IRE) | I21: Carroll, G F | J21: Cromwell, Gavin Patrick | K21: 7 | L21: 0 | M21: 2 | O21: 4 | P21: 19.326009 | Q21: 0.051743742 | R21: 19 | S21: =IF(AND(ISNUMBER(R21),R21>1,P21>0),R21/P21-1,"") -> -0.016868907 | T21: =IF(AND(ISNUMBER(P21),P21>0),P21*EXP('Read me'!$B$22),"") -> 23.60484
A22: 2:34 | B22: Down Royal | C22: Irish EBF Auction Series Fillies Maiden | E22: 7 | F22: Good | G22: 9 | H22: Leap Of Light (IRE) | I22: Kennedy, K G | J22: Harrington, Mrs John | K22: 6 | L22: 0 | M22: 2 | N22: 11 | O22: 5 | P22: 21.851821 | Q22: 0.045762776 | R22: 7 | S22: =IF(AND(ISNUMBER(R22),R22>1,P22>0),R22/P22-1,"") -> -0.67966057 | T22: =IF(AND(ISNUMBER(P22),P22>0),P22*EXP('Read me'!$B$22),"") -> 26.689874
A23: 2:34 | B23: Down Royal | C23: Irish EBF Auction Series Fillies Maiden | E23: 7 | F23: Good | G23: 9 | H23: Shadowbelle (IRE) | J23: Oliver, Andrew | K23: 10 | L23: 0 | M23: 2 | N23: 11 | O23: 6 | P23: 37.70972 | Q23: 0.026518362 | R23: 51 | S23: =IF(AND(ISNUMBER(R23),R23>1,P23>0),R23/P23-1,"") -> 0.35243645 | T23: =IF(AND(ISNUMBER(P23),P23>0),P23*EXP('Read me'!$B$22),"") -> 46.058756
A24: 2:34 | B24: Down Royal | C24: Irish EBF Auction Series Fillies Maiden | E24: 7 | F24: Good | G24: 9 | H24: Handsoffshesmine (IRE) | I24: Dalton, J S | J24: Slattery, Andrew | K24: 1 | L24: 0 | M24: 2 | O24: 7 | P24: 39.972723 | Q24: 0.02501706 | R24: 34 | S24: =IF(AND(ISNUMBER(R24),R24>1,P24>0),R24/P24-1,"") -> -0.14941996 | T24: =IF(AND(ISNUMBER(P24),P24>0),P24*EXP('Read me'!$B$22),"") -> 48.822794
A25: 2:34 | B25: Down Royal | C25: Irish EBF Auction Series Fillies Maiden | E25: 7 | F25: Good | G25: 9 | H25: Spectrolyte (IRE) | I25: Slattery, A J | J25: Slattery, Andrew | K25: 5 | L25: 0 | M25: 2 | N25: 65 | O25: 8 | P25: 40.672638 | Q25: 0.024586554 | R25: 10 | S25: =IF(AND(ISNUMBER(R25),R25>1,P25>0),R25/P25-1,"") -> -0.75413446 | T25: =IF(AND(ISNUMBER(P25),P25>0),P25*EXP('Read me'!$B$22),"") -> 49.677672
A26: 2:34 | B26: Down Royal | C26: Irish EBF Auction Series Fillies Maiden | E26: 7 | F26: Good | G26: 9 | H26: Alpha Betty (IRE) | I26: Cleary, R P | J26: Farrell, C W J | K26: 2 | L26: 0 | M26: 2 | O26: 9 | P26: 97.954535 | Q26: 0.010208818 | R26: 67 | S26: =IF(AND(ISNUMBER(R26),R26>1,P26>0),R26/P26-1,"") -> -0.31600921 | T26: =IF(AND(ISNUMBER(P26),P26>0),P26*EXP('Read me'!$B$22),"") -> 119.64194
A27: 3:09 | B27: Down Royal | C27: Madri Excepcional Maiden | E27: 7 | F27: Good | G27: 9 | H27: Daring Heart (IRE) | I27: Carroll, G F | J27: Lyons, G M | K27: 2 | L27: 0 | M27: 3 | N27: 136 | O27: 1 | P27: 2.5919908 | Q27: 0.38580384 | R27: 2.1 | S27: =IF(AND(ISNUMBER(R27),R27>1,P27>0),R27/P27-1,"") -> -0.18981194 | T27: =IF(AND(ISNUMBER(P27),P27>0),P27*EXP('Read me'!$B$22),"") -> 3.1658647
A28: 3:09 | B28: Down Royal | C28: Madri Excepcional Maiden | E28: 7 | F28: Good | G28: 9 | H28: Blooming Rose (IRE) | I28: Sheridan, J M | J28: OBrien, Joseph Patrick | K28: 10 | L28: 0 | M28: 3 | N28: 109 | O28: 2 | P28: 4.82396 | Q28: 0.20729857 | R28: 5 | S28: =IF(AND(ISNUMBER(R28),R28>1,P28>0),R28/P28-1,"") -> 0.03649285 | T28: =IF(AND(ISNUMBER(P28),P28>0),P28*EXP('Read me'!$B$22),"") -> 5.891998
A29: 3:09 | B29: Down Royal | C29: Madri Excepcional Maiden | E29: 7 | F29: Good | G29: 9 | H29: Monmouth (IRE) | I29: Lordan, W M | J29: OBrien, A P | K29: 1 | L29: 74 | M29: 3 | N29: 101 | O29: 3 | P29: 5.1813018 | Q29: 0.19300169 | R29: 4.5 | S29: =IF(AND(ISNUMBER(R29),R29>1,P29>0),R29/P29-1,"") -> -0.1314924 | T29: =IF(AND(ISNUMBER(P29),P29>0),P29*EXP('Read me'!$B$22),"") -> 6.3284563
A30: 3:09 | B30: Down Royal | C30: Madri Excepcional Maiden | E30: 7 | F30: Good | G30: 9 | H30: Orellana (IRE) | I30: Rutledge, Siobhan | J30: Rogers, H | K30: 4 | L30: 75 | M30: 3 | N30: 7 | O30: 4 | P30: 6.8158325 | Q30: 0.14671722 | R30: 4.5 | S30: =IF(AND(ISNUMBER(R30),R30>1,P30>0),R30/P30-1,"") -> -0.3397725 | T30: =IF(AND(ISNUMBER(P30),P30>0),P30*EXP('Read me'!$B$22),"") -> 8.3248766
A31: 3:09 | B31: Down Royal | C31: Madri Excepcional Maiden | E31: 7 | F31: Good | G31: 9 | H31: Mac An Luais (IRE) | I31: McAteer, L T | J31: Foley, Patrick T | K31: 6 | L31: 0 | M31: 3 | N31: 101 | O31: 5 | P31: 15.928027 | Q31: 0.062782413 | R31: 21 | S31: =IF(AND(ISNUMBER(R31),R31>1,P31>0),R31/P31-1,"") -> 0.31843068 | T31: =IF(AND(ISNUMBER(P31),P31>0),P31*EXP('Read me'!$B$22),"") -> 19.454537
A32: 3:09 | B32: Down Royal | C32: Madri Excepcional Maiden | E32: 7 | F32: Good | G32: 9 | H32: Monty Bear (IRE) | I32: Holohan, Reese | J32: Fahey, Mark | K32: 3 | L32: 0 | M32: 3 | N32: 283 | O32: 6 | P32: 479.8726 | Q32: 0.0020838864 | R32: 151 | S32: =IF(AND(ISNUMBER(R32),R32>1,P32>0),R32/P32-1,"") -> -0.68533315 | T32: =IF(AND(ISNUMBER(P32),P32>0),P32*EXP('Read me'!$B$22),"") -> 586.11772
A33: 3:09 | B33: Down Royal | C33: Madri Excepcional Maiden | E33: 7 | F33: Good | G33: 9 | H33: Caption This (IRE) | I33: Colgan, R C | J33: Nash, J A | K33: 9 | L33: 0 | M33: 3 | N33: 19 | O33: 7 | P33: 1013.4055 | Q33: 0.00098677184 | R33: 126 | S33: =IF(AND(ISNUMBER(R33),R33>1,P33>0),R33/P33-1,"") -> -0.87566675 | T33: =IF(AND(ISNUMBER(P33),P33>0),P33*EXP('Read me'!$B$22),"") -> 1237.7763
A34: 3:09 | B34: Down Royal | C34: Madri Excepcional Maiden | E34: 7 | F34: Good | G34: 9 | H34: Freddiesadienray (IRE) | I34: Burns, Nicola | J34: Keane, Gerard | K34: 7 | L34: 0 | M34: 3 | N34: 7 | O34: 8 | P34: 1491.7045 | Q34: 0.00067037406 | R34: 126 | S34: =IF(AND(ISNUMBER(R34),R34>1,P34>0),R34/P34-1,"") -> -0.91553287 | T34: =IF(AND(ISNUMBER(P34),P34>0),P34*EXP('Read me'!$B$22),"") -> 1821.972
A35: 3:09 | B35: Down Royal | C35: Madri Excepcional Maiden | E35: 7 | F35: Good | G35: 9 | H35: Notahairoutofplace | I35: Ryan, J J G | J35: Watson, R K | K35: 5 | L35: 0 | M35: 3 | N35: 73 | O35: 9 | P35: 1526.1733 | Q35: 0.00065523356 | R35: 201 | S35: =IF(AND(ISNUMBER(R35),R35>1,P35>0),R35/P35-1,"") -> -0.86829805 | T35: =IF(AND(ISNUMBER(P35),P35>0),P35*EXP('Read me'!$B$22),"") -> 1864.0723
A36: 3:44 | B36: Down Royal | C36: Molson Coors Beverage Company Handicap | E36: 7 | F36: Good | G36: 14 | H36: Send Harry (IRE) | I36: Dalton, J S | J36: McCutcheon, Miss Evanna | K36: 7 | L36: 70 | M36: 4 | N36: 10 | O36: 1 | P36: 6.9803971 | Q36: 0.14325833 | R36: 7 | S36: =IF(AND(ISNUMBER(R36),R36>1,P36>0),R36/P36-1,"") -> 0.0028082771 | T36: =IF(AND(ISNUMBER(P36),P36>0),P36*EXP('Read me'!$B$22),"") -> 8.5258763
A37: 3:44 | B37: Down Royal | C37: Molson Coors Beverage Company Handicap | E37: 7 | F37: Good | G37: 14 | H37: Barbapapa (IRE) | I37: Grant, A S | J37: Bromhead, Henry De | K37: 2 | L37: 74 | M37: 7 | N37: 68 | O37: 2 | P37: 7.3739447 | Q37: 0.13561263 | R37: 7.5 | S37: =IF(AND(ISNUMBER(R37),R37>1,P37>0),R37/P37-1,"") -> 0.017094694 | T37: =IF(AND(ISNUMBER(P37),P37>0),P37*EXP('Read me'!$B$22),"") -> 9.0065564
A38: 3:44 | B38: Down Royal | C38: Molson Coors Beverage Company Handicap | E38: 7 | F38: Good | G38: 14 | H38: Faoladh (IRE) | I38: Coen, S | J38: Slattery, Andrew | K38: 9 | L38: 68 | M38: 4 | N38: 7 | O38: 3 | P38: 7.863027 | Q38: 0.12717749 | R38: 8 | S38: =IF(AND(ISNUMBER(R38),R38>1,P38>0),R38/P38-1,"") -> 0.017419884 | T38: =IF(AND(ISNUMBER(P38),P38>0),P38*EXP('Read me'!$B$22),"") -> 9.6039228
... A91: 5:25 | B91: Down Royal | C91: Molson Coors Beverage Handicap | E91: 13 | F91: Good | G91: 14 | H91: Michinaga (IRE) | I91: McAteer, L T | J91: Weld, Charles | K91: 3 | L91: 76 | M91: 3 | N91: 23 | O91: 14 | P91: 98.132695 | Q91: 0.010190284 | R91: 29 | S91: =IF(AND(ISNUMBER(R91),R91>1,P91>0),R91/P91-1,"") -> -0.70448177 | T91: =IF(AND(ISNUMBER(P91),P91>0),P91*EXP('Read me'!$B$22),"") -> 119.85954

Sheet Brighton
A1: Time | B1: Course | C1: Race | D1: Class | E1: Furlongs | F1: Going | G1: Runners | H1: Horse | I1: Jockey | J1: Trainer | K1: Draw | L1: OR | M1: Age | N1: Days since run | O1: Model rank | P1: Predicted BSP | Q1: Win probability | R1: Card odds (HRB) | S1: Card odds vs model | T1: Rule: back at Betfair ≥
A2: 1:30 | B2: Brighton | C2: Matchbook SignUp - Get 20% Back On Losses Handicap | D2: Class 6 | F2: Good To Firm | G2: 10 | H2: Bated Breeze (IRE) | I2: Marsh, Finley | J2: Moore, Gary and Josh | K2: 3 | L2: 47 | M2: 5 | N2: 21 | O2: 1 | P2: 5.1776255 | Q2: 0.19313873 | R2: 5.5 | S2: =IF(AND(ISNUMBER(R2),R2>1,P2>0),R2/P2-1,"") -> 0.062263002 | T2: =IF(AND(ISNUMBER(P2),P2>0),P2*EXP('Read me'!$B$22),"") -> 6.3239661
A3: 1:30 | B3: Brighton | C3: Matchbook SignUp - Get 20% Back On Losses Handicap | D3: Class 6 | F3: Good To Firm | G3: 10 | H3: Roman Spring (IRE) | I3: ONeill, K T | J3: Bridger, J / Cook, R | K3: 9 | L3: 50 | M3: 6 | N3: 21 | O3: 2 | P3: 6.3779397 | Q3: 0.15679044 | R3: 5 | S3: =IF(AND(ISNUMBER(R3),R3>1,P3>0),R3/P3-1,"") -> -0.21604778 | T3: =IF(AND(ISNUMBER(P3),P3>0),P3*EXP('Read me'!$B$22),"") -> 7.7900331
A4: 1:30 | B4: Brighton | C4: Matchbook SignUp - Get 20% Back On Losses Handicap | D4: Class 6 | F4: Good To Firm | G4: 10 | H4: Dreambird Dolly | I4: Ryan, Rossa | J4: Gallagher, J | K4: 7 | L4: 53 | M4: 4 | N4: 21 | O4: 3 | P4: 6.7049693 | Q4: 0.14914311 | R4: 7.5 | S4: =IF(AND(ISNUMBER(R4),R4>1,P4>0),R4/P4-1,"") -> 0.11857336 | T4: =IF(AND(ISNUMBER(P4),P4>0),P4*EXP('Read me'!$B$22),"") -> 8.189468
A5: 1:30 | B5: Brighton | C5: Matchbook SignUp - Get 20% Back On Losses Handicap | D5: Class 6 | F5: Good To Firm | G5: 10 | H5: Danger Alert | I5: Langley, Taryn | J5: Kirby, Adam | K5: 1 | L5: 59 | M5: 6 | N5: 4 | O5: 4 | P5: 7.4440022 | Q5: 0.13433634 | R5: 4.5 | S5: =IF(AND(ISNUMBER(R5),R5>1,P5>0),R5/P5-1,"") -> -0.39548648 | T5: =IF(AND(ISNUMBER(P5),P5>0),P5*EXP('Read me'!$B$22),"") -> 9.0921248
A6: 1:30 | B6: Brighton | C6: Matchbook SignUp - Get 20% Back On Losses Handicap | D6: Class 6 | F6: Good To Firm | G6: 10 | H6: Beach Partee | I6: Howarth, Christian | J6: Dixon, Scott | K6: 4 | L6: 52 | M6: 3 | N6: 11 | O6: 5 | P6: 9.0419547 | Q6: 0.11059556 | R6: 10 | S6: =IF(AND(ISNUMBER(R6),R6>1,P6>0),R6/P6-1,"") -> 0.10595555 | T6: =IF(AND(ISNUMBER(P6),P6>0),P6*EXP('Read me'!$B$22),"") -> 11.043868
A7: 1:30 | B7: Brighton | C7: Matchbook SignUp - Get 20% Back On Losses Handicap | D7: Class 6 | F7: Good To Firm | G7: 10 | H7: Harry Brown | I7: Hornby, Rob | J7: Crate, Peter | K7: 2 | L7: 52 | M7: 6 | N7: 12 | O7: 6 | P7: 10.257453 | Q7: 0.097490092 | R7: 4 | S7: =IF(AND(ISNUMBER(R7),R7>1,P7>0),R7/P7-1,"") -> -0.61003963 | T7: =IF(AND(ISNUMBER(P7),P7>0),P7*EXP('Read me'!$B$22),"") -> 12.528481
A8: 1:30 | B8: Brighton | C8: Matchbook SignUp - Get 20% Back On Losses Handicap | D8: Class 6 | F8: Good To Firm | G8: 10 | H8: Diamond Dreamer | I8: Probert, David | J8: Chamings, P R | K8: 10 | L8: 58 | M8: 6 | N8: 41 | O8: 7 | P8: 16.868674 | Q8: 0.059281484 | R8: 23 | S8: =IF(AND(ISNUMBER(R8),R8>1,P8>0),R8/P8-1,"") -> 0.36347413 | T8: =IF(AND(ISNUMBER(P8),P8>0),P8*EXP('Read me'!$B$22),"") -> 20.603444
A9: 1:30 | B9: Brighton | C9: Matchbook SignUp - Get 20% Back On Losses Handicap | D9: Class 6 | F9: Good To Firm | G9: 10 | H9: Stapleford Park | I9: Fox, Kieren | J9: Attwater, M J | K9: 8 | L9: 49 | M9: 4 | N9: 26 | O9: 8 | P9: 22.816178 | Q9: 0.04382855 | R9: 34 | S9: =IF(AND(ISNUMBER(R9),R9>1,P9>0),R9/P9-1,"") -> 0.49017069 | T9: =IF(AND(ISNUMBER(P9),P9>0),P9*EXP('Read me'!$B$22),"") -> 27.867743
A10: 1:30 | B10: Brighton | C10: Matchbook SignUp - Get 20% Back On Losses Handicap | D10: Class 6 | F10: Good To Firm | G10: 10 | H10: Anglesey Lad (IRE) | I10: Cox, William | J10: Dixon, Scott | K10: 5 | L10: 45 | M10: 5 | N10: 138 | O10: 9 | P10: 27.754463 | Q10: 0.036030241 | R10: 34 | S10: =IF(AND(ISNUMBER(R10),R10>1,P10>0),R10/P10-1,"") -> 0.2250282 | T10: =IF(AND(ISNUMBER(P10),P10>0),P10*EXP('Read me'!$B$22),"") -> 33.899378
A11: 1:30 | B11: Brighton | C11: Matchbook SignUp - Get 20% Back On Losses Handicap | D11: Class 6 | F11: Good To Firm | G11: 10 | H11: Desdemona | J11: Attwater, M J | K11: 6 | L11: 56 | M11: 4 | N11: 35 | O11: 10 | P11: 51.638347 | Q11: 0.019365454 | R11: 81 | S11: =IF(AND(ISNUMBER(R11),R11>1,P11>0),R11/P11-1,"") -> 0.56860173 | T11: =IF(AND(ISNUMBER(P11),P11>0),P11*EXP('Read me'!$B$22),"") -> 63.071219
A12: 2:05 | B12: Brighton | C12: Matchbook Betting Exchange Supporting UK Racing Maiden Stakes (GBB Race) | D12: Class 4 | E12: 7 | F12: Good To Firm | G12: 4 | H12: Galileo Star | I12: Ryan, Rossa | J12: Tate, James | K12: 6 | L12: 0 | M12: 3 | O12: 1 | P12: 2.5514401 | Q12: 0.39193551 | R12: 1.5714286 | S12: =IF(AND(ISNUMBER(R12),R12>1,P12>0),R12/P12-1,"") -> -0.38410134 | T12: =IF(AND(ISNUMBER(P12),P12>0),P12*EXP('Read me'!$B$22),"") -> 3.116336
A13: 2:05 | B13: Brighton | C13: Matchbook Betting Exchange Supporting UK Racing Maiden Stakes (GBB Race) | D13: Class 4 | E13: 7 | F13: Good To Firm | G13: 4 | H13: River Nile (IRE) | I13: Watson, Jason | J13: Balding, A M | K13: 3 | L13: 74 | M13: 3 | N13: 11 | O13: 2 | P13: 2.984331 | Q13: 0.33508347 | R13: 3 | S13: =IF(AND(ISNUMBER(R13),R13>1,P13>0),R13/P13-1,"") -> 0.0052504123 | T13: =IF(AND(ISNUMBER(P13),P13>0),P13*EXP('Read me'!$B$22),"") -> 3.6450702
A14: 2:05 | B14: Brighton | C14: Matchbook Betting Exchange Supporting UK Racing Maiden Stakes (GBB Race) | D14: Class 4 | E14: 7 | F14: Good To Firm | G14: 4 | H14: All Shall Be Well | I14: Shoemark, Kieran | J14: Jones, Jack | K14: 1 | L14: 0 | M14: 3 | N14: 25 | O14: 3 | P14: 3.807163 | Q14: 0.26266277 | R14: 7 | S14: =IF(AND(ISNUMBER(R14),R14>1,P14>0),R14/P14-1,"") -> 0.83863942 | T14: =IF(AND(ISNUMBER(P14),P14>0),P14*EXP('Read me'!$B$22),"") -> 4.6500794
A15: 2:05 | B15: Brighton | C15: Matchbook Betting Exchange Supporting UK Racing Maiden Stakes (GBB Race) | D15: Class 4 | E15: 7 | F15: Good To Firm | G15: 4 | H15: Irish Spring | I15: Hogan, D E | J15: Jewell, Karen | K15: 5 | L15: 0 | M15: 4 | N15: 32 | O15: 4 | P15: 96.91573 | Q15: 0.010318242 | R15: 101 | S15: =IF(AND(ISNUMBER(R15),R15>1,P15>0),R15/P15-1,"") -> 0.042142488 | T15: =IF(AND(ISNUMBER(P15),P15>0),P15*EXP('Read me'!$B$22),"") -> 118.37314
A16: 2:40 | B16: Brighton | C16: Follow Matchbook On X Nursery | D16: Class 6 | E16: 8 | F16: Good To Firm | G16: 13 | H16: Magical Life | I16: Ryan, Rossa | J16: Moore, J S | K16: 5 | L16: 57 | M16: 2 | N16: 15 | O16: 1 | P16: 6.7963234 | Q16: 0.14713838 | R16: 5.5 | S16: =IF(AND(ISNUMBER(R16),R16>1,P16>0),R16/P16-1,"") -> -0.19073892 | T16: =IF(AND(ISNUMBER(P16),P16>0),P16*EXP('Read me'!$B$22),"") -> 8.3010481
A17: 2:40 | B17: Brighton | C17: Follow Matchbook On X Nursery | D17: Class 6 | E17: 8 | F17: Good To Firm | G17: 13 | H17: Hello You Ten (IRE) | I17: Osborne, Saffie | J17: Osborne, J A | K17: 3 | L17: 63 | M17: 2 | N17: 17 | O17: 2 | P17: 8.0427547 | Q17: 0.12433551 | R17: 5 | S17: =IF(AND(ISNUMBER(R17),R17>1,P17>0),R17/P17-1,"") -> -0.37832245 | T17: =IF(AND(ISNUMBER(P17),P17>0),P17*EXP('Read me'!$B$22),"") -> 9.8234428
A18: 2:40 | B18: Brighton | C18: Follow Matchbook On X Nursery | D18: Class 6 | E18: 8 | F18: Good To Firm | G18: 13 | H18: Banged Up | I18: Bishop, Charles | J18: Houghton, Eve Johnson | K18: 13 | L18: 63 | M18: 2 | N18: 35 | O18: 3 | P18: 8.7848286 | Q18: 0.11383261 | R18: 15 | S18: =IF(AND(ISNUMBER(R18),R18>1,P18>0),R18/P18-1,"") -> 0.7074892 | T18: =IF(AND(ISNUMBER(P18),P18>0),P18*EXP('Read me'!$B$22),"") -> 10.729814
A19: 2:40 | B19: Brighton | C19: Follow Matchbook On X Nursery | D19: Class 6 | E19: 8 | F19: Good To Firm | G19: 13 | H19: Wild Orchid | I19: Callan, Jack | J19: Johnston, Charlie | K19: 11 | L19: 50 | M19: 2 | N19: 11 | O19: 4 | P19: 10.888916 | Q19: 0.091836504 | R19: 8 | S19: =IF(AND(ISNUMBER(R19),R19>1,P19>0),R19/P19-1,"") -> -0.26530797 | T19: =IF(AND(ISNUMBER(P19),P19>0),P19*EXP('Read me'!$B$22),"") -> 13.299752
A20: 2:40 | B20: Brighton | C20: Follow Matchbook On X Nursery | D20: Class 6 | E20: 8 | F20: Good To Firm | G20: 13 | H20: Blue Skies Above | I20: Shoemark, Kieran | J20: Cole, Oliver | K20: 12 | L20: 62 | M20: 2 | N20: 21 | O20: 5 | P20: 11.739505 | Q20: 0.085182468 | R20: 6.5 | S20: =IF(AND(ISNUMBER(R20),R20>1,P20>0),R20/P20-1,"") -> -0.44631396 | T20: =IF(AND(ISNUMBER(P20),P20>0),P20*EXP('Read me'!$B$22),"") -> 14.338664
A21: 2:40 | B21: Brighton | C21: Follow Matchbook On X Nursery | D21: Class 6 | E21: 8 | F21: Good To Firm | G21: 13 | H21: Mandolin Rain (IRE) | I21: Probert, David | J21: Cunha, Dylan | K21: 6 | L21: 65 | M21: 2 | N21: 13 | O21: 6 | P21: 12.353536 | Q21: 0.080948485 | R21: 13 | S21: =IF(AND(ISNUMBER(R21),R21>1,P21>0),R21/P21-1,"") -> 0.052330303 | T21: =IF(AND(ISNUMBER(P21),P21>0),P21*EXP('Read me'!$B$22),"") -> 15.088643
A22: 2:40 | B22: Brighton | C22: Follow Matchbook On X Nursery | D22: Class 6 | E22: 8 | F22: Good To Firm | G22: 13 | H22: Allaboutthelunch | I22: Chalmers, Isobelle | J22: Smyth-Osbourne, Edward | K22: 9 | L22: 46 | M22: 2 | N22: 15 | O22: 7 | P22: 14.861761 | Q22: 0.067286778 | R22: 8.5 | S22: =IF(AND(ISNUMBER(R22),R22>1,P22>0),R22/P22-1,"") -> -0.42806239 | T22: =IF(AND(ISNUMBER(P22),P22>0),P22*EXP('Read me'!$B$22),"") -> 18.152196
A23: 2:40 | B23: Brighton | C23: Follow Matchbook On X Nursery | D23: Class 6 | E23: 8 | F23: Good To Firm | G23: 13 | H23: Enhancing | I23: Fallon, Cieren | J23: Palmer, Hugo | K23: 1 | L23: 62 | M23: 2 | N23: 84 | O23: 8 | P23: 16.328806 | Q23: 0.061241465 | R23: 15 | S23: =IF(AND(ISNUMBER(R23),R23>1,P23>0),R23/P23-1,"") -> -0.081378027 | T23: =IF(AND(ISNUMBER(P23),P23>0),P23*EXP('Read me'!$B$22),"") -> 19.944049
A24: 2:40 | B24: Brighton | C24: Follow Matchbook On X Nursery | D24: Class 6 | E24: 8 | F24: Good To Firm | G24: 13 | H24: Best Yet | I24: Marsh, Finley | J24: Hughes, Richard | K24: 4 | L24: 57 | M24: 2 | N24: 33 | O24: 9 | P24: 17.409374 | Q24: 0.057440318 | R24: 29 | S24: =IF(AND(ISNUMBER(R24),R24>1,P24>0),R24/P24-1,"") -> 0.66576923 | T24: =IF(AND(ISNUMBER(P24),P24>0),P24*EXP('Read me'!$B$22),"") -> 21.263858
... A64: 5:00 | B64: Brighton | C64: Download The Matchbook Exchange App Apprentice Handicap | D64: Class 6 | E64: 6 | F64: Good To Firm | G64: 8 | H64: Daley T (IRE) | I64: Gunn, Molly | J64: Carroll, A W | K64: 6 | L64: 46 | M64: 6 | N64: 26 | O64: 8 | P64: 71.412081 | Q64: 0.014003233 | R64: 34 | S64: =IF(AND(ISNUMBER(R64),R64>1,P64>0),R64/P64-1,"") -> -0.52389008 | T64: =IF(AND(ISNUMBER(P64),P64>0),P64*EXP('Read me'!$B$22),"") -> 87.222913

Sheet Roscommon
A1: Time | B1: Course | C1: Race | D1: Class | E1: Furlongs | F1: Going | G1: Runners | H1: Horse | I1: Jockey | J1: Trainer | K1: Draw | L1: OR | M1: Age | N1: Days since run | O1: Model rank | P1: Predicted BSP | Q1: Win probability | R1: Card odds (HRB) | S1: Card odds vs model | T1: Rule: back at Betfair ≥
A2: 1:35 | B2: Roscommon | C2: Athleague Maiden Hurdle | E2: 15.5 | F2: Good | G2: 13 | H2: Direct Approach (IRE) | I2: Kennedy, J W | J2: Elliott, Gordon | K2: 2 | L2: 97 | M2: 4 | N2: 10 | O2: 1 | P2: 3.1862358 | Q2: 0.31384997 | R2: 5 | S2: =IF(AND(ISNUMBER(R2),R2>1,P2>0),R2/P2-1,"") -> 0.56924983 | T2: =IF(AND(ISNUMBER(P2),P2>0),P2*EXP('Read me'!$B$22),"") -> 3.8916772
A3: 1:35 | B3: Roscommon | C3: Athleague Maiden Hurdle | E3: 15.5 | F3: Good | G3: 13 | H3: Telegram Sam (IRE) | I3: Flanagan, S W | J3: Murray, Adrian | K3: 7 | L3: 0 | M3: 4 | N3: 25 | O3: 2 | P3: 3.1927228 | Q3: 0.31321228 | R3: 1.6153846 | S3: =IF(AND(ISNUMBER(R3),R3>1,P3>0),R3/P3-1,"") -> -0.49404169 | T3: =IF(AND(ISNUMBER(P3),P3>0),P3*EXP('Read me'!$B$22),"") -> 3.8996004
A4: 1:35 | B4: Roscommon | C4: Athleague Maiden Hurdle | E4: 15.5 | F4: Good | G4: 13 | H4: Sonas (IRE) | I4: OKeeffe, Darragh | J4: Bromhead, Henry De | K4: 15 | L4: 0 | M4: 4 | N4: 31 | O4: 3 | P4: 8.1237049 | Q4: 0.12309654 | R4: 10 | S4: =IF(AND(ISNUMBER(R4),R4>1,P4>0),R4/P4-1,"") -> 0.23096545 | T4: =IF(AND(ISNUMBER(P4),P4>0),P4*EXP('Read me'!$B$22),"") -> 9.9223155
A5: 1:35 | B5: Roscommon | C5: Athleague Maiden Hurdle | E5: 15.5 | F5: Good | G5: 13 | H5: God The Highness (IRE) | I5: Meyler, D | J5: Harrington, Mrs John | K5: 3 | L5: 0 | M5: 4 | N5: 54 | O5: 4 | P5: 10.014695 | Q5: 0.099853265 | R5: 7.5 | S5: =IF(AND(ISNUMBER(R5),R5>1,P5>0),R5/P5-1,"") -> -0.25110051 | T5: =IF(AND(ISNUMBER(P5),P5>0),P5*EXP('Read me'!$B$22),"") -> 12.231976
A6: 1:35 | B6: Roscommon | C6: Athleague Maiden Hurdle | E6: 15.5 | F6: Good | G6: 13 | H6: The Flying Rambler (IRE) | I6: King, D | J6: Dempsey, J P | K6: 9 | L6: 0 | M6: 4 | N6: 58 | O6: 5 | P6: 23.925484 | Q6: 0.041796438 | R6: 21 | S6: =IF(AND(ISNUMBER(R6),R6>1,P6>0),R6/P6-1,"") -> -0.12227481 | T6: =IF(AND(ISNUMBER(P6),P6>0),P6*EXP('Read me'!$B$22),"") -> 29.222652
A7: 1:35 | B7: Roscommon | C7: Athleague Maiden Hurdle | E7: 15.5 | F7: Good | G7: 13 | H7: Pallatine Hills (IRE) | I7: Buckley, Kieran | J7: Harty, Edward and Patrick | K7: 6 | L7: 0 | M7: 4 | N7: 23 | O7: 6 | P7: 26.155292 | Q7: 0.038233181 | R7: 15 | S7: =IF(AND(ISNUMBER(R7),R7>1,P7>0),R7/P7-1,"") -> -0.42650229 | T7: =IF(AND(ISNUMBER(P7),P7>0),P7*EXP('Read me'!$B$22),"") -> 31.946145
A8: 1:35 | B8: Roscommon | C8: Athleague Maiden Hurdle | E8: 15.5 | F8: Good | G8: 13 | H8: Abando (GER) | I8: Smith, James | J8: McCann, Anthony | K8: 1 | L8: 0 | M8: 4 | N8: 97 | O8: 7 | P8: 44.129249 | Q8: 0.022660707 | R8: 34 | S8: =IF(AND(ISNUMBER(R8),R8>1,P8>0),R8/P8-1,"") -> -0.22953595 | T8: =IF(AND(ISNUMBER(P8),P8>0),P8*EXP('Read me'!$B$22),"") -> 53.899587
A9: 1:35 | B9: Roscommon | C9: Athleague Maiden Hurdle | E9: 15.5 | F9: Good | G9: 13 | H9: Lucky Signal (FR) | I9: Ewing, Sam | J9: Elliott, Gordon | K9: 5 | L9: 0 | M9: 4 | N9: 25 | O9: 8 | P9: 75.723937 | Q9: 0.013205864 | R9: 101 | S9: =IF(AND(ISNUMBER(R9),R9>1,P9>0),R9/P9-1,"") -> 0.33379225 | T9: =IF(AND(ISNUMBER(P9),P9>0),P9*EXP('Read me'!$B$22),"") -> 92.489425
A10: 1:35 | B10: Roscommon | C10: Athleague Maiden Hurdle | E10: 15.5 | F10: Good | G10: 13 | H10: Gratitudeforgrace (FR) | I10: Gilligan, D J | J10: Elliott, Gordon | K10: 13 | L10: 0 | M10: 4 | N10: 67 | O10: 9 | P10: 85.68318 | Q10: 0.011670902 | R10: 101 | S10: =IF(AND(ISNUMBER(R10),R10>1,P10>0),R10/P10-1,"") -> 0.1787611 | T10: =IF(AND(ISNUMBER(P10),P10>0),P10*EXP('Read me'!$B$22),"") -> 104.65367
A11: 1:35 | B11: Roscommon | C11: Athleague Maiden Hurdle | E11: 15.5 | F11: Good | G11: 13 | H11: Hill Of Berries (IRE) | I11: Gainford, Jordan | J11: Dempsey, J P | K11: 4 | L11: 0 | M11: 4 | O11: 10 | P11: 131.32591 | Q11: 0.0076146435 | R11: 81 | S11: =IF(AND(ISNUMBER(R11),R11>1,P11>0),R11/P11-1,"") -> -0.38321388 | T11: =IF(AND(ISNUMBER(P11),P11>0),P11*EXP('Read me'!$B$22),"") -> 160.40183
A12: 1:35 | B12: Roscommon | C12: Athleague Maiden Hurdle | E12: 15.5 | F12: Good | G12: 13 | H12: Everin Dream (IRE) | I12: Smithers, P T | J12: Fahey, Jarlath P | K12: 12 | L12: 0 | M12: 4 | O12: 11 | P12: 159.93786 | Q12: 0.0062524284 | R12: 101 | S12: =IF(AND(ISNUMBER(R12),R12>1,P12>0),R12/P12-1,"") -> -0.36850473 | T12: =IF(AND(ISNUMBER(P12),P12>0),P12*EXP('Read me'!$B$22),"") -> 195.34854
A13: 1:35 | B13: Roscommon | C13: Athleague Maiden Hurdle | E13: 15.5 | F13: Good | G13: 13 | H13: Neat As A Pin (IRE) | I13: Lane, R J | J13: Bolger, E | K13: 14 | L13: 0 | M13: 4 | N13: 56 | O13: 12 | P13: 167.62823 | Q13: 0.0059655824 | R13: 151 | S13: =IF(AND(ISNUMBER(R13),R13>1,P13>0),R13/P13-1,"") -> -0.09919706 | T13: =IF(AND(ISNUMBER(P13),P13>0),P13*EXP('Read me'!$B$22),"") -> 204.74158
A14: 1:35 | B14: Roscommon | C14: Athleague Maiden Hurdle | E14: 15.5 | F14: Good | G14: 13 | H14: Emmamia (IRE) | I14: Enright, P T | J14: McNiff, Mark Michael | K14: 11 | L14: 0 | M14: 4 | N14: 69 | O14: 13 | P14: 386.36984 | Q14: 0.0025881937 | R14: 201 | S14: =IF(AND(ISNUMBER(R14),R14>1,P14>0),R14/P14-1,"") -> -0.47977306 | T14: =IF(AND(ISNUMBER(P14),P14>0),P14*EXP('Read me'!$B$22),"") -> 471.91319
A15: 2:10 | B15: Roscommon | C15: Garys Gardening Services Handicap Hurdle (0-100) | E15: 15.5 | F15: Good | G15: 16 | H15: Cool Summer (IRE) | I15: Enright, P T | J15: McLoughlin, Hilary | K15: 3 | L15: 95 | M15: 6 | N15: 31 | O15: 1 | P15: 3.935622 | Q15: 0.25408944 | R15: 4 | S15: =IF(AND(ISNUMBER(R15),R15>1,P15>0),R15/P15-1,"") -> 0.016357772 | T15: =IF(AND(ISNUMBER(P15),P15>0),P15*EXP('Read me'!$B$22),"") -> 4.8069796
A16: 2:10 | B16: Roscommon | C16: Garys Gardening Services Handicap Hurdle (0-100) | E16: 15.5 | F16: Good | G16: 16 | H16: Colesberg (IRE) | I16: Canavan, Jordan J | J16: Flavin, J P | K16: 2 | L16: 95 | M16: 5 | N16: 43 | O16: 2 | P16: 8.6710864 | Q16: 0.1153258 | R16: 7 | S16: =IF(AND(ISNUMBER(R16),R16>1,P16>0),R16/P16-1,"") -> -0.19271938 | T16: =IF(AND(ISNUMBER(P16),P16>0),P16*EXP('Read me'!$B$22),"") -> 10.590889
A17: 2:10 | B17: Roscommon | C17: Garys Gardening Services Handicap Hurdle (0-100) | E17: 15.5 | F17: Good | G17: 16 | H17: Patrick Street | I17: King, D | J17: Kinirons, A | K17: 12 | L17: 82 | M17: 7 | N17: 13 | O17: 3 | P17: 10.070653 | Q17: 0.099298423 | R17: 5 | S17: =IF(AND(ISNUMBER(R17),R17>1,P17>0),R17/P17-1,"") -> -0.50350789 | T17: =IF(AND(ISNUMBER(P17),P17>0),P17*EXP('Read me'!$B$22),"") -> 12.300324
A18: 2:10 | B18: Roscommon | C18: Garys Gardening Services Handicap Hurdle (0-100) | E18: 15.5 | F18: Good | G18: 16 | H18: Classy Cc (IRE) | I18: Brassil, C | J18: Brassil, Martin | K18: 1 | L18: 95 | M18: 6 | N18: 139 | O18: 4 | P18: 10.419183 | Q18: 0.095976819 | R18: 12 | S18: =IF(AND(ISNUMBER(R18),R18>1,P18>0),R18/P18-1,"") -> 0.15172183 | T18: =IF(AND(ISNUMBER(P18),P18>0),P18*EXP('Read me'!$B$22),"") -> 12.726018
A19: 2:10 | B19: Roscommon | C19: Garys Gardening Services Handicap Hurdle (0-100) | E19: 15.5 | F19: Good | G19: 16 | H19: Eyetrap | I19: Smithers, C D | J19: Melia, Aidan | K19: 4 | L19: 95 | M19: 6 | N19: 245 | O19: 5 | P19: 12.881168 | Q19: 0.07763271 | R19: 7 | S19: =IF(AND(ISNUMBER(R19),R19>1,P19>0),R19/P19-1,"") -> -0.45657103 | T19: =IF(AND(ISNUMBER(P19),P19>0),P19*EXP('Read me'!$B$22),"") -> 15.733094
A20: 2:10 | B20: Roscommon | C20: Garys Gardening Services Handicap Hurdle (0-100) | E20: 15.5 | F20: Good | G20: 16 | H20: Patty Ofarrell (IRE) | I20: Flanagan, S W | J20: Maher, Peter | K20: 5 | L20: 95 | M20: 8 | N20: 84 | O20: 6 | P20: 14.054189 | Q20: 0.071153165 | R20: 21 | S20: =IF(AND(ISNUMBER(R20),R20>1,P20>0),R20/P20-1,"") -> 0.49421646 | T20: =IF(AND(ISNUMBER(P20),P20>0),P20*EXP('Read me'!$B$22),"") -> 17.165825
A21: 2:10 | B21: Roscommon | C21: Garys Gardening Services Handicap Hurdle (0-100) | E21: 15.5 | F21: Good | G21: 16 | H21: Our Girl Ellie (IRE) | I21: Slevin, J J | J21: Ryan, Stephen | K21: 8 | L21: 92 | M21: 6 | N21: 137 | O21: 7 | P21: 19.598345 | Q21: 0.051024717 | R21: 19 | S21: =IF(AND(ISNUMBER(R21),R21>1,P21>0),R21/P21-1,"") -> -0.030530374 | T21: =IF(AND(ISNUMBER(P21),P21>0),P21*EXP('Read me'!$B$22),"") -> 23.937472
A22: 2:10 | B22: Roscommon | C22: Garys Gardening Services Handicap Hurdle (0-100) | E22: 15.5 | F22: Good | G22: 16 | H22: Avandra (IRE) | I22: OCallaghan, Shane | J22: Rothwell, P J | K22: 16 | L22: 72 | M22: 6 | N22: 33 | O22: 8 | P22: 23.325763 | Q22: 0.042871052 | R22: 13 | S22: =IF(AND(ISNUMBER(R22),R22>1,P22>0),R22/P22-1,"") -> -0.44267632 | T22: =IF(AND(ISNUMBER(P22),P22>0),P22*EXP('Read me'!$B$22),"") -> 28.490151
A23: 2:10 | B23: Roscommon | C23: Garys Gardening Services Handicap Hurdle (0-100) | E23: 15.5 | F23: Good | G23: 16 | H23: Speakasyoufind (IRE) | I23: Sugrue, R | J23: Rothwell, P J | K23: 9 | L23: 89 | M23: 5 | N23: 50 | O23: 9 | P23: 26.804016 | Q23: 0.037307842 | R23: 11 | S23: =IF(AND(ISNUMBER(R23),R23>1,P23>0),R23/P23-1,"") -> -0.58961373 | T23: =IF(AND(ISNUMBER(P23),P23>0),P23*EXP('Read me'!$B$22),"") -> 32.738499
A24: 2:10 | B24: Roscommon | C24: Garys Gardening Services Handicap Hurdle (0-100) | E24: 15.5 | F24: Good | G24: 16 | H24: Dalmatic (IRE) | I24: Byrnes, Philip | J24: Odoherty, William Joseph | K24: 7 | L24: 92 | M24: 6 | N24: 157 | O24: 10 | P24: 28.437064 | Q24: 0.035165374 | R24: 21 | S24: =IF(AND(ISNUMBER(R24),R24>1,P24>0),R24/P24-1,"") -> -0.26152714 | T24: =IF(AND(ISNUMBER(P24),P24>0),P24*EXP('Read me'!$B$22),"") -> 34.733109
... A72: 3:55 | B72: Roscommon | C72: Castlecoote Handicap Hurdle | E72: 24 | F72: Good | G72: 11 | H72: Free Flowing (IRE) | I72: Nugent, Mr E M | J72: Lee, Norman | K72: 12 | L72: 96 | M72: 10 | N72: 111 | O72: 11 | P72: 106.39056 | Q72: 0.00939933 | R72: 51 | S72: =IF(AND(ISNUMBER(R72),R72>1,P72>0),R72/P72-1,"") -> -0.52063417 | T72: =IF(AND(ISNUMBER(P72),P72>0),P72*EXP('Read me'!$B$22),"") -> 129.94573
A73: 4:30 | B73: Roscommon | C73: Mon 28th Sep 2026 | D73: Grade 3 | E73: 16.5 | F73: Yielding | G73: 4 | H73: Wild Bill Hickok (IRE) | I73: Finegan, Eoghan | J73: Murphy, Ciaran | K73: 2 | L73: 133 | M73: 4 | N73: 60 | O73: 1 | P73: 1.8662594 | Q73: 0.53583121 | R73: 2.5 | S73: =IF(AND(ISNUMBER(R73),R73>1,P73>0),R73/P73-1,"") -> 0.33957801 | T73: =IF(AND(ISNUMBER(P73),P73>0),P73*EXP('Read me'!$B$22),"") -> 2.2794543
A74: 4:30 | B74: Roscommon | C74: Mon 28th Sep 2026 | D74: Grade 3 | E74: 16.5 | F74: Yielding | G74: 4 | H74: Femme Magnifique (IRE) | I74: Quirke, Cian | J74: Kelly, David Harry | K74: 4 | L74: 125 | M74: 8 | N74: 31 | O74: 2 | P74: 4.1708458 | Q74: 0.23975952 | R74: 2.375 | S74: =IF(AND(ISNUMBER(R74),R74>1,P74>0),R74/P74-1,"") -> -0.43057113 | T74: =IF(AND(ISNUMBER(P74),P74>0),P74*EXP('Read me'!$B$22),"") -> 5.0942826
A75: 4:30 | B75: Roscommon | C75: Mon 28th Sep 2026 | D75: Grade 3 | E75: 16.5 | F75: Yielding | G75: 4 | H75: A Snow White Park (IRE) | I75: Mullins, D E | J75: Mullins, Ms Margaret | K75: 3 | L75: 112 | M75: 5 | N75: 43 | O75: 3 | P75: 6.4118529 | Q75: 0.15596116 | R75: 6 | S75: =IF(AND(ISNUMBER(R75),R75>1,P75>0),R75/P75-1,"") -> -0.064233057 | T75: =IF(AND(ISNUMBER(P75),P75>0),P75*EXP('Read me'!$B$22),"") -> 7.8314548
A76: 4:30 | B76: Roscommon | C76: Mon 28th Sep 2026 | D76: Grade 3 | E76: 16.5 | F76: Yielding | G76: 4 | H76: Miss Fourie (IRE) | I76: Gilligan, D J | J76: Elliott, Gordon | K76: 5 | L76: 0 | M76: 9 | N76: 43 | O76: 4 | P76: 14.609606 | Q76: 0.068448115 | R76: 8.5 | S76: =IF(AND(ISNUMBER(R76),R76>1,P76>0),R76/P76-1,"") -> -0.41819102 | T76: =IF(AND(ISNUMBER(P76),P76>0),P76*EXP('Read me'!$B$22),"") -> 17.844213
A77: 5:05 | B77: Roscommon | C77: Irish Stallion Farms EBF Mares Handicap Chase | E77: 21.5 | F77: Yielding | G77: 10 | H77: Jolie Jewel (FR) | I77: Smith, James | J77: McMahon, Brian M | K77: 2 | L77: 112 | M77: 7 | N77: 35 | O77: 1 | P77: 4.1067972 | Q77: 0.24349875 | R77: 4.3333333 | S77: =IF(AND(ISNUMBER(R77),R77>1,P77>0),R77/P77-1,"") -> 0.055161267 | T77: =IF(AND(ISNUMBER(P77),P77>0),P77*EXP('Read me'!$B$22),"") -> 5.0160534
A78: 5:05 | B78: Roscommon | C78: Irish Stallion Farms EBF Mares Handicap Chase | E78: 21.5 | F78: Yielding | G78: 10 | H78: Ladies Well (IRE) | I78: Quirke, Cian | J78: Slattery, Andrew | K78: 8 | L78: 98 | M78: 6 | N78: 17 | O78: 2 | P78: 5.3771887 | Q78: 0.18597079 | R78: 4.5 | S78: =IF(AND(ISNUMBER(R78),R78>1,P78>0),R78/P78-1,"") -> -0.16313147 | T78: =IF(AND(ISNUMBER(P78),P78>0),P78*EXP('Read me'!$B$22),"") -> 6.5677131
A79: 5:05 | B79: Roscommon | C79: Irish Stallion Farms EBF Mares Handicap Chase | E79: 21.5 | F79: Yielding | G79: 10 | H79: Chosen Shant (IRE) | I79: Enright, P T | J79: King, Aengus | K79: 7 | L79: 100 | M79: 10 | N79: 8 | O79: 3 | P79: 6.910896 | Q79: 0.14469904 | R79: 7.5 | S79: =IF(AND(ISNUMBER(R79),R79>1,P79>0),R79/P79-1,"") -> 0.085242777 | T79: =IF(AND(ISNUMBER(P79),P79>0),P79*EXP('Read me'!$B$22),"") -> 8.4409875
A80: 5:05 | B80: Roscommon | C80: Irish Stallion Farms EBF Mares Handicap Chase | E80: 21.5 | F80: Yielding | G80: 10 | H80: Miss Lia (IRE) | I80: OCallaghan, Shane | J80: Rothwell, P J | K80: 10 | L80: 88 | M80: 6 | N80: 50 | O80: 4 | P80: 9.0822396 | Q80: 0.110105 | R80: 4 | S80: =IF(AND(ISNUMBER(R80),R80>1,P80>0),R80/P80-1,"") -> -0.55958 | T80: =IF(AND(ISNUMBER(P80),P80>0),P80*EXP('Read me'!$B$22),"") -> 11.093073
A81: 5:05 | B81: Roscommon | C81: Irish Stallion Farms EBF Mares Handicap Chase | E81: 21.5 | F81: Yielding | G81: 10 | H81: Nastya (IRE) | I81: OKeeffe, Darragh | J81: Bromhead, Henry De | K81: 1 | L81: 116 | M81: 7 | N81: 43 | O81: 5 | P81: 9.1680313 | Q81: 0.10907467 | R81: 13 | S81: =IF(AND(ISNUMBER(R81),R81>1,P81>0),R81/P81-1,"") -> 0.41797073 | T81: =IF(AND(ISNUMBER(P81),P81>0),P81*EXP('Read me'!$B$22),"") -> 11.197859
A82: 5:05 | B82: Roscommon | C82: Irish Stallion Farms EBF Mares Handicap Chase | E82: 21.5 | F82: Yielding | G82: 10 | H82: Shannon Bank (IRE) | I82: King, D | J82: Kinirons, A | K82: 9 | L82: 97 | M82: 7 | N82: 39 | O82: 6 | P82: 13.313156 | Q82: 0.075113671 | R82: 10 | S82: =IF(AND(ISNUMBER(R82),R82>1,P82>0),R82/P82-1,"") -> -0.24886329 | T82: =IF(AND(ISNUMBER(P82),P82>0),P82*EXP('Read me'!$B$22),"") -> 16.260725
A83: 5:05 | B83: Roscommon | C83: Irish Stallion Farms EBF Mares Handicap Chase | E83: 21.5 | F83: Yielding | G83: 10 | H83: Ad Caelum (IRE) | I83: OSullivan, Alan | J83: Ryan, John Patrick | K83: 6 | L83: 102 | M83: 7 | N83: 17 | O83: 7 | P83: 21.370942 | Q83: 0.04679251 | R83: 8.5 | S83: =IF(AND(ISNUMBER(R83),R83>1,P83>0),R83/P83-1,"") -> -0.60226366 | T83: =IF(AND(ISNUMBER(P83),P83>0),P83*EXP('Read me'!$B$22),"") -> 26.102527
A84: 5:05 | B84: Roscommon | C84: Irish Stallion Farms EBF Mares Handicap Chase | E84: 21.5 | F84: Yielding | G84: 10 | H84: Bynx (IRE) | I84: Flanagan, S W | J84: Hassett, Martin | K84: 4 | L84: 110 | M84: 8 | N84: 8 | O84: 8 | P84: 24.145024 | Q84: 0.041416402 | R84: 26 | S84: =IF(AND(ISNUMBER(R84),R84>1,P84>0),R84/P84-1,"") -> 0.076826445 | T84: =IF(AND(ISNUMBER(P84),P84>0),P84*EXP('Read me'!$B$22),"") -> 29.490798
A85: 5:05 | B85: Roscommon | C85: Irish Stallion Farms EBF Mares Handicap Chase | E85: 21.5 | F85: Yielding | G85: 10 | H85: Neon Diamond (IRE) | I85: Ewing, Sam | J85: Elliott, Gordon | K85: 5 | L85: 110 | M85: 7 | N85: 113 | O85: 9 | P85: 40.85904 | Q85: 0.024474388 | R85: 29 | S85: =IF(AND(ISNUMBER(R85),R85>1,P85>0),R85/P85-1,"") -> -0.29024275 | T85: =IF(AND(ISNUMBER(P85),P85>0),P85*EXP('Read me'!$B$22),"") -> 49.905344
A86: 5:05 | B86: Roscommon | C86: Irish Stallion Farms EBF Mares Handicap Chase | E86: 21.5 | F86: Yielding | G86: 10 | H86: Beauforts Storm (IRE) | I86: Doyle, Mr D | J86: Doyle, Timothy | K86: 3 | L86: 110 | M86: 7 | N86: 31 | O86: 10 | P86: 53.036944 | Q86: 0.018854782 | R86: 26 | S86: =IF(AND(ISNUMBER(R86),R86>1,P86>0),R86/P86-1,"") -> -0.50977567 | T86: =IF(AND(ISNUMBER(P86),P86>0),P86*EXP('Read me'!$B$22),"") -> 64.779469
A87: 5:40 | B87: Roscommon | C87: GavinLynchRacing.com Flat Race | E87: 15.5 | F87: Good | G87: 16 | H87: Dr Bones (IRE) | I87: Mullins, Mr P W | J87: Mullins, W P | K87: 16 | L87: 0 | M87: 4 | O87: 1 | P87: 3.5731655 | Q87: 0.27986389 | R87: 2.75 | S87: =IF(AND(ISNUMBER(R87),R87>1,P87>0),R87/P87-1,"") -> -0.23037431 | T87: =IF(AND(ISNUMBER(P87),P87>0),P87*EXP('Read me'!$B$22),"") -> 4.3642742
A88: 5:40 | B88: Roscommon | C88: GavinLynchRacing.com Flat Race | E88: 15.5 | F88: Good | G88: 16 | H88: Touch The Clouds (IRE) | I88: Shanahan, Mr L P | J88: OSullivan, Ross | K88: 10 | L88: 0 | M88: 5 | N88: 246 | O88: 2 | P88: 7.9755179 | Q88: 0.12538371 | R88: 6 | S88: =IF(AND(ISNUMBER(R88),R88>1,P88>0),R88/P88-1,"") -> -0.24769775 | T88: =IF(AND(ISNUMBER(P88),P88>0),P88*EXP('Read me'!$B$22),"") -> 9.7413195
A89: 5:40 | B89: Roscommon | C89: GavinLynchRacing.com Flat Race | E89: 15.5 | F89: Good | G89: 16 | H89: The Last Line (IRE) | I89: Lillingston, Mr Hugh | J89: Kiely, J E and Thomas | K89: 8 | L89: 0 | M89: 6 | N89: 815 | O89: 3 | P89: 9.1084388 | Q89: 0.1097883 | R89: 23 | S89: =IF(AND(ISNUMBER(R89),R89>1,P89>0),R89/P89-1,"") -> 1.5251309 | T89: =IF(AND(ISNUMBER(P89),P89>0),P89*EXP('Read me'!$B$22),"") -> 11.125072
A90: 5:40 | B90: Roscommon | C90: GavinLynchRacing.com Flat Race | E90: 15.5 | F90: Good | G90: 16 | H90: Finest Band (FR) | I90: Maguire, Mr F | J90: Connell, B | K90: 2 | L90: 0 | M90: 5 | O90: 4 | P90: 9.9165217 | Q90: 0.10084181 | R90: 4.3333333 | S90: =IF(AND(ISNUMBER(R90),R90>1,P90>0),R90/P90-1,"") -> -0.56301882 | T90: =IF(AND(ISNUMBER(P90),P90>0),P90*EXP('Read me'!$B$22),"") -> 12.112067
A91: 5:40 | B91: Roscommon | C91: GavinLynchRacing.com Flat Race | E91: 15.5 | F91: Good | G91: 16 | H91: Aruntotheace (IRE) | I91: Gleeson, Mr J L | J91: Brassil, Martin | K91: 11 | L91: 0 | M91: 4 | O91: 5 | P91: 10.307499 | Q91: 0.097016745 | R91: 8.5 | S91: =IF(AND(ISNUMBER(R91),R91>1,P91>0),R91/P91-1,"") -> -0.17535767 | T91: =IF(AND(ISNUMBER(P91),P91>0),P91*EXP('Read me'!$B$22),"") -> 12.589608
A92: 5:40 | B92: Roscommon | C92: GavinLynchRacing.com Flat Race | E92: 15.5 | F92: Good | G92: 16 | H92: Tale Of Intrigue (IRE) | I92: Halford, Mr T A | J92: Buckley, D | K92: 7 | L92: 0 | M92: 5 | N92: 45 | O92: 6 | P92: 13.427533 | Q92: 0.074473842 | R92: 9.5 | S92: =IF(AND(ISNUMBER(R92),R92>1,P92>0),R92/P92-1,"") -> -0.2924985 | T92: =IF(AND(ISNUMBER(P92),P92>0),P92*EXP('Read me'!$B$22),"") -> 16.400426
A93: 5:40 | B93: Roscommon | C93: GavinLynchRacing.com Flat Race | E93: 15.5 | F93: Good | G93: 16 | H93: Greattobeable (IRE) | I93: Doyle, Mr D | J93: Curling, S | K93: 3 | L93: 0 | M93: 5 | O93: 7 | P93: 23.815645 | Q93: 0.041989205 | R93: 10 | S93: =IF(AND(ISNUMBER(R93),R93>1,P93>0),R93/P93-1,"") -> -0.58010795 | T93: =IF(AND(ISNUMBER(P93),P93>0),P93*EXP('Read me'!$B$22),"") -> 29.088494
A94: 5:40 | B94: Roscommon | C94: GavinLynchRacing.com Flat Race | E94: 15.5 | F94: Good | G94: 16 | H94: Peat Sounds (IRE) | I94: Townend, Miss J | J94: Mullins, W P | K94: 15 | L94: 0 | M94: 5 | N94: 25 | O94: 8 | P94: 24.547975 | Q94: 0.040736558 | R94: 11 | S94: =IF(AND(ISNUMBER(R94),R94>1,P94>0),R94/P94-1,"") -> -0.55189786 | T94: =IF(AND(ISNUMBER(P94),P94>0),P94*EXP('Read me'!$B$22),"") -> 29.982964
A95: 5:40 | B95: Roscommon | C95: GavinLynchRacing.com Flat Race | E95: 15.5 | F95: Good | G95: 16 | H95: Thrill A Minute (IRE) | I95: Ryan, Mr A P | J95: Doyle, Jack | K95: 9 | L95: 0 | M95: 5 | O95: 9 | P95: 33.122301 | Q95: 0.030191139 | R95: 23 | S95: =IF(AND(ISNUMBER(R95),R95>1,P95>0),R95/P95-1,"") -> -0.3056038 | T95: =IF(AND(ISNUMBER(P95),P95>0),P95*EXP('Read me'!$B$22),"") -> 40.45567
A96: 5:40 | B96: Roscommon | C96: GavinLynchRacing.com Flat Race | E96: 15.5 | F96: Good | G96: 16 | H96: Our Sonny (IRE) | I96: Mullins, Mr C | J96: Mullins, Thomas | K96: 6 | L96: 0 | M96: 5 | N96: 478 | O96: 10 | P96: 40.206957 | Q96: 0.024871318 | R96: 51 | S96: =IF(AND(ISNUMBER(R96),R96>1,P96>0),R96/P96-1,"") -> 0.2684372 | T96: =IF(AND(ISNUMBER(P96),P96>0),P96*EXP('Read me'!$B$22),"") -> 49.108888
A97: 5:40 | B97: Roscommon | C97: GavinLynchRacing.com Flat Race | E97: 15.5 | F97: Good | G97: 16 | H97: Madison Twist (FR) | I97: Murphy, Mr B Doyle | J97: Doyle, Miss Elizabeth | K97: 12 | L97: 0 | M97: 4 | N97: 120 | O97: 11 | P97: 52.349701 | Q97: 0.019102306 | R97: 51 | S97: =IF(AND(ISNUMBER(R97),R97>1,P97>0),R97/P97-1,"") -> -0.025782399 | T97: =IF(AND(ISNUMBER(P97),P97>0),P97*EXP('Read me'!$B$22),"") -> 63.940069
A98: 5:40 | B98: Roscommon | C98: GavinLynchRacing.com Flat Race | E98: 15.5 | F98: Good | G98: 16 | H98: Champagne Order (IRE) | I98: Swan, H C | J98: OMara, T J | K98: 1 | L98: 0 | M98: 6 | O98: 12 | P98: 53.454491 | Q98: 0.018707502 | R98: 29 | S98: =IF(AND(ISNUMBER(R98),R98>1,P98>0),R98/P98-1,"") -> -0.45748244 | T98: =IF(AND(ISNUMBER(P98),P98>0),P98*EXP('Read me'!$B$22),"") -> 65.289462
A99: 5:40 | B99: Roscommon | C99: GavinLynchRacing.com Flat Race | E99: 15.5 | F99: Good | G99: 16 | H99: Ilens Dream (IRE) | I99: James, Mr R | J99: OLoughlin, G | K99: 4 | L99: 0 | M99: 6 | O99: 13 | P99: 62.602491 | Q99: 0.015973805 | R99: 101 | S99: =IF(AND(ISNUMBER(R99),R99>1,P99>0),R99/P99-1,"") -> 0.61335432 | T99: =IF(AND(ISNUMBER(P99),P99>0),P99*EXP('Read me'!$B$22),"") -> 76.462856
A100: 5:40 | B100: Roscommon | C100: GavinLynchRacing.com Flat Race | E100: 15.5 | F100: Good | G100: 16 | H100: Pillars Presence (IRE) | I100: Conheady, Mr J | J100: Conheady, James | K100: 13 | L100: 0 | M100: 4 | O100: 14 | P100: 89.174893 | Q100: 0.011213919 | R100: 67 | S100: =IF(AND(ISNUMBER(R100),R100>1,P100>0),R100/P100-1,"") -> -0.24866745 | T100: =IF(AND(ISNUMBER(P100),P100>0),P100*EXP('Read me'!$B$22),"") -> 108.91846
A101: 5:40 | B101: Roscommon | C101: GavinLynchRacing.com Flat Race | E101: 15.5 | F101: Good | G101: 16 | H101: Long Story (IRE) | I101: Mahon, Mr E | J101: Neilan, John | K101: 5 | L101: 0 | M101: 6 | N101: 38 | O101: 15 | P101: 130.92496 | Q101: 0.0076379629 | R101: 67 | S101: =IF(AND(ISNUMBER(R101),R101>1,P101>0),R101/P101-1,"") -> -0.48825649 | T101: =IF(AND(ISNUMBER(P101),P101>0),P101*EXP('Read me'!$B$22),"") -> 159.91211
A102: 5:40 | B102: Roscommon | C102: GavinLynchRacing.com Flat Race | E102: 15.5 | F102: Good | G102: 16 | H102: Throwmedownsomthin (IRE) | I102: Sampson, Mr J P | J102: Madden, I | K102: 14 | L102: 0 | M102: 4 | N102: 55 | O102: 16 | P102: 452.90022 | Q102: 0.0022079919 | R102: 201 | S102: =IF(AND(ISNUMBER(R102),R102>1,P102>0),R102/P102-1,"") -> -0.55619364 | T102: =IF(AND(ISNUMBER(P102),P102>0),P102*EXP('Read me'!$B$22),"") -> 553.17358

Sheet Hamilton
A1: Time | B1: Course | C1: Race | D1: Class | E1: Furlongs | F1: Going | G1: Runners | H1: Horse | I1: Jockey | J1: Trainer | K1: Draw | L1: OR | M1: Age | N1: Days since run | O1: Model rank | P1: Predicted BSP | Q1: Win probability | R1: Card odds (HRB) | S1: Card odds vs model | T1: Rule: back at Betfair ≥
A2: 1:44 | B2: Hamilton | C2: Clearwater DC Ltd Environmental Solutions Amateur Jockeys Handicap | D2: Class 5 | E2: 6 | F2: Soft | G2: 6 | H2: Annie Edson Taylor | I2: Brown, Pippa | J2: Makin, Phillip | K2: 2 | L2: 72 | M2: 5 | N2: 8 | O2: 1 | P2: 3.1430511 | Q2: 0.31816218 | R2: 2.5 | S2: =IF(AND(ISNUMBER(R2),R2>1,P2>0),R2/P2-1,"") -> -0.20459455 | T2: =IF(AND(ISNUMBER(P2),P2>0),P2*EXP('Read me'!$B$22),"") -> 3.8389313
A3: 1:44 | B3: Hamilton | C3: Clearwater DC Ltd Environmental Solutions Amateur Jockeys Handicap | D3: Class 5 | E3: 6 | F3: Soft | G3: 6 | H3: Bay Breeze | I3: Burley, Miss Rebecca | J3: Easterby, T D | K3: 1 | L3: 62 | M3: 7 | N3: 7 | O3: 2 | P3: 4.5721161 | Q3: 0.21871711 | R3: 3.75 | S3: =IF(AND(ISNUMBER(R3),R3>1,P3>0),R3/P3-1,"") -> -0.17981085 | T3: =IF(AND(ISNUMBER(P3),P3>0),P3*EXP('Read me'!$B$22),"") -> 5.5843952
A4: 1:44 | B4: Hamilton | C4: Clearwater DC Ltd Environmental Solutions Amateur Jockeys Handicap | D4: Class 5 | E4: 6 | F4: Soft | G4: 6 | H4: Lumenbourg | I4: Barlow, Patrick | J4: Camacho, Miss J A | K4: 6 | L4: 65 | M4: 5 | N4: 26 | O4: 3 | P4: 6.4457915 | Q4: 0.15513999 | R4: 6 | S4: =IF(AND(ISNUMBER(R4),R4>1,P4>0),R4/P4-1,"") -> -0.069160085 | T4: =IF(AND(ISNUMBER(P4),P4>0),P4*EXP('Read me'!$B$22),"") -> 7.8729075
A5: 1:44 | B5: Hamilton | C5: Clearwater DC Ltd Environmental Solutions Amateur Jockeys Handicap | D5: Class 5 | E5: 6 | F5: Soft | G5: 6 | H5: Thistle Nil (IRE) | I5: Cagney, Eireann | J5: Goldie, J S | K5: 3 | L5: 68 | M5: 4 | N5: 7 | O5: 4 | P5: 7.120566 | Q5: 0.14043827 | R5: 10 | S5: =IF(AND(ISNUMBER(R5),R5>1,P5>0),R5/P5-1,"") -> 0.40438275 | T5: =IF(AND(ISNUMBER(P5),P5>0),P5*EXP('Read me'!$B$22),"") -> 8.6970789
A6: 1:44 | B6: Hamilton | C6: Clearwater DC Ltd Environmental Solutions Amateur Jockeys Handicap | D6: Class 5 | E6: 6 | F6: Soft | G6: 6 | H6: Maldevious (IRE) | I6: Brown, Mr M W | J6: Ellison, B | K6: 4 | L6: 69 | M6: 4 | N6: 23 | O6: 5 | P6: 8.7790261 | Q6: 0.11390785 | R6: 8 | S6: =IF(AND(ISNUMBER(R6),R6>1,P6>0),R6/P6-1,"") -> -0.088737194 | T6: =IF(AND(ISNUMBER(P6),P6>0),P6*EXP('Read me'!$B$22),"") -> 10.722727
A7: 1:44 | B7: Hamilton | C7: Clearwater DC Ltd Environmental Solutions Amateur Jockeys Handicap | D7: Class 5 | E7: 6 | F7: Soft | G7: 6 | H7: Punchbowl Flyer (IRE) | I7: Hampson, Brodie | J7: Oshea, J G M | K7: 5 | L7: 64 | M7: 9 | N7: 21 | O7: 6 | P7: 18.64468 | Q7: 0.053634603 | R7: 15 | S7: =IF(AND(ISNUMBER(R7),R7>1,P7>0),R7/P7-1,"") -> -0.19548095 | T7: =IF(AND(ISNUMBER(P7),P7>0),P7*EXP('Read me'!$B$22),"") -> 22.772663
A8: 2:19 | B8: Hamilton | C8: Moira Stein Memorial EBF Restricted Maiden Stakes (GBB Race) | D8: Class 4 | E8: 5 | F8: Soft | G8: 6 | H8: Cyberspace | I8: Mulrennan, Paul | J8: Smart, B | K8: 6 | L8: 0 | M8: 2 | N8: 13 | O8: 1 | P8: 2.0902903 | Q8: 0.47840245 | R8: 2.75 | S8: =IF(AND(ISNUMBER(R8),R8>1,P8>0),R8/P8-1,"") -> 0.31560672 | T8: =IF(AND(ISNUMBER(P8),P8>0),P8*EXP('Read me'!$B$22),"") -> 2.5530864
A9: 2:19 | B9: Hamilton | C9: Moira Stein Memorial EBF Restricted Maiden Stakes (GBB Race) | D9: Class 4 | E9: 5 | F9: Soft | G9: 6 | H9: Ponte Carlo (IRE) | I9: Allan, David | J9: Easterby, T D | K9: 3 | L9: 63 | M9: 2 | N9: 19 | O9: 2 | P9: 4.2862463 | Q9: 0.23330437 | R9: 2.625 | S9: =IF(AND(ISNUMBER(R9),R9>1,P9>0),R9/P9-1,"") -> -0.38757602 | T9: =IF(AND(ISNUMBER(P9),P9>0),P9*EXP('Read me'!$B$22),"") -> 5.235233
A10: 2:19 | B10: Hamilton | C10: Moira Stein Memorial EBF Restricted Maiden Stakes (GBB Race) | D10: Class 4 | E10: 5 | F10: Soft | G10: 6 | H10: Kompozitor | I10: Beasley, Connor | J10: Barron, T D | K10: 1 | L10: 0 | M10: 2 | N10: 12 | O10: 3 | P10: 7.9445966 | Q10: 0.12587171 | R10: 6 | S10: =IF(AND(ISNUMBER(R10),R10>1,P10>0),R10/P10-1,"") -> -0.24476971 | T10: =IF(AND(ISNUMBER(P10),P10>0),P10*EXP('Read me'!$B$22),"") -> 9.7035522
A11: 2:19 | B11: Hamilton | C11: Moira Stein Memorial EBF Restricted Maiden Stakes (GBB Race) | D11: Class 4 | E11: 5 | F11: Soft | G11: 6 | H11: Youngheartsrunfree (IRE) | I11: Wheatley, Zak | J11: Carroll, D | K11: 2 | L11: 0 | M11: 2 | N11: 12 | O11: 4 | P11: 9.9194898 | Q11: 0.10081164 | R11: 9 | S11: =IF(AND(ISNUMBER(R11),R11>1,P11>0),R11/P11-1,"") -> -0.092695274 | T11: =IF(AND(ISNUMBER(P11),P11>0),P11*EXP('Read me'!$B$22),"") -> 12.115692
A12: 2:19 | B12: Hamilton | C12: Moira Stein Memorial EBF Restricted Maiden Stakes (GBB Race) | D12: Class 4 | E12: 5 | F12: Soft | G12: 6 | H12: Valentina Bonita (IRE) | I12: Garritty, Billy | J12: Easterby, M W | K12: 5 | L12: 0 | M12: 2 | N12: 12 | O12: 5 | P12: 26.097023 | Q12: 0.038318547 | R12: 15 | S12: =IF(AND(ISNUMBER(R12),R12>1,P12>0),R12/P12-1,"") -> -0.42522179 | T12: =IF(AND(ISNUMBER(P12),P12>0),P12*EXP('Read me'!$B$22),"") -> 31.874976
A13: 2:19 | B13: Hamilton | C13: Moira Stein Memorial EBF Restricted Maiden Stakes (GBB Race) | D13: Class 4 | E13: 5 | F13: Soft | G13: 6 | H13: Justice Time (IRE) | I13: Marshall, Tom Kiely | J13: Ellison, B | K13: 4 | L13: 59 | M13: 2 | N13: 12 | O13: 6 | P13: 42.934517 | Q13: 0.023291283 | R13: 19 | S13: =IF(AND(ISNUMBER(R13),R13>1,P13>0),R13/P13-1,"") -> -0.55746562 | T13: =IF(AND(ISNUMBER(P13),P13>0),P13*EXP('Read me'!$B$22),"") -> 52.440337
... A60: 5:13 | B60: Hamilton | C60: Annual Members Of Hamilton Park Handicap | D60: Class 6 | E60: 12 | F60: Soft | G60: 10 | H60: Masekela (IRE) | I60: Mulrennan, Paul | J60: Moffatt, James | K60: 10 | L60: 60 | M60: 7 | N60: 30 | O60: 10 | P60: 40.601426 | Q60: 0.024629677 | R60: 51 | S60: =IF(AND(ISNUMBER(R60),R60>1,P60>0),R60/P60-1,"") -> 0.25611353 | T60: =IF(AND(ISNUMBER(P60),P60>0),P60*EXP('Read me'!$B$22),"") -> 49.590693

Sheet Newton Abbot
A1: Time | B1: Course | C1: Race | D1: Class | E1: Furlongs | F1: Going | G1: Runners | H1: Horse | I1: Jockey | J1: Trainer | K1: Draw | L1: OR | M1: Age | N1: Days since run | O1: Model rank | P1: Predicted BSP | Q1: Win probability | R1: Card odds (HRB) | S1: Card odds vs model | T1: Rule: back at Betfair ≥
A2: 1:50 | B2: Newton Abbot | C2: Celebrating Devon Women In Business Handicap Chase (GBB Race) | D2: Class 3 | E2: 26 | F2: Good | G2: 3 | H2: Depalma (IRE) | I2: Skelton, Harry | J2: Skelton, Daniel | K2: 3 | L2: 102 | M2: 7 | N2: 10 | O2: 1 | P2: 2.195562 | Q2: 0.45546425 | R2: 1.6666667 | S2: =IF(AND(ISNUMBER(R2),R2>1,P2>0),R2/P2-1,"") -> -0.24089292 | T2: =IF(AND(ISNUMBER(P2),P2>0),P2*EXP('Read me'!$B$22),"") -> 2.6816655
A3: 1:50 | B3: Newton Abbot | C3: Celebrating Devon Women In Business Handicap Chase (GBB Race) | D3: Class 3 | E3: 26 | F3: Good | G3: 3 | H3: Muskerry Rock (IRE) | I3: Bowen, Sean P | J3: Bowen, Mickey | K3: 1 | L3: 120 | M3: 7 | N3: 40 | O3: 2 | P3: 3.1859008 | Q3: 0.31388297 | R3: 5.5 | S3: =IF(AND(ISNUMBER(R3),R3>1,P3>0),R3/P3-1,"") -> 0.72635634 | T3: =IF(AND(ISNUMBER(P3),P3>0),P3*EXP('Read me'!$B$22),"") -> 3.891268
A4: 1:50 | B4: Newton Abbot | C4: Celebrating Devon Women In Business Handicap Chase (GBB Race) | D4: Class 3 | E4: 26 | F4: Good | G4: 3 | H4: Limerick Leader (FR) | I4: Bowen, James C | J4: Scholfield, Nick | K4: 2 | L4: 110 | M4: 9 | N4: 12 | O4: 3 | P4: 4.3355211 | Q4: 0.23065278 | R4: 3.5 | S4: =IF(AND(ISNUMBER(R4),R4>1,P4>0),R4/P4-1,"") -> -0.19271526 | T4: =IF(AND(ISNUMBER(P4),P4>0),P4*EXP('Read me'!$B$22),"") -> 5.2954174
A5: 2:25 | B5: Newton Abbot | C5: Jodie Standings Point-To-Point Recruits Novices Hurdle (GBB Race) | D5: Class 4 | E5: 17 | F5: Good | G5: 6 | H5: Matiwo (FR) | I5: Gethings, Ciaran | J5: Williams, Mrs Jane | K5: 4 | L5: 119 | M5: 4 | N5: 219 | O5: 1 | P5: 1.3053142 | Q5: 0.7660991 | R5: 1.2857143 | S5: =IF(AND(ISNUMBER(R5),R5>1,P5>0),R5/P5-1,"") -> -0.015015449 | T5: =IF(AND(ISNUMBER(P5),P5>0),P5*EXP('Read me'!$B$22),"") -> 1.5943143
A6: 2:25 | B6: Newton Abbot | C6: Jodie Standings Point-To-Point Recruits Novices Hurdle (GBB Race) | D6: Class 4 | E6: 17 | F6: Good | G6: 6 | H6: Scotts Legacy (IRE) | I6: Twiston-Davies, Sam | J6: Twiston-Davies, N A | K6: 6 | L6: 0 | M6: 4 | N6: 188 | O6: 2 | P6: 5.188916 | Q6: 0.19271848 | R6: 4 | S6: =IF(AND(ISNUMBER(R6),R6>1,P6>0),R6/P6-1,"") -> -0.22912608 | T6: =IF(AND(ISNUMBER(P6),P6>0),P6*EXP('Read me'!$B$22),"") -> 6.3377563
A7: 2:25 | B7: Newton Abbot | C7: Jodie Standings Point-To-Point Recruits Novices Hurdle (GBB Race) | D7: Class 4 | E7: 17 | F7: Good | G7: 6 | H7: Silver Whisper | I7: Noonan, David G | J7: Clarke, Ben | K7: 7 | L7: 0 | M7: 4 | N7: 22 | O7: 3 | P7: 55.960858 | Q7: 0.017869633 | R7: 41 | S7: =IF(AND(ISNUMBER(R7),R7>1,P7>0),R7/P7-1,"") -> -0.26734504 | T7: =IF(AND(ISNUMBER(P7),P7>0),P7*EXP('Read me'!$B$22),"") -> 68.350746
A8: 2:25 | B8: Newton Abbot | C8: Jodie Standings Point-To-Point Recruits Novices Hurdle (GBB Race) | D8: Class 4 | E8: 17 | F8: Good | G8: 6 | H8: Happy Chandler | I8: Reed, Harry | J8: Blake, Michael | K8: 1 | L8: 0 | M8: 5 | N8: 21 | O8: 4 | P8: 80.642014 | Q8: 0.012400484 | R8: 21 | S8: =IF(AND(ISNUMBER(R8),R8>1,P8>0),R8/P8-1,"") -> -0.73958984 | T8: =IF(AND(ISNUMBER(P8),P8>0),P8*EXP('Read me'!$B$22),"") -> 98.496378
A9: 2:25 | B9: Newton Abbot | C9: Jodie Standings Point-To-Point Recruits Novices Hurdle (GBB Race) | D9: Class 4 | E9: 17 | F9: Good | G9: 6 | H9: Savanna Storm (IRE) | I9: Corcoran, Rian | J9: Pipe, D E | K9: 5 | L9: 0 | M9: 4 | N9: 18 | O9: 5 | P9: 155.93307 | Q9: 0.0064130076 | R9: 51 | S9: =IF(AND(ISNUMBER(R9),R9>1,P9>0),R9/P9-1,"") -> -0.67293661 | T9: =IF(AND(ISNUMBER(P9),P9>0),P9*EXP('Read me'!$B$22),"") -> 190.45709
A10: 2:25 | B10: Newton Abbot | C10: Jodie Standings Point-To-Point Recruits Novices Hurdle (GBB Race) | D10: Class 4 | E10: 17 | F10: Good | G10: 6 | H10: Pappano | I10: Collier, Ellis | J10: Hosie, Syd | K10: 2 | L10: 0 | M10: 5 | N10: 10 | O10: 6 | P10: 222.25676 | Q10: 0.0044993008 | R10: 41 | S10: =IF(AND(ISNUMBER(R10),R10>1,P10>0),R10/P10-1,"") -> -0.81552867 | T10: =IF(AND(ISNUMBER(P10),P10>0),P10*EXP('Read me'!$B$22),"") -> 271.46501
A11: 3:00 | B11: Newton Abbot | C11: Shelley Coles - Setting the Pace at 60 Novices Limited Handicap Chase (GBB Race) | D11: Class 3 | E11: 16.5 | F11: Good | G11: 4 | H11: Gore Point | I11: Cobden, Harry | J11: Honeyball, A J | K11: 1 | L11: 125 | M11: 6 | N11: 32 | O11: 1 | P11: 3.5423789 | Q11: 0.28229617 | R11: 5.5 | S11: =IF(AND(ISNUMBER(R11),R11>1,P11>0),R11/P11-1,"") -> 0.55262894 | T11: =IF(AND(ISNUMBER(P11),P11>0),P11*EXP('Read me'!$B$22),"") -> 4.3266714
A12: 3:00 | B12: Newton Abbot | C12: Shelley Coles - Setting the Pace at 60 Novices Limited Handicap Chase (GBB Race) | D12: Class 3 | E12: 16.5 | F12: Good | G12: 4 | H12: Juggernaut (FR) | I12: Bament, Chad | J12: Honeyball, A J | K12: 4 | L12: 106 | M12: 7 | N12: 21 | O12: 2 | P12: 3.6735701 | Q12: 0.27221476 | R12: 3.5 | S12: =IF(AND(ISNUMBER(R12),R12>1,P12>0),R12/P12-1,"") -> -0.047248349 | T12: =IF(AND(ISNUMBER(P12),P12>0),P12*EXP('Read me'!$B$22),"") -> 4.4869087
A13: 3:00 | B13: Newton Abbot | C13: Shelley Coles - Setting the Pace at 60 Novices Limited Handicap Chase (GBB Race) | D13: Class 3 | E13: 16.5 | F13: Good | G13: 4 | H13: Inside Man (FR) | I13: Gethings, Ciaran | J13: Williams, Mrs Jane | K13: 3 | L13: 120 | M13: 6 | N13: 157 | O13: 3 | P13: 3.8573224 | Q13: 0.25924719 | R13: 3.25 | S13: =IF(AND(ISNUMBER(R13),R13>1,P13>0),R13/P13-1,"") -> -0.15744662 | T13: =IF(AND(ISNUMBER(P13),P13>0),P13*EXP('Read me'!$B$22),"") -> 4.7113442
A14: 3:00 | B14: Newton Abbot | C14: Shelley Coles - Setting the Pace at 60 Novices Limited Handicap Chase (GBB Race) | D14: Class 3 | E14: 16.5 | F14: Good | G14: 4 | H14: Minella Jury (IRE) | I14: Twiston-Davies, Sam | J14: Twiston-Davies, N A | K14: 2 | L14: 122 | M14: 6 | N14: 175 | O14: 4 | P14: 5.3693616 | Q14: 0.18624188 | R14: 3.25 | S14: =IF(AND(ISNUMBER(R14),R14>1,P14>0),R14/P14-1,"") -> -0.39471389 | T14: =IF(AND(ISNUMBER(P14),P14>0),P14*EXP('Read me'!$B$22),"") -> 6.5581531
A15: 3:35 | B15: Newton Abbot | C15: Final Furlong Before I Do Selling Handicap Hurdle | D15: Class 5 | E15: 17 | F15: Good | G15: 6 | H15: Berry Edge (IRE) | J15: Skelton, Daniel | K15: 4 | L15: 87 | M15: 8 | N15: 18 | O15: 1 | P15: 2.6844746 | Q15: 0.37251237 | R15: 2.875 | S15: =IF(AND(ISNUMBER(R15),R15>1,P15>0),R15/P15-1,"") -> 0.070973074 | T15: =IF(AND(ISNUMBER(P15),P15>0),P15*EXP('Read me'!$B$22),"") -> 3.2788247
A16: 3:35 | B16: Newton Abbot | C16: Final Furlong Before I Do Selling Handicap Hurdle | D16: Class 5 | E16: 17 | F16: Good | G16: 6 | H16: Saint Polo (FR) | I16: Scott, Luke | J16: Candlish, Jennie | K16: 1 | L16: 109 | M16: 6 | N16: 21 | O16: 2 | P16: 3.6120282 | Q16: 0.27685276 | R16: 3.25 | S16: =IF(AND(ISNUMBER(R16),R16>1,P16>0),R16/P16-1,"") -> -0.10022852 | T16: =IF(AND(ISNUMBER(P16),P16>0),P16*EXP('Read me'!$B$22),"") -> 4.4117413
A17: 3:35 | B17: Newton Abbot | C17: Final Furlong Before I Do Selling Handicap Hurdle | D17: Class 5 | E17: 17 | F17: Good | G17: 6 | H17: Saucats (FR) | I17: Pritchard, Callum | J17: Tickle, J | K17: 6 | L17: 83 | M17: 5 | N17: 10 | O17: 3 | P17: 9.7988917 | Q17: 0.10205236 | R17: 4.3333333 | S17: =IF(AND(ISNUMBER(R17),R17>1,P17>0),R17/P17-1,"") -> -0.55777312 | T17: =IF(AND(ISNUMBER(P17),P17>0),P17*EXP('Read me'!$B$22),"") -> 11.968393
A18: 3:35 | B18: Newton Abbot | C18: Final Furlong Before I Do Selling Handicap Hurdle | D18: Class 5 | E18: 17 | F18: Good | G18: 6 | H18: Lightning Flash (IRE) | I18: Twiston-Davies, Sam | J18: Twiston-Davies, N A | K18: 2 | L18: 106 | M18: 6 | N18: 145 | O18: 4 | P18: 10.843981 | Q18: 0.092217057 | R18: 3.25 | S18: =IF(AND(ISNUMBER(R18),R18>1,P18>0),R18/P18-1,"") -> -0.70029457 | T18: =IF(AND(ISNUMBER(P18),P18>0),P18*EXP('Read me'!$B$22),"") -> 13.244868
A19: 3:35 | B19: Newton Abbot | C19: Final Furlong Before I Do Selling Handicap Hurdle | D19: Class 5 | E19: 17 | F19: Good | G19: 6 | H19: Cogital | I19: Atkins, Harry | J19: Llewellyn, B J | K19: 3 | L19: 91 | M19: 11 | N19: 38 | O19: 5 | P19: 11.26941 | Q19: 0.088735791 | R19: 6.5 | S19: =IF(AND(ISNUMBER(R19),R19>1,P19>0),R19/P19-1,"") -> -0.42321736 | T19: =IF(AND(ISNUMBER(P19),P19>0),P19*EXP('Read me'!$B$22),"") -> 13.764488
A20: 3:35 | B20: Newton Abbot | C20: Final Furlong Before I Do Selling Handicap Hurdle | D20: Class 5 | E20: 17 | F20: Good | G20: 6 | H20: Princess Of Ballea (IRE) | I20: Reed, Harry | J20: Hitchins, Daisy | K20: 5 | L20: 85 | M20: 4 | N20: 34 | O20: 6 | P20: 14.786412 | Q20: 0.067629658 | R20: 12 | S20: =IF(AND(ISNUMBER(R20),R20>1,P20>0),R20/P20-1,"") -> -0.18844411 | T20: =IF(AND(ISNUMBER(P20),P20>0),P20*EXP('Read me'!$B$22),"") -> 18.060165
A21: 4:10 | B21: Newton Abbot | C21: Paul Fergusons Jumpers To Follow Handicap Hurdle | D21: Class 4 | E21: 22 | F21: Good | G21: 4 | H21: Kom Tu Voudras (FR) | I21: Cobden, Harry | J21: Bramley, Faye | K21: 1 | L21: 115 | M21: 6 | N21: 10 | O21: 1 | P21: 3.0587372 | Q21: 0.3269323 | R21: 3.5 | S21: =IF(AND(ISNUMBER(R21),R21>1,P21>0),R21/P21-1,"") -> 0.14426307 | T21: =IF(AND(ISNUMBER(P21),P21>0),P21*EXP('Read me'!$B$22),"") -> 3.73595
A22: 4:10 | B22: Newton Abbot | C22: Paul Fergusons Jumpers To Follow Handicap Hurdle | D22: Class 4 | E22: 22 | F22: Good | G22: 4 | H22: Kilnew Supreme (IRE) | I22: Twiston-Davies, Sam | J22: Nicholls, P F | K22: 2 | L22: 106 | M22: 5 | N22: 159 | O22: 2 | P22: 3.2802206 | Q22: 0.30485755 | R22: 2.75 | S22: =IF(AND(ISNUMBER(R22),R22>1,P22>0),R22/P22-1,"") -> -0.16164175 | T22: =IF(AND(ISNUMBER(P22),P22>0),P22*EXP('Read me'!$B$22),"") -> 4.0064705
A23: 4:10 | B23: Newton Abbot | C23: Paul Fergusons Jumpers To Follow Handicap Hurdle | D23: Class 4 | E23: 22 | F23: Good | G23: 4 | H23: Kittys Glance | I23: Cannon, Tom J | J23: King, A | K23: 4 | L23: 105 | M23: 5 | N23: 39 | O23: 3 | P23: 4.5485046 | Q23: 0.21985247 | R23: 4 | S23: =IF(AND(ISNUMBER(R23),R23>1,P23>0),R23/P23-1,"") -> -0.1205901 | T23: =IF(AND(ISNUMBER(P23),P23>0),P23*EXP('Read me'!$B$22),"") -> 5.5555561
A24: 4:10 | B24: Newton Abbot | C24: Paul Fergusons Jumpers To Follow Handicap Hurdle | D24: Class 4 | E24: 22 | F24: Good | G24: 4 | H24: Ellerton (FR) | I24: Powell, Brendan | J24: Tizzard, Joe | K24: 3 | L24: 106 | M24: 6 | N24: 21 | O24: 4 | P24: 6.7404669 | Q24: 0.14835767 | R24: 5.5 | S24: =IF(AND(ISNUMBER(R24),R24>1,P24>0),R24/P24-1,"") -> -0.18403279 | T24: =IF(AND(ISNUMBER(P24),P24>0),P24*EXP('Read me'!$B$22),"") -> 8.2328249
A25: 4:43 | B25: Newton Abbot | C25: Par Inn Bulpin Cup Amateur Jockeys Handicap Hurdle | D25: Class 5 | E25: 27 | F25: Good | G25: 7 | H25: Pooroldmackley (IRE) | I25: Williams, Eleanor | J25: Williams, Mrs C | K25: 4 | L25: 83 | M25: 7 | N25: 8 | O25: 1 | P25: 2.9188361 | Q25: 0.34260231 | R25: 3.25 | S25: =IF(AND(ISNUMBER(R25),R25>1,P25>0),R25/P25-1,"") -> 0.1134575 | T25: =IF(AND(ISNUMBER(P25),P25>0),P25*EXP('Read me'!$B$22),"") -> 3.5650745
A26: 4:43 | B26: Newton Abbot | C26: Par Inn Bulpin Cup Amateur Jockeys Handicap Hurdle | D26: Class 5 | E26: 27 | F26: Good | G26: 7 | H26: Final Entry (IRE) | I26: Shaw, Mr James | J26: Pipe, D E | K26: 2 | L26: 97 | M26: 5 | N26: 24 | O26: 2 | P26: 5.1859691 | Q26: 0.19282799 | R26: 5 | S26: =IF(AND(ISNUMBER(R26),R26>1,P26>0),R26/P26-1,"") -> -0.035860052 | T26: =IF(AND(ISNUMBER(P26),P26>0),P26*EXP('Read me'!$B$22),"") -> 6.334157
A27: 4:43 | B27: Newton Abbot | C27: Par Inn Bulpin Cup Amateur Jockeys Handicap Hurdle | D27: Class 5 | E27: 27 | F27: Good | G27: 7 | H27: French Diablo (FR) | I27: Jones, Miss Aimee | J27: Comley, Max | K27: 7 | L27: 84 | M27: 4 | N27: 8 | O27: 3 | P27: 6.1924563 | Q27: 0.16148681 | R27: 4.5 | S27: =IF(AND(ISNUMBER(R27),R27>1,P27>0),R27/P27-1,"") -> -0.27330936 | T27: =IF(AND(ISNUMBER(P27),P27>0),P27*EXP('Read me'!$B$22),"") -> 7.5634832
... A31: 4:43 | B31: Newton Abbot | C31: Par Inn Bulpin Cup Amateur Jockeys Handicap Hurdle | D31: Class 5 | E31: 27 | F31: Good | G31: 7 | H31: Poets Muse (IRE) | I31: King, Mr James | J31: Chanin, I | K31: 3 | L31: 87 | M31: 5 | N31: 131 | O31: 7 | P31: 15.63877 | Q31: 0.063943647 | R31: 11 | S31: =IF(AND(ISNUMBER(R31),R31>1,P31>0),R31/P31-1,"") -> -0.29661988 | T31: =IF(AND(ISNUMBER(P31),P31>0),P31*EXP('Read me'!$B$22),"") -> 19.101237

Sheet Wolverhampton
A1: Time | B1: Course | C1: Race | D1: Class | E1: Furlongs | F1: Going | G1: Runners | H1: Horse | I1: Jockey | J1: Trainer | K1: Draw | L1: OR | M1: Age | N1: Days since run | O1: Model rank | P1: Predicted BSP | Q1: Win probability | R1: Card odds (HRB) | S1: Card odds vs model | T1: Rule: back at Betfair ≥
A2: 4:22 | B2: Wolverhampton | C2: Free Tips On attheraces.com Amateur Jockeys Handicap | D2: Class 6 | E2: 9.5 | F2: Standard | G2: 10 | H2: No Knee Never (IRE) | I2: Callan, Mr Henry | J2: Owen, J P | K2: 11 | L2: 63 | M2: 5 | N2: 11 | O2: 1 | P2: 3.5076096 | Q2: 0.28509444 | R2: 3.5 | S2: =IF(AND(ISNUMBER(R2),R2>1,P2>0),R2/P2-1,"") -> -0.0021694686 | T2: =IF(AND(ISNUMBER(P2),P2>0),P2*EXP('Read me'!$B$22),"") -> 4.2842041
A3: 4:22 | B3: Wolverhampton | C3: Free Tips On attheraces.com Amateur Jockeys Handicap | D3: Class 6 | E3: 9.5 | F3: Standard | G3: 10 | H3: Pursuit Of Truth (IRE) | I3: Easterby, Mr Thomas | J3: Menzies, Rebecca | K3: 7 | L3: 65 | M3: 5 | N3: 67 | O3: 2 | P3: 6.5228194 | Q3: 0.15330794 | R3: 6.5 | S3: =IF(AND(ISNUMBER(R3),R3>1,P3>0),R3/P3-1,"") -> -0.0034983998 | T3: =IF(AND(ISNUMBER(P3),P3>0),P3*EXP('Read me'!$B$22),"") -> 7.9669896
A4: 4:22 | B4: Wolverhampton | C4: Free Tips On attheraces.com Amateur Jockeys Handicap | D4: Class 6 | E4: 9.5 | F4: Standard | G4: 10 | H4: Little She (FR) | I4: Tregoning, Miss Alice | J4: Tregoning, M P | K4: 2 | L4: 49 | M4: 4 | N4: 27 | O4: 3 | P4: 7.2197592 | Q4: 0.13850877 | R4: 5 | S4: =IF(AND(ISNUMBER(R4),R4>1,P4>0),R4/P4-1,"") -> -0.30745613 | T4: =IF(AND(ISNUMBER(P4),P4>0),P4*EXP('Read me'!$B$22),"") -> 8.8182338
A5: 4:22 | B5: Wolverhampton | C5: Free Tips On attheraces.com Amateur Jockeys Handicap | D5: Class 6 | E5: 9.5 | F5: Standard | G5: 10 | H5: Stipulation (IRE) | I5: Loughnane, Mr Jack | J5: Loughnane, Daniel Mark | K5: 4 | L5: 58 | M5: 5 | N5: 13 | O5: 4 | P5: 8.0207278 | Q5: 0.12467696 | R5: 5 | S5: =IF(AND(ISNUMBER(R5),R5>1,P5>0),R5/P5-1,"") -> -0.37661518 | T5: =IF(AND(ISNUMBER(P5),P5>0),P5*EXP('Read me'!$B$22),"") -> 9.7965391
A6: 4:22 | B6: Wolverhampton | C6: Free Tips On attheraces.com Amateur Jockeys Handicap | D6: Class 6 | E6: 9.5 | F6: Standard | G6: 10 | H6: Star Start (IRE) | I6: Parker, Miss C | J6: Carr, Mrs R A | K6: 6 | L6: 60 | M6: 6 | N6: 9 | O6: 5 | P6: 9.2139726 | Q6: 0.10853082 | R6: 7 | S6: =IF(AND(ISNUMBER(R6),R6>1,P6>0),R6/P6-1,"") -> -0.24028426 | T6: =IF(AND(ISNUMBER(P6),P6>0),P6*EXP('Read me'!$B$22),"") -> 11.253972
A7: 4:22 | B7: Wolverhampton | C7: Free Tips On attheraces.com Amateur Jockeys Handicap | D7: Class 6 | E7: 9.5 | F7: Standard | G7: 10 | H7: Wrist Art (IRE) | I7: Criscuolo, Miss Ruby | J7: Owen, J P | K7: 5 | L7: 49 | M7: 9 | N7: 11 | O7: 6 | P7: 16.490467 | Q7: 0.060641097 | R7: 13 | S7: =IF(AND(ISNUMBER(R7),R7>1,P7>0),R7/P7-1,"") -> -0.21166574 | T7: =IF(AND(ISNUMBER(P7),P7>0),P7*EXP('Read me'!$B$22),"") -> 20.141502
A8: 4:22 | B8: Wolverhampton | C8: Free Tips On attheraces.com Amateur Jockeys Handicap | D8: Class 6 | E8: 9.5 | F8: Standard | G8: 10 | H8: Popeye Doyle (FR) | J8: Bedi, Miss J | K8: 1 | L8: 61 | M8: 4 | N8: 72 | O8: 7 | P8: 20.259766 | Q8: 0.049358911 | R8: 19 | S8: =IF(AND(ISNUMBER(R8),R8>1,P8>0),R8/P8-1,"") -> -0.062180691 | T8: =IF(AND(ISNUMBER(P8),P8>0),P8*EXP('Read me'!$B$22),"") -> 24.745334
A9: 4:22 | B9: Wolverhampton | C9: Free Tips On attheraces.com Amateur Jockeys Handicap | D9: Class 6 | E9: 9.5 | F9: Standard | G9: 10 | H9: Harbour Vision | I9: Tett, Frederick | J9: Dixon, Scott | K9: 10 | L9: 58 | M9: 11 | N9: 7 | O9: 8 | P9: 28.407188 | Q9: 0.035202358 | R9: 29 | S9: =IF(AND(ISNUMBER(R9),R9>1,P9>0),R9/P9-1,"") -> 0.020868391 | T9: =IF(AND(ISNUMBER(P9),P9>0),P9*EXP('Read me'!$B$22),"") -> 34.696617
A10: 4:22 | B10: Wolverhampton | C10: Free Tips On attheraces.com Amateur Jockeys Handicap | D10: Class 6 | E10: 9.5 | F10: Standard | G10: 10 | H10: Redredrobin | I10: Wingrove, Miss Jodie | J10: Wingrove, D | K10: 9 | L10: 55 | M10: 9 | N10: 18 | O10: 9 | P10: 31.736752 | Q10: 0.03150921 | R10: 34 | S10: =IF(AND(ISNUMBER(R10),R10>1,P10>0),R10/P10-1,"") -> 0.071313151 | T10: =IF(AND(ISNUMBER(P10),P10>0),P10*EXP('Read me'!$B$22),"") -> 38.763357
A11: 4:22 | B11: Wolverhampton | C11: Free Tips On attheraces.com Amateur Jockeys Handicap | D11: Class 6 | E11: 9.5 | F11: Standard | G11: 10 | H11: Molly Valentine (IRE) | I11: Holman, Jake | J11: Cassidy, Stephanie | K11: 3 | L11: 52 | M11: 6 | N11: 104 | O11: 10 | P11: 75.933094 | Q11: 0.013169488 | R11: 34 | S11: =IF(AND(ISNUMBER(R11),R11>1,P11>0),R11/P11-1,"") -> -0.55223739 | T11: =IF(AND(ISNUMBER(P11),P11>0),P11*EXP('Read me'!$B$22),"") -> 92.74489
A12: 4:55 | B12: Wolverhampton | C12: Download The At The Races App Novice Stakes (GBB Race) | D12: Class 4 | E12: 8.5 | F12: Standard | G12: 11 | H12: Najidi Storm | I12: Keane, C T | J12: Charlton, Roger/Harry | K12: 5 | L12: 93 | M12: 3 | N12: 20 | O12: 1 | P12: 3.6175253 | Q12: 0.27643206 | R12: 2.5 | S12: =IF(AND(ISNUMBER(R12),R12>1,P12>0),R12/P12-1,"") -> -0.30891984 | T12: =IF(AND(ISNUMBER(P12),P12>0),P12*EXP('Read me'!$B$22),"") -> 4.4184554
A13: 4:55 | B13: Wolverhampton | C13: Download The At The Races App Novice Stakes (GBB Race) | D13: Class 4 | E13: 8.5 | F13: Standard | G13: 11 | H13: Al Jolson | I13: Davies, Harry | J13: Crisford, Simon | K13: 4 | L13: 0 | M13: 3 | N13: 19 | O13: 2 | P13: 4.1610397 | Q13: 0.24032455 | R13: 8 | S13: =IF(AND(ISNUMBER(R13),R13>1,P13>0),R13/P13-1,"") -> 0.92259641 | T13: =IF(AND(ISNUMBER(P13),P13>0),P13*EXP('Read me'!$B$22),"") -> 5.0823054
A14: 4:55 | B14: Wolverhampton | C14: Download The At The Races App Novice Stakes (GBB Race) | D14: Class 4 | E14: 8.5 | F14: Standard | G14: 11 | H14: Shadow Boxer (FR) | I14: Murphy, Oisin | J14: Crisford, Simon | K14: 10 | L14: 0 | M14: 3 | N14: 166 | O14: 3 | P14: 4.2761671 | Q14: 0.23385429 | R14: 5 | S14: =IF(AND(ISNUMBER(R14),R14>1,P14>0),R14/P14-1,"") -> 0.16927143 | T14: =IF(AND(ISNUMBER(P14),P14>0),P14*EXP('Read me'!$B$22),"") -> 5.2229223
A15: 4:55 | B15: Wolverhampton | C15: Download The At The Races App Novice Stakes (GBB Race) | D15: Class 4 | E15: 8.5 | F15: Standard | G15: 11 | H15: Wootz (IRE) | I15: Dawson, R | J15: Varian, Roger | K15: 7 | L15: 94 | M15: 3 | N15: 14 | O15: 4 | P15: 4.6005503 | Q15: 0.2173653 | R15: 2.5 | S15: =IF(AND(ISNUMBER(R15),R15>1,P15>0),R15/P15-1,"") -> -0.45658675 | T15: =IF(AND(ISNUMBER(P15),P15>0),P15*EXP('Read me'!$B$22),"") -> 5.6191248
A16: 4:55 | B16: Wolverhampton | C16: Download The At The Races App Novice Stakes (GBB Race) | D16: Class 4 | E16: 8.5 | F16: Standard | G16: 11 | H16: Petworth (GER) | I16: Hutchinson, Callum | J16: Balding, A M | K16: 9 | L16: 0 | M16: 3 | N16: 136 | O16: 5 | P16: 63.172883 | Q16: 0.015829577 | R16: 26 | S16: =IF(AND(ISNUMBER(R16),R16>1,P16>0),R16/P16-1,"") -> -0.58843101 | T16: =IF(AND(ISNUMBER(P16),P16>0),P16*EXP('Read me'!$B$22),"") -> 77.159534
A17: 4:55 | B17: Wolverhampton | C17: Download The At The Races App Novice Stakes (GBB Race) | D17: Class 4 | E17: 8.5 | F17: Standard | G17: 11 | H17: North Beach (IRE) | I17: Loughnane, Billy | J17: Loughnane, Daniel Mark | K17: 8 | L17: 0 | M17: 3 | N17: 136 | O17: 6 | P17: 110.32638 | Q17: 0.0090640157 | R17: 41 | S17: =IF(AND(ISNUMBER(R17),R17>1,P17>0),R17/P17-1,"") -> -0.62837536 | T17: =IF(AND(ISNUMBER(P17),P17>0),P17*EXP('Read me'!$B$22),"") -> 134.75294
A18: 4:55 | B18: Wolverhampton | C18: Download The At The Races App Novice Stakes (GBB Race) | D18: Class 4 | E18: 8.5 | F18: Standard | G18: 11 | H18: Mashkur (USA) | I18: Carver, William | J18: Osborne, J A | K18: 6 | L18: 0 | M18: 3 | O18: 7 | P18: 251.55108 | Q18: 0.0039753358 | R18: 81 | S18: =IF(AND(ISNUMBER(R18),R18>1,P18>0),R18/P18-1,"") -> -0.6779978 | T18: =IF(AND(ISNUMBER(P18),P18>0),P18*EXP('Read me'!$B$22),"") -> 307.24518
A19: 4:55 | B19: Wolverhampton | C19: Download The At The Races App Novice Stakes (GBB Race) | D19: Class 4 | E19: 8.5 | F19: Standard | G19: 11 | H19: Herstmonceux | I19: Edmunds, Lewis | J19: Muir, W R & Grassick, C | K19: 3 | L19: 0 | M19: 3 | N19: 38 | O19: 8 | P19: 733.91406 | Q19: 0.0013625574 | R19: 126 | S19: =IF(AND(ISNUMBER(R19),R19>1,P19>0),R19/P19-1,"") -> -0.82831777 | T19: =IF(AND(ISNUMBER(P19),P19>0),P19*EXP('Read me'!$B$22),"") -> 896.40466
A20: 4:55 | B20: Wolverhampton | C20: Download The At The Races App Novice Stakes (GBB Race) | D20: Class 4 | E20: 8.5 | F20: Standard | G20: 11 | H20: Khachaturian | I20: Heard, Tyler | J20: Mackie, J | K20: 1 | L20: 0 | M20: 3 | O20: 9 | P20: 1565.8919 | Q20: 0.0006386137 | R20: 201 | S20: =IF(AND(ISNUMBER(R20),R20>1,P20>0),R20/P20-1,"") -> -0.87163865 | T20: =IF(AND(ISNUMBER(P20),P20>0),P20*EXP('Read me'!$B$22),"") -> 1912.5847
A21: 4:55 | B21: Wolverhampton | C21: Download The At The Races App Novice Stakes (GBB Race) | D21: Class 4 | E21: 8.5 | F21: Standard | G21: 11 | H21: Elsa Tan | I21: Sayette, B D L | J21: Baker, George | K21: 2 | L21: 0 | M21: 3 | N21: 77 | O21: 10 | P21: 1681.3614 | Q21: 0.00059475615 | R21: 251 | S21: =IF(AND(ISNUMBER(R21),R21>1,P21>0),R21/P21-1,"") -> -0.85071621 | T21: =IF(AND(ISNUMBER(P21),P21>0),P21*EXP('Read me'!$B$22),"") -> 2053.6194
A22: 4:55 | B22: Wolverhampton | C22: Download The At The Races App Novice Stakes (GBB Race) | D22: Class 4 | E22: 8.5 | F22: Standard | G22: 11 | H22: Circle Of Secrets (FR) | I22: Mangan, Gina | J22: OBrien, Fergal | K22: 11 | L22: 0 | M22: 4 | N22: 7 | O22: 11 | P22: 1789.0946 | Q22: 0.00055894194 | R22: 201 | S22: =IF(AND(ISNUMBER(R22),R22>1,P22>0),R22/P22-1,"") -> -0.88765267 | T22: =IF(AND(ISNUMBER(P22),P22>0),P22*EXP('Read me'!$B$22),"") -> 2185.2051
A23: 5:30 | B23: Wolverhampton | C23: Follow AtTheRaces On Instagram EBF Fillies Novice Stakes (GBB Race) | D23: Class 3 | E23: 7 | F23: Standard | G23: 7 | H23: Speed Nation (IRE) | I23: Murphy, Oisin | J23: Crisford, Simon | K23: 4 | L23: 77 | M23: 2 | N23: 27 | O23: 1 | P23: 1.8107264 | Q23: 0.55226455 | R23: 2.625 | S23: =IF(AND(ISNUMBER(R23),R23>1,P23>0),R23/P23-1,"") -> 0.44969445 | T23: =IF(AND(ISNUMBER(P23),P23>0),P23*EXP('Read me'!$B$22),"") -> 2.2116262
A24: 5:30 | B24: Wolverhampton | C24: Follow AtTheRaces On Instagram EBF Fillies Novice Stakes (GBB Race) | D24: Class 3 | E24: 7 | F24: Standard | G24: 7 | H24: Majestic Flame | I24: Loughnane, Billy | J24: Hughes, Richard | K24: 6 | L24: 0 | M24: 2 | N24: 30 | O24: 2 | P24: 5.1753202 | Q24: 0.19322476 | R24: 2.875 | S24: =IF(AND(ISNUMBER(R24),R24>1,P24>0),R24/P24-1,"") -> -0.44447882 | T24: =IF(AND(ISNUMBER(P24),P24>0),P24*EXP('Read me'!$B$22),"") -> 6.3211504
A25: 5:30 | B25: Wolverhampton | C25: Follow AtTheRaces On Instagram EBF Fillies Novice Stakes (GBB Race) | D25: Class 3 | E25: 7 | F25: Standard | G25: 7 | H25: Quintana | I25: Keane, C T | J25: Charlton, Roger/Harry | K25: 2 | L25: 0 | M25: 2 | N25: 25 | O25: 3 | P25: 11.567571 | Q25: 0.086448572 | R25: 5 | S25: =IF(AND(ISNUMBER(R25),R25>1,P25>0),R25/P25-1,"") -> -0.56775714 | T25: =IF(AND(ISNUMBER(P25),P25>0),P25*EXP('Read me'!$B$22),"") -> 14.128663
A26: 5:30 | B26: Wolverhampton | C26: Follow AtTheRaces On Instagram EBF Fillies Novice Stakes (GBB Race) | D26: Class 3 | E26: 7 | F26: Standard | G26: 7 | H26: Ambience | I26: Scott, Rowan | J26: Foy, Kevin | K26: 5 | L26: 0 | M26: 2 | N26: 135 | O26: 4 | P26: 12.856675 | Q26: 0.077780607 | R26: 8 | S26: =IF(AND(ISNUMBER(R26),R26>1,P26>0),R26/P26-1,"") -> -0.37775514 | T26: =IF(AND(ISNUMBER(P26),P26>0),P26*EXP('Read me'!$B$22),"") -> 15.703178
A27: 5:30 | B27: Wolverhampton | C27: Follow AtTheRaces On Instagram EBF Fillies Novice Stakes (GBB Race) | D27: Class 3 | E27: 7 | F27: Standard | G27: 7 | H27: Sax Symbol | I27: Shepherd, Callum | J27: Johnston, Charlie | K27: 7 | L27: 0 | M27: 2 | O27: 5 | P27: 17.965834 | Q27: 0.055661208 | R27: 34 | S27: =IF(AND(ISNUMBER(R27),R27>1,P27>0),R27/P27-1,"") -> 0.89248107 | T27: =IF(AND(ISNUMBER(P27),P27>0),P27*EXP('Read me'!$B$22),"") -> 21.943519
A28: 5:30 | B28: Wolverhampton | C28: Follow AtTheRaces On Instagram EBF Fillies Novice Stakes (GBB Race) | D28: Class 3 | E28: 7 | F28: Standard | G28: 7 | H28: Rubyroo (IRE) | I28: Marquand, Tom | J28: Palmer, Hugo | K28: 3 | L28: 0 | M28: 2 | N28: 25 | O28: 6 | P28: 30.471277 | Q28: 0.032817791 | R28: 23 | S28: =IF(AND(ISNUMBER(R28),R28>1,P28>0),R28/P28-1,"") -> -0.2451908 | T28: =IF(AND(ISNUMBER(P28),P28>0),P28*EXP('Read me'!$B$22),"") -> 37.217701
A29: 5:30 | B29: Wolverhampton | C29: Follow AtTheRaces On Instagram EBF Fillies Novice Stakes (GBB Race) | D29: Class 3 | E29: 7 | F29: Standard | G29: 7 | H29: Appassionata | I29: Morris, Luke | J29: Prescott, Sir Mark | K29: 1 | L29: 0 | M29: 2 | N29: 13 | O29: 7 | P29: 554.78139 | Q29: 0.0018025118 | R29: 201 | S29: =IF(AND(ISNUMBER(R29),R29>1,P29>0),R29/P29-1,"") -> -0.63769513 | T29: =IF(AND(ISNUMBER(P29),P29>0),P29*EXP('Read me'!$B$22),"") -> 677.61152
A30: 6:00 | B30: Wolverhampton | C30: Cavani Style & Speed Handicap (Div 1) | D30: Class 6 | E30: 7 | F30: Standard | G30: 11 | H30: Ridger (IRE) | I30: Murphy, Oisin | J30: Sangster, Ollie | K30: 10 | L30: 46 | M30: 3 | N30: 7 | O30: 1 | P30: 2.2382211 | Q30: 0.44678339 | R30: 1.8333333 | S30: =IF(AND(ISNUMBER(R30),R30>1,P30>0),R30/P30-1,"") -> -0.18089712 | T30: =IF(AND(ISNUMBER(P30),P30>0),P30*EXP('Read me'!$B$22),"") -> 2.7337694
A31: 6:00 | B31: Wolverhampton | C31: Cavani Style & Speed Handicap (Div 1) | D31: Class 6 | E31: 7 | F31: Standard | G31: 11 | H31: Escape Magic | I31: Rodriguez, Callum | J31: Burrows, Owen | K31: 6 | L31: 55 | M31: 3 | N31: 28 | O31: 2 | P31: 3.7489319 | Q31: 0.26674264 | R31: 3.5 | S31: =IF(AND(ISNUMBER(R31),R31>1,P31>0),R31/P31-1,"") -> -0.066400749 | T31: =IF(AND(ISNUMBER(P31),P31>0),P31*EXP('Read me'!$B$22),"") -> 4.5789557
A32: 6:00 | B32: Wolverhampton | C32: Cavani Style & Speed Handicap (Div 1) | D32: Class 6 | E32: 7 | F32: Standard | G32: 11 | H32: Saisons Dor (IRE) | I32: Garritty, Jack | J32: OKeeffe, Jedd | K32: 3 | L32: 55 | M32: 11 | N32: 20 | O32: 3 | P32: 12.745803 | Q32: 0.078457197 | R32: 10 | S32: =IF(AND(ISNUMBER(R32),R32>1,P32>0),R32/P32-1,"") -> -0.21542803 | T32: =IF(AND(ISNUMBER(P32),P32>0),P32*EXP('Read me'!$B$22),"") -> 15.567759
A33: 6:00 | B33: Wolverhampton | C33: Cavani Style & Speed Handicap (Div 1) | D33: Class 6 | E33: 7 | F33: Standard | G33: 11 | H33: Mintana | I33: Leavy, Joe | J33: Evans, H J | K33: 11 | L33: 47 | M33: 6 | N33: 27 | O33: 4 | P33: 17.878907 | Q33: 0.055931832 | R33: 15 | S33: =IF(AND(ISNUMBER(R33),R33>1,P33>0),R33/P33-1,"") -> -0.16102252 | T33: =IF(AND(ISNUMBER(P33),P33>0),P33*EXP('Read me'!$B$22),"") -> 21.837346
A34: 6:00 | B34: Wolverhampton | C34: Cavani Style & Speed Handicap (Div 1) | D34: Class 6 | E34: 7 | F34: Standard | G34: 11 | H34: Romanovich (IRE) | I34: Carson, William | J34: Oshea, J G M | K34: 8 | L34: 53 | M34: 7 | N34: 74 | O34: 5 | P34: 19.877442 | Q34: 0.050308285 | R34: 17 | S34: =IF(AND(ISNUMBER(R34),R34>1,P34>0),R34/P34-1,"") -> -0.14475916 | T34: =IF(AND(ISNUMBER(P34),P34>0),P34*EXP('Read me'!$B$22),"") -> 24.278362
A35: 6:00 | B35: Wolverhampton | C35: Cavani Style & Speed Handicap (Div 1) | D35: Class 6 | E35: 7 | F35: Standard | G35: 11 | H35: Create (IRE) | I35: Heard, Tyler | J35: Dixon, Scott | K35: 2 | L35: 50 | M35: 6 | N35: 13 | O35: 6 | P35: 32.010881 | Q35: 0.031239378 | R35: 17 | S35: =IF(AND(ISNUMBER(R35),R35>1,P35>0),R35/P35-1,"") -> -0.46893058 | T35: =IF(AND(ISNUMBER(P35),P35>0),P35*EXP('Read me'!$B$22),"") -> 39.098178
A36: 6:00 | B36: Wolverhampton | C36: Cavani Style & Speed Handicap (Div 1) | D36: Class 6 | E36: 7 | F36: Standard | G36: 11 | H36: No News (IRE) | I36: Edmunds, Lewis | J36: Jenkins, J R | K36: 7 | L36: 46 | M36: 6 | N36: 41 | O36: 7 | P36: 39.465597 | Q36: 0.025338525 | R36: 26 | S36: =IF(AND(ISNUMBER(R36),R36>1,P36>0),R36/P36-1,"") -> -0.34119836 | T36: =IF(AND(ISNUMBER(P36),P36>0),P36*EXP('Read me'!$B$22),"") -> 48.203389
A37: 6:00 | B37: Wolverhampton | C37: Cavani Style & Speed Handicap (Div 1) | D37: Class 6 | E37: 7 | F37: Standard | G37: 11 | H37: Mickey Mongoose | I37: Horgan, C | J37: Williams, Olly | K37: 1 | L37: 50 | M37: 6 | N37: 47 | O37: 8 | P37: 43.456464 | Q37: 0.023011537 | R37: 34 | S37: =IF(AND(ISNUMBER(R37),R37>1,P37>0),R37/P37-1,"") -> -0.21760776 | T37: =IF(AND(ISNUMBER(P37),P37>0),P37*EXP('Read me'!$B$22),"") -> 53.077845
A38: 6:00 | B38: Wolverhampton | C38: Cavani Style & Speed Handicap (Div 1) | D38: Class 6 | E38: 7 | F38: Standard | G38: 11 | H38: Horus | I38: Morris, Luke | J38: Attwater, M J | K38: 4 | L38: 46 | M38: 4 | N38: 7 | O38: 9 | P38: 67.807765 | Q38: 0.014747573 | R38: 51 | S38: =IF(AND(ISNUMBER(R38),R38>1,P38>0),R38/P38-1,"") -> -0.24787376 | T38: =IF(AND(ISNUMBER(P38),P38>0),P38*EXP('Read me'!$B$22),"") -> 82.820592
A39: 6:00 | B39: Wolverhampton | C39: Cavani Style & Speed Handicap (Div 1) | D39: Class 6 | E39: 7 | F39: Standard | G39: 11 | H39: Pink Socks (IRE) | I39: Carmichael, Oliver | J39: Cassidy, Stephanie | K39: 9 | L39: 46 | M39: 7 | N39: 32 | O39: 10 | P39: 211.33423 | Q39: 0.0047318412 | R39: 81 | S39: =IF(AND(ISNUMBER(R39),R39>1,P39>0),R39/P39-1,"") -> -0.61672086 | T39: =IF(AND(ISNUMBER(P39),P39>0),P39*EXP('Read me'!$B$22),"") -> 258.12421
... A92: 8:30 | B92: Wolverhampton | C92: Free Digital Racecard At raceday-ready.com Handicap | D92: Class 5 | E92: 9.5 | F92: Standard | G92: 11 | H92: Far Far Out (IRE) | I92: Carson, William | J92: Carroll, A W | K92: 8 | L92: 57 | M92: 3 | N92: 33 | O92: 11 | P92: 257.50541 | Q92: 0.0038834136 | R92: 67 | S92: =IF(AND(ISNUMBER(R92),R92>1,P92>0),R92/P92-1,"") -> -0.73981129 | T92: =IF(AND(ISNUMBER(P92),P92>0),P92*EXP('Read me'!$B$22),"") -> 314.51781
